Workbook

Sheet Factures BLS
A1: ID Client | B1: n° facture | C1: Date Prestation | D1: Dossier | E1: Libellé | F1: Impact CO2 | G1: Unité | H1: Quantité | I1: Prix Unitaire | J1: Montant H,T, | K1: Code Tva
B2: 2601458 | C2: 46174 | D2: 12118 | E2: De 21 Créancey A 13 Aubagne | J2: 1300 | K2: 1
B3: 2601458 | C3: 46176 | D3: 12116 | E3: De 21 Créancey A 60 Grandvilliers | G3: M | H3: 1.6 | J3: 325 | K3: 1
B4: 2601458 | C4: 46176 | D4: 12144 | E4: De 21 Créancey A 49 Saint-Jean-de-Linières | G4: M | H4: 1.6 | J4: 340 | K4: 1
B5: 2601458 | C5: 46176 | D5: 12145 | E5: De 21 Créancey A 76 Grand-Couronne | G5: M | H5: 0.4 | J5: 180 | K5: 1
B6: 2601458 | C6: 46176 | D6: 12147 | E6: De 75 Paris A 21 Créancey | G6: M | H6: 0.8 | J6: 300 | K6: 1
B7: 2601458 | C7: 46177 | D7: 12165 | E7: V/Réf HYD06260004 2764316 De 21 Créancey A 21 Ouges | G7: M | H7: 1.2 | J7: 200 | K7: 1
B8: 2601458 | C8: 46177 | D8: 12204 | E8: De 21 Créancey A 34 Castelnau-le-Lez | G8: M | H8: 1.2 | J8: 995 | K8: 1
B9: 2601458 | C9: 46181 | D9: 12245 | E9: De 21 Créancey A 95 Vémars | G9: M | H9: 0.5 | J9: 195 | K9: 1
B10: 2601458 | C10: 46182 | D10: 12201 | E10: De 21 Savigny-lès-Beaune A I00 Roma-00176 | G10: M | H10: 0.8 | J10: 480 | K10: 1
B11: 2601458 | C11: 46185 | D11: 12339 | E11: V/Réf ALPEXPO GRENOBLE De 21 Créancey A 38 Grenoble | G11: M | H11: 0.01 | J11: 575 | K11: 1
B12: 2601458 | C12: 46189 | D12: 12414 | E12: De 21 Créancey A 25 Pontarlier | G12: M | H12: 0.8 | J12: 550 | K12: 1
B13: 2601458 | C13: 46197 | D13: 12532 | E13: De 75 Paris A 21 Créancey | G13: M | H13: 0.8 | J13: 190 | K13: 1
B14: 2601458 | C14: 46198 | D14: 12550 | E14: De 21 Créancey A 75 Paris/16ème Arrondissement | G14: M | H14: 1.2 | J14: 265 | K14: 1
... B16: 2601458 | C16: 46203 | D16: 12676 | E16: De 21 Créancey A 13 Marseille/16ème Arrondissement | G16: M | H16: 6 | J16: 800 | K16: 1

Sheet Bilan PDF
A3: Étiquettes de lignes | B3: Somme de Montant H,T, | D3: PDF | E3: Ecart
A4: (vide) | D4: 6830 | E4: =B5-D4 -> 0
A5: 2601458 | B5: 6830
A6: Total général | B6: 6830

Sheet Import CSV
A1: Transporteur | B1: Date validité tarif | C1: Réf.1 | D1: Réf. 2 | E1: Id client | F1: N° Tracking | G1: Nom | H1: E / P | I1: Pays | J1: Zone | K1: Nbr Colis | L1: Poids | M1: mode envoi | N1: TVA | O1: Droits et taxes | P1: Assurance | Q1: Zones éloignées | R1: Colis volumineux | S1: Adresses | T1: Frêt | U1: plus-value BtoC | V1: Gazole | W1: Nb Colis
A2: BLS | B2: 46174 | F2: ='Factures BLS'!D2 -> 12118 | G2: ='Factures BLS'!E2 -> De 21 Créancey A 13 Aubagne | H2: E | I2: France | J2: France | K2: 1 | L2: 100 | M2: ST | N2: 0.2 | T2: ='Factures BLS'!J2 -> 1300
A3: BLS | B3: =B2 -> 46174 | F3: ='Factures BLS'!D3 -> 12116 | G3: ='Factures BLS'!E3 -> De 21 Créancey A 60 Grandvilliers | H3: E | I3: France | J3: France | K3: 4 | L3: 1157 | M3: ST | N3: =N2 -> 0.2 | T3: ='Factures BLS'!J3 -> 325
A4: BLS | B4: =B3 -> 46174 | F4: ='Factures BLS'!D4 -> 12144 | G4: ='Factures BLS'!E4 -> De 21 Créancey A 49 Saint-Jean-de-Linières | H4: E | I4: France | J4: France | K4: 4 | L4: 1161 | M4: ST | N4: =N3 -> 0.2 | T4: ='Factures BLS'!J4 -> 340
A5: BLS | B5: =B4 -> 46174 | F5: ='Factures BLS'!D5 -> 12145 | G5: ='Factures BLS'!E5 -> De 21 Créancey A 76 Grand-Couronne | H5: E | I5: France | J5: France | K5: 1 | L5: 270 | M5: ST | N5: =N4 -> 0.2 | T5: ='Factures BLS'!J5 -> 180
A6: BLS | B6: =B5 -> 46174 | F6: ='Factures BLS'!D6 -> 12147 | G6: ='Factures BLS'!E6 -> De 75 Paris A 21 Créancey | H6: E | I6: France | J6: France | K6: 2 | L6: 347 | M6: ST | N6: =N5 -> 0.2 | T6: ='Factures BLS'!J6 -> 300
A7: BLS | B7: =B6 -> 46174 | F7: ='Factures BLS'!D7 -> 12165 | G7: ='Factures BLS'!E7 -> V/Réf HYD06260004 2764316 De 21 Créancey A 21 Ouges | H7: E | I7: France | J7: France | K7: 1 | L7: 100 | M7: ST | N7: =N6 -> 0.2 | T7: ='Factures BLS'!J7 -> 200
A8: BLS | B8: =B7 -> 46174 | F8: ='Factures BLS'!D8 -> 12204 | G8: ='Factures BLS'!E8 -> De 21 Créancey A 34 Castelnau-le-Lez | H8: E | I8: France | J8: France | K8: 3 | L8: 775.5 | M8: ST | N8: =N7 -> 0.2 | T8: ='Factures BLS'!J8 -> 995
A9: BLS | B9: =B8 -> 46174 | F9: ='Factures BLS'!D9 -> 12245 | G9: ='Factures BLS'!E9 -> De 21 Créancey A 95 Vémars | H9: E | I9: France | J9: France | K9: 1 | L9: 100 | M9: ST | N9: =N8 -> 0.2 | T9: ='Factures BLS'!J9 -> 195
A10: BLS | B10: =B9 -> 46174 | F10: ='Factures BLS'!D10 -> 12201 | G10: ='Factures BLS'!E10 -> De 21 Savigny-lès-Beaune A I00 Roma-00176 | H10: E | I10: France | J10: France | K10: 2 | L10: 1050 | M10: ST | N10: =N9 -> 0.2 | T10: ='Factures BLS'!J10 -> 480
A11: BLS | B11: =B10 -> 46174 | F11: ='Factures BLS'!D11 -> 12339 | G11: ='Factures BLS'!E11 -> V/Réf ALPEXPO GRENOBLE De 21 Créancey A 38 Grenoble | H11: E | I11: France | J11: France | K11: 4 | L11: 30 | M11: ST | N11: =N10 -> 0.2 | T11: ='Factures BLS'!J11 -> 575
A12: BLS | B12: =B11 -> 46174 | F12: ='Factures BLS'!D12 -> 12414 | G12: ='Factures BLS'!E12 -> De 21 Créancey A 25 Pontarlier | H12: E | I12: France | J12: France | K12: 2 | L12: 275 | M12: ST | N12: =N11 -> 0.2 | T12: ='Factures BLS'!J12 -> 550
A13: BLS | B13: =B12 -> 46174 | F13: ='Factures BLS'!D13 -> 12532 | G13: ='Factures BLS'!E13 -> De 75 Paris A 21 Créancey | H13: E | I13: France | J13: France | K13: 3 | L13: 681 | M13: ST | N13: =N12 -> 0.2 | T13: ='Factures BLS'!J13 -> 190
A14: BLS | B14: =B13 -> 46174 | F14: ='Factures BLS'!D14 -> 12550 | G14: ='Factures BLS'!E14 -> De 21 Créancey A 75 Paris/16ème Arrondissement | H14: E | I14: France | J14: France | K14: 1 | L14: 100 | M14: ST | N14: =N13 -> 0.2 | T14: ='Factures BLS'!J14 -> 265
... A16: BLS | B16: =B15 -> 46174 | F16: ='Factures BLS'!D16 -> 12676 | G16: ='Factures BLS'!E16 -> De 21 Créancey A 13 Marseille/16ème Arrondissement | H16: E | I16: France | J16: France | K16: 15 | L16: 3000 | M16: ST | N16: =N15 -> 0.2 | T16: ='Factures BLS'!J16 -> 800

Sheet Bilan client
A3: Étiquettes de lignes | B3: Somme de Montant H,T,
A4: (vide)
A5: 3752 | B5: 1820
A6: 8041 | B6: 315
A7: 7261 | B7: 250
A8: 6071 | B8: 340
A9: 361 | B9: 700
A10: 8484 | B10: 180
A11: 3888 | B11: 495
A12: Total général | B12: 4100

Sheet Avoir
A1: Tracking | B1: Transport | C1: Avoir | D1: Raison
