Workbook

Sheet Factures Geodis
A1: ID Client | B1: Coller en valeur la colonne C (Récépissé) et convertir en nombre | C1: Récépissé | D1: Total hors GO | E1: Total + GO | F1: Droits et taxes | G1: Assurance | H1: Zones éloignées | I1: Colis volumineux | J1: Adresses | K1: Frêt | L1: Plus value B2C | M1: Gazole | N1: N° pièce | O1: Date pièce | P1: Type de pièce | Q1: Code tiers | R1: Raison sociale | S1: Code agence traitante | T1: Référence 1 | U1: Référence 2 | V1: N° récépissé | W1: Date récépissé | X1: Code produit | Y1: Instruction livraison 1 | Z1: Instruction livraison 2 | AA1: Nom client départ | AB1: Adresse client départ | AC1: Adresse 2 client départ | AD1: Code pays client départ | AE1: Département Client départ | AF1: Code postal Client départ | AG1: Localité client départ | AH1: Nom destinataire | AI1: Adresse destinataire | AJ1: Adresse 2 destinataire | AK1: Code pays destinataire | AL1: Code département destinataire | AM1: Code postal destinataire | AN1: Localité destinataire | AO1: Nature de marchandises | AP1: Nb Colis | AQ1: Poids origine (kg) | AR1: Poids repesé (kg) | AS1: Volume d'origine (m3) | AT1: Volume réel (m3) | AU1: Poids et/ou volume déclaré erroné | AV1: Mètres plancher | AW1: Nb d'unités | AX1: Type d'unités | AY1: Mt HT /EXO Transport | AZ1: Mt HT/EXO Options et autres | BA1: Mt HT/EXO Total Facturé | BB1: Surcharge Carburant (HT) | BC1: Participation Sûreté & Environnement (HT) | BD1: Montant TVA | BE1: Montant TTC | BF1: Montant Assurance ad valorem (HT) | BG1: Montant valeur assurée | BH1: Contre-remboursement (HT) | BI1: Port dû (HT) | BJ1: Incoterm | BK1: Course (HT) | BL1: Top H (HT) | BM1: Frais fixes administratifs (HT) | BN1: Enlèvement à blanc (HT) | BO1: Enlèvement extérieur (HT) | BP1: Traitement multi-colis (HT) | BQ1: Localités spécifiques (HT) | BR1: Livraison saisonnière (HT) | BS1: Livraison Paris - Région parisienne (HT) | BT1: Nouvelle présentation (HT) | BU1: Livraison GMS et PF logistiques (HT) | BV1: Livraison MIN (HT) | BW1: Livraison Transitaire (HT) | BX1: Livraison du particulier (HT) | BY1: Traitement manuel (HT) | BZ1: Modification d'écriture (HT) | CA1: Expédition Hors Norme (HT) | CB1: Signature hors tablette (HT) | CC1: Transmission POD (HT) | CD1: Surcharge monétaire (HT) | CE1: Taxe kilométrique Belgique (HT) | CF1: Livraison sur RV tél, (HT) | CG1: Livraison sur RV web (HT) | CH1: Livraison le samedi (HT) | CI1: Livraison l'après-midi (HT) | CJ1: Livraison le matin (HT) | CK1: Livraison à date fixe (HT) | CL1: Livraison à l'étage (HT) | CM1: Mise en lieu d'ut, (HT) | CN1: Dépotage (HT) | CO1: Echange à la livraison (HT) | CP1: Remise d'un BL au desti, (HT) | CQ1: Signature sur BL client (HT) | CR1: Gestion des palettes Europe (HT) | CS1: Formalités Douane Exp (HT) | CT1: Formalités Douane Imp, (HT) | CU1: Traitement inform, De douane (HT) | CV1: Marchandises Dang, ADR (HT) | CW1: Marchandises Dang, LQEQ (HT) | CX1: Suivi de Température (HT) | CY1: Vins & Spiritueux (HT) | CZ1: Suivi au colis (HT) | DA1: LC2 - LIVRAISON SUR CRENEAU HORAIRE (HT) | DB1: LCS - LIVRAISON A HEURE DETERMINEE (HT) | DC1: Total CO2eq (kg) | DD1: Particules (g) | DE1: Poids taxable (kg)
C2: =RIGHT(V2,8) -> 93847354 | D2: =SUM(F2:L2) -> 5.7 | E2: =D2+M2 -> 5.7 | F2: =CS2+CT2+CU2 -> 0 | G2: =BF2 -> 0 | H2: =BQ2 -> 0 | I2: =AU2+CA2 -> 0 | J2: =BN2+BO2+BR2+CE2 -> 0 | K2: =AY2+BC2+BI2+BK2+BL2+BM2+BP2+BS2+BT2+BU2+BV2+BW2+BX2+BY2+BZ2+CA2+CB2+CC2+CF2+CG2+CH2+CI2+CJ2+CK2+CL2+CM2+CN2+CO2+CP2+CQ2+CV2+CW2+CY2+CZ2+DA2+DB2 -> 5.7 | M2: =BB2 -> 0 | N2: 2502109369 | O2: 46203 | P2: F | Q2: 600017 | R2: LA RUCHE LOGISTIQUE | S2: 001021 | T2: 2763729 | V2: 93847354 | W2: 2026-05-28 | X2: MES | AA2: LA RUCHE LOGISTIQUE | AB2: VOIE COMMUNALE 4 | AD2: FR | AE2: 21 | AF2: 21320 | AG2: CREANCEY | AH2: ATIDA OMNIPHAR 07 | AI2: LOT BEL SOULEIL | AK2: FR | AL2: 31 | AM2: 31850 | AN2: MONTRABE | AO2: EQUIPEMENTS | AP2: 1 | AQ2: 32 | AR2: 32 | AS2: 0 | AT2: 0 | AV2: 0 | AW2: 0 | AZ2: 5.7 | BA2: 5.7 | BD2: 1.18 | BE2: 6.88 | BG2: 0 | CF2: 5.7 | DC2: - | DD2: - | DE2: 32
C3: =RIGHT(V3,8) -> 94081655 | D3: =SUM(F3:L3) -> 48.1 | E3: =D3+M3 -> 54.91 | F3: =CS3+CT3+CU3 -> 0 | G3: =BF3 -> 0 | H3: =BQ3 -> 0 | I3: =AU3+CA3 -> 0 | J3: =BN3+BO3+BR3+CE3 -> 0 | K3: =AY3+BC3+BI3+BK3+BL3+BM3+BP3+BS3+BT3+BU3+BV3+BW3+BX3+BY3+BZ3+CA3+CB3+CC3+CF3+CG3+CH3+CI3+CJ3+CK3+CL3+CM3+CN3+CO3+CP3+CQ3+CV3+CW3+CY3+CZ3+DA3+DB3 -> 48.1 | M3: =BB3 -> 6.81 | N3: 2502109369 | O3: 46203 | P3: F | Q3: 600017 | R3: LA RUCHE LOGISTIQUE | S3: 001021 | T3: 2766395 | V3: 94081655 | W3: 2026-06-02 | X3: MES | AA3: LA RUCHE LOGISTIQUE | AB3: VOIE COMMUNALE 4 | AD3: FR | AE3: 21 | AF3: 21320 | AG3: CREANCEY | AH3: ATIDA OMNIPHAR 07 | AI3: LOT BEL SOULEIL | AK3: FR | AL3: 31 | AM3: 31850 | AN3: MONTRABE | AP3: 1 | AQ3: 44 | AR3: 44 | AS3: 0 | AT3: 0 | AV3: 0 | AW3: 0 | AY3: 39.8 | AZ3: 5.7 | BA3: 45.5 | BB3: 6.81 | BC3: 2.6 | BD3: 10.98 | BE3: 65.89 | BG3: 0 | CF3: 5.7 | DC3: - | DD3: - | DE3: 44
C4: =RIGHT(V4,8) -> 94231593 | D4: =SUM(F4:L4) -> 110 | E4: =D4+M4 -> 128.37 | F4: =CS4+CT4+CU4 -> 0 | G4: =BF4 -> 0 | H4: =BQ4 -> 0 | I4: =AU4+CA4 -> 0 | J4: =BN4+BO4+BR4+CE4 -> 0 | K4: =AY4+BC4+BI4+BK4+BL4+BM4+BP4+BS4+BT4+BU4+BV4+BW4+BX4+BY4+BZ4+CA4+CB4+CC4+CF4+CG4+CH4+CI4+CJ4+CK4+CL4+CM4+CN4+CO4+CP4+CQ4+CV4+CW4+CY4+CZ4+DA4+DB4 -> 110 | M4: =BB4 -> 18.37 | N4: 2502109369 | O4: 46203 | P4: F | Q4: 600017 | R4: LA RUCHE LOGISTIQUE | S4: 001021 | T4: 2766417 | V4: 94231593 | W4: 2026-06-03 | X4: CX | Y4: PRENDRE RDV AVEC M. CHADER (RDV OBLIGATOIRE POUR LA LIVRAISON): M. CHA | Z4: DER TEL+33 (0)6 69 98 42 58E-MAIL : MCHADER@MALONGO.COM | AA4: LA RUCHE LOGISTIQUE | AB4: VOIE COMMUNALE 4 | AD4: FR | AE4: 21 | AF4: 21320 | AG4: CREANCEY | AH4: CMC MALONGO LOGISTIQUE | AI4: 1ERE AVENUE - 2EME RUE | AJ4: PORTAIL N 2 | AK4: FR | AL4: 06 | AM4: 06510 | AN4: CARROS | AO4: EQUIPEMENTS | AP4: 2 | AQ4: 28 | AR4: 28 | AS4: 0 | AT4: 0 | AV4: 0 | AW4: 0 | AY4: 107.4 | BA4: 107.4 | BB4: 18.37 | BC4: 2.6 | BD4: 25.67 | BE4: 154.04 | BG4: 0 | DC4: - | DD4: - | DE4: 28
C5: =RIGHT(V5,8) -> 41488288 | D5: =SUM(F5:L5) -> 295.36 | E5: =D5+M5 -> 315.85 | F5: =CS5+CT5+CU5 -> 0 | G5: =BF5 -> 0 | H5: =BQ5 -> 0 | I5: =AU5+CA5 -> 0 | J5: =BN5+BO5+BR5+CE5 -> 0 | K5: =AY5+BC5+BI5+BK5+BL5+BM5+BP5+BS5+BT5+BU5+BV5+BW5+BX5+BY5+BZ5+CA5+CB5+CC5+CF5+CG5+CH5+CI5+CJ5+CK5+CL5+CM5+CN5+CO5+CP5+CQ5+CV5+CW5+CY5+CZ5+DA5+DB5 -> 295.36 | M5: =BB5 -> 20.49 | N5: 2502109369 | O5: 46203 | P5: F | Q5: 600017 | R5: LA RUCHE LOGISTIQUE | S5: 001021 | V5: 999941488288 | W5: 2026-06-04 | X5: AFF | Y5: JE REVIENS POUR L HEURE DE RDV | AA5: LA RUCHE LOGISTIQUE | AB5: VOIE COMMUNALE 4 | AD5: FR | AE5: 21 | AF5: 21320 | AG5: CREANCEY | AH5: SAMADA (BÂTIMENT PROLOGIS) | AI5: 1754 AVENUE PAUL DELOUVRIER | AJ5: PARK MOISSY 2 LES CHEVRONS PORTE J | AK5: FR | AL5: 77 | AM5: 77550 | AN5: MOISSY CRAMAYEL | AP5: 3 | AQ5: 343 | AR5: 343 | AS5: 0 | AT5: 0 | AV5: 1.2 | AW5: 0 | AY5: 292.76 | BA5: 292.76 | BB5: 20.49 | BC5: 2.6 | BD5: 63.17 | BE5: 379.02 | BG5: 0 | DC5: - | DD5: -
C6: =RIGHT(V6,8) -> 41536885 | D6: =SUM(F6:L6) -> 57.08 | E6: =D6+M6 -> 66.4 | F6: =CS6+CT6+CU6 -> 0 | G6: =BF6 -> 0 | H6: =BQ6 -> 0 | I6: =AU6+CA6 -> 0 | J6: =BN6+BO6+BR6+CE6 -> 0 | K6: =AY6+BC6+BI6+BK6+BL6+BM6+BP6+BS6+BT6+BU6+BV6+BW6+BX6+BY6+BZ6+CA6+CB6+CC6+CF6+CG6+CH6+CI6+CJ6+CK6+CL6+CM6+CN6+CO6+CP6+CQ6+CV6+CW6+CY6+CZ6+DA6+DB6 -> 57.08 | M6: =BB6 -> 9.32 | N6: 2502109369 | O6: 46203 | P6: F | Q6: 600017 | R6: LA RUCHE LOGISTIQUE | S6: 001021 | T6: 000093630935 | U6: 2757138 | V6: 999941536885 | W6: 2026-06-05 | X6: ENL | Y6: RESTITUTION D'expédition 000093630935 | AA6: RETOUR CERP RRM | AB6: Z.A.C. DE L'ANJOLY | AC6: VOIE D'IRLANDE | AD6: FR | AE6: 13 | AF6: 13400 | AG6: AUBAGNE | AH6: LA RUCHE LOGISTIQUE | AI6: VOIE COMMUNALE 4 | AK6: FR | AL6: 21 | AM6: 21320 | AN6: CREANCEY | AO6: EQUIPEMENTS | AP6: 1 | AQ6: 8.7 | AR6: 8.7 | AS6: 0 | AT6: 0 | AV6: 0 | AW6: 0 | AY6: 54.48 | BA6: 54.48 | BB6: 9.32 | BC6: 2.6 | BD6: 13.28 | BE6: 79.68 | BG6: 0 | DC6: - | DD6: - | DE6: 9
C7: =RIGHT(V7,8) -> 94320254 | D7: =SUM(F7:L7) -> 133.9 | E7: =D7+M7 -> 143.32 | F7: =CS7+CT7+CU7 -> 0 | G7: =BF7 -> 0 | H7: =BQ7 -> 0 | I7: =AU7+CA7 -> 0 | J7: =BN7+BO7+BR7+CE7 -> 0 | K7: =AY7+BC7+BI7+BK7+BL7+BM7+BP7+BS7+BT7+BU7+BV7+BW7+BX7+BY7+BZ7+CA7+CB7+CC7+CF7+CG7+CH7+CI7+CJ7+CK7+CL7+CM7+CN7+CO7+CP7+CQ7+CV7+CW7+CY7+CZ7+DA7+DB7 -> 133.9 | M7: =BB7 -> 9.42 | N7: 2502109369 | O7: 46203 | P7: F | Q7: 600017 | R7: LA RUCHE LOGISTIQUE | S7: 001021 | T7: 94320254 | V7: 94320254 | W7: 2026-06-05 | X7: CX | Y7: PARC DES EXPOS PARIS LE BOURGET HALL 4 / CARREFOUR CHARLES LINDBERGH | Z7: - LIVRAISON AVEC TOP H AVANT 11H + APPELER CONTACT | AA7: LA RUCHE LOGISTIQUE | AB7: VOIE COMMUNALE 4 | AD7: FR | AE7: 21 | AF7: 21320 | AG7: CREANCEY | AH7: STAND PHARMACIE | AI7: CARREFOUR CHARLES LINDBERGH | AK7: FR | AL7: 93 | AM7: 93350 | AN7: LE BOURGET | AP7: 2 | AQ7: 17.7 | AR7: 18 | AS7: 0 | AT7: 0 | AV7: 0 | AW7: 0 | AY7: 55.1 | AZ7: 76.2 | BA7: 131.3 | BB7: 9.42 | BC7: 2.6 | BD7: 28.66 | BE7: 171.98 | BG7: 0 | BS7: 9.9 | DB7: 66.3 | DC7: - | DD7: -
C8: =RIGHT(V8,8) -> 94380676 | D8: =SUM(F8:L8) -> 97.94 | E8: =D8+M8 -> 113.27 | F8: =CS8+CT8+CU8 -> 0 | G8: =BF8 -> 0 | H8: =BQ8 -> 0 | I8: =AU8+CA8 -> 0 | J8: =BN8+BO8+BR8+CE8 -> 0 | K8: =AY8+BC8+BI8+BK8+BL8+BM8+BP8+BS8+BT8+BU8+BV8+BW8+BX8+BY8+BZ8+CA8+CB8+CC8+CF8+CG8+CH8+CI8+CJ8+CK8+CL8+CM8+CN8+CO8+CP8+CQ8+CV8+CW8+CY8+CZ8+DA8+DB8 -> 97.94 | M8: =BB8 -> 15.33 | N8: 2502109369 | O8: 46203 | P8: F | Q8: 600017 | R8: LA RUCHE LOGISTIQUE | S8: 001021 | T8: 2781238 | U8: BDC79432 | V8: 94380676 | W8: 2026-06-05 | X8: MES | Y8: PRISE DE RDV : HTTPS://ESSENTIELS-PHARMA.FR/PRISE-DE-RENDEZ-VOUS/LUNDI | Z8: AU VENDREDI DE 7H A 10H30 | AA8: LA RUCHE LOGISTIQUE | AB8: VOIE COMMUNALE 4 | AD8: FR | AE8: 21 | AF8: 21320 | AG8: CREANCEY | AH8: ESSENTIELS PHARMA | AI8: 1 RUE DE L'ARDELIERE | AK8: FR | AL8: 49 | AM8: 49070 | AN8: BEAUCOUZE | AP8: 1 | AQ8: 170 | AR8: 170 | AS8: 0 | AT8: 0 | AV8: 0 | AW8: 0 | AY8: 89.64 | AZ8: 5.7 | BA8: 95.34 | BB8: 15.33 | BC8: 2.6 | BD8: 22.66 | BE8: 135.93 | BG8: 0 | CF8: 5.7 | DC8: - | DD8: - | DE8: 170
C9: =RIGHT(V9,8) -> 94431027 | D9: =SUM(F9:L9) -> 40.55 | E9: =D9+M9 -> 46.06 | F9: =CS9+CT9+CU9 -> 0 | G9: =BF9 -> 0 | H9: =BQ9 -> 0 | I9: =AU9+CA9 -> 0 | J9: =BN9+BO9+BR9+CE9 -> 0 | K9: =AY9+BC9+BI9+BK9+BL9+BM9+BP9+BS9+BT9+BU9+BV9+BW9+BX9+BY9+BZ9+CA9+CB9+CC9+CF9+CG9+CH9+CI9+CJ9+CK9+CL9+CM9+CN9+CO9+CP9+CQ9+CV9+CW9+CY9+CZ9+DA9+DB9 -> 40.55 | M9: =BB9 -> 5.51 | N9: 2502109369 | O9: 46203 | P9: F | Q9: 600017 | R9: LA RUCHE LOGISTIQUE | S9: 001021 | T9: 2782347 | V9: 94431027 | W9: 2026-06-08 | X9: MES | Y9: PRISE DE RDV OBLIGATOIRE TEL 0685119484-0631875898- MAIL:C.VALLEE@TRAN | Z9: SCAN.FR | AA9: LA RUCHE LOGISTIQUE | AB9: VOIE COMMUNALE 4 | AD9: FR | AE9: 21 | AF9: 21320 | AG9: CREANCEY | AH9: EASY PARAPHARMACIE | AI9: DEPOT N 7 1ERE AVENUE | AJ9: TRANSCAN 4789 | AK9: FR | AL9: 06 | AM9: 06510 | AN9: CARROS | AP9: 3 | AQ9: 21 | AR9: 21 | AS9: 0 | AT9: 0 | AV9: 0 | AW9: 0 | AY9: 32.25 | AZ9: 5.7 | BA9: 37.95 | BB9: 5.51 | BC9: 2.6 | BD9: 9.21 | BE9: 55.27 | BG9: 0 | CF9: 5.7 | DC9: - | DD9: - | DE9: 21
C10: =RIGHT(V10,8) -> 94433083 | D10: =SUM(F10:L10) -> 26.16 | E10: =D10+M10 -> 29.21 | F10: =CS10+CT10+CU10 -> 0 | G10: =BF10 -> 0 | H10: =BQ10 -> 0 | I10: =AU10+CA10 -> 0 | J10: =BN10+BO10+BR10+CE10 -> 0 | K10: =AY10+BC10+BI10+BK10+BL10+BM10+BP10+BS10+BT10+BU10+BV10+BW10+BX10+BY10+BZ10+CA10+CB10+CC10+CF10+CG10+CH10+CI10+CJ10+CK10+CL10+CM10+CN10+CO10+CP10+CQ10+CV10+CW10+CY10+CZ10+DA10+DB10 -> 26.16 | M10: =BB10 -> 3.05 | N10: 2502109369 | O10: 46203 | P10: F | Q10: 600017 | R10: LA RUCHE LOGISTIQUE | S10: 001021 | T10: 2778926 | V10: 94433083 | W10: 2026-06-08 | X10: MES | Y10: N DE COMMANDE : FBC974244 N D'ACCORD DE LIVRAISON : PPS260603020 PRI | Z10: SE DE RDV: HTTPS://WWW.SHIPT.IO/SLOTIFY/ALLTRICKSBRUYERE / TEL: 013048 | AA10: LA RUCHE LOGISTIQUE | AB10: VOIE COMMUNALE 4 | AD10: FR | AE10: 21 | AF10: 21320 | AG10: CREANCEY | AH10: ALLTRICKS FRANCE | AI10: 10 RUE DE LA BRUYERE | AJ10: AVANIS ALLTRICKS | AK10: FR | AL10: 28 | AM10: 28200 | AN10: CHATEAUDUN | AO10: EQUIPEMENTS | AP10: 1 | AQ10: 8 | AR10: 8 | AS10: 0 | AT10: 0 | AV10: 0 | AW10: 0 | AY10: 17.86 | AZ10: 5.7 | BA10: 23.56 | BB10: 3.05 | BC10: 2.6 | BD10: 5.84 | BE10: 35.05 | BG10: 0 | CF10: 5.7 | DC10: - | DD10: - | DE10: 8
C11: =RIGHT(V11,8) -> 94464606 | D11: =SUM(F11:L11) -> 41.54 | E11: =D11+M11 -> 48.2 | F11: =CS11+CT11+CU11 -> 0 | G11: =BF11 -> 0 | H11: =BQ11 -> 0 | I11: =AU11+CA11 -> 0 | J11: =BN11+BO11+BR11+CE11 -> 0 | K11: =AY11+BC11+BI11+BK11+BL11+BM11+BP11+BS11+BT11+BU11+BV11+BW11+BX11+BY11+BZ11+CA11+CB11+CC11+CF11+CG11+CH11+CI11+CJ11+CK11+CL11+CM11+CN11+CO11+CP11+CQ11+CV11+CW11+CY11+CZ11+DA11+DB11 -> 41.54 | M11: =BB11 -> 6.66 | N11: 2502109369 | O11: 46203 | P11: F | Q11: 600017 | R11: LA RUCHE LOGISTIQUE | S11: 001021 | T11: 2774798 | V11: 94464606 | W11: 2026-06-08 | X11: MES | AA11: LA RUCHE LOGISTIQUE | AB11: VOIE COMMUNALE 4 | AD11: FR | AE11: 21 | AF11: 21320 | AG11: CREANCEY | AH11: DHYGIETAL | AI11: 1 RUE DE LA NAU DES VIGNES | AK11: FR | AL11: 51 | AM11: 51520 | AN11: LA VEUVE | AO11: EQUIPEMENTS | AP11: 9 | AQ11: 80 | AR11: 80 | AS11: 0 | AT11: 0 | AV11: 0 | AW11: 0 | AY11: 38.94 | BA11: 38.94 | BB11: 6.66 | BC11: 2.6 | BD11: 9.64 | BE11: 57.84 | BG11: 0 | DC11: - | DD11: - | DE11: 80
C12: =RIGHT(V12,8) -> 41517742 | D12: =SUM(F12:L12) -> 123.12 | E12: =D12+M12 -> 131.56 | F12: =CS12+CT12+CU12 -> 0 | G12: =BF12 -> 0 | H12: =BQ12 -> 0 | I12: =AU12+CA12 -> 0 | J12: =BN12+BO12+BR12+CE12 -> 0 | K12: =AY12+BC12+BI12+BK12+BL12+BM12+BP12+BS12+BT12+BU12+BV12+BW12+BX12+BY12+BZ12+CA12+CB12+CC12+CF12+CG12+CH12+CI12+CJ12+CK12+CL12+CM12+CN12+CO12+CP12+CQ12+CV12+CW12+CY12+CZ12+DA12+DB12 -> 123.12 | M12: =BB12 -> 8.44 | N12: 2502109369 | O12: 46203 | P12: F | Q12: 600017 | R12: LA RUCHE LOGISTIQUE | S12: 001021 | T12: HYD06260008 | V12: 999941517742 | W12: 2026-06-09 | X12: AFF | Y12: LIV IMPERATIVE LE 11/06 ENTRE 6 ET 8H00 | AA12: LA RUCHE LOGISTIQUE | AB12: VOIE COMMUNALE 4 | AD12: FR | AE12: 21 | AF12: 21320 | AG12: CREANCEY | AH12: ENTREPÔT SAMADA | AI12: PARC DU HAUT DE WISSOUS 2 | AJ12: CHEMIN DE LA CROIX BRISÉE (QUAI 153 | AK12: FR | AL12: 91 | AM12: 91320 | AN12: WISSOUS | AP12: 1 | AQ12: 132 | AR12: 132 | AS12: 0 | AT12: 0 | AV12: 0.4 | AW12: 0 | AY12: 120.52 | BA12: 120.52 | BB12: 8.44 | BC12: 2.6 | BD12: 26.31 | BE12: 157.87 | BG12: 0 | DC12: - | DD12: -
C13: =RIGHT(V13,8) -> 94291375 | D13: =SUM(F13:L13) -> 140.06 | E13: =D13+M13 -> 163.57 | F13: =CS13+CT13+CU13 -> 0 | G13: =BF13 -> 0 | H13: =BQ13 -> 0 | I13: =AU13+CA13 -> 0 | J13: =BN13+BO13+BR13+CE13 -> 0 | K13: =AY13+BC13+BI13+BK13+BL13+BM13+BP13+BS13+BT13+BU13+BV13+BW13+BX13+BY13+BZ13+CA13+CB13+CC13+CF13+CG13+CH13+CI13+CJ13+CK13+CL13+CM13+CN13+CO13+CP13+CQ13+CV13+CW13+CY13+CZ13+DA13+DB13 -> 140.06 | M13: =BB13 -> 23.51 | N13: 2502109369 | O13: 46203 | P13: F | Q13: 600017 | R13: LA RUCHE LOGISTIQUE | S13: 001021 | T13: 2777656 | V13: 94291375 | W13: 2026-06-10 | X13: AFG | AA13: LA RUCHE LOGISTIQUE | AB13: VOIE COMMUNALE 4 | AD13: FR | AE13: 21 | AF13: 21320 | AG13: CREANCEY | AH13: B2B PHARMA | AI13: 11 RUE DES FONDEURS | AJ13: ENTREPOT TRIGNAC - ZA ALTITUDE | AK13: FR | AL13: 44 | AM13: 44570 | AN13: TRIGNAC | AO13: EQUIPEMENTS | AP13: 2 | AQ13: 437 | AR13: 437 | AS13: 0 | AT13: 0 | AV13: 0 | AW13: 0 | AY13: 137.46 | BA13: 137.46 | BB13: 23.51 | BC13: 2.6 | BD13: 32.71 | BE13: 196.28 | BG13: 0 | DC13: - | DD13: - | DE13: 2
C14: =RIGHT(V14,8) -> 41565971 | D14: =SUM(F14:L14) -> 435.6 | E14: =D14+M14 -> 465.91 | F14: =CS14+CT14+CU14 -> 0 | G14: =BF14 -> 0 | H14: =BQ14 -> 0 | I14: =AU14+CA14 -> 0 | J14: =BN14+BO14+BR14+CE14 -> 0 | K14: =AY14+BC14+BI14+BK14+BL14+BM14+BP14+BS14+BT14+BU14+BV14+BW14+BX14+BY14+BZ14+CA14+CB14+CC14+CF14+CG14+CH14+CI14+CJ14+CK14+CL14+CM14+CN14+CO14+CP14+CQ14+CV14+CW14+CY14+CZ14+DA14+DB14 -> 435.6 | M14: =BB14 -> 30.31 | N14: 2502109369 | O14: 46203 | P14: F | Q14: 600017 | R14: LA RUCHE LOGISTIQUE | S14: 001021 | V14: 999941565971 | W14: 2026-06-11 | X14: ERD | AA14: NUTRILIQ BY FORENA | AB14: VLAANDERENLAAN 27 | AD14: BE | AE14: 89 | AF14: 8970 | AG14: POPERINGE | AH14: LA RUCHE LOGISTIQUE | AI14: VOIE COMMUNALE 4 | AK14: FR | AL14: 21 | AM14: 21320 | AN14: CREANCEY | AP14: 4 | AQ14: 1289 | AR14: 1289 | AS14: 0 | AT14: 0 | AV14: 1.6 | AW14: 0 | AY14: 433 | BA14: 433 | BB14: 30.31 | BC14: 2.6 | BD14: 93.18 | BE14: 559.09 | BG14: 0 | BJ14: EXW | DC14: - | DD14: -
C15: =RIGHT(V15,8) -> 94806618 | D15: =SUM(F15:L15) -> 52.2 | E15: =D15+M15 -> 59.01 | F15: =CS15+CT15+CU15 -> 0 | G15: =BF15 -> 0 | H15: =BQ15 -> 0 | I15: =AU15+CA15 -> 9.8 | J15: =BN15+BO15+BR15+CE15 -> 0 | K15: =AY15+BC15+BI15+BK15+BL15+BM15+BP15+BS15+BT15+BU15+BV15+BW15+BX15+BY15+BZ15+CA15+CB15+CC15+CF15+CG15+CH15+CI15+CJ15+CK15+CL15+CM15+CN15+CO15+CP15+CQ15+CV15+CW15+CY15+CZ15+DA15+DB15 -> 42.4 | M15: =BB15 -> 6.81 | N15: 2502109369 | O15: 46203 | P15: F | Q15: 600017 | R15: LA RUCHE LOGISTIQUE | S15: 001021 | T15: 2792629 | V15: 94806618 | W15: 2026-06-12 | X15: MES | AA15: LA RUCHE LOGISTIQUE | AB15: VOIE COMMUNALE 4 | AD15: FR | AE15: 21 | AF15: 21320 | AG15: CREANCEY | AH15: ATIDA OMNIPHAR 07 | AI15: LOT BEL SOULEIL | AK15: FR | AL15: 31 | AM15: 31850 | AN15: MONTRABE | AO15: EQUIPEMENTS | AP15: 1 | AQ15: 47 | AR15: 47 | AS15: 0 | AT15: 0 | AU15: 9.8 | AV15: 0 | AW15: 0 | AY15: 39.8 | BA15: 39.8 | BB15: 6.81 | BC15: 2.6 | BD15: 11.8 | BE15: 70.81 | BG15: 0 | DC15: - | DD15: - | DE15: 47
C16: =RIGHT(V16,8) -> 94851743 | D16: =SUM(F16:L16) -> 71.58 | E16: =D16+M16 -> 82.4 | F16: =CS16+CT16+CU16 -> 0 | G16: =BF16 -> 0 | H16: =BQ16 -> 0 | I16: =AU16+CA16 -> 0 | J16: =BN16+BO16+BR16+CE16 -> 0 | K16: =AY16+BC16+BI16+BK16+BL16+BM16+BP16+BS16+BT16+BU16+BV16+BW16+BX16+BY16+BZ16+CA16+CB16+CC16+CF16+CG16+CH16+CI16+CJ16+CK16+CL16+CM16+CN16+CO16+CP16+CQ16+CV16+CW16+CY16+CZ16+DA16+DB16 -> 71.58 | M16: =BB16 -> 10.82 | N16: 2502109369 | O16: 46203 | P16: F | Q16: 600017 | R16: LA RUCHE LOGISTIQUE | S16: 001021 | T16: BDC2026061180462 | U16: 2792712 | V16: 94851743 | W16: 2026-06-15 | X16: MES | Y16: PRISE DE RDV : HTTPS://ESSENTIELS-PHARMA.FR/PRISE-DE-RENDEZ-VOUS/LUNDI | Z16: AU VENDREDI DE 7H A 10H30 | AA16: LA RUCHE LOGISTIQUE | AB16: VOIE COMMUNALE 4 | AD16: FR | AE16: 21 | AF16: 21320 | AG16: CREANCEY | AH16: ESSENTIELS PHARMA | AI16: 1 RUE DE L'ARDELIERE | AK16: FR | AL16: 49 | AM16: 49070 | AN16: BEAUCOUZE | AP16: 1 | AQ16: 115 | AR16: 115 | AS16: 0 | AT16: 0 | AV16: 0 | AW16: 0 | AY16: 63.28 | AZ16: 5.7 | BA16: 68.98 | BB16: 10.82 | BC16: 2.6 | BD16: 16.48 | BE16: 98.88 | BG16: 0 | CF16: 5.7 | DC16: - | DD16: - | DE16: 120
C17: =RIGHT(V17,8) -> 94906944 | D17: =SUM(F17:L17) -> 377.86 | E17: =D17+M17 -> 417.25 | F17: =CS17+CT17+CU17 -> 0 | G17: =BF17 -> 0 | H17: =BQ17 -> 0 | I17: =AU17+CA17 -> 0 | J17: =BN17+BO17+BR17+CE17 -> 0 | K17: =AY17+BC17+BI17+BK17+BL17+BM17+BP17+BS17+BT17+BU17+BV17+BW17+BX17+BY17+BZ17+CA17+CB17+CC17+CF17+CG17+CH17+CI17+CJ17+CK17+CL17+CM17+CN17+CO17+CP17+CQ17+CV17+CW17+CY17+CZ17+DA17+DB17 -> 377.86 | M17: =BB17 -> 39.39 | N17: 2502109369 | O17: 46203 | P17: F | Q17: 600017 | R17: LA RUCHE LOGISTIQUE | S17: 001021 | T17: 2798843 | V17: 94906944 | W17: 2026-06-15 | X17: CX | AA17: LA RUCHE LOGISTIQUE | AB17: VOIE COMMUNALE 4 | AD17: FR | AE17: 21 | AF17: 21320 | AG17: CREANCEY | AH17: LAGARDERE TRAVEL RETAIL FCE | AI17: 7 RUE JEAN JAURES | AK17: FR | AL17: 95 | AM17: 95670 | AN17: MARLY LA VILLE | AP17: 1 | AQ17: 104 | AR17: 104 | AS17: 0 | AT17: 0 | AV17: 0 | AW17: 0 | AY17: 230.36 | AZ17: 144.9 | BA17: 375.26 | BB17: 39.39 | BC17: 2.6 | BD17: 83.45 | BE17: 500.7 | BG17: 0 | BL17: 135 | BS17: 9.9 | DC17: - | DD17: - | DE17: 110
C18: =RIGHT(V18,8) -> 41668167 | D18: =SUM(F18:L18) -> 225.73 | E18: =D18+M18 -> 241.35 | F18: =CS18+CT18+CU18 -> 0 | G18: =BF18 -> 0 | H18: =BQ18 -> 0 | I18: =AU18+CA18 -> 0 | J18: =BN18+BO18+BR18+CE18 -> 0 | K18: =AY18+BC18+BI18+BK18+BL18+BM18+BP18+BS18+BT18+BU18+BV18+BW18+BX18+BY18+BZ18+CA18+CB18+CC18+CF18+CG18+CH18+CI18+CJ18+CK18+CL18+CM18+CN18+CO18+CP18+CQ18+CV18+CW18+CY18+CZ18+DA18+DB18 -> 225.73 | M18: =BB18 -> 15.62 | N18: 2502109369 | O18: 46203 | P18: F | Q18: 600017 | R18: LA RUCHE LOGISTIQUE | S18: 001021 | V18: 999941668167 | W18: 2026-06-18 | X18: AFF | AA18: LA RUCHE LOGISTIQUE | AB18: VOIE COMMUNALE 4 | AD18: FR | AE18: 21 | AF18: 21320 | AG18: CREANCEY | AH18: M&M MILITZER & MÜNCH | AI18: 19 ALLÉE DU CLOS DE CHARMES | AK18: FR | AL18: 77 | AM18: 77090 | AN18: COLLEGIEN | AP18: 4 | AQ18: 850 | AR18: 850 | AS18: 0 | AT18: 0 | AV18: 1.6 | AW18: 0 | AY18: 223.13 | BA18: 223.13 | BB18: 15.62 | BC18: 2.6 | BD18: 48.27 | BE18: 289.62 | BG18: 0 | DC18: - | DD18: -
C19: =RIGHT(V19,8) -> 95104244 | D19: =SUM(F19:L19) -> 83.11 | E19: =D19+M19 -> 92.5 | F19: =CS19+CT19+CU19 -> 0 | G19: =BF19 -> 0 | H19: =BQ19 -> 0 | I19: =AU19+CA19 -> 0 | J19: =BN19+BO19+BR19+CE19 -> 0 | K19: =AY19+BC19+BI19+BK19+BL19+BM19+BP19+BS19+BT19+BU19+BV19+BW19+BX19+BY19+BZ19+CA19+CB19+CC19+CF19+CG19+CH19+CI19+CJ19+CK19+CL19+CM19+CN19+CO19+CP19+CQ19+CV19+CW19+CY19+CZ19+DA19+DB19 -> 83.11 | M19: =BB19 -> 9.39 | N19: 2502109369 | O19: 46203 | P19: F | Q19: 600017 | R19: LA RUCHE LOGISTIQUE | S19: 001021 | T19: EXP20260615-2799804 | U19: 440823 | V19: 95104244 | W19: 2026-06-18 | X19: MES | Y19: PRENDRE RDV AVEC M. CHADER (RDV OBLIGATOIRE POUR LA LIVRAISON): M. CHA | Z19: DER TEL+33 (0)6 69 98 42 58E-MAIL : MCHADER@MALONGO.COM | AA19: LA RUCHE LOGISTIQUE | AB19: VOIE COMMUNALE 4 | AD19: FR | AE19: 21 | AF19: 21320 | AG19: CREANCEY | AH19: CMC MALONGO LOGISTIQUE | AI19: 1ERE AVENUE - 2EME RUE | AJ19: PORTAIL N 2 | AK19: FR | AL19: 06 | AM19: 06510 | AN19: CARROS | AP19: 1 | AQ19: 80 | AR19: 80 | AS19: 0 | AT19: 0 | AV19: 0 | AW19: 0 | AY19: 54.91 | AZ19: 25.6 | BA19: 80.51 | BB19: 9.39 | BC19: 2.6 | BD19: 18.5 | BE19: 111 | BG19: 0 | BT19: 19.9 | CF19: 5.7 | DC19: - | DD19: - | DE19: 80
C20: =RIGHT(V20,8) -> 95191602 | D20: =SUM(F20:L20) -> 34.85 | E20: =D20+M20 -> 40.36 | F20: =CS20+CT20+CU20 -> 0 | G20: =BF20 -> 0 | H20: =BQ20 -> 0 | I20: =AU20+CA20 -> 0 | J20: =BN20+BO20+BR20+CE20 -> 0 | K20: =AY20+BC20+BI20+BK20+BL20+BM20+BP20+BS20+BT20+BU20+BV20+BW20+BX20+BY20+BZ20+CA20+CB20+CC20+CF20+CG20+CH20+CI20+CJ20+CK20+CL20+CM20+CN20+CO20+CP20+CQ20+CV20+CW20+CY20+CZ20+DA20+DB20 -> 34.85 | M20: =BB20 -> 5.51 | N20: 2502109369 | O20: 46203 | P20: F | Q20: 600017 | R20: LA RUCHE LOGISTIQUE | S20: 001021 | T20: 2805970 | V20: 95191602 | W20: 2026-06-19 | X20: MES | Y20: PRISE DE RDV OBLIGATOIRE TEL 0685119484-0631875898- MAIL:C.VALLEE@TRAN | Z20: SCAN.FR | AA20: LA RUCHE LOGISTIQUE | AB20: VOIE COMMUNALE 4 | AD20: FR | AE20: 21 | AF20: 21320 | AG20: CREANCEY | AH20: EASY PARAPHARMACIE | AI20: DEPOT N 7 1ERE AVENUE | AJ20: TRANSCAN 4789 | AK20: FR | AL20: 06 | AM20: 06510 | AN20: CARROS | AO20: EQUIPEMENTS | AP20: 3 | AQ20: 24.7 | AR20: 26 | AS20: 0 | AT20: 0 | AV20: 0 | AW20: 0 | AY20: 32.25 | BA20: 32.25 | BB20: 5.51 | BC20: 2.6 | BD20: 8.07 | BE20: 48.43 | BG20: 0 | DC20: - | DD20: - | DE20: 26
C21: =RIGHT(V21,8) -> 95325743 | D21: =SUM(F21:L21) -> 90.12 | E21: =D21+M21 -> 102.76 | F21: =CS21+CT21+CU21 -> 0 | G21: =BF21 -> 0 | H21: =BQ21 -> 0 | I21: =AU21+CA21 -> 0 | J21: =BN21+BO21+BR21+CE21 -> 0 | K21: =AY21+BC21+BI21+BK21+BL21+BM21+BP21+BS21+BT21+BU21+BV21+BW21+BX21+BY21+BZ21+CA21+CB21+CC21+CF21+CG21+CH21+CI21+CJ21+CK21+CL21+CM21+CN21+CO21+CP21+CQ21+CV21+CW21+CY21+CZ21+DA21+DB21 -> 90.12 | M21: =BB21 -> 12.64 | N21: 2502109369 | O21: 46203 | P21: F | Q21: 600017 | R21: LA RUCHE LOGISTIQUE | S21: 001021 | T21: 2806998 | U21: BDC2026061881351 | V21: 95325743 | W21: 2026-06-23 | X21: MES | Y21: HORAIRE DE LIVRAISON : 08H30-12H00 DU LUNDI AU JEUDI PAS DE LIVRAISON | Z21: LE VENDREDI. | AA21: LA RUCHE LOGISTIQUE | AB21: VOIE COMMUNALE 4 | AD21: FR | AE21: 21 | AF21: 21320 | AG21: CREANCEY | AH21: INFLIGHT SALES | AI21: 3 RUE DES FRERES THONET | AJ21: PARC DES ENTREPRENEURS | AK21: FR | AL21: 94 | AM21: 94450 | AN21: LIMEIL BREVANNES | AP21: 1 | AQ21: 150 | AR21: 150 | AS21: 0 | AT21: 0 | AV21: 0 | AW21: 0 | AY21: 73.92 | AZ21: 13.6 | BA21: 87.52 | BB21: 12.64 | BC21: 2.6 | BD21: 20.55 | BE21: 123.31 | BG21: 0 | BS21: 9.9 | CK21: 3.7 | DC21: - | DD21: - | DE21: 150
C22: =RIGHT(V22,8) -> 95334322 | D22: =SUM(F22:L22) -> 75.34 | E22: =D22+M22 -> 85.45 | F22: =CS22+CT22+CU22 -> 0 | G22: =BF22 -> 0 | H22: =BQ22 -> 0 | I22: =AU22+CA22 -> 0 | J22: =BN22+BO22+BR22+CE22 -> 0 | K22: =AY22+BC22+BI22+BK22+BL22+BM22+BP22+BS22+BT22+BU22+BV22+BW22+BX22+BY22+BZ22+CA22+CB22+CC22+CF22+CG22+CH22+CI22+CJ22+CK22+CL22+CM22+CN22+CO22+CP22+CQ22+CV22+CW22+CY22+CZ22+DA22+DB22 -> 75.34 | M22: =BB22 -> 10.11 | N22: 2502109369 | O22: 46203 | P22: F | Q22: 600017 | R22: LA RUCHE LOGISTIQUE | S22: 001021 | T22: 2805267 | V22: 95334322 | W22: 2026-06-23 | X22: MES | AA22: LA RUCHE LOGISTIQUE | AB22: VOIE COMMUNALE 4 | AD22: FR | AE22: 21 | AF22: 21320 | AG22: CREANCEY | AH22: LAGARDERE TRAVEL RETAIL FCE | AI22: 7 RUE JEAN JAURES | AK22: FR | AL22: 95 | AM22: 95670 | AN22: MARLY LA VILLE | AO22: EQUIPEMENTS | AP22: 1 | AQ22: 111 | AR22: 111 | AS22: 0 | AT22: 0 | AV22: 0 | AW22: 0 | AY22: 59.14 | AZ22: 13.6 | BA22: 72.74 | BB22: 10.11 | BC22: 2.6 | BD22: 17.09 | BE22: 102.54 | BG22: 0 | BS22: 9.9 | CK22: 3.7 | DC22: - | DD22: - | DE22: 120
C23: =RIGHT(V23,8) -> 95392225 | D23: =SUM(F23:L23) -> 48.1 | E23: =D23+M23 -> 54.91 | F23: =CS23+CT23+CU23 -> 0 | G23: =BF23 -> 0 | H23: =BQ23 -> 0 | I23: =AU23+CA23 -> 0 | J23: =BN23+BO23+BR23+CE23 -> 0 | K23: =AY23+BC23+BI23+BK23+BL23+BM23+BP23+BS23+BT23+BU23+BV23+BW23+BX23+BY23+BZ23+CA23+CB23+CC23+CF23+CG23+CH23+CI23+CJ23+CK23+CL23+CM23+CN23+CO23+CP23+CQ23+CV23+CW23+CY23+CZ23+DA23+DB23 -> 48.1 | M23: =BB23 -> 6.81 | N23: 2502109369 | O23: 46203 | P23: F | Q23: 600017 | R23: LA RUCHE LOGISTIQUE | S23: 001021 | T23: 2813733 | V23: 95392225 | W23: 2026-06-23 | X23: MES | AA23: LA RUCHE LOGISTIQUE | AB23: VOIE COMMUNALE 4 | AD23: FR | AE23: 21 | AF23: 21320 | AG23: CREANCEY | AH23: ATIDA OMNIPHAR 07 | AI23: LOT BEL SOULEIL | AK23: FR | AL23: 31 | AM23: 31850 | AN23: MONTRABE | AO23: EQUIPEMENT | AP23: 1 | AQ23: 40 | AR23: 40 | AS23: 0 | AT23: 0 | AV23: 0 | AW23: 0 | AY23: 39.8 | AZ23: 5.7 | BA23: 45.5 | BB23: 6.81 | BC23: 2.6 | BD23: 10.98 | BE23: 65.89 | BG23: 0 | CF23: 5.7 | DC23: - | DD23: - | DE23: 40
C24: =RIGHT(V24,8) -> 95455892 | D24: =SUM(F24:L24) -> 293.46 | E24: =D24+M24 -> 341.52 | F24: =CS24+CT24+CU24 -> 0 | G24: =BF24 -> 0 | H24: =BQ24 -> 0 | I24: =AU24+CA24 -> 9.8 | J24: =BN24+BO24+BR24+CE24 -> 0 | K24: =AY24+BC24+BI24+BK24+BL24+BM24+BP24+BS24+BT24+BU24+BV24+BW24+BX24+BY24+BZ24+CA24+CB24+CC24+CF24+CG24+CH24+CI24+CJ24+CK24+CL24+CM24+CN24+CO24+CP24+CQ24+CV24+CW24+CY24+CZ24+DA24+DB24 -> 283.66 | M24: =BB24 -> 48.06 | N24: 2502109369 | O24: 46203 | P24: F | Q24: 600017 | R24: LA RUCHE LOGISTIQUE | S24: 001021 | T24: EXP20260624-2815943 | V24: 95455892 | W24: 2026-06-24 | X24: MEI | Y24: LE TRANSPORTEUR DOIT RESERVER LE CRENEAU DE DECHARGEMENT A L'ENTREPOT | Z24: SUR LE PORTAIL SUIVANT : HTTPS://I-RS.RIVALTASPED.NET/ | AA24: LA RUCHE LOGISTIQUE | AB24: VOIE COMMUNALE 4 | AD24: FR | AE24: 21 | AF24: 21320 | AG24: CREANCEY | AH24: WAREHOUSE RS 2.0 TORRE GAROFOLI | AI24: STRADA COMUNALE BOSCO SNC | AK24: IT | AL24: 15 | AM24: 15057 | AN24: TORTONA | AP24: 1 | AQ24: 250 | AR24: 250 | AS24: 1.728 | AT24: 2.02 | AU24: 9.8 | AV24: 0 | AW24: 0 | AY24: 281.06 | BA24: 281.06 | BB24: 48.06 | BC24: 2.6 | BD24: 68.3 | BE24: 409.82 | BG24: 0 | BJ24: DAP | DC24: - | DD24: - | DE24: 510
C25: =RIGHT(V25,8) -> 41756837 | D25: =SUM(F25:L25) -> 243.96 | E25: =D25+M25 -> 260.86 | F25: =CS25+CT25+CU25 -> 0 | G25: =BF25 -> 0 | H25: =BQ25 -> 0 | I25: =AU25+CA25 -> 0 | J25: =BN25+BO25+BR25+CE25 -> 0 | K25: =AY25+BC25+BI25+BK25+BL25+BM25+BP25+BS25+BT25+BU25+BV25+BW25+BX25+BY25+BZ25+CA25+CB25+CC25+CF25+CG25+CH25+CI25+CJ25+CK25+CL25+CM25+CN25+CO25+CP25+CQ25+CV25+CW25+CY25+CZ25+DA25+DB25 -> 243.96 | M25: =BB25 -> 16.9 | N25: 2502109369 | O25: 46203 | P25: F | Q25: 600017 | R25: LA RUCHE LOGISTIQUE | S25: 001021 | V25: 999941756837 | W25: 2026-06-25 | X25: AFF | AA25: SARL MAJ | AB25: 5 BOULEVARD EIFFEL | AD25: FR | AE25: 21 | AF25: 21600 | AH25: LA RUCHE LOGISTIQUE | AI25: VOIE COMMUNALE 4 | AK25: FR | AL25: 21 | AM25: 21320 | AN25: CREANCEY | AP25: 1 | AQ25: 10000 | AR25: 10000 | AS25: 0 | AT25: 0 | AV25: 13.2 | AW25: 0 | AY25: 241.36 | BA25: 241.36 | BB25: 16.9 | BC25: 2.6 | BD25: 52.17 | BE25: 313.03 | BG25: 0 | DC25: - | DD25: -
C26: =RIGHT(V26,8) -> 95496289 | D26: =SUM(F26:L26) -> 61.78 | E26: =D26+M26 -> 70.21 | F26: =CS26+CT26+CU26 -> 0 | G26: =BF26 -> 0 | H26: =BQ26 -> 0 | I26: =AU26+CA26 -> 0 | J26: =BN26+BO26+BR26+CE26 -> 0 | K26: =AY26+BC26+BI26+BK26+BL26+BM26+BP26+BS26+BT26+BU26+BV26+BW26+BX26+BY26+BZ26+CA26+CB26+CC26+CF26+CG26+CH26+CI26+CJ26+CK26+CL26+CM26+CN26+CO26+CP26+CQ26+CV26+CW26+CY26+CZ26+DA26+DB26 -> 61.78 | M26: =BB26 -> 8.43 | N26: 2502109369 | O26: 46203 | P26: F | Q26: 600017 | R26: LA RUCHE LOGISTIQUE | S26: 001021 | T26: 2816095 | V26: 95496289 | W26: 2026-06-25 | X26: MES | Y26: HORAIRE DE LIVRAISON : 08H30-12H00 DU LUNDI AU JEUDI PAS DE LIVRAISON | Z26: LE VENDREDI. | AA26: LA RUCHE LOGISTIQUE | AB26: VOIE COMMUNALE 4 | AD26: FR | AE26: 21 | AF26: 21320 | AG26: CREANCEY | AH26: INFLIGHT SALES | AI26: 3 RUE DES FRERES THONET | AJ26: PARC DES ENTREPRENEURS | AK26: FR | AL26: 94 | AM26: 94450 | AN26: LIMEIL BREVANNES | AO26: EQUIPEMENT | AP26: 1 | AQ26: 91.5 | AR26: 91.5 | AS26: 0 | AT26: 0 | AV26: 0 | AW26: 0 | AY26: 49.28 | AZ26: 9.9 | BA26: 59.18 | BB26: 8.43 | BC26: 2.6 | BD26: 14.05 | BE26: 84.26 | BG26: 0 | BS26: 9.9 | DC26: - | DD26: - | DE26: 92
C27: =RIGHT(V27,8) -> 95591735 | D27: =SUM(F27:L27) -> 75.48 | E27: =D27+M27 -> 86.99 | F27: =CS27+CT27+CU27 -> 0 | G27: =BF27 -> 0 | H27: =BQ27 -> 0 | I27: =AU27+CA27 -> 0 | J27: =BN27+BO27+BR27+CE27 -> 1.87 | K27: =AY27+BC27+BI27+BK27+BL27+BM27+BP27+BS27+BT27+BU27+BV27+BW27+BX27+BY27+BZ27+CA27+CB27+CC27+CF27+CG27+CH27+CI27+CJ27+CK27+CL27+CM27+CN27+CO27+CP27+CQ27+CV27+CW27+CY27+CZ27+DA27+DB27 -> 73.61 | M27: =BB27 -> 11.51 | N27: 2502109369 | O27: 46203 | P27: F | Q27: 600017 | R27: LA RUCHE LOGISTIQUE | S27: 001021 | T27: 2813873 | U27: B2B11235 | V27: 95591735 | W27: 2026-06-26 | X27: MEI | AA27: LA RUCHE LOGISTIQUE | AB27: VOIE COMMUNALE 4 | AD27: FR | AE27: 21 | AF27: 21320 | AG27: CREANCEY | AH27: RETAIL CONCEPTS NV | AI27: SMALLANDLAAN 9 | AK27: BE | AL27: 26 | AM27: 2660 | AN27: HOBOKEN (ANTWERPEN) | AP27: 3 | AQ27: 9 | AR27: 9 | AS27: 0.288 | AT27: 0.288 | AV27: 0 | AW27: 0 | AY27: 67.31 | AZ27: 5.57 | BA27: 72.88 | BB27: 11.51 | BC27: 2.6 | BD27: 17.39 | BE27: 104.38 | BG27: 0 | BJ27: DAP | CE27: 1.87 | CK27: 3.7 | DC27: - | DD27: - | DE27: 72
C28: =RIGHT(V28,8) -> 95597955 | D28: =SUM(F28:L28) -> 176.52 | E28: =D28+M28 -> 206.26 | F28: =CS28+CT28+CU28 -> 0 | G28: =BF28 -> 0 | H28: =BQ28 -> 0 | I28: =AU28+CA28 -> 0 | J28: =BN28+BO28+BR28+CE28 -> 0 | K28: =AY28+BC28+BI28+BK28+BL28+BM28+BP28+BS28+BT28+BU28+BV28+BW28+BX28+BY28+BZ28+CA28+CB28+CC28+CF28+CG28+CH28+CI28+CJ28+CK28+CL28+CM28+CN28+CO28+CP28+CQ28+CV28+CW28+CY28+CZ28+DA28+DB28 -> 176.52 | M28: =BB28 -> 29.74 | N28: 2502109369 | O28: 46203 | P28: F | Q28: 600017 | R28: LA RUCHE LOGISTIQUE | S28: 001021 | T28: 2815946 | V28: 95597955 | W28: 2026-06-26 | X28: CX | Y28: DU LUNDI AU VENDREDI DE 08H15-12H00 / 13H00-17H15 CONTACT : SEBASTIEN | Z28: BLACOT / 0344464397 SEBASTIEN.BLECOT@GIPHAR.NET | AA28: LA RUCHE LOGISTIQUE | AB28: VOIE COMMUNALE 4 | AD28: FR | AE28: 21 | AF28: 21320 | AG28: CREANCEY | AH28: GROSSISTE/REPART | AI28: 42 RUE HYACINTHE PETIT | AK28: FR | AL28: 60 | AM28: 60210 | AN28: GRANDVILLIERS | AO28: EQUIPEMENT | AP28: 1 | AQ28: 78.5 | AR28: 78.5 | AS28: 0 | AT28: 0 | AV28: 0 | AW28: 0 | AY28: 173.92 | BA28: 173.92 | BB28: 29.74 | BC28: 2.6 | BD28: 41.25 | BE28: 247.51 | BG28: 0 | DC28: - | DD28: - | DE28: 79
C29: =RIGHT(V29,8) -> 95600280 | D29: =SUM(F29:L29) -> 1045.22 | E29: =D29+M29 -> 1223.51 | F29: =CS29+CT29+CU29 -> 0 | G29: =BF29 -> 0 | H29: =BQ29 -> 0 | I29: =AU29+CA29 -> 0 | J29: =BN29+BO29+BR29+CE29 -> 0 | K29: =AY29+BC29+BI29+BK29+BL29+BM29+BP29+BS29+BT29+BU29+BV29+BW29+BX29+BY29+BZ29+CA29+CB29+CC29+CF29+CG29+CH29+CI29+CJ29+CK29+CL29+CM29+CN29+CO29+CP29+CQ29+CV29+CW29+CY29+CZ29+DA29+DB29 -> 1045.22 | M29: =BB29 -> 178.29 | N29: 2502109369 | O29: 46203 | P29: F | Q29: 600017 | R29: LA RUCHE LOGISTIQUE | S29: 001021 | T29: 2819400 | V29: 95600280 | W29: 2026-06-26 | X29: CX | Y29: DU LUNDI AU VENDREDI 07H30-12H30 CONTACT : STEPHANIE LANNOY / 02413114 | Z29: 71 MNAGERRECEPTION.ANG@GIPHAR.NET | AA29: LA RUCHE LOGISTIQUE | AB29: VOIE COMMUNALE 4 | AD29: FR | AE29: 21 | AF29: 21320 | AG29: CREANCEY | AH29: GIPHAR ANGERS | AI29: RUE ROLAND MORENO | AK29: FR | AL29: 49 | AM29: 49170 | AN29: ST LEGER DES BOIS | AO29: EQUIPEMENT | AP29: 2 | AQ29: 421.5 | AR29: 421.5 | AS29: 0 | AT29: 0 | AV29: 0 | AW29: 0 | AY29: 1042.62 | BA29: 1042.62 | BB29: 178.29 | BC29: 2.6 | BD29: 244.7 | BE29: 1468.21 | BG29: 0 | DC29: - | DD29: - | DE29: 430
C30: =RIGHT(V30,8) -> 95596160 | D30: =SUM(F30:L30) -> 43.09 | E30: =D30+M30 -> 50.01 | F30: =CS30+CT30+CU30 -> 0 | G30: =BF30 -> 0 | H30: =BQ30 -> 0 | I30: =AU30+CA30 -> 0 | J30: =BN30+BO30+BR30+CE30 -> 0 | K30: =AY30+BC30+BI30+BK30+BL30+BM30+BP30+BS30+BT30+BU30+BV30+BW30+BX30+BY30+BZ30+CA30+CB30+CC30+CF30+CG30+CH30+CI30+CJ30+CK30+CL30+CM30+CN30+CO30+CP30+CQ30+CV30+CW30+CY30+CZ30+DA30+DB30 -> 43.09 | M30: =BB30 -> 6.92 | N30: 2502109369 | O30: 46203 | P30: F | Q30: 600017 | R30: LA RUCHE LOGISTIQUE | S30: 001021 | U30: BDC-20260624-82069 | V30: 95596160 | W30: 2026-06-26 | X30: CX | Y30: DU LUNDI AU VENDREDI DE 07H30 / 12H30 CONTACT : CHRISTOPHE THERY | Z30: / 0380820745 CHRISTOPHE.THERY@GIPHAR.NET | AA30: LA RUCHE LOGISTIQUE | AB30: VOIE COMMUNALE 4 | AD30: FR | AE30: 21 | AF30: 21320 | AG30: CREANCEY | AH30: GIPHAR OUGES | AI30: 165 RUE DE L'INNOVATION | AK30: FR | AL30: 21 | AM30: 21600 | AN30: OUGES | AP30: 1 | AQ30: 55 | AR30: 55 | AS30: 0 | AT30: 0 | AV30: 0 | AW30: 0 | AY30: 40.49 | BA30: 40.49 | BB30: 6.92 | BC30: 2.6 | BD30: 10 | BE30: 60.01 | BG30: 0 | DC30: - | DD30: - | DE30: 55
C31: =RIGHT(V31,8) -> 95599531 | D31: =SUM(F31:L31) -> 604.05 | E31: =D31+M31 -> 678.68 | F31: =CS31+CT31+CU31 -> 0 | G31: =BF31 -> 0 | H31: =BQ31 -> 0 | I31: =AU31+CA31 -> 0 | J31: =BN31+BO31+BR31+CE31 -> 0 | K31: =AY31+BC31+BI31+BK31+BL31+BM31+BP31+BS31+BT31+BU31+BV31+BW31+BX31+BY31+BZ31+CA31+CB31+CC31+CF31+CG31+CH31+CI31+CJ31+CK31+CL31+CM31+CN31+CO31+CP31+CQ31+CV31+CW31+CY31+CZ31+DA31+DB31 -> 604.05 | M31: =BB31 -> 74.63 | N31: 2502109369 | O31: 46203 | P31: F | Q31: 600017 | R31: LA RUCHE LOGISTIQUE | S31: 001021 | T31: 2816093 | V31: 95599531 | W31: 2026-06-26 | X31: CX | Y31: DU LUNDI AU VENDREDI DE 7H00 / 12H00 MANAGERRECEPTION.CLL@GIPHAR.NET / | Z31: PASCALE.COUDEYRAS@GIPHAR.NET | AA31: LA RUCHE LOGISTIQUE | AB31: VOIE COMMUNALE 4 | AD31: FR | AE31: 21 | AF31: 21320 | AG31: CREANCEY | AH31: GIPHAR CASTELNAU-LE-NEZ | AI31: 96 AV CLEMENT ADER | AK31: FR | AL31: 34 | AM31: 34170 | AN31: CASTELNAU LE LEZ | AO31: EQUIPEMENT | AP31: 1 | AQ31: 174.5 | AR31: 174.5 | AS31: 0 | AT31: 0 | AV31: 0 | AW31: 0 | AY31: 436.45 | AZ31: 165 | BA31: 601.45 | BB31: 74.63 | BC31: 2.6 | BD31: 135.74 | BE31: 814.42 | BG31: 0 | DA31: 165 | DC31: - | DD31: - | DE31: 180
C32: =RIGHT(V32,8) -> 95602040 | D32: =SUM(F32:L32) -> 66.99 | E32: =D32+M32 -> 77.03 | F32: =CS32+CT32+CU32 -> 0 | G32: =BF32 -> 0 | H32: =BQ32 -> 0 | I32: =AU32+CA32 -> 0 | J32: =BN32+BO32+BR32+CE32 -> 0 | K32: =AY32+BC32+BI32+BK32+BL32+BM32+BP32+BS32+BT32+BU32+BV32+BW32+BX32+BY32+BZ32+CA32+CB32+CC32+CF32+CG32+CH32+CI32+CJ32+CK32+CL32+CM32+CN32+CO32+CP32+CQ32+CV32+CW32+CY32+CZ32+DA32+DB32 -> 66.99 | M32: =BB32 -> 10.04 | N32: 2502109369 | O32: 46203 | P32: F | Q32: 600017 | R32: LA RUCHE LOGISTIQUE | S32: 001021 | T32: EXP20260622-2812231 | V32: 95602040 | W32: 2026-06-26 | X32: MES | AA32: LA RUCHE LOGISTIQUE | AB32: VOIE COMMUNALE 4 | AD32: FR | AE32: 21 | AF32: 21320 | AG32: CREANCEY | AH32: SOFIA COSMETIQUES | AI32: ZI 1ERE AVENUE, 4E RUE | AK32: FR | AL32: 06 | AM32: 06510 | AN32: CARROS | AP32: 1 | AQ32: 95 | AR32: 95 | AS32: 0 | AT32: 0 | AV32: 0 | AW32: 0 | AY32: 58.69 | AZ32: 5.7 | BA32: 64.39 | BB32: 10.04 | BC32: 2.6 | BD32: 15.41 | BE32: 92.44 | BG32: 0 | CF32: 5.7 | DC32: - | DD32: - | DE32: 95
C33: =RIGHT(V33,8) -> 95686648 | D33: =SUM(F33:L33) -> 46.85 | E33: =D33+M33 -> 53.44 | F33: =CS33+CT33+CU33 -> 0 | G33: =BF33 -> 0 | H33: =BQ33 -> 0 | I33: =AU33+CA33 -> 0 | J33: =BN33+BO33+BR33+CE33 -> 0 | K33: =AY33+BC33+BI33+BK33+BL33+BM33+BP33+BS33+BT33+BU33+BV33+BW33+BX33+BY33+BZ33+CA33+CB33+CC33+CF33+CG33+CH33+CI33+CJ33+CK33+CL33+CM33+CN33+CO33+CP33+CQ33+CV33+CW33+CY33+CZ33+DA33+DB33 -> 46.85 | M33: =BB33 -> 6.59 | N33: 2502109369 | O33: 46203 | P33: F | Q33: 600017 | R33: LA RUCHE LOGISTIQUE | S33: 001021 | T33: 2818456 | U33: BDC2026062582274 | V33: 95686648 | W33: 2026-06-29 | X33: MES | Y33: PRISE DE RDV : HTTPS://ESSENTIELS-PHARMA.FR/PRISE-DE-RENDEZ-VOUS/LUNDI | Z33: AU VENDREDI DE 7H A 10H30 | AA33: LA RUCHE LOGISTIQUE | AB33: VOIE COMMUNALE 4 | AD33: FR | AE33: 21 | AF33: 21320 | AG33: CREANCEY | AH33: ESSENTIELS PHARMA | AI33: 1 RUE DE L'ARDELIERE | AK33: FR | AL33: 49 | AM33: 49070 | AN33: BEAUCOUZE | AP33: 5 | AQ33: 50 | AR33: 50 | AS33: 0 | AT33: 0 | AV33: 0 | AW33: 0 | AY33: 38.55 | AZ33: 5.7 | BA33: 44.25 | BB33: 6.59 | BC33: 2.6 | BD33: 10.69 | BE33: 64.13 | BG33: 0 | CF33: 5.7 | DC33: - | DD33: - | DE33: 50
C34: =RIGHT(V34,8) -> 95732649 | D34: =SUM(F34:L34) -> 40.16 | E34: =D34+M34 -> 44.12 | F34: =CS34+CT34+CU34 -> 0 | G34: =BF34 -> 0 | H34: =BQ34 -> 0 | I34: =AU34+CA34 -> 0 | J34: =BN34+BO34+BR34+CE34 -> 0 | K34: =AY34+BC34+BI34+BK34+BL34+BM34+BP34+BS34+BT34+BU34+BV34+BW34+BX34+BY34+BZ34+CA34+CB34+CC34+CF34+CG34+CH34+CI34+CJ34+CK34+CL34+CM34+CN34+CO34+CP34+CQ34+CV34+CW34+CY34+CZ34+DA34+DB34 -> 40.16 | M34: =BB34 -> 3.96 | N34: 2502109369 | O34: 46203 | P34: F | Q34: 600017 | R34: LA RUCHE LOGISTIQUE | S34: 001021 | V34: 95732649 | W34: 2026-06-30 | X34: MES | AA34: LA RUCHE LOGISTIQUE | AB34: VOIE COMMUNALE 4 | AD34: FR | AE34: 21 | AF34: 21320 | AG34: CREANCEY | AH34: CELLUSA | AI34: 1 PLACE DE LA LOGISTIQUE | AJ34: SOGARIS-BAT S-Q2 | AK34: FR | AL34: 94 | AM34: 94150 | AN34: RUNGIS | AO34: EQUIPEMENTS | AP34: 4 | AQ34: 19 | AR34: 19 | AS34: 0 | AT34: 0 | AV34: 0 | AW34: 0 | AY34: 23.16 | AZ34: 14.4 | BA34: 37.56 | BB34: 3.96 | BC34: 2.6 | BD34: 8.82 | BE34: 52.94 | BG34: 0 | BS34: 9.9 | BX34: 4.5 | DC34: - | DD34: - | DE34: 19
C35: =RIGHT(V35,8) -> 95756330 | D35: =SUM(F35:L35) -> 391.92 | E35: =D35+M35 -> 427.73 | F35: =CS35+CT35+CU35 -> 0 | G35: =BF35 -> 0 | H35: =BQ35 -> 0 | I35: =AU35+CA35 -> 0 | J35: =BN35+BO35+BR35+CE35 -> 0 | K35: =AY35+BC35+BI35+BK35+BL35+BM35+BP35+BS35+BT35+BU35+BV35+BW35+BX35+BY35+BZ35+CA35+CB35+CC35+CF35+CG35+CH35+CI35+CJ35+CK35+CL35+CM35+CN35+CO35+CP35+CQ35+CV35+CW35+CY35+CZ35+DA35+DB35 -> 391.92 | M35: =BB35 -> 35.81 | N35: 2502109369 | O35: 46203 | P35: F | Q35: 600017 | R35: LA RUCHE LOGISTIQUE | S35: 001021 | T35: 2813677 | V35: 95756330 | W35: 2026-06-30 | X35: CX | AA35: LA RUCHE LOGISTIQUE | AB35: VOIE COMMUNALE 4 | AD35: FR | AE35: 21 | AF35: 21320 | AG35: CREANCEY | AH35: ENTREPOT SAMADA | AI35: 2 CHEMIN DE LA CROIX BRISEE | AJ35: PARC DU HAUT DE WISSOUS | AK35: FR | AL35: 91 | AM35: 91320 | AN35: WISSOUS | AP35: 1 | AQ35: 90 | AR35: 90 | AS35: 0 | AT35: 0 | AV35: 0 | AW35: 0 | AY35: 209.42 | AZ35: 179.9 | BA35: 389.32 | BB35: 35.81 | BC35: 2.6 | BD35: 85.54 | BE35: 513.27 | BG35: 0 | BL35: 170 | BS35: 9.9 | DC35: - | DD35: - | DE35: 90
C36: =RIGHT(V36,8) -> 95761019 | D36: =SUM(F36:L36) -> 38.61 | E36: =D36+M36 -> 44.77 | F36: =CS36+CT36+CU36 -> 0 | G36: =BF36 -> 0 | H36: =BQ36 -> 0 | I36: =AU36+CA36 -> 0 | J36: =BN36+BO36+BR36+CE36 -> 0 | K36: =AY36+BC36+BI36+BK36+BL36+BM36+BP36+BS36+BT36+BU36+BV36+BW36+BX36+BY36+BZ36+CA36+CB36+CC36+CF36+CG36+CH36+CI36+CJ36+CK36+CL36+CM36+CN36+CO36+CP36+CQ36+CV36+CW36+CY36+CZ36+DA36+DB36 -> 38.61 | M36: =BB36 -> 6.16 | N36: 2502109369 | O36: 46203 | P36: F | Q36: 600017 | R36: LA RUCHE LOGISTIQUE | S36: 001021 | T36: 2828727 | V36: 95761019 | W36: 2026-06-30 | X36: MES | AA36: LA RUCHE LOGISTIQUE | AB36: VOIE COMMUNALE 4 | AD36: FR | AE36: 21 | AF36: 21320 | AG36: CREANCEY | AH36: ATIDA OMNIPHAR 07 | AI36: LOT BEL SOULEIL | AK36: FR | AL36: 31 | AM36: 31850 | AN36: MONTRABE | AP36: 1 | AQ36: 35.5 | AR36: 35.5 | AS36: 0 | AT36: 0 | AV36: 0 | AW36: 0 | AY36: 36.01 | BA36: 36.01 | BB36: 6.16 | BC36: 2.6 | BD36: 8.95 | BE36: 53.72 | BG36: 0 | DC36: - | DD36: - | DE36: 36

Sheet Bilan Factures
A3: Frais de tenue de compte 28,5€/mois
A5: Étiquettes de lignes | B5: Somme de Total + GO | C5: Frais de gestion | D5: PDF | E5: Ecarts
A6: (vide) | C6: 28.5 | E6: =D6-B6 -> 0 | F6: =IF(E6=27.7,"OK","Contrôler Ecarts") -> Contrôler Ecarts
A7: 2502109369 | B7: 6453.45 | D7: 6481.95 | E7: =D7-B7-C6 -> 0 | F7: =IF(E7=27.7,"OK","Contrôler Ecarts") -> Contrôler Ecarts
A8: Total général | B8: 6453.45

Sheet Import CSV
A1: Transporteur | B1: Date validité tarif | C1: Réf.1 | D1: Réf. 2 | E1: Id client | F1: N° Tracking | G1: Nom | H1: E / P | I1: Pays | J1: Zone | K1: Nbr Colis | L1: Poids | M1: mode envoi | N1: TVA | O1: Droits et taxes | P1: Assurance | Q1: Zones éloignées | R1: Colis volumineux | S1: Adresses | T1: Frêt | U1: plus-value BtoC | V1: Gazole | W1: Nb Colis
A2: GEODIS | B2: 46174 | C2: =IF(_xlfn.XLOOKUP(F2,'Factures Geodis'!C:C,'Factures Geodis'!T:T,"")=0,"",_xlfn.XLOOKUP(F2,'Factures Geodis'!C:C,'Factures Geodis'!T:T,"")) -> 2763729 | F2: ='Factures Geodis'!C2 -> 93847354 | G2: ='Factures Geodis'!AH2 -> ATIDA OMNIPHAR 07 | I2: ='Factures Geodis'!AD2 -> FR | J2: France | K2: ='Factures Geodis'!AP2 -> 1 | L2: ='Factures Geodis'!AQ2 -> 32 | M2: ST | N2: 0.2 | O2: =IF('Factures Geodis'!F2=0,"",'Factures Geodis'!F2) | P2: =IF('Factures Geodis'!G2=0,"",'Factures Geodis'!G2) | Q2: =IF('Factures Geodis'!H2=0,"",'Factures Geodis'!H2) | R2: =IF('Factures Geodis'!I2=0,"",'Factures Geodis'!I2) | S2: =IF('Factures Geodis'!J2=0,"",'Factures Geodis'!J2) | T2: =IF('Factures Geodis'!K2=0,"",'Factures Geodis'!K2) -> 5.7 | U2: =IF('Factures Geodis'!L2=0,"",'Factures Geodis'!L2)
A3: =A2 -> GEODIS | B3: =B2 -> 46174 | C3: =IF(_xlfn.XLOOKUP(F3,'Factures Geodis'!C:C,'Factures Geodis'!T:T,"")=0,"",_xlfn.XLOOKUP(F3,'Factures Geodis'!C:C,'Factures Geodis'!T:T,"")) -> 2766395 | F3: ='Factures Geodis'!C3 -> 94081655 | G3: ='Factures Geodis'!AH3 -> ATIDA OMNIPHAR 07 | I3: ='Factures Geodis'!AD3 -> FR | J3: =J2 -> France | K3: ='Factures Geodis'!AP3 -> 1 | L3: ='Factures Geodis'!AQ3 -> 44 | M3: ST | N3: =N2 -> 0.2 | O3: =IF('Factures Geodis'!F3=0,"",'Factures Geodis'!F3) | P3: =IF('Factures Geodis'!G3=0,"",'Factures Geodis'!G3) | Q3: =IF('Factures Geodis'!H3=0,"",'Factures Geodis'!H3) | R3: =IF('Factures Geodis'!I3=0,"",'Factures Geodis'!I3) | S3: =IF('Factures Geodis'!J3=0,"",'Factures Geodis'!J3) | T3: =IF('Factures Geodis'!K3=0,"",'Factures Geodis'!K3) -> 48.1 | U3: =IF('Factures Geodis'!L3=0,"",'Factures Geodis'!L3)
A4: =A3 -> GEODIS | B4: =B3 -> 46174 | C4: =IF(_xlfn.XLOOKUP(F4,'Factures Geodis'!C:C,'Factures Geodis'!T:T,"")=0,"",_xlfn.XLOOKUP(F4,'Factures Geodis'!C:C,'Factures Geodis'!T:T,"")) -> 2766417 | F4: ='Factures Geodis'!C4 -> 94231593 | G4: ='Factures Geodis'!AH4 -> CMC MALONGO LOGISTIQUE | I4: ='Factures Geodis'!AD4 -> FR | J4: =J3 -> France | K4: ='Factures Geodis'!AP4 -> 2 | L4: ='Factures Geodis'!AQ4 -> 28 | M4: ST | N4: =N3 -> 0.2 | O4: =IF('Factures Geodis'!F4=0,"",'Factures Geodis'!F4) | P4: =IF('Factures Geodis'!G4=0,"",'Factures Geodis'!G4) | Q4: =IF('Factures Geodis'!H4=0,"",'Factures Geodis'!H4) | R4: =IF('Factures Geodis'!I4=0,"",'Factures Geodis'!I4) | S4: =IF('Factures Geodis'!J4=0,"",'Factures Geodis'!J4) | T4: =IF('Factures Geodis'!K4=0,"",'Factures Geodis'!K4) -> 110 | U4: =IF('Factures Geodis'!L4=0,"",'Factures Geodis'!L4)
A5: =A4 -> GEODIS | B5: =B4 -> 46174 | C5: =IF(_xlfn.XLOOKUP(F5,'Factures Geodis'!C:C,'Factures Geodis'!T:T,"")=0,"",_xlfn.XLOOKUP(F5,'Factures Geodis'!C:C,'Factures Geodis'!T:T,"")) | F5: ='Factures Geodis'!C5 -> 41488288 | G5: ='Factures Geodis'!AH5 -> SAMADA (BÂTIMENT PROLOGIS) | I5: ='Factures Geodis'!AD5 -> FR | J5: =J4 -> France | K5: ='Factures Geodis'!AP5 -> 3 | L5: ='Factures Geodis'!AQ5 -> 343 | M5: ST | N5: =N4 -> 0.2 | O5: =IF('Factures Geodis'!F5=0,"",'Factures Geodis'!F5) | P5: =IF('Factures Geodis'!G5=0,"",'Factures Geodis'!G5) | Q5: =IF('Factures Geodis'!H5=0,"",'Factures Geodis'!H5) | R5: =IF('Factures Geodis'!I5=0,"",'Factures Geodis'!I5) | S5: =IF('Factures Geodis'!J5=0,"",'Factures Geodis'!J5) | T5: =IF('Factures Geodis'!K5=0,"",'Factures Geodis'!K5) -> 295.36 | U5: =IF('Factures Geodis'!L5=0,"",'Factures Geodis'!L5)
A6: =A5 -> GEODIS | B6: =B5 -> 46174 | C6: =IF(_xlfn.XLOOKUP(F6,'Factures Geodis'!C:C,'Factures Geodis'!T:T,"")=0,"",_xlfn.XLOOKUP(F6,'Factures Geodis'!C:C,'Factures Geodis'!T:T,"")) -> 000093630935 | F6: ='Factures Geodis'!C6 -> 41536885 | G6: ='Factures Geodis'!AH6 -> LA RUCHE LOGISTIQUE | I6: ='Factures Geodis'!AD6 -> FR | J6: =J5 -> France | K6: ='Factures Geodis'!AP6 -> 1 | L6: ='Factures Geodis'!AQ6 -> 8.7 | M6: ST | N6: =N5 -> 0.2 | O6: =IF('Factures Geodis'!F6=0,"",'Factures Geodis'!F6) | P6: =IF('Factures Geodis'!G6=0,"",'Factures Geodis'!G6) | Q6: =IF('Factures Geodis'!H6=0,"",'Factures Geodis'!H6) | R6: =IF('Factures Geodis'!I6=0,"",'Factures Geodis'!I6) | S6: =IF('Factures Geodis'!J6=0,"",'Factures Geodis'!J6) | T6: =IF('Factures Geodis'!K6=0,"",'Factures Geodis'!K6) -> 57.08 | U6: =IF('Factures Geodis'!L6=0,"",'Factures Geodis'!L6)
A7: =A6 -> GEODIS | B7: =B6 -> 46174 | C7: =IF(_xlfn.XLOOKUP(F7,'Factures Geodis'!C:C,'Factures Geodis'!T:T,"")=0,"",_xlfn.XLOOKUP(F7,'Factures Geodis'!C:C,'Factures Geodis'!T:T,"")) -> 94320254 | F7: ='Factures Geodis'!C7 -> 94320254 | G7: ='Factures Geodis'!AH7 -> STAND PHARMACIE | I7: ='Factures Geodis'!AD7 -> FR | J7: =J6 -> France | K7: ='Factures Geodis'!AP7 -> 2 | L7: ='Factures Geodis'!AQ7 -> 17.7 | M7: ST | N7: =N6 -> 0.2 | O7: =IF('Factures Geodis'!F7=0,"",'Factures Geodis'!F7) | P7: =IF('Factures Geodis'!G7=0,"",'Factures Geodis'!G7) | Q7: =IF('Factures Geodis'!H7=0,"",'Factures Geodis'!H7) | R7: =IF('Factures Geodis'!I7=0,"",'Factures Geodis'!I7) | S7: =IF('Factures Geodis'!J7=0,"",'Factures Geodis'!J7) | T7: =IF('Factures Geodis'!K7=0,"",'Factures Geodis'!K7) -> 133.9 | U7: =IF('Factures Geodis'!L7=0,"",'Factures Geodis'!L7)
A8: =A7 -> GEODIS | B8: =B7 -> 46174 | C8: =IF(_xlfn.XLOOKUP(F8,'Factures Geodis'!C:C,'Factures Geodis'!T:T,"")=0,"",_xlfn.XLOOKUP(F8,'Factures Geodis'!C:C,'Factures Geodis'!T:T,"")) -> 2781238 | F8: ='Factures Geodis'!C8 -> 94380676 | G8: ='Factures Geodis'!AH8 -> ESSENTIELS PHARMA | I8: ='Factures Geodis'!AD8 -> FR | J8: =J7 -> France | K8: ='Factures Geodis'!AP8 -> 1 | L8: ='Factures Geodis'!AQ8 -> 170 | M8: ST | N8: =N7 -> 0.2 | O8: =IF('Factures Geodis'!F8=0,"",'Factures Geodis'!F8) | P8: =IF('Factures Geodis'!G8=0,"",'Factures Geodis'!G8) | Q8: =IF('Factures Geodis'!H8=0,"",'Factures Geodis'!H8) | R8: =IF('Factures Geodis'!I8=0,"",'Factures Geodis'!I8) | S8: =IF('Factures Geodis'!J8=0,"",'Factures Geodis'!J8) | T8: =IF('Factures Geodis'!K8=0,"",'Factures Geodis'!K8) -> 97.94 | U8: =IF('Factures Geodis'!L8=0,"",'Factures Geodis'!L8)
A9: =A8 -> GEODIS | B9: =B8 -> 46174 | C9: =IF(_xlfn.XLOOKUP(F9,'Factures Geodis'!C:C,'Factures Geodis'!T:T,"")=0,"",_xlfn.XLOOKUP(F9,'Factures Geodis'!C:C,'Factures Geodis'!T:T,"")) -> 2782347 | F9: ='Factures Geodis'!C9 -> 94431027 | G9: ='Factures Geodis'!AH9 -> EASY PARAPHARMACIE | I9: ='Factures Geodis'!AD9 -> FR | J9: =J8 -> France | K9: ='Factures Geodis'!AP9 -> 3 | L9: ='Factures Geodis'!AQ9 -> 21 | M9: ST | N9: =N8 -> 0.2 | O9: =IF('Factures Geodis'!F9=0,"",'Factures Geodis'!F9) | P9: =IF('Factures Geodis'!G9=0,"",'Factures Geodis'!G9) | Q9: =IF('Factures Geodis'!H9=0,"",'Factures Geodis'!H9) | R9: =IF('Factures Geodis'!I9=0,"",'Factures Geodis'!I9) | S9: =IF('Factures Geodis'!J9=0,"",'Factures Geodis'!J9) | T9: =IF('Factures Geodis'!K9=0,"",'Factures Geodis'!K9) -> 40.55 | U9: =IF('Factures Geodis'!L9=0,"",'Factures Geodis'!L9)
A10: =A9 -> GEODIS | B10: =B9 -> 46174 | C10: =IF(_xlfn.XLOOKUP(F10,'Factures Geodis'!C:C,'Factures Geodis'!T:T,"")=0,"",_xlfn.XLOOKUP(F10,'Factures Geodis'!C:C,'Factures Geodis'!T:T,"")) -> 2778926 | F10: ='Factures Geodis'!C10 -> 94433083 | G10: ='Factures Geodis'!AH10 -> ALLTRICKS FRANCE | I10: ='Factures Geodis'!AD10 -> FR | J10: =J9 -> France | K10: ='Factures Geodis'!AP10 -> 1 | L10: ='Factures Geodis'!AQ10 -> 8 | M10: ST | N10: =N9 -> 0.2 | O10: =IF('Factures Geodis'!F10=0,"",'Factures Geodis'!F10) | P10: =IF('Factures Geodis'!G10=0,"",'Factures Geodis'!G10) | Q10: =IF('Factures Geodis'!H10=0,"",'Factures Geodis'!H10) | R10: =IF('Factures Geodis'!I10=0,"",'Factures Geodis'!I10) | S10: =IF('Factures Geodis'!J10=0,"",'Factures Geodis'!J10) | T10: =IF('Factures Geodis'!K10=0,"",'Factures Geodis'!K10) -> 26.16 | U10: =IF('Factures Geodis'!L10=0,"",'Factures Geodis'!L10)
A11: =A10 -> GEODIS | B11: =B10 -> 46174 | C11: =IF(_xlfn.XLOOKUP(F11,'Factures Geodis'!C:C,'Factures Geodis'!T:T,"")=0,"",_xlfn.XLOOKUP(F11,'Factures Geodis'!C:C,'Factures Geodis'!T:T,"")) -> 2774798 | F11: ='Factures Geodis'!C11 -> 94464606 | G11: ='Factures Geodis'!AH11 -> DHYGIETAL | I11: ='Factures Geodis'!AD11 -> FR | J11: =J10 -> France | K11: ='Factures Geodis'!AP11 -> 9 | L11: ='Factures Geodis'!AQ11 -> 80 | M11: ST | N11: =N10 -> 0.2 | O11: =IF('Factures Geodis'!F11=0,"",'Factures Geodis'!F11) | P11: =IF('Factures Geodis'!G11=0,"",'Factures Geodis'!G11) | Q11: =IF('Factures Geodis'!H11=0,"",'Factures Geodis'!H11) | R11: =IF('Factures Geodis'!I11=0,"",'Factures Geodis'!I11) | S11: =IF('Factures Geodis'!J11=0,"",'Factures Geodis'!J11) | T11: =IF('Factures Geodis'!K11=0,"",'Factures Geodis'!K11) -> 41.54 | U11: =IF('Factures Geodis'!L11=0,"",'Factures Geodis'!L11)
A12: =A11 -> GEODIS | B12: =B11 -> 46174 | C12: =IF(_xlfn.XLOOKUP(F12,'Factures Geodis'!C:C,'Factures Geodis'!T:T,"")=0,"",_xlfn.XLOOKUP(F12,'Factures Geodis'!C:C,'Factures Geodis'!T:T,"")) -> HYD06260008 | F12: ='Factures Geodis'!C12 -> 41517742 | G12: ='Factures Geodis'!AH12 -> ENTREPÔT SAMADA | I12: ='Factures Geodis'!AD12 -> FR | J12: =J11 -> France | K12: ='Factures Geodis'!AP12 -> 1 | L12: ='Factures Geodis'!AQ12 -> 132 | M12: ST | N12: =N11 -> 0.2 | O12: =IF('Factures Geodis'!F12=0,"",'Factures Geodis'!F12) | P12: =IF('Factures Geodis'!G12=0,"",'Factures Geodis'!G12) | Q12: =IF('Factures Geodis'!H12=0,"",'Factures Geodis'!H12) | R12: =IF('Factures Geodis'!I12=0,"",'Factures Geodis'!I12) | S12: =IF('Factures Geodis'!J12=0,"",'Factures Geodis'!J12) | T12: =IF('Factures Geodis'!K12=0,"",'Factures Geodis'!K12) -> 123.12 | U12: =IF('Factures Geodis'!L12=0,"",'Factures Geodis'!L12)
A13: =A12 -> GEODIS | B13: =B12 -> 46174 | C13: =IF(_xlfn.XLOOKUP(F13,'Factures Geodis'!C:C,'Factures Geodis'!T:T,"")=0,"",_xlfn.XLOOKUP(F13,'Factures Geodis'!C:C,'Factures Geodis'!T:T,"")) -> 2777656 | F13: ='Factures Geodis'!C13 -> 94291375 | G13: ='Factures Geodis'!AH13 -> B2B PHARMA | I13: ='Factures Geodis'!AD13 -> FR | J13: =J12 -> France | K13: ='Factures Geodis'!AP13 -> 2 | L13: ='Factures Geodis'!AQ13 -> 437 | M13: ST | N13: =N12 -> 0.2 | O13: =IF('Factures Geodis'!F13=0,"",'Factures Geodis'!F13) | P13: =IF('Factures Geodis'!G13=0,"",'Factures Geodis'!G13) | Q13: =IF('Factures Geodis'!H13=0,"",'Factures Geodis'!H13) | R13: =IF('Factures Geodis'!I13=0,"",'Factures Geodis'!I13) | S13: =IF('Factures Geodis'!J13=0,"",'Factures Geodis'!J13) | T13: =IF('Factures Geodis'!K13=0,"",'Factures Geodis'!K13) -> 140.06 | U13: =IF('Factures Geodis'!L13=0,"",'Factures Geodis'!L13)
A14: =A13 -> GEODIS | B14: =B13 -> 46174 | C14: =IF(_xlfn.XLOOKUP(F14,'Factures Geodis'!C:C,'Factures Geodis'!T:T,"")=0,"",_xlfn.XLOOKUP(F14,'Factures Geodis'!C:C,'Factures Geodis'!T:T,"")) | F14: ='Factures Geodis'!C14 -> 41565971 | G14: ='Factures Geodis'!AH14 -> LA RUCHE LOGISTIQUE | I14: ='Factures Geodis'!AD14 -> BE | J14: =J13 -> France | K14: ='Factures Geodis'!AP14 -> 4 | L14: ='Factures Geodis'!AQ14 -> 1289 | M14: ST | N14: =N13 -> 0.2 | O14: =IF('Factures Geodis'!F14=0,"",'Factures Geodis'!F14) | P14: =IF('Factures Geodis'!G14=0,"",'Factures Geodis'!G14) | Q14: =IF('Factures Geodis'!H14=0,"",'Factures Geodis'!H14) | R14: =IF('Factures Geodis'!I14=0,"",'Factures Geodis'!I14) | S14: =IF('Factures Geodis'!J14=0,"",'Factures Geodis'!J14) | T14: =IF('Factures Geodis'!K14=0,"",'Factures Geodis'!K14) -> 435.6 | U14: =IF('Factures Geodis'!L14=0,"",'Factures Geodis'!L14)
... A36: =A35 -> GEODIS | B36: =B35 -> 46174 | C36: =IF(_xlfn.XLOOKUP(F36,'Factures Geodis'!C:C,'Factures Geodis'!T:T,"")=0,"",_xlfn.XLOOKUP(F36,'Factures Geodis'!C:C,'Factures Geodis'!T:T,"")) -> 2828727 | F36: ='Factures Geodis'!C36 -> 95761019 | G36: ='Factures Geodis'!AH36 -> ATIDA OMNIPHAR 07 | I36: ='Factures Geodis'!AD36 -> FR | J36: =J35 -> France | K36: ='Factures Geodis'!AP36 -> 1 | L36: ='Factures Geodis'!AQ36 -> 35.5 | M36: ST | N36: =N35 -> 0.2 | O36: =IF('Factures Geodis'!F36=0,"",'Factures Geodis'!F36) | P36: =IF('Factures Geodis'!G36=0,"",'Factures Geodis'!G36) | Q36: =IF('Factures Geodis'!H36=0,"",'Factures Geodis'!H36) | R36: =IF('Factures Geodis'!I36=0,"",'Factures Geodis'!I36) | S36: =IF('Factures Geodis'!J36=0,"",'Factures Geodis'!J36) | T36: =IF('Factures Geodis'!K36=0,"",'Factures Geodis'!K36) -> 38.61 | U36: =IF('Factures Geodis'!L36=0,"",'Factures Geodis'!L36)

Sheet Bilan Client
A3: Étiquettes de lignes | B3: Somme de Total + GO
A4: (vide) | B4: 2.61
A5: 3752 | B5: 2032.57
A6: 3888 | B6: 985
A7: 8640 | B7: 97.15
A8: 9294 | B8: 206.95
A9: 7254 | B9: 680.13
A10: 8656 | B10: 363.34
A11: 8041 | B11: 99.73
A12: 361 | B12: 144.75
A13: Total général | B13: 4612.23
