Workbook

Sheet Pays TVA
A1: AT | B1: 0.2
A2: BE | B2: 0.2
A3: CH | B3: 0
A4: DE | B4: 0.2
A5: ES | B5: 0.2
A6: GB | B6: 0
A7: GR | B7: 0.2
A8: IT | B8: 0.2
A9: LU | B9: 0.2
A10: NL | B10: 0.2
A11: PF | B11: 0

Sheet Sous-comptes
A1: 0 | B1: La Ruche
A2: 1 | B2: Ker Sun
A3: 2 | B3: Foutas
A4: 5
A5: 6

Sheet Bibliothèque transporteurs
A1: mode envoi ERP | B1: zone ERP | C1: produit chrono | D1: zone Chrono | E1: Transporteur
A2: 16 | B2: 16 | C2: 1 | E2: CHRONOPOST
A3: 2 | B3: 2 | C3: 2 | E3: CHRONOPOST
A4: 17 | B4: 17 | C4: 17 | E4: CHRONOPOST
A5: 44 | B5: 44 | C5: 44 | E5: CHRONOPOST
A6: 86 | B6: 86 | C6: 86 | E6: CHRONOPOST
A7: 16 | B7: 16 | C7: 2L | E7: CHRONOPOST
A8: 16 | B8: 16 | C8: 3Z | E8: CHRONOPOST
A9: 5X | B9: 5X | C9: 5X | E9: CHRONO_2SHOP
A10: 5Y | B10: 5Y | C10: 5Y | E10: CHRONO_2SHOP
A11: 6B | B11: 6B | C11: 6B | E11: CHRONO_2SHOP
A12: 6C | B12: 6C | C12: 6C | E12: CHRONO_2SHOP
A13: 1S | B13: 1S | C13: 1S | E13: CHRONOPOST
A14: 16 | B14: 16 | C14: 16 | E14: CHRONOPOST
A15: 5X | B15: 5X | C15: 5XK | E15: CHRONO_2SHOP_KERSUN
A16: 5Y | B16: 5Y | C16: 5YK | E16: CHRONO_2SHOP_KERSUN
A17: 6B | B17: 6B | C17: 6BK | E17: CHRONO_2SHOP_KERSUN
A18: 6C | B18: 6C | C18: 6CK | E18: CHRONO_2SHOP_KERSUN

Sheet Catégories
A1: Assurance | B1: Assurance
A2: CAP RouteCAP ROUTE | B2: Gazole
A3: Correction d'adresse | B3: Adresse
A4: Eco responsablePar | B4: Frêt
A5: ESD | B5: Gazole
A6: Frais de gestion | B6: Frais facturation
A7: Participation Eco-Responsable | B7: Frêt
A8: Supp Retour Expediteur Europe | B8: Frêt
A9: Supp Retour Expediteur Inter | B9: Frêt
A10: Supp Zone Internationale Eloignee | B10: Zones éloignées
A11: Supplement Annonce incomplète | B11: Adresse | G11: Adresse
A12: Supplement Corse | B12: Zones éloignées | G12: Gazole
A13: Supplement Corse 18h | B13: Corse | G13: Frais facturation
A14: Supplement domicile prive | B14: Zones éloignées | G14: Frêt
A15: Supplement Douane Zone C2 | B15: Droits et taxes | G15: Zones éloignées
A16: Supplement Douane Zone C4 | B16: Droits et taxes
A17: Supplement Etiquette Non Conforme | B17: Frêt | G17: Corse
A18: Supplement Forfait Expedition | B18: Frêt
A19: Supplement GT | B19: Frêt | G19: Droits et taxes
A20: Supplement Hors Norme | B20: Colis volumineux | G20: Colis volumineux
A21: Supplement Manutention | B21: Colis volumineux
A22: Supplement Retour Expediteur | B22: Frêt
A23: Supplement Retrait Bureau | B23: Zones éloignées
A24: Surcharge Carburant Aérien | B24: Gazole
A25: Surcharge Carburant Routier | B25: Gazole
A26: Surcharge Facture Papier | B26: Frais facturation
A27: Sûreté colis | B27: Frêt
A28: Traitement Réacheminement | B28: Frêt
A29: Traitement SAV complémentaire | B29: Adresse
A30: Transport | B30: Frêt
A31: Transport encompte | B31: Frêt
A32: Sûreté étendue | B32: Frêt
A33: Zones Difficiles d'accès | B33: Zones éloignées

Sheet TARIFS
C3: Tarifs LA RUCHE LOGISTIQUE
C4: C18 BAL | F4: C18 IR | I4: RELAIS
C7: OFFRE | F7: OFFRE | I7: OFFRE
C8: NAT | D8: REG/DEP | F8: NAT | G8: REG/DEP | I8: NAT | J8: REG/DEP
A10: 1er kg | C10: 6.5 | D10: =C10 | F10: 6.9 | G10: 6.9 | I10: 3.9 | J10: 3.9
A11: kg sup 1-2 | C11: 0.9 | D11: 0.9 | F11: 0.9 | G11: 0.9 | I11: 0.8 | J11: 0.8
A12: kg sup 2-3 | C12: 0.4 | D12: 0.4 | F12: 0.45 | G12: 0.45 | I12: 0.35 | J12: 0.35
A13: kg sup 3-5 | C13: 0.4 | D13: 0.4 | F13: 0.45 | G13: 0.45 | I13: 0.43 | J13: 0.43
A14: kg sup 5-10 | C14: 0.4 | D14: 0.4 | F14: 0.5 | G14: 0.5 | I14: 0.47 | J14: 0.47
A15: kg sup 10-15 | C15: 0.4 | D15: 0.4 | F15: 0.5 | G15: 0.5 | I15: 0.78 | J15: 0.78
A16: kg sup 15-20 | C16: 0.4 | D16: 0.4 | F16: 0.5 | G16: 0.5 | I16: 0.78 | J16: 0.78
A17: kg sup 20-30 | C17: 0.4 | D17: 0.4 | F17: 0.5 | G17: 0.5 | I17: 0.78 | J17: 0.78
A18: kg sup 30-999 | C18: 0.4 | D18: 0.4 | F18: 0.5 | G18: 0.5
A20: 1 | C20: =C10 | D20: =D10 | F20: =F10 | G20: =G10 | I20: =I10 | J20: =J10
A21: 2 | C21: =C20+C11 | D21: =D20+D11 | F21: =F20+F11 | G21: =G20+G11 | I21: =I20+I11 | J21: =J20+J11
A22: =+A21+1 | C22: =C21+C12 | D22: =D21+D12 | F22: =F21+F12 | G22: =G21+G12 | I22: =I21+I12 | J22: =J21+J12
A23: =+A22+1 | C23: =C22+C13 | D23: =D22+D13 | F23: =F22+F13 | G23: =G22+G13 | I23: =I22+I13 | J23: =J22+J13
A24: =+A23+1 | C24: =C23+C13 | D24: =D23+D13 | F24: =F23+F13 | G24: =G23+G13 | I24: =I23+I13 | J24: =J23+J13
A25: =+A24+1 | C25: =C24+$C$14 | D25: =D24+$D$14 | F25: =F24+$F$14 | G25: =G24+$G$14 | I25: =I24+$I$14 | J25: =J24+$J$14
A26: =+A25+1 | C26: =C25+$C$14 | D26: =D25+$D$14 | F26: =F25+$F$14 | G26: =G25+$G$14 | I26: =I25+$I$14 | J26: =J25+$J$14
A27: =+A26+1 | C27: =C26+$C$14 | D27: =D26+$D$14 | F27: =F26+$F$14 | G27: =G26+$G$14 | I27: =I26+$I$14 | J27: =J26+$J$14
A28: =+A27+1 | C28: =C27+$C$14 | D28: =D27+$D$14 | F28: =F27+$F$14 | G28: =G27+$G$14 | I28: =I27+$I$14 | J28: =J27+$J$14
A29: =+A28+1 | C29: =C28+$C$14 | D29: =D28+$D$14 | F29: =F28+$F$14 | G29: =G28+$G$14 | I29: =I28+$I$14 | J29: =J28+$J$14
A30: =+A29+1 | C30: =C29+$C$15 | D30: =D29+$D$15 | F30: =F29+$F$15 | G30: =G29+$G$15 | I30: =I29+$I$15 | J30: =J29+$J$15
A31: =+A30+1 | C31: =C30+$C$15 | D31: =D30+$D$15 | F31: =F30+$F$15 | G31: =G30+$G$15 | I31: =I30+$I$15 | J31: =J30+$J$15
A32: =+A31+1 | C32: =C31+$C$15 | D32: =D31+$D$15 | F32: =F31+$F$15 | G32: =G31+$G$15 | I32: =I31+$I$15 | J32: =J31+$J$15
A33: =+A32+1 | C33: =C32+$C$15 | D33: =D32+$D$15 | F33: =F32+$F$15 | G33: =G32+$G$15 | I33: =I32+$I$15 | J33: =J32+$J$15
A34: =+A33+1 | C34: =C33+$C$15 | D34: =D33+$D$15 | F34: =F33+$F$15 | G34: =G33+$G$15 | I34: =I33+$I$15 | J34: =J33+$J$15
A35: =+A34+1 | C35: =C34+$C$16 | D35: =D34+$D$16 | F35: =F34+$F$16 | G35: =G34+$G$16 | I35: =I34+$I$16 | J35: =J34+$J$16
A36: =+A35+1 | C36: =C35+$C$16 | D36: =D35+$D$16 | F36: =F35+$F$16 | G36: =G35+$G$16 | I36: =I35+$I$16 | J36: =J35+$J$16
A37: =+A36+1 | C37: =C36+$C$16 | D37: =D36+$D$16 | F37: =F36+$F$16 | G37: =G36+$G$16 | I37: =I36+$I$16 | J37: =J36+$J$16
A38: =+A37+1 | C38: =C37+$C$16 | D38: =D37+$D$16 | F38: =F37+$F$16 | G38: =G37+$G$16 | I38: =I37+$I$16 | J38: =J37+$J$16
A39: =+A38+1 | C39: =C38+$C$16 | D39: =D38+$D$16 | F39: =F38+$F$16 | G39: =G38+$G$16 | I39: =I38+$I$16 | J39: =J38+$J$16
A40: =+A39+1 | C40: =C39+$C$17 | D40: =D39+$D$17 | F40: =F39+$F$17 | G40: =G39+$G$17 | I40: =I39+$I$17 | J40: =J39+$J$17
A41: =+A40+1 | C41: =C40+$C$17 | D41: =D40+$D$17 | F41: =F40+$F$17 | G41: =G40+$G$17 | I41: =I40+$I$17 | J41: =J40+$J$17
A42: =+A41+1 | C42: =C41+$C$17 | D42: =D41+$D$17 | F42: =F41+$F$17 | G42: =G41+$G$17 | I42: =I41+$I$17 | J42: =J41+$J$17
A43: =+A42+1 | C43: =C42+$C$17 | D43: =D42+$D$17 | F43: =F42+$F$17 | G43: =G42+$G$17 | I43: =I42+$I$17 | J43: =J42+$J$17
A44: =+A43+1 | C44: =C43+$C$17 | D44: =D43+$D$17 | F44: =F43+$F$17 | G44: =G43+$G$17 | I44: =I43+$I$17 | J44: =J43+$J$17
A45: =+A44+1 | C45: =C44+$C$17 | D45: =D44+$D$17 | F45: =F44+$F$17 | G45: =G44+$G$17 | I45: =I44+$I$17 | J45: =J44+$J$17
A46: =+A45+1 | C46: =C45+$C$17 | D46: =D45+$D$17 | F46: =F45+$F$17 | G46: =G45+$G$17 | I46: =I45+$I$17 | J46: =J45+$J$17
A47: =+A46+1 | C47: =C46+$C$17 | D47: =D46+$D$17 | F47: =F46+$F$17 | G47: =G46+$G$17 | I47: =I46+$I$17 | J47: =J46+$J$17
A48: =+A47+1 | C48: =C47+$C$17 | D48: =D47+$D$17 | F48: =F47+$F$17 | G48: =G47+$G$17 | I48: =I47+$I$17 | J48: =J47+$J$17
A49: =+A48+1 | C49: =C48+$C$17 | D49: =D48+$D$17 | F49: =F48+$F$17 | G49: =G48+$G$17 | I49: =I48+$I$17 | J49: =J48+$J$17

Sheet cap à 5%
A1: Pour intégration dans Outil Surcharge carburant :
A3: Date indice référence : | C3: 44166
A4: Pas de chaque tranche d'indice : | C4: 0.025
A5: Surcote ou sous cote départ : | C5: 0.05
A6: Surcote ou sous cote tranche : | C6: 0.0025
A13: Pour intégration dans le contrat :
A15: type surcharge | B15: Routier
A16: type indice | B16: Pompe CNR moyenne mensuelle
A17: périodicité | B17: Mensuelle
A18: date indice référence | B18: 44166
A20: Litre de Gazole strictement supérieur à | B20: Litre de Gazole inférieur ou égal à | C20: % de surcharge applicable
A21: 0 | B21: 1.0475 | C21: 0.05
A22: 1.0475 | B22: 1.0725 | C22: 0.0525
A23: 1.0725 | B23: 1.0975 | C23: 0.055
A24: 1.0975 | B24: 1.1225 | C24: 0.0575
A25: 1.1225 | B25: 1.1475 | C25: 0.06
A26: 1.1475 | B26: 1.1725 | C26: 0.0625
A27: 1.1725 | B27: 1.1975 | C27: 0.065
A28: 1.1975 | B28: 1.2225 | C28: 0.0675
A29: 1.2225 | B29: 1.2475 | C29: 0.07
A30: 1.2475 | B30: 1.2725 | C30: 0.0725
A31: 1.2725 | B31: 1.2975 | C31: 0.075
A32: 1.2975 | B32: 1.3225 | C32: 0.0775
... A57: 1.9225 | B57: 1.9475 | C57: 0.14
A59: Par tranche supp | B59: 0.025 | C59: 0.0025

Sheet Contrôle pdf
A3: Étiquettes de lignes | B3: Somme de Montant HT | C3: pdf | D3: écarts
A4: 13617721 | B4: 4555.12 | C4: 4555.12 | D4: =B4-C4
A5: 13617722 | B5: 21.68 | C5: 21.68 | D5: =B5-C5
A6: 13617723 | B6: 6688.75 | C6: 6688.75 | D6: =B6-C6
A7: 13624019 | B7: 1487.32 | C7: 1487.32 | D7: =B7-C7
A8: 13624020 | B8: 142.46 | C8: 142.46 | D8: =B8-C8
A9: 13624021 | B9: 8246.49 | C9: 8246.49 | D9: =B9-C9
A10: (vide) | D10: =B10-C10
A11: Total général | B11: 21141.82 | C11: =SUM(C4:C10) | D11: =B11-C11
D12: =B12-C12

Sheet Zoning 2shop
A1: 6B | C1: 6C
A2: AT | B2: 1 | C2: AT | D2: 25
A3: BE | B3: 2 | C3: BE | D3: 26
A4: BG | B4: 3 | C4: BG | D4: 27
A5: CH | B5: 4 | C5: CH | D5: 28
A6: CZ | B6: 5 | C6: CZ | D6: 29
A7: DE | B7: 6 | C7: DE | D7: 30
A8: DK | B8: 7 | C8: DK | D8: 25
A9: EE | B9: 8 | C9: EE | D9: 27
A10: ES | B10: 9 | C10: ES | D10: 33
A11: FI | B11: 8 | C11: FI | D11: 27
A12: HR | B12: 8 | C12: HR | D12: 27
A13: HU | B13: 8 | C13: HU | D13: 28
... A25: SK | B25: 24 | C25: SK | D25: 25

Sheet Facture Chronopost
A1: ID Clients | B1: No Facture | C1: Sous-compte | D1: Date LT | E1: Code postal depart | F1: Code postal arrivee | G1: Pays depart | H1: Pays arrivee | I1: Ref Destinataire | J1: Ref Expediteur | K1: No Groupage tarifaire | L1: Numero LT | M1: Groupage | N1: Type prestation | O1: TVA | P1: Observations | Q1: Zone Tarifaire | R1: Poids | S1: Produit | T1: Montant HT | U1: Raison sociale | V1: Raison sociale 2 | W1: Code produit modifié | X1: Zoning 2shop | Y1: Gazole % | Z1: frêt | AA1: sureté + eco | AB1: gazole | AC1: hors gazole | AD1: Catégories | AE1: Total avec GO | AF1: Total | AG1: =SUM(AG2:AG6) | AI1: Passer la colonne S en "nombre"
B2: 13617723 | C2: 0 | D2: 46173 | K2: 0 | L2: CAPI1 | M2: X | N2: Surcharge Carburant Aérien | O2: I | P2: 0.4375 | Q2: XX | R2: 0 | S2: X | T2: 42.11 | U2: LA RUCHE LOGISTIQUE | W2: =IF(C2<>2,"",IF(S2="5X","5XK",IF(S2="5Y","5YK",IF(S2="6B","6BK",IF(S2="6C","6CK",""))))) | X2: =IF(S2="6B",_xlfn.XLOOKUP(H2,'Zoning 2shop'!A:A,'Zoning 2shop'!B:B),IF(S2="6C",_xlfn.XLOOKUP(G2,'Zoning 2shop'!C:C,'Zoning 2shop'!D:D),"")) | Y2: =AB2/Z2 | Z2: =T2 | AA2: =IF(OR(S2="6C",S2="6B",S2="5X",S2="5Y"),0.08,0.5) | AB2: =$AG$5/$AG$2*Z2 | AC2: =Z2+AA2 | AD2: =IF(COUNTIF(Catégories!A:A,N2)=0,"catégorie inconnue",LOOKUP(N2,Catégories!A:A,Catégories!B:B)) | AE2: =SUM(Z2:AB2) | AF2: Frêt | AG2: =SUM(T28:T3000)
B3: 13617723 | C3: 0 | D3: 46173 | K3: 0 | L3: CAPI2 | M3: X | N3: Surcharge Carburant Routier | O3: I | P3: 0.1425 | Q3: XX | R3: 0 | S3: X | T3: 55.57 | U3: LA RUCHE LOGISTIQUE | W3: =IF(C3<>2,"",IF(S3="5X","5XK",IF(S3="5Y","5YK",IF(S3="6B","6BK",IF(S3="6C","6CK",""))))) | X3: =IF(S3="6B",_xlfn.XLOOKUP(H3,'Zoning 2shop'!A:A,'Zoning 2shop'!B:B),IF(S3="6C",_xlfn.XLOOKUP(G3,'Zoning 2shop'!C:C,'Zoning 2shop'!D:D),"")) | Y3: =AB3/Z3 | Z3: =T3 | AA3: =IF(OR(S3="6C",S3="6B",S3="5X",S3="5Y"),0.08,0.5) | AB3: =$AG$5/$AG$2*Z3 | AC3: =Z3+AA3 | AD3: =IF(COUNTIF(Catégories!A:A,N3)=0,"catégorie inconnue",LOOKUP(N3,Catégories!A:A,Catégories!B:B)) | AE3: =SUM(Z3:AB3) | AF3: eco | AG3: =SUM(T12:T19)
B4: 13617723 | C4: 0 | D4: 46173 | K4: 0 | L4: CAPN1 | M4: X | N4: Surcharge Carburant Aérien | O4: N | P4: 0.4375 | Q4: XX | R4: 0 | S4: X | T4: 1534.86 | U4: LA RUCHE LOGISTIQUE | W4: =IF(C4<>2,"",IF(S4="5X","5XK",IF(S4="5Y","5YK",IF(S4="6B","6BK",IF(S4="6C","6CK",""))))) | X4: =IF(S4="6B",_xlfn.XLOOKUP(H4,'Zoning 2shop'!A:A,'Zoning 2shop'!B:B),IF(S4="6C",_xlfn.XLOOKUP(G4,'Zoning 2shop'!C:C,'Zoning 2shop'!D:D),"")) | Y4: =AB4/Z4 | Z4: =T4 | AA4: =IF(OR(S4="6C",S4="6B",S4="5X",S4="5Y"),0.08,0.5) | AB4: =$AG$5/$AG$2*Z4 | AC4: =Z4+AA4 | AD4: =IF(COUNTIF(Catégories!A:A,N4)=0,"catégorie inconnue",LOOKUP(N4,Catégories!A:A,Catégories!B:B)) | AE4: =SUM(Z4:AB4) | AF4: sureté | AG4: =SUM(T20:T27)
B5: 13624019 | C5: 2 | D5: 46173 | K5: 0 | L5: CAPN2 | M5: X | N5: Surcharge Carburant Routier | O5: N | P5: 0.0475 | Q5: XX | R5: 0 | S5: X | T5: 66.13 | U5: LA RUCHE LOGISTIQUE | W5: =IF(C5<>2,"",IF(S5="5X","5XK",IF(S5="5Y","5YK",IF(S5="6B","6BK",IF(S5="6C","6CK",""))))) | X5: =IF(S5="6B",_xlfn.XLOOKUP(H5,'Zoning 2shop'!A:A,'Zoning 2shop'!B:B),IF(S5="6C",_xlfn.XLOOKUP(G5,'Zoning 2shop'!C:C,'Zoning 2shop'!D:D),"")) | Y5: =AB5/Z5 | Z5: =T5 | AA5: =IF(OR(S5="6C",S5="6B",S5="5X",S5="5Y"),0.08,0.5) | AB5: =$AG$5/$AG$2*Z5 | AC5: =Z5+AA5 | AD5: =IF(COUNTIF(Catégories!A:A,N5)=0,"catégorie inconnue",LOOKUP(N5,Catégories!A:A,Catégories!B:B)) | AE5: =SUM(Z5:AB5) | AF5: Gazole | AG5: =SUM(T2:T11) | AH5: =AG5/AG2
B6: 13624020 | C6: 0 | D6: 46173 | K6: 0 | L6: CAPN2 | M6: X | N6: Surcharge Carburant Routier | O6: N | P6: 0.0475 | Q6: XX | R6: 0 | S6: X | T6: 6.43 | U6: LA RUCHE LOGISTIQUE | W6: =IF(C6<>2,"",IF(S6="5X","5XK",IF(S6="5Y","5YK",IF(S6="6B","6BK",IF(S6="6C","6CK",""))))) | X6: =IF(S6="6B",_xlfn.XLOOKUP(H6,'Zoning 2shop'!A:A,'Zoning 2shop'!B:B),IF(S6="6C",_xlfn.XLOOKUP(G6,'Zoning 2shop'!C:C,'Zoning 2shop'!D:D),"")) | Y6: =AB6/Z6 | Z6: =T6 | AA6: =IF(OR(S6="6C",S6="6B",S6="5X",S6="5Y"),0.08,0.5) | AB6: =$AG$5/$AG$2*Z6 | AC6: =Z6+AA6 | AD6: =IF(COUNTIF(Catégories!A:A,N6)=0,"catégorie inconnue",LOOKUP(N6,Catégories!A:A,Catégories!B:B)) | AE6: =SUM(Z6:AB6) | AF6: Gestion
B7: 13624021 | C7: 2 | D7: 46173 | K7: 0 | L7: CAPN2 | M7: X | N7: Surcharge Carburant Routier | O7: N | P7: 0.0475 | Q7: XX | R7: 0 | S7: X | T7: 371.42 | U7: LA RUCHE LOGISTIQUE | W7: =IF(C7<>2,"",IF(S7="5X","5XK",IF(S7="5Y","5YK",IF(S7="6B","6BK",IF(S7="6C","6CK",""))))) | X7: =IF(S7="6B",_xlfn.XLOOKUP(H7,'Zoning 2shop'!A:A,'Zoning 2shop'!B:B),IF(S7="6C",_xlfn.XLOOKUP(G7,'Zoning 2shop'!C:C,'Zoning 2shop'!D:D),"")) | Y7: =AB7/Z7 | Z7: =T7 | AA7: =IF(OR(S7="6C",S7="6B",S7="5X",S7="5Y"),0.08,0.5) | AB7: =$AG$5/$AG$2*Z7 | AC7: =Z7+AA7 | AD7: =IF(COUNTIF(Catégories!A:A,N7)=0,"catégorie inconnue",LOOKUP(N7,Catégories!A:A,Catégories!B:B)) | AE7: =SUM(Z7:AB7)
B8: 13617721 | C8: 0 | D8: 46173 | K8: 0 | L8: CAPN2 | M8: X | N8: Surcharge Carburant Routier | O8: N | P8: 0.1425 | Q8: XX | R8: 0 | S8: X | T8: 560.45 | U8: LA RUCHE LOGISTIQUE | W8: =IF(C8<>2,"",IF(S8="5X","5XK",IF(S8="5Y","5YK",IF(S8="6B","6BK",IF(S8="6C","6CK",""))))) | X8: =IF(S8="6B",_xlfn.XLOOKUP(H8,'Zoning 2shop'!A:A,'Zoning 2shop'!B:B),IF(S8="6C",_xlfn.XLOOKUP(G8,'Zoning 2shop'!C:C,'Zoning 2shop'!D:D),"")) | Y8: =AB8/Z8 | Z8: =T8 | AA8: =IF(OR(S8="6C",S8="6B",S8="5X",S8="5Y"),0.08,0.5) | AB8: =$AG$5/$AG$2*Z8 | AC8: =Z8+AA8 | AD8: =IF(COUNTIF(Catégories!A:A,N8)=0,"catégorie inconnue",LOOKUP(N8,Catégories!A:A,Catégories!B:B)) | AE8: =SUM(Z8:AB8) | AF8: Gazole réel | AH8: 0.2315 | AI8: routier
B9: 13617722 | C9: 2 | D9: 46173 | K9: 0 | L9: CAPN2 | M9: X | N9: Surcharge Carburant Routier | O9: N | P9: 0.1425 | Q9: XX | R9: 0 | S9: X | T9: 2.68 | U9: LA RUCHE LOGISTIQUE | W9: =IF(C9<>2,"",IF(S9="5X","5XK",IF(S9="5Y","5YK",IF(S9="6B","6BK",IF(S9="6C","6CK",""))))) | X9: =IF(S9="6B",_xlfn.XLOOKUP(H9,'Zoning 2shop'!A:A,'Zoning 2shop'!B:B),IF(S9="6C",_xlfn.XLOOKUP(G9,'Zoning 2shop'!C:C,'Zoning 2shop'!D:D),"")) | Y9: =AB9/Z9 | Z9: =T9 | AA9: =IF(OR(S9="6C",S9="6B",S9="5X",S9="5Y"),0.08,0.5) | AB9: =$AG$5/$AG$2*Z9 | AC9: =Z9+AA9 | AD9: =IF(COUNTIF(Catégories!A:A,N9)=0,"catégorie inconnue",LOOKUP(N9,Catégories!A:A,Catégories!B:B)) | AE9: =SUM(Z9:AB9) | AF9: (avant remise) | AH9: 0.4375 | AI9: aérien
B10: 13617723 | C10: 0 | D10: 46173 | K10: 0 | L10: CAPN2 | M10: X | N10: Surcharge Carburant Routier | O10: N | P10: 0.1425 | Q10: XX | R10: 0 | S10: X | T10: 18.56 | U10: LA RUCHE LOGISTIQUE | W10: =IF(C10<>2,"",IF(S10="5X","5XK",IF(S10="5Y","5YK",IF(S10="6B","6BK",IF(S10="6C","6CK",""))))) | X10: =IF(S10="6B",_xlfn.XLOOKUP(H10,'Zoning 2shop'!A:A,'Zoning 2shop'!B:B),IF(S10="6C",_xlfn.XLOOKUP(G10,'Zoning 2shop'!C:C,'Zoning 2shop'!D:D),"")) | Y10: =AB10/Z10 | Z10: =T10 | AA10: =IF(OR(S10="6C",S10="6B",S10="5X",S10="5Y"),0.08,0.5) | AB10: =$AG$5/$AG$2*Z10 | AC10: =Z10+AA10 | AD10: =IF(COUNTIF(Catégories!A:A,N10)=0,"catégorie inconnue",LOOKUP(N10,Catégories!A:A,Catégories!B:B)) | AE10: =SUM(Z10:AB10)
B11: 13617723 | C11: 0 | D11: 46173 | K11: 0 | L11: CAPO1 | M11: X | N11: Surcharge Carburant Aérien | O11: O | P11: 0.4375 | Q11: XX | R11: 0 | S11: X | T11: 18.19 | U11: LA RUCHE LOGISTIQUE | W11: =IF(C11<>2,"",IF(S11="5X","5XK",IF(S11="5Y","5YK",IF(S11="6B","6BK",IF(S11="6C","6CK",""))))) | X11: =IF(S11="6B",_xlfn.XLOOKUP(H11,'Zoning 2shop'!A:A,'Zoning 2shop'!B:B),IF(S11="6C",_xlfn.XLOOKUP(G11,'Zoning 2shop'!C:C,'Zoning 2shop'!D:D),"")) | Y11: =AB11/Z11 | Z11: =T11 | AA11: =IF(OR(S11="6C",S11="6B",S11="5X",S11="5Y"),0.08,0.5) | AB11: =$AG$5/$AG$2*Z11 | AC11: =Z11+AA11 | AD11: =IF(COUNTIF(Catégories!A:A,N11)=0,"catégorie inconnue",LOOKUP(N11,Catégories!A:A,Catégories!B:B)) | AE11: =SUM(Z11:AB11)
B12: 13617723 | C12: 0 | D12: 46173 | K12: 0 | L12: ECORI | M12: X | N12: Participation Eco-Responsable | O12: I | Q12: XX | R12: 0 | S12: X | T12: 3.7 | U12: LA RUCHE LOGISTIQUE | W12: =IF(C12<>2,"",IF(S12="5X","5XK",IF(S12="5Y","5YK",IF(S12="6B","6BK",IF(S12="6C","6CK",""))))) | X12: =IF(S12="6B",_xlfn.XLOOKUP(H12,'Zoning 2shop'!A:A,'Zoning 2shop'!B:B),IF(S12="6C",_xlfn.XLOOKUP(G12,'Zoning 2shop'!C:C,'Zoning 2shop'!D:D),"")) | Y12: =AB12/Z12 | Z12: =T12 | AA12: =IF(OR(S12="6C",S12="6B",S12="5X",S12="5Y"),0.08,0.5) | AB12: =$AG$5/$AG$2*Z12 | AC12: =Z12+AA12 | AD12: =IF(COUNTIF(Catégories!A:A,N12)=0,"catégorie inconnue",LOOKUP(N12,Catégories!A:A,Catégories!B:B)) | AE12: =SUM(Z12:AB12)
B13: 13624019 | C13: 2 | D13: 46173 | K13: 0 | L13: ECORN | M13: X | N13: Participation Eco-Responsable | O13: N | Q13: XX | R13: 0 | S13: X | T13: 12.99 | U13: LA RUCHE LOGISTIQUE | W13: =IF(C13<>2,"",IF(S13="5X","5XK",IF(S13="5Y","5YK",IF(S13="6B","6BK",IF(S13="6C","6CK",""))))) | X13: =IF(S13="6B",_xlfn.XLOOKUP(H13,'Zoning 2shop'!A:A,'Zoning 2shop'!B:B),IF(S13="6C",_xlfn.XLOOKUP(G13,'Zoning 2shop'!C:C,'Zoning 2shop'!D:D),"")) | Y13: =AB13/Z13 | Z13: =T13 | AA13: =IF(OR(S13="6C",S13="6B",S13="5X",S13="5Y"),0.08,0.5) | AB13: =$AG$5/$AG$2*Z13 | AC13: =Z13+AA13 | AD13: =IF(COUNTIF(Catégories!A:A,N13)=0,"catégorie inconnue",LOOKUP(N13,Catégories!A:A,Catégories!B:B)) | AE13: =SUM(Z13:AB13)
B14: 13624020 | C14: 0 | D14: 46173 | K14: 0 | L14: ECORN | M14: X | N14: Participation Eco-Responsable | O14: N | Q14: XX | R14: 0 | S14: X | T14: 0.63 | U14: LA RUCHE LOGISTIQUE | W14: =IF(C14<>2,"",IF(S14="5X","5XK",IF(S14="5Y","5YK",IF(S14="6B","6BK",IF(S14="6C","6CK",""))))) | X14: =IF(S14="6B",_xlfn.XLOOKUP(H14,'Zoning 2shop'!A:A,'Zoning 2shop'!B:B),IF(S14="6C",_xlfn.XLOOKUP(G14,'Zoning 2shop'!C:C,'Zoning 2shop'!D:D),"")) | Y14: =AB14/Z14 | Z14: =T14 | AA14: =IF(OR(S14="6C",S14="6B",S14="5X",S14="5Y"),0.08,0.5) | AB14: =$AG$5/$AG$2*Z14 | AC14: =Z14+AA14 | AD14: =IF(COUNTIF(Catégories!A:A,N14)=0,"catégorie inconnue",LOOKUP(N14,Catégories!A:A,Catégories!B:B)) | AE14: =SUM(Z14:AB14)
B15: 13624021 | C15: 2 | D15: 46173 | K15: 0 | L15: ECORN | M15: X | N15: Participation Eco-Responsable | O15: N | Q15: XX | R15: 0 | S15: X | T15: 27.78 | U15: LA RUCHE LOGISTIQUE | W15: =IF(C15<>2,"",IF(S15="5X","5XK",IF(S15="5Y","5YK",IF(S15="6B","6BK",IF(S15="6C","6CK",""))))) | X15: =IF(S15="6B",_xlfn.XLOOKUP(H15,'Zoning 2shop'!A:A,'Zoning 2shop'!B:B),IF(S15="6C",_xlfn.XLOOKUP(G15,'Zoning 2shop'!C:C,'Zoning 2shop'!D:D),"")) | Y15: =AB15/Z15 | Z15: =T15 | AA15: =IF(OR(S15="6C",S15="6B",S15="5X",S15="5Y"),0.08,0.5) | AB15: =$AG$5/$AG$2*Z15 | AC15: =Z15+AA15 | AD15: =IF(COUNTIF(Catégories!A:A,N15)=0,"catégorie inconnue",LOOKUP(N15,Catégories!A:A,Catégories!B:B)) | AE15: =SUM(Z15:AB15)
B16: 13617721 | C16: 0 | D16: 46173 | K16: 0 | L16: ECORN | M16: X | N16: Participation Eco-Responsable | O16: N | Q16: XX | R16: 0 | S16: X | T16: 53.7 | U16: LA RUCHE LOGISTIQUE | W16: =IF(C16<>2,"",IF(S16="5X","5XK",IF(S16="5Y","5YK",IF(S16="6B","6BK",IF(S16="6C","6CK",""))))) | X16: =IF(S16="6B",_xlfn.XLOOKUP(H16,'Zoning 2shop'!A:A,'Zoning 2shop'!B:B),IF(S16="6C",_xlfn.XLOOKUP(G16,'Zoning 2shop'!C:C,'Zoning 2shop'!D:D),"")) | Y16: =AB16/Z16 | Z16: =T16 | AA16: =IF(OR(S16="6C",S16="6B",S16="5X",S16="5Y"),0.08,0.5) | AB16: =$AG$5/$AG$2*Z16 | AC16: =Z16+AA16 | AD16: =IF(COUNTIF(Catégories!A:A,N16)=0,"catégorie inconnue",LOOKUP(N16,Catégories!A:A,Catégories!B:B)) | AE16: =SUM(Z16:AB16)
B17: 13617722 | C17: 2 | D17: 46173 | K17: 0 | L17: ECORN | M17: X | N17: Participation Eco-Responsable | O17: N | Q17: XX | R17: 0 | S17: X | T17: 0.2 | U17: LA RUCHE LOGISTIQUE | W17: =IF(C17<>2,"",IF(S17="5X","5XK",IF(S17="5Y","5YK",IF(S17="6B","6BK",IF(S17="6C","6CK",""))))) | X17: =IF(S17="6B",_xlfn.XLOOKUP(H17,'Zoning 2shop'!A:A,'Zoning 2shop'!B:B),IF(S17="6C",_xlfn.XLOOKUP(G17,'Zoning 2shop'!C:C,'Zoning 2shop'!D:D),"")) | Y17: =AB17/Z17 | Z17: =T17 | AA17: =IF(OR(S17="6C",S17="6B",S17="5X",S17="5Y"),0.08,0.5) | AB17: =$AG$5/$AG$2*Z17 | AC17: =Z17+AA17 | AD17: =IF(COUNTIF(Catégories!A:A,N17)=0,"catégorie inconnue",LOOKUP(N17,Catégories!A:A,Catégories!B:B)) | AE17: =SUM(Z17:AB17)
B18: 13617723 | C18: 0 | D18: 46173 | K18: 0 | L18: ECORN | M18: X | N18: Participation Eco-Responsable | O18: N | Q18: XX | R18: 0 | S18: X | T18: 23.4 | U18: LA RUCHE LOGISTIQUE | W18: =IF(C18<>2,"",IF(S18="5X","5XK",IF(S18="5Y","5YK",IF(S18="6B","6BK",IF(S18="6C","6CK",""))))) | X18: =IF(S18="6B",_xlfn.XLOOKUP(H18,'Zoning 2shop'!A:A,'Zoning 2shop'!B:B),IF(S18="6C",_xlfn.XLOOKUP(G18,'Zoning 2shop'!C:C,'Zoning 2shop'!D:D),"")) | Y18: =AB18/Z18 | Z18: =T18 | AA18: =IF(OR(S18="6C",S18="6B",S18="5X",S18="5Y"),0.08,0.5) | AB18: =$AG$5/$AG$2*Z18 | AC18: =Z18+AA18 | AD18: =IF(COUNTIF(Catégories!A:A,N18)=0,"catégorie inconnue",LOOKUP(N18,Catégories!A:A,Catégories!B:B)) | AE18: =SUM(Z18:AB18)
B19: 13617723 | C19: 0 | D19: 46173 | K19: 0 | L19: ECORO | M19: X | N19: Participation Eco-Responsable | O19: O | Q19: XX | R19: 0 | S19: X | T19: 0.1 | U19: LA RUCHE LOGISTIQUE | W19: =IF(C19<>2,"",IF(S19="5X","5XK",IF(S19="5Y","5YK",IF(S19="6B","6BK",IF(S19="6C","6CK",""))))) | X19: =IF(S19="6B",_xlfn.XLOOKUP(H19,'Zoning 2shop'!A:A,'Zoning 2shop'!B:B),IF(S19="6C",_xlfn.XLOOKUP(G19,'Zoning 2shop'!C:C,'Zoning 2shop'!D:D),"")) | Y19: =AB19/Z19 | Z19: =T19 | AA19: =IF(OR(S19="6C",S19="6B",S19="5X",S19="5Y"),0.08,0.5) | AB19: =$AG$5/$AG$2*Z19 | AC19: =Z19+AA19 | AD19: =IF(COUNTIF(Catégories!A:A,N19)=0,"catégorie inconnue",LOOKUP(N19,Catégories!A:A,Catégories!B:B)) | AE19: =SUM(Z19:AB19)
B20: 13617723 | C20: 0 | D20: 46173 | K20: 0 | L20: SURTI | M20: X | N20: Sûreté colis | O20: I | Q20: XX | R20: 0 | S20: X | T20: 14.8 | U20: LA RUCHE LOGISTIQUE | W20: =IF(C20<>2,"",IF(S20="5X","5XK",IF(S20="5Y","5YK",IF(S20="6B","6BK",IF(S20="6C","6CK",""))))) | X20: =IF(S20="6B",_xlfn.XLOOKUP(H20,'Zoning 2shop'!A:A,'Zoning 2shop'!B:B),IF(S20="6C",_xlfn.XLOOKUP(G20,'Zoning 2shop'!C:C,'Zoning 2shop'!D:D),"")) | Y20: =AB20/Z20 | Z20: =T20 | AA20: =IF(OR(S20="6C",S20="6B",S20="5X",S20="5Y"),0.08,0.5) | AB20: =$AG$5/$AG$2*Z20 | AC20: =Z20+AA20 | AD20: =IF(COUNTIF(Catégories!A:A,N20)=0,"catégorie inconnue",LOOKUP(N20,Catégories!A:A,Catégories!B:B)) | AE20: =SUM(Z20:AB20)
B21: 13624019 | C21: 2 | D21: 46173 | K21: 0 | L21: SURTN | M21: X | N21: Sûreté colis | O21: N | Q21: XX | R21: 0 | S21: X | T21: 21.65 | U21: LA RUCHE LOGISTIQUE | W21: =IF(C21<>2,"",IF(S21="5X","5XK",IF(S21="5Y","5YK",IF(S21="6B","6BK",IF(S21="6C","6CK",""))))) | X21: =IF(S21="6B",_xlfn.XLOOKUP(H21,'Zoning 2shop'!A:A,'Zoning 2shop'!B:B),IF(S21="6C",_xlfn.XLOOKUP(G21,'Zoning 2shop'!C:C,'Zoning 2shop'!D:D),"")) | Y21: =AB21/Z21 | Z21: =T21 | AA21: =IF(OR(S21="6C",S21="6B",S21="5X",S21="5Y"),0.08,0.5) | AB21: =$AG$5/$AG$2*Z21 | AC21: =Z21+AA21 | AD21: =IF(COUNTIF(Catégories!A:A,N21)=0,"catégorie inconnue",LOOKUP(N21,Catégories!A:A,Catégories!B:B)) | AE21: =SUM(Z21:AB21)
B22: 13624020 | C22: 0 | D22: 46173 | K22: 0 | L22: SURTN | M22: X | N22: Sûreté colis | O22: N | Q22: XX | R22: 0 | S22: X | T22: 1.05 | U22: LA RUCHE LOGISTIQUE | W22: =IF(C22<>2,"",IF(S22="5X","5XK",IF(S22="5Y","5YK",IF(S22="6B","6BK",IF(S22="6C","6CK",""))))) | X22: =IF(S22="6B",_xlfn.XLOOKUP(H22,'Zoning 2shop'!A:A,'Zoning 2shop'!B:B),IF(S22="6C",_xlfn.XLOOKUP(G22,'Zoning 2shop'!C:C,'Zoning 2shop'!D:D),"")) | Y22: =AB22/Z22 | Z22: =T22 | AA22: =IF(OR(S22="6C",S22="6B",S22="5X",S22="5Y"),0.08,0.5) | AB22: =$AG$5/$AG$2*Z22 | AC22: =Z22+AA22 | AD22: =IF(COUNTIF(Catégories!A:A,N22)=0,"catégorie inconnue",LOOKUP(N22,Catégories!A:A,Catégories!B:B)) | AE22: =SUM(Z22:AB22)
B23: 13624021 | C23: 2 | D23: 46173 | K23: 0 | L23: SURTN | M23: X | N23: Sûreté colis | O23: N | Q23: XX | R23: 0 | S23: X | T23: 46.3 | U23: LA RUCHE LOGISTIQUE | W23: =IF(C23<>2,"",IF(S23="5X","5XK",IF(S23="5Y","5YK",IF(S23="6B","6BK",IF(S23="6C","6CK",""))))) | X23: =IF(S23="6B",_xlfn.XLOOKUP(H23,'Zoning 2shop'!A:A,'Zoning 2shop'!B:B),IF(S23="6C",_xlfn.XLOOKUP(G23,'Zoning 2shop'!C:C,'Zoning 2shop'!D:D),"")) | Y23: =AB23/Z23 | Z23: =T23 | AA23: =IF(OR(S23="6C",S23="6B",S23="5X",S23="5Y"),0.08,0.5) | AB23: =$AG$5/$AG$2*Z23 | AC23: =Z23+AA23 | AD23: =IF(COUNTIF(Catégories!A:A,N23)=0,"catégorie inconnue",LOOKUP(N23,Catégories!A:A,Catégories!B:B)) | AE23: =SUM(Z23:AB23)
... B27: 13617723 | C27: 0 | D27: 46173 | K27: 0 | L27: SURTO | M27: X | N27: Sûreté colis | O27: O | Q27: XX | R27: 0 | S27: X | T27: 0.4 | U27: LA RUCHE LOGISTIQUE | W27: =IF(C27<>2,"",IF(S27="5X","5XK",IF(S27="5Y","5YK",IF(S27="6B","6BK",IF(S27="6C","6CK",""))))) | X27: =IF(S27="6B",_xlfn.XLOOKUP(H27,'Zoning 2shop'!A:A,'Zoning 2shop'!B:B),IF(S27="6C",_xlfn.XLOOKUP(G27,'Zoning 2shop'!C:C,'Zoning 2shop'!D:D),"")) | Y27: =AB27/Z27 | Z27: =T27 | AA27: =IF(OR(S27="6C",S27="6B",S27="5X",S27="5Y"),0.08,0.5) | AB27: =$AG$5/$AG$2*Z27 | AC27: =Z27+AA27 | AD27: =IF(COUNTIF(Catégories!A:A,N27)=0,"catégorie inconnue",LOOKUP(N27,Catégories!A:A,Catégories!B:B)) | AE27: =SUM(Z27:AB27)
B28: 13617723 | C28: 0 | D28: 46146 | E28: 21320 | F28: 13088 | G28: FR | H28: DE | I28: Martinez Cruz Daniela | J28: Laruche | K28: 999999 | L28: XF142220606FR | M28: N | N28: Transport | O28: N | P28: S | Q28: Z1 | R28: 0.783 | S28: 17 | T28: 9.94 | U28: LA RUCHE LOGISTIQUE | W28: =IF(C28<>2,"",IF(S28="5X","5XK",IF(S28="5Y","5YK",IF(S28="6B","6BK",IF(S28="6C","6CK",""))))) | X28: =IF(S28="6B",_xlfn.XLOOKUP(H28,'Zoning 2shop'!A:A,'Zoning 2shop'!B:B),IF(S28="6C",_xlfn.XLOOKUP(G28,'Zoning 2shop'!C:C,'Zoning 2shop'!D:D),"")) | Y28: =AB28/Z28 | Z28: =T28 | AA28: =IF(OR(S28="6C",S28="6B",S28="5X",S28="5Y"),0.08,0.5) | AB28: =$AG$5/$AG$2*Z28 | AC28: =Z28+AA28 | AD28: =IF(COUNTIF(Catégories!A:A,N28)=0,"catégorie inconnue",LOOKUP(N28,Catégories!A:A,Catégories!B:B)) | AE28: =SUM(Z28:AB28)
B29: 13617723 | C29: 0 | D29: 46146 | E29: 21320 | F29: 14542 | G29: FR | H29: DE | I29: Fettig Herbert | J29: Laruche | K29: 999999 | L29: XF142220708FR | M29: N | N29: Transport | O29: N | P29: S | Q29: Z1 | R29: 4.532 | S29: 17 | T29: 19.47 | U29: LA RUCHE LOGISTIQUE | W29: =IF(C29<>2,"",IF(S29="5X","5XK",IF(S29="5Y","5YK",IF(S29="6B","6BK",IF(S29="6C","6CK",""))))) | X29: =IF(S29="6B",_xlfn.XLOOKUP(H29,'Zoning 2shop'!A:A,'Zoning 2shop'!B:B),IF(S29="6C",_xlfn.XLOOKUP(G29,'Zoning 2shop'!C:C,'Zoning 2shop'!D:D),"")) | Y29: =AB29/Z29 | Z29: =T29 | AA29: =IF(OR(S29="6C",S29="6B",S29="5X",S29="5Y"),0.08,0.5) | AB29: =$AG$5/$AG$2*Z29 | AC29: =Z29+AA29 | AD29: =IF(COUNTIF(Catégories!A:A,N29)=0,"catégorie inconnue",LOOKUP(N29,Catégories!A:A,Catégories!B:B)) | AE29: =SUM(Z29:AB29)
B30: 13617723 | C30: 0 | D30: 46146 | E30: 21320 | F30: 42651 | G30: FR | H30: DE | I30: Michallek Lars | J30: Laruche | K30: 999999 | L30: XF142220932FR | M30: N | N30: Transport | O30: N | P30: S | Q30: Z1 | R30: 0.748 | S30: 17 | T30: 9.94 | U30: LA RUCHE LOGISTIQUE | W30: =IF(C30<>2,"",IF(S30="5X","5XK",IF(S30="5Y","5YK",IF(S30="6B","6BK",IF(S30="6C","6CK",""))))) | X30: =IF(S30="6B",_xlfn.XLOOKUP(H30,'Zoning 2shop'!A:A,'Zoning 2shop'!B:B),IF(S30="6C",_xlfn.XLOOKUP(G30,'Zoning 2shop'!C:C,'Zoning 2shop'!D:D),"")) | Y30: =AB30/Z30 | Z30: =T30 | AA30: =IF(OR(S30="6C",S30="6B",S30="5X",S30="5Y"),0.08,0.5) | AB30: =$AG$5/$AG$2*Z30 | AC30: =Z30+AA30 | AD30: =IF(COUNTIF(Catégories!A:A,N30)=0,"catégorie inconnue",LOOKUP(N30,Catégories!A:A,Catégories!B:B)) | AE30: =SUM(Z30:AB30)
B31: 13617723 | C31: 0 | D31: 46146 | E31: 21320 | F31: 88279 | G31: FR | H31: DE | I31: Simon Dr Karl | J31: Laruche | K31: 999999 | L31: XF142221116FR | M31: N | N31: Transport | O31: N | P31: S | Q31: Z1 | R31: 0.1 | S31: 17 | T31: 7.86 | U31: LA RUCHE LOGISTIQUE | W31: =IF(C31<>2,"",IF(S31="5X","5XK",IF(S31="5Y","5YK",IF(S31="6B","6BK",IF(S31="6C","6CK",""))))) | X31: =IF(S31="6B",_xlfn.XLOOKUP(H31,'Zoning 2shop'!A:A,'Zoning 2shop'!B:B),IF(S31="6C",_xlfn.XLOOKUP(G31,'Zoning 2shop'!C:C,'Zoning 2shop'!D:D),"")) | Y31: =AB31/Z31 | Z31: =T31 | AA31: =IF(OR(S31="6C",S31="6B",S31="5X",S31="5Y"),0.08,0.5) | AB31: =$AG$5/$AG$2*Z31 | AC31: =Z31+AA31 | AD31: =IF(COUNTIF(Catégories!A:A,N31)=0,"catégorie inconnue",LOOKUP(N31,Catégories!A:A,Catégories!B:B)) | AE31: =SUM(Z31:AB31)
B32: 13617723 | C32: 0 | D32: 46146 | E32: 21320 | F32: 1028 | G32: FR | H32: HU | I32: Moulenes Katalin | J32: Laruche | K32: 999999 | L32: XF142221147FR | M32: N | N32: Transport | O32: N | P32: S | Q32: Z3 | R32: 0.748 | S32: 17 | T32: 13.35 | U32: LA RUCHE LOGISTIQUE | W32: =IF(C32<>2,"",IF(S32="5X","5XK",IF(S32="5Y","5YK",IF(S32="6B","6BK",IF(S32="6C","6CK",""))))) | X32: =IF(S32="6B",_xlfn.XLOOKUP(H32,'Zoning 2shop'!A:A,'Zoning 2shop'!B:B),IF(S32="6C",_xlfn.XLOOKUP(G32,'Zoning 2shop'!C:C,'Zoning 2shop'!D:D),"")) | Y32: =AB32/Z32 | Z32: =T32 | AA32: =IF(OR(S32="6C",S32="6B",S32="5X",S32="5Y"),0.08,0.5) | AB32: =$AG$5/$AG$2*Z32 | AC32: =Z32+AA32 | AD32: =IF(COUNTIF(Catégories!A:A,N32)=0,"catégorie inconnue",LOOKUP(N32,Catégories!A:A,Catégories!B:B)) | AE32: =SUM(Z32:AB32)
B33: 13617723 | C33: 0 | D33: 46146 | E33: 21320 | F33: 17031 | G33: FR | H33: IT | I33: CARTA GIOBERTI Cinzia | J33: Laruche | K33: 999999 | L33: XF142221677FR | M33: N | N33: Transport | O33: N | P33: S | Q33: Z2 | R33: 4.427 | S33: 17 | T33: 18.34 | U33: LA RUCHE LOGISTIQUE | W33: =IF(C33<>2,"",IF(S33="5X","5XK",IF(S33="5Y","5YK",IF(S33="6B","6BK",IF(S33="6C","6CK",""))))) | X33: =IF(S33="6B",_xlfn.XLOOKUP(H33,'Zoning 2shop'!A:A,'Zoning 2shop'!B:B),IF(S33="6C",_xlfn.XLOOKUP(G33,'Zoning 2shop'!C:C,'Zoning 2shop'!D:D),"")) | Y33: =AB33/Z33 | Z33: =T33 | AA33: =IF(OR(S33="6C",S33="6B",S33="5X",S33="5Y"),0.08,0.5) | AB33: =$AG$5/$AG$2*Z33 | AC33: =Z33+AA33 | AD33: =IF(COUNTIF(Catégories!A:A,N33)=0,"catégorie inconnue",LOOKUP(N33,Catégories!A:A,Catégories!B:B)) | AE33: =SUM(Z33:AB33)
B34: 13617723 | C34: 0 | D34: 46146 | E34: 21320 | F34: 97348 | G34: FR | H34: DE | I34: Seel Timea | J34: Laruche | K34: 999999 | L34: XF142221779FR | M34: N | N34: Transport | O34: N | P34: S | Q34: Z1 | R34: 5.773 | S34: 17 | T34: 21.83 | U34: LA RUCHE LOGISTIQUE | W34: =IF(C34<>2,"",IF(S34="5X","5XK",IF(S34="5Y","5YK",IF(S34="6B","6BK",IF(S34="6C","6CK",""))))) | X34: =IF(S34="6B",_xlfn.XLOOKUP(H34,'Zoning 2shop'!A:A,'Zoning 2shop'!B:B),IF(S34="6C",_xlfn.XLOOKUP(G34,'Zoning 2shop'!C:C,'Zoning 2shop'!D:D),"")) | Y34: =AB34/Z34 | Z34: =T34 | AA34: =IF(OR(S34="6C",S34="6B",S34="5X",S34="5Y"),0.08,0.5) | AB34: =$AG$5/$AG$2*Z34 | AC34: =Z34+AA34 | AD34: =IF(COUNTIF(Catégories!A:A,N34)=0,"catégorie inconnue",LOOKUP(N34,Catégories!A:A,Catégories!B:B)) | AE34: =SUM(Z34:AB34)
B35: 13617723 | C35: 0 | D35: 46146 | E35: 21320 | F35: 28280 | G35: FR | H35: ES | I35: Beltran Carmen | J35: Laruche | K35: 999999 | L35: XF142224761FR | M35: N | N35: Transport | O35: N | P35: S | Q35: Z2 | R35: 0.748 | S35: 17 | T35: 9.94 | U35: LA RUCHE LOGISTIQUE | W35: =IF(C35<>2,"",IF(S35="5X","5XK",IF(S35="5Y","5YK",IF(S35="6B","6BK",IF(S35="6C","6CK",""))))) | X35: =IF(S35="6B",_xlfn.XLOOKUP(H35,'Zoning 2shop'!A:A,'Zoning 2shop'!B:B),IF(S35="6C",_xlfn.XLOOKUP(G35,'Zoning 2shop'!C:C,'Zoning 2shop'!D:D),"")) | Y35: =AB35/Z35 | Z35: =T35 | AA35: =IF(OR(S35="6C",S35="6B",S35="5X",S35="5Y"),0.08,0.5) | AB35: =$AG$5/$AG$2*Z35 | AC35: =Z35+AA35 | AD35: =IF(COUNTIF(Catégories!A:A,N35)=0,"catégorie inconnue",LOOKUP(N35,Catégories!A:A,Catégories!B:B)) | AE35: =SUM(Z35:AB35)
B36: 13617723 | C36: 0 | D36: 46146 | E36: 21320 | F36: 94065 | G36: FR | H36: DE | I36: Lutje Maximilian | J36: Laruche | K36: 999999 | L36: XF142225206FR | M36: N | N36: Transport | O36: N | P36: S | Q36: Z1 | R36: 5.76 | S36: 17 | T36: 21.83 | U36: LA RUCHE LOGISTIQUE | W36: =IF(C36<>2,"",IF(S36="5X","5XK",IF(S36="5Y","5YK",IF(S36="6B","6BK",IF(S36="6C","6CK",""))))) | X36: =IF(S36="6B",_xlfn.XLOOKUP(H36,'Zoning 2shop'!A:A,'Zoning 2shop'!B:B),IF(S36="6C",_xlfn.XLOOKUP(G36,'Zoning 2shop'!C:C,'Zoning 2shop'!D:D),"")) | Y36: =AB36/Z36 | Z36: =T36 | AA36: =IF(OR(S36="6C",S36="6B",S36="5X",S36="5Y"),0.08,0.5) | AB36: =$AG$5/$AG$2*Z36 | AC36: =Z36+AA36 | AD36: =IF(COUNTIF(Catégories!A:A,N36)=0,"catégorie inconnue",LOOKUP(N36,Catégories!A:A,Catégories!B:B)) | AE36: =SUM(Z36:AB36)
B37: 13617723 | C37: 0 | D37: 46146 | E37: 21320 | F37: 36329 | G37: FR | H37: DE | I37: Marek Nicole | J37: Laruche | K37: 999999 | L37: XF142225223FR | M37: N | N37: Transport | O37: N | P37: S | Q37: Z1 | R37: 4.266 | S37: 17 | T37: 18.34 | U37: LA RUCHE LOGISTIQUE | W37: =IF(C37<>2,"",IF(S37="5X","5XK",IF(S37="5Y","5YK",IF(S37="6B","6BK",IF(S37="6C","6CK",""))))) | X37: =IF(S37="6B",_xlfn.XLOOKUP(H37,'Zoning 2shop'!A:A,'Zoning 2shop'!B:B),IF(S37="6C",_xlfn.XLOOKUP(G37,'Zoning 2shop'!C:C,'Zoning 2shop'!D:D),"")) | Y37: =AB37/Z37 | Z37: =T37 | AA37: =IF(OR(S37="6C",S37="6B",S37="5X",S37="5Y"),0.08,0.5) | AB37: =$AG$5/$AG$2*Z37 | AC37: =Z37+AA37 | AD37: =IF(COUNTIF(Catégories!A:A,N37)=0,"catégorie inconnue",LOOKUP(N37,Catégories!A:A,Catégories!B:B)) | AE37: =SUM(Z37:AB37)
B38: 13617723 | C38: 0 | D38: 46146 | E38: 21320 | F38: 57074 | G38: FR | H38: DE | I38: Serra Daniela | J38: Laruche | K38: 999999 | L38: XF142225342FR | M38: N | N38: Transport | O38: N | P38: S | Q38: Z1 | R38: 4.266 | S38: 17 | T38: 18.34 | U38: LA RUCHE LOGISTIQUE | W38: =IF(C38<>2,"",IF(S38="5X","5XK",IF(S38="5Y","5YK",IF(S38="6B","6BK",IF(S38="6C","6CK",""))))) | X38: =IF(S38="6B",_xlfn.XLOOKUP(H38,'Zoning 2shop'!A:A,'Zoning 2shop'!B:B),IF(S38="6C",_xlfn.XLOOKUP(G38,'Zoning 2shop'!C:C,'Zoning 2shop'!D:D),"")) | Y38: =AB38/Z38 | Z38: =T38 | AA38: =IF(OR(S38="6C",S38="6B",S38="5X",S38="5Y"),0.08,0.5) | AB38: =$AG$5/$AG$2*Z38 | AC38: =Z38+AA38 | AD38: =IF(COUNTIF(Catégories!A:A,N38)=0,"catégorie inconnue",LOOKUP(N38,Catégories!A:A,Catégories!B:B)) | AE38: =SUM(Z38:AB38)
B39: 13617723 | C39: 0 | D39: 46146 | E39: 21320 | F39: 9991 | G39: FR | H39: BE | I39: Van Robays Steven | J39: Laruche | K39: 999999 | L39: XF142225838FR | M39: N | N39: Transport | O39: N | P39: S | Q39: Z1 | R39: 5.904 | S39: 17 | T39: 21.83 | U39: LA RUCHE LOGISTIQUE | W39: =IF(C39<>2,"",IF(S39="5X","5XK",IF(S39="5Y","5YK",IF(S39="6B","6BK",IF(S39="6C","6CK",""))))) | X39: =IF(S39="6B",_xlfn.XLOOKUP(H39,'Zoning 2shop'!A:A,'Zoning 2shop'!B:B),IF(S39="6C",_xlfn.XLOOKUP(G39,'Zoning 2shop'!C:C,'Zoning 2shop'!D:D),"")) | Y39: =AB39/Z39 | Z39: =T39 | AA39: =IF(OR(S39="6C",S39="6B",S39="5X",S39="5Y"),0.08,0.5) | AB39: =$AG$5/$AG$2*Z39 | AC39: =Z39+AA39 | AD39: =IF(COUNTIF(Catégories!A:A,N39)=0,"catégorie inconnue",LOOKUP(N39,Catégories!A:A,Catégories!B:B)) | AE39: =SUM(Z39:AB39)
... B118: 13617723 | C118: 0 | D118: 46161 | E118: 21320 | F118: 28200 | G118: FR | H118: ES | I118: Aguilera Reija Ersilia | J118: Laruche | K118: 999999 | L118: XF142970539FR | M118: N | N118: Transport | O118: N | P118: S | Q118: Z2 | R118: 0.328 | S118: 17 | T118: 7.86 | U118: LA RUCHE LOGISTIQUE | W118: =IF(C118<>2,"",IF(S118="5X","5XK",IF(S118="5Y","5YK",IF(S118="6B","6BK",IF(S118="6C","6CK",""))))) | X118: =IF(S118="6B",_xlfn.XLOOKUP(H118,'Zoning 2shop'!A:A,'Zoning 2shop'!B:B),IF(S118="6C",_xlfn.XLOOKUP(G118,'Zoning 2shop'!C:C,'Zoning 2shop'!D:D),"")) | Y118: =AB118/Z118 | Z118: =T118 | AA118: =IF(OR(S118="6C",S118="6B",S118="5X",S118="5Y"),0.08,0.5) | AB118: =$AG$5/$AG$2*Z118 | AC118: =Z118+AA118 | AD118: =IF(COUNTIF(Catégories!A:A,N118)=0,"catégorie inconnue",LOOKUP(N118,Catégories!A:A,Catégories!B:B)) | AE118: =SUM(Z118:AB118)
B119: 13617723 | C119: 0 | D119: 46161 | E119: 21320 | F119: 28200 | G119: FR | H119: ES | I119: Aguilera Reija Ersilia | J119: Laruche | K119: 999999 | L119: XF142970539FR | M119: N | N119: Supp Zone Internationale Eloignee | O119: N | Q119: Z2 | R119: 0 | S119: 17 | T119: 17 | U119: LA RUCHE LOGISTIQUE | W119: =IF(C119<>2,"",IF(S119="5X","5XK",IF(S119="5Y","5YK",IF(S119="6B","6BK",IF(S119="6C","6CK",""))))) | X119: =IF(S119="6B",_xlfn.XLOOKUP(H119,'Zoning 2shop'!A:A,'Zoning 2shop'!B:B),IF(S119="6C",_xlfn.XLOOKUP(G119,'Zoning 2shop'!C:C,'Zoning 2shop'!D:D),"")) | Y119: =AB119/Z119 | Z119: =T119 | AA119: =IF(OR(S119="6C",S119="6B",S119="5X",S119="5Y"),0.08,0.5) | AB119: =$AG$5/$AG$2*Z119 | AC119: =Z119+AA119 | AD119: =IF(COUNTIF(Catégories!A:A,N119)=0,"catégorie inconnue",LOOKUP(N119,Catégories!A:A,Catégories!B:B)) | AE119: =SUM(Z119:AB119)
B120: 13617723 | C120: 0 | D120: 46161 | E120: 21320 | F120: 53925 | G120: FR | H120: DE | I120: Schumacher Franca | J120: Laruche | K120: 999999 | L120: XF142970715FR | M120: N | N120: Transport | O120: N | P120: S | Q120: Z1 | R120: 0.738 | S120: 17 | T120: 9.94 | U120: LA RUCHE LOGISTIQUE | W120: =IF(C120<>2,"",IF(S120="5X","5XK",IF(S120="5Y","5YK",IF(S120="6B","6BK",IF(S120="6C","6CK",""))))) | X120: =IF(S120="6B",_xlfn.XLOOKUP(H120,'Zoning 2shop'!A:A,'Zoning 2shop'!B:B),IF(S120="6C",_xlfn.XLOOKUP(G120,'Zoning 2shop'!C:C,'Zoning 2shop'!D:D),"")) | Y120: =AB120/Z120 | Z120: =T120 | AA120: =IF(OR(S120="6C",S120="6B",S120="5X",S120="5Y"),0.08,0.5) | AB120: =$AG$5/$AG$2*Z120 | AC120: =Z120+AA120 | AD120: =IF(COUNTIF(Catégories!A:A,N120)=0,"catégorie inconnue",LOOKUP(N120,Catégories!A:A,Catégories!B:B)) | AE120: =SUM(Z120:AB120)
B121: 13617723 | C121: 0 | D121: 46161 | E121: 21320 | F121: 27356 | G121: FR | H121: DE | I121: Schroeder Torsten | J121: Laruche | K121: 999999 | L121: XF142971004FR | M121: N | N121: Transport | O121: N | P121: S | Q121: Z1 | R121: 4.266 | S121: 17 | T121: 18.34 | U121: LA RUCHE LOGISTIQUE | W121: =IF(C121<>2,"",IF(S121="5X","5XK",IF(S121="5Y","5YK",IF(S121="6B","6BK",IF(S121="6C","6CK",""))))) | X121: =IF(S121="6B",_xlfn.XLOOKUP(H121,'Zoning 2shop'!A:A,'Zoning 2shop'!B:B),IF(S121="6C",_xlfn.XLOOKUP(G121,'Zoning 2shop'!C:C,'Zoning 2shop'!D:D),"")) | Y121: =AB121/Z121 | Z121: =T121 | AA121: =IF(OR(S121="6C",S121="6B",S121="5X",S121="5Y"),0.08,0.5) | AB121: =$AG$5/$AG$2*Z121 | AC121: =Z121+AA121 | AD121: =IF(COUNTIF(Catégories!A:A,N121)=0,"catégorie inconnue",LOOKUP(N121,Catégories!A:A,Catégories!B:B)) | AE121: =SUM(Z121:AB121)
B122: 13617723 | C122: 0 | D122: 46161 | E122: 21320 | F122: 40625 | G122: FR | H122: DE | I122: Dalhoff-Schereik Julia | J122: Laruche | K122: 999999 | L122: XF142971110FR | M122: N | N122: Transport | O122: N | P122: S | Q122: Z1 | R122: 4.532 | S122: 17 | T122: 19.47 | U122: LA RUCHE LOGISTIQUE | W122: =IF(C122<>2,"",IF(S122="5X","5XK",IF(S122="5Y","5YK",IF(S122="6B","6BK",IF(S122="6C","6CK",""))))) | X122: =IF(S122="6B",_xlfn.XLOOKUP(H122,'Zoning 2shop'!A:A,'Zoning 2shop'!B:B),IF(S122="6C",_xlfn.XLOOKUP(G122,'Zoning 2shop'!C:C,'Zoning 2shop'!D:D),"")) | Y122: =AB122/Z122 | Z122: =T122 | AA122: =IF(OR(S122="6C",S122="6B",S122="5X",S122="5Y"),0.08,0.5) | AB122: =$AG$5/$AG$2*Z122 | AC122: =Z122+AA122 | AD122: =IF(COUNTIF(Catégories!A:A,N122)=0,"catégorie inconnue",LOOKUP(N122,Catégories!A:A,Catégories!B:B)) | AE122: =SUM(Z122:AB122)
B123: 13617723 | C123: 0 | D123: 46161 | E123: 21320 | F123: 32657 | G123: FR | H123: DE | I123: Werner Annika | J123: Laruche | K123: 999999 | L123: XF142971199FR | M123: N | N123: Transport | O123: N | P123: S | Q123: Z1 | R123: 0.25 | S123: 17 | T123: 7.86 | U123: LA RUCHE LOGISTIQUE | W123: =IF(C123<>2,"",IF(S123="5X","5XK",IF(S123="5Y","5YK",IF(S123="6B","6BK",IF(S123="6C","6CK",""))))) | X123: =IF(S123="6B",_xlfn.XLOOKUP(H123,'Zoning 2shop'!A:A,'Zoning 2shop'!B:B),IF(S123="6C",_xlfn.XLOOKUP(G123,'Zoning 2shop'!C:C,'Zoning 2shop'!D:D),"")) | Y123: =AB123/Z123 | Z123: =T123 | AA123: =IF(OR(S123="6C",S123="6B",S123="5X",S123="5Y"),0.08,0.5) | AB123: =$AG$5/$AG$2*Z123 | AC123: =Z123+AA123 | AD123: =IF(COUNTIF(Catégories!A:A,N123)=0,"catégorie inconnue",LOOKUP(N123,Catégories!A:A,Catégories!B:B)) | AE123: =SUM(Z123:AB123)
B124: 13617723 | C124: 0 | D124: 46161 | E124: 21320 | F124: 32657 | G124: FR | H124: DE | I124: Werner Annika | J124: Laruche | K124: 999999 | L124: XF142971199FR | M124: N | N124: Supp Retour Expediteur Inter | O124: N | Q124: Z1 | R124: 0 | S124: 17 | T124: 45 | U124: LA RUCHE LOGISTIQUE | W124: =IF(C124<>2,"",IF(S124="5X","5XK",IF(S124="5Y","5YK",IF(S124="6B","6BK",IF(S124="6C","6CK",""))))) | X124: =IF(S124="6B",_xlfn.XLOOKUP(H124,'Zoning 2shop'!A:A,'Zoning 2shop'!B:B),IF(S124="6C",_xlfn.XLOOKUP(G124,'Zoning 2shop'!C:C,'Zoning 2shop'!D:D),"")) | Y124: =AB124/Z124 | Z124: =T124 | AA124: =IF(OR(S124="6C",S124="6B",S124="5X",S124="5Y"),0.08,0.5) | AB124: =$AG$5/$AG$2*Z124 | AC124: =Z124+AA124 | AD124: =IF(COUNTIF(Catégories!A:A,N124)=0,"catégorie inconnue",LOOKUP(N124,Catégories!A:A,Catégories!B:B)) | AE124: =SUM(Z124:AB124)
B125: 13617723 | C125: 0 | D125: 46161 | E125: 21320 | F125: 10557 | G125: FR | H125: DE | I125: Forster Judith | J125: Laruche | K125: 999999 | L125: XF142971211FR | M125: N | N125: Transport | O125: N | P125: S | Q125: Z1 | R125: 0.25 | S125: 17 | T125: 7.86 | U125: LA RUCHE LOGISTIQUE | W125: =IF(C125<>2,"",IF(S125="5X","5XK",IF(S125="5Y","5YK",IF(S125="6B","6BK",IF(S125="6C","6CK",""))))) | X125: =IF(S125="6B",_xlfn.XLOOKUP(H125,'Zoning 2shop'!A:A,'Zoning 2shop'!B:B),IF(S125="6C",_xlfn.XLOOKUP(G125,'Zoning 2shop'!C:C,'Zoning 2shop'!D:D),"")) | Y125: =AB125/Z125 | Z125: =T125 | AA125: =IF(OR(S125="6C",S125="6B",S125="5X",S125="5Y"),0.08,0.5) | AB125: =$AG$5/$AG$2*Z125 | AC125: =Z125+AA125 | AD125: =IF(COUNTIF(Catégories!A:A,N125)=0,"catégorie inconnue",LOOKUP(N125,Catégories!A:A,Catégories!B:B)) | AE125: =SUM(Z125:AB125)
B126: 13617723 | C126: 0 | D126: 46161 | E126: 21320 | F126: 29700 | G126: FR | H126: ES | I126: Power Alejandra | J126: Laruche | K126: 999999 | L126: XF142972163FR | M126: N | N126: Transport | O126: N | P126: S | Q126: Z2 | R126: 0.748 | S126: 17 | T126: 9.94 | U126: LA RUCHE LOGISTIQUE | W126: =IF(C126<>2,"",IF(S126="5X","5XK",IF(S126="5Y","5YK",IF(S126="6B","6BK",IF(S126="6C","6CK",""))))) | X126: =IF(S126="6B",_xlfn.XLOOKUP(H126,'Zoning 2shop'!A:A,'Zoning 2shop'!B:B),IF(S126="6C",_xlfn.XLOOKUP(G126,'Zoning 2shop'!C:C,'Zoning 2shop'!D:D),"")) | Y126: =AB126/Z126 | Z126: =T126 | AA126: =IF(OR(S126="6C",S126="6B",S126="5X",S126="5Y"),0.08,0.5) | AB126: =$AG$5/$AG$2*Z126 | AC126: =Z126+AA126 | AD126: =IF(COUNTIF(Catégories!A:A,N126)=0,"catégorie inconnue",LOOKUP(N126,Catégories!A:A,Catégories!B:B)) | AE126: =SUM(Z126:AB126)
B127: 13617723 | C127: 0 | D127: 46161 | E127: 21320 | F127: 29700 | G127: FR | H127: ES | I127: Power Alejandra | J127: Laruche | K127: 999999 | L127: XF142972163FR | M127: N | N127: Supp Retour Expediteur Inter | O127: N | Q127: Z2 | R127: 0 | S127: 17 | T127: 45 | U127: LA RUCHE LOGISTIQUE | W127: =IF(C127<>2,"",IF(S127="5X","5XK",IF(S127="5Y","5YK",IF(S127="6B","6BK",IF(S127="6C","6CK",""))))) | X127: =IF(S127="6B",_xlfn.XLOOKUP(H127,'Zoning 2shop'!A:A,'Zoning 2shop'!B:B),IF(S127="6C",_xlfn.XLOOKUP(G127,'Zoning 2shop'!C:C,'Zoning 2shop'!D:D),"")) | Y127: =AB127/Z127 | Z127: =T127 | AA127: =IF(OR(S127="6C",S127="6B",S127="5X",S127="5Y"),0.08,0.5) | AB127: =$AG$5/$AG$2*Z127 | AC127: =Z127+AA127 | AD127: =IF(COUNTIF(Catégories!A:A,N127)=0,"catégorie inconnue",LOOKUP(N127,Catégories!A:A,Catégories!B:B)) | AE127: =SUM(Z127:AB127)
B128: 13617723 | C128: 0 | D128: 46161 | E128: 21320 | F128: 32361 | G128: FR | H128: DE | I128: Splettstoser Janette | J128: Laruche | K128: 999999 | L128: XF142984025FR | M128: N | N128: Transport | O128: N | P128: S | Q128: Z1 | R128: 5.76 | S128: 17 | T128: 21.83 | U128: LA RUCHE LOGISTIQUE | W128: =IF(C128<>2,"",IF(S128="5X","5XK",IF(S128="5Y","5YK",IF(S128="6B","6BK",IF(S128="6C","6CK",""))))) | X128: =IF(S128="6B",_xlfn.XLOOKUP(H128,'Zoning 2shop'!A:A,'Zoning 2shop'!B:B),IF(S128="6C",_xlfn.XLOOKUP(G128,'Zoning 2shop'!C:C,'Zoning 2shop'!D:D),"")) | Y128: =AB128/Z128 | Z128: =T128 | AA128: =IF(OR(S128="6C",S128="6B",S128="5X",S128="5Y"),0.08,0.5) | AB128: =$AG$5/$AG$2*Z128 | AC128: =Z128+AA128 | AD128: =IF(COUNTIF(Catégories!A:A,N128)=0,"catégorie inconnue",LOOKUP(N128,Catégories!A:A,Catégories!B:B)) | AE128: =SUM(Z128:AB128)
B129: 13617723 | C129: 0 | D129: 46161 | E129: 21320 | F129: 55124 | G129: FR | H129: DE | I129: Schlechtriemen-Kos Agnes | J129: Laruche | K129: 999999 | L129: XF142986471FR | M129: N | N129: Transport | O129: N | P129: S | Q129: Z1 | R129: 4.427 | S129: 17 | T129: 18.34 | U129: LA RUCHE LOGISTIQUE | W129: =IF(C129<>2,"",IF(S129="5X","5XK",IF(S129="5Y","5YK",IF(S129="6B","6BK",IF(S129="6C","6CK",""))))) | X129: =IF(S129="6B",_xlfn.XLOOKUP(H129,'Zoning 2shop'!A:A,'Zoning 2shop'!B:B),IF(S129="6C",_xlfn.XLOOKUP(G129,'Zoning 2shop'!C:C,'Zoning 2shop'!D:D),"")) | Y129: =AB129/Z129 | Z129: =T129 | AA129: =IF(OR(S129="6C",S129="6B",S129="5X",S129="5Y"),0.08,0.5) | AB129: =$AG$5/$AG$2*Z129 | AC129: =Z129+AA129 | AD129: =IF(COUNTIF(Catégories!A:A,N129)=0,"catégorie inconnue",LOOKUP(N129,Catégories!A:A,Catégories!B:B)) | AE129: =SUM(Z129:AB129)
B130: 13617723 | C130: 0 | D130: 46161 | E130: 21320 | F130: 54470 | G130: FR | H130: DE | I130: Hermann Liane | J130: Laruche | K130: 999999 | L130: XF142987123FR | M130: N | N130: Transport | O130: N | P130: S | Q130: Z1 | R130: 0.781 | S130: 17 | T130: 9.94 | U130: LA RUCHE LOGISTIQUE | W130: =IF(C130<>2,"",IF(S130="5X","5XK",IF(S130="5Y","5YK",IF(S130="6B","6BK",IF(S130="6C","6CK",""))))) | X130: =IF(S130="6B",_xlfn.XLOOKUP(H130,'Zoning 2shop'!A:A,'Zoning 2shop'!B:B),IF(S130="6C",_xlfn.XLOOKUP(G130,'Zoning 2shop'!C:C,'Zoning 2shop'!D:D),"")) | Y130: =AB130/Z130 | Z130: =T130 | AA130: =IF(OR(S130="6C",S130="6B",S130="5X",S130="5Y"),0.08,0.5) | AB130: =$AG$5/$AG$2*Z130 | AC130: =Z130+AA130 | AD130: =IF(COUNTIF(Catégories!A:A,N130)=0,"catégorie inconnue",LOOKUP(N130,Catégories!A:A,Catégories!B:B)) | AE130: =SUM(Z130:AB130)
B131: 13617723 | C131: 0 | D131: 46161 | E131: 21320 | F131: 20123 | G131: FR | H131: IT | I131: RINALDI MICHELE | J131: Laruche | K131: 999999 | L131: XF142995487FR | M131: N | N131: Transport | O131: N | P131: S | Q131: Z2 | R131: 4.532 | S131: 17 | T131: 19.47 | U131: LA RUCHE LOGISTIQUE | W131: =IF(C131<>2,"",IF(S131="5X","5XK",IF(S131="5Y","5YK",IF(S131="6B","6BK",IF(S131="6C","6CK",""))))) | X131: =IF(S131="6B",_xlfn.XLOOKUP(H131,'Zoning 2shop'!A:A,'Zoning 2shop'!B:B),IF(S131="6C",_xlfn.XLOOKUP(G131,'Zoning 2shop'!C:C,'Zoning 2shop'!D:D),"")) | Y131: =AB131/Z131 | Z131: =T131 | AA131: =IF(OR(S131="6C",S131="6B",S131="5X",S131="5Y"),0.08,0.5) | AB131: =$AG$5/$AG$2*Z131 | AC131: =Z131+AA131 | AD131: =IF(COUNTIF(Catégories!A:A,N131)=0,"catégorie inconnue",LOOKUP(N131,Catégories!A:A,Catégories!B:B)) | AE131: =SUM(Z131:AB131)
B132: 13617723 | C132: 0 | D132: 46161 | E132: 21320 | F132: 76297 | G132: FR | H132: DE | I132: Redweik Kirstin | J132: Laruche | K132: 999999 | L132: XF143016663FR | M132: N | N132: Transport | O132: N | P132: S | Q132: Z1 | R132: 0.56 | S132: 17 | T132: 9.94 | U132: LA RUCHE LOGISTIQUE | W132: =IF(C132<>2,"",IF(S132="5X","5XK",IF(S132="5Y","5YK",IF(S132="6B","6BK",IF(S132="6C","6CK",""))))) | X132: =IF(S132="6B",_xlfn.XLOOKUP(H132,'Zoning 2shop'!A:A,'Zoning 2shop'!B:B),IF(S132="6C",_xlfn.XLOOKUP(G132,'Zoning 2shop'!C:C,'Zoning 2shop'!D:D),"")) | Y132: =AB132/Z132 | Z132: =T132 | AA132: =IF(OR(S132="6C",S132="6B",S132="5X",S132="5Y"),0.08,0.5) | AB132: =$AG$5/$AG$2*Z132 | AC132: =Z132+AA132 | AD132: =IF(COUNTIF(Catégories!A:A,N132)=0,"catégorie inconnue",LOOKUP(N132,Catégories!A:A,Catégories!B:B)) | AE132: =SUM(Z132:AB132)
B133: 13617723 | C133: 0 | D133: 46161 | E133: 21320 | F133: 2622AZ | G133: FR | H133: NL | I133: van Vliet Annemiek | J133: Laruche | K133: 999999 | L133: XF143022641FR | M133: N | N133: Transport | O133: N | P133: S | Q133: Z1 | R133: 0.25 | S133: 17 | T133: 7.86 | U133: LA RUCHE LOGISTIQUE | W133: =IF(C133<>2,"",IF(S133="5X","5XK",IF(S133="5Y","5YK",IF(S133="6B","6BK",IF(S133="6C","6CK",""))))) | X133: =IF(S133="6B",_xlfn.XLOOKUP(H133,'Zoning 2shop'!A:A,'Zoning 2shop'!B:B),IF(S133="6C",_xlfn.XLOOKUP(G133,'Zoning 2shop'!C:C,'Zoning 2shop'!D:D),"")) | Y133: =AB133/Z133 | Z133: =T133 | AA133: =IF(OR(S133="6C",S133="6B",S133="5X",S133="5Y"),0.08,0.5) | AB133: =$AG$5/$AG$2*Z133 | AC133: =Z133+AA133 | AD133: =IF(COUNTIF(Catégories!A:A,N133)=0,"catégorie inconnue",LOOKUP(N133,Catégories!A:A,Catégories!B:B)) | AE133: =SUM(Z133:AB133)
B134: 13617723 | C134: 0 | D134: 46161 | E134: 21320 | F134: 1012 | G134: FR | H134: HU | I134: Bomer Matt | J134: Laruche | K134: 999999 | L134: XF143022690FR | M134: N | N134: Transport | O134: N | P134: S | Q134: Z3 | R134: 0.7 | S134: 17 | T134: 13.35 | U134: LA RUCHE LOGISTIQUE | W134: =IF(C134<>2,"",IF(S134="5X","5XK",IF(S134="5Y","5YK",IF(S134="6B","6BK",IF(S134="6C","6CK",""))))) | X134: =IF(S134="6B",_xlfn.XLOOKUP(H134,'Zoning 2shop'!A:A,'Zoning 2shop'!B:B),IF(S134="6C",_xlfn.XLOOKUP(G134,'Zoning 2shop'!C:C,'Zoning 2shop'!D:D),"")) | Y134: =AB134/Z134 | Z134: =T134 | AA134: =IF(OR(S134="6C",S134="6B",S134="5X",S134="5Y"),0.08,0.5) | AB134: =$AG$5/$AG$2*Z134 | AC134: =Z134+AA134 | AD134: =IF(COUNTIF(Catégories!A:A,N134)=0,"catégorie inconnue",LOOKUP(N134,Catégories!A:A,Catégories!B:B)) | AE134: =SUM(Z134:AB134)
B135: 13617723 | C135: 0 | D135: 46162 | E135: 21320 | F135: 04740 | G135: FR | H135: ES | I135: Jimenez Maria | J135: Laruche | K135: 999999 | L135: XF143055052FR | M135: N | N135: Transport | O135: N | P135: S | Q135: Z2 | R135: 0.25 | S135: 17 | T135: 7.86 | U135: LA RUCHE LOGISTIQUE | W135: =IF(C135<>2,"",IF(S135="5X","5XK",IF(S135="5Y","5YK",IF(S135="6B","6BK",IF(S135="6C","6CK",""))))) | X135: =IF(S135="6B",_xlfn.XLOOKUP(H135,'Zoning 2shop'!A:A,'Zoning 2shop'!B:B),IF(S135="6C",_xlfn.XLOOKUP(G135,'Zoning 2shop'!C:C,'Zoning 2shop'!D:D),"")) | Y135: =AB135/Z135 | Z135: =T135 | AA135: =IF(OR(S135="6C",S135="6B",S135="5X",S135="5Y"),0.08,0.5) | AB135: =$AG$5/$AG$2*Z135 | AC135: =Z135+AA135 | AD135: =IF(COUNTIF(Catégories!A:A,N135)=0,"catégorie inconnue",LOOKUP(N135,Catégories!A:A,Catégories!B:B)) | AE135: =SUM(Z135:AB135)
B136: 13617723 | C136: 0 | D136: 46162 | E136: 21320 | F136: 93086 | G136: FR | H136: DE | I136: Rosch Anja | J136: Laruche | K136: 999999 | L136: XF143055256FR | M136: N | N136: Transport | O136: N | P136: S | Q136: Z1 | R136: 0.748 | S136: 17 | T136: 9.94 | U136: LA RUCHE LOGISTIQUE | W136: =IF(C136<>2,"",IF(S136="5X","5XK",IF(S136="5Y","5YK",IF(S136="6B","6BK",IF(S136="6C","6CK",""))))) | X136: =IF(S136="6B",_xlfn.XLOOKUP(H136,'Zoning 2shop'!A:A,'Zoning 2shop'!B:B),IF(S136="6C",_xlfn.XLOOKUP(G136,'Zoning 2shop'!C:C,'Zoning 2shop'!D:D),"")) | Y136: =AB136/Z136 | Z136: =T136 | AA136: =IF(OR(S136="6C",S136="6B",S136="5X",S136="5Y"),0.08,0.5) | AB136: =$AG$5/$AG$2*Z136 | AC136: =Z136+AA136 | AD136: =IF(COUNTIF(Catégories!A:A,N136)=0,"catégorie inconnue",LOOKUP(N136,Catégories!A:A,Catégories!B:B)) | AE136: =SUM(Z136:AB136)
B137: 13617723 | C137: 0 | D137: 46162 | E137: 21320 | F137: 95234 | G137: FR | H137: DE | I137: Schuder Barbara | J137: Laruche | K137: 999999 | L137: XF143055976FR | M137: N | N137: Transport | O137: N | P137: S | Q137: Z1 | R137: 5.914 | S137: 17 | T137: 21.83 | U137: LA RUCHE LOGISTIQUE | W137: =IF(C137<>2,"",IF(S137="5X","5XK",IF(S137="5Y","5YK",IF(S137="6B","6BK",IF(S137="6C","6CK",""))))) | X137: =IF(S137="6B",_xlfn.XLOOKUP(H137,'Zoning 2shop'!A:A,'Zoning 2shop'!B:B),IF(S137="6C",_xlfn.XLOOKUP(G137,'Zoning 2shop'!C:C,'Zoning 2shop'!D:D),"")) | Y137: =AB137/Z137 | Z137: =T137 | AA137: =IF(OR(S137="6C",S137="6B",S137="5X",S137="5Y"),0.08,0.5) | AB137: =$AG$5/$AG$2*Z137 | AC137: =Z137+AA137 | AD137: =IF(COUNTIF(Catégories!A:A,N137)=0,"catégorie inconnue",LOOKUP(N137,Catégories!A:A,Catégories!B:B)) | AE137: =SUM(Z137:AB137)
B138: 13617723 | C138: 0 | D138: 46162 | E138: 21320 | F138: 10713 | G138: FR | H138: DE | I138: Gurbanberdiyev Hekim | J138: Laruche | K138: 999999 | L138: XF143056000FR | M138: N | N138: Transport | O138: N | P138: S | Q138: Z1 | R138: 0.25 | S138: 17 | T138: 7.86 | U138: LA RUCHE LOGISTIQUE | W138: =IF(C138<>2,"",IF(S138="5X","5XK",IF(S138="5Y","5YK",IF(S138="6B","6BK",IF(S138="6C","6CK",""))))) | X138: =IF(S138="6B",_xlfn.XLOOKUP(H138,'Zoning 2shop'!A:A,'Zoning 2shop'!B:B),IF(S138="6C",_xlfn.XLOOKUP(G138,'Zoning 2shop'!C:C,'Zoning 2shop'!D:D),"")) | Y138: =AB138/Z138 | Z138: =T138 | AA138: =IF(OR(S138="6C",S138="6B",S138="5X",S138="5Y"),0.08,0.5) | AB138: =$AG$5/$AG$2*Z138 | AC138: =Z138+AA138 | AD138: =IF(COUNTIF(Catégories!A:A,N138)=0,"catégorie inconnue",LOOKUP(N138,Catégories!A:A,Catégories!B:B)) | AE138: =SUM(Z138:AB138)
B139: 13617723 | C139: 0 | D139: 46162 | E139: 21320 | F139: 62010 | G139: FR | H139: IT | I139: Gagliardini Tommaso | J139: Laruche | K139: 999999 | L139: XF143056265FR | M139: N | N139: Transport | O139: N | P139: S | Q139: Z2 | R139: 0.748 | S139: 17 | T139: 9.94 | U139: LA RUCHE LOGISTIQUE | W139: =IF(C139<>2,"",IF(S139="5X","5XK",IF(S139="5Y","5YK",IF(S139="6B","6BK",IF(S139="6C","6CK",""))))) | X139: =IF(S139="6B",_xlfn.XLOOKUP(H139,'Zoning 2shop'!A:A,'Zoning 2shop'!B:B),IF(S139="6C",_xlfn.XLOOKUP(G139,'Zoning 2shop'!C:C,'Zoning 2shop'!D:D),"")) | Y139: =AB139/Z139 | Z139: =T139 | AA139: =IF(OR(S139="6C",S139="6B",S139="5X",S139="5Y"),0.08,0.5) | AB139: =$AG$5/$AG$2*Z139 | AC139: =Z139+AA139 | AD139: =IF(COUNTIF(Catégories!A:A,N139)=0,"catégorie inconnue",LOOKUP(N139,Catégories!A:A,Catégories!B:B)) | AE139: =SUM(Z139:AB139)
... B163: 13617723 | C163: 0 | D163: 46164 | E163: 21320 | F163: 71020 | G163: FR | H163: IT | I163: Arcuri Enza | J163: Laruche | K163: 999999 | L163: XF143199462FR | M163: N | N163: Transport | O163: N | P163: S | Q163: Z2 | R163: 0.25 | S163: 17 | T163: 7.86 | U163: LA RUCHE LOGISTIQUE | W163: =IF(C163<>2,"",IF(S163="5X","5XK",IF(S163="5Y","5YK",IF(S163="6B","6BK",IF(S163="6C","6CK",""))))) | X163: =IF(S163="6B",_xlfn.XLOOKUP(H163,'Zoning 2shop'!A:A,'Zoning 2shop'!B:B),IF(S163="6C",_xlfn.XLOOKUP(G163,'Zoning 2shop'!C:C,'Zoning 2shop'!D:D),"")) | Y163: =AB163/Z163 | Z163: =T163 | AA163: =IF(OR(S163="6C",S163="6B",S163="5X",S163="5Y"),0.08,0.5) | AB163: =$AG$5/$AG$2*Z163 | AC163: =Z163+AA163 | AD163: =IF(COUNTIF(Catégories!A:A,N163)=0,"catégorie inconnue",LOOKUP(N163,Catégories!A:A,Catégories!B:B)) | AE163: =SUM(Z163:AB163)
B164: 13617723 | C164: 0 | D164: 46164 | E164: 21320 | F164: 71020 | G164: FR | H164: IT | I164: Arcuri Enza | J164: Laruche | K164: 999999 | L164: XF143199462FR | M164: N | N164: Supp Zone Internationale Eloignee | O164: N | Q164: Z2 | R164: 0 | S164: 17 | T164: 17 | U164: LA RUCHE LOGISTIQUE | W164: =IF(C164<>2,"",IF(S164="5X","5XK",IF(S164="5Y","5YK",IF(S164="6B","6BK",IF(S164="6C","6CK",""))))) | X164: =IF(S164="6B",_xlfn.XLOOKUP(H164,'Zoning 2shop'!A:A,'Zoning 2shop'!B:B),IF(S164="6C",_xlfn.XLOOKUP(G164,'Zoning 2shop'!C:C,'Zoning 2shop'!D:D),"")) | Y164: =AB164/Z164 | Z164: =T164 | AA164: =IF(OR(S164="6C",S164="6B",S164="5X",S164="5Y"),0.08,0.5) | AB164: =$AG$5/$AG$2*Z164 | AC164: =Z164+AA164 | AD164: =IF(COUNTIF(Catégories!A:A,N164)=0,"catégorie inconnue",LOOKUP(N164,Catégories!A:A,Catégories!B:B)) | AE164: =SUM(Z164:AB164)
B165: 13617723 | C165: 0 | D165: 46164 | E165: 21320 | F165: 86153 | G165: FR | H165: DE | I165: Monninghoff Jutta | J165: Laruche | K165: 999999 | L165: XF143200109FR | M165: N | N165: Transport | O165: N | P165: S | Q165: Z1 | R165: 4.266 | S165: 17 | T165: 18.34 | U165: LA RUCHE LOGISTIQUE | W165: =IF(C165<>2,"",IF(S165="5X","5XK",IF(S165="5Y","5YK",IF(S165="6B","6BK",IF(S165="6C","6CK",""))))) | X165: =IF(S165="6B",_xlfn.XLOOKUP(H165,'Zoning 2shop'!A:A,'Zoning 2shop'!B:B),IF(S165="6C",_xlfn.XLOOKUP(G165,'Zoning 2shop'!C:C,'Zoning 2shop'!D:D),"")) | Y165: =AB165/Z165 | Z165: =T165 | AA165: =IF(OR(S165="6C",S165="6B",S165="5X",S165="5Y"),0.08,0.5) | AB165: =$AG$5/$AG$2*Z165 | AC165: =Z165+AA165 | AD165: =IF(COUNTIF(Catégories!A:A,N165)=0,"catégorie inconnue",LOOKUP(N165,Catégories!A:A,Catégories!B:B)) | AE165: =SUM(Z165:AB165)
B166: 13617723 | C166: 0 | D166: 46164 | E166: 21320 | F166: 70056 | G166: FR | H166: IT | I166: Montemurro Natalia | J166: Laruche | K166: 999999 | L166: XF143200143FR | M166: N | N166: Transport | O166: N | P166: S | Q166: Z2 | R166: 4.403 | S166: 17 | T166: 18.34 | U166: LA RUCHE LOGISTIQUE | W166: =IF(C166<>2,"",IF(S166="5X","5XK",IF(S166="5Y","5YK",IF(S166="6B","6BK",IF(S166="6C","6CK",""))))) | X166: =IF(S166="6B",_xlfn.XLOOKUP(H166,'Zoning 2shop'!A:A,'Zoning 2shop'!B:B),IF(S166="6C",_xlfn.XLOOKUP(G166,'Zoning 2shop'!C:C,'Zoning 2shop'!D:D),"")) | Y166: =AB166/Z166 | Z166: =T166 | AA166: =IF(OR(S166="6C",S166="6B",S166="5X",S166="5Y"),0.08,0.5) | AB166: =$AG$5/$AG$2*Z166 | AC166: =Z166+AA166 | AD166: =IF(COUNTIF(Catégories!A:A,N166)=0,"catégorie inconnue",LOOKUP(N166,Catégories!A:A,Catégories!B:B)) | AE166: =SUM(Z166:AB166)
B167: 13617723 | C167: 0 | D167: 46164 | E167: 21320 | F167: 74336 | G167: FR | H167: DE | I167: Steiner Sina | J167: Laruche | K167: 999999 | L167: XF143200228FR | M167: N | N167: Transport | O167: N | P167: S | Q167: Z1 | R167: 0.8 | S167: 17 | T167: 9.94 | U167: LA RUCHE LOGISTIQUE | W167: =IF(C167<>2,"",IF(S167="5X","5XK",IF(S167="5Y","5YK",IF(S167="6B","6BK",IF(S167="6C","6CK",""))))) | X167: =IF(S167="6B",_xlfn.XLOOKUP(H167,'Zoning 2shop'!A:A,'Zoning 2shop'!B:B),IF(S167="6C",_xlfn.XLOOKUP(G167,'Zoning 2shop'!C:C,'Zoning 2shop'!D:D),"")) | Y167: =AB167/Z167 | Z167: =T167 | AA167: =IF(OR(S167="6C",S167="6B",S167="5X",S167="5Y"),0.08,0.5) | AB167: =$AG$5/$AG$2*Z167 | AC167: =Z167+AA167 | AD167: =IF(COUNTIF(Catégories!A:A,N167)=0,"catégorie inconnue",LOOKUP(N167,Catégories!A:A,Catégories!B:B)) | AE167: =SUM(Z167:AB167)
B168: 13617723 | C168: 0 | D168: 46164 | E168: 21320 | F168: 8267AL | G168: FR | H168: NL | I168: Winkelman Fiene | J168: Laruche | K168: 999999 | L168: XF143219706FR | M168: N | N168: Transport | O168: N | P168: S | Q168: Z1 | R168: 4.488 | S168: 17 | T168: 18.34 | U168: LA RUCHE LOGISTIQUE | W168: =IF(C168<>2,"",IF(S168="5X","5XK",IF(S168="5Y","5YK",IF(S168="6B","6BK",IF(S168="6C","6CK",""))))) | X168: =IF(S168="6B",_xlfn.XLOOKUP(H168,'Zoning 2shop'!A:A,'Zoning 2shop'!B:B),IF(S168="6C",_xlfn.XLOOKUP(G168,'Zoning 2shop'!C:C,'Zoning 2shop'!D:D),"")) | Y168: =AB168/Z168 | Z168: =T168 | AA168: =IF(OR(S168="6C",S168="6B",S168="5X",S168="5Y"),0.08,0.5) | AB168: =$AG$5/$AG$2*Z168 | AC168: =Z168+AA168 | AD168: =IF(COUNTIF(Catégories!A:A,N168)=0,"catégorie inconnue",LOOKUP(N168,Catégories!A:A,Catégories!B:B)) | AE168: =SUM(Z168:AB168)
B169: 13617723 | C169: 0 | D169: 46164 | E169: 21320 | F169: 80797 | G169: FR | H169: DE | I169: Freitag Petra | J169: Laruche | K169: 999999 | L169: XF143228518FR | M169: N | N169: Transport | O169: N | P169: S | Q169: Z1 | R169: 0.25 | S169: 17 | T169: 7.86 | U169: LA RUCHE LOGISTIQUE | W169: =IF(C169<>2,"",IF(S169="5X","5XK",IF(S169="5Y","5YK",IF(S169="6B","6BK",IF(S169="6C","6CK",""))))) | X169: =IF(S169="6B",_xlfn.XLOOKUP(H169,'Zoning 2shop'!A:A,'Zoning 2shop'!B:B),IF(S169="6C",_xlfn.XLOOKUP(G169,'Zoning 2shop'!C:C,'Zoning 2shop'!D:D),"")) | Y169: =AB169/Z169 | Z169: =T169 | AA169: =IF(OR(S169="6C",S169="6B",S169="5X",S169="5Y"),0.08,0.5) | AB169: =$AG$5/$AG$2*Z169 | AC169: =Z169+AA169 | AD169: =IF(COUNTIF(Catégories!A:A,N169)=0,"catégorie inconnue",LOOKUP(N169,Catégories!A:A,Catégories!B:B)) | AE169: =SUM(Z169:AB169)
B170: 13617723 | C170: 0 | D170: 46164 | E170: 21320 | F170: 78462 | G170: FR | H170: DE | I170: Wieland Helmut | J170: Laruche | K170: 999999 | L170: XF143228739FR | M170: N | N170: Transport | O170: N | P170: S | Q170: Z1 | R170: 5.773 | S170: 17 | T170: 21.83 | U170: LA RUCHE LOGISTIQUE | W170: =IF(C170<>2,"",IF(S170="5X","5XK",IF(S170="5Y","5YK",IF(S170="6B","6BK",IF(S170="6C","6CK",""))))) | X170: =IF(S170="6B",_xlfn.XLOOKUP(H170,'Zoning 2shop'!A:A,'Zoning 2shop'!B:B),IF(S170="6C",_xlfn.XLOOKUP(G170,'Zoning 2shop'!C:C,'Zoning 2shop'!D:D),"")) | Y170: =AB170/Z170 | Z170: =T170 | AA170: =IF(OR(S170="6C",S170="6B",S170="5X",S170="5Y"),0.08,0.5) | AB170: =$AG$5/$AG$2*Z170 | AC170: =Z170+AA170 | AD170: =IF(COUNTIF(Catégories!A:A,N170)=0,"catégorie inconnue",LOOKUP(N170,Catégories!A:A,Catégories!B:B)) | AE170: =SUM(Z170:AB170)
B171: 13617723 | C171: 0 | D171: 46164 | E171: 21320 | F171: 65843 | G171: FR | H171: DE | I171: Schumacher Sabine | J171: Laruche | K171: 999999 | L171: XF143230091FR | M171: N | N171: Transport | O171: N | P171: S | Q171: Z1 | R171: 5.904 | S171: 17 | T171: 21.83 | U171: LA RUCHE LOGISTIQUE | W171: =IF(C171<>2,"",IF(S171="5X","5XK",IF(S171="5Y","5YK",IF(S171="6B","6BK",IF(S171="6C","6CK",""))))) | X171: =IF(S171="6B",_xlfn.XLOOKUP(H171,'Zoning 2shop'!A:A,'Zoning 2shop'!B:B),IF(S171="6C",_xlfn.XLOOKUP(G171,'Zoning 2shop'!C:C,'Zoning 2shop'!D:D),"")) | Y171: =AB171/Z171 | Z171: =T171 | AA171: =IF(OR(S171="6C",S171="6B",S171="5X",S171="5Y"),0.08,0.5) | AB171: =$AG$5/$AG$2*Z171 | AC171: =Z171+AA171 | AD171: =IF(COUNTIF(Catégories!A:A,N171)=0,"catégorie inconnue",LOOKUP(N171,Catégories!A:A,Catégories!B:B)) | AE171: =SUM(Z171:AB171)
B172: 13617723 | C172: 0 | D172: 46164 | E172: 21320 | F172: 22297 | G172: FR | H172: DE | I172: Kutter Christopher | J172: Laruche | K172: 999999 | L172: XF143235641FR | M172: N | N172: Transport | O172: N | P172: S | Q172: Z1 | R172: 5.904 | S172: 17 | T172: 21.83 | U172: LA RUCHE LOGISTIQUE | W172: =IF(C172<>2,"",IF(S172="5X","5XK",IF(S172="5Y","5YK",IF(S172="6B","6BK",IF(S172="6C","6CK",""))))) | X172: =IF(S172="6B",_xlfn.XLOOKUP(H172,'Zoning 2shop'!A:A,'Zoning 2shop'!B:B),IF(S172="6C",_xlfn.XLOOKUP(G172,'Zoning 2shop'!C:C,'Zoning 2shop'!D:D),"")) | Y172: =AB172/Z172 | Z172: =T172 | AA172: =IF(OR(S172="6C",S172="6B",S172="5X",S172="5Y"),0.08,0.5) | AB172: =$AG$5/$AG$2*Z172 | AC172: =Z172+AA172 | AD172: =IF(COUNTIF(Catégories!A:A,N172)=0,"catégorie inconnue",LOOKUP(N172,Catégories!A:A,Catégories!B:B)) | AE172: =SUM(Z172:AB172)
B173: 13617723 | C173: 0 | D173: 46167 | E173: 21320 | F173: 85599 | G173: FR | H173: DE | I173: Girard Kathrin | J173: Laruche | K173: 999999 | L173: XF143259285FR | M173: N | N173: Transport | O173: N | P173: S | Q173: Z1 | R173: 5.76 | S173: 17 | T173: 21.83 | U173: LA RUCHE LOGISTIQUE | W173: =IF(C173<>2,"",IF(S173="5X","5XK",IF(S173="5Y","5YK",IF(S173="6B","6BK",IF(S173="6C","6CK",""))))) | X173: =IF(S173="6B",_xlfn.XLOOKUP(H173,'Zoning 2shop'!A:A,'Zoning 2shop'!B:B),IF(S173="6C",_xlfn.XLOOKUP(G173,'Zoning 2shop'!C:C,'Zoning 2shop'!D:D),"")) | Y173: =AB173/Z173 | Z173: =T173 | AA173: =IF(OR(S173="6C",S173="6B",S173="5X",S173="5Y"),0.08,0.5) | AB173: =$AG$5/$AG$2*Z173 | AC173: =Z173+AA173 | AD173: =IF(COUNTIF(Catégories!A:A,N173)=0,"catégorie inconnue",LOOKUP(N173,Catégories!A:A,Catégories!B:B)) | AE173: =SUM(Z173:AB173)
B174: 13617723 | C174: 0 | D174: 46167 | E174: 21320 | F174: 3561XD | G174: FR | H174: NL | I174: Horde Marijke | J174: Laruche | K174: 999999 | L174: XF143259311FR | M174: N | N174: Transport | O174: N | P174: S | Q174: Z1 | R174: 0.252 | S174: 17 | T174: 7.86 | U174: LA RUCHE LOGISTIQUE | W174: =IF(C174<>2,"",IF(S174="5X","5XK",IF(S174="5Y","5YK",IF(S174="6B","6BK",IF(S174="6C","6CK",""))))) | X174: =IF(S174="6B",_xlfn.XLOOKUP(H174,'Zoning 2shop'!A:A,'Zoning 2shop'!B:B),IF(S174="6C",_xlfn.XLOOKUP(G174,'Zoning 2shop'!C:C,'Zoning 2shop'!D:D),"")) | Y174: =AB174/Z174 | Z174: =T174 | AA174: =IF(OR(S174="6C",S174="6B",S174="5X",S174="5Y"),0.08,0.5) | AB174: =$AG$5/$AG$2*Z174 | AC174: =Z174+AA174 | AD174: =IF(COUNTIF(Catégories!A:A,N174)=0,"catégorie inconnue",LOOKUP(N174,Catégories!A:A,Catégories!B:B)) | AE174: =SUM(Z174:AB174)
B175: 13617723 | C175: 0 | D175: 46167 | E175: 21320 | F175: 1325KG | G175: FR | H175: NL | I175: Scholtus ME | J175: Laruche | K175: 999999 | L175: XF143259360FR | M175: N | N175: Transport | O175: N | P175: S | Q175: Z1 | R175: 0.882 | S175: 17 | T175: 9.94 | U175: LA RUCHE LOGISTIQUE | W175: =IF(C175<>2,"",IF(S175="5X","5XK",IF(S175="5Y","5YK",IF(S175="6B","6BK",IF(S175="6C","6CK",""))))) | X175: =IF(S175="6B",_xlfn.XLOOKUP(H175,'Zoning 2shop'!A:A,'Zoning 2shop'!B:B),IF(S175="6C",_xlfn.XLOOKUP(G175,'Zoning 2shop'!C:C,'Zoning 2shop'!D:D),"")) | Y175: =AB175/Z175 | Z175: =T175 | AA175: =IF(OR(S175="6C",S175="6B",S175="5X",S175="5Y"),0.08,0.5) | AB175: =$AG$5/$AG$2*Z175 | AC175: =Z175+AA175 | AD175: =IF(COUNTIF(Catégories!A:A,N175)=0,"catégorie inconnue",LOOKUP(N175,Catégories!A:A,Catégories!B:B)) | AE175: =SUM(Z175:AB175)
B176: 13617723 | C176: 0 | D176: 46167 | E176: 21320 | F176: 93059 | G176: FR | H176: DE | I176: Rugamer Lena | J176: Laruche | K176: 999999 | L176: XF143259475FR | M176: N | N176: Transport | O176: N | P176: S | Q176: Z1 | R176: 4.532 | S176: 17 | T176: 19.47 | U176: LA RUCHE LOGISTIQUE | W176: =IF(C176<>2,"",IF(S176="5X","5XK",IF(S176="5Y","5YK",IF(S176="6B","6BK",IF(S176="6C","6CK",""))))) | X176: =IF(S176="6B",_xlfn.XLOOKUP(H176,'Zoning 2shop'!A:A,'Zoning 2shop'!B:B),IF(S176="6C",_xlfn.XLOOKUP(G176,'Zoning 2shop'!C:C,'Zoning 2shop'!D:D),"")) | Y176: =AB176/Z176 | Z176: =T176 | AA176: =IF(OR(S176="6C",S176="6B",S176="5X",S176="5Y"),0.08,0.5) | AB176: =$AG$5/$AG$2*Z176 | AC176: =Z176+AA176 | AD176: =IF(COUNTIF(Catégories!A:A,N176)=0,"catégorie inconnue",LOOKUP(N176,Catégories!A:A,Catégories!B:B)) | AE176: =SUM(Z176:AB176)
... B233: 13617723 | C233: 0 | D233: 46169 | E233: 21320 | F233: 1141KG | G233: FR | H233: NL | I233: Post Patrick | J233: Laruche | K233: 999999 | L233: XF143372554FR | M233: N | N233: Transport | O233: N | P233: S | Q233: Z1 | R233: 1.307 | S233: 17 | T233: 11.56 | U233: LA RUCHE LOGISTIQUE | W233: =IF(C233<>2,"",IF(S233="5X","5XK",IF(S233="5Y","5YK",IF(S233="6B","6BK",IF(S233="6C","6CK",""))))) | X233: =IF(S233="6B",_xlfn.XLOOKUP(H233,'Zoning 2shop'!A:A,'Zoning 2shop'!B:B),IF(S233="6C",_xlfn.XLOOKUP(G233,'Zoning 2shop'!C:C,'Zoning 2shop'!D:D),"")) | Y233: =AB233/Z233 | Z233: =T233 | AA233: =IF(OR(S233="6C",S233="6B",S233="5X",S233="5Y"),0.08,0.5) | AB233: =$AG$5/$AG$2*Z233 | AC233: =Z233+AA233 | AD233: =IF(COUNTIF(Catégories!A:A,N233)=0,"catégorie inconnue",LOOKUP(N233,Catégories!A:A,Catégories!B:B)) | AE233: =SUM(Z233:AB233)
B234: 13617723 | C234: 0 | D234: 46169 | E234: 21320 | F234: 1141KG | G234: FR | H234: NL | I234: Post Patrick | J234: Laruche | K234: 999999 | L234: XF143372554FR | M234: N | N234: Supplement Etiquette Non Conforme | O234: N | Q234: Z1 | R234: 0 | S234: 17 | T234: 2 | U234: LA RUCHE LOGISTIQUE | W234: =IF(C234<>2,"",IF(S234="5X","5XK",IF(S234="5Y","5YK",IF(S234="6B","6BK",IF(S234="6C","6CK",""))))) | X234: =IF(S234="6B",_xlfn.XLOOKUP(H234,'Zoning 2shop'!A:A,'Zoning 2shop'!B:B),IF(S234="6C",_xlfn.XLOOKUP(G234,'Zoning 2shop'!C:C,'Zoning 2shop'!D:D),"")) | Y234: =AB234/Z234 | Z234: =T234 | AA234: =IF(OR(S234="6C",S234="6B",S234="5X",S234="5Y"),0.08,0.5) | AB234: =$AG$5/$AG$2*Z234 | AC234: =Z234+AA234 | AD234: =IF(COUNTIF(Catégories!A:A,N234)=0,"catégorie inconnue",LOOKUP(N234,Catégories!A:A,Catégories!B:B)) | AE234: =SUM(Z234:AB234)
B235: 13617723 | C235: 0 | D235: 46169 | E235: 21320 | F235: 20070 | G235: FR | H235: IT | I235: Fusco Marco | J235: Laruche | K235: 999999 | L235: XF143372979FR | M235: N | N235: Transport | O235: N | P235: S | Q235: Z2 | R235: 0.583 | S235: 17 | T235: 9.94 | U235: LA RUCHE LOGISTIQUE | W235: =IF(C235<>2,"",IF(S235="5X","5XK",IF(S235="5Y","5YK",IF(S235="6B","6BK",IF(S235="6C","6CK",""))))) | X235: =IF(S235="6B",_xlfn.XLOOKUP(H235,'Zoning 2shop'!A:A,'Zoning 2shop'!B:B),IF(S235="6C",_xlfn.XLOOKUP(G235,'Zoning 2shop'!C:C,'Zoning 2shop'!D:D),"")) | Y235: =AB235/Z235 | Z235: =T235 | AA235: =IF(OR(S235="6C",S235="6B",S235="5X",S235="5Y"),0.08,0.5) | AB235: =$AG$5/$AG$2*Z235 | AC235: =Z235+AA235 | AD235: =IF(COUNTIF(Catégories!A:A,N235)=0,"catégorie inconnue",LOOKUP(N235,Catégories!A:A,Catégories!B:B)) | AE235: =SUM(Z235:AB235)
B236: 13617723 | C236: 0 | D236: 46169 | E236: 21320 | F236: 51588 | G236: FR | H236: DE | I236: Nasimzadah-Lalee Faranus | J236: Laruche | K236: 999999 | L236: XF143373081FR | M236: N | N236: Transport | O236: N | P236: S | Q236: Z1 | R236: 4.638 | S236: 17 | T236: 19.47 | U236: LA RUCHE LOGISTIQUE | W236: =IF(C236<>2,"",IF(S236="5X","5XK",IF(S236="5Y","5YK",IF(S236="6B","6BK",IF(S236="6C","6CK",""))))) | X236: =IF(S236="6B",_xlfn.XLOOKUP(H236,'Zoning 2shop'!A:A,'Zoning 2shop'!B:B),IF(S236="6C",_xlfn.XLOOKUP(G236,'Zoning 2shop'!C:C,'Zoning 2shop'!D:D),"")) | Y236: =AB236/Z236 | Z236: =T236 | AA236: =IF(OR(S236="6C",S236="6B",S236="5X",S236="5Y"),0.08,0.5) | AB236: =$AG$5/$AG$2*Z236 | AC236: =Z236+AA236 | AD236: =IF(COUNTIF(Catégories!A:A,N236)=0,"catégorie inconnue",LOOKUP(N236,Catégories!A:A,Catégories!B:B)) | AE236: =SUM(Z236:AB236)
B237: 13617723 | C237: 0 | D237: 46169 | E237: 21320 | F237: 25421 | G237: FR | H237: DE | I237: Bandorf Philip | J237: Laruche | K237: 999999 | L237: XF143373325FR | M237: N | N237: Transport | O237: N | P237: S | Q237: Z1 | R237: 4.678 | S237: 17 | T237: 19.47 | U237: LA RUCHE LOGISTIQUE | W237: =IF(C237<>2,"",IF(S237="5X","5XK",IF(S237="5Y","5YK",IF(S237="6B","6BK",IF(S237="6C","6CK",""))))) | X237: =IF(S237="6B",_xlfn.XLOOKUP(H237,'Zoning 2shop'!A:A,'Zoning 2shop'!B:B),IF(S237="6C",_xlfn.XLOOKUP(G237,'Zoning 2shop'!C:C,'Zoning 2shop'!D:D),"")) | Y237: =AB237/Z237 | Z237: =T237 | AA237: =IF(OR(S237="6C",S237="6B",S237="5X",S237="5Y"),0.08,0.5) | AB237: =$AG$5/$AG$2*Z237 | AC237: =Z237+AA237 | AD237: =IF(COUNTIF(Catégories!A:A,N237)=0,"catégorie inconnue",LOOKUP(N237,Catégories!A:A,Catégories!B:B)) | AE237: =SUM(Z237:AB237)
B238: 13617723 | C238: 0 | D238: 46169 | E238: 21320 | F238: 80804 | G238: FR | H238: DE | I238: Mendez Carrillo Miguelangel | J238: Laruche | K238: 999999 | L238: XF143373395FR | M238: N | N238: Transport | O238: N | P238: S | Q238: Z1 | R238: 0.931 | S238: 17 | T238: 9.94 | U238: LA RUCHE LOGISTIQUE | W238: =IF(C238<>2,"",IF(S238="5X","5XK",IF(S238="5Y","5YK",IF(S238="6B","6BK",IF(S238="6C","6CK",""))))) | X238: =IF(S238="6B",_xlfn.XLOOKUP(H238,'Zoning 2shop'!A:A,'Zoning 2shop'!B:B),IF(S238="6C",_xlfn.XLOOKUP(G238,'Zoning 2shop'!C:C,'Zoning 2shop'!D:D),"")) | Y238: =AB238/Z238 | Z238: =T238 | AA238: =IF(OR(S238="6C",S238="6B",S238="5X",S238="5Y"),0.08,0.5) | AB238: =$AG$5/$AG$2*Z238 | AC238: =Z238+AA238 | AD238: =IF(COUNTIF(Catégories!A:A,N238)=0,"catégorie inconnue",LOOKUP(N238,Catégories!A:A,Catégories!B:B)) | AE238: =SUM(Z238:AB238)
B239: 13617723 | C239: 0 | D239: 46169 | E239: 21320 | F239: 31620 | G239: FR | H239: ES | I239: Ainciburu Elena | J239: Laruche | K239: 999999 | L239: XF143374966FR | M239: N | N239: Transport | O239: N | P239: S | Q239: Z2 | R239: 4.836 | S239: 17 | T239: 19.47 | U239: LA RUCHE LOGISTIQUE | W239: =IF(C239<>2,"",IF(S239="5X","5XK",IF(S239="5Y","5YK",IF(S239="6B","6BK",IF(S239="6C","6CK",""))))) | X239: =IF(S239="6B",_xlfn.XLOOKUP(H239,'Zoning 2shop'!A:A,'Zoning 2shop'!B:B),IF(S239="6C",_xlfn.XLOOKUP(G239,'Zoning 2shop'!C:C,'Zoning 2shop'!D:D),"")) | Y239: =AB239/Z239 | Z239: =T239 | AA239: =IF(OR(S239="6C",S239="6B",S239="5X",S239="5Y"),0.08,0.5) | AB239: =$AG$5/$AG$2*Z239 | AC239: =Z239+AA239 | AD239: =IF(COUNTIF(Catégories!A:A,N239)=0,"catégorie inconnue",LOOKUP(N239,Catégories!A:A,Catégories!B:B)) | AE239: =SUM(Z239:AB239)
B240: 13617723 | C240: 0 | D240: 46169 | E240: 21320 | F240: 79364 | G240: FR | H240: DE | I240: Peikert Anna | J240: Laruche | K240: 999999 | L240: XF143389197FR | M240: N | N240: Transport | O240: N | P240: S | Q240: Z1 | R240: 4.825 | S240: 17 | T240: 19.47 | U240: LA RUCHE LOGISTIQUE | W240: =IF(C240<>2,"",IF(S240="5X","5XK",IF(S240="5Y","5YK",IF(S240="6B","6BK",IF(S240="6C","6CK",""))))) | X240: =IF(S240="6B",_xlfn.XLOOKUP(H240,'Zoning 2shop'!A:A,'Zoning 2shop'!B:B),IF(S240="6C",_xlfn.XLOOKUP(G240,'Zoning 2shop'!C:C,'Zoning 2shop'!D:D),"")) | Y240: =AB240/Z240 | Z240: =T240 | AA240: =IF(OR(S240="6C",S240="6B",S240="5X",S240="5Y"),0.08,0.5) | AB240: =$AG$5/$AG$2*Z240 | AC240: =Z240+AA240 | AD240: =IF(COUNTIF(Catégories!A:A,N240)=0,"catégorie inconnue",LOOKUP(N240,Catégories!A:A,Catégories!B:B)) | AE240: =SUM(Z240:AB240)
B241: 13617723 | C241: 0 | D241: 46169 | E241: 21320 | F241: 66130 | G241: FR | H241: DE | I241: Wolff monika | J241: Laruche | K241: 999999 | L241: XF143389308FR | M241: N | N241: Transport | O241: N | P241: S | Q241: Z1 | R241: 0.26 | S241: 17 | T241: 7.86 | U241: LA RUCHE LOGISTIQUE | W241: =IF(C241<>2,"",IF(S241="5X","5XK",IF(S241="5Y","5YK",IF(S241="6B","6BK",IF(S241="6C","6CK",""))))) | X241: =IF(S241="6B",_xlfn.XLOOKUP(H241,'Zoning 2shop'!A:A,'Zoning 2shop'!B:B),IF(S241="6C",_xlfn.XLOOKUP(G241,'Zoning 2shop'!C:C,'Zoning 2shop'!D:D),"")) | Y241: =AB241/Z241 | Z241: =T241 | AA241: =IF(OR(S241="6C",S241="6B",S241="5X",S241="5Y"),0.08,0.5) | AB241: =$AG$5/$AG$2*Z241 | AC241: =Z241+AA241 | AD241: =IF(COUNTIF(Catégories!A:A,N241)=0,"catégorie inconnue",LOOKUP(N241,Catégories!A:A,Catégories!B:B)) | AE241: =SUM(Z241:AB241)
B242: 13617723 | C242: 0 | D242: 46169 | E242: 21320 | F242: 97502 | G242: FR | H242: DE | I242: Handel Natascha | J242: Laruche | K242: 999999 | L242: XF143411187FR | M242: N | N242: Transport | O242: N | P242: S | Q242: Z1 | R242: 1.786 | S242: 17 | T242: 12.69 | U242: LA RUCHE LOGISTIQUE | W242: =IF(C242<>2,"",IF(S242="5X","5XK",IF(S242="5Y","5YK",IF(S242="6B","6BK",IF(S242="6C","6CK",""))))) | X242: =IF(S242="6B",_xlfn.XLOOKUP(H242,'Zoning 2shop'!A:A,'Zoning 2shop'!B:B),IF(S242="6C",_xlfn.XLOOKUP(G242,'Zoning 2shop'!C:C,'Zoning 2shop'!D:D),"")) | Y242: =AB242/Z242 | Z242: =T242 | AA242: =IF(OR(S242="6C",S242="6B",S242="5X",S242="5Y"),0.08,0.5) | AB242: =$AG$5/$AG$2*Z242 | AC242: =Z242+AA242 | AD242: =IF(COUNTIF(Catégories!A:A,N242)=0,"catégorie inconnue",LOOKUP(N242,Catégories!A:A,Catégories!B:B)) | AE242: =SUM(Z242:AB242)
B243: 13617723 | C243: 0 | D243: 46169 | E243: 21320 | F243: 61267 | G243: FR | H243: DE | I243: Rentel Karl-Heinz | J243: Laruche | K243: 999999 | L243: XF143412443FR | M243: N | N243: Transport | O243: N | P243: S | Q243: Z1 | R243: 6.273 | S243: 17 | T243: 23.01 | U243: LA RUCHE LOGISTIQUE | W243: =IF(C243<>2,"",IF(S243="5X","5XK",IF(S243="5Y","5YK",IF(S243="6B","6BK",IF(S243="6C","6CK",""))))) | X243: =IF(S243="6B",_xlfn.XLOOKUP(H243,'Zoning 2shop'!A:A,'Zoning 2shop'!B:B),IF(S243="6C",_xlfn.XLOOKUP(G243,'Zoning 2shop'!C:C,'Zoning 2shop'!D:D),"")) | Y243: =AB243/Z243 | Z243: =T243 | AA243: =IF(OR(S243="6C",S243="6B",S243="5X",S243="5Y"),0.08,0.5) | AB243: =$AG$5/$AG$2*Z243 | AC243: =Z243+AA243 | AD243: =IF(COUNTIF(Catégories!A:A,N243)=0,"catégorie inconnue",LOOKUP(N243,Catégories!A:A,Catégories!B:B)) | AE243: =SUM(Z243:AB243)
B244: 13617723 | C244: 0 | D244: 46169 | E244: 21320 | F244: 20141 | G244: FR | H244: IT | I244: Gambardella Antonella | J244: Laruche | K244: 999999 | L244: XF143412810FR | M244: N | N244: Transport | O244: N | P244: S | Q244: Z2 | R244: 0.768 | S244: 17 | T244: 9.94 | U244: LA RUCHE LOGISTIQUE | W244: =IF(C244<>2,"",IF(S244="5X","5XK",IF(S244="5Y","5YK",IF(S244="6B","6BK",IF(S244="6C","6CK",""))))) | X244: =IF(S244="6B",_xlfn.XLOOKUP(H244,'Zoning 2shop'!A:A,'Zoning 2shop'!B:B),IF(S244="6C",_xlfn.XLOOKUP(G244,'Zoning 2shop'!C:C,'Zoning 2shop'!D:D),"")) | Y244: =AB244/Z244 | Z244: =T244 | AA244: =IF(OR(S244="6C",S244="6B",S244="5X",S244="5Y"),0.08,0.5) | AB244: =$AG$5/$AG$2*Z244 | AC244: =Z244+AA244 | AD244: =IF(COUNTIF(Catégories!A:A,N244)=0,"catégorie inconnue",LOOKUP(N244,Catégories!A:A,Catégories!B:B)) | AE244: =SUM(Z244:AB244)
B245: 13617723 | C245: 0 | D245: 46170 | E245: 21320 | F245: 3441EE | G245: FR | H245: NL | I245: ter Steege Yannick | J245: Laruche | K245: 999999 | L245: XF143442365FR | M245: N | N245: Transport | O245: N | P245: S | Q245: Z1 | R245: 1.271 | S245: 17 | T245: 11.56 | U245: LA RUCHE LOGISTIQUE | W245: =IF(C245<>2,"",IF(S245="5X","5XK",IF(S245="5Y","5YK",IF(S245="6B","6BK",IF(S245="6C","6CK",""))))) | X245: =IF(S245="6B",_xlfn.XLOOKUP(H245,'Zoning 2shop'!A:A,'Zoning 2shop'!B:B),IF(S245="6C",_xlfn.XLOOKUP(G245,'Zoning 2shop'!C:C,'Zoning 2shop'!D:D),"")) | Y245: =AB245/Z245 | Z245: =T245 | AA245: =IF(OR(S245="6C",S245="6B",S245="5X",S245="5Y"),0.08,0.5) | AB245: =$AG$5/$AG$2*Z245 | AC245: =Z245+AA245 | AD245: =IF(COUNTIF(Catégories!A:A,N245)=0,"catégorie inconnue",LOOKUP(N245,Catégories!A:A,Catégories!B:B)) | AE245: =SUM(Z245:AB245)
B246: 13617723 | C246: 0 | D246: 46170 | E246: 21320 | F246: 17480 | G246: FR | H246: ES | I246: Singh Rohit | J246: Laruche | K246: 999999 | L246: XF143442975FR | M246: N | N246: Transport | O246: N | P246: S | Q246: Z2 | R246: 0.185 | S246: 17 | T246: 7.86 | U246: LA RUCHE LOGISTIQUE | W246: =IF(C246<>2,"",IF(S246="5X","5XK",IF(S246="5Y","5YK",IF(S246="6B","6BK",IF(S246="6C","6CK",""))))) | X246: =IF(S246="6B",_xlfn.XLOOKUP(H246,'Zoning 2shop'!A:A,'Zoning 2shop'!B:B),IF(S246="6C",_xlfn.XLOOKUP(G246,'Zoning 2shop'!C:C,'Zoning 2shop'!D:D),"")) | Y246: =AB246/Z246 | Z246: =T246 | AA246: =IF(OR(S246="6C",S246="6B",S246="5X",S246="5Y"),0.08,0.5) | AB246: =$AG$5/$AG$2*Z246 | AC246: =Z246+AA246 | AD246: =IF(COUNTIF(Catégories!A:A,N246)=0,"catégorie inconnue",LOOKUP(N246,Catégories!A:A,Catégories!B:B)) | AE246: =SUM(Z246:AB246)
... B262: 13617723 | C262: 0 | D262: 46171 | E262: 21320 | F262: 20359 | G262: FR | H262: DE | I262: Sonnichsen Godja | J262: Laruche | K262: 999999 | L262: XF143542443FR | M262: N | N262: Transport | O262: N | P262: S | Q262: Z1 | R262: 4.266 | S262: 17 | T262: 18.34 | U262: LA RUCHE LOGISTIQUE | W262: =IF(C262<>2,"",IF(S262="5X","5XK",IF(S262="5Y","5YK",IF(S262="6B","6BK",IF(S262="6C","6CK",""))))) | X262: =IF(S262="6B",_xlfn.XLOOKUP(H262,'Zoning 2shop'!A:A,'Zoning 2shop'!B:B),IF(S262="6C",_xlfn.XLOOKUP(G262,'Zoning 2shop'!C:C,'Zoning 2shop'!D:D),"")) | Y262: =AB262/Z262 | Z262: =T262 | AA262: =IF(OR(S262="6C",S262="6B",S262="5X",S262="5Y"),0.08,0.5) | AB262: =$AG$5/$AG$2*Z262 | AC262: =Z262+AA262 | AD262: =IF(COUNTIF(Catégories!A:A,N262)=0,"catégorie inconnue",LOOKUP(N262,Catégories!A:A,Catégories!B:B)) | AE262: =SUM(Z262:AB262)
B263: 13617721 | C263: 0 | D263: 46146 | E263: 21320 | F263: 06500 | I263: GUERRETTA NELLY | J263: Laruche | K263: 999999 | L263: XN091315302JB | M263: N | N263: Transport | O263: N | P263: S | Q263: NT | R263: 4.638 | S263: 16 | T263: 8.6 | U263: LA RUCHE LOGISTIQUE | W263: =IF(C263<>2,"",IF(S263="5X","5XK",IF(S263="5Y","5YK",IF(S263="6B","6BK",IF(S263="6C","6CK",""))))) | X263: =IF(S263="6B",_xlfn.XLOOKUP(H263,'Zoning 2shop'!A:A,'Zoning 2shop'!B:B),IF(S263="6C",_xlfn.XLOOKUP(G263,'Zoning 2shop'!C:C,'Zoning 2shop'!D:D),"")) | Y263: =AB263/Z263 | Z263: =T263 | AA263: =IF(OR(S263="6C",S263="6B",S263="5X",S263="5Y"),0.08,0.5) | AB263: =$AG$5/$AG$2*Z263 | AC263: =Z263+AA263 | AD263: =IF(COUNTIF(Catégories!A:A,N263)=0,"catégorie inconnue",LOOKUP(N263,Catégories!A:A,Catégories!B:B)) | AE263: =SUM(Z263:AB263)
B264: 13617721 | C264: 0 | D264: 46146 | E264: 21320 | F264: 75016 | I264: Cherif Myriam | J264: Laruche | K264: 999999 | L264: XN091319600JB | M264: N | N264: Transport | O264: N | P264: S | Q264: NT | R264: 0.05 | S264: 16 | T264: 7 | U264: LA RUCHE LOGISTIQUE | W264: =IF(C264<>2,"",IF(S264="5X","5XK",IF(S264="5Y","5YK",IF(S264="6B","6BK",IF(S264="6C","6CK",""))))) | X264: =IF(S264="6B",_xlfn.XLOOKUP(H264,'Zoning 2shop'!A:A,'Zoning 2shop'!B:B),IF(S264="6C",_xlfn.XLOOKUP(G264,'Zoning 2shop'!C:C,'Zoning 2shop'!D:D),"")) | Y264: =AB264/Z264 | Z264: =T264 | AA264: =IF(OR(S264="6C",S264="6B",S264="5X",S264="5Y"),0.08,0.5) | AB264: =$AG$5/$AG$2*Z264 | AC264: =Z264+AA264 | AD264: =IF(COUNTIF(Catégories!A:A,N264)=0,"catégorie inconnue",LOOKUP(N264,Catégories!A:A,Catégories!B:B)) | AE264: =SUM(Z264:AB264)
B265: 13617721 | C265: 0 | D265: 46146 | E265: 21320 | F265: 34340 | I265: Palpacuer Lydie | J265: Laruche | K265: 999999 | L265: XN091324437JB | M265: N | N265: Transport | O265: N | P265: S | Q265: NT | R265: 0.42 | S265: 16 | T265: 7 | U265: LA RUCHE LOGISTIQUE | W265: =IF(C265<>2,"",IF(S265="5X","5XK",IF(S265="5Y","5YK",IF(S265="6B","6BK",IF(S265="6C","6CK",""))))) | X265: =IF(S265="6B",_xlfn.XLOOKUP(H265,'Zoning 2shop'!A:A,'Zoning 2shop'!B:B),IF(S265="6C",_xlfn.XLOOKUP(G265,'Zoning 2shop'!C:C,'Zoning 2shop'!D:D),"")) | Y265: =AB265/Z265 | Z265: =T265 | AA265: =IF(OR(S265="6C",S265="6B",S265="5X",S265="5Y"),0.08,0.5) | AB265: =$AG$5/$AG$2*Z265 | AC265: =Z265+AA265 | AD265: =IF(COUNTIF(Catégories!A:A,N265)=0,"catégorie inconnue",LOOKUP(N265,Catégories!A:A,Catégories!B:B)) | AE265: =SUM(Z265:AB265)
B266: 13617721 | C266: 0 | D266: 46146 | E266: 21320 | F266: 59247 | I266: longuepee domonique | J266: Laruche | K266: 999999 | L266: XN091329575JB | M266: N | N266: Transport | O266: N | P266: S | Q266: NT | R266: 4.787 | S266: 16 | T266: 8.6 | U266: LA RUCHE LOGISTIQUE | W266: =IF(C266<>2,"",IF(S266="5X","5XK",IF(S266="5Y","5YK",IF(S266="6B","6BK",IF(S266="6C","6CK",""))))) | X266: =IF(S266="6B",_xlfn.XLOOKUP(H266,'Zoning 2shop'!A:A,'Zoning 2shop'!B:B),IF(S266="6C",_xlfn.XLOOKUP(G266,'Zoning 2shop'!C:C,'Zoning 2shop'!D:D),"")) | Y266: =AB266/Z266 | Z266: =T266 | AA266: =IF(OR(S266="6C",S266="6B",S266="5X",S266="5Y"),0.08,0.5) | AB266: =$AG$5/$AG$2*Z266 | AC266: =Z266+AA266 | AD266: =IF(COUNTIF(Catégories!A:A,N266)=0,"catégorie inconnue",LOOKUP(N266,Catégories!A:A,Catégories!B:B)) | AE266: =SUM(Z266:AB266)
B267: 13617721 | C267: 0 | D267: 46146 | E267: 21320 | F267: 75015 | I267: TRINCA Giancarlo | J267: Laruche | K267: 999999 | L267: XN091366012JB | M267: N | N267: Transport | O267: N | P267: S | Q267: NT | R267: 0.05 | S267: 16 | T267: 7 | U267: LA RUCHE LOGISTIQUE | W267: =IF(C267<>2,"",IF(S267="5X","5XK",IF(S267="5Y","5YK",IF(S267="6B","6BK",IF(S267="6C","6CK",""))))) | X267: =IF(S267="6B",_xlfn.XLOOKUP(H267,'Zoning 2shop'!A:A,'Zoning 2shop'!B:B),IF(S267="6C",_xlfn.XLOOKUP(G267,'Zoning 2shop'!C:C,'Zoning 2shop'!D:D),"")) | Y267: =AB267/Z267 | Z267: =T267 | AA267: =IF(OR(S267="6C",S267="6B",S267="5X",S267="5Y"),0.08,0.5) | AB267: =$AG$5/$AG$2*Z267 | AC267: =Z267+AA267 | AD267: =IF(COUNTIF(Catégories!A:A,N267)=0,"catégorie inconnue",LOOKUP(N267,Catégories!A:A,Catégories!B:B)) | AE267: =SUM(Z267:AB267)
B268: 13617721 | C268: 0 | D268: 46146 | E268: 21320 | F268: 35620 | I268: Le Berre Julien | J268: Laruche | K268: 999999 | L268: XN091366851JB | M268: N | N268: Transport | O268: N | P268: S | Q268: NT | R268: 0.27 | S268: 16 | T268: 7 | U268: LA RUCHE LOGISTIQUE | W268: =IF(C268<>2,"",IF(S268="5X","5XK",IF(S268="5Y","5YK",IF(S268="6B","6BK",IF(S268="6C","6CK",""))))) | X268: =IF(S268="6B",_xlfn.XLOOKUP(H268,'Zoning 2shop'!A:A,'Zoning 2shop'!B:B),IF(S268="6C",_xlfn.XLOOKUP(G268,'Zoning 2shop'!C:C,'Zoning 2shop'!D:D),"")) | Y268: =AB268/Z268 | Z268: =T268 | AA268: =IF(OR(S268="6C",S268="6B",S268="5X",S268="5Y"),0.08,0.5) | AB268: =$AG$5/$AG$2*Z268 | AC268: =Z268+AA268 | AD268: =IF(COUNTIF(Catégories!A:A,N268)=0,"catégorie inconnue",LOOKUP(N268,Catégories!A:A,Catégories!B:B)) | AE268: =SUM(Z268:AB268)
B269: 13617721 | C269: 0 | D269: 46146 | E269: 21320 | F269: 69870 | I269: DROIN Helene | J269: Laruche | K269: 999999 | L269: XN091373398JB | M269: N | N269: Transport | O269: N | P269: S | Q269: NT | R269: 4.638 | S269: 16 | T269: 8.6 | U269: LA RUCHE LOGISTIQUE | W269: =IF(C269<>2,"",IF(S269="5X","5XK",IF(S269="5Y","5YK",IF(S269="6B","6BK",IF(S269="6C","6CK",""))))) | X269: =IF(S269="6B",_xlfn.XLOOKUP(H269,'Zoning 2shop'!A:A,'Zoning 2shop'!B:B),IF(S269="6C",_xlfn.XLOOKUP(G269,'Zoning 2shop'!C:C,'Zoning 2shop'!D:D),"")) | Y269: =AB269/Z269 | Z269: =T269 | AA269: =IF(OR(S269="6C",S269="6B",S269="5X",S269="5Y"),0.08,0.5) | AB269: =$AG$5/$AG$2*Z269 | AC269: =Z269+AA269 | AD269: =IF(COUNTIF(Catégories!A:A,N269)=0,"catégorie inconnue",LOOKUP(N269,Catégories!A:A,Catégories!B:B)) | AE269: =SUM(Z269:AB269)
B270: 13617721 | C270: 0 | D270: 46146 | E270: 21320 | F270: 69008 | I270: Eloundou Eleana | J270: Laruche | K270: 999999 | L270: XN091386652JB | M270: N | N270: Transport | O270: N | P270: S | Q270: NT | R270: 4.678 | S270: 16 | T270: 8.6 | U270: LA RUCHE LOGISTIQUE | W270: =IF(C270<>2,"",IF(S270="5X","5XK",IF(S270="5Y","5YK",IF(S270="6B","6BK",IF(S270="6C","6CK",""))))) | X270: =IF(S270="6B",_xlfn.XLOOKUP(H270,'Zoning 2shop'!A:A,'Zoning 2shop'!B:B),IF(S270="6C",_xlfn.XLOOKUP(G270,'Zoning 2shop'!C:C,'Zoning 2shop'!D:D),"")) | Y270: =AB270/Z270 | Z270: =T270 | AA270: =IF(OR(S270="6C",S270="6B",S270="5X",S270="5Y"),0.08,0.5) | AB270: =$AG$5/$AG$2*Z270 | AC270: =Z270+AA270 | AD270: =IF(COUNTIF(Catégories!A:A,N270)=0,"catégorie inconnue",LOOKUP(N270,Catégories!A:A,Catégories!B:B)) | AE270: =SUM(Z270:AB270)
B271: 13617721 | C271: 0 | D271: 46146 | E271: 21320 | F271: 74400 | I271: Fournier Lucie | J271: Laruche | K271: 999999 | L271: XN091740021JB | M271: N | N271: Transport | O271: N | P271: S | Q271: NT | R271: 4.532 | S271: 16 | T271: 8.6 | U271: LA RUCHE LOGISTIQUE | W271: =IF(C271<>2,"",IF(S271="5X","5XK",IF(S271="5Y","5YK",IF(S271="6B","6BK",IF(S271="6C","6CK",""))))) | X271: =IF(S271="6B",_xlfn.XLOOKUP(H271,'Zoning 2shop'!A:A,'Zoning 2shop'!B:B),IF(S271="6C",_xlfn.XLOOKUP(G271,'Zoning 2shop'!C:C,'Zoning 2shop'!D:D),"")) | Y271: =AB271/Z271 | Z271: =T271 | AA271: =IF(OR(S271="6C",S271="6B",S271="5X",S271="5Y"),0.08,0.5) | AB271: =$AG$5/$AG$2*Z271 | AC271: =Z271+AA271 | AD271: =IF(COUNTIF(Catégories!A:A,N271)=0,"catégorie inconnue",LOOKUP(N271,Catégories!A:A,Catégories!B:B)) | AE271: =SUM(Z271:AB271)
B272: 13617721 | C272: 0 | D272: 46146 | E272: 21320 | F272: 74400 | I272: Fournier Lucie | J272: Laruche | K272: 999999 | L272: XN091740021JB | M272: N | N272: Zones Difficiles d'accès | O272: N | Q272: NT | R272: 0 | S272: 16 | T272: 5 | U272: LA RUCHE LOGISTIQUE | W272: =IF(C272<>2,"",IF(S272="5X","5XK",IF(S272="5Y","5YK",IF(S272="6B","6BK",IF(S272="6C","6CK",""))))) | X272: =IF(S272="6B",_xlfn.XLOOKUP(H272,'Zoning 2shop'!A:A,'Zoning 2shop'!B:B),IF(S272="6C",_xlfn.XLOOKUP(G272,'Zoning 2shop'!C:C,'Zoning 2shop'!D:D),"")) | Y272: =AB272/Z272 | Z272: =T272 | AA272: =IF(OR(S272="6C",S272="6B",S272="5X",S272="5Y"),0.08,0.5) | AB272: =$AG$5/$AG$2*Z272 | AC272: =Z272+AA272 | AD272: =IF(COUNTIF(Catégories!A:A,N272)=0,"catégorie inconnue",LOOKUP(N272,Catégories!A:A,Catégories!B:B)) | AE272: =SUM(Z272:AB272)
B273: 13617721 | C273: 0 | D273: 46146 | E273: 21320 | F273: 30300 | I273: CHAUDON Nelson | J273: Laruche | K273: 999999 | L273: XN091799248JB | M273: N | N273: Transport | O273: N | P273: S | Q273: NT | R273: 2.153 | S273: 16 | T273: 7.8 | U273: LA RUCHE LOGISTIQUE | W273: =IF(C273<>2,"",IF(S273="5X","5XK",IF(S273="5Y","5YK",IF(S273="6B","6BK",IF(S273="6C","6CK",""))))) | X273: =IF(S273="6B",_xlfn.XLOOKUP(H273,'Zoning 2shop'!A:A,'Zoning 2shop'!B:B),IF(S273="6C",_xlfn.XLOOKUP(G273,'Zoning 2shop'!C:C,'Zoning 2shop'!D:D),"")) | Y273: =AB273/Z273 | Z273: =T273 | AA273: =IF(OR(S273="6C",S273="6B",S273="5X",S273="5Y"),0.08,0.5) | AB273: =$AG$5/$AG$2*Z273 | AC273: =Z273+AA273 | AD273: =IF(COUNTIF(Catégories!A:A,N273)=0,"catégorie inconnue",LOOKUP(N273,Catégories!A:A,Catégories!B:B)) | AE273: =SUM(Z273:AB273)
B274: 13617721 | C274: 0 | D274: 46146 | E274: 21320 | F274: 22800 | I274: Durand Antoine | J274: Laruche | K274: 999999 | L274: XN091825098JB | M274: N | N274: Transport | O274: N | P274: S | Q274: NT | R274: 1.04 | S274: 16 | T274: 7.4 | U274: LA RUCHE LOGISTIQUE | W274: =IF(C274<>2,"",IF(S274="5X","5XK",IF(S274="5Y","5YK",IF(S274="6B","6BK",IF(S274="6C","6CK",""))))) | X274: =IF(S274="6B",_xlfn.XLOOKUP(H274,'Zoning 2shop'!A:A,'Zoning 2shop'!B:B),IF(S274="6C",_xlfn.XLOOKUP(G274,'Zoning 2shop'!C:C,'Zoning 2shop'!D:D),"")) | Y274: =AB274/Z274 | Z274: =T274 | AA274: =IF(OR(S274="6C",S274="6B",S274="5X",S274="5Y"),0.08,0.5) | AB274: =$AG$5/$AG$2*Z274 | AC274: =Z274+AA274 | AD274: =IF(COUNTIF(Catégories!A:A,N274)=0,"catégorie inconnue",LOOKUP(N274,Catégories!A:A,Catégories!B:B)) | AE274: =SUM(Z274:AB274)
B275: 13617721 | C275: 0 | D275: 46146 | E275: 21320 | F275: 57070 | I275: El Bouari Nouralhouda | J275: Laruche | K275: 999999 | L275: XN091856064JB | M275: N | N275: Transport | O275: N | P275: S | Q275: NT | R275: 0.391 | S275: 16 | T275: 7 | U275: LA RUCHE LOGISTIQUE | W275: =IF(C275<>2,"",IF(S275="5X","5XK",IF(S275="5Y","5YK",IF(S275="6B","6BK",IF(S275="6C","6CK",""))))) | X275: =IF(S275="6B",_xlfn.XLOOKUP(H275,'Zoning 2shop'!A:A,'Zoning 2shop'!B:B),IF(S275="6C",_xlfn.XLOOKUP(G275,'Zoning 2shop'!C:C,'Zoning 2shop'!D:D),"")) | Y275: =AB275/Z275 | Z275: =T275 | AA275: =IF(OR(S275="6C",S275="6B",S275="5X",S275="5Y"),0.08,0.5) | AB275: =$AG$5/$AG$2*Z275 | AC275: =Z275+AA275 | AD275: =IF(COUNTIF(Catégories!A:A,N275)=0,"catégorie inconnue",LOOKUP(N275,Catégories!A:A,Catégories!B:B)) | AE275: =SUM(Z275:AB275)
...

Sheet TCD poids
A1: Étiquettes de lignes | B1: Somme de Poids | C1: Poids arrondi
A2: CAPI1 | B2: 0 | C2: =ROUNDUP(B2,1)
A3: CAPI2 | B3: 0 | C3: =ROUNDUP(B3,1)
A4: CAPN1 | B4: 0 | C4: =ROUNDUP(B4,1)
A5: CAPN2 | B5: 0 | C5: =ROUNDUP(B5,1)
A6: CAPO1 | B6: 0 | C6: =ROUNDUP(B6,1)
A7: ECORI | B7: 0 | C7: =ROUNDUP(B7,1)
A8: ECORN | B8: 0 | C8: =ROUNDUP(B8,1)
A9: ECORO | B9: 0 | C9: =ROUNDUP(B9,1)
A10: SURTI | B10: 0 | C10: =ROUNDUP(B10,1)
A11: SURTN | B11: 0 | C11: =ROUNDUP(B11,1)
A12: SURTO | B12: 0 | C12: =ROUNDUP(B12,1)
A13: XF142220606FR | B13: 0.783 | C13: =ROUNDUP(B13,1)
... A2208: XY514004567JB | B2208: 0.2 | C2208: =ROUNDUP(B2208,1)
A2209: (vide) | C2209: =ROUNDUP(B2209,1)

Sheet TCD
A1: Total GO | B1: Total avec CAP + ECO… | C1: Total hors GO | D1: ID client | E1: Somme de Montant HT | I1: Catégories | X1: Gazole + facturation + divers
E2: Numero LT | F2: Produit | G2: TVA | H2: Zone Tarifaire | I2: Adresse | J2: Assurance | K2: Colis volumineux | L2: Corse | M2: Droits et taxes | N2: Frais facturation | O2: Frêt | P2: Gazole | Q2: Zones éloignées | R2: (vide) | S2: Sureté + eco | U2: zone | V2: Transporteur | W2: Frêt + CAP + ECO… (hors gazole) | X2: =SUM(N$3:N$1048576)+SUM(P$3:P$1048576)+SUM(O3:O13) | Y2: Formule Test a vérifier | Z2: Vérif avec ancienne formule
E3: CAPI1 | F3: X | G3: I | H3: XX | P3: 42.11 | S3: =_xlfn.XLOOKUP(E3,'Facture Chronopost'!L:L,'Facture Chronopost'!AA:AA,"") | T3: =IF(COUNTIF('Bibliothèque transporteurs'!C:C,F3)=0,"inconnu",_xlfn.XLOOKUP(F3,'Bibliothèque transporteurs'!C:C,'Bibliothèque transporteurs'!A:A)) | U3: =IF(OR(F3="6C",F3="6B"),_xlfn.XLOOKUP(E3,'Facture Chronopost'!L:L,'Facture Chronopost'!X:X),IF(OR(F3=17,F3=44),F3&"_"&H3,IF(COUNTIF('Bibliothèque transporteurs'!C:C,F3)=0,"inconnu",_xlfn.XLOOKUP(F3,'Bibliothèque transporteurs'!C:C,'Bibliothèque transporteurs'!B:B)))) | V3: =IF(COUNTIF('Bibliothèque transporteurs'!C:C,F3)=0,"inconnu",_xlfn.XLOOKUP(F3,'Bibliothèque transporteurs'!C:C,'Bibliothèque transporteurs'!E:E))
E4: CAPI2 | F4: X | G4: I | H4: XX | P4: 55.57 | S4: =_xlfn.XLOOKUP(E4,'Facture Chronopost'!L:L,'Facture Chronopost'!AA:AA,"") | T4: =IF(COUNTIF('Bibliothèque transporteurs'!C:C,F4)=0,"inconnu",_xlfn.XLOOKUP(F4,'Bibliothèque transporteurs'!C:C,'Bibliothèque transporteurs'!A:A)) | U4: =IF(OR(F4="6C",F4="6B"),_xlfn.XLOOKUP(E4,'Facture Chronopost'!L:L,'Facture Chronopost'!X:X),IF(OR(F4=17,F4=44),F4&"_"&H4,IF(COUNTIF('Bibliothèque transporteurs'!C:C,F4)=0,"inconnu",_xlfn.XLOOKUP(F4,'Bibliothèque transporteurs'!C:C,'Bibliothèque transporteurs'!B:B)))) | V4: =IF(COUNTIF('Bibliothèque transporteurs'!C:C,F4)=0,"inconnu",_xlfn.XLOOKUP(F4,'Bibliothèque transporteurs'!C:C,'Bibliothèque transporteurs'!E:E))
E5: CAPN1 | F5: X | G5: N | H5: XX | P5: 1534.86 | S5: =_xlfn.XLOOKUP(E5,'Facture Chronopost'!L:L,'Facture Chronopost'!AA:AA,"") | T5: =IF(COUNTIF('Bibliothèque transporteurs'!C:C,F5)=0,"inconnu",_xlfn.XLOOKUP(F5,'Bibliothèque transporteurs'!C:C,'Bibliothèque transporteurs'!A:A)) | U5: =IF(OR(F5="6C",F5="6B"),_xlfn.XLOOKUP(E5,'Facture Chronopost'!L:L,'Facture Chronopost'!X:X),IF(OR(F5=17,F5=44),F5&"_"&H5,IF(COUNTIF('Bibliothèque transporteurs'!C:C,F5)=0,"inconnu",_xlfn.XLOOKUP(F5,'Bibliothèque transporteurs'!C:C,'Bibliothèque transporteurs'!B:B)))) | V5: =IF(COUNTIF('Bibliothèque transporteurs'!C:C,F5)=0,"inconnu",_xlfn.XLOOKUP(F5,'Bibliothèque transporteurs'!C:C,'Bibliothèque transporteurs'!E:E))
E6: CAPN2 | F6: X | G6: N | H6: XX | P6: 1025.67 | S6: =_xlfn.XLOOKUP(E6,'Facture Chronopost'!L:L,'Facture Chronopost'!AA:AA,"") | T6: =IF(COUNTIF('Bibliothèque transporteurs'!C:C,F6)=0,"inconnu",_xlfn.XLOOKUP(F6,'Bibliothèque transporteurs'!C:C,'Bibliothèque transporteurs'!A:A)) | U6: =IF(OR(F6="6C",F6="6B"),_xlfn.XLOOKUP(E6,'Facture Chronopost'!L:L,'Facture Chronopost'!X:X),IF(OR(F6=17,F6=44),F6&"_"&H6,IF(COUNTIF('Bibliothèque transporteurs'!C:C,F6)=0,"inconnu",_xlfn.XLOOKUP(F6,'Bibliothèque transporteurs'!C:C,'Bibliothèque transporteurs'!B:B)))) | V6: =IF(COUNTIF('Bibliothèque transporteurs'!C:C,F6)=0,"inconnu",_xlfn.XLOOKUP(F6,'Bibliothèque transporteurs'!C:C,'Bibliothèque transporteurs'!E:E))
E7: CAPO1 | F7: X | G7: O | H7: XX | P7: 18.19 | S7: =_xlfn.XLOOKUP(E7,'Facture Chronopost'!L:L,'Facture Chronopost'!AA:AA,"") | T7: =IF(COUNTIF('Bibliothèque transporteurs'!C:C,F7)=0,"inconnu",_xlfn.XLOOKUP(F7,'Bibliothèque transporteurs'!C:C,'Bibliothèque transporteurs'!A:A)) | U7: =IF(OR(F7="6C",F7="6B"),_xlfn.XLOOKUP(E7,'Facture Chronopost'!L:L,'Facture Chronopost'!X:X),IF(OR(F7=17,F7=44),F7&"_"&H7,IF(COUNTIF('Bibliothèque transporteurs'!C:C,F7)=0,"inconnu",_xlfn.XLOOKUP(F7,'Bibliothèque transporteurs'!C:C,'Bibliothèque transporteurs'!B:B)))) | V7: =IF(COUNTIF('Bibliothèque transporteurs'!C:C,F7)=0,"inconnu",_xlfn.XLOOKUP(F7,'Bibliothèque transporteurs'!C:C,'Bibliothèque transporteurs'!E:E))
E8: ECORI | F8: X | G8: I | H8: XX | O8: 3.7 | S8: =_xlfn.XLOOKUP(E8,'Facture Chronopost'!L:L,'Facture Chronopost'!AA:AA,"") | T8: =IF(COUNTIF('Bibliothèque transporteurs'!C:C,F8)=0,"inconnu",_xlfn.XLOOKUP(F8,'Bibliothèque transporteurs'!C:C,'Bibliothèque transporteurs'!A:A)) | U8: =IF(OR(F8="6C",F8="6B"),_xlfn.XLOOKUP(E8,'Facture Chronopost'!L:L,'Facture Chronopost'!X:X),IF(OR(F8=17,F8=44),F8&"_"&H8,IF(COUNTIF('Bibliothèque transporteurs'!C:C,F8)=0,"inconnu",_xlfn.XLOOKUP(F8,'Bibliothèque transporteurs'!C:C,'Bibliothèque transporteurs'!B:B)))) | V8: =IF(COUNTIF('Bibliothèque transporteurs'!C:C,F8)=0,"inconnu",_xlfn.XLOOKUP(F8,'Bibliothèque transporteurs'!C:C,'Bibliothèque transporteurs'!E:E))
E9: ECORN | F9: X | G9: N | H9: XX | O9: 118.7 | S9: =_xlfn.XLOOKUP(E9,'Facture Chronopost'!L:L,'Facture Chronopost'!AA:AA,"") | T9: =IF(COUNTIF('Bibliothèque transporteurs'!C:C,F9)=0,"inconnu",_xlfn.XLOOKUP(F9,'Bibliothèque transporteurs'!C:C,'Bibliothèque transporteurs'!A:A)) | U9: =IF(OR(F9="6C",F9="6B"),_xlfn.XLOOKUP(E9,'Facture Chronopost'!L:L,'Facture Chronopost'!X:X),IF(OR(F9=17,F9=44),F9&"_"&H9,IF(COUNTIF('Bibliothèque transporteurs'!C:C,F9)=0,"inconnu",_xlfn.XLOOKUP(F9,'Bibliothèque transporteurs'!C:C,'Bibliothèque transporteurs'!B:B)))) | V9: =IF(COUNTIF('Bibliothèque transporteurs'!C:C,F9)=0,"inconnu",_xlfn.XLOOKUP(F9,'Bibliothèque transporteurs'!C:C,'Bibliothèque transporteurs'!E:E))
A10: =C10/SUM(C:C)*(SUM(C:C)+$X$2) | B10: =C10/SUM(C:C)*(SUM(C:C)+SUM($N$3:$O$7))+S10 | C10: =SUM(I10:Q10)-N10-P10 | E10: ECORO | F10: X | G10: O | H10: XX | O10: 0.1 | S10: =_xlfn.XLOOKUP(E10,'Facture Chronopost'!L:L,'Facture Chronopost'!AA:AA,"") | T10: =IF(COUNTIF('Bibliothèque transporteurs'!C:C,F10)=0,"inconnu",_xlfn.XLOOKUP(F10,'Bibliothèque transporteurs'!C:C,'Bibliothèque transporteurs'!A:A)) | U10: =IF(OR(F10="6C",F10="6B"),_xlfn.XLOOKUP(E10,'Facture Chronopost'!L:L,'Facture Chronopost'!X:X),IF(OR(F10=17,F10=44),F10&"_"&H10,IF(COUNTIF('Bibliothèque transporteurs'!C:C,F10)=0,"inconnu",_xlfn.XLOOKUP(F10,'Bibliothèque transporteurs'!C:C,'Bibliothèque transporteurs'!B:B)))) | V10: =IF(COUNTIF('Bibliothèque transporteurs'!C:C,F10)=0,"inconnu",_xlfn.XLOOKUP(F10,'Bibliothèque transporteurs'!C:C,'Bibliothèque transporteurs'!E:E)) | W10: =IF(T10="FR_2SHOP",O10,IF(O10=0,0,ROUNDUP(O10/C10*B10,2))) | Y10: =ROUNDUP(B10,2)-M10-L10-N10-J10-K10-I10-Q10 | Z10: =IF(Y10=W10,"OK","Non")
A11: =C11/SUM(C:C)*(SUM(C:C)+$X$2) | B11: =C11/SUM(C:C)*(SUM(C:C)+SUM($N$3:$O$7))+S11 | C11: =SUM(I11:Q11)-N11-P11 | E11: SURTI | F11: X | G11: I | H11: XX | O11: 14.8 | S11: =_xlfn.XLOOKUP(E11,'Facture Chronopost'!L:L,'Facture Chronopost'!AA:AA,"") | T11: =IF(COUNTIF('Bibliothèque transporteurs'!C:C,F11)=0,"inconnu",_xlfn.XLOOKUP(F11,'Bibliothèque transporteurs'!C:C,'Bibliothèque transporteurs'!A:A)) | U11: =IF(OR(F11="6C",F11="6B"),_xlfn.XLOOKUP(E11,'Facture Chronopost'!L:L,'Facture Chronopost'!X:X),IF(OR(F11=17,F11=44),F11&"_"&H11,IF(COUNTIF('Bibliothèque transporteurs'!C:C,F11)=0,"inconnu",_xlfn.XLOOKUP(F11,'Bibliothèque transporteurs'!C:C,'Bibliothèque transporteurs'!B:B)))) | V11: =IF(COUNTIF('Bibliothèque transporteurs'!C:C,F11)=0,"inconnu",_xlfn.XLOOKUP(F11,'Bibliothèque transporteurs'!C:C,'Bibliothèque transporteurs'!E:E)) | W11: =IF(T11="FR_2SHOP",O11,IF(O11=0,0,ROUNDUP(O11/C11*B11,2))) | Y11: =ROUNDUP(B11,2)-M11-L11-N11-J11-K11-I11-Q11 | Z11: =IF(Y11=W11,"OK","Non")
A12: =C12/SUM(C:C)*(SUM(C:C)+$X$2) | B12: =C12/SUM(C:C)*(SUM(C:C)+SUM($N$3:$O$7))+S12 | C12: =SUM(I12:Q12)-N12-P12 | E12: SURTN | F12: X | G12: N | H12: XX | O12: 378.2 | S12: =_xlfn.XLOOKUP(E12,'Facture Chronopost'!L:L,'Facture Chronopost'!AA:AA,"") | T12: =IF(COUNTIF('Bibliothèque transporteurs'!C:C,F12)=0,"inconnu",_xlfn.XLOOKUP(F12,'Bibliothèque transporteurs'!C:C,'Bibliothèque transporteurs'!A:A)) | U12: =IF(OR(F12="6C",F12="6B"),_xlfn.XLOOKUP(E12,'Facture Chronopost'!L:L,'Facture Chronopost'!X:X),IF(OR(F12=17,F12=44),F12&"_"&H12,IF(COUNTIF('Bibliothèque transporteurs'!C:C,F12)=0,"inconnu",_xlfn.XLOOKUP(F12,'Bibliothèque transporteurs'!C:C,'Bibliothèque transporteurs'!B:B)))) | V12: =IF(COUNTIF('Bibliothèque transporteurs'!C:C,F12)=0,"inconnu",_xlfn.XLOOKUP(F12,'Bibliothèque transporteurs'!C:C,'Bibliothèque transporteurs'!E:E)) | W12: =IF(T12="FR_2SHOP",O12,IF(O12=0,0,ROUNDUP(O12/C12*B12,2))) | Y12: =ROUNDUP(B12,2)-M12-L12-N12-J12-K12-I12-Q12 | Z12: =IF(Y12=W12,"OK","Non")
A13: =C13/SUM(C:C)*(SUM(C:C)+$X$2) | B13: =C13/SUM(C:C)*(SUM(C:C)+SUM($N$3:$O$7))+S13 | C13: =SUM(I13:Q13)-N13-P13 | E13: SURTO | F13: X | G13: O | H13: XX | O13: 0.4 | S13: =_xlfn.XLOOKUP(E13,'Facture Chronopost'!L:L,'Facture Chronopost'!AA:AA,"") | T13: =IF(COUNTIF('Bibliothèque transporteurs'!C:C,F13)=0,"inconnu",_xlfn.XLOOKUP(F13,'Bibliothèque transporteurs'!C:C,'Bibliothèque transporteurs'!A:A)) | U13: =IF(OR(F13="6C",F13="6B"),_xlfn.XLOOKUP(E13,'Facture Chronopost'!L:L,'Facture Chronopost'!X:X),IF(OR(F13=17,F13=44),F13&"_"&H13,IF(COUNTIF('Bibliothèque transporteurs'!C:C,F13)=0,"inconnu",_xlfn.XLOOKUP(F13,'Bibliothèque transporteurs'!C:C,'Bibliothèque transporteurs'!B:B)))) | V13: =IF(COUNTIF('Bibliothèque transporteurs'!C:C,F13)=0,"inconnu",_xlfn.XLOOKUP(F13,'Bibliothèque transporteurs'!C:C,'Bibliothèque transporteurs'!E:E)) | W13: =IF(T13="FR_2SHOP",O13,IF(O13=0,0,ROUNDUP(O13/C13*B13,2))) | Y13: =ROUNDUP(B13,2)-M13-L13-N13-J13-K13-I13-Q13 | Z13: =IF(Y13=W13,"OK","Non")
A14: =C14/SUM(C:C)*(SUM(C:C)+$X$2) | B14: =C14/SUM(C:C)*(SUM(C:C)+SUM($N$3:$O$7))+S14 | C14: =SUM(I14:Q14)-N14-P14 | D14: 6235 | E14: XF142220606FR | F14: 17 | G14: N | H14: Z1 | O14: 9.94 | S14: =_xlfn.XLOOKUP(E14,'Facture Chronopost'!L:L,'Facture Chronopost'!AA:AA,"") | T14: =IF(COUNTIF('Bibliothèque transporteurs'!C:C,F14)=0,"inconnu",_xlfn.XLOOKUP(F14,'Bibliothèque transporteurs'!C:C,'Bibliothèque transporteurs'!A:A)) | U14: =IF(OR(F14="6C",F14="6B"),_xlfn.XLOOKUP(E14,'Facture Chronopost'!L:L,'Facture Chronopost'!X:X),IF(OR(F14=17,F14=44),F14&"_"&H14,IF(COUNTIF('Bibliothèque transporteurs'!C:C,F14)=0,"inconnu",_xlfn.XLOOKUP(F14,'Bibliothèque transporteurs'!C:C,'Bibliothèque transporteurs'!B:B)))) | V14: =IF(COUNTIF('Bibliothèque transporteurs'!C:C,F14)=0,"inconnu",_xlfn.XLOOKUP(F14,'Bibliothèque transporteurs'!C:C,'Bibliothèque transporteurs'!E:E)) | W14: =IF(T14="FR_2SHOP",O14,IF(O14=0,0,ROUNDUP(O14/C14*B14,2))) | Y14: =ROUNDUP(B14,2)-M14-L14-N14-J14-K14-I14-Q14 | Z14: =IF(Y14=W14,"OK","Non")
A15: =C15/SUM(C:C)*(SUM(C:C)+$X$2) | B15: =C15/SUM(C:C)*(SUM(C:C)+SUM($N$3:$O$7))+S15 | C15: =SUM(I15:Q15)-N15-P15 | D15: 6235 | E15: XF142220708FR | F15: 17 | G15: N | H15: Z1 | O15: 19.47 | S15: =_xlfn.XLOOKUP(E15,'Facture Chronopost'!L:L,'Facture Chronopost'!AA:AA,"") | T15: =IF(COUNTIF('Bibliothèque transporteurs'!C:C,F15)=0,"inconnu",_xlfn.XLOOKUP(F15,'Bibliothèque transporteurs'!C:C,'Bibliothèque transporteurs'!A:A)) | U15: =IF(OR(F15="6C",F15="6B"),_xlfn.XLOOKUP(E15,'Facture Chronopost'!L:L,'Facture Chronopost'!X:X),IF(OR(F15=17,F15=44),F15&"_"&H15,IF(COUNTIF('Bibliothèque transporteurs'!C:C,F15)=0,"inconnu",_xlfn.XLOOKUP(F15,'Bibliothèque transporteurs'!C:C,'Bibliothèque transporteurs'!B:B)))) | V15: =IF(COUNTIF('Bibliothèque transporteurs'!C:C,F15)=0,"inconnu",_xlfn.XLOOKUP(F15,'Bibliothèque transporteurs'!C:C,'Bibliothèque transporteurs'!E:E)) | W15: =IF(T15="FR_2SHOP",O15,IF(O15=0,0,ROUNDUP(O15/C15*B15,2))) | Y15: =ROUNDUP(B15,2)-M15-L15-N15-J15-K15-I15-Q15 | Z15: =IF(Y15=W15,"OK","Non")
A16: =C16/SUM(C:C)*(SUM(C:C)+$X$2) | B16: =C16/SUM(C:C)*(SUM(C:C)+SUM($N$3:$O$7))+S16 | C16: =SUM(I16:Q16)-N16-P16 | D16: 6235 | E16: XF142220932FR | F16: 17 | G16: N | H16: Z1 | O16: 9.94 | S16: =_xlfn.XLOOKUP(E16,'Facture Chronopost'!L:L,'Facture Chronopost'!AA:AA,"") | T16: =IF(COUNTIF('Bibliothèque transporteurs'!C:C,F16)=0,"inconnu",_xlfn.XLOOKUP(F16,'Bibliothèque transporteurs'!C:C,'Bibliothèque transporteurs'!A:A)) | U16: =IF(OR(F16="6C",F16="6B"),_xlfn.XLOOKUP(E16,'Facture Chronopost'!L:L,'Facture Chronopost'!X:X),IF(OR(F16=17,F16=44),F16&"_"&H16,IF(COUNTIF('Bibliothèque transporteurs'!C:C,F16)=0,"inconnu",_xlfn.XLOOKUP(F16,'Bibliothèque transporteurs'!C:C,'Bibliothèque transporteurs'!B:B)))) | V16: =IF(COUNTIF('Bibliothèque transporteurs'!C:C,F16)=0,"inconnu",_xlfn.XLOOKUP(F16,'Bibliothèque transporteurs'!C:C,'Bibliothèque transporteurs'!E:E)) | W16: =IF(T16="FR_2SHOP",O16,IF(O16=0,0,ROUNDUP(O16/C16*B16,2))) | Y16: =ROUNDUP(B16,2)-M16-L16-N16-J16-K16-I16-Q16 | Z16: =IF(Y16=W16,"OK","Non")
A17: =C17/SUM(C:C)*(SUM(C:C)+$X$2) | B17: =C17/SUM(C:C)*(SUM(C:C)+SUM($N$3:$O$7))+S17 | C17: =SUM(I17:Q17)-N17-P17 | D17: 6235 | E17: XF142221116FR | F17: 17 | G17: N | H17: Z1 | O17: 7.86 | S17: =_xlfn.XLOOKUP(E17,'Facture Chronopost'!L:L,'Facture Chronopost'!AA:AA,"") | T17: =IF(COUNTIF('Bibliothèque transporteurs'!C:C,F17)=0,"inconnu",_xlfn.XLOOKUP(F17,'Bibliothèque transporteurs'!C:C,'Bibliothèque transporteurs'!A:A)) | U17: =IF(OR(F17="6C",F17="6B"),_xlfn.XLOOKUP(E17,'Facture Chronopost'!L:L,'Facture Chronopost'!X:X),IF(OR(F17=17,F17=44),F17&"_"&H17,IF(COUNTIF('Bibliothèque transporteurs'!C:C,F17)=0,"inconnu",_xlfn.XLOOKUP(F17,'Bibliothèque transporteurs'!C:C,'Bibliothèque transporteurs'!B:B)))) | V17: =IF(COUNTIF('Bibliothèque transporteurs'!C:C,F17)=0,"inconnu",_xlfn.XLOOKUP(F17,'Bibliothèque transporteurs'!C:C,'Bibliothèque transporteurs'!E:E)) | W17: =IF(T17="FR_2SHOP",O17,IF(O17=0,0,ROUNDUP(O17/C17*B17,2))) | Y17: =ROUNDUP(B17,2)-M17-L17-N17-J17-K17-I17-Q17 | Z17: =IF(Y17=W17,"OK","Non")
A18: =C18/SUM(C:C)*(SUM(C:C)+$X$2) | B18: =C18/SUM(C:C)*(SUM(C:C)+SUM($N$3:$O$7))+S18 | C18: =SUM(I18:Q18)-N18-P18 | D18: 6235 | E18: XF142221147FR | F18: 17 | G18: N | H18: Z3 | O18: 13.35 | S18: =_xlfn.XLOOKUP(E18,'Facture Chronopost'!L:L,'Facture Chronopost'!AA:AA,"") | T18: =IF(COUNTIF('Bibliothèque transporteurs'!C:C,F18)=0,"inconnu",_xlfn.XLOOKUP(F18,'Bibliothèque transporteurs'!C:C,'Bibliothèque transporteurs'!A:A)) | U18: =IF(OR(F18="6C",F18="6B"),_xlfn.XLOOKUP(E18,'Facture Chronopost'!L:L,'Facture Chronopost'!X:X),IF(OR(F18=17,F18=44),F18&"_"&H18,IF(COUNTIF('Bibliothèque transporteurs'!C:C,F18)=0,"inconnu",_xlfn.XLOOKUP(F18,'Bibliothèque transporteurs'!C:C,'Bibliothèque transporteurs'!B:B)))) | V18: =IF(COUNTIF('Bibliothèque transporteurs'!C:C,F18)=0,"inconnu",_xlfn.XLOOKUP(F18,'Bibliothèque transporteurs'!C:C,'Bibliothèque transporteurs'!E:E)) | W18: =IF(T18="FR_2SHOP",O18,IF(O18=0,0,ROUNDUP(O18/C18*B18,2))) | Y18: =ROUNDUP(B18,2)-M18-L18-N18-J18-K18-I18-Q18 | Z18: =IF(Y18=W18,"OK","Non")
A19: =C19/SUM(C:C)*(SUM(C:C)+$X$2) | B19: =C19/SUM(C:C)*(SUM(C:C)+SUM($N$3:$O$7))+S19 | C19: =SUM(I19:Q19)-N19-P19 | D19: 6235 | E19: XF142221677FR | F19: 17 | G19: N | H19: Z2 | O19: 18.34 | S19: =_xlfn.XLOOKUP(E19,'Facture Chronopost'!L:L,'Facture Chronopost'!AA:AA,"") | T19: =IF(COUNTIF('Bibliothèque transporteurs'!C:C,F19)=0,"inconnu",_xlfn.XLOOKUP(F19,'Bibliothèque transporteurs'!C:C,'Bibliothèque transporteurs'!A:A)) | U19: =IF(OR(F19="6C",F19="6B"),_xlfn.XLOOKUP(E19,'Facture Chronopost'!L:L,'Facture Chronopost'!X:X),IF(OR(F19=17,F19=44),F19&"_"&H19,IF(COUNTIF('Bibliothèque transporteurs'!C:C,F19)=0,"inconnu",_xlfn.XLOOKUP(F19,'Bibliothèque transporteurs'!C:C,'Bibliothèque transporteurs'!B:B)))) | V19: =IF(COUNTIF('Bibliothèque transporteurs'!C:C,F19)=0,"inconnu",_xlfn.XLOOKUP(F19,'Bibliothèque transporteurs'!C:C,'Bibliothèque transporteurs'!E:E)) | W19: =IF(T19="FR_2SHOP",O19,IF(O19=0,0,ROUNDUP(O19/C19*B19,2))) | Y19: =ROUNDUP(B19,2)-M19-L19-N19-J19-K19-I19-Q19 | Z19: =IF(Y19=W19,"OK","Non")
A20: =C20/SUM(C:C)*(SUM(C:C)+$X$2) | B20: =C20/SUM(C:C)*(SUM(C:C)+SUM($N$3:$O$7))+S20 | C20: =SUM(I20:Q20)-N20-P20 | D20: 6235 | E20: XF142221779FR | F20: 17 | G20: N | H20: Z1 | O20: 21.83 | S20: =_xlfn.XLOOKUP(E20,'Facture Chronopost'!L:L,'Facture Chronopost'!AA:AA,"") | T20: =IF(COUNTIF('Bibliothèque transporteurs'!C:C,F20)=0,"inconnu",_xlfn.XLOOKUP(F20,'Bibliothèque transporteurs'!C:C,'Bibliothèque transporteurs'!A:A)) | U20: =IF(OR(F20="6C",F20="6B"),_xlfn.XLOOKUP(E20,'Facture Chronopost'!L:L,'Facture Chronopost'!X:X),IF(OR(F20=17,F20=44),F20&"_"&H20,IF(COUNTIF('Bibliothèque transporteurs'!C:C,F20)=0,"inconnu",_xlfn.XLOOKUP(F20,'Bibliothèque transporteurs'!C:C,'Bibliothèque transporteurs'!B:B)))) | V20: =IF(COUNTIF('Bibliothèque transporteurs'!C:C,F20)=0,"inconnu",_xlfn.XLOOKUP(F20,'Bibliothèque transporteurs'!C:C,'Bibliothèque transporteurs'!E:E)) | W20: =IF(T20="FR_2SHOP",O20,IF(O20=0,0,ROUNDUP(O20/C20*B20,2))) | Y20: =ROUNDUP(B20,2)-M20-L20-N20-J20-K20-I20-Q20 | Z20: =IF(Y20=W20,"OK","Non")
A21: =C21/SUM(C:C)*(SUM(C:C)+$X$2) | B21: =C21/SUM(C:C)*(SUM(C:C)+SUM($N$3:$O$7))+S21 | C21: =SUM(I21:Q21)-N21-P21 | D21: 6235 | E21: XF142224761FR | F21: 17 | G21: N | H21: Z2 | O21: 9.94 | S21: =_xlfn.XLOOKUP(E21,'Facture Chronopost'!L:L,'Facture Chronopost'!AA:AA,"") | T21: =IF(COUNTIF('Bibliothèque transporteurs'!C:C,F21)=0,"inconnu",_xlfn.XLOOKUP(F21,'Bibliothèque transporteurs'!C:C,'Bibliothèque transporteurs'!A:A)) | U21: =IF(OR(F21="6C",F21="6B"),_xlfn.XLOOKUP(E21,'Facture Chronopost'!L:L,'Facture Chronopost'!X:X),IF(OR(F21=17,F21=44),F21&"_"&H21,IF(COUNTIF('Bibliothèque transporteurs'!C:C,F21)=0,"inconnu",_xlfn.XLOOKUP(F21,'Bibliothèque transporteurs'!C:C,'Bibliothèque transporteurs'!B:B)))) | V21: =IF(COUNTIF('Bibliothèque transporteurs'!C:C,F21)=0,"inconnu",_xlfn.XLOOKUP(F21,'Bibliothèque transporteurs'!C:C,'Bibliothèque transporteurs'!E:E)) | W21: =IF(T21="FR_2SHOP",O21,IF(O21=0,0,ROUNDUP(O21/C21*B21,2))) | Y21: =ROUNDUP(B21,2)-M21-L21-N21-J21-K21-I21-Q21 | Z21: =IF(Y21=W21,"OK","Non")
A22: =C22/SUM(C:C)*(SUM(C:C)+$X$2) | B22: =C22/SUM(C:C)*(SUM(C:C)+SUM($N$3:$O$7))+S22 | C22: =SUM(I22:Q22)-N22-P22 | D22: 6235 | E22: XF142225206FR | F22: 17 | G22: N | H22: Z1 | O22: 21.83 | S22: =_xlfn.XLOOKUP(E22,'Facture Chronopost'!L:L,'Facture Chronopost'!AA:AA,"") | T22: =IF(COUNTIF('Bibliothèque transporteurs'!C:C,F22)=0,"inconnu",_xlfn.XLOOKUP(F22,'Bibliothèque transporteurs'!C:C,'Bibliothèque transporteurs'!A:A)) | U22: =IF(OR(F22="6C",F22="6B"),_xlfn.XLOOKUP(E22,'Facture Chronopost'!L:L,'Facture Chronopost'!X:X),IF(OR(F22=17,F22=44),F22&"_"&H22,IF(COUNTIF('Bibliothèque transporteurs'!C:C,F22)=0,"inconnu",_xlfn.XLOOKUP(F22,'Bibliothèque transporteurs'!C:C,'Bibliothèque transporteurs'!B:B)))) | V22: =IF(COUNTIF('Bibliothèque transporteurs'!C:C,F22)=0,"inconnu",_xlfn.XLOOKUP(F22,'Bibliothèque transporteurs'!C:C,'Bibliothèque transporteurs'!E:E)) | W22: =IF(T22="FR_2SHOP",O22,IF(O22=0,0,ROUNDUP(O22/C22*B22,2))) | Y22: =ROUNDUP(B22,2)-M22-L22-N22-J22-K22-I22-Q22 | Z22: =IF(Y22=W22,"OK","Non")
A23: =C23/SUM(C:C)*(SUM(C:C)+$X$2) | B23: =C23/SUM(C:C)*(SUM(C:C)+SUM($N$3:$O$7))+S23 | C23: =SUM(I23:Q23)-N23-P23 | D23: 6235 | E23: XF142225223FR | F23: 17 | G23: N | H23: Z1 | O23: 18.34 | S23: =_xlfn.XLOOKUP(E23,'Facture Chronopost'!L:L,'Facture Chronopost'!AA:AA,"") | T23: =IF(COUNTIF('Bibliothèque transporteurs'!C:C,F23)=0,"inconnu",_xlfn.XLOOKUP(F23,'Bibliothèque transporteurs'!C:C,'Bibliothèque transporteurs'!A:A)) | U23: =IF(OR(F23="6C",F23="6B"),_xlfn.XLOOKUP(E23,'Facture Chronopost'!L:L,'Facture Chronopost'!X:X),IF(OR(F23=17,F23=44),F23&"_"&H23,IF(COUNTIF('Bibliothèque transporteurs'!C:C,F23)=0,"inconnu",_xlfn.XLOOKUP(F23,'Bibliothèque transporteurs'!C:C,'Bibliothèque transporteurs'!B:B)))) | V23: =IF(COUNTIF('Bibliothèque transporteurs'!C:C,F23)=0,"inconnu",_xlfn.XLOOKUP(F23,'Bibliothèque transporteurs'!C:C,'Bibliothèque transporteurs'!E:E)) | W23: =IF(T23="FR_2SHOP",O23,IF(O23=0,0,ROUNDUP(O23/C23*B23,2))) | Y23: =ROUNDUP(B23,2)-M23-L23-N23-J23-K23-I23-Q23 | Z23: =IF(Y23=W23,"OK","Non")
A24: =C24/SUM(C:C)*(SUM(C:C)+$X$2) | B24: =C24/SUM(C:C)*(SUM(C:C)+SUM($N$3:$O$7))+S24 | C24: =SUM(I24:Q24)-N24-P24 | D24: 6235 | E24: XF142225342FR | F24: 17 | G24: N | H24: Z1 | O24: 18.34 | S24: =_xlfn.XLOOKUP(E24,'Facture Chronopost'!L:L,'Facture Chronopost'!AA:AA,"") | T24: =IF(COUNTIF('Bibliothèque transporteurs'!C:C,F24)=0,"inconnu",_xlfn.XLOOKUP(F24,'Bibliothèque transporteurs'!C:C,'Bibliothèque transporteurs'!A:A)) | U24: =IF(OR(F24="6C",F24="6B"),_xlfn.XLOOKUP(E24,'Facture Chronopost'!L:L,'Facture Chronopost'!X:X),IF(OR(F24=17,F24=44),F24&"_"&H24,IF(COUNTIF('Bibliothèque transporteurs'!C:C,F24)=0,"inconnu",_xlfn.XLOOKUP(F24,'Bibliothèque transporteurs'!C:C,'Bibliothèque transporteurs'!B:B)))) | V24: =IF(COUNTIF('Bibliothèque transporteurs'!C:C,F24)=0,"inconnu",_xlfn.XLOOKUP(F24,'Bibliothèque transporteurs'!C:C,'Bibliothèque transporteurs'!E:E)) | W24: =IF(T24="FR_2SHOP",O24,IF(O24=0,0,ROUNDUP(O24/C24*B24,2))) | Y24: =ROUNDUP(B24,2)-M24-L24-N24-J24-K24-I24-Q24 | Z24: =IF(Y24=W24,"OK","Non")
A25: =C25/SUM(C:C)*(SUM(C:C)+$X$2) | B25: =C25/SUM(C:C)*(SUM(C:C)+SUM($N$3:$O$7))+S25 | C25: =SUM(I25:Q25)-N25-P25 | D25: 6235 | E25: XF142225838FR | F25: 17 | G25: N | H25: Z1 | O25: 21.83 | S25: =_xlfn.XLOOKUP(E25,'Facture Chronopost'!L:L,'Facture Chronopost'!AA:AA,"") | T25: =IF(COUNTIF('Bibliothèque transporteurs'!C:C,F25)=0,"inconnu",_xlfn.XLOOKUP(F25,'Bibliothèque transporteurs'!C:C,'Bibliothèque transporteurs'!A:A)) | U25: =IF(OR(F25="6C",F25="6B"),_xlfn.XLOOKUP(E25,'Facture Chronopost'!L:L,'Facture Chronopost'!X:X),IF(OR(F25=17,F25=44),F25&"_"&H25,IF(COUNTIF('Bibliothèque transporteurs'!C:C,F25)=0,"inconnu",_xlfn.XLOOKUP(F25,'Bibliothèque transporteurs'!C:C,'Bibliothèque transporteurs'!B:B)))) | V25: =IF(COUNTIF('Bibliothèque transporteurs'!C:C,F25)=0,"inconnu",_xlfn.XLOOKUP(F25,'Bibliothèque transporteurs'!C:C,'Bibliothèque transporteurs'!E:E)) | W25: =IF(T25="FR_2SHOP",O25,IF(O25=0,0,ROUNDUP(O25/C25*B25,2))) | Y25: =ROUNDUP(B25,2)-M25-L25-N25-J25-K25-I25-Q25 | Z25: =IF(Y25=W25,"OK","Non")
... A103: =C103/SUM(C:C)*(SUM(C:C)+$X$2) | B103: =C103/SUM(C:C)*(SUM(C:C)+SUM($N$3:$O$7))+S103 | C103: =SUM(I103:Q103)-N103-P103 | D103: 6235 | E103: XF142970423FR | F103: 17 | G103: N | H103: Z2 | O103: 9.94 | S103: =_xlfn.XLOOKUP(E103,'Facture Chronopost'!L:L,'Facture Chronopost'!AA:AA,"") | T103: =IF(COUNTIF('Bibliothèque transporteurs'!C:C,F103)=0,"inconnu",_xlfn.XLOOKUP(F103,'Bibliothèque transporteurs'!C:C,'Bibliothèque transporteurs'!A:A)) | U103: =IF(OR(F103="6C",F103="6B"),_xlfn.XLOOKUP(E103,'Facture Chronopost'!L:L,'Facture Chronopost'!X:X),IF(OR(F103=17,F103=44),F103&"_"&H103,IF(COUNTIF('Bibliothèque transporteurs'!C:C,F103)=0,"inconnu",_xlfn.XLOOKUP(F103,'Bibliothèque transporteurs'!C:C,'Bibliothèque transporteurs'!B:B)))) | V103: =IF(COUNTIF('Bibliothèque transporteurs'!C:C,F103)=0,"inconnu",_xlfn.XLOOKUP(F103,'Bibliothèque transporteurs'!C:C,'Bibliothèque transporteurs'!E:E)) | W103: =IF(T103="FR_2SHOP",O103,IF(O103=0,0,ROUNDUP(O103/C103*B103,2))) | Y103: =ROUNDUP(B103,2)-M103-L103-N103-J103-K103-I103-Q103 | Z103: =IF(Y103=W103,"OK","Non")
A104: =C104/SUM(C:C)*(SUM(C:C)+$X$2) | B104: =C104/SUM(C:C)*(SUM(C:C)+SUM($N$3:$O$7))+S104 | C104: =SUM(I104:Q104)-N104-P104 | D104: 6235 | E104: XF142970539FR | F104: 17 | G104: N | H104: Z2 | O104: 7.86 | Q104: 17 | S104: =_xlfn.XLOOKUP(E104,'Facture Chronopost'!L:L,'Facture Chronopost'!AA:AA,"") | T104: =IF(COUNTIF('Bibliothèque transporteurs'!C:C,F104)=0,"inconnu",_xlfn.XLOOKUP(F104,'Bibliothèque transporteurs'!C:C,'Bibliothèque transporteurs'!A:A)) | U104: =IF(OR(F104="6C",F104="6B"),_xlfn.XLOOKUP(E104,'Facture Chronopost'!L:L,'Facture Chronopost'!X:X),IF(OR(F104=17,F104=44),F104&"_"&H104,IF(COUNTIF('Bibliothèque transporteurs'!C:C,F104)=0,"inconnu",_xlfn.XLOOKUP(F104,'Bibliothèque transporteurs'!C:C,'Bibliothèque transporteurs'!B:B)))) | V104: =IF(COUNTIF('Bibliothèque transporteurs'!C:C,F104)=0,"inconnu",_xlfn.XLOOKUP(F104,'Bibliothèque transporteurs'!C:C,'Bibliothèque transporteurs'!E:E)) | W104: =IF(T104="FR_2SHOP",O104,IF(O104=0,0,ROUNDUP(O104/C104*B104,2))) | Y104: =ROUNDUP(B104,2)-M104-L104-N104-J104-K104-I104-Q104 | Z104: =IF(Y104=W104,"OK","Non")
A105: =C105/SUM(C:C)*(SUM(C:C)+$X$2) | B105: =C105/SUM(C:C)*(SUM(C:C)+SUM($N$3:$O$7))+S105 | C105: =SUM(I105:Q105)-N105-P105 | D105: 6235 | E105: XF142970715FR | F105: 17 | G105: N | H105: Z1 | O105: 9.94 | S105: =_xlfn.XLOOKUP(E105,'Facture Chronopost'!L:L,'Facture Chronopost'!AA:AA,"") | T105: =IF(COUNTIF('Bibliothèque transporteurs'!C:C,F105)=0,"inconnu",_xlfn.XLOOKUP(F105,'Bibliothèque transporteurs'!C:C,'Bibliothèque transporteurs'!A:A)) | U105: =IF(OR(F105="6C",F105="6B"),_xlfn.XLOOKUP(E105,'Facture Chronopost'!L:L,'Facture Chronopost'!X:X),IF(OR(F105=17,F105=44),F105&"_"&H105,IF(COUNTIF('Bibliothèque transporteurs'!C:C,F105)=0,"inconnu",_xlfn.XLOOKUP(F105,'Bibliothèque transporteurs'!C:C,'Bibliothèque transporteurs'!B:B)))) | V105: =IF(COUNTIF('Bibliothèque transporteurs'!C:C,F105)=0,"inconnu",_xlfn.XLOOKUP(F105,'Bibliothèque transporteurs'!C:C,'Bibliothèque transporteurs'!E:E)) | W105: =IF(T105="FR_2SHOP",O105,IF(O105=0,0,ROUNDUP(O105/C105*B105,2))) | Y105: =ROUNDUP(B105,2)-M105-L105-N105-J105-K105-I105-Q105 | Z105: =IF(Y105=W105,"OK","Non")
A106: =C106/SUM(C:C)*(SUM(C:C)+$X$2) | B106: =C106/SUM(C:C)*(SUM(C:C)+SUM($N$3:$O$7))+S106 | C106: =SUM(I106:Q106)-N106-P106 | D106: 6235 | E106: XF142971004FR | F106: 17 | G106: N | H106: Z1 | O106: 18.34 | S106: =_xlfn.XLOOKUP(E106,'Facture Chronopost'!L:L,'Facture Chronopost'!AA:AA,"") | T106: =IF(COUNTIF('Bibliothèque transporteurs'!C:C,F106)=0,"inconnu",_xlfn.XLOOKUP(F106,'Bibliothèque transporteurs'!C:C,'Bibliothèque transporteurs'!A:A)) | U106: =IF(OR(F106="6C",F106="6B"),_xlfn.XLOOKUP(E106,'Facture Chronopost'!L:L,'Facture Chronopost'!X:X),IF(OR(F106=17,F106=44),F106&"_"&H106,IF(COUNTIF('Bibliothèque transporteurs'!C:C,F106)=0,"inconnu",_xlfn.XLOOKUP(F106,'Bibliothèque transporteurs'!C:C,'Bibliothèque transporteurs'!B:B)))) | V106: =IF(COUNTIF('Bibliothèque transporteurs'!C:C,F106)=0,"inconnu",_xlfn.XLOOKUP(F106,'Bibliothèque transporteurs'!C:C,'Bibliothèque transporteurs'!E:E)) | W106: =IF(T106="FR_2SHOP",O106,IF(O106=0,0,ROUNDUP(O106/C106*B106,2))) | Y106: =ROUNDUP(B106,2)-M106-L106-N106-J106-K106-I106-Q106 | Z106: =IF(Y106=W106,"OK","Non")
A107: =C107/SUM(C:C)*(SUM(C:C)+$X$2) | B107: =C107/SUM(C:C)*(SUM(C:C)+SUM($N$3:$O$7))+S107 | C107: =SUM(I107:Q107)-N107-P107 | D107: 6235 | E107: XF142971110FR | F107: 17 | G107: N | H107: Z1 | O107: 19.47 | S107: =_xlfn.XLOOKUP(E107,'Facture Chronopost'!L:L,'Facture Chronopost'!AA:AA,"") | T107: =IF(COUNTIF('Bibliothèque transporteurs'!C:C,F107)=0,"inconnu",_xlfn.XLOOKUP(F107,'Bibliothèque transporteurs'!C:C,'Bibliothèque transporteurs'!A:A)) | U107: =IF(OR(F107="6C",F107="6B"),_xlfn.XLOOKUP(E107,'Facture Chronopost'!L:L,'Facture Chronopost'!X:X),IF(OR(F107=17,F107=44),F107&"_"&H107,IF(COUNTIF('Bibliothèque transporteurs'!C:C,F107)=0,"inconnu",_xlfn.XLOOKUP(F107,'Bibliothèque transporteurs'!C:C,'Bibliothèque transporteurs'!B:B)))) | V107: =IF(COUNTIF('Bibliothèque transporteurs'!C:C,F107)=0,"inconnu",_xlfn.XLOOKUP(F107,'Bibliothèque transporteurs'!C:C,'Bibliothèque transporteurs'!E:E)) | W107: =IF(T107="FR_2SHOP",O107,IF(O107=0,0,ROUNDUP(O107/C107*B107,2))) | Y107: =ROUNDUP(B107,2)-M107-L107-N107-J107-K107-I107-Q107 | Z107: =IF(Y107=W107,"OK","Non")
A108: =C108/SUM(C:C)*(SUM(C:C)+$X$2) | B108: =C108/SUM(C:C)*(SUM(C:C)+SUM($N$3:$O$7))+S108 | C108: =SUM(I108:Q108)-N108-P108 | D108: 6235 | E108: XF142971199FR | F108: 17 | G108: N | H108: Z1 | O108: 52.86 | S108: =_xlfn.XLOOKUP(E108,'Facture Chronopost'!L:L,'Facture Chronopost'!AA:AA,"") | T108: =IF(COUNTIF('Bibliothèque transporteurs'!C:C,F108)=0,"inconnu",_xlfn.XLOOKUP(F108,'Bibliothèque transporteurs'!C:C,'Bibliothèque transporteurs'!A:A)) | U108: =IF(OR(F108="6C",F108="6B"),_xlfn.XLOOKUP(E108,'Facture Chronopost'!L:L,'Facture Chronopost'!X:X),IF(OR(F108=17,F108=44),F108&"_"&H108,IF(COUNTIF('Bibliothèque transporteurs'!C:C,F108)=0,"inconnu",_xlfn.XLOOKUP(F108,'Bibliothèque transporteurs'!C:C,'Bibliothèque transporteurs'!B:B)))) | V108: =IF(COUNTIF('Bibliothèque transporteurs'!C:C,F108)=0,"inconnu",_xlfn.XLOOKUP(F108,'Bibliothèque transporteurs'!C:C,'Bibliothèque transporteurs'!E:E)) | W108: =IF(T108="FR_2SHOP",O108,IF(O108=0,0,ROUNDUP(O108/C108*B108,2))) | Y108: =ROUNDUP(B108,2)-M108-L108-N108-J108-K108-I108-Q108 | Z108: =IF(Y108=W108,"OK","Non")
A109: =C109/SUM(C:C)*(SUM(C:C)+$X$2) | B109: =C109/SUM(C:C)*(SUM(C:C)+SUM($N$3:$O$7))+S109 | C109: =SUM(I109:Q109)-N109-P109 | D109: 6235 | E109: XF142971211FR | F109: 17 | G109: N | H109: Z1 | O109: 7.86 | S109: =_xlfn.XLOOKUP(E109,'Facture Chronopost'!L:L,'Facture Chronopost'!AA:AA,"") | T109: =IF(COUNTIF('Bibliothèque transporteurs'!C:C,F109)=0,"inconnu",_xlfn.XLOOKUP(F109,'Bibliothèque transporteurs'!C:C,'Bibliothèque transporteurs'!A:A)) | U109: =IF(OR(F109="6C",F109="6B"),_xlfn.XLOOKUP(E109,'Facture Chronopost'!L:L,'Facture Chronopost'!X:X),IF(OR(F109=17,F109=44),F109&"_"&H109,IF(COUNTIF('Bibliothèque transporteurs'!C:C,F109)=0,"inconnu",_xlfn.XLOOKUP(F109,'Bibliothèque transporteurs'!C:C,'Bibliothèque transporteurs'!B:B)))) | V109: =IF(COUNTIF('Bibliothèque transporteurs'!C:C,F109)=0,"inconnu",_xlfn.XLOOKUP(F109,'Bibliothèque transporteurs'!C:C,'Bibliothèque transporteurs'!E:E)) | W109: =IF(T109="FR_2SHOP",O109,IF(O109=0,0,ROUNDUP(O109/C109*B109,2))) | Y109: =ROUNDUP(B109,2)-M109-L109-N109-J109-K109-I109-Q109 | Z109: =IF(Y109=W109,"OK","Non")
A110: =C110/SUM(C:C)*(SUM(C:C)+$X$2) | B110: =C110/SUM(C:C)*(SUM(C:C)+SUM($N$3:$O$7))+S110 | C110: =SUM(I110:Q110)-N110-P110 | D110: 6235 | E110: XF142972163FR | F110: 17 | G110: N | H110: Z2 | O110: 54.94 | S110: =_xlfn.XLOOKUP(E110,'Facture Chronopost'!L:L,'Facture Chronopost'!AA:AA,"") | T110: =IF(COUNTIF('Bibliothèque transporteurs'!C:C,F110)=0,"inconnu",_xlfn.XLOOKUP(F110,'Bibliothèque transporteurs'!C:C,'Bibliothèque transporteurs'!A:A)) | U110: =IF(OR(F110="6C",F110="6B"),_xlfn.XLOOKUP(E110,'Facture Chronopost'!L:L,'Facture Chronopost'!X:X),IF(OR(F110=17,F110=44),F110&"_"&H110,IF(COUNTIF('Bibliothèque transporteurs'!C:C,F110)=0,"inconnu",_xlfn.XLOOKUP(F110,'Bibliothèque transporteurs'!C:C,'Bibliothèque transporteurs'!B:B)))) | V110: =IF(COUNTIF('Bibliothèque transporteurs'!C:C,F110)=0,"inconnu",_xlfn.XLOOKUP(F110,'Bibliothèque transporteurs'!C:C,'Bibliothèque transporteurs'!E:E)) | W110: =IF(T110="FR_2SHOP",O110,IF(O110=0,0,ROUNDUP(O110/C110*B110,2))) | Y110: =ROUNDUP(B110,2)-M110-L110-N110-J110-K110-I110-Q110 | Z110: =IF(Y110=W110,"OK","Non")
A111: =C111/SUM(C:C)*(SUM(C:C)+$X$2) | B111: =C111/SUM(C:C)*(SUM(C:C)+SUM($N$3:$O$7))+S111 | C111: =SUM(I111:Q111)-N111-P111 | D111: 6235 | E111: XF142984025FR | F111: 17 | G111: N | H111: Z1 | O111: 21.83 | S111: =_xlfn.XLOOKUP(E111,'Facture Chronopost'!L:L,'Facture Chronopost'!AA:AA,"") | T111: =IF(COUNTIF('Bibliothèque transporteurs'!C:C,F111)=0,"inconnu",_xlfn.XLOOKUP(F111,'Bibliothèque transporteurs'!C:C,'Bibliothèque transporteurs'!A:A)) | U111: =IF(OR(F111="6C",F111="6B"),_xlfn.XLOOKUP(E111,'Facture Chronopost'!L:L,'Facture Chronopost'!X:X),IF(OR(F111=17,F111=44),F111&"_"&H111,IF(COUNTIF('Bibliothèque transporteurs'!C:C,F111)=0,"inconnu",_xlfn.XLOOKUP(F111,'Bibliothèque transporteurs'!C:C,'Bibliothèque transporteurs'!B:B)))) | V111: =IF(COUNTIF('Bibliothèque transporteurs'!C:C,F111)=0,"inconnu",_xlfn.XLOOKUP(F111,'Bibliothèque transporteurs'!C:C,'Bibliothèque transporteurs'!E:E)) | W111: =IF(T111="FR_2SHOP",O111,IF(O111=0,0,ROUNDUP(O111/C111*B111,2))) | Y111: =ROUNDUP(B111,2)-M111-L111-N111-J111-K111-I111-Q111 | Z111: =IF(Y111=W111,"OK","Non")
A112: =C112/SUM(C:C)*(SUM(C:C)+$X$2) | B112: =C112/SUM(C:C)*(SUM(C:C)+SUM($N$3:$O$7))+S112 | C112: =SUM(I112:Q112)-N112-P112 | D112: 6235 | E112: XF142986471FR | F112: 17 | G112: N | H112: Z1 | O112: 18.34 | S112: =_xlfn.XLOOKUP(E112,'Facture Chronopost'!L:L,'Facture Chronopost'!AA:AA,"") | T112: =IF(COUNTIF('Bibliothèque transporteurs'!C:C,F112)=0,"inconnu",_xlfn.XLOOKUP(F112,'Bibliothèque transporteurs'!C:C,'Bibliothèque transporteurs'!A:A)) | U112: =IF(OR(F112="6C",F112="6B"),_xlfn.XLOOKUP(E112,'Facture Chronopost'!L:L,'Facture Chronopost'!X:X),IF(OR(F112=17,F112=44),F112&"_"&H112,IF(COUNTIF('Bibliothèque transporteurs'!C:C,F112)=0,"inconnu",_xlfn.XLOOKUP(F112,'Bibliothèque transporteurs'!C:C,'Bibliothèque transporteurs'!B:B)))) | V112: =IF(COUNTIF('Bibliothèque transporteurs'!C:C,F112)=0,"inconnu",_xlfn.XLOOKUP(F112,'Bibliothèque transporteurs'!C:C,'Bibliothèque transporteurs'!E:E)) | W112: =IF(T112="FR_2SHOP",O112,IF(O112=0,0,ROUNDUP(O112/C112*B112,2))) | Y112: =ROUNDUP(B112,2)-M112-L112-N112-J112-K112-I112-Q112 | Z112: =IF(Y112=W112,"OK","Non")
A113: =C113/SUM(C:C)*(SUM(C:C)+$X$2) | B113: =C113/SUM(C:C)*(SUM(C:C)+SUM($N$3:$O$7))+S113 | C113: =SUM(I113:Q113)-N113-P113 | D113: 6235 | E113: XF142987123FR | F113: 17 | G113: N | H113: Z1 | O113: 9.94 | S113: =_xlfn.XLOOKUP(E113,'Facture Chronopost'!L:L,'Facture Chronopost'!AA:AA,"") | T113: =IF(COUNTIF('Bibliothèque transporteurs'!C:C,F113)=0,"inconnu",_xlfn.XLOOKUP(F113,'Bibliothèque transporteurs'!C:C,'Bibliothèque transporteurs'!A:A)) | U113: =IF(OR(F113="6C",F113="6B"),_xlfn.XLOOKUP(E113,'Facture Chronopost'!L:L,'Facture Chronopost'!X:X),IF(OR(F113=17,F113=44),F113&"_"&H113,IF(COUNTIF('Bibliothèque transporteurs'!C:C,F113)=0,"inconnu",_xlfn.XLOOKUP(F113,'Bibliothèque transporteurs'!C:C,'Bibliothèque transporteurs'!B:B)))) | V113: =IF(COUNTIF('Bibliothèque transporteurs'!C:C,F113)=0,"inconnu",_xlfn.XLOOKUP(F113,'Bibliothèque transporteurs'!C:C,'Bibliothèque transporteurs'!E:E)) | W113: =IF(T113="FR_2SHOP",O113,IF(O113=0,0,ROUNDUP(O113/C113*B113,2))) | Y113: =ROUNDUP(B113,2)-M113-L113-N113-J113-K113-I113-Q113 | Z113: =IF(Y113=W113,"OK","Non")
A114: =C114/SUM(C:C)*(SUM(C:C)+$X$2) | B114: =C114/SUM(C:C)*(SUM(C:C)+SUM($N$3:$O$7))+S114 | C114: =SUM(I114:Q114)-N114-P114 | D114: 6235 | E114: XF142995487FR | F114: 17 | G114: N | H114: Z2 | O114: 19.47 | S114: =_xlfn.XLOOKUP(E114,'Facture Chronopost'!L:L,'Facture Chronopost'!AA:AA,"") | T114: =IF(COUNTIF('Bibliothèque transporteurs'!C:C,F114)=0,"inconnu",_xlfn.XLOOKUP(F114,'Bibliothèque transporteurs'!C:C,'Bibliothèque transporteurs'!A:A)) | U114: =IF(OR(F114="6C",F114="6B"),_xlfn.XLOOKUP(E114,'Facture Chronopost'!L:L,'Facture Chronopost'!X:X),IF(OR(F114=17,F114=44),F114&"_"&H114,IF(COUNTIF('Bibliothèque transporteurs'!C:C,F114)=0,"inconnu",_xlfn.XLOOKUP(F114,'Bibliothèque transporteurs'!C:C,'Bibliothèque transporteurs'!B:B)))) | V114: =IF(COUNTIF('Bibliothèque transporteurs'!C:C,F114)=0,"inconnu",_xlfn.XLOOKUP(F114,'Bibliothèque transporteurs'!C:C,'Bibliothèque transporteurs'!E:E)) | W114: =IF(T114="FR_2SHOP",O114,IF(O114=0,0,ROUNDUP(O114/C114*B114,2))) | Y114: =ROUNDUP(B114,2)-M114-L114-N114-J114-K114-I114-Q114 | Z114: =IF(Y114=W114,"OK","Non")
A115: =C115/SUM(C:C)*(SUM(C:C)+$X$2) | B115: =C115/SUM(C:C)*(SUM(C:C)+SUM($N$3:$O$7))+S115 | C115: =SUM(I115:Q115)-N115-P115 | D115: 6235 | E115: XF143016663FR | F115: 17 | G115: N | H115: Z1 | O115: 9.94 | S115: =_xlfn.XLOOKUP(E115,'Facture Chronopost'!L:L,'Facture Chronopost'!AA:AA,"") | T115: =IF(COUNTIF('Bibliothèque transporteurs'!C:C,F115)=0,"inconnu",_xlfn.XLOOKUP(F115,'Bibliothèque transporteurs'!C:C,'Bibliothèque transporteurs'!A:A)) | U115: =IF(OR(F115="6C",F115="6B"),_xlfn.XLOOKUP(E115,'Facture Chronopost'!L:L,'Facture Chronopost'!X:X),IF(OR(F115=17,F115=44),F115&"_"&H115,IF(COUNTIF('Bibliothèque transporteurs'!C:C,F115)=0,"inconnu",_xlfn.XLOOKUP(F115,'Bibliothèque transporteurs'!C:C,'Bibliothèque transporteurs'!B:B)))) | V115: =IF(COUNTIF('Bibliothèque transporteurs'!C:C,F115)=0,"inconnu",_xlfn.XLOOKUP(F115,'Bibliothèque transporteurs'!C:C,'Bibliothèque transporteurs'!E:E)) | W115: =IF(T115="FR_2SHOP",O115,IF(O115=0,0,ROUNDUP(O115/C115*B115,2))) | Y115: =ROUNDUP(B115,2)-M115-L115-N115-J115-K115-I115-Q115 | Z115: =IF(Y115=W115,"OK","Non")
A116: =C116/SUM(C:C)*(SUM(C:C)+$X$2) | B116: =C116/SUM(C:C)*(SUM(C:C)+SUM($N$3:$O$7))+S116 | C116: =SUM(I116:Q116)-N116-P116 | D116: 6235 | E116: XF143022641FR | F116: 17 | G116: N | H116: Z1 | O116: 7.86 | S116: =_xlfn.XLOOKUP(E116,'Facture Chronopost'!L:L,'Facture Chronopost'!AA:AA,"") | T116: =IF(COUNTIF('Bibliothèque transporteurs'!C:C,F116)=0,"inconnu",_xlfn.XLOOKUP(F116,'Bibliothèque transporteurs'!C:C,'Bibliothèque transporteurs'!A:A)) | U116: =IF(OR(F116="6C",F116="6B"),_xlfn.XLOOKUP(E116,'Facture Chronopost'!L:L,'Facture Chronopost'!X:X),IF(OR(F116=17,F116=44),F116&"_"&H116,IF(COUNTIF('Bibliothèque transporteurs'!C:C,F116)=0,"inconnu",_xlfn.XLOOKUP(F116,'Bibliothèque transporteurs'!C:C,'Bibliothèque transporteurs'!B:B)))) | V116: =IF(COUNTIF('Bibliothèque transporteurs'!C:C,F116)=0,"inconnu",_xlfn.XLOOKUP(F116,'Bibliothèque transporteurs'!C:C,'Bibliothèque transporteurs'!E:E)) | W116: =IF(T116="FR_2SHOP",O116,IF(O116=0,0,ROUNDUP(O116/C116*B116,2))) | Y116: =ROUNDUP(B116,2)-M116-L116-N116-J116-K116-I116-Q116 | Z116: =IF(Y116=W116,"OK","Non")
... A145: =C145/SUM(C:C)*(SUM(C:C)+$X$2) | B145: =C145/SUM(C:C)*(SUM(C:C)+SUM($N$3:$O$7))+S145 | C145: =SUM(I145:Q145)-N145-P145 | D145: 6235 | E145: XF143199365FR | F145: 17 | G145: N | H145: Z1 | O145: 21.83 | S145: =_xlfn.XLOOKUP(E145,'Facture Chronopost'!L:L,'Facture Chronopost'!AA:AA,"") | T145: =IF(COUNTIF('Bibliothèque transporteurs'!C:C,F145)=0,"inconnu",_xlfn.XLOOKUP(F145,'Bibliothèque transporteurs'!C:C,'Bibliothèque transporteurs'!A:A)) | U145: =IF(OR(F145="6C",F145="6B"),_xlfn.XLOOKUP(E145,'Facture Chronopost'!L:L,'Facture Chronopost'!X:X),IF(OR(F145=17,F145=44),F145&"_"&H145,IF(COUNTIF('Bibliothèque transporteurs'!C:C,F145)=0,"inconnu",_xlfn.XLOOKUP(F145,'Bibliothèque transporteurs'!C:C,'Bibliothèque transporteurs'!B:B)))) | V145: =IF(COUNTIF('Bibliothèque transporteurs'!C:C,F145)=0,"inconnu",_xlfn.XLOOKUP(F145,'Bibliothèque transporteurs'!C:C,'Bibliothèque transporteurs'!E:E)) | W145: =IF(T145="FR_2SHOP",O145,IF(O145=0,0,ROUNDUP(O145/C145*B145,2))) | Y145: =ROUNDUP(B145,2)-M145-L145-N145-J145-K145-I145-Q145 | Z145: =IF(Y145=W145,"OK","Non")
A146: =C146/SUM(C:C)*(SUM(C:C)+$X$2) | B146: =C146/SUM(C:C)*(SUM(C:C)+SUM($N$3:$O$7))+S146 | C146: =SUM(I146:Q146)-N146-P146 | D146: 6235 | E146: XF143199462FR | F146: 17 | G146: N | H146: Z2 | O146: 7.86 | Q146: 17 | S146: =_xlfn.XLOOKUP(E146,'Facture Chronopost'!L:L,'Facture Chronopost'!AA:AA,"") | T146: =IF(COUNTIF('Bibliothèque transporteurs'!C:C,F146)=0,"inconnu",_xlfn.XLOOKUP(F146,'Bibliothèque transporteurs'!C:C,'Bibliothèque transporteurs'!A:A)) | U146: =IF(OR(F146="6C",F146="6B"),_xlfn.XLOOKUP(E146,'Facture Chronopost'!L:L,'Facture Chronopost'!X:X),IF(OR(F146=17,F146=44),F146&"_"&H146,IF(COUNTIF('Bibliothèque transporteurs'!C:C,F146)=0,"inconnu",_xlfn.XLOOKUP(F146,'Bibliothèque transporteurs'!C:C,'Bibliothèque transporteurs'!B:B)))) | V146: =IF(COUNTIF('Bibliothèque transporteurs'!C:C,F146)=0,"inconnu",_xlfn.XLOOKUP(F146,'Bibliothèque transporteurs'!C:C,'Bibliothèque transporteurs'!E:E)) | W146: =IF(T146="FR_2SHOP",O146,IF(O146=0,0,ROUNDUP(O146/C146*B146,2))) | Y146: =ROUNDUP(B146,2)-M146-L146-N146-J146-K146-I146-Q146 | Z146: =IF(Y146=W146,"OK","Non")
A147: =C147/SUM(C:C)*(SUM(C:C)+$X$2) | B147: =C147/SUM(C:C)*(SUM(C:C)+SUM($N$3:$O$7))+S147 | C147: =SUM(I147:Q147)-N147-P147 | D147: 6235 | E147: XF143200109FR | F147: 17 | G147: N | H147: Z1 | O147: 18.34 | S147: =_xlfn.XLOOKUP(E147,'Facture Chronopost'!L:L,'Facture Chronopost'!AA:AA,"") | T147: =IF(COUNTIF('Bibliothèque transporteurs'!C:C,F147)=0,"inconnu",_xlfn.XLOOKUP(F147,'Bibliothèque transporteurs'!C:C,'Bibliothèque transporteurs'!A:A)) | U147: =IF(OR(F147="6C",F147="6B"),_xlfn.XLOOKUP(E147,'Facture Chronopost'!L:L,'Facture Chronopost'!X:X),IF(OR(F147=17,F147=44),F147&"_"&H147,IF(COUNTIF('Bibliothèque transporteurs'!C:C,F147)=0,"inconnu",_xlfn.XLOOKUP(F147,'Bibliothèque transporteurs'!C:C,'Bibliothèque transporteurs'!B:B)))) | V147: =IF(COUNTIF('Bibliothèque transporteurs'!C:C,F147)=0,"inconnu",_xlfn.XLOOKUP(F147,'Bibliothèque transporteurs'!C:C,'Bibliothèque transporteurs'!E:E)) | W147: =IF(T147="FR_2SHOP",O147,IF(O147=0,0,ROUNDUP(O147/C147*B147,2))) | Y147: =ROUNDUP(B147,2)-M147-L147-N147-J147-K147-I147-Q147 | Z147: =IF(Y147=W147,"OK","Non")
A148: =C148/SUM(C:C)*(SUM(C:C)+$X$2) | B148: =C148/SUM(C:C)*(SUM(C:C)+SUM($N$3:$O$7))+S148 | C148: =SUM(I148:Q148)-N148-P148 | D148: 6235 | E148: XF143200143FR | F148: 17 | G148: N | H148: Z2 | O148: 18.34 | S148: =_xlfn.XLOOKUP(E148,'Facture Chronopost'!L:L,'Facture Chronopost'!AA:AA,"") | T148: =IF(COUNTIF('Bibliothèque transporteurs'!C:C,F148)=0,"inconnu",_xlfn.XLOOKUP(F148,'Bibliothèque transporteurs'!C:C,'Bibliothèque transporteurs'!A:A)) | U148: =IF(OR(F148="6C",F148="6B"),_xlfn.XLOOKUP(E148,'Facture Chronopost'!L:L,'Facture Chronopost'!X:X),IF(OR(F148=17,F148=44),F148&"_"&H148,IF(COUNTIF('Bibliothèque transporteurs'!C:C,F148)=0,"inconnu",_xlfn.XLOOKUP(F148,'Bibliothèque transporteurs'!C:C,'Bibliothèque transporteurs'!B:B)))) | V148: =IF(COUNTIF('Bibliothèque transporteurs'!C:C,F148)=0,"inconnu",_xlfn.XLOOKUP(F148,'Bibliothèque transporteurs'!C:C,'Bibliothèque transporteurs'!E:E)) | W148: =IF(T148="FR_2SHOP",O148,IF(O148=0,0,ROUNDUP(O148/C148*B148,2))) | Y148: =ROUNDUP(B148,2)-M148-L148-N148-J148-K148-I148-Q148 | Z148: =IF(Y148=W148,"OK","Non")
A149: =C149/SUM(C:C)*(SUM(C:C)+$X$2) | B149: =C149/SUM(C:C)*(SUM(C:C)+SUM($N$3:$O$7))+S149 | C149: =SUM(I149:Q149)-N149-P149 | D149: 6235 | E149: XF143200228FR | F149: 17 | G149: N | H149: Z1 | O149: 9.94 | S149: =_xlfn.XLOOKUP(E149,'Facture Chronopost'!L:L,'Facture Chronopost'!AA:AA,"") | T149: =IF(COUNTIF('Bibliothèque transporteurs'!C:C,F149)=0,"inconnu",_xlfn.XLOOKUP(F149,'Bibliothèque transporteurs'!C:C,'Bibliothèque transporteurs'!A:A)) | U149: =IF(OR(F149="6C",F149="6B"),_xlfn.XLOOKUP(E149,'Facture Chronopost'!L:L,'Facture Chronopost'!X:X),IF(OR(F149=17,F149=44),F149&"_"&H149,IF(COUNTIF('Bibliothèque transporteurs'!C:C,F149)=0,"inconnu",_xlfn.XLOOKUP(F149,'Bibliothèque transporteurs'!C:C,'Bibliothèque transporteurs'!B:B)))) | V149: =IF(COUNTIF('Bibliothèque transporteurs'!C:C,F149)=0,"inconnu",_xlfn.XLOOKUP(F149,'Bibliothèque transporteurs'!C:C,'Bibliothèque transporteurs'!E:E)) | W149: =IF(T149="FR_2SHOP",O149,IF(O149=0,0,ROUNDUP(O149/C149*B149,2))) | Y149: =ROUNDUP(B149,2)-M149-L149-N149-J149-K149-I149-Q149 | Z149: =IF(Y149=W149,"OK","Non")
A150: =C150/SUM(C:C)*(SUM(C:C)+$X$2) | B150: =C150/SUM(C:C)*(SUM(C:C)+SUM($N$3:$O$7))+S150 | C150: =SUM(I150:Q150)-N150-P150 | D150: 6235 | E150: XF143219706FR | F150: 17 | G150: N | H150: Z1 | O150: 18.34 | S150: =_xlfn.XLOOKUP(E150,'Facture Chronopost'!L:L,'Facture Chronopost'!AA:AA,"") | T150: =IF(COUNTIF('Bibliothèque transporteurs'!C:C,F150)=0,"inconnu",_xlfn.XLOOKUP(F150,'Bibliothèque transporteurs'!C:C,'Bibliothèque transporteurs'!A:A)) | U150: =IF(OR(F150="6C",F150="6B"),_xlfn.XLOOKUP(E150,'Facture Chronopost'!L:L,'Facture Chronopost'!X:X),IF(OR(F150=17,F150=44),F150&"_"&H150,IF(COUNTIF('Bibliothèque transporteurs'!C:C,F150)=0,"inconnu",_xlfn.XLOOKUP(F150,'Bibliothèque transporteurs'!C:C,'Bibliothèque transporteurs'!B:B)))) | V150: =IF(COUNTIF('Bibliothèque transporteurs'!C:C,F150)=0,"inconnu",_xlfn.XLOOKUP(F150,'Bibliothèque transporteurs'!C:C,'Bibliothèque transporteurs'!E:E)) | W150: =IF(T150="FR_2SHOP",O150,IF(O150=0,0,ROUNDUP(O150/C150*B150,2))) | Y150: =ROUNDUP(B150,2)-M150-L150-N150-J150-K150-I150-Q150 | Z150: =IF(Y150=W150,"OK","Non")
A151: =C151/SUM(C:C)*(SUM(C:C)+$X$2) | B151: =C151/SUM(C:C)*(SUM(C:C)+SUM($N$3:$O$7))+S151 | C151: =SUM(I151:Q151)-N151-P151 | D151: 6235 | E151: XF143228518FR | F151: 17 | G151: N | H151: Z1 | O151: 7.86 | S151: =_xlfn.XLOOKUP(E151,'Facture Chronopost'!L:L,'Facture Chronopost'!AA:AA,"") | T151: =IF(COUNTIF('Bibliothèque transporteurs'!C:C,F151)=0,"inconnu",_xlfn.XLOOKUP(F151,'Bibliothèque transporteurs'!C:C,'Bibliothèque transporteurs'!A:A)) | U151: =IF(OR(F151="6C",F151="6B"),_xlfn.XLOOKUP(E151,'Facture Chronopost'!L:L,'Facture Chronopost'!X:X),IF(OR(F151=17,F151=44),F151&"_"&H151,IF(COUNTIF('Bibliothèque transporteurs'!C:C,F151)=0,"inconnu",_xlfn.XLOOKUP(F151,'Bibliothèque transporteurs'!C:C,'Bibliothèque transporteurs'!B:B)))) | V151: =IF(COUNTIF('Bibliothèque transporteurs'!C:C,F151)=0,"inconnu",_xlfn.XLOOKUP(F151,'Bibliothèque transporteurs'!C:C,'Bibliothèque transporteurs'!E:E)) | W151: =IF(T151="FR_2SHOP",O151,IF(O151=0,0,ROUNDUP(O151/C151*B151,2))) | Y151: =ROUNDUP(B151,2)-M151-L151-N151-J151-K151-I151-Q151 | Z151: =IF(Y151=W151,"OK","Non")
A152: =C152/SUM(C:C)*(SUM(C:C)+$X$2) | B152: =C152/SUM(C:C)*(SUM(C:C)+SUM($N$3:$O$7))+S152 | C152: =SUM(I152:Q152)-N152-P152 | D152: 6235 | E152: XF143228739FR | F152: 17 | G152: N | H152: Z1 | O152: 21.83 | S152: =_xlfn.XLOOKUP(E152,'Facture Chronopost'!L:L,'Facture Chronopost'!AA:AA,"") | T152: =IF(COUNTIF('Bibliothèque transporteurs'!C:C,F152)=0,"inconnu",_xlfn.XLOOKUP(F152,'Bibliothèque transporteurs'!C:C,'Bibliothèque transporteurs'!A:A)) | U152: =IF(OR(F152="6C",F152="6B"),_xlfn.XLOOKUP(E152,'Facture Chronopost'!L:L,'Facture Chronopost'!X:X),IF(OR(F152=17,F152=44),F152&"_"&H152,IF(COUNTIF('Bibliothèque transporteurs'!C:C,F152)=0,"inconnu",_xlfn.XLOOKUP(F152,'Bibliothèque transporteurs'!C:C,'Bibliothèque transporteurs'!B:B)))) | V152: =IF(COUNTIF('Bibliothèque transporteurs'!C:C,F152)=0,"inconnu",_xlfn.XLOOKUP(F152,'Bibliothèque transporteurs'!C:C,'Bibliothèque transporteurs'!E:E)) | W152: =IF(T152="FR_2SHOP",O152,IF(O152=0,0,ROUNDUP(O152/C152*B152,2))) | Y152: =ROUNDUP(B152,2)-M152-L152-N152-J152-K152-I152-Q152 | Z152: =IF(Y152=W152,"OK","Non")
A153: =C153/SUM(C:C)*(SUM(C:C)+$X$2) | B153: =C153/SUM(C:C)*(SUM(C:C)+SUM($N$3:$O$7))+S153 | C153: =SUM(I153:Q153)-N153-P153 | D153: 6235 | E153: XF143230091FR | F153: 17 | G153: N | H153: Z1 | O153: 21.83 | S153: =_xlfn.XLOOKUP(E153,'Facture Chronopost'!L:L,'Facture Chronopost'!AA:AA,"") | T153: =IF(COUNTIF('Bibliothèque transporteurs'!C:C,F153)=0,"inconnu",_xlfn.XLOOKUP(F153,'Bibliothèque transporteurs'!C:C,'Bibliothèque transporteurs'!A:A)) | U153: =IF(OR(F153="6C",F153="6B"),_xlfn.XLOOKUP(E153,'Facture Chronopost'!L:L,'Facture Chronopost'!X:X),IF(OR(F153=17,F153=44),F153&"_"&H153,IF(COUNTIF('Bibliothèque transporteurs'!C:C,F153)=0,"inconnu",_xlfn.XLOOKUP(F153,'Bibliothèque transporteurs'!C:C,'Bibliothèque transporteurs'!B:B)))) | V153: =IF(COUNTIF('Bibliothèque transporteurs'!C:C,F153)=0,"inconnu",_xlfn.XLOOKUP(F153,'Bibliothèque transporteurs'!C:C,'Bibliothèque transporteurs'!E:E)) | W153: =IF(T153="FR_2SHOP",O153,IF(O153=0,0,ROUNDUP(O153/C153*B153,2))) | Y153: =ROUNDUP(B153,2)-M153-L153-N153-J153-K153-I153-Q153 | Z153: =IF(Y153=W153,"OK","Non")
A154: =C154/SUM(C:C)*(SUM(C:C)+$X$2) | B154: =C154/SUM(C:C)*(SUM(C:C)+SUM($N$3:$O$7))+S154 | C154: =SUM(I154:Q154)-N154-P154 | D154: 6235 | E154: XF143235641FR | F154: 17 | G154: N | H154: Z1 | O154: 21.83 | S154: =_xlfn.XLOOKUP(E154,'Facture Chronopost'!L:L,'Facture Chronopost'!AA:AA,"") | T154: =IF(COUNTIF('Bibliothèque transporteurs'!C:C,F154)=0,"inconnu",_xlfn.XLOOKUP(F154,'Bibliothèque transporteurs'!C:C,'Bibliothèque transporteurs'!A:A)) | U154: =IF(OR(F154="6C",F154="6B"),_xlfn.XLOOKUP(E154,'Facture Chronopost'!L:L,'Facture Chronopost'!X:X),IF(OR(F154=17,F154=44),F154&"_"&H154,IF(COUNTIF('Bibliothèque transporteurs'!C:C,F154)=0,"inconnu",_xlfn.XLOOKUP(F154,'Bibliothèque transporteurs'!C:C,'Bibliothèque transporteurs'!B:B)))) | V154: =IF(COUNTIF('Bibliothèque transporteurs'!C:C,F154)=0,"inconnu",_xlfn.XLOOKUP(F154,'Bibliothèque transporteurs'!C:C,'Bibliothèque transporteurs'!E:E)) | W154: =IF(T154="FR_2SHOP",O154,IF(O154=0,0,ROUNDUP(O154/C154*B154,2))) | Y154: =ROUNDUP(B154,2)-M154-L154-N154-J154-K154-I154-Q154 | Z154: =IF(Y154=W154,"OK","Non")
A155: =C155/SUM(C:C)*(SUM(C:C)+$X$2) | B155: =C155/SUM(C:C)*(SUM(C:C)+SUM($N$3:$O$7))+S155 | C155: =SUM(I155:Q155)-N155-P155 | D155: 6235 | E155: XF143259285FR | F155: 17 | G155: N | H155: Z1 | O155: 21.83 | S155: =_xlfn.XLOOKUP(E155,'Facture Chronopost'!L:L,'Facture Chronopost'!AA:AA,"") | T155: =IF(COUNTIF('Bibliothèque transporteurs'!C:C,F155)=0,"inconnu",_xlfn.XLOOKUP(F155,'Bibliothèque transporteurs'!C:C,'Bibliothèque transporteurs'!A:A)) | U155: =IF(OR(F155="6C",F155="6B"),_xlfn.XLOOKUP(E155,'Facture Chronopost'!L:L,'Facture Chronopost'!X:X),IF(OR(F155=17,F155=44),F155&"_"&H155,IF(COUNTIF('Bibliothèque transporteurs'!C:C,F155)=0,"inconnu",_xlfn.XLOOKUP(F155,'Bibliothèque transporteurs'!C:C,'Bibliothèque transporteurs'!B:B)))) | V155: =IF(COUNTIF('Bibliothèque transporteurs'!C:C,F155)=0,"inconnu",_xlfn.XLOOKUP(F155,'Bibliothèque transporteurs'!C:C,'Bibliothèque transporteurs'!E:E)) | W155: =IF(T155="FR_2SHOP",O155,IF(O155=0,0,ROUNDUP(O155/C155*B155,2))) | Y155: =ROUNDUP(B155,2)-M155-L155-N155-J155-K155-I155-Q155 | Z155: =IF(Y155=W155,"OK","Non")
A156: =C156/SUM(C:C)*(SUM(C:C)+$X$2) | B156: =C156/SUM(C:C)*(SUM(C:C)+SUM($N$3:$O$7))+S156 | C156: =SUM(I156:Q156)-N156-P156 | D156: 6235 | E156: XF143259311FR | F156: 17 | G156: N | H156: Z1 | O156: 7.86 | S156: =_xlfn.XLOOKUP(E156,'Facture Chronopost'!L:L,'Facture Chronopost'!AA:AA,"") | T156: =IF(COUNTIF('Bibliothèque transporteurs'!C:C,F156)=0,"inconnu",_xlfn.XLOOKUP(F156,'Bibliothèque transporteurs'!C:C,'Bibliothèque transporteurs'!A:A)) | U156: =IF(OR(F156="6C",F156="6B"),_xlfn.XLOOKUP(E156,'Facture Chronopost'!L:L,'Facture Chronopost'!X:X),IF(OR(F156=17,F156=44),F156&"_"&H156,IF(COUNTIF('Bibliothèque transporteurs'!C:C,F156)=0,"inconnu",_xlfn.XLOOKUP(F156,'Bibliothèque transporteurs'!C:C,'Bibliothèque transporteurs'!B:B)))) | V156: =IF(COUNTIF('Bibliothèque transporteurs'!C:C,F156)=0,"inconnu",_xlfn.XLOOKUP(F156,'Bibliothèque transporteurs'!C:C,'Bibliothèque transporteurs'!E:E)) | W156: =IF(T156="FR_2SHOP",O156,IF(O156=0,0,ROUNDUP(O156/C156*B156,2))) | Y156: =ROUNDUP(B156,2)-M156-L156-N156-J156-K156-I156-Q156 | Z156: =IF(Y156=W156,"OK","Non")
A157: =C157/SUM(C:C)*(SUM(C:C)+$X$2) | B157: =C157/SUM(C:C)*(SUM(C:C)+SUM($N$3:$O$7))+S157 | C157: =SUM(I157:Q157)-N157-P157 | D157: 6235 | E157: XF143259360FR | F157: 17 | G157: N | H157: Z1 | O157: 9.94 | S157: =_xlfn.XLOOKUP(E157,'Facture Chronopost'!L:L,'Facture Chronopost'!AA:AA,"") | T157: =IF(COUNTIF('Bibliothèque transporteurs'!C:C,F157)=0,"inconnu",_xlfn.XLOOKUP(F157,'Bibliothèque transporteurs'!C:C,'Bibliothèque transporteurs'!A:A)) | U157: =IF(OR(F157="6C",F157="6B"),_xlfn.XLOOKUP(E157,'Facture Chronopost'!L:L,'Facture Chronopost'!X:X),IF(OR(F157=17,F157=44),F157&"_"&H157,IF(COUNTIF('Bibliothèque transporteurs'!C:C,F157)=0,"inconnu",_xlfn.XLOOKUP(F157,'Bibliothèque transporteurs'!C:C,'Bibliothèque transporteurs'!B:B)))) | V157: =IF(COUNTIF('Bibliothèque transporteurs'!C:C,F157)=0,"inconnu",_xlfn.XLOOKUP(F157,'Bibliothèque transporteurs'!C:C,'Bibliothèque transporteurs'!E:E)) | W157: =IF(T157="FR_2SHOP",O157,IF(O157=0,0,ROUNDUP(O157/C157*B157,2))) | Y157: =ROUNDUP(B157,2)-M157-L157-N157-J157-K157-I157-Q157 | Z157: =IF(Y157=W157,"OK","Non")
A158: =C158/SUM(C:C)*(SUM(C:C)+$X$2) | B158: =C158/SUM(C:C)*(SUM(C:C)+SUM($N$3:$O$7))+S158 | C158: =SUM(I158:Q158)-N158-P158 | D158: 6235 | E158: XF143259475FR | F158: 17 | G158: N | H158: Z1 | O158: 19.47 | S158: =_xlfn.XLOOKUP(E158,'Facture Chronopost'!L:L,'Facture Chronopost'!AA:AA,"") | T158: =IF(COUNTIF('Bibliothèque transporteurs'!C:C,F158)=0,"inconnu",_xlfn.XLOOKUP(F158,'Bibliothèque transporteurs'!C:C,'Bibliothèque transporteurs'!A:A)) | U158: =IF(OR(F158="6C",F158="6B"),_xlfn.XLOOKUP(E158,'Facture Chronopost'!L:L,'Facture Chronopost'!X:X),IF(OR(F158=17,F158=44),F158&"_"&H158,IF(COUNTIF('Bibliothèque transporteurs'!C:C,F158)=0,"inconnu",_xlfn.XLOOKUP(F158,'Bibliothèque transporteurs'!C:C,'Bibliothèque transporteurs'!B:B)))) | V158: =IF(COUNTIF('Bibliothèque transporteurs'!C:C,F158)=0,"inconnu",_xlfn.XLOOKUP(F158,'Bibliothèque transporteurs'!C:C,'Bibliothèque transporteurs'!E:E)) | W158: =IF(T158="FR_2SHOP",O158,IF(O158=0,0,ROUNDUP(O158/C158*B158,2))) | Y158: =ROUNDUP(B158,2)-M158-L158-N158-J158-K158-I158-Q158 | Z158: =IF(Y158=W158,"OK","Non")
... A251: =C251/SUM(C:C)*(SUM(C:C)+$X$2) | B251: =C251/SUM(C:C)*(SUM(C:C)+SUM($N$3:$O$7))+S251 | C251: =SUM(I251:Q251)-N251-P251 | D251: 6235 | E251: XN091386652JB | F251: 16 | G251: N | H251: NT | O251: 8.6 | S251: =_xlfn.XLOOKUP(E251,'Facture Chronopost'!L:L,'Facture Chronopost'!AA:AA,"") | T251: =IF(COUNTIF('Bibliothèque transporteurs'!C:C,F251)=0,"inconnu",_xlfn.XLOOKUP(F251,'Bibliothèque transporteurs'!C:C,'Bibliothèque transporteurs'!A:A)) | U251: =IF(OR(F251="6C",F251="6B"),_xlfn.XLOOKUP(E251,'Facture Chronopost'!L:L,'Facture Chronopost'!X:X),IF(OR(F251=17,F251=44),F251&"_"&H251,IF(COUNTIF('Bibliothèque transporteurs'!C:C,F251)=0,"inconnu",_xlfn.XLOOKUP(F251,'Bibliothèque transporteurs'!C:C,'Bibliothèque transporteurs'!B:B)))) | V251: =IF(COUNTIF('Bibliothèque transporteurs'!C:C,F251)=0,"inconnu",_xlfn.XLOOKUP(F251,'Bibliothèque transporteurs'!C:C,'Bibliothèque transporteurs'!E:E)) | W251: =IF(T251="FR_2SHOP",O251,IF(O251=0,0,ROUNDUP(O251/C251*B251,2))) | Y251: =ROUNDUP(B251,2)-M251-L251-N251-J251-K251-I251-Q251 | Z251: =IF(Y251=W251,"OK","Non")
A252: =C252/SUM(C:C)*(SUM(C:C)+$X$2) | B252: =C252/SUM(C:C)*(SUM(C:C)+SUM($N$3:$O$7))+S252 | C252: =SUM(I252:Q252)-N252-P252 | D252: 6235 | E252: XN091740021JB | F252: 16 | G252: N | H252: NT | O252: 8.6 | Q252: 5 | S252: =_xlfn.XLOOKUP(E252,'Facture Chronopost'!L:L,'Facture Chronopost'!AA:AA,"") | T252: =IF(COUNTIF('Bibliothèque transporteurs'!C:C,F252)=0,"inconnu",_xlfn.XLOOKUP(F252,'Bibliothèque transporteurs'!C:C,'Bibliothèque transporteurs'!A:A)) | U252: =IF(OR(F252="6C",F252="6B"),_xlfn.XLOOKUP(E252,'Facture Chronopost'!L:L,'Facture Chronopost'!X:X),IF(OR(F252=17,F252=44),F252&"_"&H252,IF(COUNTIF('Bibliothèque transporteurs'!C:C,F252)=0,"inconnu",_xlfn.XLOOKUP(F252,'Bibliothèque transporteurs'!C:C,'Bibliothèque transporteurs'!B:B)))) | V252: =IF(COUNTIF('Bibliothèque transporteurs'!C:C,F252)=0,"inconnu",_xlfn.XLOOKUP(F252,'Bibliothèque transporteurs'!C:C,'Bibliothèque transporteurs'!E:E)) | W252: =IF(T252="FR_2SHOP",O252,IF(O252=0,0,ROUNDUP(O252/C252*B252,2))) | Y252: =ROUNDUP(B252,2)-M252-L252-N252-J252-K252-I252-Q252 | Z252: =IF(Y252=W252,"OK","Non")
A253: =C253/SUM(C:C)*(SUM(C:C)+$X$2) | B253: =C253/SUM(C:C)*(SUM(C:C)+SUM($N$3:$O$7))+S253 | C253: =SUM(I253:Q253)-N253-P253 | D253: 7261 | E253: XN091799248JB | F253: 16 | G253: N | H253: NT | O253: 7.8 | S253: =_xlfn.XLOOKUP(E253,'Facture Chronopost'!L:L,'Facture Chronopost'!AA:AA,"") | T253: =IF(COUNTIF('Bibliothèque transporteurs'!C:C,F253)=0,"inconnu",_xlfn.XLOOKUP(F253,'Bibliothèque transporteurs'!C:C,'Bibliothèque transporteurs'!A:A)) | U253: =IF(OR(F253="6C",F253="6B"),_xlfn.XLOOKUP(E253,'Facture Chronopost'!L:L,'Facture Chronopost'!X:X),IF(OR(F253=17,F253=44),F253&"_"&H253,IF(COUNTIF('Bibliothèque transporteurs'!C:C,F253)=0,"inconnu",_xlfn.XLOOKUP(F253,'Bibliothèque transporteurs'!C:C,'Bibliothèque transporteurs'!B:B)))) | V253: =IF(COUNTIF('Bibliothèque transporteurs'!C:C,F253)=0,"inconnu",_xlfn.XLOOKUP(F253,'Bibliothèque transporteurs'!C:C,'Bibliothèque transporteurs'!E:E)) | W253: =IF(T253="FR_2SHOP",O253,IF(O253=0,0,ROUNDUP(O253/C253*B253,2))) | Y253: =ROUNDUP(B253,2)-M253-L253-N253-J253-K253-I253-Q253 | Z253: =IF(Y253=W253,"OK","Non")
A254: =C254/SUM(C:C)*(SUM(C:C)+$X$2) | B254: =C254/SUM(C:C)*(SUM(C:C)+SUM($N$3:$O$7))+S254 | C254: =SUM(I254:Q254)-N254-P254 | D254: 3752 | E254: XN091825098JB | F254: 16 | G254: N | H254: NT | O254: 7.4 | S254: =_xlfn.XLOOKUP(E254,'Facture Chronopost'!L:L,'Facture Chronopost'!AA:AA,"") | T254: =IF(COUNTIF('Bibliothèque transporteurs'!C:C,F254)=0,"inconnu",_xlfn.XLOOKUP(F254,'Bibliothèque transporteurs'!C:C,'Bibliothèque transporteurs'!A:A)) | U254: =IF(OR(F254="6C",F254="6B"),_xlfn.XLOOKUP(E254,'Facture Chronopost'!L:L,'Facture Chronopost'!X:X),IF(OR(F254=17,F254=44),F254&"_"&H254,IF(COUNTIF('Bibliothèque transporteurs'!C:C,F254)=0,"inconnu",_xlfn.XLOOKUP(F254,'Bibliothèque transporteurs'!C:C,'Bibliothèque transporteurs'!B:B)))) | V254: =IF(COUNTIF('Bibliothèque transporteurs'!C:C,F254)=0,"inconnu",_xlfn.XLOOKUP(F254,'Bibliothèque transporteurs'!C:C,'Bibliothèque transporteurs'!E:E)) | W254: =IF(T254="FR_2SHOP",O254,IF(O254=0,0,ROUNDUP(O254/C254*B254,2))) | Y254: =ROUNDUP(B254,2)-M254-L254-N254-J254-K254-I254-Q254 | Z254: =IF(Y254=W254,"OK","Non")
A255: =C255/SUM(C:C)*(SUM(C:C)+$X$2) | B255: =C255/SUM(C:C)*(SUM(C:C)+SUM($N$3:$O$7))+S255 | C255: =SUM(I255:Q255)-N255-P255 | D255: 6235 | E255: XN091856064JB | F255: 16 | G255: N | H255: NT | O255: 7 | S255: =_xlfn.XLOOKUP(E255,'Facture Chronopost'!L:L,'Facture Chronopost'!AA:AA,"") | T255: =IF(COUNTIF('Bibliothèque transporteurs'!C:C,F255)=0,"inconnu",_xlfn.XLOOKUP(F255,'Bibliothèque transporteurs'!C:C,'Bibliothèque transporteurs'!A:A)) | U255: =IF(OR(F255="6C",F255="6B"),_xlfn.XLOOKUP(E255,'Facture Chronopost'!L:L,'Facture Chronopost'!X:X),IF(OR(F255=17,F255=44),F255&"_"&H255,IF(COUNTIF('Bibliothèque transporteurs'!C:C,F255)=0,"inconnu",_xlfn.XLOOKUP(F255,'Bibliothèque transporteurs'!C:C,'Bibliothèque transporteurs'!B:B)))) | V255: =IF(COUNTIF('Bibliothèque transporteurs'!C:C,F255)=0,"inconnu",_xlfn.XLOOKUP(F255,'Bibliothèque transporteurs'!C:C,'Bibliothèque transporteurs'!E:E)) | W255: =IF(T255="FR_2SHOP",O255,IF(O255=0,0,ROUNDUP(O255/C255*B255,2))) | Y255: =ROUNDUP(B255,2)-M255-L255-N255-J255-K255-I255-Q255 | Z255: =IF(Y255=W255,"OK","Non")
A256: =C256/SUM(C:C)*(SUM(C:C)+$X$2) | B256: =C256/SUM(C:C)*(SUM(C:C)+SUM($N$3:$O$7))+S256 | C256: =SUM(I256:Q256)-N256-P256 | D256: 7515 | E256: XN091857161JB | F256: 16 | G256: N | H256: NT | O256: 8.2 | S256: =_xlfn.XLOOKUP(E256,'Facture Chronopost'!L:L,'Facture Chronopost'!AA:AA,"") | T256: =IF(COUNTIF('Bibliothèque transporteurs'!C:C,F256)=0,"inconnu",_xlfn.XLOOKUP(F256,'Bibliothèque transporteurs'!C:C,'Bibliothèque transporteurs'!A:A)) | U256: =IF(OR(F256="6C",F256="6B"),_xlfn.XLOOKUP(E256,'Facture Chronopost'!L:L,'Facture Chronopost'!X:X),IF(OR(F256=17,F256=44),F256&"_"&H256,IF(COUNTIF('Bibliothèque transporteurs'!C:C,F256)=0,"inconnu",_xlfn.XLOOKUP(F256,'Bibliothèque transporteurs'!C:C,'Bibliothèque transporteurs'!B:B)))) | V256: =IF(COUNTIF('Bibliothèque transporteurs'!C:C,F256)=0,"inconnu",_xlfn.XLOOKUP(F256,'Bibliothèque transporteurs'!C:C,'Bibliothèque transporteurs'!E:E)) | W256: =IF(T256="FR_2SHOP",O256,IF(O256=0,0,ROUNDUP(O256/C256*B256,2))) | Y256: =ROUNDUP(B256,2)-M256-L256-N256-J256-K256-I256-Q256 | Z256: =IF(Y256=W256,"OK","Non")
A257: =C257/SUM(C:C)*(SUM(C:C)+$X$2) | B257: =C257/SUM(C:C)*(SUM(C:C)+SUM($N$3:$O$7))+S257 | C257: =SUM(I257:Q257)-N257-P257 | D257: 3752 | E257: XN091891432JB | F257: 16 | G257: N | H257: NT | O257: 8.6 | S257: =_xlfn.XLOOKUP(E257,'Facture Chronopost'!L:L,'Facture Chronopost'!AA:AA,"") | T257: =IF(COUNTIF('Bibliothèque transporteurs'!C:C,F257)=0,"inconnu",_xlfn.XLOOKUP(F257,'Bibliothèque transporteurs'!C:C,'Bibliothèque transporteurs'!A:A)) | U257: =IF(OR(F257="6C",F257="6B"),_xlfn.XLOOKUP(E257,'Facture Chronopost'!L:L,'Facture Chronopost'!X:X),IF(OR(F257=17,F257=44),F257&"_"&H257,IF(COUNTIF('Bibliothèque transporteurs'!C:C,F257)=0,"inconnu",_xlfn.XLOOKUP(F257,'Bibliothèque transporteurs'!C:C,'Bibliothèque transporteurs'!B:B)))) | V257: =IF(COUNTIF('Bibliothèque transporteurs'!C:C,F257)=0,"inconnu",_xlfn.XLOOKUP(F257,'Bibliothèque transporteurs'!C:C,'Bibliothèque transporteurs'!E:E)) | W257: =IF(T257="FR_2SHOP",O257,IF(O257=0,0,ROUNDUP(O257/C257*B257,2))) | Y257: =ROUNDUP(B257,2)-M257-L257-N257-J257-K257-I257-Q257 | Z257: =IF(Y257=W257,"OK","Non")
A258: =C258/SUM(C:C)*(SUM(C:C)+$X$2) | B258: =C258/SUM(C:C)*(SUM(C:C)+SUM($N$3:$O$7))+S258 | C258: =SUM(I258:Q258)-N258-P258 | D258: 6235 | E258: XN091892910JB | F258: 16 | G258: N | H258: NT | O258: 7 | Q258: 5 | S258: =_xlfn.XLOOKUP(E258,'Facture Chronopost'!L:L,'Facture Chronopost'!AA:AA,"") | T258: =IF(COUNTIF('Bibliothèque transporteurs'!C:C,F258)=0,"inconnu",_xlfn.XLOOKUP(F258,'Bibliothèque transporteurs'!C:C,'Bibliothèque transporteurs'!A:A)) | U258: =IF(OR(F258="6C",F258="6B"),_xlfn.XLOOKUP(E258,'Facture Chronopost'!L:L,'Facture Chronopost'!X:X),IF(OR(F258=17,F258=44),F258&"_"&H258,IF(COUNTIF('Bibliothèque transporteurs'!C:C,F258)=0,"inconnu",_xlfn.XLOOKUP(F258,'Bibliothèque transporteurs'!C:C,'Bibliothèque transporteurs'!B:B)))) | V258: =IF(COUNTIF('Bibliothèque transporteurs'!C:C,F258)=0,"inconnu",_xlfn.XLOOKUP(F258,'Bibliothèque transporteurs'!C:C,'Bibliothèque transporteurs'!E:E)) | W258: =IF(T258="FR_2SHOP",O258,IF(O258=0,0,ROUNDUP(O258/C258*B258,2))) | Y258: =ROUNDUP(B258,2)-M258-L258-N258-J258-K258-I258-Q258 | Z258: =IF(Y258=W258,"OK","Non")
A259: =C259/SUM(C:C)*(SUM(C:C)+$X$2) | B259: =C259/SUM(C:C)*(SUM(C:C)+SUM($N$3:$O$7))+S259 | C259: =SUM(I259:Q259)-N259-P259 | D259: 6235 | E259: XN091895553JB | F259: 16 | G259: N | H259: NT | O259: 7 | S259: =_xlfn.XLOOKUP(E259,'Facture Chronopost'!L:L,'Facture Chronopost'!AA:AA,"") | T259: =IF(COUNTIF('Bibliothèque transporteurs'!C:C,F259)=0,"inconnu",_xlfn.XLOOKUP(F259,'Bibliothèque transporteurs'!C:C,'Bibliothèque transporteurs'!A:A)) | U259: =IF(OR(F259="6C",F259="6B"),_xlfn.XLOOKUP(E259,'Facture Chronopost'!L:L,'Facture Chronopost'!X:X),IF(OR(F259=17,F259=44),F259&"_"&H259,IF(COUNTIF('Bibliothèque transporteurs'!C:C,F259)=0,"inconnu",_xlfn.XLOOKUP(F259,'Bibliothèque transporteurs'!C:C,'Bibliothèque transporteurs'!B:B)))) | V259: =IF(COUNTIF('Bibliothèque transporteurs'!C:C,F259)=0,"inconnu",_xlfn.XLOOKUP(F259,'Bibliothèque transporteurs'!C:C,'Bibliothèque transporteurs'!E:E)) | W259: =IF(T259="FR_2SHOP",O259,IF(O259=0,0,ROUNDUP(O259/C259*B259,2))) | Y259: =ROUNDUP(B259,2)-M259-L259-N259-J259-K259-I259-Q259 | Z259: =IF(Y259=W259,"OK","Non")
A260: =C260/SUM(C:C)*(SUM(C:C)+$X$2) | B260: =C260/SUM(C:C)*(SUM(C:C)+SUM($N$3:$O$7))+S260 | C260: =SUM(I260:Q260)-N260-P260 | D260: 8640 | E260: XN091896307JB | F260: 16 | G260: N | H260: NT | O260: 7.4 | S260: =_xlfn.XLOOKUP(E260,'Facture Chronopost'!L:L,'Facture Chronopost'!AA:AA,"") | T260: =IF(COUNTIF('Bibliothèque transporteurs'!C:C,F260)=0,"inconnu",_xlfn.XLOOKUP(F260,'Bibliothèque transporteurs'!C:C,'Bibliothèque transporteurs'!A:A)) | U260: =IF(OR(F260="6C",F260="6B"),_xlfn.XLOOKUP(E260,'Facture Chronopost'!L:L,'Facture Chronopost'!X:X),IF(OR(F260=17,F260=44),F260&"_"&H260,IF(COUNTIF('Bibliothèque transporteurs'!C:C,F260)=0,"inconnu",_xlfn.XLOOKUP(F260,'Bibliothèque transporteurs'!C:C,'Bibliothèque transporteurs'!B:B)))) | V260: =IF(COUNTIF('Bibliothèque transporteurs'!C:C,F260)=0,"inconnu",_xlfn.XLOOKUP(F260,'Bibliothèque transporteurs'!C:C,'Bibliothèque transporteurs'!E:E)) | W260: =IF(T260="FR_2SHOP",O260,IF(O260=0,0,ROUNDUP(O260/C260*B260,2))) | Y260: =ROUNDUP(B260,2)-M260-L260-N260-J260-K260-I260-Q260 | Z260: =IF(Y260=W260,"OK","Non")
A261: =C261/SUM(C:C)*(SUM(C:C)+$X$2) | B261: =C261/SUM(C:C)*(SUM(C:C)+SUM($N$3:$O$7))+S261 | C261: =SUM(I261:Q261)-N261-P261 | D261: 8640 | E261: XN091897404JB | F261: 16 | G261: N | H261: NT | O261: 7.8 | S261: =_xlfn.XLOOKUP(E261,'Facture Chronopost'!L:L,'Facture Chronopost'!AA:AA,"") | T261: =IF(COUNTIF('Bibliothèque transporteurs'!C:C,F261)=0,"inconnu",_xlfn.XLOOKUP(F261,'Bibliothèque transporteurs'!C:C,'Bibliothèque transporteurs'!A:A)) | U261: =IF(OR(F261="6C",F261="6B"),_xlfn.XLOOKUP(E261,'Facture Chronopost'!L:L,'Facture Chronopost'!X:X),IF(OR(F261=17,F261=44),F261&"_"&H261,IF(COUNTIF('Bibliothèque transporteurs'!C:C,F261)=0,"inconnu",_xlfn.XLOOKUP(F261,'Bibliothèque transporteurs'!C:C,'Bibliothèque transporteurs'!B:B)))) | V261: =IF(COUNTIF('Bibliothèque transporteurs'!C:C,F261)=0,"inconnu",_xlfn.XLOOKUP(F261,'Bibliothèque transporteurs'!C:C,'Bibliothèque transporteurs'!E:E)) | W261: =IF(T261="FR_2SHOP",O261,IF(O261=0,0,ROUNDUP(O261/C261*B261,2))) | Y261: =ROUNDUP(B261,2)-M261-L261-N261-J261-K261-I261-Q261 | Z261: =IF(Y261=W261,"OK","Non")
A262: =C262/SUM(C:C)*(SUM(C:C)+$X$2) | B262: =C262/SUM(C:C)*(SUM(C:C)+SUM($N$3:$O$7))+S262 | C262: =SUM(I262:Q262)-N262-P262 | D262: 8640 | E262: XN091898515JB | F262: 16 | G262: N | H262: NT | O262: 7.8 | S262: =_xlfn.XLOOKUP(E262,'Facture Chronopost'!L:L,'Facture Chronopost'!AA:AA,"") | T262: =IF(COUNTIF('Bibliothèque transporteurs'!C:C,F262)=0,"inconnu",_xlfn.XLOOKUP(F262,'Bibliothèque transporteurs'!C:C,'Bibliothèque transporteurs'!A:A)) | U262: =IF(OR(F262="6C",F262="6B"),_xlfn.XLOOKUP(E262,'Facture Chronopost'!L:L,'Facture Chronopost'!X:X),IF(OR(F262=17,F262=44),F262&"_"&H262,IF(COUNTIF('Bibliothèque transporteurs'!C:C,F262)=0,"inconnu",_xlfn.XLOOKUP(F262,'Bibliothèque transporteurs'!C:C,'Bibliothèque transporteurs'!B:B)))) | V262: =IF(COUNTIF('Bibliothèque transporteurs'!C:C,F262)=0,"inconnu",_xlfn.XLOOKUP(F262,'Bibliothèque transporteurs'!C:C,'Bibliothèque transporteurs'!E:E)) | W262: =IF(T262="FR_2SHOP",O262,IF(O262=0,0,ROUNDUP(O262/C262*B262,2))) | Y262: =ROUNDUP(B262,2)-M262-L262-N262-J262-K262-I262-Q262 | Z262: =IF(Y262=W262,"OK","Non")
A263: =C263/SUM(C:C)*(SUM(C:C)+$X$2) | B263: =C263/SUM(C:C)*(SUM(C:C)+SUM($N$3:$O$7))+S263 | C263: =SUM(I263:Q263)-N263-P263 | D263: 6235 | E263: XN091899436JB | F263: 16 | G263: N | H263: NT | O263: 8.6 | Q263: 5 | S263: =_xlfn.XLOOKUP(E263,'Facture Chronopost'!L:L,'Facture Chronopost'!AA:AA,"") | T263: =IF(COUNTIF('Bibliothèque transporteurs'!C:C,F263)=0,"inconnu",_xlfn.XLOOKUP(F263,'Bibliothèque transporteurs'!C:C,'Bibliothèque transporteurs'!A:A)) | U263: =IF(OR(F263="6C",F263="6B"),_xlfn.XLOOKUP(E263,'Facture Chronopost'!L:L,'Facture Chronopost'!X:X),IF(OR(F263=17,F263=44),F263&"_"&H263,IF(COUNTIF('Bibliothèque transporteurs'!C:C,F263)=0,"inconnu",_xlfn.XLOOKUP(F263,'Bibliothèque transporteurs'!C:C,'Bibliothèque transporteurs'!B:B)))) | V263: =IF(COUNTIF('Bibliothèque transporteurs'!C:C,F263)=0,"inconnu",_xlfn.XLOOKUP(F263,'Bibliothèque transporteurs'!C:C,'Bibliothèque transporteurs'!E:E)) | W263: =IF(T263="FR_2SHOP",O263,IF(O263=0,0,ROUNDUP(O263/C263*B263,2))) | Y263: =ROUNDUP(B263,2)-M263-L263-N263-J263-K263-I263-Q263 | Z263: =IF(Y263=W263,"OK","Non")
A264: =C264/SUM(C:C)*(SUM(C:C)+$X$2) | B264: =C264/SUM(C:C)*(SUM(C:C)+SUM($N$3:$O$7))+S264 | C264: =SUM(I264:Q264)-N264-P264 | D264: 6813 | E264: XN091899820JB | F264: 16 | G264: N | H264: NT | O264: 7 | S264: =_xlfn.XLOOKUP(E264,'Facture Chronopost'!L:L,'Facture Chronopost'!AA:AA,"") | T264: =IF(COUNTIF('Bibliothèque transporteurs'!C:C,F264)=0,"inconnu",_xlfn.XLOOKUP(F264,'Bibliothèque transporteurs'!C:C,'Bibliothèque transporteurs'!A:A)) | U264: =IF(OR(F264="6C",F264="6B"),_xlfn.XLOOKUP(E264,'Facture Chronopost'!L:L,'Facture Chronopost'!X:X),IF(OR(F264=17,F264=44),F264&"_"&H264,IF(COUNTIF('Bibliothèque transporteurs'!C:C,F264)=0,"inconnu",_xlfn.XLOOKUP(F264,'Bibliothèque transporteurs'!C:C,'Bibliothèque transporteurs'!B:B)))) | V264: =IF(COUNTIF('Bibliothèque transporteurs'!C:C,F264)=0,"inconnu",_xlfn.XLOOKUP(F264,'Bibliothèque transporteurs'!C:C,'Bibliothèque transporteurs'!E:E)) | W264: =IF(T264="FR_2SHOP",O264,IF(O264=0,0,ROUNDUP(O264/C264*B264,2))) | Y264: =ROUNDUP(B264,2)-M264-L264-N264-J264-K264-I264-Q264 | Z264: =IF(Y264=W264,"OK","Non")
A265: =C265/SUM(C:C)*(SUM(C:C)+$X$2) | B265: =C265/SUM(C:C)*(SUM(C:C)+SUM($N$3:$O$7))+S265 | C265: =SUM(I265:Q265)-N265-P265 | D265: 6235 | E265: XN091900355JB | F265: 16 | G265: N | H265: NT | O265: 8.6 | Q265: 5 | S265: =_xlfn.XLOOKUP(E265,'Facture Chronopost'!L:L,'Facture Chronopost'!AA:AA,"") | T265: =IF(COUNTIF('Bibliothèque transporteurs'!C:C,F265)=0,"inconnu",_xlfn.XLOOKUP(F265,'Bibliothèque transporteurs'!C:C,'Bibliothèque transporteurs'!A:A)) | U265: =IF(OR(F265="6C",F265="6B"),_xlfn.XLOOKUP(E265,'Facture Chronopost'!L:L,'Facture Chronopost'!X:X),IF(OR(F265=17,F265=44),F265&"_"&H265,IF(COUNTIF('Bibliothèque transporteurs'!C:C,F265)=0,"inconnu",_xlfn.XLOOKUP(F265,'Bibliothèque transporteurs'!C:C,'Bibliothèque transporteurs'!B:B)))) | V265: =IF(COUNTIF('Bibliothèque transporteurs'!C:C,F265)=0,"inconnu",_xlfn.XLOOKUP(F265,'Bibliothèque transporteurs'!C:C,'Bibliothèque transporteurs'!E:E)) | W265: =IF(T265="FR_2SHOP",O265,IF(O265=0,0,ROUNDUP(O265/C265*B265,2))) | Y265: =ROUNDUP(B265,2)-M265-L265-N265-J265-K265-I265-Q265 | Z265: =IF(Y265=W265,"OK","Non")
A266: =C266/SUM(C:C)*(SUM(C:C)+$X$2) | B266: =C266/SUM(C:C)*(SUM(C:C)+SUM($N$3:$O$7))+S266 | C266: =SUM(I266:Q266)-N266-P266 | D266: 6235 | E266: XN091906707JB | F266: 16 | G266: N | H266: NT | O266: 9.4 | S266: =_xlfn.XLOOKUP(E266,'Facture Chronopost'!L:L,'Facture Chronopost'!AA:AA,"") | T266: =IF(COUNTIF('Bibliothèque transporteurs'!C:C,F266)=0,"inconnu",_xlfn.XLOOKUP(F266,'Bibliothèque transporteurs'!C:C,'Bibliothèque transporteurs'!A:A)) | U266: =IF(OR(F266="6C",F266="6B"),_xlfn.XLOOKUP(E266,'Facture Chronopost'!L:L,'Facture Chronopost'!X:X),IF(OR(F266=17,F266=44),F266&"_"&H266,IF(COUNTIF('Bibliothèque transporteurs'!C:C,F266)=0,"inconnu",_xlfn.XLOOKUP(F266,'Bibliothèque transporteurs'!C:C,'Bibliothèque transporteurs'!B:B)))) | V266: =IF(COUNTIF('Bibliothèque transporteurs'!C:C,F266)=0,"inconnu",_xlfn.XLOOKUP(F266,'Bibliothèque transporteurs'!C:C,'Bibliothèque transporteurs'!E:E)) | W266: =IF(T266="FR_2SHOP",O266,IF(O266=0,0,ROUNDUP(O266/C266*B266,2))) | Y266: =ROUNDUP(B266,2)-M266-L266-N266-J266-K266-I266-Q266 | Z266: =IF(Y266=W266,"OK","Non")
A267: =C267/SUM(C:C)*(SUM(C:C)+$X$2) | B267: =C267/SUM(C:C)*(SUM(C:C)+SUM($N$3:$O$7))+S267 | C267: =SUM(I267:Q267)-N267-P267 | D267: 9160 | E267: XN092286885JB | F267: 16 | G267: N | H267: NT | O267: 7.8 | S267: =_xlfn.XLOOKUP(E267,'Facture Chronopost'!L:L,'Facture Chronopost'!AA:AA,"") | T267: =IF(COUNTIF('Bibliothèque transporteurs'!C:C,F267)=0,"inconnu",_xlfn.XLOOKUP(F267,'Bibliothèque transporteurs'!C:C,'Bibliothèque transporteurs'!A:A)) | U267: =IF(OR(F267="6C",F267="6B"),_xlfn.XLOOKUP(E267,'Facture Chronopost'!L:L,'Facture Chronopost'!X:X),IF(OR(F267=17,F267=44),F267&"_"&H267,IF(COUNTIF('Bibliothèque transporteurs'!C:C,F267)=0,"inconnu",_xlfn.XLOOKUP(F267,'Bibliothèque transporteurs'!C:C,'Bibliothèque transporteurs'!B:B)))) | V267: =IF(COUNTIF('Bibliothèque transporteurs'!C:C,F267)=0,"inconnu",_xlfn.XLOOKUP(F267,'Bibliothèque transporteurs'!C:C,'Bibliothèque transporteurs'!E:E)) | W267: =IF(T267="FR_2SHOP",O267,IF(O267=0,0,ROUNDUP(O267/C267*B267,2))) | Y267: =ROUNDUP(B267,2)-M267-L267-N267-J267-K267-I267-Q267 | Z267: =IF(Y267=W267,"OK","Non")
A268: =C268/SUM(C:C)*(SUM(C:C)+$X$2) | B268: =C268/SUM(C:C)*(SUM(C:C)+SUM($N$3:$O$7))+S268 | C268: =SUM(I268:Q268)-N268-P268 | D268: 6235 | E268: XN092381988JB | F268: 16 | G268: N | H268: NT | O268: 7 | S268: =_xlfn.XLOOKUP(E268,'Facture Chronopost'!L:L,'Facture Chronopost'!AA:AA,"") | T268: =IF(COUNTIF('Bibliothèque transporteurs'!C:C,F268)=0,"inconnu",_xlfn.XLOOKUP(F268,'Bibliothèque transporteurs'!C:C,'Bibliothèque transporteurs'!A:A)) | U268: =IF(OR(F268="6C",F268="6B"),_xlfn.XLOOKUP(E268,'Facture Chronopost'!L:L,'Facture Chronopost'!X:X),IF(OR(F268=17,F268=44),F268&"_"&H268,IF(COUNTIF('Bibliothèque transporteurs'!C:C,F268)=0,"inconnu",_xlfn.XLOOKUP(F268,'Bibliothèque transporteurs'!C:C,'Bibliothèque transporteurs'!B:B)))) | V268: =IF(COUNTIF('Bibliothèque transporteurs'!C:C,F268)=0,"inconnu",_xlfn.XLOOKUP(F268,'Bibliothèque transporteurs'!C:C,'Bibliothèque transporteurs'!E:E)) | W268: =IF(T268="FR_2SHOP",O268,IF(O268=0,0,ROUNDUP(O268/C268*B268,2))) | Y268: =ROUNDUP(B268,2)-M268-L268-N268-J268-K268-I268-Q268 | Z268: =IF(Y268=W268,"OK","Non")
A269: =C269/SUM(C:C)*(SUM(C:C)+$X$2) | B269: =C269/SUM(C:C)*(SUM(C:C)+SUM($N$3:$O$7))+S269 | C269: =SUM(I269:Q269)-N269-P269 | D269: 3752 | E269: XN092824068JB | F269: 16 | G269: N | H269: NT | O269: 7 | S269: =_xlfn.XLOOKUP(E269,'Facture Chronopost'!L:L,'Facture Chronopost'!AA:AA,"") | T269: =IF(COUNTIF('Bibliothèque transporteurs'!C:C,F269)=0,"inconnu",_xlfn.XLOOKUP(F269,'Bibliothèque transporteurs'!C:C,'Bibliothèque transporteurs'!A:A)) | U269: =IF(OR(F269="6C",F269="6B"),_xlfn.XLOOKUP(E269,'Facture Chronopost'!L:L,'Facture Chronopost'!X:X),IF(OR(F269=17,F269=44),F269&"_"&H269,IF(COUNTIF('Bibliothèque transporteurs'!C:C,F269)=0,"inconnu",_xlfn.XLOOKUP(F269,'Bibliothèque transporteurs'!C:C,'Bibliothèque transporteurs'!B:B)))) | V269: =IF(COUNTIF('Bibliothèque transporteurs'!C:C,F269)=0,"inconnu",_xlfn.XLOOKUP(F269,'Bibliothèque transporteurs'!C:C,'Bibliothèque transporteurs'!E:E)) | W269: =IF(T269="FR_2SHOP",O269,IF(O269=0,0,ROUNDUP(O269/C269*B269,2))) | Y269: =ROUNDUP(B269,2)-M269-L269-N269-J269-K269-I269-Q269 | Z269: =IF(Y269=W269,"OK","Non")
A270: =C270/SUM(C:C)*(SUM(C:C)+$X$2) | B270: =C270/SUM(C:C)*(SUM(C:C)+SUM($N$3:$O$7))+S270 | C270: =SUM(I270:Q270)-N270-P270 | D270: 6235 | E270: XN093248509JB | F270: 16 | G270: N | H270: NT | O270: 7 | S270: =_xlfn.XLOOKUP(E270,'Facture Chronopost'!L:L,'Facture Chronopost'!AA:AA,"") | T270: =IF(COUNTIF('Bibliothèque transporteurs'!C:C,F270)=0,"inconnu",_xlfn.XLOOKUP(F270,'Bibliothèque transporteurs'!C:C,'Bibliothèque transporteurs'!A:A)) | U270: =IF(OR(F270="6C",F270="6B"),_xlfn.XLOOKUP(E270,'Facture Chronopost'!L:L,'Facture Chronopost'!X:X),IF(OR(F270=17,F270=44),F270&"_"&H270,IF(COUNTIF('Bibliothèque transporteurs'!C:C,F270)=0,"inconnu",_xlfn.XLOOKUP(F270,'Bibliothèque transporteurs'!C:C,'Bibliothèque transporteurs'!B:B)))) | V270: =IF(COUNTIF('Bibliothèque transporteurs'!C:C,F270)=0,"inconnu",_xlfn.XLOOKUP(F270,'Bibliothèque transporteurs'!C:C,'Bibliothèque transporteurs'!E:E)) | W270: =IF(T270="FR_2SHOP",O270,IF(O270=0,0,ROUNDUP(O270/C270*B270,2))) | Y270: =ROUNDUP(B270,2)-M270-L270-N270-J270-K270-I270-Q270 | Z270: =IF(Y270=W270,"OK","Non")
A271: =C271/SUM(C:C)*(SUM(C:C)+$X$2) | B271: =C271/SUM(C:C)*(SUM(C:C)+SUM($N$3:$O$7))+S271 | C271: =SUM(I271:Q271)-N271-P271 | D271: 8640 | E271: XN093332484JB | F271: 16 | G271: N | H271: NT | O271: 7.8 | S271: =_xlfn.XLOOKUP(E271,'Facture Chronopost'!L:L,'Facture Chronopost'!AA:AA,"") | T271: =IF(COUNTIF('Bibliothèque transporteurs'!C:C,F271)=0,"inconnu",_xlfn.XLOOKUP(F271,'Bibliothèque transporteurs'!C:C,'Bibliothèque transporteurs'!A:A)) | U271: =IF(OR(F271="6C",F271="6B"),_xlfn.XLOOKUP(E271,'Facture Chronopost'!L:L,'Facture Chronopost'!X:X),IF(OR(F271=17,F271=44),F271&"_"&H271,IF(COUNTIF('Bibliothèque transporteurs'!C:C,F271)=0,"inconnu",_xlfn.XLOOKUP(F271,'Bibliothèque transporteurs'!C:C,'Bibliothèque transporteurs'!B:B)))) | V271: =IF(COUNTIF('Bibliothèque transporteurs'!C:C,F271)=0,"inconnu",_xlfn.XLOOKUP(F271,'Bibliothèque transporteurs'!C:C,'Bibliothèque transporteurs'!E:E)) | W271: =IF(T271="FR_2SHOP",O271,IF(O271=0,0,ROUNDUP(O271/C271*B271,2))) | Y271: =ROUNDUP(B271,2)-M271-L271-N271-J271-K271-I271-Q271 | Z271: =IF(Y271=W271,"OK","Non")
A272: =C272/SUM(C:C)*(SUM(C:C)+$X$2) | B272: =C272/SUM(C:C)*(SUM(C:C)+SUM($N$3:$O$7))+S272 | C272: =SUM(I272:Q272)-N272-P272 | D272: 4813 | E272: XN093365213JB | F272: 16 | G272: N | H272: NT | O272: 7 | S272: =_xlfn.XLOOKUP(E272,'Facture Chronopost'!L:L,'Facture Chronopost'!AA:AA,"") | T272: =IF(COUNTIF('Bibliothèque transporteurs'!C:C,F272)=0,"inconnu",_xlfn.XLOOKUP(F272,'Bibliothèque transporteurs'!C:C,'Bibliothèque transporteurs'!A:A)) | U272: =IF(OR(F272="6C",F272="6B"),_xlfn.XLOOKUP(E272,'Facture Chronopost'!L:L,'Facture Chronopost'!X:X),IF(OR(F272=17,F272=44),F272&"_"&H272,IF(COUNTIF('Bibliothèque transporteurs'!C:C,F272)=0,"inconnu",_xlfn.XLOOKUP(F272,'Bibliothèque transporteurs'!C:C,'Bibliothèque transporteurs'!B:B)))) | V272: =IF(COUNTIF('Bibliothèque transporteurs'!C:C,F272)=0,"inconnu",_xlfn.XLOOKUP(F272,'Bibliothèque transporteurs'!C:C,'Bibliothèque transporteurs'!E:E)) | W272: =IF(T272="FR_2SHOP",O272,IF(O272=0,0,ROUNDUP(O272/C272*B272,2))) | Y272: =ROUNDUP(B272,2)-M272-L272-N272-J272-K272-I272-Q272 | Z272: =IF(Y272=W272,"OK","Non")
A273: =C273/SUM(C:C)*(SUM(C:C)+$X$2) | B273: =C273/SUM(C:C)*(SUM(C:C)+SUM($N$3:$O$7))+S273 | C273: =SUM(I273:Q273)-N273-P273 | D273: 8656 | E273: XN093366514JB | F273: 16 | G273: N | H273: NT | O273: 10.2 | S273: =_xlfn.XLOOKUP(E273,'Facture Chronopost'!L:L,'Facture Chronopost'!AA:AA,"") | T273: =IF(COUNTIF('Bibliothèque transporteurs'!C:C,F273)=0,"inconnu",_xlfn.XLOOKUP(F273,'Bibliothèque transporteurs'!C:C,'Bibliothèque transporteurs'!A:A)) | U273: =IF(OR(F273="6C",F273="6B"),_xlfn.XLOOKUP(E273,'Facture Chronopost'!L:L,'Facture Chronopost'!X:X),IF(OR(F273=17,F273=44),F273&"_"&H273,IF(COUNTIF('Bibliothèque transporteurs'!C:C,F273)=0,"inconnu",_xlfn.XLOOKUP(F273,'Bibliothèque transporteurs'!C:C,'Bibliothèque transporteurs'!B:B)))) | V273: =IF(COUNTIF('Bibliothèque transporteurs'!C:C,F273)=0,"inconnu",_xlfn.XLOOKUP(F273,'Bibliothèque transporteurs'!C:C,'Bibliothèque transporteurs'!E:E)) | W273: =IF(T273="FR_2SHOP",O273,IF(O273=0,0,ROUNDUP(O273/C273*B273,2))) | Y273: =ROUNDUP(B273,2)-M273-L273-N273-J273-K273-I273-Q273 | Z273: =IF(Y273=W273,"OK","Non")
A274: =C274/SUM(C:C)*(SUM(C:C)+$X$2) | B274: =C274/SUM(C:C)*(SUM(C:C)+SUM($N$3:$O$7))+S274 | C274: =SUM(I274:Q274)-N274-P274 | D274: 8640 | E274: XN093382110JB | F274: 16 | G274: N | H274: NT | O274: 7.8 | S274: =_xlfn.XLOOKUP(E274,'Facture Chronopost'!L:L,'Facture Chronopost'!AA:AA,"") | T274: =IF(COUNTIF('Bibliothèque transporteurs'!C:C,F274)=0,"inconnu",_xlfn.XLOOKUP(F274,'Bibliothèque transporteurs'!C:C,'Bibliothèque transporteurs'!A:A)) | U274: =IF(OR(F274="6C",F274="6B"),_xlfn.XLOOKUP(E274,'Facture Chronopost'!L:L,'Facture Chronopost'!X:X),IF(OR(F274=17,F274=44),F274&"_"&H274,IF(COUNTIF('Bibliothèque transporteurs'!C:C,F274)=0,"inconnu",_xlfn.XLOOKUP(F274,'Bibliothèque transporteurs'!C:C,'Bibliothèque transporteurs'!B:B)))) | V274: =IF(COUNTIF('Bibliothèque transporteurs'!C:C,F274)=0,"inconnu",_xlfn.XLOOKUP(F274,'Bibliothèque transporteurs'!C:C,'Bibliothèque transporteurs'!E:E)) | W274: =IF(T274="FR_2SHOP",O274,IF(O274=0,0,ROUNDUP(O274/C274*B274,2))) | Y274: =ROUNDUP(B274,2)-M274-L274-N274-J274-K274-I274-Q274 | Z274: =IF(Y274=W274,"OK","Non")
A275: =C275/SUM(C:C)*(SUM(C:C)+$X$2) | B275: =C275/SUM(C:C)*(SUM(C:C)+SUM($N$3:$O$7))+S275 | C275: =SUM(I275:Q275)-N275-P275 | D275: 8640 | E275: XN093438763JB | F275: 16 | G275: N | H275: NT | O275: 7.8 | S275: =_xlfn.XLOOKUP(E275,'Facture Chronopost'!L:L,'Facture Chronopost'!AA:AA,"") | T275: =IF(COUNTIF('Bibliothèque transporteurs'!C:C,F275)=0,"inconnu",_xlfn.XLOOKUP(F275,'Bibliothèque transporteurs'!C:C,'Bibliothèque transporteurs'!A:A)) | U275: =IF(OR(F275="6C",F275="6B"),_xlfn.XLOOKUP(E275,'Facture Chronopost'!L:L,'Facture Chronopost'!X:X),IF(OR(F275=17,F275=44),F275&"_"&H275,IF(COUNTIF('Bibliothèque transporteurs'!C:C,F275)=0,"inconnu",_xlfn.XLOOKUP(F275,'Bibliothèque transporteurs'!C:C,'Bibliothèque transporteurs'!B:B)))) | V275: =IF(COUNTIF('Bibliothèque transporteurs'!C:C,F275)=0,"inconnu",_xlfn.XLOOKUP(F275,'Bibliothèque transporteurs'!C:C,'Bibliothèque transporteurs'!E:E)) | W275: =IF(T275="FR_2SHOP",O275,IF(O275=0,0,ROUNDUP(O275/C275*B275,2))) | Y275: =ROUNDUP(B275,2)-M275-L275-N275-J275-K275-I275-Q275 | Z275: =IF(Y275=W275,"OK","Non")
A276: =C276/SUM(C:C)*(SUM(C:C)+$X$2) | B276: =C276/SUM(C:C)*(SUM(C:C)+SUM($N$3:$O$7))+S276 | C276: =SUM(I276:Q276)-N276-P276 | D276: 6235 | E276: XN093533177JB | F276: 16 | G276: N | H276: NT | O276: 8.6 | S276: =_xlfn.XLOOKUP(E276,'Facture Chronopost'!L:L,'Facture Chronopost'!AA:AA,"") | T276: =IF(COUNTIF('Bibliothèque transporteurs'!C:C,F276)=0,"inconnu",_xlfn.XLOOKUP(F276,'Bibliothèque transporteurs'!C:C,'Bibliothèque transporteurs'!A:A)) | U276: =IF(OR(F276="6C",F276="6B"),_xlfn.XLOOKUP(E276,'Facture Chronopost'!L:L,'Facture Chronopost'!X:X),IF(OR(F276=17,F276=44),F276&"_"&H276,IF(COUNTIF('Bibliothèque transporteurs'!C:C,F276)=0,"inconnu",_xlfn.XLOOKUP(F276,'Bibliothèque transporteurs'!C:C,'Bibliothèque transporteurs'!B:B)))) | V276: =IF(COUNTIF('Bibliothèque transporteurs'!C:C,F276)=0,"inconnu",_xlfn.XLOOKUP(F276,'Bibliothèque transporteurs'!C:C,'Bibliothèque transporteurs'!E:E)) | W276: =IF(T276="FR_2SHOP",O276,IF(O276=0,0,ROUNDUP(O276/C276*B276,2))) | Y276: =ROUNDUP(B276,2)-M276-L276-N276-J276-K276-I276-Q276 | Z276: =IF(Y276=W276,"OK","Non")
A277: =C277/SUM(C:C)*(SUM(C:C)+$X$2) | B277: =C277/SUM(C:C)*(SUM(C:C)+SUM($N$3:$O$7))+S277 | C277: =SUM(I277:Q277)-N277-P277 | D277: 6235 | E277: XN093534901JB | F277: 16 | G277: N | H277: NT | O277: 8.6 | S277: =_xlfn.XLOOKUP(E277,'Facture Chronopost'!L:L,'Facture Chronopost'!AA:AA,"") | T277: =IF(COUNTIF('Bibliothèque transporteurs'!C:C,F277)=0,"inconnu",_xlfn.XLOOKUP(F277,'Bibliothèque transporteurs'!C:C,'Bibliothèque transporteurs'!A:A)) | U277: =IF(OR(F277="6C",F277="6B"),_xlfn.XLOOKUP(E277,'Facture Chronopost'!L:L,'Facture Chronopost'!X:X),IF(OR(F277=17,F277=44),F277&"_"&H277,IF(COUNTIF('Bibliothèque transporteurs'!C:C,F277)=0,"inconnu",_xlfn.XLOOKUP(F277,'Bibliothèque transporteurs'!C:C,'Bibliothèque transporteurs'!B:B)))) | V277: =IF(COUNTIF('Bibliothèque transporteurs'!C:C,F277)=0,"inconnu",_xlfn.XLOOKUP(F277,'Bibliothèque transporteurs'!C:C,'Bibliothèque transporteurs'!E:E)) | W277: =IF(T277="FR_2SHOP",O277,IF(O277=0,0,ROUNDUP(O277/C277*B277,2))) | Y277: =ROUNDUP(B277,2)-M277-L277-N277-J277-K277-I277-Q277 | Z277: =IF(Y277=W277,"OK","Non")
... A284: =C284/SUM(C:C)*(SUM(C:C)+$X$2) | B284: =C284/SUM(C:C)*(SUM(C:C)+SUM($N$3:$O$7))+S284 | C284: =SUM(I284:Q284)-N284-P284 | D284: 6813 | E284: XN095600400JB | F284: 16 | G284: N | H284: NT | O284: 7.4 | S284: =_xlfn.XLOOKUP(E284,'Facture Chronopost'!L:L,'Facture Chronopost'!AA:AA,"") | T284: =IF(COUNTIF('Bibliothèque transporteurs'!C:C,F284)=0,"inconnu",_xlfn.XLOOKUP(F284,'Bibliothèque transporteurs'!C:C,'Bibliothèque transporteurs'!A:A)) | U284: =IF(OR(F284="6C",F284="6B"),_xlfn.XLOOKUP(E284,'Facture Chronopost'!L:L,'Facture Chronopost'!X:X),IF(OR(F284=17,F284=44),F284&"_"&H284,IF(COUNTIF('Bibliothèque transporteurs'!C:C,F284)=0,"inconnu",_xlfn.XLOOKUP(F284,'Bibliothèque transporteurs'!C:C,'Bibliothèque transporteurs'!B:B)))) | V284: =IF(COUNTIF('Bibliothèque transporteurs'!C:C,F284)=0,"inconnu",_xlfn.XLOOKUP(F284,'Bibliothèque transporteurs'!C:C,'Bibliothèque transporteurs'!E:E)) | W284: =IF(T284="FR_2SHOP",O284,IF(O284=0,0,ROUNDUP(O284/C284*B284,2))) | Y284: =ROUNDUP(B284,2)-M284-L284-N284-J284-K284-I284-Q284 | Z284: =IF(Y284=W284,"OK","Non")
A285: =C285/SUM(C:C)*(SUM(C:C)+$X$2) | B285: =C285/SUM(C:C)*(SUM(C:C)+SUM($N$3:$O$7))+S285 | C285: =SUM(I285:Q285)-N285-P285 | D285: 3752 | E285: XN095606416JB | F285: 16 | G285: N | H285: NT | O285: 7 | Q285: 5 | S285: =_xlfn.XLOOKUP(E285,'Facture Chronopost'!L:L,'Facture Chronopost'!AA:AA,"") | T285: =IF(COUNTIF('Bibliothèque transporteurs'!C:C,F285)=0,"inconnu",_xlfn.XLOOKUP(F285,'Bibliothèque transporteurs'!C:C,'Bibliothèque transporteurs'!A:A)) | U285: =IF(OR(F285="6C",F285="6B"),_xlfn.XLOOKUP(E285,'Facture Chronopost'!L:L,'Facture Chronopost'!X:X),IF(OR(F285=17,F285=44),F285&"_"&H285,IF(COUNTIF('Bibliothèque transporteurs'!C:C,F285)=0,"inconnu",_xlfn.XLOOKUP(F285,'Bibliothèque transporteurs'!C:C,'Bibliothèque transporteurs'!B:B)))) | V285: =IF(COUNTIF('Bibliothèque transporteurs'!C:C,F285)=0,"inconnu",_xlfn.XLOOKUP(F285,'Bibliothèque transporteurs'!C:C,'Bibliothèque transporteurs'!E:E)) | W285: =IF(T285="FR_2SHOP",O285,IF(O285=0,0,ROUNDUP(O285/C285*B285,2))) | Y285: =ROUNDUP(B285,2)-M285-L285-N285-J285-K285-I285-Q285 | Z285: =IF(Y285=W285,"OK","Non")
A286: =C286/SUM(C:C)*(SUM(C:C)+$X$2) | B286: =C286/SUM(C:C)*(SUM(C:C)+SUM($N$3:$O$7))+S286 | C286: =SUM(I286:Q286)-N286-P286 | D286: 6235 | E286: XN095731484JB | F286: 16 | G286: N | H286: NT | O286: 7 | S286: =_xlfn.XLOOKUP(E286,'Facture Chronopost'!L:L,'Facture Chronopost'!AA:AA,"") | T286: =IF(COUNTIF('Bibliothèque transporteurs'!C:C,F286)=0,"inconnu",_xlfn.XLOOKUP(F286,'Bibliothèque transporteurs'!C:C,'Bibliothèque transporteurs'!A:A)) | U286: =IF(OR(F286="6C",F286="6B"),_xlfn.XLOOKUP(E286,'Facture Chronopost'!L:L,'Facture Chronopost'!X:X),IF(OR(F286=17,F286=44),F286&"_"&H286,IF(COUNTIF('Bibliothèque transporteurs'!C:C,F286)=0,"inconnu",_xlfn.XLOOKUP(F286,'Bibliothèque transporteurs'!C:C,'Bibliothèque transporteurs'!B:B)))) | V286: =IF(COUNTIF('Bibliothèque transporteurs'!C:C,F286)=0,"inconnu",_xlfn.XLOOKUP(F286,'Bibliothèque transporteurs'!C:C,'Bibliothèque transporteurs'!E:E)) | W286: =IF(T286="FR_2SHOP",O286,IF(O286=0,0,ROUNDUP(O286/C286*B286,2))) | Y286: =ROUNDUP(B286,2)-M286-L286-N286-J286-K286-I286-Q286 | Z286: =IF(Y286=W286,"OK","Non")
A287: =C287/SUM(C:C)*(SUM(C:C)+$X$2) | B287: =C287/SUM(C:C)*(SUM(C:C)+SUM($N$3:$O$7))+S287 | C287: =SUM(I287:Q287)-N287-P287 | D287: 6235 | E287: XN095734622JB | F287: 16 | G287: N | H287: NT | O287: 9.4 | S287: =_xlfn.XLOOKUP(E287,'Facture Chronopost'!L:L,'Facture Chronopost'!AA:AA,"") | T287: =IF(COUNTIF('Bibliothèque transporteurs'!C:C,F287)=0,"inconnu",_xlfn.XLOOKUP(F287,'Bibliothèque transporteurs'!C:C,'Bibliothèque transporteurs'!A:A)) | U287: =IF(OR(F287="6C",F287="6B"),_xlfn.XLOOKUP(E287,'Facture Chronopost'!L:L,'Facture Chronopost'!X:X),IF(OR(F287=17,F287=44),F287&"_"&H287,IF(COUNTIF('Bibliothèque transporteurs'!C:C,F287)=0,"inconnu",_xlfn.XLOOKUP(F287,'Bibliothèque transporteurs'!C:C,'Bibliothèque transporteurs'!B:B)))) | V287: =IF(COUNTIF('Bibliothèque transporteurs'!C:C,F287)=0,"inconnu",_xlfn.XLOOKUP(F287,'Bibliothèque transporteurs'!C:C,'Bibliothèque transporteurs'!E:E)) | W287: =IF(T287="FR_2SHOP",O287,IF(O287=0,0,ROUNDUP(O287/C287*B287,2))) | Y287: =ROUNDUP(B287,2)-M287-L287-N287-J287-K287-I287-Q287 | Z287: =IF(Y287=W287,"OK","Non")
A288: =C288/SUM(C:C)*(SUM(C:C)+$X$2) | B288: =C288/SUM(C:C)*(SUM(C:C)+SUM($N$3:$O$7))+S288 | C288: =SUM(I288:Q288)-N288-P288 | D288: 6235 | E288: XN095737632JB | F288: 16 | G288: N | H288: NT | K288: 6 | O288: 18.2 | S288: =_xlfn.XLOOKUP(E288,'Facture Chronopost'!L:L,'Facture Chronopost'!AA:AA,"") | T288: =IF(COUNTIF('Bibliothèque transporteurs'!C:C,F288)=0,"inconnu",_xlfn.XLOOKUP(F288,'Bibliothèque transporteurs'!C:C,'Bibliothèque transporteurs'!A:A)) | U288: =IF(OR(F288="6C",F288="6B"),_xlfn.XLOOKUP(E288,'Facture Chronopost'!L:L,'Facture Chronopost'!X:X),IF(OR(F288=17,F288=44),F288&"_"&H288,IF(COUNTIF('Bibliothèque transporteurs'!C:C,F288)=0,"inconnu",_xlfn.XLOOKUP(F288,'Bibliothèque transporteurs'!C:C,'Bibliothèque transporteurs'!B:B)))) | V288: =IF(COUNTIF('Bibliothèque transporteurs'!C:C,F288)=0,"inconnu",_xlfn.XLOOKUP(F288,'Bibliothèque transporteurs'!C:C,'Bibliothèque transporteurs'!E:E)) | W288: =IF(T288="FR_2SHOP",O288,IF(O288=0,0,ROUNDUP(O288/C288*B288,2))) | Y288: =ROUNDUP(B288,2)-M288-L288-N288-J288-K288-I288-Q288 | Z288: =IF(Y288=W288,"OK","Non")
A289: =C289/SUM(C:C)*(SUM(C:C)+$X$2) | B289: =C289/SUM(C:C)*(SUM(C:C)+SUM($N$3:$O$7))+S289 | C289: =SUM(I289:Q289)-N289-P289 | D289: 6235 | E289: XN095755110JB | F289: 16 | G289: N | H289: NT | O289: 8.6 | S289: =_xlfn.XLOOKUP(E289,'Facture Chronopost'!L:L,'Facture Chronopost'!AA:AA,"") | T289: =IF(COUNTIF('Bibliothèque transporteurs'!C:C,F289)=0,"inconnu",_xlfn.XLOOKUP(F289,'Bibliothèque transporteurs'!C:C,'Bibliothèque transporteurs'!A:A)) | U289: =IF(OR(F289="6C",F289="6B"),_xlfn.XLOOKUP(E289,'Facture Chronopost'!L:L,'Facture Chronopost'!X:X),IF(OR(F289=17,F289=44),F289&"_"&H289,IF(COUNTIF('Bibliothèque transporteurs'!C:C,F289)=0,"inconnu",_xlfn.XLOOKUP(F289,'Bibliothèque transporteurs'!C:C,'Bibliothèque transporteurs'!B:B)))) | V289: =IF(COUNTIF('Bibliothèque transporteurs'!C:C,F289)=0,"inconnu",_xlfn.XLOOKUP(F289,'Bibliothèque transporteurs'!C:C,'Bibliothèque transporteurs'!E:E)) | W289: =IF(T289="FR_2SHOP",O289,IF(O289=0,0,ROUNDUP(O289/C289*B289,2))) | Y289: =ROUNDUP(B289,2)-M289-L289-N289-J289-K289-I289-Q289 | Z289: =IF(Y289=W289,"OK","Non")
A290: =C290/SUM(C:C)*(SUM(C:C)+$X$2) | B290: =C290/SUM(C:C)*(SUM(C:C)+SUM($N$3:$O$7))+S290 | C290: =SUM(I290:Q290)-N290-P290 | D290: 6235 | E290: XN095762929JB | F290: 16 | G290: N | H290: NT | O290: 8.6 | S290: =_xlfn.XLOOKUP(E290,'Facture Chronopost'!L:L,'Facture Chronopost'!AA:AA,"") | T290: =IF(COUNTIF('Bibliothèque transporteurs'!C:C,F290)=0,"inconnu",_xlfn.XLOOKUP(F290,'Bibliothèque transporteurs'!C:C,'Bibliothèque transporteurs'!A:A)) | U290: =IF(OR(F290="6C",F290="6B"),_xlfn.XLOOKUP(E290,'Facture Chronopost'!L:L,'Facture Chronopost'!X:X),IF(OR(F290=17,F290=44),F290&"_"&H290,IF(COUNTIF('Bibliothèque transporteurs'!C:C,F290)=0,"inconnu",_xlfn.XLOOKUP(F290,'Bibliothèque transporteurs'!C:C,'Bibliothèque transporteurs'!B:B)))) | V290: =IF(COUNTIF('Bibliothèque transporteurs'!C:C,F290)=0,"inconnu",_xlfn.XLOOKUP(F290,'Bibliothèque transporteurs'!C:C,'Bibliothèque transporteurs'!E:E)) | W290: =IF(T290="FR_2SHOP",O290,IF(O290=0,0,ROUNDUP(O290/C290*B290,2))) | Y290: =ROUNDUP(B290,2)-M290-L290-N290-J290-K290-I290-Q290 | Z290: =IF(Y290=W290,"OK","Non")
A291: =C291/SUM(C:C)*(SUM(C:C)+$X$2) | B291: =C291/SUM(C:C)*(SUM(C:C)+SUM($N$3:$O$7))+S291 | C291: =SUM(I291:Q291)-N291-P291 | D291: 6235 | E291: XN095781154JB | F291: 16 | G291: N | H291: NT | O291: 7 | Q291: 5 | S291: =_xlfn.XLOOKUP(E291,'Facture Chronopost'!L:L,'Facture Chronopost'!AA:AA,"") | T291: =IF(COUNTIF('Bibliothèque transporteurs'!C:C,F291)=0,"inconnu",_xlfn.XLOOKUP(F291,'Bibliothèque transporteurs'!C:C,'Bibliothèque transporteurs'!A:A)) | U291: =IF(OR(F291="6C",F291="6B"),_xlfn.XLOOKUP(E291,'Facture Chronopost'!L:L,'Facture Chronopost'!X:X),IF(OR(F291=17,F291=44),F291&"_"&H291,IF(COUNTIF('Bibliothèque transporteurs'!C:C,F291)=0,"inconnu",_xlfn.XLOOKUP(F291,'Bibliothèque transporteurs'!C:C,'Bibliothèque transporteurs'!B:B)))) | V291: =IF(COUNTIF('Bibliothèque transporteurs'!C:C,F291)=0,"inconnu",_xlfn.XLOOKUP(F291,'Bibliothèque transporteurs'!C:C,'Bibliothèque transporteurs'!E:E)) | W291: =IF(T291="FR_2SHOP",O291,IF(O291=0,0,ROUNDUP(O291/C291*B291,2))) | Y291: =ROUNDUP(B291,2)-M291-L291-N291-J291-K291-I291-Q291 | Z291: =IF(Y291=W291,"OK","Non")
A292: =C292/SUM(C:C)*(SUM(C:C)+$X$2) | B292: =C292/SUM(C:C)*(SUM(C:C)+SUM($N$3:$O$7))+S292 | C292: =SUM(I292:Q292)-N292-P292 | D292: 4813 | E292: XN095805607JB | F292: 16 | G292: N | H292: NT | O292: 7 | S292: =_xlfn.XLOOKUP(E292,'Facture Chronopost'!L:L,'Facture Chronopost'!AA:AA,"") | T292: =IF(COUNTIF('Bibliothèque transporteurs'!C:C,F292)=0,"inconnu",_xlfn.XLOOKUP(F292,'Bibliothèque transporteurs'!C:C,'Bibliothèque transporteurs'!A:A)) | U292: =IF(OR(F292="6C",F292="6B"),_xlfn.XLOOKUP(E292,'Facture Chronopost'!L:L,'Facture Chronopost'!X:X),IF(OR(F292=17,F292=44),F292&"_"&H292,IF(COUNTIF('Bibliothèque transporteurs'!C:C,F292)=0,"inconnu",_xlfn.XLOOKUP(F292,'Bibliothèque transporteurs'!C:C,'Bibliothèque transporteurs'!B:B)))) | V292: =IF(COUNTIF('Bibliothèque transporteurs'!C:C,F292)=0,"inconnu",_xlfn.XLOOKUP(F292,'Bibliothèque transporteurs'!C:C,'Bibliothèque transporteurs'!E:E)) | W292: =IF(T292="FR_2SHOP",O292,IF(O292=0,0,ROUNDUP(O292/C292*B292,2))) | Y292: =ROUNDUP(B292,2)-M292-L292-N292-J292-K292-I292-Q292 | Z292: =IF(Y292=W292,"OK","Non")
A293: =C293/SUM(C:C)*(SUM(C:C)+$X$2) | B293: =C293/SUM(C:C)*(SUM(C:C)+SUM($N$3:$O$7))+S293 | C293: =SUM(I293:Q293)-N293-P293 | D293: 8656 | E293: XN095806749JB | F293: 16 | G293: N | H293: NT | O293: 7.8 | S293: =_xlfn.XLOOKUP(E293,'Facture Chronopost'!L:L,'Facture Chronopost'!AA:AA,"") | T293: =IF(COUNTIF('Bibliothèque transporteurs'!C:C,F293)=0,"inconnu",_xlfn.XLOOKUP(F293,'Bibliothèque transporteurs'!C:C,'Bibliothèque transporteurs'!A:A)) | U293: =IF(OR(F293="6C",F293="6B"),_xlfn.XLOOKUP(E293,'Facture Chronopost'!L:L,'Facture Chronopost'!X:X),IF(OR(F293=17,F293=44),F293&"_"&H293,IF(COUNTIF('Bibliothèque transporteurs'!C:C,F293)=0,"inconnu",_xlfn.XLOOKUP(F293,'Bibliothèque transporteurs'!C:C,'Bibliothèque transporteurs'!B:B)))) | V293: =IF(COUNTIF('Bibliothèque transporteurs'!C:C,F293)=0,"inconnu",_xlfn.XLOOKUP(F293,'Bibliothèque transporteurs'!C:C,'Bibliothèque transporteurs'!E:E)) | W293: =IF(T293="FR_2SHOP",O293,IF(O293=0,0,ROUNDUP(O293/C293*B293,2))) | Y293: =ROUNDUP(B293,2)-M293-L293-N293-J293-K293-I293-Q293 | Z293: =IF(Y293=W293,"OK","Non")
A294: =C294/SUM(C:C)*(SUM(C:C)+$X$2) | B294: =C294/SUM(C:C)*(SUM(C:C)+SUM($N$3:$O$7))+S294 | C294: =SUM(I294:Q294)-N294-P294 | D294: 8656 | E294: XN095809419JB | F294: 16 | G294: N | H294: NT | O294: 7.8 | S294: =_xlfn.XLOOKUP(E294,'Facture Chronopost'!L:L,'Facture Chronopost'!AA:AA,"") | T294: =IF(COUNTIF('Bibliothèque transporteurs'!C:C,F294)=0,"inconnu",_xlfn.XLOOKUP(F294,'Bibliothèque transporteurs'!C:C,'Bibliothèque transporteurs'!A:A)) | U294: =IF(OR(F294="6C",F294="6B"),_xlfn.XLOOKUP(E294,'Facture Chronopost'!L:L,'Facture Chronopost'!X:X),IF(OR(F294=17,F294=44),F294&"_"&H294,IF(COUNTIF('Bibliothèque transporteurs'!C:C,F294)=0,"inconnu",_xlfn.XLOOKUP(F294,'Bibliothèque transporteurs'!C:C,'Bibliothèque transporteurs'!B:B)))) | V294: =IF(COUNTIF('Bibliothèque transporteurs'!C:C,F294)=0,"inconnu",_xlfn.XLOOKUP(F294,'Bibliothèque transporteurs'!C:C,'Bibliothèque transporteurs'!E:E)) | W294: =IF(T294="FR_2SHOP",O294,IF(O294=0,0,ROUNDUP(O294/C294*B294,2))) | Y294: =ROUNDUP(B294,2)-M294-L294-N294-J294-K294-I294-Q294 | Z294: =IF(Y294=W294,"OK","Non")
A295: =C295/SUM(C:C)*(SUM(C:C)+$X$2) | B295: =C295/SUM(C:C)*(SUM(C:C)+SUM($N$3:$O$7))+S295 | C295: =SUM(I295:Q295)-N295-P295 | D295: 4813 | E295: XN095846005JB | F295: 16 | G295: N | H295: NT | O295: 7.4 | S295: =_xlfn.XLOOKUP(E295,'Facture Chronopost'!L:L,'Facture Chronopost'!AA:AA,"") | T295: =IF(COUNTIF('Bibliothèque transporteurs'!C:C,F295)=0,"inconnu",_xlfn.XLOOKUP(F295,'Bibliothèque transporteurs'!C:C,'Bibliothèque transporteurs'!A:A)) | U295: =IF(OR(F295="6C",F295="6B"),_xlfn.XLOOKUP(E295,'Facture Chronopost'!L:L,'Facture Chronopost'!X:X),IF(OR(F295=17,F295=44),F295&"_"&H295,IF(COUNTIF('Bibliothèque transporteurs'!C:C,F295)=0,"inconnu",_xlfn.XLOOKUP(F295,'Bibliothèque transporteurs'!C:C,'Bibliothèque transporteurs'!B:B)))) | V295: =IF(COUNTIF('Bibliothèque transporteurs'!C:C,F295)=0,"inconnu",_xlfn.XLOOKUP(F295,'Bibliothèque transporteurs'!C:C,'Bibliothèque transporteurs'!E:E)) | W295: =IF(T295="FR_2SHOP",O295,IF(O295=0,0,ROUNDUP(O295/C295*B295,2))) | Y295: =ROUNDUP(B295,2)-M295-L295-N295-J295-K295-I295-Q295 | Z295: =IF(Y295=W295,"OK","Non")
A296: =C296/SUM(C:C)*(SUM(C:C)+$X$2) | B296: =C296/SUM(C:C)*(SUM(C:C)+SUM($N$3:$O$7))+S296 | C296: =SUM(I296:Q296)-N296-P296 | D296: 4813 | E296: XN095847788JB | F296: 16 | G296: N | H296: NT | O296: 7.8 | S296: =_xlfn.XLOOKUP(E296,'Facture Chronopost'!L:L,'Facture Chronopost'!AA:AA,"") | T296: =IF(COUNTIF('Bibliothèque transporteurs'!C:C,F296)=0,"inconnu",_xlfn.XLOOKUP(F296,'Bibliothèque transporteurs'!C:C,'Bibliothèque transporteurs'!A:A)) | U296: =IF(OR(F296="6C",F296="6B"),_xlfn.XLOOKUP(E296,'Facture Chronopost'!L:L,'Facture Chronopost'!X:X),IF(OR(F296=17,F296=44),F296&"_"&H296,IF(COUNTIF('Bibliothèque transporteurs'!C:C,F296)=0,"inconnu",_xlfn.XLOOKUP(F296,'Bibliothèque transporteurs'!C:C,'Bibliothèque transporteurs'!B:B)))) | V296: =IF(COUNTIF('Bibliothèque transporteurs'!C:C,F296)=0,"inconnu",_xlfn.XLOOKUP(F296,'Bibliothèque transporteurs'!C:C,'Bibliothèque transporteurs'!E:E)) | W296: =IF(T296="FR_2SHOP",O296,IF(O296=0,0,ROUNDUP(O296/C296*B296,2))) | Y296: =ROUNDUP(B296,2)-M296-L296-N296-J296-K296-I296-Q296 | Z296: =IF(Y296=W296,"OK","Non")
A297: =C297/SUM(C:C)*(SUM(C:C)+$X$2) | B297: =C297/SUM(C:C)*(SUM(C:C)+SUM($N$3:$O$7))+S297 | C297: =SUM(I297:Q297)-N297-P297 | D297: 6235 | E297: XN096178886JB | F297: 16 | G297: N | H297: NT | O297: 8.6 | S297: =_xlfn.XLOOKUP(E297,'Facture Chronopost'!L:L,'Facture Chronopost'!AA:AA,"") | T297: =IF(COUNTIF('Bibliothèque transporteurs'!C:C,F297)=0,"inconnu",_xlfn.XLOOKUP(F297,'Bibliothèque transporteurs'!C:C,'Bibliothèque transporteurs'!A:A)) | U297: =IF(OR(F297="6C",F297="6B"),_xlfn.XLOOKUP(E297,'Facture Chronopost'!L:L,'Facture Chronopost'!X:X),IF(OR(F297=17,F297=44),F297&"_"&H297,IF(COUNTIF('Bibliothèque transporteurs'!C:C,F297)=0,"inconnu",_xlfn.XLOOKUP(F297,'Bibliothèque transporteurs'!C:C,'Bibliothèque transporteurs'!B:B)))) | V297: =IF(COUNTIF('Bibliothèque transporteurs'!C:C,F297)=0,"inconnu",_xlfn.XLOOKUP(F297,'Bibliothèque transporteurs'!C:C,'Bibliothèque transporteurs'!E:E)) | W297: =IF(T297="FR_2SHOP",O297,IF(O297=0,0,ROUNDUP(O297/C297*B297,2))) | Y297: =ROUNDUP(B297,2)-M297-L297-N297-J297-K297-I297-Q297 | Z297: =IF(Y297=W297,"OK","Non")
A298: =C298/SUM(C:C)*(SUM(C:C)+$X$2) | B298: =C298/SUM(C:C)*(SUM(C:C)+SUM($N$3:$O$7))+S298 | C298: =SUM(I298:Q298)-N298-P298 | D298: 6235 | E298: XN096181531JB | F298: 16 | G298: N | H298: NT | O298: 8.6 | S298: =_xlfn.XLOOKUP(E298,'Facture Chronopost'!L:L,'Facture Chronopost'!AA:AA,"") | T298: =IF(COUNTIF('Bibliothèque transporteurs'!C:C,F298)=0,"inconnu",_xlfn.XLOOKUP(F298,'Bibliothèque transporteurs'!C:C,'Bibliothèque transporteurs'!A:A)) | U298: =IF(OR(F298="6C",F298="6B"),_xlfn.XLOOKUP(E298,'Facture Chronopost'!L:L,'Facture Chronopost'!X:X),IF(OR(F298=17,F298=44),F298&"_"&H298,IF(COUNTIF('Bibliothèque transporteurs'!C:C,F298)=0,"inconnu",_xlfn.XLOOKUP(F298,'Bibliothèque transporteurs'!C:C,'Bibliothèque transporteurs'!B:B)))) | V298: =IF(COUNTIF('Bibliothèque transporteurs'!C:C,F298)=0,"inconnu",_xlfn.XLOOKUP(F298,'Bibliothèque transporteurs'!C:C,'Bibliothèque transporteurs'!E:E)) | W298: =IF(T298="FR_2SHOP",O298,IF(O298=0,0,ROUNDUP(O298/C298*B298,2))) | Y298: =ROUNDUP(B298,2)-M298-L298-N298-J298-K298-I298-Q298 | Z298: =IF(Y298=W298,"OK","Non")
A299: =C299/SUM(C:C)*(SUM(C:C)+$X$2) | B299: =C299/SUM(C:C)*(SUM(C:C)+SUM($N$3:$O$7))+S299 | C299: =SUM(I299:Q299)-N299-P299 | D299: 4813 | E299: XN096220941JB | F299: 16 | G299: N | H299: ND | O299: 7 | S299: =_xlfn.XLOOKUP(E299,'Facture Chronopost'!L:L,'Facture Chronopost'!AA:AA,"") | T299: =IF(COUNTIF('Bibliothèque transporteurs'!C:C,F299)=0,"inconnu",_xlfn.XLOOKUP(F299,'Bibliothèque transporteurs'!C:C,'Bibliothèque transporteurs'!A:A)) | U299: =IF(OR(F299="6C",F299="6B"),_xlfn.XLOOKUP(E299,'Facture Chronopost'!L:L,'Facture Chronopost'!X:X),IF(OR(F299=17,F299=44),F299&"_"&H299,IF(COUNTIF('Bibliothèque transporteurs'!C:C,F299)=0,"inconnu",_xlfn.XLOOKUP(F299,'Bibliothèque transporteurs'!C:C,'Bibliothèque transporteurs'!B:B)))) | V299: =IF(COUNTIF('Bibliothèque transporteurs'!C:C,F299)=0,"inconnu",_xlfn.XLOOKUP(F299,'Bibliothèque transporteurs'!C:C,'Bibliothèque transporteurs'!E:E)) | W299: =IF(T299="FR_2SHOP",O299,IF(O299=0,0,ROUNDUP(O299/C299*B299,2))) | Y299: =ROUNDUP(B299,2)-M299-L299-N299-J299-K299-I299-Q299 | Z299: =IF(Y299=W299,"OK","Non")
A300: =C300/SUM(C:C)*(SUM(C:C)+$X$2) | B300: =C300/SUM(C:C)*(SUM(C:C)+SUM($N$3:$O$7))+S300 | C300: =SUM(I300:Q300)-N300-P300 | D300: 3752 | E300: XN096222647JB | F300: 16 | G300: N | H300: NT | O300: 7 | S300: =_xlfn.XLOOKUP(E300,'Facture Chronopost'!L:L,'Facture Chronopost'!AA:AA,"") | T300: =IF(COUNTIF('Bibliothèque transporteurs'!C:C,F300)=0,"inconnu",_xlfn.XLOOKUP(F300,'Bibliothèque transporteurs'!C:C,'Bibliothèque transporteurs'!A:A)) | U300: =IF(OR(F300="6C",F300="6B"),_xlfn.XLOOKUP(E300,'Facture Chronopost'!L:L,'Facture Chronopost'!X:X),IF(OR(F300=17,F300=44),F300&"_"&H300,IF(COUNTIF('Bibliothèque transporteurs'!C:C,F300)=0,"inconnu",_xlfn.XLOOKUP(F300,'Bibliothèque transporteurs'!C:C,'Bibliothèque transporteurs'!B:B)))) | V300: =IF(COUNTIF('Bibliothèque transporteurs'!C:C,F300)=0,"inconnu",_xlfn.XLOOKUP(F300,'Bibliothèque transporteurs'!C:C,'Bibliothèque transporteurs'!E:E)) | W300: =IF(T300="FR_2SHOP",O300,IF(O300=0,0,ROUNDUP(O300/C300*B300,2))) | Y300: =ROUNDUP(B300,2)-M300-L300-N300-J300-K300-I300-Q300 | Z300: =IF(Y300=W300,"OK","Non")
A301: =C301/SUM(C:C)*(SUM(C:C)+$X$2) | B301: =C301/SUM(C:C)*(SUM(C:C)+SUM($N$3:$O$7))+S301 | C301: =SUM(I301:Q301)-N301-P301 | D301: 6235 | E301: XN096645359JB | F301: 16 | G301: N | H301: NT | O301: 8.6 | S301: =_xlfn.XLOOKUP(E301,'Facture Chronopost'!L:L,'Facture Chronopost'!AA:AA,"") | T301: =IF(COUNTIF('Bibliothèque transporteurs'!C:C,F301)=0,"inconnu",_xlfn.XLOOKUP(F301,'Bibliothèque transporteurs'!C:C,'Bibliothèque transporteurs'!A:A)) | U301: =IF(OR(F301="6C",F301="6B"),_xlfn.XLOOKUP(E301,'Facture Chronopost'!L:L,'Facture Chronopost'!X:X),IF(OR(F301=17,F301=44),F301&"_"&H301,IF(COUNTIF('Bibliothèque transporteurs'!C:C,F301)=0,"inconnu",_xlfn.XLOOKUP(F301,'Bibliothèque transporteurs'!C:C,'Bibliothèque transporteurs'!B:B)))) | V301: =IF(COUNTIF('Bibliothèque transporteurs'!C:C,F301)=0,"inconnu",_xlfn.XLOOKUP(F301,'Bibliothèque transporteurs'!C:C,'Bibliothèque transporteurs'!E:E)) | W301: =IF(T301="FR_2SHOP",O301,IF(O301=0,0,ROUNDUP(O301/C301*B301,2))) | Y301: =ROUNDUP(B301,2)-M301-L301-N301-J301-K301-I301-Q301 | Z301: =IF(Y301=W301,"OK","Non")
A302: =C302/SUM(C:C)*(SUM(C:C)+$X$2) | B302: =C302/SUM(C:C)*(SUM(C:C)+SUM($N$3:$O$7))+S302 | C302: =SUM(I302:Q302)-N302-P302 | D302: 6235 | E302: XN096647329JB | F302: 16 | G302: N | H302: NT | O302: 7 | S302: =_xlfn.XLOOKUP(E302,'Facture Chronopost'!L:L,'Facture Chronopost'!AA:AA,"") | T302: =IF(COUNTIF('Bibliothèque transporteurs'!C:C,F302)=0,"inconnu",_xlfn.XLOOKUP(F302,'Bibliothèque transporteurs'!C:C,'Bibliothèque transporteurs'!A:A)) | U302: =IF(OR(F302="6C",F302="6B"),_xlfn.XLOOKUP(E302,'Facture Chronopost'!L:L,'Facture Chronopost'!X:X),IF(OR(F302=17,F302=44),F302&"_"&H302,IF(COUNTIF('Bibliothèque transporteurs'!C:C,F302)=0,"inconnu",_xlfn.XLOOKUP(F302,'Bibliothèque transporteurs'!C:C,'Bibliothèque transporteurs'!B:B)))) | V302: =IF(COUNTIF('Bibliothèque transporteurs'!C:C,F302)=0,"inconnu",_xlfn.XLOOKUP(F302,'Bibliothèque transporteurs'!C:C,'Bibliothèque transporteurs'!E:E)) | W302: =IF(T302="FR_2SHOP",O302,IF(O302=0,0,ROUNDUP(O302/C302*B302,2))) | Y302: =ROUNDUP(B302,2)-M302-L302-N302-J302-K302-I302-Q302 | Z302: =IF(Y302=W302,"OK","Non")
A303: =C303/SUM(C:C)*(SUM(C:C)+$X$2) | B303: =C303/SUM(C:C)*(SUM(C:C)+SUM($N$3:$O$7))+S303 | C303: =SUM(I303:Q303)-N303-P303 | D303: 3752 | E303: XN096658556JB | F303: 16 | G303: N | H303: NT | O303: 7 | S303: =_xlfn.XLOOKUP(E303,'Facture Chronopost'!L:L,'Facture Chronopost'!AA:AA,"") | T303: =IF(COUNTIF('Bibliothèque transporteurs'!C:C,F303)=0,"inconnu",_xlfn.XLOOKUP(F303,'Bibliothèque transporteurs'!C:C,'Bibliothèque transporteurs'!A:A)) | U303: =IF(OR(F303="6C",F303="6B"),_xlfn.XLOOKUP(E303,'Facture Chronopost'!L:L,'Facture Chronopost'!X:X),IF(OR(F303=17,F303=44),F303&"_"&H303,IF(COUNTIF('Bibliothèque transporteurs'!C:C,F303)=0,"inconnu",_xlfn.XLOOKUP(F303,'Bibliothèque transporteurs'!C:C,'Bibliothèque transporteurs'!B:B)))) | V303: =IF(COUNTIF('Bibliothèque transporteurs'!C:C,F303)=0,"inconnu",_xlfn.XLOOKUP(F303,'Bibliothèque transporteurs'!C:C,'Bibliothèque transporteurs'!E:E)) | W303: =IF(T303="FR_2SHOP",O303,IF(O303=0,0,ROUNDUP(O303/C303*B303,2))) | Y303: =ROUNDUP(B303,2)-M303-L303-N303-J303-K303-I303-Q303 | Z303: =IF(Y303=W303,"OK","Non")
...

Sheet Fichier import
A1: Transporteur | B1: Date validité tarif | C1: Réf.1 | D1: Réf. 2 | E1: Id client | F1: N° Tracking | G1: Nom | H1: E / P | I1: Pays | J1: Zone | K1: Nbr Colis | L1: Poids | M1: mode envoi | N1: TVA | O1: Droits et taxes | P1: Assurance | Q1: Zones éloignées | R1: Colis volumineux | S1: Adresses | T1: Frêt | U1: plus-value BtoC | V1: gazole | W1: 2SHOP : ne pas mettre de gazole
A2: =TCD!V3 | B2: 46143 | F2: =TCD!E3 | H2: =IF(RIGHT(J2,3)="BTB","E","P") | I2: =LOOKUP(F2,'Facture Chronopost'!L:L,'Facture Chronopost'!H:H) | J2: =TCD!U3 | K2: 1 | L2: =_xlfn.XLOOKUP(F2,'TCD poids'!A:A,'TCD poids'!C:C) | M2: =TCD!T3 | N2: =IF(I2="",0.2,LOOKUP(I2,'Pays TVA'!A:A,'Pays TVA'!B:B)) | O2: =IF(TCD!M3="","",TCD!M3) | P2: =IF(TCD!J3="","",TCD!J3) | Q2: =IF(AND(TCD!L3="",TCD!Q3=""),"",IF(SUM(TCD!L3,TCD!Q3)>15,29,9.5)) | R2: =_xlfn.XLOOKUP(F2,TCD!E:E,TCD!K:K,"") | S2: =IF(TCD!I3="","",IF(TCD!I3>8.5,17,8.5)) | T2: =TCD!Y3 | W2: dans les coûts de revient
A3: =TCD!V4 | B3: =B2 | F3: =TCD!E4 | H3: =IF(RIGHT(J3,3)="BTB","E","P") | I3: =LOOKUP(F3,'Facture Chronopost'!L:L,'Facture Chronopost'!H:H) | J3: =TCD!U4 | K3: =K2 | L3: =_xlfn.XLOOKUP(F3,'TCD poids'!A:A,'TCD poids'!C:C) | M3: =TCD!T4 | N3: =IF(I3="",0.2,LOOKUP(I3,'Pays TVA'!A:A,'Pays TVA'!B:B)) | O3: =IF(TCD!M4="","",TCD!M4) | P3: =IF(TCD!J4="","",TCD!J4) | Q3: =IF(AND(TCD!L4="",TCD!Q4=""),"",IF(SUM(TCD!L4,TCD!Q4)>15,29,9.5)) | R3: =_xlfn.XLOOKUP(F3,TCD!E:E,TCD!K:K,"") | S3: =IF(TCD!I4="","",IF(TCD!I4>8.5,17,8.5)) | T3: =TCD!Y4
A4: =TCD!V5 | B4: =B3 | F4: =TCD!E5 | H4: =IF(RIGHT(J4,3)="BTB","E","P") | I4: =LOOKUP(F4,'Facture Chronopost'!L:L,'Facture Chronopost'!H:H) | J4: =TCD!U5 | K4: =K3 | L4: =_xlfn.XLOOKUP(F4,'TCD poids'!A:A,'TCD poids'!C:C) | M4: =TCD!T5 | N4: =IF(I4="",0.2,LOOKUP(I4,'Pays TVA'!A:A,'Pays TVA'!B:B)) | O4: =IF(TCD!M5="","",TCD!M5) | P4: =IF(TCD!J5="","",TCD!J5) | Q4: =IF(AND(TCD!L5="",TCD!Q5=""),"",IF(SUM(TCD!L5,TCD!Q5)>15,29,9.5)) | R4: =_xlfn.XLOOKUP(F4,TCD!E:E,TCD!K:K,"") | S4: =IF(TCD!I5="","",IF(TCD!I5>8.5,17,8.5)) | T4: =TCD!Y5 | W4: Renseigner "Pays"
A5: =TCD!V6 | B5: =B4 | F5: =TCD!E6 | H5: =IF(RIGHT(J5,3)="BTB","E","P") | I5: =LOOKUP(F5,'Facture Chronopost'!L:L,'Facture Chronopost'!H:H) | J5: =TCD!U6 | K5: =K4 | L5: =_xlfn.XLOOKUP(F5,'TCD poids'!A:A,'TCD poids'!C:C) | M5: =TCD!T6 | N5: =IF(I5="",0.2,LOOKUP(I5,'Pays TVA'!A:A,'Pays TVA'!B:B)) | O5: =IF(TCD!M6="","",TCD!M6) | P5: =IF(TCD!J6="","",TCD!J6) | Q5: =IF(AND(TCD!L6="",TCD!Q6=""),"",IF(SUM(TCD!L6,TCD!Q6)>15,29,9.5)) | R5: =_xlfn.XLOOKUP(F5,TCD!E:E,TCD!K:K,"") | S5: =IF(TCD!I6="","",IF(TCD!I6>8.5,17,8.5)) | T5: =TCD!Y6
A6: =TCD!V7 | B6: =B5 | F6: =TCD!E7 | H6: =IF(RIGHT(J6,3)="BTB","E","P") | I6: =LOOKUP(F6,'Facture Chronopost'!L:L,'Facture Chronopost'!H:H) | J6: =TCD!U7 | K6: =K5 | L6: =_xlfn.XLOOKUP(F6,'TCD poids'!A:A,'TCD poids'!C:C) | M6: =TCD!T7 | N6: =IF(I6="",0.2,LOOKUP(I6,'Pays TVA'!A:A,'Pays TVA'!B:B)) | O6: =IF(TCD!M7="","",TCD!M7) | P6: =IF(TCD!J7="","",TCD!J7) | Q6: =IF(AND(TCD!L7="",TCD!Q7=""),"",IF(SUM(TCD!L7,TCD!Q7)>15,29,9.5)) | R6: =_xlfn.XLOOKUP(F6,TCD!E:E,TCD!K:K,"") | S6: =IF(TCD!I7="","",IF(TCD!I7>8.5,17,8.5)) | T6: =TCD!Y7
A7: =TCD!V8 | B7: =B6 | F7: =TCD!E8 | H7: =IF(RIGHT(J7,3)="BTB","E","P") | I7: =LOOKUP(F7,'Facture Chronopost'!L:L,'Facture Chronopost'!H:H) | J7: =TCD!U8 | K7: =K6 | L7: =_xlfn.XLOOKUP(F7,'TCD poids'!A:A,'TCD poids'!C:C) | M7: =TCD!T8 | N7: =IF(I7="",0.2,LOOKUP(I7,'Pays TVA'!A:A,'Pays TVA'!B:B)) | O7: =IF(TCD!M8="","",TCD!M8) | P7: =IF(TCD!J8="","",TCD!J8) | Q7: =IF(AND(TCD!L8="",TCD!Q8=""),"",IF(SUM(TCD!L8,TCD!Q8)>15,29,9.5)) | R7: =_xlfn.XLOOKUP(F7,TCD!E:E,TCD!K:K,"") | S7: =IF(TCD!I8="","",IF(TCD!I8>8.5,17,8.5)) | T7: =TCD!Y8
A8: =TCD!V9 | B8: =B7 | F8: =TCD!E9 | H8: =IF(RIGHT(J8,3)="BTB","E","P") | I8: =LOOKUP(F8,'Facture Chronopost'!L:L,'Facture Chronopost'!H:H) | J8: =TCD!U9 | K8: =K7 | L8: =_xlfn.XLOOKUP(F8,'TCD poids'!A:A,'TCD poids'!C:C) | M8: =TCD!T9 | N8: =IF(I8="",0.2,LOOKUP(I8,'Pays TVA'!A:A,'Pays TVA'!B:B)) | O8: =IF(TCD!M9="","",TCD!M9) | P8: =IF(TCD!J9="","",TCD!J9) | Q8: =IF(AND(TCD!L9="",TCD!Q9=""),"",IF(SUM(TCD!L9,TCD!Q9)>15,29,9.5)) | R8: =_xlfn.XLOOKUP(F8,TCD!E:E,TCD!K:K,"") | S8: =IF(TCD!I9="","",IF(TCD!I9>8.5,17,8.5)) | T8: =TCD!Y9
A9: =TCD!V10 | B9: =B8 | F9: =TCD!E10 | H9: =IF(RIGHT(J9,3)="BTB","E","P") | I9: =LOOKUP(F9,'Facture Chronopost'!L:L,'Facture Chronopost'!H:H) | J9: =TCD!U10 | K9: =K8 | L9: =_xlfn.XLOOKUP(F9,'TCD poids'!A:A,'TCD poids'!C:C) | M9: =TCD!T10 | N9: =IF(I9="",0.2,LOOKUP(I9,'Pays TVA'!A:A,'Pays TVA'!B:B)) | O9: =IF(TCD!M10="","",TCD!M10) | P9: =IF(TCD!J10="","",TCD!J10) | Q9: =IF(AND(TCD!L10="",TCD!Q10=""),"",IF(SUM(TCD!L10,TCD!Q10)>15,29,9.5)) | R9: =_xlfn.XLOOKUP(F9,TCD!E:E,TCD!K:K,"") | S9: =IF(TCD!I10="","",IF(TCD!I10>8.5,17,8.5)) | T9: =TCD!Y10
A10: =TCD!V11 | B10: =B9 | F10: =TCD!E11 | H10: =IF(RIGHT(J10,3)="BTB","E","P") | I10: =LOOKUP(F10,'Facture Chronopost'!L:L,'Facture Chronopost'!H:H) | J10: =TCD!U11 | K10: =K9 | L10: =_xlfn.XLOOKUP(F10,'TCD poids'!A:A,'TCD poids'!C:C) | M10: =TCD!T11 | N10: =IF(I10="",0.2,LOOKUP(I10,'Pays TVA'!A:A,'Pays TVA'!B:B)) | O10: =IF(TCD!M11="","",TCD!M11) | P10: =IF(TCD!J11="","",TCD!J11) | Q10: =IF(AND(TCD!L11="",TCD!Q11=""),"",IF(SUM(TCD!L11,TCD!Q11)>15,29,9.5)) | R10: =_xlfn.XLOOKUP(F10,TCD!E:E,TCD!K:K,"") | S10: =IF(TCD!I11="","",IF(TCD!I11>8.5,17,8.5)) | T10: =TCD!Y11
A11: =TCD!V12 | B11: =B10 | F11: =TCD!E12 | H11: =IF(RIGHT(J11,3)="BTB","E","P") | I11: =LOOKUP(F11,'Facture Chronopost'!L:L,'Facture Chronopost'!H:H) | J11: =TCD!U12 | K11: =K10 | L11: =_xlfn.XLOOKUP(F11,'TCD poids'!A:A,'TCD poids'!C:C) | M11: =TCD!T12 | N11: =IF(I11="",0.2,LOOKUP(I11,'Pays TVA'!A:A,'Pays TVA'!B:B)) | O11: =IF(TCD!M12="","",TCD!M12) | P11: =IF(TCD!J12="","",TCD!J12) | Q11: =IF(AND(TCD!L12="",TCD!Q12=""),"",IF(SUM(TCD!L12,TCD!Q12)>15,29,9.5)) | R11: =_xlfn.XLOOKUP(F11,TCD!E:E,TCD!K:K,"") | S11: =IF(TCD!I12="","",IF(TCD!I12>8.5,17,8.5)) | T11: =TCD!Y12
A12: =TCD!V13 | B12: =B11 | F12: =TCD!E13 | H12: =IF(RIGHT(J12,3)="BTB","E","P") | I12: =LOOKUP(F12,'Facture Chronopost'!L:L,'Facture Chronopost'!H:H) | J12: =TCD!U13 | K12: =K11 | L12: =_xlfn.XLOOKUP(F12,'TCD poids'!A:A,'TCD poids'!C:C) | M12: =TCD!T13 | N12: =IF(I12="",0.2,LOOKUP(I12,'Pays TVA'!A:A,'Pays TVA'!B:B)) | O12: =IF(TCD!M13="","",TCD!M13) | P12: =IF(TCD!J13="","",TCD!J13) | Q12: =IF(AND(TCD!L13="",TCD!Q13=""),"",IF(SUM(TCD!L13,TCD!Q13)>15,29,9.5)) | R12: =_xlfn.XLOOKUP(F12,TCD!E:E,TCD!K:K,"") | S12: =IF(TCD!I13="","",IF(TCD!I13>8.5,17,8.5)) | T12: =TCD!Y13
A13: =TCD!V14 | B13: =B12 | F13: =TCD!E14 | H13: =IF(RIGHT(J13,3)="BTB","E","P") | I13: =LOOKUP(F13,'Facture Chronopost'!L:L,'Facture Chronopost'!H:H) | J13: =TCD!U14 | K13: =K12 | L13: =_xlfn.XLOOKUP(F13,'TCD poids'!A:A,'TCD poids'!C:C) | M13: =TCD!T14 | N13: =IF(I13="",0.2,LOOKUP(I13,'Pays TVA'!A:A,'Pays TVA'!B:B)) | O13: =IF(TCD!M14="","",TCD!M14) | P13: =IF(TCD!J14="","",TCD!J14) | Q13: =IF(AND(TCD!L14="",TCD!Q14=""),"",IF(SUM(TCD!L14,TCD!Q14)>15,29,9.5)) | R13: =_xlfn.XLOOKUP(F13,TCD!E:E,TCD!K:K,"") | S13: =IF(TCD!I14="","",IF(TCD!I14>8.5,17,8.5)) | T13: =TCD!Y14
A14: =TCD!V15 | B14: =B13 | F14: =TCD!E15 | H14: =IF(RIGHT(J14,3)="BTB","E","P") | I14: =LOOKUP(F14,'Facture Chronopost'!L:L,'Facture Chronopost'!H:H) | J14: =TCD!U15 | K14: =K13 | L14: =_xlfn.XLOOKUP(F14,'TCD poids'!A:A,'TCD poids'!C:C) | M14: =TCD!T15 | N14: =IF(I14="",0.2,LOOKUP(I14,'Pays TVA'!A:A,'Pays TVA'!B:B)) | O14: =IF(TCD!M15="","",TCD!M15) | P14: =IF(TCD!J15="","",TCD!J15) | Q14: =IF(AND(TCD!L15="",TCD!Q15=""),"",IF(SUM(TCD!L15,TCD!Q15)>15,29,9.5)) | R14: =_xlfn.XLOOKUP(F14,TCD!E:E,TCD!K:K,"") | S14: =IF(TCD!I15="","",IF(TCD!I15>8.5,17,8.5)) | T14: =TCD!Y15
A15: =TCD!V16 | B15: =B14 | F15: =TCD!E16 | H15: =IF(RIGHT(J15,3)="BTB","E","P") | I15: =LOOKUP(F15,'Facture Chronopost'!L:L,'Facture Chronopost'!H:H) | J15: =TCD!U16 | K15: =K14 | L15: =_xlfn.XLOOKUP(F15,'TCD poids'!A:A,'TCD poids'!C:C) | M15: =TCD!T16 | N15: =IF(I15="",0.2,LOOKUP(I15,'Pays TVA'!A:A,'Pays TVA'!B:B)) | O15: =IF(TCD!M16="","",TCD!M16) | P15: =IF(TCD!J16="","",TCD!J16) | Q15: =IF(AND(TCD!L16="",TCD!Q16=""),"",IF(SUM(TCD!L16,TCD!Q16)>15,29,9.5)) | R15: =_xlfn.XLOOKUP(F15,TCD!E:E,TCD!K:K,"") | S15: =IF(TCD!I16="","",IF(TCD!I16>8.5,17,8.5)) | T15: =TCD!Y16
