Workbook

Sheet Zoning
A1: Pays | B1: Code ISO | C1: FICP | D1: IE | E1: RE | F1: Zone
A2: Andorre | B2: AD | C2: S | D2: T
A3: Émirats arabes unis | B3: AE | C3: C
A4: Afghanistan | B4: AF
A5: Antigua-et-Barbuda | B5: AG
A6: Anguilla | B6: AI | C6: D
A7: Albanie | B7: AL | C7: W
A8: Arménie | B8: AM | C8: C
A9: Angola | B9: AO | C9: E
A10: Argentine | B10: AR | C10: D
A11: Samoa américaines | B11: AS
A12: Autriche | B12: AT | C12: T | F12: Europe
A13: Australie | B13: AU | C13: G
A14: Aruba | B14: AW | C14: D
A15: Azerbaïdjan | B15: AZ | C15: C
A16: Bosnie-Herzégovine | B16: BA | C16: W | F16: Europe
A17: Barbade | B17: BB | C17: D
A18: Bangladesh | B18: BD | C18: C
A19: Belgique | B19: BE | C19: R | F19: Europe
A20: Burkina Faso | B20: BF | C20: E
A21: Bulgarie | B21: BG | C21: U | F21: Europe
A22: Bahreïn | B22: BH | C22: C
A23: Burundi | B23: BI | C23: E
A24: Bénin | B24: BJ | C24: E
A25: Saint-Barthélemy | B25: BL
A26: Bermudes | B26: BM | C26: D
A27: Brunei | B27: BN | C27: C
A28: Bolivie | B28: BO | C28: D
A29: Pays-Bas caribéens | B29: BQ
A30: Brésil | B30: BR | C30: D | F30: International
A31: Bahamas | B31: BS | C31: D
A32: Bhoutan | B32: BT | C32: C
A33: Botswana | B33: BW | C33: E
A34: Biélorussie | B34: BY
A35: Belize | B35: BZ | C35: D
A36: Canada | B36: CA | C36: A | F36: International
A37: République démocratique du Congo | B37: CD | C37: E
A38: République centrafricaine | B38: CF
A39: Congo | B39: CG | C39: E
A40: Suisse | B40: CH | C40: U | F40: International
A41: Côte d’Ivoire | B41: CI
A42: Îles Cook | B42: CK | C42: E
A43: Chili | B43: CL | C43: D
A44: Cameroun | B44: CM | C44: E
A45: Chine | B45: CN | C45: F
A46: Colombie | B46: CO | C46: D
A47: Costa Rica | B47: CR | C47: D
A48: Cap-Vert | B48: CV | C48: E
A49: Curaçao | B49: CW | C49: D
A50: Chypre | B50: CY | C50: W | F50: Europe
A51: Tchéquie | B51: CZ | C51: U | F51: Europe
A52: Allemagne | B52: DE | C52: R | F52: Europe
A53: Djibouti | B53: DJ | C53: E
A54: Danemark | B54: DK | C54: T | F54: Europe
A55: Dominique | B55: DM | C55: D
A56: République dominicaine | B56: DO | C56: D
A57: Algérie | B57: DZ | C57: C
A58: Équateur | B58: EC | C58: D
A59: Estonie | B59: EE | C59: U | F59: Europe
A60: Égypte | B60: EG | C60: C
A61: Érythrée | B61: ER | C61: E
A62: Espagne | B62: ES | C62: S | F62: Europe
A63: Éthiopie | B63: ET | C63: E
A64: Finlande | B64: FI | C64: T | F64: Europe
A65: Fidji | B65: FJ | C65: E
A66: Micronésie | B66: FM | C66: E
A67: Îles Féroé | B67: FO | C67: E
A68: France | B68: FR | C68: France | D68: France | E68: France | F68: ST
A69: Gabon | B69: GA | C69: E
A70: Royaume-Uni | B70: GB | C70: X | F70: International
A71: Grenade | B71: GD | C71: D
A72: Géorgie | B72: GE | C72: C
A73: Guyane française | B73: GF | C73: D
A74: Ghana | B74: GH | C74: E
A75: Gibraltar | B75: GI | C75: S | D75: U
A76: Groenland | B76: GL | C76: E
A77: Gambie | B77: GM | C77: E
A78: Guinée | B78: GN | C78: E
A79: Guadeloupe | B79: GP | C79: D
A80: Guinée équatoriale | B80: GQ | C80: E
A81: Grèce | B81: GR | C81: U | F81: Europe
A82: Guatemala | B82: GT | C82: D
A83: Guam | B83: GU | C83: E
A84: Guinée-Bissau | B84: GW | C84: E
A85: Guyana | B85: GY | C85: D
A86: Hong Kong | B86: HK | C86: F
A87: Honduras | B87: HN | C87: D
A88: Croatie | B88: HR | C88: U | F88: Europe
A89: Haïti | B89: HT | C89: D
A90: Hongrie | B90: HU | C90: U | F90: Europe
A91: Indonésie | B91: ID | C91: B | F91: International
A92: Irlande | B92: IE | C92: T | F92: Europe
A93: Israël | B93: IL | C93: C
A94: Inde | B94: IN | C94: C
A95: Irak | B95: IQ | C95: E
A96: Iran | B96: IR
A97: Islande | B97: IS | C97: W
A98: Italie | B98: IT | C98: S | F98: Europe
A99: Jamaïque | B99: JM | C99: D
A100: Jordanie | B100: JO | C100: C
...

Sheet Bilan factures
A3: Étiquettes de lignes | B3: Frêt HT | C3: Total TTC | D3: PDF | E3: Ecart
A4: 634323394 | B4: 217.91 | C4: 368.95 | D4: 368.95 | E4: =C4-D4 -> 0
A5: 634324015 | B5: 4124.86 | C5: 9093.5 | D5: 9093.5 | E5: =C5-D5 -> -2.0008883e-11
A6: 634333315 | B6: 34.63 | C6: 112.36 | D6: 112.36 | E6: =C6-D6 -> 0
A7: 634333759 | B7: 12657.37 | C7: 36460 | D7: 36460 | E7: =C7-D7 -> 2.6193447e-10
A8: 634343396 | B8: 119.26 | C8: 188.96 | D8: 188.96 | E8: =C8-D8 -> 0
A9: 634343823 | B9: 10563.68 | C9: 28893.06 | D9: 28893.06 | E9: =C9-D9 -> -4.3655746e-11
A10: 634353470 | B10: 117.97 | C10: 196.76 | D10: 196.76 | E10: =C10-D10 -> 0
A11: 634353938 | B11: 8832.41 | C11: 14308.73 | D11: 14308.73 | E11: =C11-D11 -> -6.184564e-11
A12: 634364547 | B12: 8847.74 | C12: 13684.18 | D12: 13684.18 | E12: =C12-D12 -> -4.1836756e-11
A13: (vide) | E13: =C13-D13 -> 0
A14: Total général | B14: 45515.83 | C14: 103306.5

Sheet Shipment Detail
A1: Montant | B1: Clients | C1: Catégorie | D1: E/P | E1: Mode d'envoi | F1: Payer Account | G1: Invoice Month (yyyymm) | H1: OPCO | I1: Service Type | J1: Service Description | K1: Pay Type | L1: Shipment Date (mm/dd/yyyy) | M1: Shipment Delivery Date (mm/dd/yyyy) | N1: Shipment Tracking Number | O1: Postal Identification Number | P1: Shipper Name | Q1: Shipper Company Name | R1: Shipper Address | S1: Shipper City | T1: Shipper State/Province | U1: Shipper Country/Territory | V1: Shipper Postal Code | W1: Shipment Freight Charge Amount USD | X1: Shipment Miscellaneous Charge USD | Y1: Shipment Duty and Tax Charge USD | Z1: Shipment Discount Amount USD | AA1: Net Charge Amount USD | AB1: Pieces In Shipment | AC1: Shipment Rated Weight (Pounds) | AD1: Original Weight (Pounds) | AE1: Proof Of Delivery Recipient | AF1: Recipient Name | AG1: Recipient Company Name | AH1: Recipient Address | AI1: Recipient City | AJ1: Recipient State/Province | AK1: Recipient Country/Territory | AL1: Recipient Postal Code | AM1: Reference Notes Line 1 | AN1: Reference Notes Line 2 | AO1: Reference Notes Line 3 | AP1: Department Number | AQ1: PO Number | AR1: Pricing Zone | AS1: Shipment DIM Flag (Y or N) | AT1: Dimmed Height (cm) | AU1: Dimmed Width (cm) | AV1: Dimmed Length (cm) | AW1: Recipient Original Address | AX1: Recipient Original City | AY1: Recipient Original State/Province | AZ1: Recipient Original Postal Code | BA1: Recipient Original Country/Territory | BB1: Shipment Declared Value Amount | BC1: Customs Value | BD1: Customs Value Currency Code | BE1: Invoice Date (mm/dd/yyyy) | BF1: Invoice Number | BG1: Master Tracking Number | BH1: Domestic/Intl | BI1: Package Type | BJ1: Shipment Delivery Time (12 Hours) | BK1: Shipment Freight Charge Billed Currency | BL1: Shipment Miscellaneous Charge Billed Currency | BM1: Shipment Duty And Tax Charge Billed Currency | BN1: Shipment Discount Billed Currency | BO1: Net Charge Billed Currency | BP1: Billed Currency Code | BQ1: Exchange Rate to USD | BR1: Weight Type Code | BS1: Customer Order Number
A2: =BK2+BN2 -> 13.48 | B2: 3752 | D2: entreprise | E2: =IF(J2="FedEx Priority","ST","FICP") -> ST | F2: 200720433 | G2: 202606 | H2: Express | I2: UO | J2: FedEx Priority | K2: Bill_Sender_Prepaid | L2: 46028 | M2: 46059 | N2: 872386856889 | P2: HYDRATIS B2B | Q2: HYDRATIS B2B | R2: VOIE COMMUNALE 4 | S2: CR?ANCEY | T2: 21 | U2: FR | V2: 21320 | W2: 65.79 | X2: 7.79 | Y2: 0 | Z2: -50.06 | AA2: 23.52 | AB2: 3 | AC2: 59.4 | AD2: 11.88 | AE2: M,AISON BLANCHE | AF2: PHARMACIE AUBIJOUX | AG2: PHARMACIE AUBIJOUX | AH2: 160 AVENUE D'ITALIE | AI2: PARIS 13 | AJ2: 75 | AK2: FR | AL2: 75013 | AS2: N | AT2: 30 | AU2: 31 | AV2: 40 | BB2: 0 | BC2: 0 | BD2: EUR | BE2: 46240 | BF2: 634324015 | BH2: Domestic | BI2: Your Packaging | BJ2: 0.52361111 | BK2: 56.4 | BL2: 6.68 | BM2: 0 | BN2: -42.92 | BO2: 20.16 | BP2: EUR | BQ2: 1.1664392 | BR2: kg
A3: =BK3+BN3 -> 9.8 | B3: 3752 | D3: entreprise | E3: =IF(J3="FedEx Priority","ST","FICP") -> ST | F3: 200720433 | G3: 202606 | H3: Express | I3: UO | J3: FedEx Priority | K3: Bill_Sender_Prepaid | L3: 05/28/2026 | M3: 05/29/2026 | N3: 872328943547 | P3: HYDRATIS B2B | Q3: HYDRATIS B2B | R3: VOIE COMMUNALE 4 | S3: CR?ANCEY | T3: 21 | U3: FR | V3: 21320 | W3: 47.7 | X3: 13.49 | Y3: 0 | Z3: -36.3 | AA3: 24.9 | AB3: 2 | AC3: 35.2 | AD3: 3.96 | AE3: B,AZINET | AF3: PHARMACIE MC PHARMA | AG3: PHARMACIE MC PHARMA | AH3: CCIAL LA GRANDE ROCADE | AI3: PRADES | AJ3: 66 | AK3: FR | AL3: 66500 | AS3: N | AT3: 0 | AU3: 0 | AV3: 0 | BB3: 0 | BC3: 0 | BD3: EUR | BE3: 46240 | BF3: 634324015 | BH3: Domestic | BI3: Your Packaging | BJ3: 0.46111111 | BK3: 41 | BL3: 11.6 | BM3: 0 | BN3: -31.2 | BO3: 21.4 | BP3: EUR | BQ3: 1.1633182 | BR3: kg
A4: =BK4+BN4 -> 12.14 | B4: 3752 | D4: entreprise | E4: =IF(J4="FedEx Priority","ST","FICP") -> ST | F4: 200720433 | G4: 202606 | H4: Express | I4: UO | J4: FedEx Priority | K4: Bill_Sender_Prepaid | L4: 46028 | M4: 46087 | N4: 872391359368 | P4: HYDRATIS B2B | Q4: HYDRATIS B2B | R4: VOIE COMMUNALE 4 | S4: CR?ANCEY | T4: 21 | U4: FR | V4: 21320 | W4: 59.26 | X4: 7.02 | Y4: 0 | Z4: -45.09 | AA4: 21.18 | AB4: 4 | AC4: 48.84 | AD4: 10.56 | AE4: P, CENTRE | AF4: PHARMACIE DU CENTRE | AG4: PHARMACIE DU CENTRE | AH4: 148 AVENUE SAINT ALBERT | AI4: PUGET SUR ARGENS | AJ4: 83 | AK4: FR | AL4: 83480 | AS4: N | AT4: 0 | AU4: 0 | AV4: 0 | BB4: 0 | BC4: 0 | BD4: EUR | BE4: 46240 | BF4: 634324015 | BH4: Domestic | BI4: Your Packaging | BJ4: 0.51875 | BK4: 50.8 | BL4: 6.02 | BM4: 0 | BN4: -38.66 | BO4: 18.16 | BP4: EUR | BQ4: 1.1664392 | BR4: kg
A5: =BK5+BN5 -> 13.48 | B5: 3752 | D5: entreprise | E5: =IF(J5="FedEx Priority","ST","FICP") -> ST | F5: 200720433 | G5: 202606 | H5: Express | I5: UO | J5: FedEx Priority | K5: Bill_Sender_Prepaid | L5: 05/29/2026 | M5: 05/30/2026 | N5: 872337970166 | P5: HYDRATIS B2B | Q5: HYDRATIS B2B | R5: VOIE COMMUNALE 4 | S5: CR?ANCEY | T5: 21 | U5: FR | V5: 21320 | W5: 65.63 | X5: 6.99 | Y5: 0 | Z5: -49.95 | AA5: 22.68 | AB5: 5 | AC5: 58.08 | AD5: 18.7 | AE5: P,ARIS | AF5: PHARMACIE SAINTPOL | AG5: PHARMACIE SAINTPOL | AH5: 12 PLACE DU GENERAL DE SAINT POL | AI5: NOGENT-LE-ROTROU | AJ5: 28 | AK5: FR | AL5: 28400 | AS5: N | AT5: 0 | AU5: 0 | AV5: 0 | BB5: 0 | BC5: 0 | BD5: EUR | BE5: 46240 | BF5: 634324015 | BH5: Domestic | BI5: Your Packaging | BJ5: 0.42291667 | BK5: 56.4 | BL5: 6.01 | BM5: 0 | BN5: -42.92 | BO5: 19.49 | BP5: EUR | BQ5: 1.1637244 | BR5: kg
A6: =BK6+BN6 -> 11.47 | B6: 3752 | D6: entreprise | E6: =IF(J6="FedEx Priority","ST","FICP") -> ST | F6: 200720433 | G6: 202606 | H6: Express | I6: UO | J6: FedEx Priority | K6: Bill_Sender_Prepaid | L6: 05/29/2026 | M6: 05/30/2026 | N6: 872384769195 | P6: HYDRATIS B2B | Q6: HYDRATIS B2B | R6: VOIE COMMUNALE 4 | S6: CR?ANCEY | T6: 21 | U6: FR | V6: 21320 | W6: 55.86 | X6: 5.95 | Y6: 0 | Z6: -42.51 | AA6: 19.29 | AB6: 3 | AC6: 46.2 | AD6: 9.9 | AE6: A,Behue | AF6: PHARMACIE DES VIGNES | AG6: PHARMACIE DES VIGNES | AH6: 1 D RUE D'ALMAS PELLOUAILLES | AI6: VERRIERES-EN-ANJOU | AJ6: 49 | AK6: FR | AL6: 49112 | AS6: N | AT6: 30 | AU6: 31 | AV6: 38 | BB6: 0 | BC6: 0 | BD6: EUR | BE6: 46240 | BF6: 634324015 | BH6: Domestic | BI6: Your Packaging | BJ6: 0.46527778 | BK6: 48 | BL6: 5.11 | BM6: 0 | BN6: -36.53 | BO6: 16.58 | BP6: EUR | BQ6: 1.1637244 | BR6: kg
A7: =BK7+BN7 -> 7.12 | B7: 3752 | D7: entreprise | E7: =IF(J7="FedEx Priority","ST","FICP") -> ST | F7: 200720433 | G7: 202606 | H7: Express | I7: UO | J7: FedEx Priority | K7: Bill_Sender_Prepaid | L7: 46028 | M7: 46059 | N7: 872384622893 | P7: HYDRATIS B2B | Q7: HYDRATIS B2B | R7: VOIE COMMUNALE 4 | S7: CR?ANCEY | T7: 21 | U7: FR | V7: 21320 | W7: 34.76 | X7: 4.13 | Y7: 0 | Z7: -26.45 | AA7: 12.43 | AB7: 1 | AC7: 15.84 | AD7: 1.98 | AE7: F,ABIENNE | AF7: OCP STC BAULE | AG7: OCP STC BAULE | AH7: 600 RUE 1ERE AVENUE | AI7: BAULE | AJ7: 45 | AK7: FR | AL7: 45130 | AS7: Y | AT7: 30 | AU7: 30 | AV7: 40 | BB7: 0 | BC7: 0 | BD7: EUR | BE7: 46240 | BF7: 634324015 | BH7: Domestic | BI7: Your Packaging | BJ7: 0.40486111 | BK7: 29.8 | BL7: 3.54 | BM7: 0 | BN7: -22.68 | BO7: 10.66 | BP7: EUR | BQ7: 1.1664392 | BR7: kg
A8: =BK8+BN8 -> 8.8 | B8: 3752 | D8: entreprise | E8: =IF(J8="FedEx Priority","ST","FICP") -> ST | F8: 200720433 | G8: 202606 | H8: Express | I8: UO | J8: FedEx Priority | K8: Bill_Sender_Prepaid | L8: 05/28/2026 | M8: 05/29/2026 | N8: 872285404035 | P8: HYDRATIS B2B | Q8: HYDRATIS B2B | R8: VOIE COMMUNALE 4 | S8: CR?ANCEY | T8: 21 | U8: FR | V8: 21320 | W8: 42.81 | X8: 4.56 | Y8: 0 | Z8: -32.57 | AA8: 14.8 | AB8: 2 | AC8: 28.6 | AD8: 4.84 | AE8: P,HI ETAIN | AF8: PHARMACIE DU POT D'ETAIN | AG8: PHARMACIE DU POT D'ETAIN | AH8: 11 BIS PLACE DU POT D'ETAIN | AI8: PONT-AUDEMER | AJ8: 27 | AK8: FR | AL8: 27500 | AS8: N | AT8: 0 | AU8: 0 | AV8: 0 | BB8: 0 | BC8: 0 | BD8: EUR | BE8: 46240 | BF8: 634324015 | BH8: Domestic | BI8: Your Packaging | BJ8: 0.49930556 | BK8: 36.8 | BL8: 3.92 | BM8: 0 | BN8: -28 | BO8: 12.72 | BP8: EUR | BQ8: 1.1633182 | BR8: kg
A9: =BK9+BN9 -> 7.79 | B9: 3752 | D9: entreprise | E9: =IF(J9="FedEx Priority","ST","FICP") -> ST | F9: 200720433 | G9: 202606 | H9: Express | I9: UO | J9: FedEx Priority | K9: Bill_Sender_Prepaid | L9: 05/29/2026 | M9: 46059 | N9: 872385135922 | P9: HYDRATIS B2B | Q9: HYDRATIS B2B | R9: VOIE COMMUNALE 4 | S9: CR?ANCEY | T9: 21 | U9: FR | V9: 21320 | W9: 37.94 | X9: 4.04 | Y9: 0 | Z9: -28.87 | AA9: 13.1 | AB9: 2 | AC9: 21.12 | AD9: 2.64 | AE9: M,Marina | AF9: PHARMACIE DES PAGES | AG9: PHARMACIE DES PAGES | AH9: 16/18 ROUTE DE MONTESSON | AI9: LE V?SINET | AJ9: 78 | AK9: FR | AL9: 78110 | AS9: N | AT9: 0 | AU9: 0 | AV9: 0 | BB9: 0 | BC9: 0 | BD9: EUR | BE9: 46240 | BF9: 634324015 | BH9: Domestic | BI9: Your Packaging | BJ9: 0.45069444 | BK9: 32.6 | BL9: 3.47 | BM9: 0 | BN9: -24.81 | BO9: 11.26 | BP9: EUR | BQ9: 1.1637244 | BR9: kg
A10: =BK10+BN10 -> 10.47 | B10: 3752 | D10: entreprise | E10: =IF(J10="FedEx Priority","ST","FICP") -> ST | F10: 200720433 | G10: 202606 | H10: Express | I10: UO | J10: FedEx Priority | K10: Bill_Sender_Prepaid | L10: 46028 | M10: 46059 | N10: 872285149227 | P10: HYDRATIS B2B | Q10: HYDRATIS B2B | R10: VOIE COMMUNALE 4 | S10: CR?ANCEY | T10: 21 | U10: FR | V10: 21320 | W10: 51.09 | X10: 6.05 | Y10: 0 | Z10: -38.88 | AA10: 18.27 | AB10: 3 | AC10: 39.38 | AD10: 5.94 | AE10: R,OSSI | AF10: INTERSPORT DENAIN 04967/000 | AG10: INTERSPORT DENAIN 04967/000 | AH10: SAS AFC SPORTS ST GEOIRS | AI10: SAINT-ETIENNE-DE-SAINT-GEOIRS | AJ10: 38 | AK10: FR | AL10: 38590 | AS10: N | AT10: 30 | AU10: 31 | AV10: 40 | BB10: 0 | BC10: 0 | BD10: EUR | BE10: 46240 | BF10: 634324015 | BH10: Domestic | BI10: Your Packaging | BJ10: 0.38541667 | BK10: 43.8 | BL10: 5.19 | BM10: 0 | BN10: -33.33 | BO10: 15.66 | BP10: EUR | BQ10: 1.1664392 | BR10: kg
A11: =BK11+BN11 -> 6.45 | B11: 3752 | D11: entreprise | E11: =IF(J11="FedEx Priority","ST","FICP") -> ST | F11: 200720433 | G11: 202606 | H11: Express | I11: UO | J11: FedEx Priority | K11: Bill_Sender_Prepaid | L11: 46059 | M11: 46118 | N11: 872389888666 | P11: HYDRATIS B2B | Q11: HYDRATIS B2B | R11: VOIE COMMUNALE 4 | S11: CR?ANCEY | T11: 21 | U11: FR | V11: 21320 | W11: 31.49 | X11: 3.73 | Y11: 0 | Z11: -23.97 | AA11: 11.26 | AB11: 1 | AC11: 13.2 | AD11: 1.1 | AE11: C,YRIL | AF11: SOLIDRO PARAPHARMACIE LECLERC | AG11: SOLIDRO PARAPHARMACIE LECLERC | AH11: BP9 ROUTE DE PERIGUEUX | AI11: RIBERAC | AJ11: 24 | AK11: FR | AL11: 24600 | AS11: N | AT11: 0 | AU11: 0 | AV11: 0 | BB11: 0 | BC11: 0 | BD11: EUR | BE11: 46240 | BF11: 634324015 | BH11: Domestic | BI11: Your Packaging | BJ11: 0.45208333 | BK11: 27 | BL11: 3.2 | BM11: 0 | BN11: -20.55 | BO11: 9.65 | BP11: EUR | BQ11: 1.166344 | BR11: kg
A12: =BK12+BN12 -> 7.79 | B12: 3752 | D12: entreprise | E12: =IF(J12="FedEx Priority","ST","FICP") -> ST | F12: 200720433 | G12: 202606 | H12: Express | I12: UO | J12: FedEx Priority | K12: Bill_Sender_Prepaid | L12: 05/28/2026 | M12: 05/29/2026 | N12: 872328680201 | P12: HYDRATIS B2B | Q12: HYDRATIS B2B | R12: VOIE COMMUNALE 4 | S12: CR?ANCEY | T12: 21 | U12: FR | V12: 21320 | W12: 37.92 | X12: 4.04 | Y12: 0 | Z12: -28.86 | AA12: 13.1 | AB12: 2 | AC12: 21.56 | AD12: 3.52 | AE12: Q,UERE | AF12: PHARMACIE DES GRANDS JARDINS | AG12: PHARMACIE DES GRANDS JARDINS | AH12: 6 PLACE DU MARCHE | AI12: MESLAY-DU-MAINE | AJ12: 53 | AK12: FR | AL12: 53170 | AS12: N | AT12: 0 | AU12: 0 | AV12: 0 | BB12: 0 | BC12: 0 | BD12: EUR | BE12: 46240 | BF12: 634324015 | BH12: Domestic | BI12: Your Packaging | BJ12: 0.39305556 | BK12: 32.6 | BL12: 3.47 | BM12: 0 | BN12: -24.81 | BO12: 11.26 | BP12: EUR | BQ12: 1.1633182 | BR12: kg
A13: =BK13+BN13 -> 10.13 | B13: 3752 | D13: entreprise | E13: =IF(J13="FedEx Priority","ST","FICP") -> ST | F13: 200720433 | G13: 202606 | H13: Express | I13: UO | J13: FedEx Priority | K13: Bill_Sender_Prepaid | L13: 05/29/2026 | M13: 05/30/2026 | N13: 872385768346 | P13: HYDRATIS B2B | Q13: HYDRATIS B2B | R13: VOIE COMMUNALE 4 | S13: CR?ANCEY | T13: 21 | U13: FR | V13: 21320 | W13: 49.34 | X13: 5.25 | Y13: 0 | Z13: -37.55 | AA13: 17.04 | AB13: 3 | AC13: 37.18 | AD13: 4.62 | AE13: L,Delaneau | AF13: PHARMACIE DE LARCAY | AG13: PHARMACIE DE LARCAY | AH13: 1 ALLEE DE LA BERGERIE | AI13: LARCAY | AJ13: 37 | AK13: FR | AL13: 37270 | AS13: N | AT13: 30 | AU13: 31 | AV13: 40 | BB13: 0 | BC13: 0 | BD13: EUR | BE13: 46240 | BF13: 634324015 | BH13: Domestic | BI13: Your Packaging | BJ13: 0.35972222 | BK13: 42.4 | BL13: 4.51 | BM13: 0 | BN13: -32.27 | BO13: 14.64 | BP13: EUR | BQ13: 1.1637244 | BR13: kg
A14: =BK14+BN14 -> 12.14 | B14: 3752 | D14: entreprise | E14: =IF(J14="FedEx Priority","ST","FICP") -> ST | F14: 200720433 | G14: 202606 | H14: Express | I14: UO | J14: FedEx Priority | K14: Bill_Sender_Prepaid | L14: 05/28/2026 | M14: 46028 | N14: 872278253231 | P14: HYDRATIS B2B | Q14: HYDRATIS B2B | R14: VOIE COMMUNALE 4 | S14: CR?ANCEY | T14: 21 | U14: FR | V14: 21320 | W14: 59.1 | X14: 6.28 | Y14: 0 | Z14: -44.97 | AA14: 20.4 | AB14: 3 | AC14: 50.6 | AD14: 8.58 | AE14: N,ICO | AF14: PARAPHARMACIE LECLERC LANDI DIS | AG14: PARAPHARMACIE LECLERC LANDI DI | AH14: 4 BOULEVARD DE LA REPUBLIQUE | AI14: LANDIVISIAU | AJ14: 29 | AK14: FR | AL14: 29403 | AS14: N | AT14: 0 | AU14: 0 | AV14: 0 | BB14: 0 | BC14: 0 | BD14: EUR | BE14: 46240 | BF14: 634324015 | BH14: Domestic | BI14: Your Packaging | BJ14: 0.60138889 | BK14: 50.8 | BL14: 5.4 | BM14: 0 | BN14: -38.66 | BO14: 17.54 | BP14: EUR | BQ14: 1.1633182 | BR14: kg
A15: =BK15+BN15 -> 8.46 | B15: 3752 | E15: =IF(J15="FedEx Priority","ST","FICP") -> ST | F15: 200720433 | G15: 202606 | H15: Express | I15: UO | J15: FedEx Priority | K15: Bill_Sender_Prepaid | L15: 46087 | M15: 46118 | N15: 872530870896 | P15: HYDRATIS B2B | Q15: HYDRATIS B2B | R15: VOIE COMMUNALE 4 | S15: CR?ANCEY | T15: 21 | U15: FR | V15: 21320 | W15: 41.21 | X15: 13.6 | Y15: 0 | Z15: -31.36 | AA15: 23.44 | AB15: 2 | AC15: 26.4 | AD15: 3.08 | AE15: P,EIGNER | AF15: PHARMACIE PEIGNIER | AG15: PHARMACIE PEIGNIER | AH15: 99 GRANDE RUE | AI15: LE VAL D'AJOL | AJ15: 88 | AK15: FR | AL15: 88340 | AS15: N | AT15: 0 | AU15: 0 | AV15: 0 | BB15: 0 | BC15: 0 | BD15: EUR | BE15: 46240 | BF15: 634324015 | BH15: Domestic | BI15: Your Packaging | BJ15: 0.45694444 | BK15: 35.4 | BL15: 11.68 | BM15: 0 | BN15: -26.94 | BO15: 20.14 | BP15: EUR | BQ15: 1.1640901 | BR15: kg
A16: =BK16+BN16 -> 19.84 | B16: 3752 | D16: entreprise | E16: =IF(J16="FedEx Priority","ST","FICP") -> ST | F16: 200720433 | G16: 202606 | H16: Express | I16: UO | J16: FedEx Priority | K16: Bill_Sender_Prepaid | L16: 05/29/2026 | M16: 46028 | N16: 872382473532 | P16: HYDRATIS B2B | Q16: HYDRATIS B2B | R16: VOIE COMMUNALE 4 | S16: CR?ANCEY | T16: 21 | U16: FR | V16: 21320 | W16: 96.59 | X16: 10.29 | Y16: 0 | Z16: -73.5 | AA16: 33.38 | AB16: 5 | AC16: 101.2 | AD16: 25.3 | AE16: A,NNE | AF16: GRANDE PHARMACIE DE CAVIGNAC | AG16: GRANDE PHARMACIE DE CAVIGNAC | AH16: CC SUPER U | AI16: CAVIGNAC | AJ16: 33 | AK16: FR | AL16: 33620 | AS16: N | AT16: 0 | AU16: 0 | AV16: 0 | BB16: 0 | BC16: 0 | BD16: EUR | BE16: 46240 | BF16: 634324015 | BH16: Domestic | BI16: Your Packaging | BJ16: 0.40486111 | BK16: 83 | BL16: 8.84 | BM16: 0 | BN16: -63.16 | BO16: 28.68 | BP16: EUR | BQ16: 1.1637244 | BR16: kg
A17: =BK17+BN17 -> 22.18 | B17: 3752 | D17: entreprise | E17: =IF(J17="FedEx Priority","ST","FICP") -> ST | F17: 200720433 | G17: 202606 | H17: Express | I17: UO | J17: FedEx Priority | K17: Bill_Sender_Prepaid | L17: 46301 | M17: 46332 | N17: 872882388981 | P17: HYDRATIS B2B | Q17: HYDRATIS B2B | R17: VOIE COMMUNALE 4 | S17: CR?ANCEY | T17: 21 | U17: FR | V17: 21320 | W17: 107.01 | X17: 112.32 | Y17: 0 | Z17: -81.44 | AA17: 137.9 | AB17: 10 | AC17: 116.38 | AD17: 116.38 | AE17: M,Melani | AF17: PHARMACIE GAERTNER | AG17: PHARMACIE GAERTNER | AH17: 41 ROUTE DE RHINAU | AI17: BOOFZHEIM | AJ17: 67 | AK17: FR | AL17: 67860 | AS17: N | AT17: 0 | AU17: 0 | AV17: 0 | BB17: 0 | BC17: 0 | BD17: EUR | BE17: 06/15/2026 | BF17: 634333759 | BH17: Domestic | BI17: Your Packaging | BJ17: 0.49236111 | BK17: 92.8 | BL17: 97.4 | BM17: 0 | BN17: -70.62 | BO17: 119.58 | BP17: EUR | BQ17: 1.1531631 | BR17: kg
A18: =BK18+BN18 -> 7.12 | B18: 3752 | D18: entreprise | E18: =IF(J18="FedEx Priority","ST","FICP") -> ST | F18: 200720433 | G18: 202606 | H18: Express | I18: UO | J18: FedEx Priority | K18: Bill_Sender_Prepaid | L18: 05/20/2026 | M18: 1 | N18: 871971966607 | P18: HYDRATIS B2B | Q18: HYDRATIS B2B | R18: VOIE COMMUNALE 4 | S18: CR?ANCEY | T18: 21 | U18: FR | V18: 21320 | W18: 34.69 | X18: 3.7 | Y18: 0 | Z18: -26.4 | AA18: 11.99 | AB18: 1 | AC18: 17.6 | AD18: 1.54 | AF18: INTERSPORT PONTAULT 00670/000 | AG18: INTERSPORT PONTAULT 00670/000 | AH18: PROSPORT XIX SAS | AI18: PONTAULT-COMBAULT | AJ18: 77 | AK18: FR | AL18: 77340 | AS18: N | AT18: 30 | AU18: 31 | AV18: 39 | BB18: 0 | BC18: 0 | BD18: EUR | BE18: 46240 | BF18: 634324015 | BH18: Domestic | BI18: Your Packaging | BJ18: 0 | BK18: 29.8 | BL18: 3.18 | BM18: 0 | BN18: -22.68 | BO18: 10.3 | BP18: EUR | BQ18: 1.1639411 | BR18: kg
A19: =BK19+BN19 -> 11.81 | B19: 3752 | D19: entreprise | E19: =IF(J19="FedEx Priority","ST","FICP") -> ST | F19: 200720433 | G19: 202606 | H19: Express | I19: UO | J19: FedEx Priority | K19: Bill_Sender_Prepaid | L19: 05/29/2026 | M19: 46028 | N19: 872336662060 | P19: HYDRATIS B2B | Q19: HYDRATIS B2B | R19: VOIE COMMUNALE 4 | S19: CR?ANCEY | T19: 21 | U19: FR | V19: 21320 | W19: 57.49 | X19: 6.13 | Y19: 0 | Z19: -43.74 | AA19: 19.88 | AB19: 3 | AC19: 48.4 | AD19: 11.22 | AE19: L,EA | AF19: PHARMACIE DES BANCHAIS | AG19: PHARMACIE DES BANCHAIS | AH19: 360 RUE HAUTE DES BANCHAIS | AI19: SAINT BARTHELEMY D'ANJOU | AJ19: 49 | AK19: FR | AL19: 49124 | AS19: N | AT19: 30 | AU19: 31 | AV19: 39 | BB19: 0 | BC19: 0 | BD19: EUR | BE19: 46240 | BF19: 634324015 | BH19: Domestic | BI19: Your Packaging | BJ19: 0.41666667 | BK19: 49.4 | BL19: 5.27 | BM19: 0 | BN19: -37.59 | BO19: 17.08 | BP19: EUR | BQ19: 1.1637244 | BR19: kg
A20: =BK20+BN20 -> 8.46 | B20: 3752 | D20: entreprise | E20: =IF(J20="FedEx Priority","ST","FICP") -> ST | F20: 200720433 | G20: 202606 | H20: Express | I20: UO | J20: FedEx Priority | K20: Bill_Sender_Prepaid | L20: 05/29/2026 | M20: 46028 | N20: 872334971921 | P20: HYDRATIS B2B | Q20: HYDRATIS B2B | R20: VOIE COMMUNALE 4 | S20: CR?ANCEY | T20: 21 | U20: FR | V20: 21320 | W20: 41.2 | X20: 4.39 | Y20: 0 | Z20: -31.35 | AA20: 14.23 | AB20: 2 | AC20: 26.4 | AD20: 2.64 | AE20: L,E DUFF | AF20: PHARMACIE DU KERVENT | AG20: PHARMACIE DU KERVENT | AH20: CCIAL LECLERC / ZAC KERVENT | AI20: SAINT-POL-DE-L?ON | AJ20: 29 | AK20: FR | AL20: 29250 | AS20: N | AT20: 0 | AU20: 0 | AV20: 0 | BB20: 0 | BC20: 0 | BD20: EUR | BE20: 46240 | BF20: 634324015 | BH20: Domestic | BI20: Your Packaging | BJ20: 0.42777778 | BK20: 35.4 | BL20: 3.77 | BM20: 0 | BN20: -26.94 | BO20: 12.23 | BP20: EUR | BQ20: 1.1637244 | BR20: kg
A21: =BK21+BN21 -> 8.46 | B21: 3752 | D21: entreprise | E21: =IF(J21="FedEx Priority","ST","FICP") -> ST | F21: 200720433 | G21: 202606 | H21: Express | I21: UO | J21: FedEx Priority | K21: Bill_Sender_Prepaid | L21: 05/29/2026 | M21: 46028 | N21: 872382386231 | P21: HYDRATIS B2B | Q21: HYDRATIS B2B | R21: VOIE COMMUNALE 4 | S21: CR?ANCEY | T21: 21 | U21: FR | V21: 21320 | W21: 41.2 | X21: 4.39 | Y21: 0 | Z21: -31.35 | AA21: 14.23 | AB21: 2 | AC21: 26.4 | AD21: 3.08 | AE21: M,Anne | AF21: PHARMACIE DE RICHTER | AG21: PHARMACIE DE RICHTER | AH21: 181 PLACE ERNEST GRANIER | AI21: MONTPELLIER | AJ21: 34 | AK21: FR | AL21: 34000 | AS21: N | AT21: 0 | AU21: 0 | AV21: 0 | BB21: 0 | BC21: 0 | BD21: EUR | BE21: 46240 | BF21: 634324015 | BH21: Domestic | BI21: Your Packaging | BJ21: 0.49930556 | BK21: 35.4 | BL21: 3.77 | BM21: 0 | BN21: -26.94 | BO21: 12.23 | BP21: EUR | BQ21: 1.1637244 | BR21: kg
A22: =BK22+BN22 -> 8.46 | B22: 3752 | E22: =IF(J22="FedEx Priority","ST","FICP") -> ST | F22: 200720433 | G22: 202606 | H22: Express | I22: UO | J22: FedEx Priority | K22: Bill_Sender_Prepaid | L22: 46087 | M22: 46118 | N22: 872531222769 | P22: HYDRATIS B2B | Q22: HYDRATIS B2B | R22: VOIE COMMUNALE 4 | S22: CR?ANCEY | T22: 21 | U22: FR | V22: 21320 | W22: 41.21 | X22: 4.89 | Y22: 0 | Z22: -31.36 | AA22: 14.74 | AB22: 2 | AC22: 26.4 | AD22: 3.96 | AE22: B,ODIN | AF22: PHARMACIE D ANDARD | AG22: PHARMACIE D ANDARD | AH22: 55 B GRANDE RUE | AI22: LOIRE-AUTHION | AJ22: 49 | AK22: FR | AL22: 49800 | AS22: N | AT22: 0 | AU22: 0 | AV22: 0 | BB22: 0 | BC22: 0 | BD22: EUR | BE22: 46240 | BF22: 634324015 | BH22: Domestic | BI22: Your Packaging | BJ22: 0.44027778 | BK22: 35.4 | BL22: 4.2 | BM22: 0 | BN22: -26.94 | BO22: 12.66 | BP22: EUR | BQ22: 1.1640901 | BR22: kg
A23: =BK23+BN23 -> 10.47 | B23: 3752 | D23: entreprise | E23: =IF(J23="FedEx Priority","ST","FICP") -> ST | F23: 200720433 | G23: 202606 | H23: Express | I23: UO | J23: FedEx Priority | K23: Bill_Sender_Prepaid | L23: 05/28/2026 | M23: 05/29/2026 | N23: 872332173220 | P23: HYDRATIS B2B | Q23: HYDRATIS B2B | R23: VOIE COMMUNALE 4 | S23: CR?ANCEY | T23: 21 | U23: FR | V23: 21320 | W23: 50.95 | X23: 5.42 | Y23: 0 | Z23: -38.77 | AA23: 17.6 | AB23: 3 | AC23: 38.06 | AD23: 8.58 | AE23: J,Jeudy | AF23: PHARMACIE SAINT EPAIN | AG23: PHARMACIE SAINT EPAIN | AH23: 6 PLACE DE LA MAIRIE | AI23: SAINT-?PAIN | AJ23: 37 | AK23: FR | AL23: 37800 | AS23: N | AT23: 30 | AU23: 32 | AV23: 39 | BB23: 0 | BC23: 0 | BD23: EUR | BE23: 46240 | BF23: 634324015 | BH23: Domestic | BI23: Your Packaging | BJ23: 0.37708333 | BK23: 43.8 | BL23: 4.66 | BM23: 0 | BN23: -33.33 | BO23: 15.13 | BP23: EUR | BQ23: 1.1633182 | BR23: kg
A24: =BK24+BN24 -> 12.48 | B24: 3752 | D24: entreprise | E24: =IF(J24="FedEx Priority","ST","FICP") -> ST | F24: 200720433 | G24: 202606 | H24: Express | I24: UO | J24: FedEx Priority | K24: Bill_Sender_Prepaid | L24: 05/29/2026 | M24: 46028 | N24: 872385254070 | P24: HYDRATIS B2B | Q24: HYDRATIS B2B | R24: VOIE COMMUNALE 4 | S24: CR?ANCEY | T24: 21 | U24: FR | V24: 21320 | W24: 60.75 | X24: 6.47 | Y24: 0 | Z24: -46.22 | AA24: 20.99 | AB24: 3 | AC24: 52.8 | AD24: 9.24 | AE24: K,IM | AF24: PHARMACIE CAP VALESCURE | AG24: PHARMACIE CAP VALESCURE | AH24: 37 ALLEE DU PARC ARUNDO | AI24: FREJUS | AJ24: 83 | AK24: FR | AL24: 83600 | AS24: N | AT24: 30 | AU24: 30 | AV24: 40 | BB24: 0 | BC24: 0 | BD24: EUR | BE24: 46240 | BF24: 634324015 | BH24: Domestic | BI24: Your Packaging | BJ24: 0.49861111 | BK24: 52.2 | BL24: 5.56 | BM24: 0 | BN24: -39.72 | BO24: 18.04 | BP24: EUR | BQ24: 1.1637244 | BR24: kg
A25: =BK25+BN25 -> 12.14 | B25: 3752 | D25: entreprise | E25: =IF(J25="FedEx Priority","ST","FICP") -> ST | F25: 200720433 | G25: 202606 | H25: Express | I25: UO | J25: FedEx Priority | K25: Bill_Sender_Prepaid | L25: 05/28/2026 | M25: 05/29/2026 | N25: 872331112770 | P25: HYDRATIS B2B | Q25: HYDRATIS B2B | R25: VOIE COMMUNALE 4 | S25: CR?ANCEY | T25: 21 | U25: FR | V25: 21320 | W25: 59.1 | X25: 6.28 | Y25: 0 | Z25: -44.97 | AA25: 20.4 | AB25: 4 | AC25: 50.6 | AD25: 17.6 | AE25: P,HIE ZARROUCK | AF25: PHARMACIE SAINT BLAISE | AG25: PHARMACIE SAINT BLAISE | AH25: 1 RUE STENDHAL | AI25: PARIS 20 | AJ25: 75 | AK25: FR | AL25: 75020 | AS25: N | AT25: 30 | AU25: 31 | AV25: 40 | BB25: 0 | BC25: 0 | BD25: EUR | BE25: 46240 | BF25: 634324015 | BH25: Domestic | BI25: Your Packaging | BJ25: 0.475 | BK25: 50.8 | BL25: 5.4 | BM25: 0 | BN25: -38.66 | BO25: 17.54 | BP25: EUR | BQ25: 1.1633182 | BR25: kg
A26: =BK26+BN26 -> 13.48 | B26: 3752 | D26: entreprise | E26: =IF(J26="FedEx Priority","ST","FICP") -> ST | F26: 200720433 | G26: 202606 | H26: Express | I26: UO | J26: FedEx Priority | K26: Bill_Sender_Prepaid | L26: 46028 | M26: 46059 | N26: 872338229810 | P26: HYDRATIS B2B | Q26: HYDRATIS B2B | R26: VOIE COMMUNALE 4 | S26: CR?ANCEY | T26: 21 | U26: FR | V26: 21320 | W26: 65.79 | X26: 7.79 | Y26: 0 | Z26: -50.06 | AA26: 23.52 | AB26: 5 | AC26: 57.42 | AD26: 12.1 | AE26: A,Arcade | AF26: PHARMACIE DES ARCADES | AG26: PHARMACIE DES ARCADES | AH26: 1 PLACE DE LA BEURRERIE | AI26: NOZAY | AJ26: 44 | AK26: FR | AL26: 44170 | AS26: N | AT26: 0 | AU26: 0 | AV26: 0 | BB26: 0 | BC26: 0 | BD26: EUR | BE26: 46240 | BF26: 634324015 | BH26: Domestic | BI26: Your Packaging | BJ26: 0.45347222 | BK26: 56.4 | BL26: 6.68 | BM26: 0 | BN26: -42.92 | BO26: 20.16 | BP26: EUR | BQ26: 1.1664392 | BR26: kg
A27: =BK27+BN27 -> 8.46 | B27: 3752 | D27: entreprise | E27: =IF(J27="FedEx Priority","ST","FICP") -> ST | F27: 200720433 | G27: 202606 | H27: Express | I27: UO | J27: FedEx Priority | K27: Bill_Sender_Prepaid | L27: 46028 | M27: 46059 | N27: 872386996430 | P27: HYDRATIS B2B | Q27: HYDRATIS B2B | R27: VOIE COMMUNALE 4 | S27: CR?ANCEY | T27: 21 | U27: FR | V27: 21320 | W27: 41.29 | X27: 4.9 | Y27: 0 | Z27: -31.42 | AA27: 14.77 | AB27: 2 | AC27: 25.08 | AD27: 5.72 | AE27: V,Viressel | AF27: DELMONICO DOREL | AG27: DELMONICO DOREL | AH27: RIVE DE GIER | AI27: RIVE-DE-GIER | AJ27: 42 | AK27: FR | AL27: 42800 | AS27: N | AT27: 30 | AU27: 31 | AV27: 40 | BB27: 0 | BC27: 0 | BD27: EUR | BE27: 46240 | BF27: 634324015 | BH27: Domestic | BI27: Your Packaging | BJ27: 0.49097222 | BK27: 35.4 | BL27: 4.2 | BM27: 0 | BN27: -26.94 | BO27: 12.66 | BP27: EUR | BQ27: 1.1664392 | BR27: kg
A28: =BK28+BN28 -> 27.53 | B28: 3752 | D28: entreprise | E28: =IF(J28="FedEx Priority","ST","FICP") -> ST | F28: 200720433 | G28: 202606 | H28: Express | I28: UO | J28: FedEx Priority | K28: Bill_Sender_Prepaid | L28: 46028 | M28: 46059 | N28: 872327509740 | P28: HYDRATIS B2B | Q28: HYDRATIS B2B | R28: VOIE COMMUNALE 4 | S28: CR?ANCEY | T28: 21 | U28: FR | V28: 21320 | W28: 134.37 | X28: 116.7 | Y28: 0 | Z28: -102.26 | AA28: 148.81 | AB28: 10 | AC28: 150.48 | AD28: 70.4 | AE28: J,OUBERT | AF28: GRANDE PHARMACIE JOUBERT | AG28: GRANDE PHARMACIE JOUBERT | AH28: 9 RUE RENE GOSCINNY | AI28: ANGOUL?ME | AJ28: 16 | AK28: FR | AL28: 16006 | AS28: N | AT28: 0 | AU28: 0 | AV28: 0 | BB28: 0 | BC28: 0 | BD28: EUR | BE28: 46240 | BF28: 634324015 | BH28: Domestic | BI28: Your Packaging | BJ28: 0.44375 | BK28: 115.2 | BL28: 100.05 | BM28: 0 | BN28: -87.67 | BO28: 127.58 | BP28: EUR | BQ28: 1.1664392 | BR28: kg
A29: =BK29+BN29 -> 8.8 | B29: 3752 | D29: entreprise | E29: =IF(J29="FedEx Priority","ST","FICP") -> ST | F29: 200720433 | G29: 202606 | H29: Express | I29: UO | J29: FedEx Priority | K29: Bill_Sender_Prepaid | L29: 05/26/2026 | M29: 05/29/2026 | N29: 872124873682 | P29: HYDRATIS B2B | Q29: HYDRATIS B2B | R29: VOIE COMMUNALE 4 | S29: CR?ANCEY | T29: 21 | U29: FR | V29: 21320 | W29: 42.72 | X29: 4.55 | Y29: 0 | Z29: -32.5 | AA29: 14.77 | AB29: 2 | AC29: 28.6 | AD29: 4.4 | AE29: M,AUDE | AF29: PHARMACIE D'ARITXAGUE | AG29: PHARMACIE D'ARITXAGUE | AH29: C,C, D'ARITXAGUE | AI29: ANGLET | AJ29: 64 | AK29: FR | AL29: 64600 | AS29: N | AT29: 30 | AU29: 31 | AV29: 40 | BB29: 0 | BC29: 0 | BD29: EUR | BE29: 46240 | BF29: 634324015 | BH29: Domestic | BI29: Your Packaging | BJ29: 0.39861111 | BK29: 36.8 | BL29: 3.92 | BM29: 0 | BN29: -28 | BO29: 12.72 | BP29: EUR | BQ29: 1.1608335 | BR29: kg
A30: =BK30+BN30 -> 8.13 | B30: 3752 | D30: entreprise | E30: =IF(J30="FedEx Priority","ST","FICP") -> ST | F30: 200720433 | G30: 202606 | H30: Express | I30: UO | J30: FedEx Priority | K30: Bill_Sender_Prepaid | L30: 46059 | M30: 46087 | N30: 872389481693 | P30: HYDRATIS B2B | Q30: HYDRATIS B2B | R30: VOIE COMMUNALE 4 | S30: CR?ANCEY | T30: 21 | U30: FR | V30: 21320 | W30: 39.66 | X30: 4.7 | Y30: 0 | Z30: -30.17 | AA30: 14.18 | AB30: 3 | AC30: 23.54 | AD30: 4.62 | AE30: P,HIE DU PARCS | AF30: PHARMACIE DU PARC | AG30: PHARMACIE DU PARC | AH30: 51 RUE DE PARIS | AI30: TORCY | AJ30: 77 | AK30: FR | AL30: 77200 | AS30: N | AT30: 13 | AU30: 21 | AV30: 29 | BB30: 0 | BC30: 0 | BD30: EUR | BE30: 46240 | BF30: 634324015 | BH30: Domestic | BI30: Your Packaging | BJ30: 0.54097222 | BK30: 34 | BL30: 4.03 | BM30: 0 | BN30: -25.87 | BO30: 12.16 | BP30: EUR | BQ30: 1.166344 | BR30: kg
A31: =BK31+BN31 -> 8.46 | B31: 3752 | D31: entreprise | E31: =IF(J31="FedEx Priority","ST","FICP") -> ST | F31: 200720433 | G31: 202606 | H31: Express | I31: UO | J31: FedEx Priority | K31: Bill_Sender_Prepaid | L31: 05/29/2026 | M31: 46028 | N31: 872385056711 | P31: HYDRATIS B2B | Q31: HYDRATIS B2B | R31: VOIE COMMUNALE 4 | S31: CR?ANCEY | T31: 21 | U31: FR | V31: 21320 | W31: 41.2 | X31: 4.39 | Y31: 0 | Z31: -31.35 | AA31: 14.23 | AB31: 2 | AC31: 26.4 | AD31: 5.28 | AE31: M,OMCELLIER | AF31: PHARMACIE DU TERRE FORT | AG31: PHARMACIE DU TERRE FORT | AH31: 29 AVENUE DU TERRE FORT | AI31: SAINT-HILAIRE-DE-RIEZ | AJ31: 85 | AK31: FR | AL31: 85270 | AS31: N | AT31: 0 | AU31: 0 | AV31: 0 | BB31: 0 | BC31: 0 | BD31: EUR | BE31: 46240 | BF31: 634324015 | BH31: Domestic | BI31: Your Packaging | BJ31: 0.51180556 | BK31: 35.4 | BL31: 3.77 | BM31: 0 | BN31: -26.94 | BO31: 12.23 | BP31: EUR | BQ31: 1.1637244 | BR31: kg
A32: =BK32+BN32 -> 10.13 | B32: 3752 | D32: entreprise | E32: =IF(J32="FedEx Priority","ST","FICP") -> ST | F32: 200720433 | G32: 202606 | H32: Express | I32: UO | J32: FedEx Priority | K32: Bill_Sender_Prepaid | L32: 05/28/2026 | M32: 05/29/2026 | N32: 872333265107 | P32: HYDRATIS B2B | Q32: HYDRATIS B2B | R32: VOIE COMMUNALE 4 | S32: CR?ANCEY | T32: 21 | U32: FR | V32: 21320 | W32: 49.32 | X32: 5.25 | Y32: 0 | Z32: -37.54 | AA32: 17.03 | AB32: 2 | AC32: 35.64 | AD32: 3.08 | AE32: P,HE | AF32: PHARMACIE DE LA FONTAINE | AG32: PHARMACIE DE LA FONTAINE | AH32: 3 PLACE CARNOT | AI32: LILLEBONNE | AJ32: 76 | AK32: FR | AL32: 76170 | AS32: N | AT32: 30 | AU32: 32 | AV32: 39 | BB32: 0 | BC32: 0 | BD32: EUR | BE32: 46240 | BF32: 634324015 | BH32: Domestic | BI32: Your Packaging | BJ32: 0.43680556 | BK32: 42.4 | BL32: 4.51 | BM32: 0 | BN32: -32.27 | BO32: 14.64 | BP32: EUR | BQ32: 1.1633182 | BR32: kg
A33: =BK33+BN33 -> 10.13 | B33: 3752 | D33: entreprise | E33: =IF(J33="FedEx Priority","ST","FICP") -> ST | F33: 200720433 | G33: 202606 | H33: Express | I33: UO | J33: FedEx Priority | K33: Bill_Sender_Prepaid | L33: 46028 | M33: 46059 | N33: 872284412449 | P33: HYDRATIS B2B | Q33: HYDRATIS B2B | R33: VOIE COMMUNALE 4 | S33: CR?ANCEY | T33: 21 | U33: FR | V33: 21320 | W33: 49.46 | X33: 5.87 | Y33: 0 | Z33: -37.64 | AA33: 17.68 | AB33: 2 | AC33: 37.4 | AD33: 4.4 | AE33: R,ECEP | AF33: PARAPHARMACIE AUCHAN BIGANOS | AG33: PARAPHARMACIE AUCHAN BIGANOS | AH33: 71 RUE DES FONDERIES | AI33: BIGANOS | AJ33: 33 | AK33: FR | AL33: 33380 | AS33: N | AT33: 29 | AU33: 30 | AV33: 40 | BB33: 0 | BC33: 0 | BD33: EUR | BE33: 46240 | BF33: 634324015 | BH33: Domestic | BI33: Your Packaging | BJ33: 0.49861111 | BK33: 42.4 | BL33: 5.03 | BM33: 0 | BN33: -32.27 | BO33: 15.16 | BP33: EUR | BQ33: 1.1664392 | BR33: kg
A34: =BK34+BN34 -> 8.46 | B34: 3752 | D34: entreprise | E34: =IF(J34="FedEx Priority","ST","FICP") -> ST | F34: 200720433 | G34: 202606 | H34: Express | I34: UO | J34: FedEx Priority | K34: Bill_Sender_Prepaid | L34: 05/28/2026 | M34: 05/29/2026 | N34: 872331093657 | P34: HYDRATIS B2B | Q34: HYDRATIS B2B | R34: VOIE COMMUNALE 4 | S34: CR?ANCEY | T34: 21 | U34: FR | V34: 21320 | W34: 41.18 | X34: 4.39 | Y34: 0 | Z34: -31.34 | AA34: 14.23 | AB34: 2 | AC34: 26.4 | AD34: 4.4 | AE34: C,OURALET | AF34: PHARMACIE DU MINAGE | AG34: PHARMACIE DU MINAGE | AH34: 1 RUE DU CORDOUAN | AI34: LA ROCHELLE | AJ34: 17 | AK34: FR | AL34: 17000 | AS34: N | AT34: 0 | AU34: 0 | AV34: 0 | BB34: 0 | BC34: 0 | BD34: EUR | BE34: 46240 | BF34: 634324015 | BH34: Domestic | BI34: Your Packaging | BJ34: 0.44513889 | BK34: 35.4 | BL34: 3.77 | BM34: 0 | BN34: -26.94 | BO34: 12.23 | BP34: EUR | BQ34: 1.1633182 | BR34: kg
A35: =BK35+BN35 -> 8.46 | B35: 3752 | D35: entreprise | E35: =IF(J35="FedEx Priority","ST","FICP") -> ST | F35: 200720433 | G35: 202606 | H35: Express | I35: UO | J35: FedEx Priority | K35: Bill_Sender_Prepaid | L35: 05/28/2026 | M35: 46028 | N35: 872329618198 | P35: HYDRATIS B2B | Q35: HYDRATIS B2B | R35: VOIE COMMUNALE 4 | S35: CR?ANCEY | T35: 21 | U35: FR | V35: 21320 | W35: 41.18 | X35: 4.39 | Y35: 0 | Z35: -31.34 | AA35: 14.23 | AB35: 2 | AC35: 26.4 | AD35: 24.2 | AE35: P,HARMACIE DE LA | AF35: PHARMACIE DE LA PLAGE | AG35: PHARMACIE DE LA PLAGE | AH35: 33 PROMENADE DE LA MER | AI35: CAVALAIRE-SUR-MER | AJ35: 83 | AK35: FR | AL35: 83240 | AS35: N | AT35: 20 | AU35: 20 | AV35: 30 | BB35: 0 | BC35: 0 | BD35: EUR | BE35: 46240 | BF35: 634324015 | BH35: Domestic | BI35: Your Packaging | BJ35: 0.44305556 | BK35: 35.4 | BL35: 3.77 | BM35: 0 | BN35: -26.94 | BO35: 12.23 | BP35: EUR | BQ35: 1.1633182 | BR35: kg
A36: =BK36+BN36 -> 9.13 | B36: 3752 | D36: entreprise | E36: =IF(J36="FedEx Priority","ST","FICP") -> ST | F36: 200720433 | G36: 202606 | H36: Express | I36: UO | J36: FedEx Priority | K36: Bill_Sender_Prepaid | L36: 05/28/2026 | M36: 05/29/2026 | N36: 872285381670 | P36: HYDRATIS B2B | Q36: HYDRATIS B2B | R36: VOIE COMMUNALE 4 | S36: CR?ANCEY | T36: 21 | U36: FR | V36: 21320 | W36: 44.44 | X36: 4.73 | Y36: 0 | Z36: -33.82 | AA36: 15.36 | AB36: 2 | AC36: 30.8 | AD36: 3.96 | AE36: M,ARIE | AF36: PHARMACIE DE LA CROIX VALMER | AG36: PHARMACIE DE LA CROIX VALMER | AH36: RUE LOUIS MARTIN | AI36: LA CROIX-VALMER | AJ36: 83 | AK36: FR | AL36: 83420 | AS36: N | AT36: 30 | AU36: 31 | AV36: 39 | BB36: 0 | BC36: 0 | BD36: EUR | BE36: 46240 | BF36: 634324015 | BH36: Domestic | BI36: Your Packaging | BJ36: 0.52222222 | BK36: 38.2 | BL36: 4.07 | BM36: 0 | BN36: -29.07 | BO36: 13.2 | BP36: EUR | BQ36: 1.1633182 | BR36: kg
A37: =BK37+BN37 -> 12.48 | B37: 3752 | D37: entreprise | E37: =IF(J37="FedEx Priority","ST","FICP") -> ST | F37: 200720433 | G37: 202606 | H37: Express | I37: UO | J37: FedEx Priority | K37: Bill_Sender_Prepaid | L37: 46301 | M37: 46332 | N37: 872884057299 | P37: HYDRATIS B2B | Q37: HYDRATIS B2B | R37: VOIE COMMUNALE 4 | S37: CR?ANCEY | T37: 21 | U37: FR | V37: 21320 | W37: 60.2 | X37: 7.14 | Y37: 0 | Z37: -45.8 | AA37: 21.53 | AB37: 3 | AC37: 52.58 | AD37: 52.58 | AE37: P,H | AF37: PHARMACIE DES ARCADES | AG37: PHARMACIE DES ARCADES | AH37: 100 RUE DU 23 AOUT 1944 | AI37: MIONS | AJ37: 69 | AK37: FR | AL37: 69780 | AS37: N | AT37: 4 | AU37: 74 | AV37: 114 | BB37: 0 | BC37: 0 | BD37: EUR | BE37: 06/15/2026 | BF37: 634333759 | BH37: Domestic | BI37: Your Packaging | BJ37: 0.39305556 | BK37: 52.2 | BL37: 6.19 | BM37: 0 | BN37: -39.72 | BO37: 18.67 | BP37: EUR | BQ37: 1.1531631 | BR37: kg
A38: =BK38+BN38 -> 8.13 | B38: 3752 | E38: =IF(J38="FedEx Priority","ST","FICP") -> ST | F38: 200720433 | G38: 202606 | H38: Express | I38: UO | J38: FedEx Priority | K38: Bill_Sender_Prepaid | L38: 46087 | M38: 46118 | N38: 872531520801 | P38: HYDRATIS B2B | Q38: HYDRATIS B2B | R38: VOIE COMMUNALE 4 | S38: CR?ANCEY | T38: 21 | U38: FR | V38: 21320 | W38: 39.58 | X38: 4.69 | Y38: 0 | Z38: -30.12 | AA38: 14.16 | AB38: 2 | AC38: 24.2 | AD38: 3.52 | AE38: A,UBERT | AF38: PHARMACIE DE L'ODON | AG38: PHARMACIE DE L'ODON | AH38: 62 ROUTE DE BRETAGNE | AI38: BRETTEVILLE-SUR-ODON | AJ38: 14 | AK38: FR | AL38: 14760 | AS38: N | AT38: 30 | AU38: 31 | AV38: 40 | BB38: 0 | BC38: 0 | BD38: EUR | BE38: 46240 | BF38: 634324015 | BH38: Domestic | BI38: Your Packaging | BJ38: 0.38611111 | BK38: 34 | BL38: 4.03 | BM38: 0 | BN38: -25.87 | BO38: 12.16 | BP38: EUR | BQ38: 1.1640901 | BR38: kg
A39: =BK39+BN39 -> 10.47 | B39: 3752 | D39: entreprise | E39: =IF(J39="FedEx Priority","ST","FICP") -> ST | F39: 200720433 | G39: 202606 | H39: Express | I39: UO | J39: FedEx Priority | K39: Bill_Sender_Prepaid | L39: 05/29/2026 | M39: 05/30/2026 | N39: 872382459480 | P39: HYDRATIS B2B | Q39: HYDRATIS B2B | R39: VOIE COMMUNALE 4 | S39: CR?ANCEY | T39: 21 | U39: FR | V39: 21320 | W39: 50.97 | X39: 5.42 | Y39: 0 | Z39: -38.79 | AA39: 17.61 | AB39: 2 | AC39: 39.6 | AD39: 3.96 | AE39: P,HARMA PANO | AF39: PHARMACIE DU PANORAMA | AG39: PHARMACIE DU PANORAMA | AH39: 16 PLACE DU PANORAMA | AI39: CLAMART | AJ39: 92 | AK39: FR | AL39: 92140 | AS39: N | AT39: 30 | AU39: 30 | AV39: 38 | BB39: 0 | BC39: 0 | BD39: EUR | BE39: 46240 | BF39: 634324015 | BH39: Domestic | BI39: Your Packaging | BJ39: 0.32986111 | BK39: 43.8 | BL39: 4.66 | BM39: 0 | BN39: -33.33 | BO39: 15.13 | BP39: EUR | BQ39: 1.1637244 | BR39: kg
A40: =BK40+BN40 -> 7.46 | B40: 3752 | D40: entreprise | E40: =IF(J40="FedEx Priority","ST","FICP") -> ST | F40: 200720433 | G40: 202606 | H40: Express | I40: UO | J40: FedEx Priority | K40: Bill_Sender_Prepaid | L40: 05/28/2026 | M40: 05/29/2026 | N40: 872285433650 | P40: HYDRATIS B2B | Q40: HYDRATIS B2B | R40: VOIE COMMUNALE 4 | S40: CR?ANCEY | T40: 21 | U40: FR | V40: 21320 | W40: 36.3 | X40: 3.87 | Y40: 0 | Z40: -27.62 | AA40: 12.55 | AB40: 1 | AC40: 19.8 | AD40: 1.32 | AE40: C,YCL | AF40: RUN ADDICT CUCQ | AG40: RUN ADDICT CUCQ | AH40: E-BIKE SARL | AI40: CUCQ | AJ40: 62 | AK40: FR | AL40: 62780 | AS40: N | AT40: 30 | AU40: 31 | AV40: 40 | BB40: 0 | BC40: 0 | BD40: EUR | BE40: 46240 | BF40: 634324015 | BH40: Domestic | BI40: Your Packaging | BJ40: 0.47222222 | BK40: 31.2 | BL40: 3.33 | BM40: 0 | BN40: -23.74 | BO40: 10.79 | BP40: EUR | BQ40: 1.1633182 | BR40: kg
A41: =BK41+BN41 -> 12.48 | B41: 3752 | D41: entreprise | E41: =IF(J41="FedEx Priority","ST","FICP") -> ST | F41: 200720433 | G41: 202606 | H41: Express | I41: UO | J41: FedEx Priority | K41: Bill_Sender_Prepaid | L41: 05/29/2026 | M41: 46028 | N41: 872384849440 | P41: HYDRATIS B2B | Q41: HYDRATIS B2B | R41: VOIE COMMUNALE 4 | S41: CR?ANCEY | T41: 21 | U41: FR | V41: 21320 | W41: 60.75 | X41: 6.47 | Y41: 0 | Z41: -46.22 | AA41: 20.99 | AB41: 4 | AC41: 52.14 | AD41: 14.96 | AE41: P,HIE | AF41: PHARMACIE DU VAL DE LYS | AG41: PHARMACIE DU VAL DE LYS | AH41: 85 RUE DU BOIS | AI41: AIRE SUR LA LYS | AJ41: 62 | AK41: FR | AL41: 62120 | AS41: N | AT41: 30 | AU41: 31 | AV41: 40 | BB41: 0 | BC41: 0 | BD41: EUR | BE41: 46240 | BF41: 634324015 | BH41: Domestic | BI41: Your Packaging | BJ41: 0.425 | BK41: 52.2 | BL41: 5.56 | BM41: 0 | BN41: -39.72 | BO41: 18.04 | BP41: EUR | BQ41: 1.1637244 | BR41: kg
A42: =BK42+BN42 -> 13.14 | B42: 3752 | D42: entreprise | E42: =IF(J42="FedEx Priority","ST","FICP") -> ST | F42: 200720433 | G42: 202606 | H42: Express | I42: UO | J42: FedEx Priority | K42: Bill_Sender_Prepaid | L42: 05/29/2026 | M42: 05/30/2026 | N42: 872381645380 | P42: HYDRATIS B2B | Q42: HYDRATIS B2B | R42: VOIE COMMUNALE 4 | S42: CR?ANCEY | T42: 21 | U42: FR | V42: 21320 | W42: 64 | X42: 6.82 | Y42: 0 | Z42: -48.71 | AA42: 22.11 | AB42: 3 | AC42: 55.88 | AD42: 7.92 | AE42: M,ARIE | AF42: PHARMACIE DE LA PAIX | AG42: PHARMACIE DE LA PAIX | AH42: 34 BIS BOULEVARD DE LA PAIX | AI42: REIMS | AJ42: 51 | AK42: FR | AL42: 51100 | AS42: N | AT42: 30 | AU42: 32 | AV42: 39 | BB42: 0 | BC42: 0 | BD42: EUR | BE42: 46240 | BF42: 634324015 | BH42: Domestic | BI42: Your Packaging | BJ42: 0.40972222 | BK42: 55 | BL42: 5.86 | BM42: 0 | BN42: -41.86 | BO42: 19 | BP42: EUR | BQ42: 1.1637244 | BR42: kg
A43: =BK43+BN43 -> 9.46 | B43: 3752 | D43: entreprise | E43: =IF(J43="FedEx Priority","ST","FICP") -> ST | F43: 200720433 | G43: 202606 | H43: Express | I43: UO | J43: FedEx Priority | K43: Bill_Sender_Prepaid | L43: 46148 | M43: 46271 | N43: 872691013860 | P43: HYDRATIS B2B | Q43: HYDRATIS B2B | R43: VOIE COMMUNALE 4 | S43: CR?ANCEY | T43: 21 | U43: FR | V43: 21320 | W43: 45.98 | X43: 5.45 | Y43: 0 | Z43: -35 | AA43: 16.43 | AB43: 2 | AC43: 33 | AD43: 33 | AE43: M,OLINIETR | AF43: PHARMACIE MOLINIER | AG43: PHARMACIE MOLINIER | AH43: 47 RUE GEORGES CLEMENCEAU | AI43: LANNEMEZAN | AJ43: 65 | AK43: FR | AL43: 65300 | AS43: N | AT43: 0 | AU43: 0 | AV43: 0 | BB43: 0 | BC43: 0 | BD43: EUR | BE43: 06/15/2026 | BF43: 634333759 | BH43: Domestic | BI43: Your Packaging | BJ43: 0.42222222 | BK43: 39.6 | BL43: 4.69 | BM43: 0 | BN43: -30.14 | BO43: 14.15 | BP43: EUR | BQ43: 1.1612109 | BR43: kg
A44: =BK44+BN44 -> 9.8 | B44: 3752 | D44: entreprise | E44: =IF(J44="FedEx Priority","ST","FICP") -> ST | F44: 200720433 | G44: 202606 | H44: Express | I44: UO | J44: FedEx Priority | K44: Bill_Sender_Prepaid | L44: 46028 | M44: 46059 | N44: 872328123110 | P44: HYDRATIS B2B | Q44: HYDRATIS B2B | R44: VOIE COMMUNALE 4 | S44: CR?ANCEY | T44: 21 | U44: FR | V44: 21320 | W44: 47.82 | X44: 5.67 | Y44: 0 | Z44: -36.39 | AA44: 17.1 | AB44: 2 | AC44: 34.54 | AD44: 3.96 | AE44: F,Florian | AF44: SPORT 2000 AGDE | AG44: SPORT 2000 AGDE | AH44: CCIAL INTERMARCHE | AI44: AGDE | AJ44: 34 | AK44: FR | AL44: 34300 | AS44: N | AT44: 4 | AU44: 74 | AV44: 114 | BB44: 0 | BC44: 0 | BD44: EUR | BE44: 46240 | BF44: 634324015 | BH44: Domestic | BI44: Your Packaging | BJ44: 0.43819444 | BK44: 41 | BL44: 4.86 | BM44: 0 | BN44: -31.2 | BO44: 14.66 | BP44: EUR | BQ44: 1.1664392 | BR44: kg
A45: =BK45+BN45 -> 12.81 | B45: 3752 | D45: entreprise | E45: =IF(J45="FedEx Priority","ST","FICP") -> ST | F45: 200720433 | G45: 202606 | H45: Express | I45: UO | J45: FedEx Priority | K45: Bill_Sender_Prepaid | L45: 05/28/2026 | M45: 05/29/2026 | N45: 872331831558 | P45: HYDRATIS B2B | Q45: HYDRATIS B2B | R45: VOIE COMMUNALE 4 | S45: CR?ANCEY | T45: 21 | U45: FR | V45: 21320 | W45: 62.35 | X45: 6.64 | Y45: 0 | Z45: -47.45 | AA45: 21.54 | AB45: 5 | AC45: 54.12 | AD45: 14.3 | AE45: I,Dupuis | AF45: PHARMACIE DUPUIS | AG45: PHARMACIE DUPUIS | AH45: 5 RUE DE LA CHAMPIGNONNIERE | AI45: SENLIS | AJ45: 60 | AK45: FR | AL45: 60300 | AS45: N | AT45: 20 | AU45: 20 | AV45: 30 | BB45: 0 | BC45: 0 | BD45: EUR | BE45: 46240 | BF45: 634324015 | BH45: Domestic | BI45: Your Packaging | BJ45: 0.43333333 | BK45: 53.6 | BL45: 5.71 | BM45: 0 | BN45: -40.79 | BO45: 18.52 | BP45: EUR | BQ45: 1.1633182 | BR45: kg
A46: =BK46+BN46 -> 18.5 | B46: 3752 | D46: entreprise | E46: =IF(J46="FedEx Priority","ST","FICP") -> ST | F46: 200720433 | G46: 202606 | H46: Express | I46: UO | J46: FedEx Priority | K46: Bill_Sender_Prepaid | L46: 05/28/2026 | M46: 05/29/2026 | N46: 872279550660 | P46: HYDRATIS B2B | Q46: HYDRATIS B2B | R46: VOIE COMMUNALE 4 | S46: CR?ANCEY | T46: 21 | U46: FR | V46: 21320 | W46: 90.04 | X46: 110.1 | Y46: 0 | Z46: -68.52 | AA46: 131.62 | AB46: 6 | AC46: 92.4 | AD46: 17.16 | AE46: P,HIE SORNE | AF46: JOZAN MADAME | AG46: PHARMACIE DE LA SORNE | AH46: 239 RUE DU JURA | AI46: MACORNAY | AJ46: 39 | AK46: FR | AL46: 39570 | AS46: N | AT46: 0 | AU46: 0 | AV46: 0 | BB46: 0 | BC46: 0 | BD46: EUR | BE46: 46240 | BF46: 634324015 | BH46: Domestic | BI46: Your Packaging | BJ46: 0.49236111 | BK46: 77.4 | BL46: 94.64 | BM46: 0 | BN46: -58.9 | BO46: 113.14 | BP46: EUR | BQ46: 1.1633182 | BR46: kg
A47: =BK47+BN47 -> 8.46 | B47: 3752 | D47: entreprise | E47: =IF(J47="FedEx Priority","ST","FICP") -> ST | F47: 200720433 | G47: 202606 | H47: Express | I47: UO | J47: FedEx Priority | K47: Bill_Sender_Prepaid | L47: 05/29/2026 | M47: 05/30/2026 | N47: 872336463750 | P47: HYDRATIS B2B | Q47: HYDRATIS B2B | R47: VOIE COMMUNALE 4 | S47: CR?ANCEY | T47: 21 | U47: FR | V47: 21320 | W47: 41.2 | X47: 4.39 | Y47: 0 | Z47: -31.35 | AA47: 14.23 | AB47: 2 | AC47: 26.4 | AD47: 3.08 | AE47: P,HIE SAINT GEORG | AF47: PHARMACIE SAINT GEORGES | AG47: PHARMACIE SAINT GEORGES | AH47: 15 RUE HENRI MESSAGER | AI47: NOTRE-DAME-DE-GRAVENCHON | AJ47: 76 | AK47: FR | AL47: 76330 | AS47: N | AT47: 0 | AU47: 0 | AV47: 0 | BB47: 0 | BC47: 0 | BD47: EUR | BE47: 46240 | BF47: 634324015 | BH47: Domestic | BI47: Your Packaging | BJ47: 0.38819444 | BK47: 35.4 | BL47: 3.77 | BM47: 0 | BN47: -26.94 | BO47: 12.23 | BP47: EUR | BQ47: 1.1637244 | BR47: kg
A48: =BK48+BN48 -> 6.79 | B48: 3752 | D48: entreprise | E48: =IF(J48="FedEx Priority","ST","FICP") -> ST | F48: 200720433 | G48: 202606 | H48: Express | I48: UO | J48: FedEx Priority | K48: Bill_Sender_Prepaid | L48: 46028 | M48: 46087 | N48: 872384950240 | P48: HYDRATIS B2B | Q48: HYDRATIS B2B | R48: VOIE COMMUNALE 4 | S48: CR?ANCEY | T48: 21 | U48: FR | V48: 21320 | W48: 33.13 | X48: 3.92 | Y48: 0 | Z48: -25.21 | AA48: 11.84 | AB48: 1 | AC48: 15.4 | AD48: 1.32 | AE48: B,OURASSEAU | AF48: PARAPHARMACIE LECLERC CHANTONNAY | AG48: PARAPHARMACIE LECLERC CHANTONN | AH48: ZONE POLARIS NORD | AI48: CHANTONNAY | AJ48: 85 | AK48: FR | AL48: 85110 | AS48: N | AT48: 0 | AU48: 0 | AV48: 0 | BB48: 0 | BC48: 0 | BD48: EUR | BE48: 46240 | BF48: 634324015 | BH48: Domestic | BI48: Your Packaging | BJ48: 0.58958333 | BK48: 28.4 | BL48: 3.36 | BM48: 0 | BN48: -21.61 | BO48: 10.15 | BP48: EUR | BQ48: 1.1664392 | BR48: kg
A49: =BK49+BN49 -> 14.82 | B49: 3752 | D49: entreprise | E49: =IF(J49="FedEx Priority","ST","FICP") -> ST | F49: 200720433 | G49: 202606 | H49: Express | I49: UO | J49: FedEx Priority | K49: Bill_Sender_Prepaid | L49: 05/29/2026 | M49: 05/30/2026 | N49: 872335926178 | P49: HYDRATIS B2B | Q49: HYDRATIS B2B | R49: VOIE COMMUNALE 4 | S49: CR?ANCEY | T49: 21 | U49: FR | V49: 21320 | W49: 72.15 | X49: 7.68 | Y49: 0 | Z49: -54.9 | AA49: 24.93 | AB49: 4 | AC49: 66.22 | AD49: 18.48 | AE49: F,LORIAN | AF49: PHARMACIE D'IFS / ROCADE SUD | AG49: PHARMACIE D'IFS / ROCADE SUD | AH49: 190 RUE DE ROCQUANCOURT | AI49: IFS | AJ49: 14 | AK49: FR | AL49: 14123 | AS49: N | AT49: 30 | AU49: 31 | AV49: 41 | BB49: 0 | BC49: 0 | BD49: EUR | BE49: 46240 | BF49: 634324015 | BH49: Domestic | BI49: Your Packaging | BJ49: 0.39722222 | BK49: 62 | BL49: 6.6 | BM49: 0 | BN49: -47.18 | BO49: 21.42 | BP49: EUR | BQ49: 1.1637244 | BR49: kg
A50: =BK50+BN50 -> 12.14 | B50: 3752 | D50: entreprise | E50: =IF(J50="FedEx Priority","ST","FICP") -> ST | F50: 200720433 | G50: 202606 | H50: Express | I50: UO | J50: FedEx Priority | K50: Bill_Sender_Prepaid | L50: 46059 | M50: 46087 | N50: 872390485979 | P50: HYDRATIS B2B | Q50: HYDRATIS B2B | R50: VOIE COMMUNALE 4 | S50: CR?ANCEY | T50: 21 | U50: FR | V50: 21320 | W50: 59.25 | X50: 7.02 | Y50: 0 | Z50: -45.09 | AA50: 21.18 | AB50: 3 | AC50: 50.6 | AD50: 15.84 | AE50: C,Connan | AF50: UNIPHARM LOIRE-OCEAN | AG50: UNIPHARM LOIRE-OCEAN | AH50: CERP LES SORINIERES 7H30 - 11H | AI50: LES SORINI?RES | AJ50: 44 | AK50: FR | AL50: 44840 | AS50: N | AT50: 20 | AU50: 31 | AV50: 39 | BB50: 0 | BC50: 0 | BD50: EUR | BE50: 46240 | BF50: 634324015 | BH50: Domestic | BI50: Your Packaging | BJ50: 0.40555556 | BK50: 50.8 | BL50: 6.02 | BM50: 0 | BN50: -38.66 | BO50: 18.16 | BP50: EUR | BQ50: 1.166344 | BR50: kg
A51: =BK51+BN51 -> 8.46 | B51: 3752 | D51: entreprise | E51: =IF(J51="FedEx Priority","ST","FICP") -> ST | F51: 200720433 | G51: 202606 | H51: Express | I51: UO | J51: FedEx Priority | K51: Bill_Sender_Prepaid | L51: 05/29/2026 | M51: 46028 | N51: 872385719430 | P51: HYDRATIS B2B | Q51: HYDRATIS B2B | R51: VOIE COMMUNALE 4 | S51: CR?ANCEY | T51: 21 | U51: FR | V51: 21320 | W51: 41.2 | X51: 4.39 | Y51: 0 | Z51: -31.35 | AA51: 14.23 | AB51: 2 | AC51: 26.4 | AD51: 4.4 | AE51: R,Reception | AF51: PHARMACIE PERARD TROISGROS | AG51: PHARMACIE PERARD TROISGROS | AH51: 1 PLACE DE LA LIBERTE | AI51: CAP D AIL | AJ51: 6 | AK51: FR | AL51: 6320 | AS51: N | AT51: 0 | AU51: 0 | AV51: 0 | BB51: 0 | BC51: 0 | BD51: EUR | BE51: 46240 | BF51: 634324015 | BH51: Domestic | BI51: Your Packaging | BJ51: 0.49513889 | BK51: 35.4 | BL51: 3.77 | BM51: 0 | BN51: -26.94 | BO51: 12.23 | BP51: EUR | BQ51: 1.1637244 | BR51: kg
A52: =BK52+BN52 -> 42.66 | B52: 3752 | E52: =IF(J52="FedEx Priority","ST","FICP") -> ST | F52: 200720433 | G52: 202606 | H52: Express | I52: UO | J52: FedEx Priority | K52: Bill_Sender_Prepaid | L52: 46087 | M52: 46118 | N52: 872534651802 | P52: HYDRATIS B2B | Q52: HYDRATIS B2B | R52: VOIE COMMUNALE 4 | S52: CR?ANCEY | T52: 21 | U52: FR | V52: 21320 | W52: 207.79 | X52: 170.91 | Y52: 0 | Z52: -158.13 | AA52: 220.57 | AB52: 12 | AC52: 231 | AD52: 121.44 | AE52: E,LODIE | AF52: PHARMACIE DU MONT BLANC | AG52: PHARMACIE DU MONT BLANC | AH52: 15 RUE JOSEPH VALLOT | AI52: CHAMONIX-MONT-BLANC | AJ52: 74 | AK52: FR | AL52: 74400 | AS52: N | AT52: 0 | AU52: 0 | AV52: 0 | BB52: 0 | BC52: 0 | BD52: EUR | BE52: 46240 | BF52: 634324015 | BH52: Domestic | BI52: Your Packaging | BJ52: 0.44305556 | BK52: 178.5 | BL52: 146.82 | BM52: 0 | BN52: -135.84 | BO52: 189.48 | BP52: EUR | BQ52: 1.1640901 | BR52: kg
A53: =BK53+BN53 -> 8.46 | B53: 3752 | D53: entreprise | E53: =IF(J53="FedEx Priority","ST","FICP") -> ST | F53: 200720433 | G53: 202606 | H53: Express | I53: UO | J53: FedEx Priority | K53: Bill_Sender_Prepaid | L53: 46028 | M53: 46059 | N53: 872387195530 | P53: HYDRATIS B2B | Q53: HYDRATIS B2B | R53: VOIE COMMUNALE 4 | S53: CR?ANCEY | T53: 21 | U53: FR | V53: 21320 | W53: 41.29 | X53: 4.9 | Y53: 0 | Z53: -31.42 | AA53: 14.77 | AB53: 2 | AC53: 26.4 | AD53: 2.64 | AE53: P,HIE GRAVOULET | AF53: PHARMACIE GRAVOULET | AG53: PHARMACIE GRAVOULET | AH53: 5 RUE DU HAUT CHATEAU | AI53: LEYR | AJ53: 54 | AK53: FR | AL53: 54760 | AS53: N | AT53: 30 | AU53: 31 | AV53: 39 | BB53: 0 | BC53: 0 | BD53: EUR | BE53: 46240 | BF53: 634324015 | BH53: Domestic | BI53: Your Packaging | BJ53: 0.41944444 | BK53: 35.4 | BL53: 4.2 | BM53: 0 | BN53: -26.94 | BO53: 12.66 | BP53: EUR | BQ53: 1.1664392 | BR53: kg
A54: =BK54+BN54 -> 9.46 | B54: 3752 | E54: =IF(J54="FedEx Priority","ST","FICP") -> ST | F54: 200720433 | G54: 202606 | H54: Express | I54: UO | J54: FedEx Priority | K54: Bill_Sender_Prepaid | L54: 46087 | M54: 46118 | N54: 872533330020 | P54: HYDRATIS B2B | Q54: HYDRATIS B2B | R54: VOIE COMMUNALE 4 | S54: CR?ANCEY | T54: 21 | U54: FR | V54: 21320 | W54: 46.1 | X54: 5.46 | Y54: 0 | Z54: -35.09 | AA54: 16.47 | AB54: 2 | AC54: 33 | AD54: 5.28 | AE54: D,ECANTEH | AF54: PHARMACIE GAMBETTA | AG54: PHARMACIE GAMBETTA | AH54: 15 PLACE GAMBETTA | AI54: CHATEAUROUX | AJ54: 36 | AK54: FR | AL54: 36000 | AS54: N | AT54: 30 | AU54: 31 | AV54: 39 | BB54: 0 | BC54: 0 | BD54: EUR | BE54: 46240 | BF54: 634324015 | BH54: Domestic | BI54: Your Packaging | BJ54: 0.45763889 | BK54: 39.6 | BL54: 4.69 | BM54: 0 | BN54: -30.14 | BO54: 14.15 | BP54: EUR | BQ54: 1.1640901 | BR54: kg
A55: =BK55+BN55 -> 8.13 | B55: 3752 | D55: entreprise | E55: =IF(J55="FedEx Priority","ST","FICP") -> ST | F55: 200720433 | G55: 202606 | H55: Express | I55: UO | J55: FedEx Priority | K55: Bill_Sender_Prepaid | L55: 46059 | M55: 46087 | N55: 872285074832 | P55: HYDRATIS B2B | Q55: HYDRATIS B2B | R55: VOIE COMMUNALE 4 | S55: CR?ANCEY | T55: 21 | U55: FR | V55: 21320 | W55: 39.66 | X55: 4.7 | Y55: 0 | Z55: -30.17 | AA55: 14.18 | AB55: 2 | AC55: 24.2 | AD55: 5.72 | AE55: I,Isdis | AF55: INTERSPORT CERNAY 00329/000 | AG55: INTERSPORT CERNAY 00329/000 | AH55: SAS ISDIS | AI55: CERNAY | AJ55: 68 | AK55: FR | AL55: 68700 | AS55: N | AT55: 0 | AU55: 0 | AV55: 0 | BB55: 0 | BC55: 0 | BD55: EUR | BE55: 46240 | BF55: 634324015 | BH55: Domestic | BI55: Your Packaging | BJ55: 0.51944444 | BK55: 34 | BL55: 4.03 | BM55: 0 | BN55: -25.87 | BO55: 12.16 | BP55: EUR | BQ55: 1.166344 | BR55: kg
A56: =BK56+BN56 -> 21.51 | B56: 3752 | D56: entreprise | E56: =IF(J56="FedEx Priority","ST","FICP") -> ST | F56: 200720433 | G56: 202606 | H56: Express | I56: UO | J56: FedEx Priority | K56: Bill_Sender_Prepaid | L56: 05/28/2026 | M56: 05/29/2026 | N56: 872328013160 | P56: HYDRATIS B2B | Q56: HYDRATIS B2B | R56: VOIE COMMUNALE 4 | S56: CR?ANCEY | T56: 21 | U56: FR | V56: 21320 | W56: 104.7 | X56: 111.66 | Y56: 0 | Z56: -79.68 | AA56: 136.68 | AB56: 6 | AC56: 111.76 | AD56: 63.36 | AE56: P,HARMACIE DE LA | AF56: PHARMACIE DE LA VOUTE | AG56: PHARMACIE DE LA VOUTE | AH56: 28 PLACE JEAN BART | AI56: DUNKERQUE | AJ56: 59 | AK56: FR | AL56: 59140 | AS56: N | AT56: 29 | AU56: 30 | AV56: 40 | BB56: 0 | BC56: 0 | BD56: EUR | BE56: 46240 | BF56: 634324015 | BH56: Domestic | BI56: Your Packaging | BJ56: 0.43402778 | BK56: 90 | BL56: 95.98 | BM56: 0 | BN56: -68.49 | BO56: 117.49 | BP56: EUR | BQ56: 1.1633182 | BR56: kg
A57: =BK57+BN57 -> 8.46 | B57: 3752 | D57: entreprise | E57: =IF(J57="FedEx Priority","ST","FICP") -> ST | F57: 200720433 | G57: 202606 | H57: Express | I57: UO | J57: FedEx Priority | K57: Bill_Sender_Prepaid | L57: 05/29/2026 | M57: 05/30/2026 | N57: 872384934038 | P57: HYDRATIS B2B | Q57: HYDRATIS B2B | R57: VOIE COMMUNALE 4 | S57: CR?ANCEY | T57: 21 | U57: FR | V57: 21320 | W57: 41.2 | X57: 4.39 | Y57: 0 | Z57: -31.35 | AA57: 14.23 | AB57: 2 | AC57: 26.4 | AD57: 3.08 | AE57: C,HARLETTE | AF57: PHARMACIE PILAR | AG57: PHARMACIE PILAR | AH57: 119 AVENUE JEAN MERMOZ | AI57: BILLERE | AJ57: 64 | AK57: FR | AL57: 64140 | AS57: N | AT57: 0 | AU57: 0 | AV57: 0 | BB57: 0 | BC57: 0 | BD57: EUR | BE57: 46240 | BF57: 634324015 | BH57: Domestic | BI57: Your Packaging | BJ57: 0.42361111 | BK57: 35.4 | BL57: 3.77 | BM57: 0 | BN57: -26.94 | BO57: 12.23 | BP57: EUR | BQ57: 1.1637244 | BR57: kg
A58: =BK58+BN58 -> 11.47 | B58: 3752 | D58: entreprise | E58: =IF(J58="FedEx Priority","ST","FICP") -> ST | F58: 200720433 | G58: 202606 | H58: Express | I58: UO | J58: FedEx Priority | K58: Bill_Sender_Prepaid | L58: 46028 | M58: 46059 | N58: 872387772926 | P58: HYDRATIS B2B | Q58: HYDRATIS B2B | R58: VOIE COMMUNALE 4 | S58: CR?ANCEY | T58: 21 | U58: FR | V58: 21320 | W58: 55.99 | X58: 6.64 | Y58: 0 | Z58: -42.61 | AA58: 20.02 | AB58: 3 | AC58: 46.2 | AD58: 8.58 | AE58: P,Safarti | AF58: PHARMACIE DE LA MUETTE | AG58: PHARMACIE DE LA MUETTE | AH58: 2 AVENUE MOZART | AI58: PARIS 16 | AJ58: 75 | AK58: FR | AL58: 75016 | AS58: N | AT58: 0 | AU58: 0 | AV58: 0 | BB58: 0 | BC58: 0 | BD58: EUR | BE58: 46240 | BF58: 634324015 | BH58: Domestic | BI58: Your Packaging | BJ58: 0.46111111 | BK58: 48 | BL58: 5.69 | BM58: 0 | BN58: -36.53 | BO58: 17.16 | BP58: EUR | BQ58: 1.1664392 | BR58: kg
A59: =BK59+BN59 -> 10.13 | B59: 3752 | D59: entreprise | E59: =IF(J59="FedEx Priority","ST","FICP") -> ST | F59: 200720433 | G59: 202606 | H59: Express | I59: UO | J59: FedEx Priority | K59: Bill_Sender_Prepaid | L59: 05/29/2026 | M59: 46059 | N59: 872384791109 | P59: HYDRATIS B2B | Q59: HYDRATIS B2B | R59: VOIE COMMUNALE 4 | S59: CR?ANCEY | T59: 21 | U59: FR | V59: 21320 | W59: 49.34 | X59: 5.25 | Y59: 0 | Z59: -37.55 | AA59: 17.04 | AB59: 3 | AC59: 35.42 | AD59: 7.26 | AE59: B,ORDES | AF59: PHARMACIE CENTRALE | AG59: PHARMACIE CENTRALE | AH59: 11 PLACE DU BOURG | AI59: RODEZ | AJ59: 12 | AK59: FR | AL59: 12000 | AS59: N | AT59: 0 | AU59: 0 | AV59: 0 | BB59: 0 | BC59: 0 | BD59: EUR | BE59: 46240 | BF59: 634324015 | BH59: Domestic | BI59: Your Packaging | BJ59: 0.51944444 | BK59: 42.4 | BL59: 4.51 | BM59: 0 | BN59: -32.27 | BO59: 14.64 | BP59: EUR | BQ59: 1.1637244 | BR59: kg
A60: =BK60+BN60 -> 8.46 | B60: 3752 | D60: entreprise | E60: =IF(J60="FedEx Priority","ST","FICP") -> ST | F60: 200720433 | G60: 202606 | H60: Express | I60: UO | J60: FedEx Priority | K60: Bill_Sender_Prepaid | L60: 05/28/2026 | M60: 05/29/2026 | N60: 872284781860 | P60: HYDRATIS B2B | Q60: HYDRATIS B2B | R60: VOIE COMMUNALE 4 | S60: CR?ANCEY | T60: 21 | U60: FR | V60: 21320 | W60: 41.18 | X60: 4.39 | Y60: 0 | Z60: -31.34 | AA60: 14.23 | AB60: 2 | AC60: 26.4 | AD60: 4.4 | AE60: G,ASSOT | AF60: PHARMACIE MARCEAU | AG60: PHARMACIE MARCEAU | AH60: 13 RUE MARCEAU | AI60: CHARTRES | AJ60: 28 | AK60: FR | AL60: 28000 | AS60: N | AT60: 0 | AU60: 0 | AV60: 0 | BB60: 0 | BC60: 0 | BD60: EUR | BE60: 46240 | BF60: 634324015 | BH60: Domestic | BI60: Your Packaging | BJ60: 0.46805556 | BK60: 35.4 | BL60: 3.77 | BM60: 0 | BN60: -26.94 | BO60: 12.23 | BP60: EUR | BQ60: 1.1633182 | BR60: kg
A61: =BK61+BN61 -> 11.47 | B61: 3752 | D61: entreprise | E61: =IF(J61="FedEx Priority","ST","FICP") -> ST | F61: 200720433 | G61: 202606 | H61: Express | I61: UO | J61: FedEx Priority | K61: Bill_Sender_Prepaid | L61: 05/28/2026 | M61: 05/29/2026 | N61: 872332664333 | P61: HYDRATIS B2B | Q61: HYDRATIS B2B | R61: VOIE COMMUNALE 4 | S61: CR?ANCEY | T61: 21 | U61: FR | V61: 21320 | W61: 55.84 | X61: 5.94 | Y61: 0 | Z61: -42.5 | AA61: 19.29 | AB61: 3 | AC61: 46.2 | AD61: 9.9 | AE61: S,UTRA | AF61: PHARMACIE HENRI IV | AG61: PHARMACIE HENRI IV | AH61: 27 BOULEVARD HENRI IV | AI61: PARIS | AJ61: 75 | AK61: FR | AL61: 75004 | AS61: N | AT61: 20 | AU61: 20 | AV61: 30 | BB61: 0 | BC61: 0 | BD61: EUR | BE61: 46240 | BF61: 634324015 | BH61: Domestic | BI61: Your Packaging | BJ61: 0.4125 | BK61: 48 | BL61: 5.11 | BM61: 0 | BN61: -36.53 | BO61: 16.58 | BP61: EUR | BQ61: 1.1633182 | BR61: kg
A62: =BK62+BN62 -> 6.79 | B62: 3752 | D62: entreprise | E62: =IF(J62="FedEx Priority","ST","FICP") -> ST | F62: 200720433 | G62: 202606 | H62: Express | I62: UO | J62: FedEx Priority | K62: Bill_Sender_Prepaid | L62: 46301 | M62: 46332 | N62: 872886306760 | P62: HYDRATIS B2B | Q62: HYDRATIS B2B | R62: VOIE COMMUNALE 4 | S62: CR?ANCEY | T62: 21 | U62: FR | V62: 21320 | W62: 32.75 | X62: 3.87 | Y62: 0 | Z62: -24.92 | AA62: 11.7 | AB62: 2 | AC62: 14.74 | AD62: 14.74 | AE62: N,OEL | AF62: PARAPHARMACIE CARREFOUR BEGLES | AG62: PARAPHARMACIE CARREFOUR BEGLES | AH62: CHEMIN DE TARTIFUME | AI62: B?GLES | AJ62: 33 | AK62: FR | AL62: 33130 | AS62: N | AT62: 20 | AU62: 30 | AV62: 39 | BB62: 0 | BC62: 0 | BD62: EUR | BE62: 06/15/2026 | BF62: 634333759 | BH62: Domestic | BI62: Your Packaging | BJ62: 0.38402778 | BK62: 28.4 | BL62: 3.36 | BM62: 0 | BN62: -21.61 | BO62: 10.15 | BP62: EUR | BQ62: 1.1531631 | BR62: kg
A63: =BK63+BN63 -> 5.45 | B63: 3752 | D63: entreprise | E63: =IF(J63="FedEx Priority","ST","FICP") -> ST | F63: 200720433 | G63: 202606 | H63: Express | I63: UO | J63: FedEx Priority | K63: Bill_Sender_Prepaid | L63: 05/28/2026 | M63: 05/29/2026 | N63: 872284001234 | P63: HYDRATIS B2B | Q63: HYDRATIS B2B | R63: VOIE COMMUNALE 4 | S63: CR?ANCEY | T63: 21 | U63: FR | V63: 21320 | W63: 26.52 | X63: 2.82 | Y63: 0 | Z63: -20.18 | AA63: 9.16 | AB63: 1 | AC63: 6.6 | AD63: 5.06 | AE63: P,HMI | AF63: PHARMACIE DES ORGERES | AG63: PHARMACIE DES ORGERES | AH63: 6 RUE DES ROISES | AI63: BETTANCOURT-LA-FERREE | AJ63: 52 | AK63: FR | AL63: 52100 | AS63: N | AT63: 0 | AU63: 0 | AV63: 0 | BB63: 0 | BC63: 0 | BD63: EUR | BE63: 46240 | BF63: 634324015 | BH63: Domestic | BI63: Your Packaging | BJ63: 0.46736111 | BK63: 22.8 | BL63: 2.42 | BM63: 0 | BN63: -17.35 | BO63: 7.87 | BP63: EUR | BQ63: 1.1633182 | BR63: kg
A64: =BK64+BN64 -> 16.16 | B64: 3752 | D64: entreprise | E64: =IF(J64="FedEx Priority","ST","FICP") -> ST | F64: 200720433 | G64: 202606 | H64: Express | I64: UO | J64: FedEx Priority | K64: Bill_Sender_Prepaid | L64: 05/29/2026 | M64: 46059 | N64: 872381788526 | P64: HYDRATIS B2B | Q64: HYDRATIS B2B | R64: VOIE COMMUNALE 4 | S64: CR?ANCEY | T64: 21 | U64: FR | V64: 21320 | W64: 78.84 | X64: 9.34 | Y64: 0 | Z64: -60 | AA64: 28.19 | AB64: 4 | AC64: 76.34 | AD64: 20.24 | AE64: A,MELIE | AF64: PHARMACIE DAMOUR DE CLOCK | AG64: PHARMACIE DAMOUR DE CLOCK | AH64: 9 RUE JEAN JAURES | AI64: MAUREILHAN | AJ64: 34 | AK64: FR | AL64: 34370 | AS64: N | AT64: 4 | AU64: 74 | AV64: 114 | BB64: 0 | BC64: 0 | BD64: EUR | BE64: 46240 | BF64: 634324015 | BH64: Domestic | BI64: Your Packaging | BJ64: 0.43819444 | BK64: 67.6 | BL64: 8.01 | BM64: 0 | BN64: -51.44 | BO64: 24.17 | BP64: EUR | BQ64: 1.166344 | BR64: kg
A65: =BK65+BN65 -> 7.12 | B65: 3752 | D65: entreprise | E65: =IF(J65="FedEx Priority","ST","FICP") -> ST | F65: 200720433 | G65: 202606 | H65: Express | I65: UO | J65: FedEx Priority | K65: Bill_Sender_Prepaid | L65: 46028 | M65: 46059 | N65: 872384708984 | P65: HYDRATIS B2B | Q65: HYDRATIS B2B | R65: VOIE COMMUNALE 4 | S65: CR?ANCEY | T65: 21 | U65: FR | V65: 21320 | W65: 34.76 | X65: 4.13 | Y65: 0 | Z65: -26.45 | AA65: 12.43 | AB65: 1 | AC65: 16.06 | AD65: 1.54 | AE65: D,David | AF65: PARAPHARMACIE LECLERC VALENCE | AG65: PARAPHARMACIE LECLERC VALENCE | AH65: 404 AVENUE VICTOR HUGO | AI65: VALENCE | AJ65: 26 | AK65: FR | AL65: 26000 | AS65: Y | AT65: 29 | AU65: 31 | AV65: 41 | BB65: 0 | BC65: 0 | BD65: EUR | BE65: 46240 | BF65: 634324015 | BH65: Domestic | BI65: Your Packaging | BJ65: 0.41041667 | BK65: 29.8 | BL65: 3.54 | BM65: 0 | BN65: -22.68 | BO65: 10.66 | BP65: EUR | BQ65: 1.1664392 | BR65: kg
A66: =BK66+BN66 -> 7.12 | B66: 3752 | D66: entreprise | E66: =IF(J66="FedEx Priority","ST","FICP") -> ST | F66: 200720433 | G66: 202606 | H66: Express | I66: UO | J66: FedEx Priority | K66: Bill_Sender_Prepaid | L66: 05/26/2026 | M66: 05/29/2026 | N66: 872120923869 | P66: HYDRATIS B2B | Q66: HYDRATIS B2B | R66: VOIE COMMUNALE 4 | S66: CR?ANCEY | T66: 21 | U66: FR | V66: 21320 | W66: 34.59 | X66: 35.56 | Y66: 0 | Z66: -26.33 | AA66: 43.82 | AB66: 1 | AC66: 15.84 | AD66: 1.1 | AE66: L,OUIS | AF66: INTERSPORT CALVI 00214/000 | AG66: INTERSPORT CALVI 00214/000 | AH66: SAS INTERSPORT GAMMVERT | AI66: CALVI | AJ66: 20 | AK66: FR | AL66: 20260 | AS66: Y | AT66: 30 | AU66: 31 | AV66: 39 | BB66: 0 | BC66: 0 | BD66: EUR | BE66: 46240 | BF66: 634324015 | BH66: Domestic | BI66: Your Packaging | BJ66: 0.47291667 | BK66: 29.8 | BL66: 30.63 | BM66: 0 | BN66: -22.68 | BO66: 37.75 | BP66: EUR | BQ66: 1.1608335 | BR66: kg
A67: =BK67+BN67 -> 7.46 | B67: 3752 | D67: entreprise | E67: =IF(J67="FedEx Priority","ST","FICP") -> ST | F67: 200720433 | G67: 202606 | H67: Express | I67: UO | J67: FedEx Priority | K67: Bill_Sender_Prepaid | L67: 46301 | M67: 46332 | N67: 872833362880 | P67: HYDRATIS B2B | Q67: HYDRATIS B2B | R67: VOIE COMMUNALE 4 | S67: CR?ANCEY | T67: 21 | U67: FR | V67: 21320 | W67: 35.98 | X67: 4.27 | Y67: 0 | Z67: -27.38 | AA67: 12.87 | AB67: 1 | AC67: 19.8 | AD67: 19.8 | AE67: S,OPHIE | AF67: INTERSPORT DORLISHEIM 00319/000 | AG67: INTERSPORT DORLISHEIM 00319/00 | AH67: DORLISHEIM SPORT | AI67: DORLISHEIM | AJ67: 67 | AK67: FR | AL67: 67120 | AS67: N | AT67: 30 | AU67: 40 | AV67: 30 | BB67: 0 | BC67: 0 | BD67: EUR | BE67: 06/15/2026 | BF67: 634333759 | BH67: Domestic | BI67: Your Packaging | BJ67: 0.47569444 | BK67: 31.2 | BL67: 3.7 | BM67: 0 | BN67: -23.74 | BO67: 11.16 | BP67: EUR | BQ67: 1.1531631 | BR67: kg
A68: =BK68+BN68 -> 7.79 | B68: 3752 | D68: entreprise | E68: =IF(J68="FedEx Priority","ST","FICP") -> ST | F68: 200720433 | G68: 202606 | H68: Express | I68: UO | J68: FedEx Priority | K68: Bill_Sender_Prepaid | L68: 05/28/2026 | M68: 05/29/2026 | N68: 872282891437 | P68: HYDRATIS B2B | Q68: HYDRATIS B2B | R68: VOIE COMMUNALE 4 | S68: CR?ANCEY | T68: 21 | U68: FR | V68: 21320 | W68: 37.92 | X68: 4.04 | Y68: 0 | Z68: -28.86 | AA68: 13.1 | AB68: 2 | AC68: 21.34 | AD68: 3.08 | AE68: P,HAR VIELLE VILL | AF68: PHARMACIE BLOCH | AG68: PHARMACIE BLOCH | AH68: 117 GRANDE RUE | AI68: NANCY | AJ68: 54 | AK68: FR | AL68: 54000 | AS68: N | AT68: 30 | AU68: 31 | AV68: 40 | BB68: 0 | BC68: 0 | BD68: EUR | BE68: 46240 | BF68: 634324015 | BH68: Domestic | BI68: Your Packaging | BJ68: 0.53055556 | BK68: 32.6 | BL68: 3.47 | BM68: 0 | BN68: -24.81 | BO68: 11.26 | BP68: EUR | BQ68: 1.1633182 | BR68: kg
A69: =BK69+BN69 -> 17.16 | B69: 3752 | D69: entreprise | E69: =IF(J69="FedEx Priority","ST","FICP") -> ST | F69: 200720433 | G69: 202606 | H69: Express | I69: UO | J69: FedEx Priority | K69: Bill_Sender_Prepaid | L69: 46028 | M69: 46059 | N69: 872334680917 | P69: HYDRATIS B2B | Q69: HYDRATIS B2B | R69: VOIE COMMUNALE 4 | S69: CR?ANCEY | T69: 21 | U69: FR | V69: 21320 | W69: 83.75 | X69: 110.71 | Y69: 0 | Z69: -63.73 | AA69: 130.72 | AB69: 6 | AC69: 82.28 | AD69: 22.44 | AE69: L,E COROE | AF69: PHARMACIE PLERIN CENTRE | AG69: PHARMACIE PLERIN CENTRE | AH69: 23 RUE DU COMMERCE | AI69: PLERIN | AJ69: 22 | AK69: FR | AL69: 22190 | AS69: N | AT69: 0 | AU69: 0 | AV69: 0 | BB69: 0 | BC69: 0 | BD69: EUR | BE69: 46240 | BF69: 634324015 | BH69: Domestic | BI69: Your Packaging | BJ69: 0.44305556 | BK69: 71.8 | BL69: 94.91 | BM69: 0 | BN69: -54.64 | BO69: 112.07 | BP69: EUR | BQ69: 1.1664392 | BR69: kg
A70: =BK70+BN70 -> 12.81 | B70: 3752 | D70: entreprise | E70: =IF(J70="FedEx Priority","ST","FICP") -> ST | F70: 200720433 | G70: 202606 | H70: Express | I70: UO | J70: FedEx Priority | K70: Bill_Sender_Prepaid | L70: 05/28/2026 | M70: 05/29/2026 | N70: 872330626189 | P70: HYDRATIS B2B | Q70: HYDRATIS B2B | R70: VOIE COMMUNALE 4 | S70: CR?ANCEY | T70: 21 | U70: FR | V70: 21320 | W70: 62.35 | X70: 6.64 | Y70: 0 | Z70: -47.45 | AA70: 21.54 | AB70: 5 | AC70: 53.24 | AD70: 17.6 | AE70: P,Pharmahotel | AF70: PHARMACIE DE L'HOTEL DE VILLE | AG70: PHARMACIE DE L'HOTEL DE VILLE | AH70: 18 RUE DU PORT VILLIERS | AI70: CHALON-SUR-SAONE | AJ70: 71 | AK70: FR | AL70: 71100 | AS70: N | AT70: 0 | AU70: 0 | AV70: 0 | BB70: 0 | BC70: 0 | BD70: EUR | BE70: 46240 | BF70: 634324015 | BH70: Domestic | BI70: Your Packaging | BJ70: 0.36944444 | BK70: 53.6 | BL70: 5.71 | BM70: 0 | BN70: -40.79 | BO70: 18.52 | BP70: EUR | BQ70: 1.1633182 | BR70: kg
A71: =BK71+BN71 -> 9.46 | B71: 3752 | D71: entreprise | E71: =IF(J71="FedEx Priority","ST","FICP") -> ST | F71: 200720433 | G71: 202606 | H71: Express | I71: UO | J71: FedEx Priority | K71: Bill_Sender_Prepaid | L71: 46271 | M71: 46301 | N71: 872832353835 | P71: HYDRATIS B2B | Q71: HYDRATIS B2B | R71: VOIE COMMUNALE 4 | S71: CR?ANCEY | T71: 21 | U71: FR | V71: 21320 | W71: 45.64 | X71: 5.41 | Y71: 0 | Z71: -34.74 | AA71: 16.31 | AB71: 2 | AC71: 33 | AD71: 33 | AE71: F,REDE | AF71: PHARMACIE LAHET | AG71: PHARMACIE LAHET | AH71: 188 AVENUE GEORGES CLEMENCEAU | AI71: DAX | AJ71: 40 | AK71: FR | AL71: 40100 | AS71: N | AT71: 0 | AU71: 0 | AV71: 0 | BB71: 0 | BC71: 0 | BD71: EUR | BE71: 06/15/2026 | BF71: 634333759 | BH71: Domestic | BI71: Your Packaging | BJ71: 0.4625 | BK71: 39.6 | BL71: 4.69 | BM71: 0 | BN71: -30.14 | BO71: 14.15 | BP71: EUR | BQ71: 1.1526182 | BR71: kg
A72: =BK72+BN72 -> 10.13 | B72: 3752 | D72: entreprise | E72: =IF(J72="FedEx Priority","ST","FICP") -> ST | F72: 200720433 | G72: 202606 | H72: Express | I72: UO | J72: FedEx Priority | K72: Bill_Sender_Prepaid | L72: 46301 | M72: 46332 | N72: 872886845705 | P72: HYDRATIS B2B | Q72: HYDRATIS B2B | R72: VOIE COMMUNALE 4 | S72: CR?ANCEY | T72: 21 | U72: FR | V72: 21320 | W72: 48.89 | X72: 5.8 | Y72: 0 | Z72: -37.21 | AA72: 17.48 | AB72: 2 | AC72: 36.08 | AD72: 36.08 | AE72: L,UDO | AF72: PHARMACIE DE CESTAS | AG72: PHARMACIE DE CESTAS | AH72: 5 CHEM, DES BOUTIQUES | AI72: CESTAS | AJ72: 33 | AK72: FR | AL72: 33610 | AS72: N | AT72: 26 | AU72: 31 | AV72: 40 | BB72: 0 | BC72: 0 | BD72: EUR | BE72: 06/15/2026 | BF72: 634333759 | BH72: Domestic | BI72: Your Packaging | BJ72: 0.54097222 | BK72: 42.4 | BL72: 5.03 | BM72: 0 | BN72: -32.27 | BO72: 15.16 | BP72: EUR | BQ72: 1.1531631 | BR72: kg
A73: =BK73+BN73 -> 12.48 | B73: 3752 | D73: entreprise | E73: =IF(J73="FedEx Priority","ST","FICP") -> ST | F73: 200720433 | G73: 202606 | H73: Express | I73: UO | J73: FedEx Priority | K73: Bill_Sender_Prepaid | L73: 05/26/2026 | M73: 05/29/2026 | N73: 872119615527 | P73: HYDRATIS B2B | Q73: HYDRATIS B2B | R73: VOIE COMMUNALE 4 | S73: CR?ANCEY | T73: 21 | U73: FR | V73: 21320 | W73: 60.6 | X73: 6.45 | Y73: 0 | Z73: -46.11 | AA73: 20.94 | AB73: 3 | AC73: 50.82 | AD73: 9.24 | AE73: P,AULINE | AF73: INTERSPORT BIDART 04153/000 | AG73: INTERSPORT BIDART 04153/000 | AH73: CANAL BIDART SAS | AI73: BIDART | AJ73: 64 | AK73: FR | AL73: 64210 | AS73: N | AT73: 30 | AU73: 31 | AV73: 40 | BB73: 0 | BC73: 0 | BD73: EUR | BE73: 46240 | BF73: 634324015 | BH73: Domestic | BI73: Your Packaging | BJ73: 0.44097222 | BK73: 52.2 | BL73: 5.56 | BM73: 0 | BN73: -39.72 | BO73: 18.04 | BP73: EUR | BQ73: 1.1608335 | BR73: kg
A74: =BK74+BN74 -> 8.46 | B74: 3752 | D74: entreprise | E74: =IF(J74="FedEx Priority","ST","FICP") -> ST | F74: 200720433 | G74: 202606 | H74: Express | I74: UO | J74: FedEx Priority | K74: Bill_Sender_Prepaid | L74: 05/29/2026 | M74: 05/30/2026 | N74: 872382180617 | P74: HYDRATIS B2B | Q74: HYDRATIS B2B | R74: VOIE COMMUNALE 4 | S74: CR?ANCEY | T74: 21 | U74: FR | V74: 21320 | W74: 41.2 | X74: 4.39 | Y74: 0 | Z74: -31.35 | AA74: 14.23 | AB74: 2 | AC74: 26.4 | AD74: 4.4 | AE74: B,ONNEAU | AF74: PHARMACIE D'O | AG74: PHARMACIE D'O | AH74: 3BIS RUE BEAUPUY | AI74: MUSSIDAN | AJ74: 24 | AK74: FR | AL74: 24400 | AS74: N | AT74: 0 | AU74: 0 | AV74: 0 | BB74: 0 | BC74: 0 | BD74: EUR | BE74: 46240 | BF74: 634324015 | BH74: Domestic | BI74: Your Packaging | BJ74: 0.38333333 | BK74: 35.4 | BL74: 3.77 | BM74: 0 | BN74: -26.94 | BO74: 12.23 | BP74: EUR | BQ74: 1.1637244 | BR74: kg
A75: =BK75+BN75 -> 10.47 | B75: 3752 | D75: entreprise | E75: =IF(J75="FedEx Priority","ST","FICP") -> ST | F75: 200720433 | G75: 202606 | H75: Express | I75: UO | J75: FedEx Priority | K75: Bill_Sender_Prepaid | L75: 46028 | M75: 46059 | N75: 872384256456 | P75: HYDRATIS B2B | Q75: HYDRATIS B2B | R75: VOIE COMMUNALE 4 | S75: CR?ANCEY | T75: 21 | U75: FR | V75: 21320 | W75: 51.09 | X75: 6.05 | Y75: 0 | Z75: -38.88 | AA75: 18.27 | AB75: 2 | AC75: 39.6 | AD75: 5.28 | AE75: M,ARIE | AF75: LA PHARMACIE DES ALLEES | AG75: LA PHARMACIE DES ALLEES | AH75: 59 ALLEE D ALBRET | AI75: NERAC | AJ75: 47 | AK75: FR | AL75: 47600 | AS75: N | AT75: 30 | AU75: 30 | AV75: 40 | BB75: 0 | BC75: 0 | BD75: EUR | BE75: 46240 | BF75: 634324015 | BH75: Domestic | BI75: Your Packaging | BJ75: 0.39097222 | BK75: 43.8 | BL75: 5.19 | BM75: 0 | BN75: -33.33 | BO75: 15.66 | BP75: EUR | BQ75: 1.1664392 | BR75: kg
A76: =BK76+BN76 -> 8.46 | B76: 3752 | D76: entreprise | E76: =IF(J76="FedEx Priority","ST","FICP") -> ST | F76: 200720433 | G76: 202606 | H76: Express | I76: UO | J76: FedEx Priority | K76: Bill_Sender_Prepaid | L76: 46028 | M76: 46059 | N76: 872387546886 | P76: HYDRATIS B2B | Q76: HYDRATIS B2B | R76: VOIE COMMUNALE 4 | S76: CR?ANCEY | T76: 21 | U76: FR | V76: 21320 | W76: 41.29 | X76: 4.9 | Y76: 0 | Z76: -31.42 | AA76: 14.77 | AB76: 2 | AC76: 26.4 | AD76: 3.08 | AE76: L,Lah | AF76: PHARMACIE CLEMENCEAU | AG76: PHARMACIE CLEMENCEAU | AH76: 10 RUE GEORGES CLEMENCEAU | AI76: LIMAY | AJ76: 78 | AK76: FR | AL76: 78520 | AS76: N | AT76: 0 | AU76: 0 | AV76: 0 | BB76: 0 | BC76: 0 | BD76: EUR | BE76: 46240 | BF76: 634324015 | BH76: Domestic | BI76: Your Packaging | BJ76: 0.51319444 | BK76: 35.4 | BL76: 4.2 | BM76: 0 | BN76: -26.94 | BO76: 12.66 | BP76: EUR | BQ76: 1.1664392 | BR76: kg
A77: =BK77+BN77 -> 14.82 | B77: 3752 | D77: entreprise | E77: =IF(J77="FedEx Priority","ST","FICP") -> ST | F77: 200720433 | G77: 202606 | H77: Express | I77: UO | J77: FedEx Priority | K77: Bill_Sender_Prepaid | L77: 46028 | M77: 46059 | N77: 872285468507 | P77: HYDRATIS B2B | Q77: HYDRATIS B2B | R77: VOIE COMMUNALE 4 | S77: CR?ANCEY | T77: 21 | U77: FR | V77: 21320 | W77: 72.32 | X77: 8.56 | Y77: 0 | Z77: -55.03 | AA77: 25.85 | AB77: 5 | AC77: 67.98 | AD77: 20.9 | AE77: T,HBAULT | AF77: PHARMACIE THIEBAULTHARDY | AG77: PHARMACIE THIEBAULTHARDY | AH77: 46 RUE GEORGES CLEMENCEAU | AI77: ETREPAGNY | AJ77: 27 | AK77: FR | AL77: 27150 | AS77: N | AT77: 0 | AU77: 0 | AV77: 0 | BB77: 0 | BC77: 0 | BD77: EUR | BE77: 46240 | BF77: 634324015 | BH77: Domestic | BI77: Your Packaging | BJ77: 0.47013889 | BK77: 62 | BL77: 7.34 | BM77: 0 | BN77: -47.18 | BO77: 22.16 | BP77: EUR | BQ77: 1.1664392 | BR77: kg
A78: =BK78+BN78 -> 13.81 | B78: 3752 | D78: entreprise | E78: =IF(J78="FedEx Priority","ST","FICP") -> ST | F78: 200720433 | G78: 202606 | H78: Express | I78: UO | J78: FedEx Priority | K78: Bill_Sender_Prepaid | L78: 05/27/2026 | M78: 46028 | N78: 872279736607 | P78: HYDRATIS B2B | Q78: HYDRATIS B2B | R78: VOIE COMMUNALE 4 | S78: CR?ANCEY | T78: 21 | U78: FR | V78: 21320 | W78: 67.29 | X78: 7.16 | Y78: 0 | Z78: -51.22 | AA78: 23.24 | AB78: 4 | AC78: 60.28 | AD78: 14.96 | AE78: G,UILLAUMM | AF78: PARAPHARMACIE CARREFOUR BREST | AG78: PARAPHARMACIE CARREFOUR BREST | AH78: 126 BOULEVARD DE PLYMOUTH | AI78: BREST | AJ78: 29 | AK78: FR | AL78: 29200 | AS78: N | AT78: 30 | AU78: 31 | AV78: 40 | BB78: 0 | BC78: 0 | BD78: EUR | BE78: 46240 | BF78: 634324015 | BH78: Domestic | BI78: Your Packaging | BJ78: 0.37916667 | BK78: 57.8 | BL78: 6.15 | BM78: 0 | BN78: -43.99 | BO78: 19.96 | BP78: EUR | BQ78: 1.1642528 | BR78: kg
A79: =BK79+BN79 -> 12.81 | B79: 3752 | D79: entreprise | E79: =IF(J79="FedEx Priority","ST","FICP") -> ST | F79: 200720433 | G79: 202606 | H79: Express | I79: UO | J79: FedEx Priority | K79: Bill_Sender_Prepaid | L79: 05/27/2026 | M79: 05/29/2026 | N79: 872273644453 | P79: HYDRATIS B2B | Q79: HYDRATIS B2B | R79: VOIE COMMUNALE 4 | S79: CR?ANCEY | T79: 21 | U79: FR | V79: 21320 | W79: 62.4 | X79: 6.65 | Y79: 0 | Z79: -47.49 | AA79: 21.56 | AB79: 3 | AC79: 54.12 | AD79: 6.6 | AE79: K,EROUEDAN | AF79: PHARMACIE KEROUEDAN | AG79: PHARMACIE KEROUEDAN | AH79: 7 RUE DU GENERAL LAMBERT | AI79: CARHAIX-PLOUGUER | AJ79: 29 | AK79: FR | AL79: 29270 | AS79: N | AT79: 31 | AU79: 31 | AV79: 40 | BB79: 0 | BC79: 0 | BD79: EUR | BE79: 46240 | BF79: 634324015 | BH79: Domestic | BI79: Your Packaging | BJ79: 0.50625 | BK79: 53.6 | BL79: 5.71 | BM79: 0 | BN79: -40.79 | BO79: 18.52 | BP79: EUR | BQ79: 1.1642528 | BR79: kg
A80: =BK80+BN80 -> 8.8 | B80: 3752 | D80: entreprise | E80: =IF(J80="FedEx Priority","ST","FICP") -> ST | F80: 200720433 | G80: 202606 | H80: Express | I80: UO | J80: FedEx Priority | K80: Bill_Sender_Prepaid | L80: 05/28/2026 | M80: 05/29/2026 | N80: 872331560270 | P80: HYDRATIS B2B | Q80: HYDRATIS B2B | R80: VOIE COMMUNALE 4 | S80: CR?ANCEY | T80: 21 | U80: FR | V80: 21320 | W80: 42.83 | X80: 4.56 | Y80: 0 | Z80: -32.58 | AA80: 14.8 | AB80: 3 | AC80: 27.72 | AD80: 10.56 | AE80: M,Marie | AF80: PHARMACIE DE L ANGE | AG80: PHARMACIE DE L ANGE | AH80: 1 RUE GRIESMATT | AI80: MARLENHEIM | AJ80: 67 | AK80: FR | AL80: 67520 | AS80: N | AT80: 0 | AU80: 0 | AV80: 0 | BB80: 0 | BC80: 0 | BD80: EUR | BE80: 46240 | BF80: 634324015 | BH80: Domestic | BI80: Your Packaging | BJ80: 0.46597222 | BK80: 36.8 | BL80: 3.92 | BM80: 0 | BN80: -28 | BO80: 12.72 | BP80: EUR | BQ80: 1.1637244 | BR80: kg
A81: =BK81+BN81 -> 11.81 | B81: 3752 | D81: entreprise | E81: =IF(J81="FedEx Priority","ST","FICP") -> ST | F81: 200720433 | G81: 202606 | H81: Express | I81: UO | J81: FedEx Priority | K81: Bill_Sender_Prepaid | L81: 05/28/2026 | M81: 05/29/2026 | N81: 872332010646 | P81: HYDRATIS B2B | Q81: HYDRATIS B2B | R81: VOIE COMMUNALE 4 | S81: CR?ANCEY | T81: 21 | U81: FR | V81: 21320 | W81: 57.47 | X81: 6.13 | Y81: 0 | Z81: -43.73 | AA81: 19.87 | AB81: 3 | AC81: 48.4 | AD81: 11.22 | AE81: L,Lamero | AF81: PHARMACIE HAUSSMANN LABORDE | AG81: PHARMACIE HAUSSMANN LABORDE | AH81: 130 BOULEVARD HAUSSMANN | AI81: PARIS 08 | AJ81: 75 | AK81: FR | AL81: 75008 | AS81: N | AT81: 0 | AU81: 0 | AV81: 0 | BB81: 0 | BC81: 0 | BD81: EUR | BE81: 46240 | BF81: 634324015 | BH81: Domestic | BI81: Your Packaging | BJ81: 0.49166667 | BK81: 49.4 | BL81: 5.27 | BM81: 0 | BN81: -37.59 | BO81: 17.08 | BP81: EUR | BQ81: 1.1633182 | BR81: kg
A82: =BK82+BN82 -> 9.13 | B82: 3752 | D82: entreprise | E82: =IF(J82="FedEx Priority","ST","FICP") -> ST | F82: 200720433 | G82: 202606 | H82: Express | I82: UO | J82: FedEx Priority | K82: Bill_Sender_Prepaid | L82: 46148 | M82: 46240 | N82: 872690522195 | P82: HYDRATIS B2B | Q82: HYDRATIS B2B | R82: VOIE COMMUNALE 4 | S82: CR?ANCEY | T82: 21 | U82: FR | V82: 21320 | W82: 44.36 | X82: 5.26 | Y82: 0 | Z82: -33.76 | AA82: 15.86 | AB82: 2 | AC82: 30.8 | AD82: 30.8 | AE82: K,EVIN | AF82: PARAPHARMACIE LECLERC SOUTERRAINE | AG82: PARAPHARMACIE LECLERC SOUTERRA | AH82: AVENUE JEAN JAURES | AI82: LA SOUTERRAINE | AJ82: 23 | AK82: FR | AL82: 23300 | AS82: N | AT82: 0 | AU82: 0 | AV82: 0 | BB82: 0 | BC82: 0 | BD82: EUR | BE82: 06/15/2026 | BF82: 634333759 | BH82: Domestic | BI82: Your Packaging | BJ82: 0.44722222 | BK82: 38.2 | BL82: 4.53 | BM82: 0 | BN82: -29.07 | BO82: 13.66 | BP82: EUR | BQ82: 1.1612109 | BR82: kg
A83: =BK83+BN83 -> 8.46 | B83: 3752 | D83: entreprise | E83: =IF(J83="FedEx Priority","ST","FICP") -> ST | F83: 200720433 | G83: 202606 | H83: Express | I83: UO | J83: FedEx Priority | K83: Bill_Sender_Prepaid | L83: 46148 | M83: 46240 | N83: 872686627278 | P83: HYDRATIS B2B | Q83: HYDRATIS B2B | R83: VOIE COMMUNALE 4 | S83: CR?ANCEY | T83: 21 | U83: FR | V83: 21320 | W83: 41.11 | X83: 4.88 | Y83: 0 | Z83: -31.28 | AA83: 14.7 | AB83: 2 | AC83: 26.4 | AD83: 26.4 | AE83: A,UCHAN | AF83: PARAPHARMACIE AUCHAN MANDELIEU | AG83: PARAPHARMACIE AUCHAN MANDELIEU | AH83: 791 AVENUE DE FREJUS | AI83: MANDELIEU-LA-NAPOULE | AJ83: 6 | AK83: FR | AL83: 6210 | AS83: N | AT83: 0 | AU83: 0 | AV83: 0 | BB83: 0 | BC83: 0 | BD83: EUR | BE83: 06/15/2026 | BF83: 634333759 | BH83: Domestic | BI83: Your Packaging | BJ83: 0.5125 | BK83: 35.4 | BL83: 4.2 | BM83: 0 | BN83: -26.94 | BO83: 12.66 | BP83: EUR | BQ83: 1.1612109 | BR83: kg
A84: =BK84+BN84 -> 7.46 | B84: 3752 | D84: entreprise | E84: =IF(J84="FedEx Priority","ST","FICP") -> ST | F84: 200720433 | G84: 202606 | H84: Express | I84: UO | J84: FedEx Priority | K84: Bill_Sender_Prepaid | L84: 05/29/2026 | M84: 46028 | N84: 872385657232 | P84: HYDRATIS B2B | Q84: HYDRATIS B2B | R84: VOIE COMMUNALE 4 | S84: CR?ANCEY | T84: 21 | U84: FR | V84: 21320 | W84: 36.31 | X84: 3.88 | Y84: 0 | Z84: -27.63 | AA84: 12.56 | AB84: 1 | AC84: 19.8 | AD84: 1.1 | AE84: H,H | AF84: PHARMACIE DES CANADIENS | AG84: PHARMACIE DES CANADIENS | AH84: 4 RUE DES RESERVOIRS | AI84: ST MAURICE | AJ84: 94 | AK84: FR | AL84: 94410 | AS84: N | AT84: 30 | AU84: 31 | AV84: 40 | BB84: 0 | BC84: 0 | BD84: EUR | BE84: 46240 | BF84: 634324015 | BH84: Domestic | BI84: Your Packaging | BJ84: 0.49513889 | BK84: 31.2 | BL84: 3.33 | BM84: 0 | BN84: -23.74 | BO84: 10.79 | BP84: EUR | BQ84: 1.1637244 | BR84: kg
A85: =BK85+BN85 -> 19.5 | B85: 3752 | E85: =IF(J85="FedEx Priority","ST","FICP") -> ST | F85: 200720433 | G85: 202606 | H85: Express | I85: UO | J85: FedEx Priority | K85: Bill_Sender_Prepaid | L85: 46087 | M85: 46118 | N85: 872531656194 | P85: HYDRATIS B2B | Q85: HYDRATIS B2B | R85: VOIE COMMUNALE 4 | S85: CR?ANCEY | T85: 21 | U85: FR | V85: 21320 | W85: 94.99 | X85: 11.26 | Y85: 0 | Z85: -72.29 | AA85: 33.96 | AB85: 5 | AC85: 99 | AD85: 25.3 | AE85: P,HARM VALLEE | AF85: GRANDE PHARMACIE DE LA VALLEE | AG85: GRANDE PHARMACIE DE LA VALLEE | AH85: CCIAL 125 RN 7 | AI85: SALAISE SUR SANNE | AJ85: 38 | AK85: FR | AL85: 38150 | AS85: N | AT85: 0 | AU85: 0 | AV85: 0 | BB85: 0 | BC85: 0 | BD85: EUR | BE85: 46240 | BF85: 634324015 | BH85: Domestic | BI85: Your Packaging | BJ85: 0.41666667 | BK85: 81.6 | BL85: 9.67 | BM85: 0 | BN85: -62.1 | BO85: 29.17 | BP85: EUR | BQ85: 1.1640901 | BR85: kg
A86: =BK86+BN86 -> 7.46 | B86: 3752 | D86: entreprise | E86: =IF(J86="FedEx Priority","ST","FICP") -> ST | F86: 200720433 | G86: 202606 | H86: Express | I86: UO | J86: FedEx Priority | K86: Bill_Sender_Prepaid | L86: 46028 | M86: 46059 | N86: 872387755853 | P86: HYDRATIS B2B | Q86: HYDRATIS B2B | R86: VOIE COMMUNALE 4 | S86: CR?ANCEY | T86: 21 | U86: FR | V86: 21320 | W86: 36.39 | X86: 4.32 | Y86: 0 | Z86: -27.69 | AA86: 13.02 | AB86: 2 | AC86: 19.8 | AD86: 6.16 | AE86: B,ANDED | AF86: PHARMACIE BANDEL | AG86: PHARMACIE BANDEL | AH86: 37 BOULEVARD JOSEPH ROSSELLI | AI86: BELLEVILLE-EN-BEAUJOLAIS | AJ86: 69 | AK86: FR | AL86: 69220 | AS86: N | AT86: 30 | AU86: 31 | AV86: 38 | BB86: 0 | BC86: 0 | BD86: EUR | BE86: 46240 | BF86: 634324015 | BH86: Domestic | BI86: Your Packaging | BJ86: 0.43125 | BK86: 31.2 | BL86: 3.7 | BM86: 0 | BN86: -23.74 | BO86: 11.16 | BP86: EUR | BQ86: 1.1664392 | BR86: kg
A87: =BK87+BN87 -> 14.15 | B87: 3752 | E87: =IF(J87="FedEx Priority","ST","FICP") -> ST | F87: 200720433 | G87: 202606 | H87: Express | I87: UO | J87: FedEx Priority | K87: Bill_Sender_Prepaid | L87: 46059 | M87: 46087 | N87: 872526339301 | P87: HYDRATIS B2B | Q87: HYDRATIS B2B | R87: VOIE COMMUNALE 4 | S87: CR?ANCEY | T87: 21 | U87: FR | V87: 21320 | W87: 69.05 | X87: 8.19 | Y87: 0 | Z87: -52.54 | AA87: 24.69 | AB87: 4 | AC87: 63.58 | AD87: 16.72 | AE87: M,Ma | AF87: PHARMACIE DE L HOMME DE FER | AG87: PHARMACIE DE L HOMME DE FER | AH87: 2 PLACE DE L'HOMME DE FER | AI87: STRASBOURG | AJ87: 67 | AK87: FR | AL87: 67000 | AS87: N | AT87: 30 | AU87: 32 | AV87: 39 | BB87: 0 | BC87: 0 | BD87: EUR | BE87: 46240 | BF87: 634324015 | BH87: Domestic | BI87: Your Packaging | BJ87: 0.47430556 | BK87: 59.2 | BL87: 7.02 | BM87: 0 | BN87: -45.05 | BO87: 21.17 | BP87: EUR | BQ87: 1.166344 | BR87: kg
A88: =BK88+BN88 -> 16.49 | B88: 3752 | D88: entreprise | E88: =IF(J88="FedEx Priority","ST","FICP") -> ST | F88: 200720433 | G88: 202606 | H88: Express | I88: UO | J88: FedEx Priority | K88: Bill_Sender_Prepaid | L88: 46028 | M88: 46059 | N88: 872338961444 | P88: HYDRATIS B2B | Q88: HYDRATIS B2B | R88: VOIE COMMUNALE 4 | S88: CR?ANCEY | T88: 21 | U88: FR | V88: 21320 | W88: 80.48 | X88: 9.53 | Y88: 0 | Z88: -61.25 | AA88: 28.76 | AB88: 4 | AC88: 77.66 | AD88: 14.96 | AE88: M,Sarah | AF88: COSMOPHARMA | AG88: COSMOPHARMA | AH88: 42 RUE DU MOULIN A HUILE | AI88: SAINT-ANDR?-DE-SANGONIS | AJ88: 34 | AK88: FR | AL88: 34725 | AS88: N | AT88: 5 | AU88: 74 | AV88: 113 | BB88: 0 | BC88: 0 | BD88: EUR | BE88: 46240 | BF88: 634324015 | BH88: Domestic | BI88: Your Packaging | BJ88: 0.3875 | BK88: 69 | BL88: 8.17 | BM88: 0 | BN88: -52.51 | BO88: 24.66 | BP88: EUR | BQ88: 1.1664392 | BR88: kg
A89: =BK89+BN89 -> 14.48 | B89: 3752 | D89: entreprise | E89: =IF(J89="FedEx Priority","ST","FICP") -> ST | F89: 200720433 | G89: 202606 | H89: Express | I89: UO | J89: FedEx Priority | K89: Bill_Sender_Prepaid | L89: 46028 | M89: 46118 | N89: 872381766050 | P89: HYDRATIS B2B | Q89: HYDRATIS B2B | R89: VOIE COMMUNALE 4 | S89: CR?ANCEY | T89: 21 | U89: FR | V89: 21320 | W89: 70.69 | X89: 57.62 | Y89: 0 | Z89: -53.8 | AA89: 74.51 | AB89: 4 | AC89: 65.34 | AD89: 14.96 | AE89: P,HARMACIE FRANC | AF89: PHARMACIE FRANCESCHINI | AG89: PHARMACIE FRANCESCHINI | AH89: IMMEUBLE LES ARCADES | AI89: SAINT-FLORENT | AJ89: 20 | AK89: FR | AL89: 20217 | AS89: N | AT89: 0 | AU89: 0 | AV89: 0 | BB89: 0 | BC89: 0 | BD89: EUR | BE89: 46240 | BF89: 634324015 | BH89: Domestic | BI89: Your Packaging | BJ89: 0.37986111 | BK89: 60.6 | BL89: 49.4 | BM89: 0 | BN89: -46.12 | BO89: 63.88 | BP89: EUR | BQ89: 1.1664392 | BR89: kg
A90: =BK90+BN90 -> 9.13 | B90: 3752 | E90: =IF(J90="FedEx Priority","ST","FICP") -> ST | F90: 200720433 | G90: 202606 | H90: Express | I90: UO | J90: FedEx Priority | K90: Bill_Sender_Prepaid | L90: 46087 | M90: 46118 | N90: 872533619479 | P90: HYDRATIS B2B | Q90: HYDRATIS B2B | R90: VOIE COMMUNALE 4 | S90: CR?ANCEY | T90: 21 | U90: FR | V90: 21320 | W90: 44.47 | X90: 5.27 | Y90: 0 | Z90: -33.84 | AA90: 15.9 | AB90: 2 | AC90: 30.8 | AD90: 3.96 | AE90: M,AILLIART | AF90: PHARMACIE MAILLIART | AG90: PHARMACIE MAILLIART | AH90: 8 RUE DE LA REPUBLIQUE | AI90: MAMERS | AJ90: 72 | AK90: FR | AL90: 72600 | AS90: N | AT90: 0 | AU90: 0 | AV90: 0 | BB90: 0 | BC90: 0 | BD90: EUR | BE90: 46240 | BF90: 634324015 | BH90: Domestic | BI90: Your Packaging | BJ90: 0.43194444 | BK90: 38.2 | BL90: 4.53 | BM90: 0 | BN90: -29.07 | BO90: 13.66 | BP90: EUR | BQ90: 1.1640901 | BR90: kg
A91: =BK91+BN91 -> 6.79 | B91: 3752 | D91: entreprise | E91: =IF(J91="FedEx Priority","ST","FICP") -> ST | F91: 200720433 | G91: 202606 | H91: Express | I91: UO | J91: FedEx Priority | K91: Bill_Sender_Prepaid | L91: 46028 | M91: 46059 | N91: 872386967797 | P91: HYDRATIS B2B | Q91: HYDRATIS B2B | R91: VOIE COMMUNALE 4 | S91: CR?ANCEY | T91: 21 | U91: FR | V91: 21320 | W91: 33.13 | X91: 3.92 | Y91: 0 | Z91: -25.21 | AA91: 11.84 | AB91: 1 | AC91: 15.4 | AD91: 1.54 | AE91: M,ATHIAS | AF91: PARAPHARMACIE LECLERC LEGENDRE | AG91: PARAPHARMACIE LECLERC LEGENDRE | AH91: LEGENDRE MAILODIS | AI91: GELLAINVILLE | AJ91: 28 | AK91: FR | AL91: 28630 | AS91: N | AT91: 0 | AU91: 0 | AV91: 0 | BB91: 0 | BC91: 0 | BD91: EUR | BE91: 46240 | BF91: 634324015 | BH91: Domestic | BI91: Your Packaging | BJ91: 0.41180556 | BK91: 28.4 | BL91: 3.36 | BM91: 0 | BN91: -21.61 | BO91: 10.15 | BP91: EUR | BQ91: 1.1664392 | BR91: kg
A92: =BK92+BN92 -> 8.8 | B92: 3752 | D92: entreprise | E92: =IF(J92="FedEx Priority","ST","FICP") -> ST | F92: 200720433 | G92: 202606 | H92: Express | I92: UO | J92: FedEx Priority | K92: Bill_Sender_Prepaid | L92: 46028 | M92: 46059 | N92: 872389249412 | P92: HYDRATIS B2B | Q92: HYDRATIS B2B | R92: VOIE COMMUNALE 4 | S92: CR?ANCEY | T92: 21 | U92: FR | V92: 21320 | W92: 42.92 | X92: 5.09 | Y92: 0 | Z92: -32.66 | AA92: 15.35 | AB92: 3 | AC92: 28.6 | AD92: 5.94 | AE92: B,Pharmacie | AF92: GRANDE PHARMACIE BEAUNOISE | AG92: GRANDE PHARMACIE BEAUNOISE | AH92: 125 ROUTE DE DIJON | AI92: BEAUNE | AJ92: 21 | AK92: FR | AL92: 21200 | AS92: N | AT92: 0 | AU92: 0 | AV92: 0 | BB92: 0 | BC92: 0 | BD92: EUR | BE92: 46240 | BF92: 634324015 | BH92: Domestic | BI92: Your Packaging | BJ92: 0.45902778 | BK92: 36.8 | BL92: 4.36 | BM92: 0 | BN92: -28 | BO92: 13.16 | BP92: EUR | BQ92: 1.1664392 | BR92: kg
A93: =BK93+BN93 -> 9.8 | B93: 3752 | D93: entreprise | E93: =IF(J93="FedEx Priority","ST","FICP") -> ST | F93: 200720433 | G93: 202606 | H93: Express | I93: UO | J93: FedEx Priority | K93: Bill_Sender_Prepaid | L93: 05/28/2026 | M93: 05/29/2026 | N93: 872331863829 | P93: HYDRATIS B2B | Q93: HYDRATIS B2B | R93: VOIE COMMUNALE 4 | S93: CR?ANCEY | T93: 21 | U93: FR | V93: 21320 | W93: 47.7 | X93: 5.07 | Y93: 0 | Z93: -36.3 | AA93: 16.47 | AB93: 2 | AC93: 35.2 | AD93: 4.4 | AE93: P,HARMACIA | AF93: PHARMACIE DES JARDINS DE BONNEVILLE | AG93: PHARMACIE DES JARDINS DE BONNE | AH93: ROUTE DE PONTOISE | AI93: MERY-SUR-OISE | AJ93: 95 | AK93: FR | AL93: 95540 | AS93: N | AT93: 30 | AU93: 30 | AV93: 39 | BB93: 0 | BC93: 0 | BD93: EUR | BE93: 46240 | BF93: 634324015 | BH93: Domestic | BI93: Your Packaging | BJ93: 0.44583333 | BK93: 41 | BL93: 4.36 | BM93: 0 | BN93: -31.2 | BO93: 14.16 | BP93: EUR | BQ93: 1.1633182 | BR93: kg
A94: =BK94+BN94 -> 8.13 | B94: 3752 | D94: entreprise | E94: =IF(J94="FedEx Priority","ST","FICP") -> ST | F94: 200720433 | G94: 202606 | H94: Express | I94: UO | J94: FedEx Priority | K94: Bill_Sender_Prepaid | L94: 46028 | M94: 46059 | N94: 872389303917 | P94: HYDRATIS B2B | Q94: HYDRATIS B2B | R94: VOIE COMMUNALE 4 | S94: CR?ANCEY | T94: 21 | U94: FR | V94: 21320 | W94: 39.66 | X94: 4.7 | Y94: 0 | Z94: -30.18 | AA94: 14.18 | AB94: 2 | AC94: 22.22 | AD94: 4.84 | AE94: P,Phcontoy | AF94: PHARMACIE DU CONTOY | AG94: PHARMACIE DU CONTOY | AH94: RUE DU MILLENAIRE | AI94: HARLY | AJ94: 2 | AK94: FR | AL94: 2100 | AS94: N | AT94: 0 | AU94: 0 | AV94: 0 | BB94: 0 | BC94: 0 | BD94: EUR | BE94: 46240 | BF94: 634324015 | BH94: Domestic | BI94: Your Packaging | BJ94: 0.44930556 | BK94: 34 | BL94: 4.03 | BM94: 0 | BN94: -25.87 | BO94: 12.16 | BP94: EUR | BQ94: 1.1664392 | BR94: kg
A95: =BK95+BN95 -> 22.85 | B95: 3752 | E95: =IF(J95="FedEx Priority","ST","FICP") -> ST | F95: 200720433 | G95: 202606 | H95: Express | I95: UO | J95: FedEx Priority | K95: Bill_Sender_Prepaid | L95: 46059 | M95: 46087 | N95: 872528858943 | P95: HYDRATIS B2B | Q95: HYDRATIS B2B | R95: VOIE COMMUNALE 4 | S95: CR?ANCEY | T95: 21 | U95: FR | V95: 21320 | W95: 111.5 | X95: 113.99 | Y95: 0 | Z95: -84.85 | AA95: 140.64 | AB95: 8 | AC95: 119.9 | AD95: 44 | AE95: D,Valentini | AF95: PHARMACIE DE NAVENNE | AG95: PHARMACIE DE NAVENNE | AH95: 25 TER RUE PIERRE CURIE | AI95: NAVENNE | AJ95: 70 | AK95: FR | AL95: 70000 | AS95: N | AT95: 30 | AU95: 31 | AV95: 40 | BB95: 0 | BC95: 0 | BD95: EUR | BE95: 46240 | BF95: 634324015 | BH95: Domestic | BI95: Your Packaging | BJ95: 0.39027778 | BK95: 95.6 | BL95: 97.73 | BM95: 0 | BN95: -72.75 | BO95: 120.58 | BP95: EUR | BQ95: 1.166344 | BR95: kg
A96: =BK96+BN96 -> 8.46 | B96: 3752 | D96: entreprise | E96: =IF(J96="FedEx Priority","ST","FICP") -> ST | F96: 200720433 | G96: 202606 | H96: Express | I96: UO | J96: FedEx Priority | K96: Bill_Sender_Prepaid | L96: 05/28/2026 | M96: 05/29/2026 | N96: 872284582610 | P96: HYDRATIS B2B | Q96: HYDRATIS B2B | R96: VOIE COMMUNALE 4 | S96: CR?ANCEY | T96: 21 | U96: FR | V96: 21320 | W96: 41.18 | X96: 4.39 | Y96: 0 | Z96: -31.34 | AA96: 14.23 | AB96: 2 | AC96: 26.4 | AD96: 3.08 | AE96: M,Marine | AF96: PHARMACIE DU MARCHE | AG96: PHARMACIE DU MARCHE | AH96: ROUTE DE PONTIVY | AI96: BAUD | AJ96: 56 | AK96: FR | AL96: 56150 | AS96: N | AT96: 0 | AU96: 0 | AV96: 0 | BB96: 0 | BC96: 0 | BD96: EUR | BE96: 46240 | BF96: 634324015 | BH96: Domestic | BI96: Your Packaging | BJ96: 0.52986111 | BK96: 35.4 | BL96: 3.77 | BM96: 0 | BN96: -26.94 | BO96: 12.23 | BP96: EUR | BQ96: 1.1633182 | BR96: kg
A97: =BK97+BN97 -> 27.87 | B97: 3752 | D97: entreprise | E97: =IF(J97="FedEx Priority","ST","FICP") -> ST | F97: 200720433 | G97: 202606 | H97: Express | I97: UO | J97: FedEx Priority | K97: Bill_Sender_Prepaid | L97: 46059 | M97: 46087 | N97: 872387242974 | P97: HYDRATIS B2B | Q97: HYDRATIS B2B | R97: VOIE COMMUNALE 4 | S97: CR?ANCEY | T97: 21 | U97: FR | V97: 21320 | W97: 136 | X97: 116.89 | Y97: 0 | Z97: -103.49 | AA97: 149.4 | AB97: 9 | AC97: 154 | AD97: 83.16 | AE97: H,ALLES | AF97: GRANDE PHARMACIE DES HALLES | AG97: GRANDE PHARMACIE DES HALLES | AH97: 97 RUE MASSENA | AI97: LILLE | AJ97: 59 | AK97: FR | AL97: 59800 | AS97: N | AT97: 20 | AU97: 30 | AV97: 39 | BB97: 0 | BC97: 0 | BD97: EUR | BE97: 46240 | BF97: 634324015 | BH97: Domestic | BI97: Your Packaging | BJ97: 0.51875 | BK97: 116.6 | BL97: 100.22 | BM97: 0 | BN97: -88.73 | BO97: 128.09 | BP97: EUR | BQ97: 1.166344 | BR97: kg
A98: =BK98+BN98 -> 7.12 | B98: 3752 | D98: entreprise | E98: =IF(J98="FedEx Priority","ST","FICP") -> ST | F98: 200720433 | G98: 202606 | H98: Express | I98: UO | J98: FedEx Priority | K98: Bill_Sender_Prepaid | L98: 46059 | M98: 46087 | N98: 872391594696 | P98: HYDRATIS B2B | Q98: HYDRATIS B2B | R98: VOIE COMMUNALE 4 | S98: CR?ANCEY | T98: 21 | U98: FR | V98: 21320 | W98: 34.76 | X98: 4.13 | Y98: 0 | Z98: -26.45 | AA98: 12.43 | AB98: 1 | AC98: 17.6 | AD98: 1.32 | AE98: A,Lambert | AF98: INTERSPORT SARREGUEMINES | AG98: INTERSPORT SARREGUEMINES | AH98: SGM SPORT SAS | AI98: SARREGUEMINES | AJ98: 57 | AK98: FR | AL98: 57200 | AS98: N | AT98: 30 | AU98: 30 | AV98: 39 | BB98: 0 | BC98: 0 | BD98: EUR | BE98: 46240 | BF98: 634324015 | BH98: Domestic | BI98: Your Packaging | BJ98: 0.44930556 | BK98: 29.8 | BL98: 3.54 | BM98: 0 | BN98: -22.68 | BO98: 10.66 | BP98: EUR | BQ98: 1.166344 | BR98: kg
A99: =BK99+BN99 -> 10.8 | B99: 3752 | D99: entreprise | E99: =IF(J99="FedEx Priority","ST","FICP") -> ST | F99: 200720433 | G99: 202606 | H99: Express | I99: UO | J99: FedEx Priority | K99: Bill_Sender_Prepaid | L99: 05/26/2026 | M99: 05/29/2026 | N99: 872120235830 | P99: HYDRATIS B2B | Q99: HYDRATIS B2B | R99: VOIE COMMUNALE 4 | S99: CR?ANCEY | T99: 21 | U99: FR | V99: 21320 | W99: 52.47 | X99: 5.58 | Y99: 0 | Z99: -39.93 | AA99: 18.12 | AB99: 3 | AC99: 41.14 | AD99: 9.24 | AE99: S,OLANGE | AF99: INTERSPORT URRUGNE 00771/000 | AG99: INTERSPORT URRUGNE 00771/000 | AH99: DONIBANE SPORT SAS | AI99: URRUGNE | AJ99: 64 | AK99: FR | AL99: 64122 | AS99: N | AT99: 30 | AU99: 31 | AV99: 40 | BB99: 0 | BC99: 0 | BD99: EUR | BE99: 46240 | BF99: 634324015 | BH99: Domestic | BI99: Your Packaging | BJ99: 0.41666667 | BK99: 45.2 | BL99: 4.81 | BM99: 0 | BN99: -34.4 | BO99: 15.61 | BP99: EUR | BQ99: 1.1608335 | BR99: kg
A100: =BK100+BN100 -> 9.46 | B100: 3752 | D100: entreprise | E100: =IF(J100="FedEx Priority","ST","FICP") -> ST | F100: 200720433 | G100: 202606 | H100: Express | I100: UO | J100: FedEx Priority | K100: Bill_Sender_Prepaid | L100: 46301 | M100: 46332 | N100: 872882983184 | P100: HYDRATIS B2B | Q100: HYDRATIS B2B | R100: VOIE COMMUNALE 4 | S100: CR?ANCEY | T100: 21 | U100: FR | V100: 21320 | W100: 45.67 | X100: 5.41 | Y100: 0 | Z100: -34.76 | AA100: 16.32 | AB100: 2 | AC100: 33 | AD100: 33 | AE100: C,JEBLI | AF100: PHARMACIE CHEBLI | AG100: PHARMACIE CHEBLI | AH100: 1 RUE DU COUSTEL | AI100: VABRES-L'ABBAYE | AJ100: 12 | AK100: FR | AL100: 12400 | AS100: N | AT100: 0 | AU100: 0 | AV100: 0 | BB100: 0 | BC100: 0 | BD100: EUR | BE100: 06/15/2026 | BF100: 634333759 | BH100: Domestic | BI100: Your Packaging | BJ100: 0.50416667 | BK100: 39.6 | BL100: 4.69 | BM100: 0 | BN100: -30.14 | BO100: 14.15 | BP100: EUR | BQ100: 1.1531631 | BR100: kg
...

Sheet TCD
A1: Shipment Tracking Number | B1: Recipient Country/Territory | C1: Somme de Montant | D1: Somme de Shipment Rated Weight (Pounds) | E1: Poids arrondis sup (kg) | F1: E/P
A2: 381547998902 | B2: FI | C2: 70.41 | D2: 47.96 | E2: =ROUNDUP(D2*0.453592,1) -> 21.8 | F2: =IF(_xlfn.XLOOKUP(A2,'Shipment Detail'!N:N,'Shipment Detail'!D:D)="entreprise","E","P") -> E
A3: 381571985035 | B3: FI | C3: 58.57 | D3: 37.62 | E3: =ROUNDUP(D3*0.453592,1) -> 17.1 | F3: =IF(_xlfn.XLOOKUP(A3,'Shipment Detail'!N:N,'Shipment Detail'!D:D)="entreprise","E","P") -> E
A4: 381663677033 | B4: FR | C4: 8.8 | D4: 28.6 | E4: =ROUNDUP(D4*0.453592,1) -> 13 | F4: =IF(_xlfn.XLOOKUP(A4,'Shipment Detail'!N:N,'Shipment Detail'!D:D)="entreprise","E","P") -> P
A5: 381707060387 | B5: CH | C5: 15.89 | D5: 0.22 | E5: =ROUNDUP(D5*0.453592,1) -> 0.1 | F5: =IF(_xlfn.XLOOKUP(A5,'Shipment Detail'!N:N,'Shipment Detail'!D:D)="entreprise","E","P") -> P
A6: 381708365556 | B6: FR | C6: 5.45 | D6: 6.6 | E6: =ROUNDUP(D6*0.453592,1) -> 3 | F6: =IF(_xlfn.XLOOKUP(A6,'Shipment Detail'!N:N,'Shipment Detail'!D:D)="entreprise","E","P") -> P
A7: 381770737060 | B7: FR | C7: 4.78 | D7: 1.32 | E7: =ROUNDUP(D7*0.453592,1) -> 0.6 | F7: =IF(_xlfn.XLOOKUP(A7,'Shipment Detail'!N:N,'Shipment Detail'!D:D)="entreprise","E","P") -> P
A8: 381798154893 | B8: FR | C8: 6.45 | D8: 11.22 | E8: =ROUNDUP(D8*0.453592,1) -> 5.1 | F8: =IF(_xlfn.XLOOKUP(A8,'Shipment Detail'!N:N,'Shipment Detail'!D:D)="entreprise","E","P") -> P
A9: 381824285874 | B9: US | C9: 29.87 | D9: 3.74 | E9: =ROUNDUP(D9*0.453592,1) -> 1.7 | F9: =IF(_xlfn.XLOOKUP(A9,'Shipment Detail'!N:N,'Shipment Detail'!D:D)="entreprise","E","P") -> P
A10: 381863886430 | B10: FR | C10: 7.46 | D10: 19.8 | E10: =ROUNDUP(D10*0.453592,1) -> 9 | F10: =IF(_xlfn.XLOOKUP(A10,'Shipment Detail'!N:N,'Shipment Detail'!D:D)="entreprise","E","P") -> P
A11: 381905290506 | B11: FR | C11: 8.46 | D11: 24.64 | E11: =ROUNDUP(D11*0.453592,1) -> 11.2 | F11: =IF(_xlfn.XLOOKUP(A11,'Shipment Detail'!N:N,'Shipment Detail'!D:D)="entreprise","E","P") -> P
A12: 381954329162 | B12: FR | C12: 7.46 | D12: 19.8 | E12: =ROUNDUP(D12*0.453592,1) -> 9 | F12: =IF(_xlfn.XLOOKUP(A12,'Shipment Detail'!N:N,'Shipment Detail'!D:D)="entreprise","E","P") -> P
A13: 381981990415 | B13: FI | C13: 32.37 | D13: 15.84 | E13: =ROUNDUP(D13*0.453592,1) -> 7.2 | F13: =IF(_xlfn.XLOOKUP(A13,'Shipment Detail'!N:N,'Shipment Detail'!D:D)="entreprise","E","P") -> E
... A3608: 873819757072 | B3608: FR | C3608: 14.82 | D3608: 68.2 | E3608: =ROUNDUP(D3608*0.453592,1) -> 31 | F3608: =IF(_xlfn.XLOOKUP(A3608,'Shipment Detail'!N:N,'Shipment Detail'!D:D)="entreprise","E","P") -> P
A3609: (vide) | B3609: (vide) | E3609: =ROUNDUP(D3609*0.453592,1) -> 0 | F3609: =IF(_xlfn.XLOOKUP(A3609,'Shipment Detail'!N:N,'Shipment Detail'!D:D)="entreprise","E","P") -> #N/A

Sheet Bilan clients
A3: Étiquettes de lignes | B3: Somme de Montant
A4: 3752 | B4: 45112.65
A5: 6085 | B5: 58.07
A6: 7515 | B6: 34.63
A7: 8640 | B7: 67.5
A8: 8656 | B8: 242.98
A9: (vide)
A10: Total général | B10: 45515.83

Sheet Import ERP
A1: Transporteur | B1: Date validité tarif | C1: Réf.1 | D1: Réf. 2 | E1: Id client | F1: N° Tracking | G1: Nom | H1: E / P | I1: Pays | J1: Zone | K1: Nbr Colis | L1: Poids | M1: mode envoi | N1: TVA | O1: Droits et taxes | P1: Assurance | Q1: Zones éloignées | R1: Colis volumineux | S1: Adresses | T1: Frêt | U1: plus-value BtoC | V1: Gazole | W1: Nb colis
A2: =IF(OR(M2="FICP",M2="IE", M2="RE", M2="International", M2="Europe"),"FEDEX INTERNATIONAL","FEDEX FRANCE") -> FEDEX INTERNATIONAL | B2: 46174 | F2: =TCD!A2 -> 381547998902 | H2: =TCD!F2 -> E | I2: =TCD!B2 -> FI | J2: =IF(COUNTIF(Zoning!B:B,I2)=0,"inconnu",_xlfn.XLOOKUP(I2,Zoning!B:B,Zoning!C:C)) -> T | K2: =_xlfn.XLOOKUP(F2,'Shipment Detail'!N:N,'Shipment Detail'!AB:AB) -> 1 | L2: =TCD!E2 -> 21.8 | M2: =IF(J2="France","ST",_xlfn.XLOOKUP(F2,'Shipment Detail'!N:N,'Shipment Detail'!E:E,"")) -> FICP | N2: =IF(OR(I2="FR",I2="DE",I2="IT",I2="ES",I2="BE",I2="NL",I2="LU",I2="PT",I2="AT",I2="IE",I2="FI",I2="SE",I2="DK",I2="PL",I2="CZ",I2="SK",I2="HU",I2="RO",I2="BG",I2="HR",I2="SI",I2="EE",I2="LV",I2="LT",I2="GR",I2="CY",I2="MT"),0.2,0) -> 0.2 | O2: =IF(_xlfn.XLOOKUP(F2,'Shipment Detail'!N:N,'Shipment Detail'!BM:BM)=0,"",_xlfn.XLOOKUP(F2,'Shipment Detail'!N:N,'Shipment Detail'!BM:BM)) | R2: =IF(_xlfn.XLOOKUP(F2,'Shipment Detail'!N:N,'Shipment Detail'!AV:AV)>60,10,"") -> 10 | T2: =TCD!C2 -> 70.41
A3: =IF(OR(M3="FICP",M3="IE", M3="RE", M3="International", M3="Europe"),"FEDEX INTERNATIONAL","FEDEX FRANCE") -> FEDEX INTERNATIONAL | B3: =B2 -> 46174 | F3: =TCD!A3 -> 381571985035 | H3: =TCD!F3 -> E | I3: =TCD!B3 -> FI | J3: =IF(COUNTIF(Zoning!B:B,I3)=0,"inconnu",_xlfn.XLOOKUP(I3,Zoning!B:B,Zoning!C:C)) -> T | K3: =_xlfn.XLOOKUP(F3,'Shipment Detail'!N:N,'Shipment Detail'!AB:AB) -> 1 | L3: =TCD!E3 -> 17.1 | M3: =IF(J3="France","ST",_xlfn.XLOOKUP(F3,'Shipment Detail'!N:N,'Shipment Detail'!E:E,"")) -> FICP | N3: =IF(OR(I3="FR",I3="DE",I3="IT",I3="ES",I3="BE",I3="NL",I3="LU",I3="PT",I3="AT",I3="IE",I3="FI",I3="SE",I3="DK",I3="PL",I3="CZ",I3="SK",I3="HU",I3="RO",I3="BG",I3="HR",I3="SI",I3="EE",I3="LV",I3="LT",I3="GR",I3="CY",I3="MT"),0.2,0) -> 0.2 | O3: =IF(_xlfn.XLOOKUP(F3,'Shipment Detail'!N:N,'Shipment Detail'!BM:BM)=0,"",_xlfn.XLOOKUP(F3,'Shipment Detail'!N:N,'Shipment Detail'!BM:BM)) | R3: =IF(_xlfn.XLOOKUP(F3,'Shipment Detail'!N:N,'Shipment Detail'!AV:AV)>60,10,"") | T3: =TCD!C3 -> 58.57
A4: =IF(OR(M4="FICP",M4="IE", M4="RE", M4="International", M4="Europe"),"FEDEX INTERNATIONAL","FEDEX FRANCE") -> FEDEX FRANCE | B4: =B3 -> 46174 | F4: =TCD!A4 -> 381663677033 | H4: =TCD!F4 -> P | I4: =TCD!B4 -> FR | J4: =IF(COUNTIF(Zoning!B:B,I4)=0,"inconnu",_xlfn.XLOOKUP(I4,Zoning!B:B,Zoning!C:C)) -> France | K4: =_xlfn.XLOOKUP(F4,'Shipment Detail'!N:N,'Shipment Detail'!AB:AB) -> 2 | L4: =TCD!E4 -> 13 | M4: =IF(J4="France","ST",_xlfn.XLOOKUP(F4,'Shipment Detail'!N:N,'Shipment Detail'!E:E,"")) -> ST | N4: =IF(OR(I4="FR",I4="DE",I4="IT",I4="ES",I4="BE",I4="NL",I4="LU",I4="PT",I4="AT",I4="IE",I4="FI",I4="SE",I4="DK",I4="PL",I4="CZ",I4="SK",I4="HU",I4="RO",I4="BG",I4="HR",I4="SI",I4="EE",I4="LV",I4="LT",I4="GR",I4="CY",I4="MT"),0.2,0) -> 0.2 | O4: =IF(_xlfn.XLOOKUP(F4,'Shipment Detail'!N:N,'Shipment Detail'!BM:BM)=0,"",_xlfn.XLOOKUP(F4,'Shipment Detail'!N:N,'Shipment Detail'!BM:BM)) | R4: =IF(_xlfn.XLOOKUP(F4,'Shipment Detail'!N:N,'Shipment Detail'!AV:AV)>60,10,"") | T4: =TCD!C4 -> 8.8
A5: =IF(OR(M5="FICP",M5="IE", M5="RE", M5="International", M5="Europe"),"FEDEX INTERNATIONAL","FEDEX FRANCE") -> FEDEX INTERNATIONAL | B5: =B4 -> 46174 | F5: =TCD!A5 -> 381707060387 | H5: =TCD!F5 -> P | I5: =TCD!B5 -> CH | J5: =IF(COUNTIF(Zoning!B:B,I5)=0,"inconnu",_xlfn.XLOOKUP(I5,Zoning!B:B,Zoning!C:C)) -> U | K5: =_xlfn.XLOOKUP(F5,'Shipment Detail'!N:N,'Shipment Detail'!AB:AB) -> 1 | L5: =TCD!E5 -> 0.1 | M5: =IF(J5="France","ST",_xlfn.XLOOKUP(F5,'Shipment Detail'!N:N,'Shipment Detail'!E:E,"")) -> FICP | N5: =IF(OR(I5="FR",I5="DE",I5="IT",I5="ES",I5="BE",I5="NL",I5="LU",I5="PT",I5="AT",I5="IE",I5="FI",I5="SE",I5="DK",I5="PL",I5="CZ",I5="SK",I5="HU",I5="RO",I5="BG",I5="HR",I5="SI",I5="EE",I5="LV",I5="LT",I5="GR",I5="CY",I5="MT"),0.2,0) -> 0 | O5: =IF(_xlfn.XLOOKUP(F5,'Shipment Detail'!N:N,'Shipment Detail'!BM:BM)=0,"",_xlfn.XLOOKUP(F5,'Shipment Detail'!N:N,'Shipment Detail'!BM:BM)) | R5: =IF(_xlfn.XLOOKUP(F5,'Shipment Detail'!N:N,'Shipment Detail'!AV:AV)>60,10,"") | T5: =TCD!C5 -> 15.89
A6: =IF(OR(M6="FICP",M6="IE", M6="RE", M6="International", M6="Europe"),"FEDEX INTERNATIONAL","FEDEX FRANCE") -> FEDEX FRANCE | B6: =B5 -> 46174 | F6: =TCD!A6 -> 381708365556 | H6: =TCD!F6 -> P | I6: =TCD!B6 -> FR | J6: =IF(COUNTIF(Zoning!B:B,I6)=0,"inconnu",_xlfn.XLOOKUP(I6,Zoning!B:B,Zoning!C:C)) -> France | K6: =_xlfn.XLOOKUP(F6,'Shipment Detail'!N:N,'Shipment Detail'!AB:AB) -> 1 | L6: =TCD!E6 -> 3 | M6: =IF(J6="France","ST",_xlfn.XLOOKUP(F6,'Shipment Detail'!N:N,'Shipment Detail'!E:E,"")) -> ST | N6: =IF(OR(I6="FR",I6="DE",I6="IT",I6="ES",I6="BE",I6="NL",I6="LU",I6="PT",I6="AT",I6="IE",I6="FI",I6="SE",I6="DK",I6="PL",I6="CZ",I6="SK",I6="HU",I6="RO",I6="BG",I6="HR",I6="SI",I6="EE",I6="LV",I6="LT",I6="GR",I6="CY",I6="MT"),0.2,0) -> 0.2 | O6: =IF(_xlfn.XLOOKUP(F6,'Shipment Detail'!N:N,'Shipment Detail'!BM:BM)=0,"",_xlfn.XLOOKUP(F6,'Shipment Detail'!N:N,'Shipment Detail'!BM:BM)) | R6: =IF(_xlfn.XLOOKUP(F6,'Shipment Detail'!N:N,'Shipment Detail'!AV:AV)>60,10,"") | T6: =TCD!C6 -> 5.45
A7: =IF(OR(M7="FICP",M7="IE", M7="RE", M7="International", M7="Europe"),"FEDEX INTERNATIONAL","FEDEX FRANCE") -> FEDEX FRANCE | B7: =B6 -> 46174 | F7: =TCD!A7 -> 381770737060 | H7: =TCD!F7 -> P | I7: =TCD!B7 -> FR | J7: =IF(COUNTIF(Zoning!B:B,I7)=0,"inconnu",_xlfn.XLOOKUP(I7,Zoning!B:B,Zoning!C:C)) -> France | K7: =_xlfn.XLOOKUP(F7,'Shipment Detail'!N:N,'Shipment Detail'!AB:AB) -> 1 | L7: =TCD!E7 -> 0.6 | M7: =IF(J7="France","ST",_xlfn.XLOOKUP(F7,'Shipment Detail'!N:N,'Shipment Detail'!E:E,"")) -> ST | N7: =IF(OR(I7="FR",I7="DE",I7="IT",I7="ES",I7="BE",I7="NL",I7="LU",I7="PT",I7="AT",I7="IE",I7="FI",I7="SE",I7="DK",I7="PL",I7="CZ",I7="SK",I7="HU",I7="RO",I7="BG",I7="HR",I7="SI",I7="EE",I7="LV",I7="LT",I7="GR",I7="CY",I7="MT"),0.2,0) -> 0.2 | O7: =IF(_xlfn.XLOOKUP(F7,'Shipment Detail'!N:N,'Shipment Detail'!BM:BM)=0,"",_xlfn.XLOOKUP(F7,'Shipment Detail'!N:N,'Shipment Detail'!BM:BM)) | R7: =IF(_xlfn.XLOOKUP(F7,'Shipment Detail'!N:N,'Shipment Detail'!AV:AV)>60,10,"") | T7: =TCD!C7 -> 4.78
A8: =IF(OR(M8="FICP",M8="IE", M8="RE", M8="International", M8="Europe"),"FEDEX INTERNATIONAL","FEDEX FRANCE") -> FEDEX FRANCE | B8: =B7 -> 46174 | F8: =TCD!A8 -> 381798154893 | H8: =TCD!F8 -> P | I8: =TCD!B8 -> FR | J8: =IF(COUNTIF(Zoning!B:B,I8)=0,"inconnu",_xlfn.XLOOKUP(I8,Zoning!B:B,Zoning!C:C)) -> France | K8: =_xlfn.XLOOKUP(F8,'Shipment Detail'!N:N,'Shipment Detail'!AB:AB) -> 3 | L8: =TCD!E8 -> 5.1 | M8: =IF(J8="France","ST",_xlfn.XLOOKUP(F8,'Shipment Detail'!N:N,'Shipment Detail'!E:E,"")) -> ST | N8: =IF(OR(I8="FR",I8="DE",I8="IT",I8="ES",I8="BE",I8="NL",I8="LU",I8="PT",I8="AT",I8="IE",I8="FI",I8="SE",I8="DK",I8="PL",I8="CZ",I8="SK",I8="HU",I8="RO",I8="BG",I8="HR",I8="SI",I8="EE",I8="LV",I8="LT",I8="GR",I8="CY",I8="MT"),0.2,0) -> 0.2 | O8: =IF(_xlfn.XLOOKUP(F8,'Shipment Detail'!N:N,'Shipment Detail'!BM:BM)=0,"",_xlfn.XLOOKUP(F8,'Shipment Detail'!N:N,'Shipment Detail'!BM:BM)) | R8: =IF(_xlfn.XLOOKUP(F8,'Shipment Detail'!N:N,'Shipment Detail'!AV:AV)>60,10,"") | T8: =TCD!C8 -> 6.45
A9: =IF(OR(M9="FICP",M9="IE", M9="RE", M9="International", M9="Europe"),"FEDEX INTERNATIONAL","FEDEX FRANCE") -> FEDEX INTERNATIONAL | B9: =B8 -> 46174 | F9: =TCD!A9 -> 381824285874 | H9: =TCD!F9 -> P | I9: =TCD!B9 -> US | J9: =IF(COUNTIF(Zoning!B:B,I9)=0,"inconnu",_xlfn.XLOOKUP(I9,Zoning!B:B,Zoning!C:C)) -> H | K9: =_xlfn.XLOOKUP(F9,'Shipment Detail'!N:N,'Shipment Detail'!AB:AB) -> 1 | L9: =TCD!E9 -> 1.7 | M9: =IF(J9="France","ST",_xlfn.XLOOKUP(F9,'Shipment Detail'!N:N,'Shipment Detail'!E:E,"")) -> FICP | N9: =IF(OR(I9="FR",I9="DE",I9="IT",I9="ES",I9="BE",I9="NL",I9="LU",I9="PT",I9="AT",I9="IE",I9="FI",I9="SE",I9="DK",I9="PL",I9="CZ",I9="SK",I9="HU",I9="RO",I9="BG",I9="HR",I9="SI",I9="EE",I9="LV",I9="LT",I9="GR",I9="CY",I9="MT"),0.2,0) -> 0 | O9: =IF(_xlfn.XLOOKUP(F9,'Shipment Detail'!N:N,'Shipment Detail'!BM:BM)=0,"",_xlfn.XLOOKUP(F9,'Shipment Detail'!N:N,'Shipment Detail'!BM:BM)) | R9: =IF(_xlfn.XLOOKUP(F9,'Shipment Detail'!N:N,'Shipment Detail'!AV:AV)>60,10,"") | T9: =TCD!C9 -> 29.87
A10: =IF(OR(M10="FICP",M10="IE", M10="RE", M10="International", M10="Europe"),"FEDEX INTERNATIONAL","FEDEX FRANCE") -> FEDEX FRANCE | B10: =B9 -> 46174 | F10: =TCD!A10 -> 381863886430 | H10: =TCD!F10 -> P | I10: =TCD!B10 -> FR | J10: =IF(COUNTIF(Zoning!B:B,I10)=0,"inconnu",_xlfn.XLOOKUP(I10,Zoning!B:B,Zoning!C:C)) -> France | K10: =_xlfn.XLOOKUP(F10,'Shipment Detail'!N:N,'Shipment Detail'!AB:AB) -> 1 | L10: =TCD!E10 -> 9 | M10: =IF(J10="France","ST",_xlfn.XLOOKUP(F10,'Shipment Detail'!N:N,'Shipment Detail'!E:E,"")) -> ST | N10: =IF(OR(I10="FR",I10="DE",I10="IT",I10="ES",I10="BE",I10="NL",I10="LU",I10="PT",I10="AT",I10="IE",I10="FI",I10="SE",I10="DK",I10="PL",I10="CZ",I10="SK",I10="HU",I10="RO",I10="BG",I10="HR",I10="SI",I10="EE",I10="LV",I10="LT",I10="GR",I10="CY",I10="MT"),0.2,0) -> 0.2 | O10: =IF(_xlfn.XLOOKUP(F10,'Shipment Detail'!N:N,'Shipment Detail'!BM:BM)=0,"",_xlfn.XLOOKUP(F10,'Shipment Detail'!N:N,'Shipment Detail'!BM:BM)) | R10: =IF(_xlfn.XLOOKUP(F10,'Shipment Detail'!N:N,'Shipment Detail'!AV:AV)>60,10,"") | T10: =TCD!C10 -> 7.46
A11: =IF(OR(M11="FICP",M11="IE", M11="RE", M11="International", M11="Europe"),"FEDEX INTERNATIONAL","FEDEX FRANCE") -> FEDEX FRANCE | B11: =B10 -> 46174 | F11: =TCD!A11 -> 381905290506 | H11: =TCD!F11 -> P | I11: =TCD!B11 -> FR | J11: =IF(COUNTIF(Zoning!B:B,I11)=0,"inconnu",_xlfn.XLOOKUP(I11,Zoning!B:B,Zoning!C:C)) -> France | K11: =_xlfn.XLOOKUP(F11,'Shipment Detail'!N:N,'Shipment Detail'!AB:AB) -> 3 | L11: =TCD!E11 -> 11.2 | M11: =IF(J11="France","ST",_xlfn.XLOOKUP(F11,'Shipment Detail'!N:N,'Shipment Detail'!E:E,"")) -> ST | N11: =IF(OR(I11="FR",I11="DE",I11="IT",I11="ES",I11="BE",I11="NL",I11="LU",I11="PT",I11="AT",I11="IE",I11="FI",I11="SE",I11="DK",I11="PL",I11="CZ",I11="SK",I11="HU",I11="RO",I11="BG",I11="HR",I11="SI",I11="EE",I11="LV",I11="LT",I11="GR",I11="CY",I11="MT"),0.2,0) -> 0.2 | O11: =IF(_xlfn.XLOOKUP(F11,'Shipment Detail'!N:N,'Shipment Detail'!BM:BM)=0,"",_xlfn.XLOOKUP(F11,'Shipment Detail'!N:N,'Shipment Detail'!BM:BM)) | R11: =IF(_xlfn.XLOOKUP(F11,'Shipment Detail'!N:N,'Shipment Detail'!AV:AV)>60,10,"") | T11: =TCD!C11 -> 8.46
A12: =IF(OR(M12="FICP",M12="IE", M12="RE", M12="International", M12="Europe"),"FEDEX INTERNATIONAL","FEDEX FRANCE") -> FEDEX FRANCE | B12: =B11 -> 46174 | F12: =TCD!A12 -> 381954329162 | H12: =TCD!F12 -> P | I12: =TCD!B12 -> FR | J12: =IF(COUNTIF(Zoning!B:B,I12)=0,"inconnu",_xlfn.XLOOKUP(I12,Zoning!B:B,Zoning!C:C)) -> France | K12: =_xlfn.XLOOKUP(F12,'Shipment Detail'!N:N,'Shipment Detail'!AB:AB) -> 1 | L12: =TCD!E12 -> 9 | M12: =IF(J12="France","ST",_xlfn.XLOOKUP(F12,'Shipment Detail'!N:N,'Shipment Detail'!E:E,"")) -> ST | N12: =IF(OR(I12="FR",I12="DE",I12="IT",I12="ES",I12="BE",I12="NL",I12="LU",I12="PT",I12="AT",I12="IE",I12="FI",I12="SE",I12="DK",I12="PL",I12="CZ",I12="SK",I12="HU",I12="RO",I12="BG",I12="HR",I12="SI",I12="EE",I12="LV",I12="LT",I12="GR",I12="CY",I12="MT"),0.2,0) -> 0.2 | O12: =IF(_xlfn.XLOOKUP(F12,'Shipment Detail'!N:N,'Shipment Detail'!BM:BM)=0,"",_xlfn.XLOOKUP(F12,'Shipment Detail'!N:N,'Shipment Detail'!BM:BM)) | R12: =IF(_xlfn.XLOOKUP(F12,'Shipment Detail'!N:N,'Shipment Detail'!AV:AV)>60,10,"") | T12: =TCD!C12 -> 7.46
A13: =IF(OR(M13="FICP",M13="IE", M13="RE", M13="International", M13="Europe"),"FEDEX INTERNATIONAL","FEDEX FRANCE") -> FEDEX INTERNATIONAL | B13: =B12 -> 46174 | F13: =TCD!A13 -> 381981990415 | H13: =TCD!F13 -> E | I13: =TCD!B13 -> FI | J13: =IF(COUNTIF(Zoning!B:B,I13)=0,"inconnu",_xlfn.XLOOKUP(I13,Zoning!B:B,Zoning!C:C)) -> T | K13: =_xlfn.XLOOKUP(F13,'Shipment Detail'!N:N,'Shipment Detail'!AB:AB) -> 1 | L13: =TCD!E13 -> 7.2 | M13: =IF(J13="France","ST",_xlfn.XLOOKUP(F13,'Shipment Detail'!N:N,'Shipment Detail'!E:E,"")) -> FICP | N13: =IF(OR(I13="FR",I13="DE",I13="IT",I13="ES",I13="BE",I13="NL",I13="LU",I13="PT",I13="AT",I13="IE",I13="FI",I13="SE",I13="DK",I13="PL",I13="CZ",I13="SK",I13="HU",I13="RO",I13="BG",I13="HR",I13="SI",I13="EE",I13="LV",I13="LT",I13="GR",I13="CY",I13="MT"),0.2,0) -> 0.2 | O13: =IF(_xlfn.XLOOKUP(F13,'Shipment Detail'!N:N,'Shipment Detail'!BM:BM)=0,"",_xlfn.XLOOKUP(F13,'Shipment Detail'!N:N,'Shipment Detail'!BM:BM)) | R13: =IF(_xlfn.XLOOKUP(F13,'Shipment Detail'!N:N,'Shipment Detail'!AV:AV)>60,10,"") | T13: =TCD!C13 -> 32.37
A14: =IF(OR(M14="FICP",M14="IE", M14="RE", M14="International", M14="Europe"),"FEDEX INTERNATIONAL","FEDEX FRANCE") -> FEDEX INTERNATIONAL | B14: =B13 -> 46174 | F14: =TCD!A14 -> 382050598017 | H14: =TCD!F14 -> E | I14: =TCD!B14 -> SE | J14: =IF(COUNTIF(Zoning!B:B,I14)=0,"inconnu",_xlfn.XLOOKUP(I14,Zoning!B:B,Zoning!C:C)) -> T | K14: =_xlfn.XLOOKUP(F14,'Shipment Detail'!N:N,'Shipment Detail'!AB:AB) -> 1 | L14: =TCD!E14 -> 13.8 | M14: =IF(J14="France","ST",_xlfn.XLOOKUP(F14,'Shipment Detail'!N:N,'Shipment Detail'!E:E,"")) -> FICP | N14: =IF(OR(I14="FR",I14="DE",I14="IT",I14="ES",I14="BE",I14="NL",I14="LU",I14="PT",I14="AT",I14="IE",I14="FI",I14="SE",I14="DK",I14="PL",I14="CZ",I14="SK",I14="HU",I14="RO",I14="BG",I14="HR",I14="SI",I14="EE",I14="LV",I14="LT",I14="GR",I14="CY",I14="MT"),0.2,0) -> 0.2 | O14: =IF(_xlfn.XLOOKUP(F14,'Shipment Detail'!N:N,'Shipment Detail'!BM:BM)=0,"",_xlfn.XLOOKUP(F14,'Shipment Detail'!N:N,'Shipment Detail'!BM:BM)) | R14: =IF(_xlfn.XLOOKUP(F14,'Shipment Detail'!N:N,'Shipment Detail'!AV:AV)>60,10,"") | T14: =TCD!C14 -> 49.88
... A3608: =IF(OR(M3608="FICP",M3608="IE", M3608="RE", M3608="International", M3608="Europe"),"FEDEX INTERNATIONAL","FEDEX FRANCE") -> FEDEX FRANCE | B3608: =B3607 -> 46174 | F3608: =TCD!A3608 -> 873819757072 | H3608: =TCD!F3608 -> P | I3608: =TCD!B3608 -> FR | J3608: =IF(COUNTIF(Zoning!B:B,I3608)=0,"inconnu",_xlfn.XLOOKUP(I3608,Zoning!B:B,Zoning!C:C)) -> France | K3608: =_xlfn.XLOOKUP(F3608,'Shipment Detail'!N:N,'Shipment Detail'!AB:AB) -> 7 | L3608: =TCD!E3608 -> 31 | M3608: =IF(J3608="France","ST",_xlfn.XLOOKUP(F3608,'Shipment Detail'!N:N,'Shipment Detail'!E:E,"")) -> ST | N3608: =IF(OR(I3608="FR",I3608="DE",I3608="IT",I3608="ES",I3608="BE",I3608="NL",I3608="LU",I3608="PT",I3608="AT",I3608="IE",I3608="FI",I3608="SE",I3608="DK",I3608="PL",I3608="CZ",I3608="SK",I3608="HU",I3608="RO",I3608="BG",I3608="HR",I3608="SI",I3608="EE",I3608="LV",I3608="LT",I3608="GR",I3608="CY",I3608="MT"),0.2,0) -> 0.2 | O3608: =IF(_xlfn.XLOOKUP(F3608,'Shipment Detail'!N:N,'Shipment Detail'!BM:BM)=0,"",_xlfn.XLOOKUP(F3608,'Shipment Detail'!N:N,'Shipment Detail'!BM:BM)) | R3608: =IF(_xlfn.XLOOKUP(F3608,'Shipment Detail'!N:N,'Shipment Detail'!AV:AV)>60,10,"") | T3608: =TCD!C3608 -> 14.82
