Workbook

Sheet Catégories
A1: CNM | B1: Colis volumineux
A2: AS_AD_VAL | B2: Assurance
A3: DR | B3: Frêt
A4: FACTOR_FOR | B4: Frêt
A5: LS | B5: Frêt
A6: RS | B6: Frêt
A7: SURCH_CARB | B7: Gazole
A8: TMC | B8: Frêt
A9: Z | B9: Frêt
A10: ZEL | B10: Zones éloignées
A11: SURCH_CARB | B11: Gazole
A12: AS_AD_VAL | B12: Assurance
... A26: FACTOR_FOR | B26: Frêt
B27: Frêt

Sheet Recherche tracking
A1: numero envoi | B1: id colis
A2: E00000000000000 | B2: '
A3: E20260601123351 | B3: '
A4: E20260601123351 | B4: '6343814314751131
A5: E20260601123351 | B5: '6343814314751148
A6: E20260601123352 | B6: '
A7: E20260601123352 | B7: '6543814314751205
A8: E20260601123353 | B8: '
A9: E20260601123353 | B9: '7443814314751128
A10: E20260601123355 | B10: '
A11: E20260601123355 | B11: '5643814314751081
A12: E20260601123356 | B12: '
... A1202: (vide) | B1202: (vide)

Sheet Nb colis et poids
A1: code complement | B1: TMC | E1: Étiquettes de lignes | F1: Max. de poids colis
F2: 0
A3: Étiquettes de lignes | B3: Somme de montant HT | E3: 0143814314751704 | F3: 1.34
A4: 0143814314754170 | B4: 1 | E4: 0143814314752278 | F4: 0.8
A5: 0643814314752665 | B5: 1 | E5: 0143814314752704 | F5: 3.84
A6: 0643814314754648 | B6: 8 | E6: 0143814314754170 | F6: 12.61
A7: 0743814314753622 | B7: 1 | E7: 0143814314756819 | F7: 11.69
A8: 1143814314757169 | B8: 1 | E8: 0243814314752776 | F8: 4.01
A9: 1343814314754157 | B9: 2 | E9: 0343814314755970 | F9: 0.8
A10: 1343814314756278 | B10: 2 | E10: 0443814314751303 | F10: 1.6
A11: 1443814314751684 | B11: 1 | E11: 0543814314752536 | F11: 2.9
A12: 1443814314752131 | B12: 1 | E12: 0643814314751591 | F12: 2.9
A13: 1443814314752190 | B13: 2 | E13: 0643814314752078 | F13: 9.2
A14: 1743814314752225 | B14: 2 | E14: 0643814314752665 | F14: 11.8
A15: 1743814314753657 | B15: 1 | E15: 0643814314752717 | F15: 2.9
... A104: 9543814314757247 | B104: 4 | E104: 2543814314752930 | F104: 24.04
E105: 2543814314754952 | F105: 6.01
E106: 2543814314757693 | F106: 3.5
E107: 2643814314752908 | F107: 10.8
E108: 2643814314754839 | F108: 3.5
E109: 2643814314757125 | F109: 2.6
E110: 2743814314752617 | F110: 3.6
E111: 2743814314754992 | F111: 3.9
E112: 2943814314753670 | F112: 26.3
E113: 2943814314754006 | F113: 2.9
E114: 2943814314754686 | F114: 3.2
E115: 2943814314756795 | F115: 3.8
E116: 3043814314752882 | F116: 1
... E515: 9543814314757247 | F515: 76.9
E516: (vide)

Sheet Facture TNT
A1: Problème | B1: Catégorie | C1: Tracking | D1: Mois de Facturation | E1: Indicatif Facture | F1: Numero de Facture | G1: Compte Expediteur | H1: Client Facturé | I1: Ligne Facture | J1: id colis | K1: date Expedition | L1: numero envoi | M1: code Produit | N1: poids colis | O1: code complement | P1: montant HT | Q1: raison sociale expéditeur | R1: adresse 1 | S1: adresse 2 | T1: pays | U1: departement | V1: code postal | W1: ville | X1: raison sociale destinataire | Y1: adresse 1 | Z1: adresse 2 | AA1: pays | AB1: departement | AC1: code postal | AD1: ville
B2: =IF(O2="","Frêt",_xlfn.XLOOKUP(O2,Catégories!A:A,Catégories!B:B,"inconnu")) -> Gazole | C2: =RIGHT(LOOKUP(L2,'Recherche tracking'!A:A,'Recherche tracking'!B:B),16) | D2: 202606 | E2: 51 | F2: 1085442 | G2: '03814314 | H2: '03814314 | I2: EXP | J2: ' | K2: 0 | L2: E00000000000000 | N2: 0 | O2: SURCH_CARB | P2: 422.52 | U2: ' | V2: ' | AB2: ' | AC2: '
B3: =IF(O3="","Frêt",_xlfn.XLOOKUP(O3,Catégories!A:A,Catégories!B:B,"inconnu")) -> Frêt | C3: =RIGHT(LOOKUP(L3,'Recherche tracking'!A:A,'Recherche tracking'!B:B),16) -> 6343814314751148 | D3: 202606 | E3: 51 | F3: 1085442 | G3: '03814314 | H3: '03814314 | I3: ENV | J3: ' | K3: 20260601 | L3: E20260601123351 | M3: J18 | N3: 12.7 | P3: 7.27 | Q3: LARUCHE | R3: VOIE COMMUNALE 4 | T3: FR | U3: '21 | V3: '21320 | W3: CREANCEY | X3: ARNAUD PHILIPPE | Y3: 97 AVENUE JOSEPH CLAUSSAT | AA3: FR | AB3: '63 | AC3: '63400 | AD3: CHAMALIERES
B4: =IF(O4="","Frêt",_xlfn.XLOOKUP(O4,Catégories!A:A,Catégories!B:B,"inconnu")) -> Frêt | C4: =RIGHT(LOOKUP(L4,'Recherche tracking'!A:A,'Recherche tracking'!B:B),16) -> 6343814314751148 | D4: 202606 | E4: 51 | F4: 1085442 | G4: '03814314 | H4: '03814314 | I4: COL | J4: '6343814314751131 | K4: 20260601 | L4: E20260601123351 | M4: J18 | N4: 5.4 | P4: 0 | Q4: LARUCHE | R4: VOIE COMMUNALE 4 | T4: FR | U4: '21 | V4: '21320 | W4: CREANCEY | X4: ARNAUD PHILIPPE | Y4: 97 AVENUE JOSEPH CLAUSSAT | AA4: FR | AB4: '63 | AC4: '63400 | AD4: CHAMALIERES
B5: =IF(O5="","Frêt",_xlfn.XLOOKUP(O5,Catégories!A:A,Catégories!B:B,"inconnu")) -> Frêt | C5: =RIGHT(LOOKUP(L5,'Recherche tracking'!A:A,'Recherche tracking'!B:B),16) -> 6343814314751148 | D5: 202606 | E5: 51 | F5: 1085442 | G5: '03814314 | H5: '03814314 | I5: CPC | J5: '6343814314751131 | K5: 20260601 | L5: E20260601123351 | N5: 5.4 | O5: RS | P5: 0 | Q5: LARUCHE | R5: VOIE COMMUNALE 4 | T5: FR | U5: '21 | V5: '21320 | W5: CREANCEY | X5: ARNAUD PHILIPPE | Y5: 97 AVENUE JOSEPH CLAUSSAT | AA5: FR | AB5: '63 | AC5: '63400 | AD5: CHAMALIERES
B6: =IF(O6="","Frêt",_xlfn.XLOOKUP(O6,Catégories!A:A,Catégories!B:B,"inconnu")) -> Frêt | C6: =RIGHT(LOOKUP(L6,'Recherche tracking'!A:A,'Recherche tracking'!B:B),16) -> 6343814314751148 | D6: 202606 | E6: 51 | F6: 1085442 | G6: '03814314 | H6: '03814314 | I6: COL | J6: '6343814314751148 | K6: 20260601 | L6: E20260601123351 | M6: J18 | N6: 7.3 | P6: 0 | Q6: LARUCHE | R6: VOIE COMMUNALE 4 | T6: FR | U6: '21 | V6: '21320 | W6: CREANCEY | X6: ARNAUD PHILIPPE | Y6: 97 AVENUE JOSEPH CLAUSSAT | AA6: FR | AB6: '63 | AC6: '63400 | AD6: CHAMALIERES
B7: =IF(O7="","Frêt",_xlfn.XLOOKUP(O7,Catégories!A:A,Catégories!B:B,"inconnu")) -> Frêt | C7: =RIGHT(LOOKUP(L7,'Recherche tracking'!A:A,'Recherche tracking'!B:B),16) -> 6343814314751148 | D7: 202606 | E7: 51 | F7: 1085442 | G7: '03814314 | H7: '03814314 | I7: CPC | J7: '6343814314751148 | K7: 20260601 | L7: E20260601123351 | N7: 7.3 | O7: RS | P7: 0 | Q7: LARUCHE | R7: VOIE COMMUNALE 4 | T7: FR | U7: '21 | V7: '21320 | W7: CREANCEY | X7: ARNAUD PHILIPPE | Y7: 97 AVENUE JOSEPH CLAUSSAT | AA7: FR | AB7: '63 | AC7: '63400 | AD7: CHAMALIERES
B8: =IF(O8="","Frêt",_xlfn.XLOOKUP(O8,Catégories!A:A,Catégories!B:B,"inconnu")) -> Frêt | C8: =RIGHT(LOOKUP(L8,'Recherche tracking'!A:A,'Recherche tracking'!B:B),16) -> 6343814314751148 | D8: 202606 | E8: 51 | F8: 1085442 | G8: '03814314 | H8: '03814314 | I8: CPC | J8: '6343814314751148 | K8: 20260601 | L8: E20260601123351 | N8: 7.3 | O8: TMC | P8: 1 | Q8: LARUCHE | R8: VOIE COMMUNALE 4 | T8: FR | U8: '21 | V8: '21320 | W8: CREANCEY | X8: ARNAUD PHILIPPE | Y8: 97 AVENUE JOSEPH CLAUSSAT | AA8: FR | AB8: '63 | AC8: '63400 | AD8: CHAMALIERES
B9: =IF(O9="","Frêt",_xlfn.XLOOKUP(O9,Catégories!A:A,Catégories!B:B,"inconnu")) -> Frêt | C9: =RIGHT(LOOKUP(L9,'Recherche tracking'!A:A,'Recherche tracking'!B:B),16) -> 6543814314751205 | D9: 202606 | E9: 51 | F9: 1085442 | G9: '03814314 | H9: '03814314 | I9: ENV | J9: ' | K9: 20260601 | L9: E20260601123352 | M9: J18 | N9: 2.9 | P9: 4.67 | Q9: LARUCHE | R9: VOIE COMMUNALE 4 | T9: FR | U9: '21 | V9: '21320 | W9: CREANCEY | X9: BACHA LOLA | Y9: 82 RUE THIERS | AA9: FR | AB9: '65 | AC9: '65300 | AD9: LANNEMEZAN
B10: =IF(O10="","Frêt",_xlfn.XLOOKUP(O10,Catégories!A:A,Catégories!B:B,"inconnu")) -> Frêt | C10: =RIGHT(LOOKUP(L10,'Recherche tracking'!A:A,'Recherche tracking'!B:B),16) -> 6543814314751205 | D10: 202606 | E10: 51 | F10: 1085442 | G10: '03814314 | H10: '03814314 | I10: COL | J10: '6543814314751205 | K10: 20260601 | L10: E20260601123352 | M10: J18 | N10: 2.9 | P10: 0 | Q10: LARUCHE | R10: VOIE COMMUNALE 4 | T10: FR | U10: '21 | V10: '21320 | W10: CREANCEY | X10: BACHA LOLA | Y10: 82 RUE THIERS | AA10: FR | AB10: '65 | AC10: '65300 | AD10: LANNEMEZAN
B11: =IF(O11="","Frêt",_xlfn.XLOOKUP(O11,Catégories!A:A,Catégories!B:B,"inconnu")) -> Frêt | C11: =RIGHT(LOOKUP(L11,'Recherche tracking'!A:A,'Recherche tracking'!B:B),16) -> 6543814314751205 | D11: 202606 | E11: 51 | F11: 1085442 | G11: '03814314 | H11: '03814314 | I11: CPC | J11: '6543814314751205 | K11: 20260601 | L11: E20260601123352 | N11: 2.9 | O11: RS | P11: 0 | Q11: LARUCHE | R11: VOIE COMMUNALE 4 | T11: FR | U11: '21 | V11: '21320 | W11: CREANCEY | X11: BACHA LOLA | Y11: 82 RUE THIERS | AA11: FR | AB11: '65 | AC11: '65300 | AD11: LANNEMEZAN
B12: =IF(O12="","Frêt",_xlfn.XLOOKUP(O12,Catégories!A:A,Catégories!B:B,"inconnu")) -> Frêt | C12: =RIGHT(LOOKUP(L12,'Recherche tracking'!A:A,'Recherche tracking'!B:B),16) -> 7443814314751128 | D12: 202606 | E12: 51 | F12: 1085442 | G12: '03814314 | H12: '03814314 | I12: ENV | J12: ' | K12: 20260601 | L12: E20260601123353 | M12: J18 | N12: 22.1 | P12: 9.87 | Q12: LARUCHE | R12: VOIE COMMUNALE 4 | T12: FR | U12: '21 | V12: '21320 | W12: CREANCEY | X12: BALLET THEO | Y12: 21 PLACE BALMAT | AA12: FR | AB12: '74 | AC12: '74400 | AD12: CHAMONIX-MONT-BLANC
B13: =IF(O13="","Frêt",_xlfn.XLOOKUP(O13,Catégories!A:A,Catégories!B:B,"inconnu")) -> Frêt | C13: =RIGHT(LOOKUP(L13,'Recherche tracking'!A:A,'Recherche tracking'!B:B),16) -> 7443814314751128 | D13: 202606 | E13: 51 | F13: 1085442 | G13: '03814314 | H13: '03814314 | I13: COL | J13: '7443814314751128 | K13: 20260601 | L13: E20260601123353 | M13: J18 | N13: 22.1 | P13: 0 | Q13: LARUCHE | R13: VOIE COMMUNALE 4 | T13: FR | U13: '21 | V13: '21320 | W13: CREANCEY | X13: BALLET THEO | Y13: 21 PLACE BALMAT | AA13: FR | AB13: '74 | AC13: '74400 | AD13: CHAMONIX-MONT-BLANC
B14: =IF(O14="","Frêt",_xlfn.XLOOKUP(O14,Catégories!A:A,Catégories!B:B,"inconnu")) -> Frêt | C14: =RIGHT(LOOKUP(L14,'Recherche tracking'!A:A,'Recherche tracking'!B:B),16) -> 7443814314751128 | D14: 202606 | E14: 51 | F14: 1085442 | G14: '03814314 | H14: '03814314 | I14: CPC | J14: '7443814314751128 | K14: 20260601 | L14: E20260601123353 | N14: 22.1 | O14: RS | P14: 0 | Q14: LARUCHE | R14: VOIE COMMUNALE 4 | T14: FR | U14: '21 | V14: '21320 | W14: CREANCEY | X14: BALLET THEO | Y14: 21 PLACE BALMAT | AA14: FR | AB14: '74 | AC14: '74400 | AD14: CHAMONIX-MONT-BLANC
B15: =IF(O15="","Frêt",_xlfn.XLOOKUP(O15,Catégories!A:A,Catégories!B:B,"inconnu")) -> Zones éloignées | C15: =RIGHT(LOOKUP(L15,'Recherche tracking'!A:A,'Recherche tracking'!B:B),16) -> 7443814314751128 | D15: 202606 | E15: 51 | F15: 1085442 | G15: '03814314 | H15: '03814314 | I15: CPC | J15: '7443814314751128 | K15: 20260601 | L15: E20260601123353 | N15: 22.1 | O15: ZEL | P15: 5 | Q15: LARUCHE | R15: VOIE COMMUNALE 4 | T15: FR | U15: '21 | V15: '21320 | W15: CREANCEY | X15: BALLET THEO | Y15: 21 PLACE BALMAT | AA15: FR | AB15: '74 | AC15: '74400 | AD15: CHAMONIX-MONT-BLANC
B16: =IF(O16="","Frêt",_xlfn.XLOOKUP(O16,Catégories!A:A,Catégories!B:B,"inconnu")) -> Frêt | C16: =RIGHT(LOOKUP(L16,'Recherche tracking'!A:A,'Recherche tracking'!B:B),16) -> 5643814314751081 | D16: 202606 | E16: 51 | F16: 1085442 | G16: '03814314 | H16: '03814314 | I16: ENV | J16: ' | K16: 20260601 | L16: E20260601123355 | M16: J18 | N16: 10.4 | P16: 6.75 | Q16: LARUCHE | R16: VOIE COMMUNALE 4 | T16: FR | U16: '21 | V16: '21320 | W16: CREANCEY | X16: BATEJAT VICTOR | Y16: 19 RUE DES VIERGES | AA16: FR | AB16: '56 | AC16: '56000 | AD16: VANNES
B17: =IF(O17="","Frêt",_xlfn.XLOOKUP(O17,Catégories!A:A,Catégories!B:B,"inconnu")) -> Frêt | C17: =RIGHT(LOOKUP(L17,'Recherche tracking'!A:A,'Recherche tracking'!B:B),16) -> 5643814314751081 | D17: 202606 | E17: 51 | F17: 1085442 | G17: '03814314 | H17: '03814314 | I17: COL | J17: '5643814314751081 | K17: 20260601 | L17: E20260601123355 | M17: J18 | N17: 10.4 | P17: 0 | Q17: LARUCHE | R17: VOIE COMMUNALE 4 | T17: FR | U17: '21 | V17: '21320 | W17: CREANCEY | X17: BATEJAT VICTOR | Y17: 19 RUE DES VIERGES | AA17: FR | AB17: '56 | AC17: '56000 | AD17: VANNES
B18: =IF(O18="","Frêt",_xlfn.XLOOKUP(O18,Catégories!A:A,Catégories!B:B,"inconnu")) -> Frêt | C18: =RIGHT(LOOKUP(L18,'Recherche tracking'!A:A,'Recherche tracking'!B:B),16) -> 5643814314751081 | D18: 202606 | E18: 51 | F18: 1085442 | G18: '03814314 | H18: '03814314 | I18: CPC | J18: '5643814314751081 | K18: 20260601 | L18: E20260601123355 | N18: 10.4 | O18: RS | P18: 0 | Q18: LARUCHE | R18: VOIE COMMUNALE 4 | T18: FR | U18: '21 | V18: '21320 | W18: CREANCEY | X18: BATEJAT VICTOR | Y18: 19 RUE DES VIERGES | AA18: FR | AB18: '56 | AC18: '56000 | AD18: VANNES
B19: =IF(O19="","Frêt",_xlfn.XLOOKUP(O19,Catégories!A:A,Catégories!B:B,"inconnu")) -> Frêt | C19: =RIGHT(LOOKUP(L19,'Recherche tracking'!A:A,'Recherche tracking'!B:B),16) -> 9343814314751052 | D19: 202606 | E19: 51 | F19: 1085442 | G19: '03814314 | H19: '03814314 | I19: ENV | J19: ' | K19: 20260601 | L19: E20260601123356 | M19: J18 | N19: 2.84 | P19: 4.67 | Q19: LARUCHE | R19: VOIE COMMUNALE 4 | T19: FR | U19: '21 | V19: '21320 | W19: CREANCEY | X19: BERRIAS HOUDA | Y19: 16 PLACE DU GENERAL DE GAULLE | AA19: FR | AB19: '93 | AC19: '93220 | AD19: GAGNY
B20: =IF(O20="","Frêt",_xlfn.XLOOKUP(O20,Catégories!A:A,Catégories!B:B,"inconnu")) -> Frêt | C20: =RIGHT(LOOKUP(L20,'Recherche tracking'!A:A,'Recherche tracking'!B:B),16) -> 9343814314751052 | D20: 202606 | E20: 51 | F20: 1085442 | G20: '03814314 | H20: '03814314 | I20: COL | J20: '9343814314751052 | K20: 20260601 | L20: E20260601123356 | M20: J18 | N20: 2.84 | P20: 0 | Q20: LARUCHE | R20: VOIE COMMUNALE 4 | T20: FR | U20: '21 | V20: '21320 | W20: CREANCEY | X20: BERRIAS HOUDA | Y20: 16 PLACE DU GENERAL DE GAULLE | AA20: FR | AB20: '93 | AC20: '93220 | AD20: GAGNY
B21: =IF(O21="","Frêt",_xlfn.XLOOKUP(O21,Catégories!A:A,Catégories!B:B,"inconnu")) -> Frêt | C21: =RIGHT(LOOKUP(L21,'Recherche tracking'!A:A,'Recherche tracking'!B:B),16) -> 9343814314751052 | D21: 202606 | E21: 51 | F21: 1085442 | G21: '03814314 | H21: '03814314 | I21: CPC | J21: '9343814314751052 | K21: 20260601 | L21: E20260601123356 | N21: 2.84 | O21: RS | P21: 0 | Q21: LARUCHE | R21: VOIE COMMUNALE 4 | T21: FR | U21: '21 | V21: '21320 | W21: CREANCEY | X21: BERRIAS HOUDA | Y21: 16 PLACE DU GENERAL DE GAULLE | AA21: FR | AB21: '93 | AC21: '93220 | AD21: GAGNY
B22: =IF(O22="","Frêt",_xlfn.XLOOKUP(O22,Catégories!A:A,Catégories!B:B,"inconnu")) -> Frêt | C22: =RIGHT(LOOKUP(L22,'Recherche tracking'!A:A,'Recherche tracking'!B:B),16) -> 7543814314751091 | D22: 202606 | E22: 51 | F22: 1085442 | G22: '03814314 | H22: '03814314 | I22: ENV | J22: ' | K22: 20260601 | L22: E20260601123357 | M22: J18 | N22: 3.2 | P22: 4.93 | Q22: LARUCHE | R22: VOIE COMMUNALE 4 | T22: FR | U22: '21 | V22: '21320 | W22: CREANCEY | X22: BOURGUIBA CHEYMA | Y22: 42 RUE DU CHEMIN VERT | AA22: FR | AB22: '75 | AC22: '75011 | AD22: PARIS
B23: =IF(O23="","Frêt",_xlfn.XLOOKUP(O23,Catégories!A:A,Catégories!B:B,"inconnu")) -> Frêt | C23: =RIGHT(LOOKUP(L23,'Recherche tracking'!A:A,'Recherche tracking'!B:B),16) -> 7543814314751091 | D23: 202606 | E23: 51 | F23: 1085442 | G23: '03814314 | H23: '03814314 | I23: COL | J23: '7543814314751091 | K23: 20260601 | L23: E20260601123357 | M23: J18 | N23: 3.2 | P23: 0 | Q23: LARUCHE | R23: VOIE COMMUNALE 4 | T23: FR | U23: '21 | V23: '21320 | W23: CREANCEY | X23: BOURGUIBA CHEYMA | Y23: 42 RUE DU CHEMIN VERT | AA23: FR | AB23: '75 | AC23: '75011 | AD23: PARIS
B24: =IF(O24="","Frêt",_xlfn.XLOOKUP(O24,Catégories!A:A,Catégories!B:B,"inconnu")) -> Frêt | C24: =RIGHT(LOOKUP(L24,'Recherche tracking'!A:A,'Recherche tracking'!B:B),16) -> 7543814314751091 | D24: 202606 | E24: 51 | F24: 1085442 | G24: '03814314 | H24: '03814314 | I24: CPC | J24: '7543814314751091 | K24: 20260601 | L24: E20260601123357 | N24: 3.2 | O24: RS | P24: 0 | Q24: LARUCHE | R24: VOIE COMMUNALE 4 | T24: FR | U24: '21 | V24: '21320 | W24: CREANCEY | X24: BOURGUIBA CHEYMA | Y24: 42 RUE DU CHEMIN VERT | AA24: FR | AB24: '75 | AC24: '75011 | AD24: PARIS
B25: =IF(O25="","Frêt",_xlfn.XLOOKUP(O25,Catégories!A:A,Catégories!B:B,"inconnu")) -> Frêt | C25: =RIGHT(LOOKUP(L25,'Recherche tracking'!A:A,'Recherche tracking'!B:B),16) -> 9443814314751187 | D25: 202606 | E25: 51 | F25: 1085442 | G25: '03814314 | H25: '03814314 | I25: ENV | J25: ' | K25: 20260601 | L25: E20260601123358 | M25: J18 | N25: 10 | P25: 6.49 | Q25: LARUCHE | R25: VOIE COMMUNALE 4 | T25: FR | U25: '21 | V25: '21320 | W25: CREANCEY | X25: CASSE LIONEL | Y25: 12 AVENUE DE VERDUN | AA25: FR | AB25: '94 | AC25: '94410 | AD25: SAINT MAURICE
B26: =IF(O26="","Frêt",_xlfn.XLOOKUP(O26,Catégories!A:A,Catégories!B:B,"inconnu")) -> Frêt | C26: =RIGHT(LOOKUP(L26,'Recherche tracking'!A:A,'Recherche tracking'!B:B),16) -> 9443814314751187 | D26: 202606 | E26: 51 | F26: 1085442 | G26: '03814314 | H26: '03814314 | I26: COL | J26: '9443814314751175 | K26: 20260601 | L26: E20260601123358 | M26: J18 | N26: 5.3 | P26: 0 | Q26: LARUCHE | R26: VOIE COMMUNALE 4 | T26: FR | U26: '21 | V26: '21320 | W26: CREANCEY | X26: CASSE LIONEL | Y26: 12 AVENUE DE VERDUN | AA26: FR | AB26: '94 | AC26: '94410 | AD26: SAINT MAURICE
B27: =IF(O27="","Frêt",_xlfn.XLOOKUP(O27,Catégories!A:A,Catégories!B:B,"inconnu")) -> Frêt | C27: =RIGHT(LOOKUP(L27,'Recherche tracking'!A:A,'Recherche tracking'!B:B),16) -> 9443814314751187 | D27: 202606 | E27: 51 | F27: 1085442 | G27: '03814314 | H27: '03814314 | I27: CPC | J27: '9443814314751175 | K27: 20260601 | L27: E20260601123358 | N27: 5.3 | O27: RS | P27: 0 | Q27: LARUCHE | R27: VOIE COMMUNALE 4 | T27: FR | U27: '21 | V27: '21320 | W27: CREANCEY | X27: CASSE LIONEL | Y27: 12 AVENUE DE VERDUN | AA27: FR | AB27: '94 | AC27: '94410 | AD27: SAINT MAURICE
B28: =IF(O28="","Frêt",_xlfn.XLOOKUP(O28,Catégories!A:A,Catégories!B:B,"inconnu")) -> Frêt | C28: =RIGHT(LOOKUP(L28,'Recherche tracking'!A:A,'Recherche tracking'!B:B),16) -> 9443814314751187 | D28: 202606 | E28: 51 | F28: 1085442 | G28: '03814314 | H28: '03814314 | I28: COL | J28: '9443814314751187 | K28: 20260601 | L28: E20260601123358 | M28: J18 | N28: 4.7 | P28: 0 | Q28: LARUCHE | R28: VOIE COMMUNALE 4 | T28: FR | U28: '21 | V28: '21320 | W28: CREANCEY | X28: CASSE LIONEL | Y28: 12 AVENUE DE VERDUN | AA28: FR | AB28: '94 | AC28: '94410 | AD28: SAINT MAURICE
B29: =IF(O29="","Frêt",_xlfn.XLOOKUP(O29,Catégories!A:A,Catégories!B:B,"inconnu")) -> Frêt | C29: =RIGHT(LOOKUP(L29,'Recherche tracking'!A:A,'Recherche tracking'!B:B),16) -> 9443814314751187 | D29: 202606 | E29: 51 | F29: 1085442 | G29: '03814314 | H29: '03814314 | I29: CPC | J29: '9443814314751187 | K29: 20260601 | L29: E20260601123358 | N29: 4.7 | O29: RS | P29: 0 | Q29: LARUCHE | R29: VOIE COMMUNALE 4 | T29: FR | U29: '21 | V29: '21320 | W29: CREANCEY | X29: CASSE LIONEL | Y29: 12 AVENUE DE VERDUN | AA29: FR | AB29: '94 | AC29: '94410 | AD29: SAINT MAURICE
B30: =IF(O30="","Frêt",_xlfn.XLOOKUP(O30,Catégories!A:A,Catégories!B:B,"inconnu")) -> Frêt | C30: =RIGHT(LOOKUP(L30,'Recherche tracking'!A:A,'Recherche tracking'!B:B),16) -> 9443814314751187 | D30: 202606 | E30: 51 | F30: 1085442 | G30: '03814314 | H30: '03814314 | I30: CPC | J30: '9443814314751187 | K30: 20260601 | L30: E20260601123358 | N30: 4.7 | O30: TMC | P30: 1 | Q30: LARUCHE | R30: VOIE COMMUNALE 4 | T30: FR | U30: '21 | V30: '21320 | W30: CREANCEY | X30: CASSE LIONEL | Y30: 12 AVENUE DE VERDUN | AA30: FR | AB30: '94 | AC30: '94410 | AD30: SAINT MAURICE
B31: =IF(O31="","Frêt",_xlfn.XLOOKUP(O31,Catégories!A:A,Catégories!B:B,"inconnu")) -> Frêt | C31: =RIGHT(LOOKUP(L31,'Recherche tracking'!A:A,'Recherche tracking'!B:B),16) -> 2543814314751261 | D31: 202606 | E31: 51 | F31: 1085442 | G31: '03814314 | H31: '03814314 | I31: ENV | J31: ' | K31: 20260601 | L31: E20260601123359 | M31: J18 | N31: 6.8 | P31: 5.71 | Q31: LARUCHE | R31: VOIE COMMUNALE 4 | T31: FR | U31: '21 | V31: '21320 | W31: CREANCEY | X31: CHRISTOPHE DENNIEL | Y31: 87 GRANDE RUE | AA31: FR | AB31: '25 | AC31: '25000 | AD31: BESANCON
B32: =IF(O32="","Frêt",_xlfn.XLOOKUP(O32,Catégories!A:A,Catégories!B:B,"inconnu")) -> Frêt | C32: =RIGHT(LOOKUP(L32,'Recherche tracking'!A:A,'Recherche tracking'!B:B),16) -> 2543814314751261 | D32: 202606 | E32: 51 | F32: 1085442 | G32: '03814314 | H32: '03814314 | I32: COL | J32: '2543814314751261 | K32: 20260601 | L32: E20260601123359 | M32: J18 | N32: 6.8 | P32: 0 | Q32: LARUCHE | R32: VOIE COMMUNALE 4 | T32: FR | U32: '21 | V32: '21320 | W32: CREANCEY | X32: CHRISTOPHE DENNIEL | Y32: 87 GRANDE RUE | AA32: FR | AB32: '25 | AC32: '25000 | AD32: BESANCON
B33: =IF(O33="","Frêt",_xlfn.XLOOKUP(O33,Catégories!A:A,Catégories!B:B,"inconnu")) -> Frêt | C33: =RIGHT(LOOKUP(L33,'Recherche tracking'!A:A,'Recherche tracking'!B:B),16) -> 2543814314751261 | D33: 202606 | E33: 51 | F33: 1085442 | G33: '03814314 | H33: '03814314 | I33: CPC | J33: '2543814314751261 | K33: 20260601 | L33: E20260601123359 | N33: 6.8 | O33: RS | P33: 0 | Q33: LARUCHE | R33: VOIE COMMUNALE 4 | T33: FR | U33: '21 | V33: '21320 | W33: CREANCEY | X33: CHRISTOPHE DENNIEL | Y33: 87 GRANDE RUE | AA33: FR | AB33: '25 | AC33: '25000 | AD33: BESANCON
B34: =IF(O34="","Frêt",_xlfn.XLOOKUP(O34,Catégories!A:A,Catégories!B:B,"inconnu")) -> Frêt | C34: =RIGHT(LOOKUP(L34,'Recherche tracking'!A:A,'Recherche tracking'!B:B),16) -> 8043814314751285 | D34: 202606 | E34: 51 | F34: 1085442 | G34: '03814314 | H34: '03814314 | I34: ENV | J34: ' | K34: 20260601 | L34: E20260601123361 | M34: J18 | N34: 6.8 | P34: 5.71 | Q34: LARUCHE | R34: VOIE COMMUNALE 4 | T34: FR | U34: '21 | V34: '21320 | W34: CREANCEY | X34: DELABYE VIRGINIE | Y34: 14 RUE DES VERGEAUX | AA34: FR | AB34: '80 | AC34: '80000 | AD34: AMIENS
B35: =IF(O35="","Frêt",_xlfn.XLOOKUP(O35,Catégories!A:A,Catégories!B:B,"inconnu")) -> Frêt | C35: =RIGHT(LOOKUP(L35,'Recherche tracking'!A:A,'Recherche tracking'!B:B),16) -> 8043814314751285 | D35: 202606 | E35: 51 | F35: 1085442 | G35: '03814314 | H35: '03814314 | I35: COL | J35: '8043814314751285 | K35: 20260601 | L35: E20260601123361 | M35: J18 | N35: 6.8 | P35: 0 | Q35: LARUCHE | R35: VOIE COMMUNALE 4 | T35: FR | U35: '21 | V35: '21320 | W35: CREANCEY | X35: DELABYE VIRGINIE | Y35: 14 RUE DES VERGEAUX | AA35: FR | AB35: '80 | AC35: '80000 | AD35: AMIENS
B36: =IF(O36="","Frêt",_xlfn.XLOOKUP(O36,Catégories!A:A,Catégories!B:B,"inconnu")) -> Frêt | C36: =RIGHT(LOOKUP(L36,'Recherche tracking'!A:A,'Recherche tracking'!B:B),16) -> 8043814314751285 | D36: 202606 | E36: 51 | F36: 1085442 | G36: '03814314 | H36: '03814314 | I36: CPC | J36: '8043814314751285 | K36: 20260601 | L36: E20260601123361 | N36: 6.8 | O36: RS | P36: 0 | Q36: LARUCHE | R36: VOIE COMMUNALE 4 | T36: FR | U36: '21 | V36: '21320 | W36: CREANCEY | X36: DELABYE VIRGINIE | Y36: 14 RUE DES VERGEAUX | AA36: FR | AB36: '80 | AC36: '80000 | AD36: AMIENS
B37: =IF(O37="","Frêt",_xlfn.XLOOKUP(O37,Catégories!A:A,Catégories!B:B,"inconnu")) -> Frêt | C37: =RIGHT(LOOKUP(L37,'Recherche tracking'!A:A,'Recherche tracking'!B:B),16) -> 7143814314751103 | D37: 202606 | E37: 51 | F37: 1085442 | G37: '03814314 | H37: '03814314 | I37: ENV | J37: ' | K37: 20260601 | L37: E20260601123362 | M37: J18 | N37: 2.9 | P37: 4.67 | Q37: LARUCHE | R37: VOIE COMMUNALE 4 | T37: FR | U37: '21 | V37: '21320 | W37: CREANCEY | X37: DELFORGE STEPHANIE | Y37: 43 RUE SIGORGNE | AA37: FR | AB37: '71 | AC37: '71000 | AD37: MACON
B38: =IF(O38="","Frêt",_xlfn.XLOOKUP(O38,Catégories!A:A,Catégories!B:B,"inconnu")) -> Frêt | C38: =RIGHT(LOOKUP(L38,'Recherche tracking'!A:A,'Recherche tracking'!B:B),16) -> 7143814314751103 | D38: 202606 | E38: 51 | F38: 1085442 | G38: '03814314 | H38: '03814314 | I38: COL | J38: '7143814314751103 | K38: 20260601 | L38: E20260601123362 | M38: J18 | N38: 2.9 | P38: 0 | Q38: LARUCHE | R38: VOIE COMMUNALE 4 | T38: FR | U38: '21 | V38: '21320 | W38: CREANCEY | X38: DELFORGE STEPHANIE | Y38: 43 RUE SIGORGNE | AA38: FR | AB38: '71 | AC38: '71000 | AD38: MACON
B39: =IF(O39="","Frêt",_xlfn.XLOOKUP(O39,Catégories!A:A,Catégories!B:B,"inconnu")) -> Frêt | C39: =RIGHT(LOOKUP(L39,'Recherche tracking'!A:A,'Recherche tracking'!B:B),16) -> 7143814314751103 | D39: 202606 | E39: 51 | F39: 1085442 | G39: '03814314 | H39: '03814314 | I39: CPC | J39: '7143814314751103 | K39: 20260601 | L39: E20260601123362 | N39: 2.9 | O39: RS | P39: 0 | Q39: LARUCHE | R39: VOIE COMMUNALE 4 | T39: FR | U39: '21 | V39: '21320 | W39: CREANCEY | X39: DELFORGE STEPHANIE | Y39: 43 RUE SIGORGNE | AA39: FR | AB39: '71 | AC39: '71000 | AD39: MACON
B40: =IF(O40="","Frêt",_xlfn.XLOOKUP(O40,Catégories!A:A,Catégories!B:B,"inconnu")) -> Frêt | C40: =RIGHT(LOOKUP(L40,'Recherche tracking'!A:A,'Recherche tracking'!B:B),16) -> 6343814314751230 | D40: 202606 | E40: 51 | F40: 1085442 | G40: '03814314 | H40: '03814314 | I40: ENV | J40: ' | K40: 20260601 | L40: E20260601123364 | M40: J18 | N40: 2.9 | P40: 4.67 | Q40: LARUCHE | R40: VOIE COMMUNALE 4 | T40: FR | U40: '21 | V40: '21320 | W40: CREANCEY | X40: GUBERT PAULINE | Y40: 7 RUE DES TROENES | AA40: FR | AB40: '63 | AC40: '63500 | AD40: ISSOIRE
B41: =IF(O41="","Frêt",_xlfn.XLOOKUP(O41,Catégories!A:A,Catégories!B:B,"inconnu")) -> Frêt | C41: =RIGHT(LOOKUP(L41,'Recherche tracking'!A:A,'Recherche tracking'!B:B),16) -> 6343814314751230 | D41: 202606 | E41: 51 | F41: 1085442 | G41: '03814314 | H41: '03814314 | I41: COL | J41: '6343814314751230 | K41: 20260601 | L41: E20260601123364 | M41: J18 | N41: 2.9 | P41: 0 | Q41: LARUCHE | R41: VOIE COMMUNALE 4 | T41: FR | U41: '21 | V41: '21320 | W41: CREANCEY | X41: GUBERT PAULINE | Y41: 7 RUE DES TROENES | AA41: FR | AB41: '63 | AC41: '63500 | AD41: ISSOIRE
B42: =IF(O42="","Frêt",_xlfn.XLOOKUP(O42,Catégories!A:A,Catégories!B:B,"inconnu")) -> Frêt | C42: =RIGHT(LOOKUP(L42,'Recherche tracking'!A:A,'Recherche tracking'!B:B),16) -> 6343814314751230 | D42: 202606 | E42: 51 | F42: 1085442 | G42: '03814314 | H42: '03814314 | I42: CPC | J42: '6343814314751230 | K42: 20260601 | L42: E20260601123364 | N42: 2.9 | O42: RS | P42: 0 | Q42: LARUCHE | R42: VOIE COMMUNALE 4 | T42: FR | U42: '21 | V42: '21320 | W42: CREANCEY | X42: GUBERT PAULINE | Y42: 7 RUE DES TROENES | AA42: FR | AB42: '63 | AC42: '63500 | AD42: ISSOIRE
B43: =IF(O43="","Frêt",_xlfn.XLOOKUP(O43,Catégories!A:A,Catégories!B:B,"inconnu")) -> Frêt | C43: =RIGHT(LOOKUP(L43,'Recherche tracking'!A:A,'Recherche tracking'!B:B),16) -> 7543814314751190 | D43: 202606 | E43: 51 | F43: 1085442 | G43: '03814314 | H43: '03814314 | I43: ENV | J43: ' | K43: 20260601 | L43: E20260601123366 | M43: J18 | N43: 3.6 | P43: 4.93 | Q43: LARUCHE | R43: VOIE COMMUNALE 4 | T43: FR | U43: '21 | V43: '21320 | W43: CREANCEY | X43: KEREBEL MARIANNE | Y43: 57 RUE DE LA JONQUIERE | AA43: FR | AB43: '75 | AC43: '75017 | AD43: PARIS
B44: =IF(O44="","Frêt",_xlfn.XLOOKUP(O44,Catégories!A:A,Catégories!B:B,"inconnu")) -> Frêt | C44: =RIGHT(LOOKUP(L44,'Recherche tracking'!A:A,'Recherche tracking'!B:B),16) -> 7543814314751190 | D44: 202606 | E44: 51 | F44: 1085442 | G44: '03814314 | H44: '03814314 | I44: COL | J44: '7543814314751190 | K44: 20260601 | L44: E20260601123366 | M44: J18 | N44: 3.6 | P44: 0 | Q44: LARUCHE | R44: VOIE COMMUNALE 4 | T44: FR | U44: '21 | V44: '21320 | W44: CREANCEY | X44: KEREBEL MARIANNE | Y44: 57 RUE DE LA JONQUIERE | AA44: FR | AB44: '75 | AC44: '75017 | AD44: PARIS
B45: =IF(O45="","Frêt",_xlfn.XLOOKUP(O45,Catégories!A:A,Catégories!B:B,"inconnu")) -> Frêt | C45: =RIGHT(LOOKUP(L45,'Recherche tracking'!A:A,'Recherche tracking'!B:B),16) -> 7543814314751190 | D45: 202606 | E45: 51 | F45: 1085442 | G45: '03814314 | H45: '03814314 | I45: CPC | J45: '7543814314751190 | K45: 20260601 | L45: E20260601123366 | N45: 3.6 | O45: RS | P45: 0 | Q45: LARUCHE | R45: VOIE COMMUNALE 4 | T45: FR | U45: '21 | V45: '21320 | W45: CREANCEY | X45: KEREBEL MARIANNE | Y45: 57 RUE DE LA JONQUIERE | AA45: FR | AB45: '75 | AC45: '75017 | AD45: PARIS
B46: =IF(O46="","Frêt",_xlfn.XLOOKUP(O46,Catégories!A:A,Catégories!B:B,"inconnu")) -> Frêt | C46: =RIGHT(LOOKUP(L46,'Recherche tracking'!A:A,'Recherche tracking'!B:B),16) -> 4443814314751220 | D46: 202606 | E46: 51 | F46: 1085442 | G46: '03814314 | H46: '03814314 | I46: ENV | J46: ' | K46: 20260601 | L46: E20260601123367 | M46: J18 | N46: 3.01 | P46: 4.93 | Q46: LARUCHE | R46: VOIE COMMUNALE 4 | T46: FR | U46: '21 | V46: '21320 | W46: CREANCEY | X46: LE DANTEC DELPHINE | Y46: 1, RUE GRETRY | AA46: FR | AB46: '44 | AC46: '44000 | AD46: NANTES
B47: =IF(O47="","Frêt",_xlfn.XLOOKUP(O47,Catégories!A:A,Catégories!B:B,"inconnu")) -> Frêt | C47: =RIGHT(LOOKUP(L47,'Recherche tracking'!A:A,'Recherche tracking'!B:B),16) -> 4443814314751220 | D47: 202606 | E47: 51 | F47: 1085442 | G47: '03814314 | H47: '03814314 | I47: COL | J47: '4443814314751220 | K47: 20260601 | L47: E20260601123367 | M47: J18 | N47: 3.01 | P47: 0 | Q47: LARUCHE | R47: VOIE COMMUNALE 4 | T47: FR | U47: '21 | V47: '21320 | W47: CREANCEY | X47: LE DANTEC DELPHINE | Y47: 1, RUE GRETRY | AA47: FR | AB47: '44 | AC47: '44000 | AD47: NANTES
B48: =IF(O48="","Frêt",_xlfn.XLOOKUP(O48,Catégories!A:A,Catégories!B:B,"inconnu")) -> Frêt | C48: =RIGHT(LOOKUP(L48,'Recherche tracking'!A:A,'Recherche tracking'!B:B),16) -> 4443814314751220 | D48: 202606 | E48: 51 | F48: 1085442 | G48: '03814314 | H48: '03814314 | I48: CPC | J48: '4443814314751220 | K48: 20260601 | L48: E20260601123367 | N48: 3.01 | O48: RS | P48: 0 | Q48: LARUCHE | R48: VOIE COMMUNALE 4 | T48: FR | U48: '21 | V48: '21320 | W48: CREANCEY | X48: LE DANTEC DELPHINE | Y48: 1, RUE GRETRY | AA48: FR | AB48: '44 | AC48: '44000 | AD48: NANTES
B49: =IF(O49="","Frêt",_xlfn.XLOOKUP(O49,Catégories!A:A,Catégories!B:B,"inconnu")) -> Frêt | C49: =RIGHT(LOOKUP(L49,'Recherche tracking'!A:A,'Recherche tracking'!B:B),16) -> 0443814314751303 | D49: 202606 | E49: 51 | F49: 1085442 | G49: '03814314 | H49: '03814314 | I49: ENV | J49: ' | K49: 20260601 | L49: E20260601123369 | M49: J18 | N49: 1.6 | P49: 4.41 | Q49: LARUCHE | R49: VOIE COMMUNALE 4 | T49: FR | U49: '21 | V49: '21320 | W49: CREANCEY | X49: MARTIN FLORIANE | Y49: 11 PLACE DU SERRE | AA49: FR | AB49: '04 | AC49: '04870 | AD49: SAINT-MICHEL-L'OBSERVATOIRE
B50: =IF(O50="","Frêt",_xlfn.XLOOKUP(O50,Catégories!A:A,Catégories!B:B,"inconnu")) -> Frêt | C50: =RIGHT(LOOKUP(L50,'Recherche tracking'!A:A,'Recherche tracking'!B:B),16) -> 0443814314751303 | D50: 202606 | E50: 51 | F50: 1085442 | G50: '03814314 | H50: '03814314 | I50: COL | J50: '0443814314751303 | K50: 20260601 | L50: E20260601123369 | M50: J18 | N50: 1.6 | P50: 0 | Q50: LARUCHE | R50: VOIE COMMUNALE 4 | T50: FR | U50: '21 | V50: '21320 | W50: CREANCEY | X50: MARTIN FLORIANE | Y50: 11 PLACE DU SERRE | AA50: FR | AB50: '04 | AC50: '04870 | AD50: SAINT-MICHEL-L'OBSERVATOIRE
B51: =IF(O51="","Frêt",_xlfn.XLOOKUP(O51,Catégories!A:A,Catégories!B:B,"inconnu")) -> Frêt | C51: =RIGHT(LOOKUP(L51,'Recherche tracking'!A:A,'Recherche tracking'!B:B),16) -> 0443814314751303 | D51: 202606 | E51: 51 | F51: 1085442 | G51: '03814314 | H51: '03814314 | I51: CPC | J51: '0443814314751303 | K51: 20260601 | L51: E20260601123369 | N51: 1.6 | O51: RS | P51: 0 | Q51: LARUCHE | R51: VOIE COMMUNALE 4 | T51: FR | U51: '21 | V51: '21320 | W51: CREANCEY | X51: MARTIN FLORIANE | Y51: 11 PLACE DU SERRE | AA51: FR | AB51: '04 | AC51: '04870 | AD51: SAINT-MICHEL-L'OBSERVATOIRE
B52: =IF(O52="","Frêt",_xlfn.XLOOKUP(O52,Catégories!A:A,Catégories!B:B,"inconnu")) -> Frêt | C52: =RIGHT(LOOKUP(L52,'Recherche tracking'!A:A,'Recherche tracking'!B:B),16) -> 7543814314751321 | D52: 202606 | E52: 51 | F52: 1085442 | G52: '03814314 | H52: '03814314 | I52: ENV | J52: ' | K52: 20260601 | L52: E20260601123370 | M52: J18 | N52: 0.5 | P52: 4.15 | Q52: LARUCHE | R52: VOIE COMMUNALE 4 | T52: FR | U52: '21 | V52: '21320 | W52: CREANCEY | X52: NONNOT-CAPRON FLORENCE | Y52: 25/31 RUE PRADIER | Z52: ESC.F-CAPRON | AA52: FR | AB52: '75 | AC52: '75019 | AD52: PARIS
B53: =IF(O53="","Frêt",_xlfn.XLOOKUP(O53,Catégories!A:A,Catégories!B:B,"inconnu")) -> Frêt | C53: =RIGHT(LOOKUP(L53,'Recherche tracking'!A:A,'Recherche tracking'!B:B),16) -> 7543814314751321 | D53: 202606 | E53: 51 | F53: 1085442 | G53: '03814314 | H53: '03814314 | I53: COL | J53: '7543814314751321 | K53: 20260601 | L53: E20260601123370 | M53: J18 | N53: 0.5 | P53: 0 | Q53: LARUCHE | R53: VOIE COMMUNALE 4 | T53: FR | U53: '21 | V53: '21320 | W53: CREANCEY | X53: NONNOT-CAPRON FLORENCE | Y53: 25/31 RUE PRADIER | Z53: ESC.F-CAPRON | AA53: FR | AB53: '75 | AC53: '75019 | AD53: PARIS
B54: =IF(O54="","Frêt",_xlfn.XLOOKUP(O54,Catégories!A:A,Catégories!B:B,"inconnu")) -> Frêt | C54: =RIGHT(LOOKUP(L54,'Recherche tracking'!A:A,'Recherche tracking'!B:B),16) -> 7543814314751321 | D54: 202606 | E54: 51 | F54: 1085442 | G54: '03814314 | H54: '03814314 | I54: CPC | J54: '7543814314751321 | K54: 20260601 | L54: E20260601123370 | N54: 0.5 | O54: RS | P54: 0 | Q54: LARUCHE | R54: VOIE COMMUNALE 4 | T54: FR | U54: '21 | V54: '21320 | W54: CREANCEY | X54: NONNOT-CAPRON FLORENCE | Y54: 25/31 RUE PRADIER | Z54: ESC.F-CAPRON | AA54: FR | AB54: '75 | AC54: '75019 | AD54: PARIS
B55: =IF(O55="","Frêt",_xlfn.XLOOKUP(O55,Catégories!A:A,Catégories!B:B,"inconnu")) -> Frêt | C55: =RIGHT(LOOKUP(L55,'Recherche tracking'!A:A,'Recherche tracking'!B:B),16) -> 3143814314751245 | D55: 202606 | E55: 51 | F55: 1085442 | G55: '03814314 | H55: '03814314 | I55: ENV | J55: ' | K55: 20260601 | L55: E20260601123371 | M55: J18 | N55: 6.01 | P55: 5.71 | Q55: LARUCHE | R55: VOIE COMMUNALE 4 | T55: FR | U55: '21 | V55: '21320 | W55: CREANCEY | X55: POUSSON FRANCOIS | Y55: 6 RUE DE LA BOURSE | AA55: FR | AB55: '31 | AC55: '31000 | AD55: TOULOUSE
B56: =IF(O56="","Frêt",_xlfn.XLOOKUP(O56,Catégories!A:A,Catégories!B:B,"inconnu")) -> Frêt | C56: =RIGHT(LOOKUP(L56,'Recherche tracking'!A:A,'Recherche tracking'!B:B),16) -> 3143814314751245 | D56: 202606 | E56: 51 | F56: 1085442 | G56: '03814314 | H56: '03814314 | I56: COL | J56: '3143814314751245 | K56: 20260601 | L56: E20260601123371 | M56: J18 | N56: 6.01 | P56: 0 | Q56: LARUCHE | R56: VOIE COMMUNALE 4 | T56: FR | U56: '21 | V56: '21320 | W56: CREANCEY | X56: POUSSON FRANCOIS | Y56: 6 RUE DE LA BOURSE | AA56: FR | AB56: '31 | AC56: '31000 | AD56: TOULOUSE
B57: =IF(O57="","Frêt",_xlfn.XLOOKUP(O57,Catégories!A:A,Catégories!B:B,"inconnu")) -> Frêt | C57: =RIGHT(LOOKUP(L57,'Recherche tracking'!A:A,'Recherche tracking'!B:B),16) -> 3143814314751245 | D57: 202606 | E57: 51 | F57: 1085442 | G57: '03814314 | H57: '03814314 | I57: CPC | J57: '3143814314751245 | K57: 20260601 | L57: E20260601123371 | N57: 6.01 | O57: RS | P57: 0 | Q57: LARUCHE | R57: VOIE COMMUNALE 4 | T57: FR | U57: '21 | V57: '21320 | W57: CREANCEY | X57: POUSSON FRANCOIS | Y57: 6 RUE DE LA BOURSE | AA57: FR | AB57: '31 | AC57: '31000 | AD57: TOULOUSE
B58: =IF(O58="","Frêt",_xlfn.XLOOKUP(O58,Catégories!A:A,Catégories!B:B,"inconnu")) -> Frêt | C58: =RIGHT(LOOKUP(L58,'Recherche tracking'!A:A,'Recherche tracking'!B:B),16) -> 3643814314751275 | D58: 202606 | E58: 51 | F58: 1085442 | G58: '03814314 | H58: '03814314 | I58: ENV | J58: ' | K58: 20260601 | L58: E20260601123373 | M58: J18 | N58: 3.01 | P58: 4.93 | Q58: LARUCHE | R58: VOIE COMMUNALE 4 | T58: FR | U58: '21 | V58: '21320 | W58: CREANCEY | X58: RENOUX MARINA | Y58: 92 RUE GRANDE | AA58: FR | AB58: '36 | AC58: '36000 | AD58: CHATEAUROUX
B59: =IF(O59="","Frêt",_xlfn.XLOOKUP(O59,Catégories!A:A,Catégories!B:B,"inconnu")) -> Frêt | C59: =RIGHT(LOOKUP(L59,'Recherche tracking'!A:A,'Recherche tracking'!B:B),16) -> 3643814314751275 | D59: 202606 | E59: 51 | F59: 1085442 | G59: '03814314 | H59: '03814314 | I59: COL | J59: '3643814314751275 | K59: 20260601 | L59: E20260601123373 | M59: J18 | N59: 3.01 | P59: 0 | Q59: LARUCHE | R59: VOIE COMMUNALE 4 | T59: FR | U59: '21 | V59: '21320 | W59: CREANCEY | X59: RENOUX MARINA | Y59: 92 RUE GRANDE | AA59: FR | AB59: '36 | AC59: '36000 | AD59: CHATEAUROUX
B60: =IF(O60="","Frêt",_xlfn.XLOOKUP(O60,Catégories!A:A,Catégories!B:B,"inconnu")) -> Frêt | C60: =RIGHT(LOOKUP(L60,'Recherche tracking'!A:A,'Recherche tracking'!B:B),16) -> 3643814314751275 | D60: 202606 | E60: 51 | F60: 1085442 | G60: '03814314 | H60: '03814314 | I60: CPC | J60: '3643814314751275 | K60: 20260601 | L60: E20260601123373 | N60: 3.01 | O60: RS | P60: 0 | Q60: LARUCHE | R60: VOIE COMMUNALE 4 | T60: FR | U60: '21 | V60: '21320 | W60: CREANCEY | X60: RENOUX MARINA | Y60: 92 RUE GRANDE | AA60: FR | AB60: '36 | AC60: '36000 | AD60: CHATEAUROUX
B61: =IF(O61="","Frêt",_xlfn.XLOOKUP(O61,Catégories!A:A,Catégories!B:B,"inconnu")) -> Frêt | C61: =RIGHT(LOOKUP(L61,'Recherche tracking'!A:A,'Recherche tracking'!B:B),16) -> 7543814314751298 | D61: 202606 | E61: 51 | F61: 1085442 | G61: '03814314 | H61: '03814314 | I61: ENV | J61: ' | K61: 20260601 | L61: E20260601123374 | M61: J18 | N61: 3.5 | P61: 4.93 | Q61: LARUCHE | R61: VOIE COMMUNALE 4 | T61: FR | U61: '21 | V61: '21320 | W61: CREANCEY | X61: ROSSI MILENA | Y61: 56 TURBIGO | AA61: FR | AB61: '75 | AC61: '75003 | AD61: PARIS
B62: =IF(O62="","Frêt",_xlfn.XLOOKUP(O62,Catégories!A:A,Catégories!B:B,"inconnu")) -> Frêt | C62: =RIGHT(LOOKUP(L62,'Recherche tracking'!A:A,'Recherche tracking'!B:B),16) -> 7543814314751298 | D62: 202606 | E62: 51 | F62: 1085442 | G62: '03814314 | H62: '03814314 | I62: COL | J62: '7543814314751298 | K62: 20260601 | L62: E20260601123374 | M62: J18 | N62: 3.5 | P62: 0 | Q62: LARUCHE | R62: VOIE COMMUNALE 4 | T62: FR | U62: '21 | V62: '21320 | W62: CREANCEY | X62: ROSSI MILENA | Y62: 56 TURBIGO | AA62: FR | AB62: '75 | AC62: '75003 | AD62: PARIS
B63: =IF(O63="","Frêt",_xlfn.XLOOKUP(O63,Catégories!A:A,Catégories!B:B,"inconnu")) -> Frêt | C63: =RIGHT(LOOKUP(L63,'Recherche tracking'!A:A,'Recherche tracking'!B:B),16) -> 7543814314751298 | D63: 202606 | E63: 51 | F63: 1085442 | G63: '03814314 | H63: '03814314 | I63: CPC | J63: '7543814314751298 | K63: 20260601 | L63: E20260601123374 | N63: 3.5 | O63: RS | P63: 0 | Q63: LARUCHE | R63: VOIE COMMUNALE 4 | T63: FR | U63: '21 | V63: '21320 | W63: CREANCEY | X63: ROSSI MILENA | Y63: 56 TURBIGO | AA63: FR | AB63: '75 | AC63: '75003 | AD63: PARIS
B64: =IF(O64="","Frêt",_xlfn.XLOOKUP(O64,Catégories!A:A,Catégories!B:B,"inconnu")) -> Frêt | C64: =RIGHT(LOOKUP(L64,'Recherche tracking'!A:A,'Recherche tracking'!B:B),16) -> 4543814314751215 | D64: 202606 | E64: 51 | F64: 1085442 | G64: '03814314 | H64: '03814314 | I64: ENV | J64: ' | K64: 20260601 | L64: E20260601123375 | M64: J18 | N64: 6.01 | P64: 5.71 | Q64: LARUCHE | R64: VOIE COMMUNALE 4 | T64: FR | U64: '21 | V64: '21320 | W64: CREANCEY | X64: VERGNE ROD | Y64: GALERIE CHATELET | AA64: FR | AB64: '45 | AC64: '45000 | AD64: ORLEANS
B65: =IF(O65="","Frêt",_xlfn.XLOOKUP(O65,Catégories!A:A,Catégories!B:B,"inconnu")) -> Frêt | C65: =RIGHT(LOOKUP(L65,'Recherche tracking'!A:A,'Recherche tracking'!B:B),16) -> 4543814314751215 | D65: 202606 | E65: 51 | F65: 1085442 | G65: '03814314 | H65: '03814314 | I65: COL | J65: '4543814314751215 | K65: 20260601 | L65: E20260601123375 | M65: J18 | N65: 6.01 | P65: 0 | Q65: LARUCHE | R65: VOIE COMMUNALE 4 | T65: FR | U65: '21 | V65: '21320 | W65: CREANCEY | X65: VERGNE ROD | Y65: GALERIE CHATELET | AA65: FR | AB65: '45 | AC65: '45000 | AD65: ORLEANS
B66: =IF(O66="","Frêt",_xlfn.XLOOKUP(O66,Catégories!A:A,Catégories!B:B,"inconnu")) -> Frêt | C66: =RIGHT(LOOKUP(L66,'Recherche tracking'!A:A,'Recherche tracking'!B:B),16) -> 4543814314751215 | D66: 202606 | E66: 51 | F66: 1085442 | G66: '03814314 | H66: '03814314 | I66: CPC | J66: '4543814314751215 | K66: 20260601 | L66: E20260601123375 | N66: 6.01 | O66: RS | P66: 0 | Q66: LARUCHE | R66: VOIE COMMUNALE 4 | T66: FR | U66: '21 | V66: '21320 | W66: CREANCEY | X66: VERGNE ROD | Y66: GALERIE CHATELET | AA66: FR | AB66: '45 | AC66: '45000 | AD66: ORLEANS
B67: =IF(O67="","Frêt",_xlfn.XLOOKUP(O67,Catégories!A:A,Catégories!B:B,"inconnu")) -> Frêt | C67: =RIGHT(LOOKUP(L67,'Recherche tracking'!A:A,'Recherche tracking'!B:B),16) -> 8543814314751258 | D67: 202606 | E67: 51 | F67: 1085442 | G67: '03814314 | H67: '03814314 | I67: ENV | J67: ' | K67: 20260601 | L67: E20260601208626 | M67: J18 | N67: 3.2 | P67: 4.93 | Q67: LARUCHE | R67: VOIE COMMUNALE 4 | T67: FR | U67: '21 | V67: '21320 | W67: CREANCEY | X67: COUGNAUD MARINE | Y67: 8 RUE THIERS, COSY CAUSETTE SARL | Z67: DECOU | AA67: FR | AB67: '85 | AC67: '85000 | AD67: LA ROCHE SUR YON
B68: =IF(O68="","Frêt",_xlfn.XLOOKUP(O68,Catégories!A:A,Catégories!B:B,"inconnu")) -> Frêt | C68: =RIGHT(LOOKUP(L68,'Recherche tracking'!A:A,'Recherche tracking'!B:B),16) -> 8543814314751258 | D68: 202606 | E68: 51 | F68: 1085442 | G68: '03814314 | H68: '03814314 | I68: COL | J68: '8543814314751258 | K68: 20260601 | L68: E20260601208626 | M68: J18 | N68: 3.2 | P68: 0 | Q68: LARUCHE | R68: VOIE COMMUNALE 4 | T68: FR | U68: '21 | V68: '21320 | W68: CREANCEY | X68: COUGNAUD MARINE | Y68: 8 RUE THIERS, COSY CAUSETTE SARL | Z68: DECOU | AA68: FR | AB68: '85 | AC68: '85000 | AD68: LA ROCHE SUR YON
B69: =IF(O69="","Frêt",_xlfn.XLOOKUP(O69,Catégories!A:A,Catégories!B:B,"inconnu")) -> Frêt | C69: =RIGHT(LOOKUP(L69,'Recherche tracking'!A:A,'Recherche tracking'!B:B),16) -> 8543814314751258 | D69: 202606 | E69: 51 | F69: 1085442 | G69: '03814314 | H69: '03814314 | I69: CPC | J69: '8543814314751258 | K69: 20260601 | L69: E20260601208626 | N69: 3.2 | O69: RS | P69: 0 | Q69: LARUCHE | R69: VOIE COMMUNALE 4 | T69: FR | U69: '21 | V69: '21320 | W69: CREANCEY | X69: COUGNAUD MARINE | Y69: 8 RUE THIERS, COSY CAUSETTE SARL | Z69: DECOU | AA69: FR | AB69: '85 | AC69: '85000 | AD69: LA ROCHE SUR YON
B70: =IF(O70="","Frêt",_xlfn.XLOOKUP(O70,Catégories!A:A,Catégories!B:B,"inconnu")) -> Frêt | C70: =RIGHT(LOOKUP(L70,'Recherche tracking'!A:A,'Recherche tracking'!B:B),16) -> 8443814314751117 | D70: 202606 | E70: 51 | F70: 1085442 | G70: '03814314 | H70: '03814314 | I70: ENV | J70: ' | K70: 20260601 | L70: E20260601208627 | M70: J18 | N70: 3.01 | P70: 4.93 | Q70: LARUCHE | R70: VOIE COMMUNALE 4 | T70: FR | U70: '21 | V70: '21320 | W70: CREANCEY | X70: GASTINEAU ALEXANDRE | Y70: 87 RUE JOSEPH VERNET | AA70: FR | AB70: '84 | AC70: '84000 | AD70: AVIGNON
B71: =IF(O71="","Frêt",_xlfn.XLOOKUP(O71,Catégories!A:A,Catégories!B:B,"inconnu")) -> Frêt | C71: =RIGHT(LOOKUP(L71,'Recherche tracking'!A:A,'Recherche tracking'!B:B),16) -> 8443814314751117 | D71: 202606 | E71: 51 | F71: 1085442 | G71: '03814314 | H71: '03814314 | I71: COL | J71: '8443814314751117 | K71: 20260601 | L71: E20260601208627 | M71: J18 | N71: 3.01 | P71: 0 | Q71: LARUCHE | R71: VOIE COMMUNALE 4 | T71: FR | U71: '21 | V71: '21320 | W71: CREANCEY | X71: GASTINEAU ALEXANDRE | Y71: 87 RUE JOSEPH VERNET | AA71: FR | AB71: '84 | AC71: '84000 | AD71: AVIGNON
B72: =IF(O72="","Frêt",_xlfn.XLOOKUP(O72,Catégories!A:A,Catégories!B:B,"inconnu")) -> Frêt | C72: =RIGHT(LOOKUP(L72,'Recherche tracking'!A:A,'Recherche tracking'!B:B),16) -> 8443814314751117 | D72: 202606 | E72: 51 | F72: 1085442 | G72: '03814314 | H72: '03814314 | I72: CPC | J72: '8443814314751117 | K72: 20260601 | L72: E20260601208627 | N72: 3.01 | O72: RS | P72: 0 | Q72: LARUCHE | R72: VOIE COMMUNALE 4 | T72: FR | U72: '21 | V72: '21320 | W72: CREANCEY | X72: GASTINEAU ALEXANDRE | Y72: 87 RUE JOSEPH VERNET | AA72: FR | AB72: '84 | AC72: '84000 | AD72: AVIGNON
B73: =IF(O73="","Frêt",_xlfn.XLOOKUP(O73,Catégories!A:A,Catégories!B:B,"inconnu")) -> Frêt | C73: =RIGHT(LOOKUP(L73,'Recherche tracking'!A:A,'Recherche tracking'!B:B),16) -> 3243814314751311 | D73: 202606 | E73: 51 | F73: 1085442 | G73: '03814314 | H73: '03814314 | I73: ENV | J73: ' | K73: 20260601 | L73: E20260601208628 | M73: J18 | N73: 0.5 | P73: 4.15 | Q73: LARUCHE | R73: VOIE COMMUNALE 4 | T73: FR | U73: '21 | V73: '21320 | W73: CREANCEY | X73: JOURDANT ANNE | Y73: 1 IMPASSE DES OLIVIERS | AA73: FR | AB73: '32 | AC73: '32600 | AD73: RAZENGUES
B74: =IF(O74="","Frêt",_xlfn.XLOOKUP(O74,Catégories!A:A,Catégories!B:B,"inconnu")) -> Frêt | C74: =RIGHT(LOOKUP(L74,'Recherche tracking'!A:A,'Recherche tracking'!B:B),16) -> 3243814314751311 | D74: 202606 | E74: 51 | F74: 1085442 | G74: '03814314 | H74: '03814314 | I74: COL | J74: '3243814314751311 | K74: 20260601 | L74: E20260601208628 | M74: J18 | N74: 0.5 | P74: 0 | Q74: LARUCHE | R74: VOIE COMMUNALE 4 | T74: FR | U74: '21 | V74: '21320 | W74: CREANCEY | X74: JOURDANT ANNE | Y74: 1 IMPASSE DES OLIVIERS | AA74: FR | AB74: '32 | AC74: '32600 | AD74: RAZENGUES
B75: =IF(O75="","Frêt",_xlfn.XLOOKUP(O75,Catégories!A:A,Catégories!B:B,"inconnu")) -> Frêt | C75: =RIGHT(LOOKUP(L75,'Recherche tracking'!A:A,'Recherche tracking'!B:B),16) -> 3243814314751311 | D75: 202606 | E75: 51 | F75: 1085442 | G75: '03814314 | H75: '03814314 | I75: CPC | J75: '3243814314751311 | K75: 20260601 | L75: E20260601208628 | N75: 0.5 | O75: RS | P75: 0 | Q75: LARUCHE | R75: VOIE COMMUNALE 4 | T75: FR | U75: '21 | V75: '21320 | W75: CREANCEY | X75: JOURDANT ANNE | Y75: 1 IMPASSE DES OLIVIERS | AA75: FR | AB75: '32 | AC75: '32600 | AD75: RAZENGUES
B76: =IF(O76="","Frêt",_xlfn.XLOOKUP(O76,Catégories!A:A,Catégories!B:B,"inconnu")) -> Frêt | C76: =RIGHT(LOOKUP(L76,'Recherche tracking'!A:A,'Recherche tracking'!B:B),16) -> 4943814314751042 | D76: 202606 | E76: 51 | F76: 1085442 | G76: '03814314 | H76: '03814314 | I76: ENV | J76: ' | K76: 20260601 | L76: E20260601208629 | M76: J18 | N76: 51.6 | P76: 17.41 | Q76: LARUCHE | R76: VOIE COMMUNALE 4 | T76: FR | U76: '21 | V76: '21320 | W76: CREANCEY | X76: MARIA EMMANUEL | Y76: GORGUETTE 57 RUE DU MAIL | AA76: FR | AB76: '49 | AC76: '49100 | AD76: ANGERS
B77: =IF(O77="","Frêt",_xlfn.XLOOKUP(O77,Catégories!A:A,Catégories!B:B,"inconnu")) -> Frêt | C77: =RIGHT(LOOKUP(L77,'Recherche tracking'!A:A,'Recherche tracking'!B:B),16) -> 4943814314751042 | D77: 202606 | E77: 51 | F77: 1085442 | G77: '03814314 | H77: '03814314 | I77: COL | J77: '4943814314751020 | K77: 20260601 | L77: E20260601208629 | M77: J18 | N77: 17.2 | P77: 0 | Q77: LARUCHE | R77: VOIE COMMUNALE 4 | T77: FR | U77: '21 | V77: '21320 | W77: CREANCEY | X77: MARIA EMMANUEL | Y77: GORGUETTE 57 RUE DU MAIL | AA77: FR | AB77: '49 | AC77: '49100 | AD77: ANGERS
B78: =IF(O78="","Frêt",_xlfn.XLOOKUP(O78,Catégories!A:A,Catégories!B:B,"inconnu")) -> Frêt | C78: =RIGHT(LOOKUP(L78,'Recherche tracking'!A:A,'Recherche tracking'!B:B),16) -> 4943814314751042 | D78: 202606 | E78: 51 | F78: 1085442 | G78: '03814314 | H78: '03814314 | I78: CPC | J78: '4943814314751020 | K78: 20260601 | L78: E20260601208629 | N78: 17.2 | O78: RS | P78: 0 | Q78: LARUCHE | R78: VOIE COMMUNALE 4 | T78: FR | U78: '21 | V78: '21320 | W78: CREANCEY | X78: MARIA EMMANUEL | Y78: GORGUETTE 57 RUE DU MAIL | AA78: FR | AB78: '49 | AC78: '49100 | AD78: ANGERS
B79: =IF(O79="","Frêt",_xlfn.XLOOKUP(O79,Catégories!A:A,Catégories!B:B,"inconnu")) -> Frêt | C79: =RIGHT(LOOKUP(L79,'Recherche tracking'!A:A,'Recherche tracking'!B:B),16) -> 4943814314751042 | D79: 202606 | E79: 51 | F79: 1085442 | G79: '03814314 | H79: '03814314 | I79: COL | J79: '4943814314751036 | K79: 20260601 | L79: E20260601208629 | M79: J18 | N79: 17.2 | P79: 0 | Q79: LARUCHE | R79: VOIE COMMUNALE 4 | T79: FR | U79: '21 | V79: '21320 | W79: CREANCEY | X79: MARIA EMMANUEL | Y79: GORGUETTE 57 RUE DU MAIL | AA79: FR | AB79: '49 | AC79: '49100 | AD79: ANGERS
B80: =IF(O80="","Frêt",_xlfn.XLOOKUP(O80,Catégories!A:A,Catégories!B:B,"inconnu")) -> Frêt | C80: =RIGHT(LOOKUP(L80,'Recherche tracking'!A:A,'Recherche tracking'!B:B),16) -> 4943814314751042 | D80: 202606 | E80: 51 | F80: 1085442 | G80: '03814314 | H80: '03814314 | I80: CPC | J80: '4943814314751036 | K80: 20260601 | L80: E20260601208629 | N80: 17.2 | O80: RS | P80: 0 | Q80: LARUCHE | R80: VOIE COMMUNALE 4 | T80: FR | U80: '21 | V80: '21320 | W80: CREANCEY | X80: MARIA EMMANUEL | Y80: GORGUETTE 57 RUE DU MAIL | AA80: FR | AB80: '49 | AC80: '49100 | AD80: ANGERS
B81: =IF(O81="","Frêt",_xlfn.XLOOKUP(O81,Catégories!A:A,Catégories!B:B,"inconnu")) -> Frêt | C81: =RIGHT(LOOKUP(L81,'Recherche tracking'!A:A,'Recherche tracking'!B:B),16) -> 4943814314751042 | D81: 202606 | E81: 51 | F81: 1085442 | G81: '03814314 | H81: '03814314 | I81: CPC | J81: '4943814314751036 | K81: 20260601 | L81: E20260601208629 | N81: 17.2 | O81: TMC | P81: 1 | Q81: LARUCHE | R81: VOIE COMMUNALE 4 | T81: FR | U81: '21 | V81: '21320 | W81: CREANCEY | X81: MARIA EMMANUEL | Y81: GORGUETTE 57 RUE DU MAIL | AA81: FR | AB81: '49 | AC81: '49100 | AD81: ANGERS
B82: =IF(O82="","Frêt",_xlfn.XLOOKUP(O82,Catégories!A:A,Catégories!B:B,"inconnu")) -> Frêt | C82: =RIGHT(LOOKUP(L82,'Recherche tracking'!A:A,'Recherche tracking'!B:B),16) -> 4943814314751042 | D82: 202606 | E82: 51 | F82: 1085442 | G82: '03814314 | H82: '03814314 | I82: COL | J82: '4943814314751042 | K82: 20260601 | L82: E20260601208629 | M82: J18 | N82: 17.2 | P82: 0 | Q82: LARUCHE | R82: VOIE COMMUNALE 4 | T82: FR | U82: '21 | V82: '21320 | W82: CREANCEY | X82: MARIA EMMANUEL | Y82: GORGUETTE 57 RUE DU MAIL | AA82: FR | AB82: '49 | AC82: '49100 | AD82: ANGERS
B83: =IF(O83="","Frêt",_xlfn.XLOOKUP(O83,Catégories!A:A,Catégories!B:B,"inconnu")) -> Frêt | C83: =RIGHT(LOOKUP(L83,'Recherche tracking'!A:A,'Recherche tracking'!B:B),16) -> 4943814314751042 | D83: 202606 | E83: 51 | F83: 1085442 | G83: '03814314 | H83: '03814314 | I83: CPC | J83: '4943814314751042 | K83: 20260601 | L83: E20260601208629 | N83: 17.2 | O83: RS | P83: 0 | Q83: LARUCHE | R83: VOIE COMMUNALE 4 | T83: FR | U83: '21 | V83: '21320 | W83: CREANCEY | X83: MARIA EMMANUEL | Y83: GORGUETTE 57 RUE DU MAIL | AA83: FR | AB83: '49 | AC83: '49100 | AD83: ANGERS
B84: =IF(O84="","Frêt",_xlfn.XLOOKUP(O84,Catégories!A:A,Catégories!B:B,"inconnu")) -> Frêt | C84: =RIGHT(LOOKUP(L84,'Recherche tracking'!A:A,'Recherche tracking'!B:B),16) -> 4943814314751042 | D84: 202606 | E84: 51 | F84: 1085442 | G84: '03814314 | H84: '03814314 | I84: CPC | J84: '4943814314751042 | K84: 20260601 | L84: E20260601208629 | N84: 17.2 | O84: TMC | P84: 1 | Q84: LARUCHE | R84: VOIE COMMUNALE 4 | T84: FR | U84: '21 | V84: '21320 | W84: CREANCEY | X84: MARIA EMMANUEL | Y84: GORGUETTE 57 RUE DU MAIL | AA84: FR | AB84: '49 | AC84: '49100 | AD84: ANGERS
B85: =IF(O85="","Frêt",_xlfn.XLOOKUP(O85,Catégories!A:A,Catégories!B:B,"inconnu")) -> Frêt | C85: =RIGHT(LOOKUP(L85,'Recherche tracking'!A:A,'Recherche tracking'!B:B),16) -> 7643814314751076 | D85: 202606 | E85: 51 | F85: 1085442 | G85: '03814314 | H85: '03814314 | I85: ENV | J85: ' | K85: 20260601 | L85: E20260601228156 | M85: J18 | N85: 10.7 | P85: 6.75 | Q85: LARUCHE | R85: VOIE COMMUNALE 4 | T85: FR | U85: '21 | V85: '21320 | W85: CREANCEY | X85: RACINE JULIEN | Y85: 151 ROUTE DU COLOMBIER | AA85: FR | AB85: '76 | AC85: '76210 | AD85: BEUZEVILLE LA GRENIER
B86: =IF(O86="","Frêt",_xlfn.XLOOKUP(O86,Catégories!A:A,Catégories!B:B,"inconnu")) -> Frêt | C86: =RIGHT(LOOKUP(L86,'Recherche tracking'!A:A,'Recherche tracking'!B:B),16) -> 7643814314751076 | D86: 202606 | E86: 51 | F86: 1085442 | G86: '03814314 | H86: '03814314 | I86: COL | J86: '7643814314751060 | K86: 20260601 | L86: E20260601228156 | M86: J18 | N86: 2 | P86: 0 | Q86: LARUCHE | R86: VOIE COMMUNALE 4 | T86: FR | U86: '21 | V86: '21320 | W86: CREANCEY | X86: RACINE JULIEN | Y86: 151 ROUTE DU COLOMBIER | AA86: FR | AB86: '76 | AC86: '76210 | AD86: BEUZEVILLE LA GRENIER
B87: =IF(O87="","Frêt",_xlfn.XLOOKUP(O87,Catégories!A:A,Catégories!B:B,"inconnu")) -> Frêt | C87: =RIGHT(LOOKUP(L87,'Recherche tracking'!A:A,'Recherche tracking'!B:B),16) -> 7643814314751076 | D87: 202606 | E87: 51 | F87: 1085442 | G87: '03814314 | H87: '03814314 | I87: CPC | J87: '7643814314751060 | K87: 20260601 | L87: E20260601228156 | N87: 2 | O87: RS | P87: 0 | Q87: LARUCHE | R87: VOIE COMMUNALE 4 | T87: FR | U87: '21 | V87: '21320 | W87: CREANCEY | X87: RACINE JULIEN | Y87: 151 ROUTE DU COLOMBIER | AA87: FR | AB87: '76 | AC87: '76210 | AD87: BEUZEVILLE LA GRENIER
B88: =IF(O88="","Frêt",_xlfn.XLOOKUP(O88,Catégories!A:A,Catégories!B:B,"inconnu")) -> Frêt | C88: =RIGHT(LOOKUP(L88,'Recherche tracking'!A:A,'Recherche tracking'!B:B),16) -> 7643814314751076 | D88: 202606 | E88: 51 | F88: 1085442 | G88: '03814314 | H88: '03814314 | I88: COL | J88: '7643814314751076 | K88: 20260601 | L88: E20260601228156 | M88: J18 | N88: 8.7 | P88: 0 | Q88: LARUCHE | R88: VOIE COMMUNALE 4 | T88: FR | U88: '21 | V88: '21320 | W88: CREANCEY | X88: RACINE JULIEN | Y88: 151 ROUTE DU COLOMBIER | AA88: FR | AB88: '76 | AC88: '76210 | AD88: BEUZEVILLE LA GRENIER
B89: =IF(O89="","Frêt",_xlfn.XLOOKUP(O89,Catégories!A:A,Catégories!B:B,"inconnu")) -> Frêt | C89: =RIGHT(LOOKUP(L89,'Recherche tracking'!A:A,'Recherche tracking'!B:B),16) -> 7643814314751076 | D89: 202606 | E89: 51 | F89: 1085442 | G89: '03814314 | H89: '03814314 | I89: CPC | J89: '7643814314751076 | K89: 20260601 | L89: E20260601228156 | N89: 8.7 | O89: RS | P89: 0 | Q89: LARUCHE | R89: VOIE COMMUNALE 4 | T89: FR | U89: '21 | V89: '21320 | W89: CREANCEY | X89: RACINE JULIEN | Y89: 151 ROUTE DU COLOMBIER | AA89: FR | AB89: '76 | AC89: '76210 | AD89: BEUZEVILLE LA GRENIER
B90: =IF(O90="","Frêt",_xlfn.XLOOKUP(O90,Catégories!A:A,Catégories!B:B,"inconnu")) -> Frêt | C90: =RIGHT(LOOKUP(L90,'Recherche tracking'!A:A,'Recherche tracking'!B:B),16) -> 7643814314751076 | D90: 202606 | E90: 51 | F90: 1085442 | G90: '03814314 | H90: '03814314 | I90: CPC | J90: '7643814314751076 | K90: 20260601 | L90: E20260601228156 | N90: 8.7 | O90: TMC | P90: 1 | Q90: LARUCHE | R90: VOIE COMMUNALE 4 | T90: FR | U90: '21 | V90: '21320 | W90: CREANCEY | X90: RACINE JULIEN | Y90: 151 ROUTE DU COLOMBIER | AA90: FR | AB90: '76 | AC90: '76210 | AD90: BEUZEVILLE LA GRENIER
B91: =IF(O91="","Frêt",_xlfn.XLOOKUP(O91,Catégories!A:A,Catégories!B:B,"inconnu")) -> Frêt | C91: =RIGHT(LOOKUP(L91,'Recherche tracking'!A:A,'Recherche tracking'!B:B),16) -> 2043814314751167 | D91: 202606 | E91: 51 | F91: 1085442 | G91: '03814314 | H91: '03814314 | I91: ENV | J91: ' | K91: 20260601 | L91: E20260601257675 | M91: J18 | N91: 10 | P91: 6.49 | Q91: LARUCHE | R91: VOIE COMMUNALE 4 | T91: FR | U91: '21 | V91: '21320 | W91: CREANCEY | X91: BARISEAU BAPTISTE | Y91: RESIDENCE E RUNDINELLE, LIEU-DIT | Z91: ORZICONE | AA91: FR | AB91: '20 | AC91: '20213 | AD91: PENTA DI CASINCA
B92: =IF(O92="","Frêt",_xlfn.XLOOKUP(O92,Catégories!A:A,Catégories!B:B,"inconnu")) -> Frêt | C92: =RIGHT(LOOKUP(L92,'Recherche tracking'!A:A,'Recherche tracking'!B:B),16) -> 2043814314751167 | D92: 202606 | E92: 51 | F92: 1085442 | G92: '03814314 | H92: '03814314 | I92: COL | J92: '2043814314751155 | K92: 20260601 | L92: E20260601257675 | M92: J18 | N92: 1.9 | P92: 0 | Q92: LARUCHE | R92: VOIE COMMUNALE 4 | T92: FR | U92: '21 | V92: '21320 | W92: CREANCEY | X92: BARISEAU BAPTISTE | Y92: RESIDENCE E RUNDINELLE, LIEU-DIT | Z92: ORZICONE | AA92: FR | AB92: '20 | AC92: '20213 | AD92: PENTA DI CASINCA
B93: =IF(O93="","Frêt",_xlfn.XLOOKUP(O93,Catégories!A:A,Catégories!B:B,"inconnu")) -> Frêt | C93: =RIGHT(LOOKUP(L93,'Recherche tracking'!A:A,'Recherche tracking'!B:B),16) -> 2043814314751167 | D93: 202606 | E93: 51 | F93: 1085442 | G93: '03814314 | H93: '03814314 | I93: CPC | J93: '2043814314751155 | K93: 20260601 | L93: E20260601257675 | N93: 1.9 | O93: RS | P93: 0 | Q93: LARUCHE | R93: VOIE COMMUNALE 4 | T93: FR | U93: '21 | V93: '21320 | W93: CREANCEY | X93: BARISEAU BAPTISTE | Y93: RESIDENCE E RUNDINELLE, LIEU-DIT | Z93: ORZICONE | AA93: FR | AB93: '20 | AC93: '20213 | AD93: PENTA DI CASINCA
B94: =IF(O94="","Frêt",_xlfn.XLOOKUP(O94,Catégories!A:A,Catégories!B:B,"inconnu")) -> Frêt | C94: =RIGHT(LOOKUP(L94,'Recherche tracking'!A:A,'Recherche tracking'!B:B),16) -> 2043814314751167 | D94: 202606 | E94: 51 | F94: 1085442 | G94: '03814314 | H94: '03814314 | I94: COL | J94: '2043814314751167 | K94: 20260601 | L94: E20260601257675 | M94: J18 | N94: 8.1 | P94: 0 | Q94: LARUCHE | R94: VOIE COMMUNALE 4 | T94: FR | U94: '21 | V94: '21320 | W94: CREANCEY | X94: BARISEAU BAPTISTE | Y94: RESIDENCE E RUNDINELLE, LIEU-DIT | Z94: ORZICONE | AA94: FR | AB94: '20 | AC94: '20213 | AD94: PENTA DI CASINCA
B95: =IF(O95="","Frêt",_xlfn.XLOOKUP(O95,Catégories!A:A,Catégories!B:B,"inconnu")) -> Frêt | C95: =RIGHT(LOOKUP(L95,'Recherche tracking'!A:A,'Recherche tracking'!B:B),16) -> 2043814314751167 | D95: 202606 | E95: 51 | F95: 1085442 | G95: '03814314 | H95: '03814314 | I95: CPC | J95: '2043814314751167 | K95: 20260601 | L95: E20260601257675 | N95: 8.1 | O95: RS | P95: 0 | Q95: LARUCHE | R95: VOIE COMMUNALE 4 | T95: FR | U95: '21 | V95: '21320 | W95: CREANCEY | X95: BARISEAU BAPTISTE | Y95: RESIDENCE E RUNDINELLE, LIEU-DIT | Z95: ORZICONE | AA95: FR | AB95: '20 | AC95: '20213 | AD95: PENTA DI CASINCA
B96: =IF(O96="","Frêt",_xlfn.XLOOKUP(O96,Catégories!A:A,Catégories!B:B,"inconnu")) -> Frêt | C96: =RIGHT(LOOKUP(L96,'Recherche tracking'!A:A,'Recherche tracking'!B:B),16) -> 2043814314751167 | D96: 202606 | E96: 51 | F96: 1085442 | G96: '03814314 | H96: '03814314 | I96: CPC | J96: '2043814314751167 | K96: 20260601 | L96: E20260601257675 | N96: 8.1 | O96: TMC | P96: 1 | Q96: LARUCHE | R96: VOIE COMMUNALE 4 | T96: FR | U96: '21 | V96: '21320 | W96: CREANCEY | X96: BARISEAU BAPTISTE | Y96: RESIDENCE E RUNDINELLE, LIEU-DIT | Z96: ORZICONE | AA96: FR | AB96: '20 | AC96: '20213 | AD96: PENTA DI CASINCA
B97: =IF(O97="","Frêt",_xlfn.XLOOKUP(O97,Catégories!A:A,Catégories!B:B,"inconnu")) -> Frêt | C97: =RIGHT(LOOKUP(L97,'Recherche tracking'!A:A,'Recherche tracking'!B:B),16) -> 7543814314751436 | D97: 202606 | E97: 51 | F97: 1085442 | G97: '03814314 | H97: '03814314 | I97: ENV | J97: ' | K97: 20260602 | L97: E20260602145707 | M97: J18 | N97: 12.1 | P97: 7.27 | Q97: LARUCHE | R97: VOIE COMMUNALE 4 | T97: FR | U97: '21 | V97: '21320 | W97: CREANCEY | X97: ARSIC BILIANA | Y97: 234 AVENUE DAUMESNIL | AA97: FR | AB97: '75 | AC97: '75012 | AD97: PARIS
B98: =IF(O98="","Frêt",_xlfn.XLOOKUP(O98,Catégories!A:A,Catégories!B:B,"inconnu")) -> Frêt | C98: =RIGHT(LOOKUP(L98,'Recherche tracking'!A:A,'Recherche tracking'!B:B),16) -> 7543814314751436 | D98: 202606 | E98: 51 | F98: 1085442 | G98: '03814314 | H98: '03814314 | I98: COL | J98: '7543814314751420 | K98: 20260602 | L98: E20260602145707 | M98: J18 | N98: 3.4 | P98: 0 | Q98: LARUCHE | R98: VOIE COMMUNALE 4 | T98: FR | U98: '21 | V98: '21320 | W98: CREANCEY | X98: ARSIC BILIANA | Y98: 234 AVENUE DAUMESNIL | AA98: FR | AB98: '75 | AC98: '75012 | AD98: PARIS
B99: =IF(O99="","Frêt",_xlfn.XLOOKUP(O99,Catégories!A:A,Catégories!B:B,"inconnu")) -> Frêt | C99: =RIGHT(LOOKUP(L99,'Recherche tracking'!A:A,'Recherche tracking'!B:B),16) -> 7543814314751436 | D99: 202606 | E99: 51 | F99: 1085442 | G99: '03814314 | H99: '03814314 | I99: CPC | J99: '7543814314751420 | K99: 20260602 | L99: E20260602145707 | N99: 3.4 | O99: RS | P99: 0 | Q99: LARUCHE | R99: VOIE COMMUNALE 4 | T99: FR | U99: '21 | V99: '21320 | W99: CREANCEY | X99: ARSIC BILIANA | Y99: 234 AVENUE DAUMESNIL | AA99: FR | AB99: '75 | AC99: '75012 | AD99: PARIS
B100: =IF(O100="","Frêt",_xlfn.XLOOKUP(O100,Catégories!A:A,Catégories!B:B,"inconnu")) -> Frêt | C100: =RIGHT(LOOKUP(L100,'Recherche tracking'!A:A,'Recherche tracking'!B:B),16) -> 7543814314751436 | D100: 202606 | E100: 51 | F100: 1085442 | G100: '03814314 | H100: '03814314 | I100: COL | J100: '7543814314751436 | K100: 20260602 | L100: E20260602145707 | M100: J18 | N100: 8.7 | P100: 0 | Q100: LARUCHE | R100: VOIE COMMUNALE 4 | T100: FR | U100: '21 | V100: '21320 | W100: CREANCEY | X100: ARSIC BILIANA | Y100: 234 AVENUE DAUMESNIL | AA100: FR | AB100: '75 | AC100: '75012 | AD100: PARIS
...

Sheet TCD
A1: Total | B1: Total | C1: ID | F1: Somme de montant HT | G1: Étiquettes de colonnes | Q1: Poids | R1: Étiquettes de lignes | S1: Colis volumineux | T1: Frêt | U1: Gazole | V1: Zones éloignées | Y1: Étiquettes de lignes | Z1: Moyenne de Frêt
A2: avec GO | B2: hors GO | C2: client | D2: Tracking | E2: Poids | F2: Étiquettes de lignes | G2: Colis volumineux | H2: Frêt | I2: Gazole | J2: Zones éloignées | K2: (vide) | Q2: 0 | U2: 185.85 | Y2: 0
B3: =SUM(G3:H3) -> 0 | E3: =_xlfn.XLOOKUP(F3,'Nb colis et poids'!E:E,'Nb colis et poids'!F:F) -> 0 | F3: (vide) | Q3: 0 | Y3: 0.1 | Z3: 5.11
A4: =ROUND(B4/(SUM(G:H)+SUM(J:J))*SUM(G:J),2) -> 31.17 | B4: =SUM(G4:J4) -> 27.91 | C4: 8640 | D4: =RIGHT(_xlfn.XLOOKUP(F4,'Recherche tracking'!A:A,'Recherche tracking'!B:B),16) -> #N/A | E4: =_xlfn.XLOOKUP(F4,'Nb colis et poids'!E:E,'Nb colis et poids'!F:F) -> 76.9 | F4: 9543814314757247 | H4: 27.91 | M4: 9.5438143e+15 | N4: =LEFT(F4,15)&"0" -> 9543814314757240 | Q4: 33.9 | R4: 117777519613379 | T4: 16.32 | Y4: 0.2 | Z4: 6.11
A5: =ROUND(B5/(SUM(G:H)+SUM(J:J))*SUM(G:J),2) -> 9.57 | B5: =SUM(G5:J5) -> 8.57 | C5: 8640 | D5: =RIGHT(_xlfn.XLOOKUP(F5,'Recherche tracking'!A:A,'Recherche tracking'!B:B),16) -> #N/A | E5: =_xlfn.XLOOKUP(F5,'Nb colis et poids'!E:E,'Nb colis et poids'!F:F) -> 18 | F5: 9543814314756996 | H5: 8.57 | M5: 9.5438143e+15 | N5: =LEFT(F5,15)&"0" -> 9543814314756990 | Q5: 14.9 | R5: 143814314728836 | T5: 8.57 | Y5: 1 | Z5: 4.7633333
A6: =ROUND(B6/(SUM(G:H)+SUM(J:J))*SUM(G:J),2) -> 5.51 | B6: =SUM(G6:J6) -> 4.93 | C6: 3752 | D6: =RIGHT(_xlfn.XLOOKUP(F6,'Recherche tracking'!A:A,'Recherche tracking'!B:B),16) -> #N/A | E6: =_xlfn.XLOOKUP(F6,'Nb colis et poids'!E:E,'Nb colis et poids'!F:F) -> 3.01 | F6: 9543814314755656 | H6: 4.93 | M6: 9.5438143e+15 | N6: =LEFT(F6,15)&"0" -> 9543814314755650 | Q6: 24.5 | R6: 143814314730487 | T6: 11.07 | Y6: 3.7 | Z6: 4.82
A7: =ROUND(B7/(SUM(G:H)+SUM(J:J))*SUM(G:J),2) -> 4.64 | B7: =SUM(G7:J7) -> 4.15 | C7: 9294 | D7: =RIGHT(_xlfn.XLOOKUP(F7,'Recherche tracking'!A:A,'Recherche tracking'!B:B),16) -> #N/A | E7: =_xlfn.XLOOKUP(F7,'Nb colis et poids'!E:E,'Nb colis et poids'!F:F) -> 0.8 | F7: 9543814314754754 | H7: 4.15 | M7: 9.5438143e+15 | N7: =LEFT(F7,15)&"0" -> 9543814314754750 | Q7: 15.6 | R7: 243814314733363 | T7: 8.82 | Y7: 4 | Z7: 4.82
A8: =ROUND(B8/(SUM(G:H)+SUM(J:J))*SUM(G:J),2) -> 4.64 | B8: =SUM(G8:J8) -> 4.15 | C8: 9294 | D8: =RIGHT(_xlfn.XLOOKUP(F8,'Recherche tracking'!A:A,'Recherche tracking'!B:B),16) -> #N/A | E8: =_xlfn.XLOOKUP(F8,'Nb colis et poids'!E:E,'Nb colis et poids'!F:F) -> 0.8 | F8: 9524024014087290 | H8: 4.15 | M8: 9.524024e+15 | N8: =LEFT(F8,15)&"0" -> 9524024014087290 | Q8: 32 | R8: 343814314731826 | T8: 14.82 | Y8: 6.5 | Z8: 5.57
A9: =ROUND(B9/(SUM(G:H)+SUM(J:J))*SUM(G:J),2) -> 15.33 | B9: =SUM(G9:J9) -> 13.73 | C9: 8640 | D9: =RIGHT(_xlfn.XLOOKUP(F9,'Recherche tracking'!A:A,'Recherche tracking'!B:B),16) -> #N/A | E9: =_xlfn.XLOOKUP(F9,'Nb colis et poids'!E:E,'Nb colis et poids'!F:F) -> 33.9 | F9: 9443814314757475 | H9: 13.73 | M9: 9.4438143e+15 | N9: =LEFT(F9,15)&"0" -> 9443814314757470 | Q9: 16.2 | R9: 643814314730212 | T9: 9.07 | Y9: 7.1 | Z9: 6.82
A10: =ROUND(B10/(SUM(G:H)+SUM(J:J))*SUM(G:J),2) -> 4.64 | B10: =SUM(G10:J10) -> 4.15 | C10: 3752 | D10: =RIGHT(_xlfn.XLOOKUP(F10,'Recherche tracking'!A:A,'Recherche tracking'!B:B),16) -> #N/A | E10: =_xlfn.XLOOKUP(F10,'Nb colis et poids'!E:E,'Nb colis et poids'!F:F) -> 0.8 | F10: 9443814314756452 | H10: 4.15 | M10: 9.4438143e+15 | N10: =LEFT(F10,15)&"0" -> 9443814314756450 | Q10: 15 | R10: 643814314731340 | T10: 8.57 | Y10: 7.2 | Z10: 6.82
A11: =ROUND(B11/(SUM(G:H)+SUM(J:J))*SUM(G:J),2) -> 4.64 | B11: =SUM(G11:J11) -> 4.15 | C11: 3752 | D11: =RIGHT(_xlfn.XLOOKUP(F11,'Recherche tracking'!A:A,'Recherche tracking'!B:B),16) -> #N/A | E11: =_xlfn.XLOOKUP(F11,'Nb colis et poids'!E:E,'Nb colis et poids'!F:F) -> 0.8 | F11: 9443814314756240 | H11: 4.15 | M11: 9.4438143e+15 | N11: =LEFT(F11,15)&"0" -> 9443814314756240 | Q11: 16.4 | R11: 643814314733638 | T11: 9.07 | Y11: 7.9 | Z11: 5.82
A12: =ROUND(B12/(SUM(G:H)+SUM(J:J))*SUM(G:J),2) -> 4.64 | B12: =SUM(G12:J12) -> 4.15 | C12: 3752 | D12: =RIGHT(_xlfn.XLOOKUP(F12,'Recherche tracking'!A:A,'Recherche tracking'!B:B),16) -> #N/A | E12: =_xlfn.XLOOKUP(F12,'Nb colis et poids'!E:E,'Nb colis et poids'!F:F) -> 0.8 | F12: 9443814314756072 | H12: 4.15 | M12: 9.4438143e+15 | N12: =LEFT(F12,15)&"0" -> 9443814314756070 | Q12: 13.2 | R12: 843814314728653 | T12: 7.32 | Y12: 8.2 | Z12: 6.07
A13: =ROUND(B13/(SUM(G:H)+SUM(J:J))*SUM(G:J),2) -> 5.22 | B13: =SUM(G13:J13) -> 4.67 | C13: 3752 | D13: =RIGHT(_xlfn.XLOOKUP(F13,'Recherche tracking'!A:A,'Recherche tracking'!B:B),16) -> #N/A | E13: =_xlfn.XLOOKUP(F13,'Nb colis et poids'!E:E,'Nb colis et poids'!F:F) -> 2.84 | F13: 9443814314755728 | H13: 4.67 | M13: 9.4438143e+15 | N13: =LEFT(F13,15)&"0" -> 9443814314755720 | Q13: 26.5 | R13: 843814314729019 | T13: 13.57 | Y13: 8.6 | Z13: 7.75
A14: =ROUND(B14/(SUM(G:H)+SUM(J:J))*SUM(G:J),2) -> 5.51 | B14: =SUM(G14:J14) -> 4.93 | C14: 9351 | D14: =RIGHT(_xlfn.XLOOKUP(F14,'Recherche tracking'!A:A,'Recherche tracking'!B:B),16) -> #N/A | E14: =_xlfn.XLOOKUP(F14,'Nb colis et poids'!E:E,'Nb colis et poids'!F:F) -> 3.2 | F14: 9443814314754803 | H14: 4.93 | M14: 9.4438143e+15 | N14: =LEFT(F14,15)&"0" -> 9443814314754800 | Q14: 34 | R14: 943814314731934 | T14: 25.32 | Y14: 8.7 | Z14: 6.07
A15: =ROUND(B15/(SUM(G:H)+SUM(J:J))*SUM(G:J),2) -> 5.51 | B15: =SUM(G15:J15) -> 4.93 | C15: 9351 | D15: =RIGHT(_xlfn.XLOOKUP(F15,'Recherche tracking'!A:A,'Recherche tracking'!B:B),16) -> #N/A | E15: =_xlfn.XLOOKUP(F15,'Nb colis et poids'!E:E,'Nb colis et poids'!F:F) -> 3.6 | F15: 9443814314754050 | H15: 4.93 | M15: 9.4438143e+15 | N15: =LEFT(F15,15)&"0" -> 9443814314754050 | Q15: 25.5 | R15: 943814314732630 | T15: 13.32 | Y15: 9.9 | Z15: 9.08
... A48: =ROUND(B48/(SUM(G:H)+SUM(J:J))*SUM(G:J),2) -> 7.83 | B48: =SUM(G48:J48) -> 7.01 | C48: 8656 | D48: =RIGHT(_xlfn.XLOOKUP(F48,'Recherche tracking'!A:A,'Recherche tracking'!B:B),16) -> #N/A | E48: =_xlfn.XLOOKUP(F48,'Nb colis et poids'!E:E,'Nb colis et poids'!F:F) -> 11.52 | F48: 9243814314751971 | H48: 7.01 | M48: 9.2438143e+15 | N48: =LEFT(F48,15)&"0" -> 9243814314751970 | Q48: 8.6 | R48: 2.1838143e+15 | T48: 7.75 | Y48: 38.7 | Z48: 15.57
A49: =ROUND(B49/(SUM(G:H)+SUM(J:J))*SUM(G:J),2) -> 6.09 | B49: =SUM(G49:J49) -> 5.45 | C49: 9351 | D49: =RIGHT(_xlfn.XLOOKUP(F49,'Recherche tracking'!A:A,'Recherche tracking'!B:B),16) -> #N/A | E49: =_xlfn.XLOOKUP(F49,'Nb colis et poids'!E:E,'Nb colis et poids'!F:F) -> 5.68 | F49: 9243814314751959 | H49: 5.45 | M49: 9.2438143e+15 | N49: =LEFT(F49,15)&"0" -> 9243814314751950 | Q49: 0.2 | R49: 2.1838143e+15 | T49: 6.11 | Y49: (vide)
A50: =ROUND(B50/(SUM(G:H)+SUM(J:J))*SUM(G:J),2) -> 6.38 | B50: =SUM(G50:J50) -> 5.71 | C50: 8041 | D50: =RIGHT(_xlfn.XLOOKUP(F50,'Recherche tracking'!A:A,'Recherche tracking'!B:B),16) -> #N/A | E50: =_xlfn.XLOOKUP(F50,'Nb colis et poids'!E:E,'Nb colis et poids'!F:F) -> 6.8 | F50: 9243814314751395 | H50: 5.71 | M50: 9.2438143e+15 | N50: =LEFT(F50,15)&"0" -> 9243814314751390 | Q50: 9.9 | R50: 2.1838143e+15 | T50: 9.08 | Y50: 5.7 | Z50: 6.32
A51: =ROUND(B51/(SUM(G:H)+SUM(J:J))*SUM(G:J),2) -> 5.8 | B51: =SUM(G51:J51) -> 5.19 | C51: 9351 | D51: =RIGHT(_xlfn.XLOOKUP(F51,'Recherche tracking'!A:A,'Recherche tracking'!B:B),16) -> #N/A | E51: =_xlfn.XLOOKUP(F51,'Nb colis et poids'!E:E,'Nb colis et poids'!F:F) -> 4.01 | F51: 9143814314754974 | H51: 5.19 | M51: 9.1438143e+15 | N51: =LEFT(F51,15)&"0" -> 9143814314754970 | Q51: 5 | R51: 2.2438143e+15 | T51: 6.43 | Y51: 1.9 | Z51: 4.32
A52: =ROUND(B52/(SUM(G:H)+SUM(J:J))*SUM(G:J),2) -> 7.83 | B52: =SUM(G52:J52) -> 7.01 | C52: 8640 | D52: =RIGHT(_xlfn.XLOOKUP(F52,'Recherche tracking'!A:A,'Recherche tracking'!B:B),16) -> #N/A | E52: =_xlfn.XLOOKUP(F52,'Nb colis et poids'!E:E,'Nb colis et poids'!F:F) -> 11.69 | F52: 9143814314754330 | H52: 7.01 | M52: 9.1438143e+15 | N52: =LEFT(F52,15)&"0" -> 9143814314754330 | Q52: 14.4 | R52: 2.2438143e+15 | T52: 8.57 | Y52: 24.3 | Z52: 12.07
A53: =ROUND(B53/(SUM(G:H)+SUM(J:J))*SUM(G:J),2) -> 12.43 | B53: =SUM(G53:J53) -> 11.13 | C53: 8640 | D53: =RIGHT(_xlfn.XLOOKUP(F53,'Recherche tracking'!A:A,'Recherche tracking'!B:B),16) -> #N/A | E53: =_xlfn.XLOOKUP(F53,'Nb colis et poids'!E:E,'Nb colis et poids'!F:F) -> 23.72 | F53: 9143814314754323 | H53: 11.13 | M53: 9.1438143e+15 | N53: =LEFT(F53,15)&"0" -> 9143814314754320 | Q53: 14 | R53: 2.3438143e+15 | T53: 7.32 | Y53: 35.2 | Z53: 14.82
A54: =ROUND(B54/(SUM(G:H)+SUM(J:J))*SUM(G:J),2) -> 15.33 | B54: =SUM(G54:J54) -> 13.73 | C54: 8041 | D54: =RIGHT(_xlfn.XLOOKUP(F54,'Recherche tracking'!A:A,'Recherche tracking'!B:B),16) -> #N/A | E54: =_xlfn.XLOOKUP(F54,'Nb colis et poids'!E:E,'Nb colis et poids'!F:F) -> 33.9 | F54: 9143814314752795 | H54: 13.73 | M54: 9.1438143e+15 | N54: =LEFT(F54,15)&"0" -> 9143814314752790 | Q54: 15.4 | R54: 2.4438143e+15 | T54: 8.82 | Y54: 5 | Z54: 6.43
A55: =ROUND(B55/(SUM(G:H)+SUM(J:J))*SUM(G:J),2) -> 5.22 | B55: =SUM(G55:J55) -> 4.67 | C55: 9351 | D55: =RIGHT(_xlfn.XLOOKUP(F55,'Recherche tracking'!A:A,'Recherche tracking'!B:B),16) -> #N/A | E55: =_xlfn.XLOOKUP(F55,'Nb colis et poids'!E:E,'Nb colis et poids'!F:F) -> 2.9 | F55: 9143814314751645 | H55: 4.67 | M55: 9.1438143e+15 | N55: =LEFT(F55,15)&"0" -> 9143814314751640 | Q55: 15.5 | R55: 2.4438143e+15 | T55: 8.82 | Y55: 43.8 | Z55: 15.82
A56: =ROUND(B56/(SUM(G:H)+SUM(J:J))*SUM(G:J),2) -> 4.64 | B56: =SUM(G56:J56) -> 4.15 | C56: 3752 | D56: =RIGHT(_xlfn.XLOOKUP(F56,'Recherche tracking'!A:A,'Recherche tracking'!B:B),16) -> #N/A | E56: =_xlfn.XLOOKUP(F56,'Nb colis et poids'!E:E,'Nb colis et poids'!F:F) -> 0.8 | F56: 8843814314756440 | H56: 4.15 | M56: 8.8438143e+15 | N56: =LEFT(F56,15)&"0" -> 8843814314756440 | Q56: 33.7 | R56: 2.5438143e+15 | T56: 14.32 | Y56: 11.6 | Z56: 7.82
A57: =ROUND(B57/(SUM(G:H)+SUM(J:J))*SUM(G:J),2) -> 4.64 | B57: =SUM(G57:J57) -> 4.15 | C57: 3752 | D57: =RIGHT(_xlfn.XLOOKUP(F57,'Recherche tracking'!A:A,'Recherche tracking'!B:B),16) -> #N/A | E57: =_xlfn.XLOOKUP(F57,'Nb colis et poids'!E:E,'Nb colis et poids'!F:F) -> 0.8 | F57: 8743814314756165 | H57: 4.15 | M57: 8.7438143e+15 | N57: =LEFT(F57,15)&"0" -> 8743814314756160 | Q57: 11 | R57: 2.7438143e+15 | T57: 7.57 | Y57: Total général | Z57: 9.0404167
A58: =ROUND(B58/(SUM(G:H)+SUM(J:J))*SUM(G:J),2) -> 4.64 | B58: =SUM(G58:J58) -> 4.15 | C58: 3752 | D58: =RIGHT(_xlfn.XLOOKUP(F58,'Recherche tracking'!A:A,'Recherche tracking'!B:B),16) -> #N/A | E58: =_xlfn.XLOOKUP(F58,'Nb colis et poids'!E:E,'Nb colis et poids'!F:F) -> 0.8 | F58: 8643814314755525 | H58: 4.15 | M58: 8.6438143e+15 | N58: =LEFT(F58,15)&"0" -> 8643814314755520 | Q58: 15.9 | R58: 2.824264e+15 | T58: 8.82
A59: =ROUND(B59/(SUM(G:H)+SUM(J:J))*SUM(G:J),2) -> 5.51 | B59: =SUM(G59:J59) -> 4.93 | C59: 9351 | D59: =RIGHT(_xlfn.XLOOKUP(F59,'Recherche tracking'!A:A,'Recherche tracking'!B:B),16) -> #N/A | E59: =_xlfn.XLOOKUP(F59,'Nb colis et poids'!E:E,'Nb colis et poids'!F:F) -> 3.6 | F59: 8643814314754877 | H59: 4.93 | M59: 8.6438143e+15 | N59: =LEFT(F59,15)&"0" -> 8643814314754870 | Q59: 15.5 | R59: 2.8438143e+15 | T59: 8.82
A60: =ROUND(B60/(SUM(G:H)+SUM(J:J))*SUM(G:J),2) -> 5.8 | B60: =SUM(G60:J60) -> 5.19 | C60: 7254 | D60: =RIGHT(_xlfn.XLOOKUP(F60,'Recherche tracking'!A:A,'Recherche tracking'!B:B),16) -> #N/A | E60: =_xlfn.XLOOKUP(F60,'Nb colis et poids'!E:E,'Nb colis et poids'!F:F) -> 4.4 | F60: 8643814314752353 | H60: 5.19 | M60: 8.6438143e+15 | N60: =LEFT(F60,15)&"0" -> 8643814314752350 | Q60: 10.6 | R60: 2.8438143e+15 | T60: 7.57
A61: =ROUND(B61/(SUM(G:H)+SUM(J:J))*SUM(G:J),2) -> 11.27 | B61: =SUM(G61:J61) -> 10.09 | C61: 7254 | D61: =RIGHT(_xlfn.XLOOKUP(F61,'Recherche tracking'!A:A,'Recherche tracking'!B:B),16) -> #N/A | E61: =_xlfn.XLOOKUP(F61,'Nb colis et poids'!E:E,'Nb colis et poids'!F:F) -> 19.3 | F61: 8643814314752042 | H61: 10.09 | M61: 8.6438143e+15 | N61: =LEFT(F61,15)&"0" -> 8643814314752040 | Q61: 15.6 | R61: 2.8438143e+15 | T61: 8.82
A62: =ROUND(B62/(SUM(G:H)+SUM(J:J))*SUM(G:J),2) -> 5.22 | B62: =SUM(G62:J62) -> 4.67 | C62: 9351 | D62: =RIGHT(_xlfn.XLOOKUP(F62,'Recherche tracking'!A:A,'Recherche tracking'!B:B),16) -> #N/A | E62: =_xlfn.XLOOKUP(F62,'Nb colis et poids'!E:E,'Nb colis et poids'!F:F) -> 2.9 | F62: 8543814314754765 | H62: 4.67 | M62: 8.5438143e+15 | N62: =LEFT(F62,15)&"0" -> 8543814314754760 | Q62: 1 | R62: 2.9438143e+15 | T62: 4.07
A63: =ROUND(B63/(SUM(G:H)+SUM(J:J))*SUM(G:J),2) -> 12.14 | B63: =SUM(G63:J63) -> 10.87 | C63: 7254 | D63: =RIGHT(_xlfn.XLOOKUP(F63,'Recherche tracking'!A:A,'Recherche tracking'!B:B),16) -> #N/A | E63: =_xlfn.XLOOKUP(F63,'Nb colis et poids'!E:E,'Nb colis et poids'!F:F) -> 22.9 | F63: 8543814314754362 | H63: 10.87 | M63: 8.5438143e+15 | N63: =LEFT(F63,15)&"0" -> 8543814314754360 | Q63: 3.7 | R63: 2.9438143e+15 | T63: 4.82
A64: =ROUND(B64/(SUM(G:H)+SUM(J:J))*SUM(G:J),2) -> 4.64 | B64: =SUM(G64:J64) -> 4.15 | C64: 9294 | D64: =RIGHT(_xlfn.XLOOKUP(F64,'Recherche tracking'!A:A,'Recherche tracking'!B:B),16) -> #N/A | E64: =_xlfn.XLOOKUP(F64,'Nb colis et poids'!E:E,'Nb colis et poids'!F:F) -> 0.5 | F64: 8543814314753978 | H64: 4.15 | M64: 8.5438143e+15 | N64: =LEFT(F64,15)&"0" -> 8543814314753970 | Q64: 13 | R64: 2.9438143e+15 | T64: 8.07
A65: =ROUND(B65/(SUM(G:H)+SUM(J:J))*SUM(G:J),2) -> 19.07 | B65: =SUM(G65:J65) -> 17.07 | C65: 7254 | D65: =RIGHT(_xlfn.XLOOKUP(F65,'Recherche tracking'!A:A,'Recherche tracking'!B:B),16) -> #N/A | E65: =_xlfn.XLOOKUP(F65,'Nb colis et poids'!E:E,'Nb colis et poids'!F:F) -> 42.4 | F65: 8543814314753828 | H65: 17.07 | M65: 8.5438143e+15 | N65: =LEFT(F65,15)&"0" -> 8543814314753820 | Q65: 4 | R65: 2.9438143e+15 | T65: 4.82
A66: =ROUND(B66/(SUM(G:H)+SUM(J:J))*SUM(G:J),2) -> 5.51 | B66: =SUM(G66:J66) -> 4.93 | C66: 9351 | D66: =RIGHT(_xlfn.XLOOKUP(F66,'Recherche tracking'!A:A,'Recherche tracking'!B:B),16) -> #N/A | E66: =_xlfn.XLOOKUP(F66,'Nb colis et poids'!E:E,'Nb colis et poids'!F:F) -> 3.2 | F66: 8543814314751258 | H66: 4.93 | M66: 8.5438143e+15 | N66: =LEFT(F66,15)&"0" -> 8543814314751250 | Q66: 15.4 | R66: 2.9438143e+15 | T66: 8.82
A67: =ROUND(B67/(SUM(G:H)+SUM(J:J))*SUM(G:J),2) -> 5.51 | B67: =SUM(G67:J67) -> 4.93 | C67: 7254 | D67: =RIGHT(_xlfn.XLOOKUP(F67,'Recherche tracking'!A:A,'Recherche tracking'!B:B),16) -> #N/A | E67: =_xlfn.XLOOKUP(F67,'Nb colis et poids'!E:E,'Nb colis et poids'!F:F) -> 3.01 | F67: 8443814314756019 | H67: 4.93 | M67: 8.4438143e+15 | N67: =LEFT(F67,15)&"0" -> 8443814314756010 | Q67: 14.5 | R67: 2.9438143e+15 | T67: 8.57
A68: =ROUND(B68/(SUM(G:H)+SUM(J:J))*SUM(G:J),2) -> 5.51 | B68: =SUM(G68:J68) -> 4.93 | C68: 3752 | D68: =RIGHT(_xlfn.XLOOKUP(F68,'Recherche tracking'!A:A,'Recherche tracking'!B:B),16) -> #N/A | E68: =_xlfn.XLOOKUP(F68,'Nb colis et poids'!E:E,'Nb colis et poids'!F:F) -> 3.01 | F68: 8443814314755660 | H68: 4.93 | M68: 8.4438143e+15 | N68: =LEFT(F68,15)&"0" -> 8443814314755660 | Q68: 43.8 | R68: 2.9438143e+15 | T68: 15.82
A69: =ROUND(B69/(SUM(G:H)+SUM(J:J))*SUM(G:J),2) -> 5.51 | B69: =SUM(G69:J69) -> 4.93 | C69: 9351 | D69: =RIGHT(_xlfn.XLOOKUP(F69,'Recherche tracking'!A:A,'Recherche tracking'!B:B),16) -> #N/A | E69: =_xlfn.XLOOKUP(F69,'Nb colis et poids'!E:E,'Nb colis et poids'!F:F) -> 3.84 | F69: 8443814314754797 | H69: 4.93 | M69: 8.4438143e+15 | N69: =LEFT(F69,15)&"0" -> 8443814314754790 | Q69: 11.3 | R69: 3.0438143e+15 | T69: 7.82
... A75: =ROUND(B75/(SUM(G:H)+SUM(J:J))*SUM(G:J),2) -> 8.7 | B75: =SUM(G75:J75) -> 7.79 | C75: 8656 | D75: =RIGHT(_xlfn.XLOOKUP(F75,'Recherche tracking'!A:A,'Recherche tracking'!B:B),16) -> #N/A | E75: =_xlfn.XLOOKUP(F75,'Nb colis et poids'!E:E,'Nb colis et poids'!F:F) -> 14.5 | F75: 8343814314753224 | H75: 7.79 | M75: 8.3438143e+15 | N75: =LEFT(F75,15)&"0" -> 8343814314753220 | Q75: 14.4 | R75: 3.1438143e+15 | T75: 7.57
A76: =ROUND(B76/(SUM(G:H)+SUM(J:J))*SUM(G:J),2) -> 6.09 | B76: =SUM(G76:J76) -> 5.45 | C76: 7254 | D76: =RIGHT(_xlfn.XLOOKUP(F76,'Recherche tracking'!A:A,'Recherche tracking'!B:B),16) -> #N/A | E76: =_xlfn.XLOOKUP(F76,'Nb colis et poids'!E:E,'Nb colis et poids'!F:F) -> 5.1 | F76: 8343814314752086 | H76: 5.45 | M76: 8.3438143e+15 | N76: =LEFT(F76,15)&"0" -> 8343814314752080
A77: =ROUND(B77/(SUM(G:H)+SUM(J:J))*SUM(G:J),2) -> 6.38 | B77: =SUM(G77:J77) -> 5.71 | C77: 9351 | D77: =RIGHT(_xlfn.XLOOKUP(F77,'Recherche tracking'!A:A,'Recherche tracking'!B:B),16) -> #N/A | E77: =_xlfn.XLOOKUP(F77,'Nb colis et poids'!E:E,'Nb colis et poids'!F:F) -> 6.2 | F77: 8243814314753215 | H77: 5.71 | M77: 8.2438143e+15 | N77: =LEFT(F77,15)&"0" -> 8243814314753210
A78: =ROUND(B78/(SUM(G:H)+SUM(J:J))*SUM(G:J),2) -> 5.22 | B78: =SUM(G78:J78) -> 4.67 | C78: 9351 | D78: =RIGHT(_xlfn.XLOOKUP(F78,'Recherche tracking'!A:A,'Recherche tracking'!B:B),16) -> #N/A | E78: =_xlfn.XLOOKUP(F78,'Nb colis et poids'!E:E,'Nb colis et poids'!F:F) -> 2.6 | F78: 8143814314755081 | H78: 4.67 | M78: 8.1438143e+15 | N78: =LEFT(F78,15)&"0" -> 8143814314755080
A79: =ROUND(B79/(SUM(G:H)+SUM(J:J))*SUM(G:J),2) -> 5.22 | B79: =SUM(G79:J79) -> 4.67 | C79: 9351 | D79: =RIGHT(_xlfn.XLOOKUP(F79,'Recherche tracking'!A:A,'Recherche tracking'!B:B),16) -> #N/A | E79: =_xlfn.XLOOKUP(F79,'Nb colis et poids'!E:E,'Nb colis et poids'!F:F) -> 2.9 | F79: 8143814314754030 | H79: 4.67 | M79: 8.1438143e+15 | N79: =LEFT(F79,15)&"0" -> 8143814314754030
A80: =ROUND(B80/(SUM(G:H)+SUM(J:J))*SUM(G:J),2) -> 5.22 | B80: =SUM(G80:J80) -> 4.67 | C80: 9351 | D80: =RIGHT(_xlfn.XLOOKUP(F80,'Recherche tracking'!A:A,'Recherche tracking'!B:B),16) -> #N/A | E80: =_xlfn.XLOOKUP(F80,'Nb colis et poids'!E:E,'Nb colis et poids'!F:F) -> 3 | F80: 8043814314755160 | H80: 4.67 | M80: 8.0438143e+15 | N80: =LEFT(F80,15)&"0" -> 8043814314755160
A81: =ROUND(B81/(SUM(G:H)+SUM(J:J))*SUM(G:J),2) -> 18.77 | B81: =SUM(G81:J81) -> 16.81 | C81: 7254 | D81: =RIGHT(_xlfn.XLOOKUP(F81,'Recherche tracking'!A:A,'Recherche tracking'!B:B),16) -> #N/A | E81: =_xlfn.XLOOKUP(F81,'Nb colis et poids'!E:E,'Nb colis et poids'!F:F) -> 41.4 | F81: 8043814314752314 | H81: 16.81 | M81: 8.0438143e+15 | N81: =LEFT(F81,15)&"0" -> 8043814314752310
A82: =ROUND(B82/(SUM(G:H)+SUM(J:J))*SUM(G:J),2) -> 6.38 | B82: =SUM(G82:J82) -> 5.71 | C82: 9351 | D82: =RIGHT(_xlfn.XLOOKUP(F82,'Recherche tracking'!A:A,'Recherche tracking'!B:B),16) -> #N/A | E82: =_xlfn.XLOOKUP(F82,'Nb colis et poids'!E:E,'Nb colis et poids'!F:F) -> 6.8 | F82: 8043814314751285 | H82: 5.71 | M82: 8.0438143e+15 | N82: =LEFT(F82,15)&"0" -> 8043814314751280
A83: =ROUND(B83/(SUM(G:H)+SUM(J:J))*SUM(G:J),2) -> 5.22 | B83: =SUM(G83:J83) -> 4.67 | C83: 9351 | D83: =RIGHT(_xlfn.XLOOKUP(F83,'Recherche tracking'!A:A,'Recherche tracking'!B:B),16) -> #N/A | E83: =_xlfn.XLOOKUP(F83,'Nb colis et poids'!E:E,'Nb colis et poids'!F:F) -> 2.9 | F83: 7943814314755147 | H83: 4.67 | M83: 7.9438143e+15 | N83: =LEFT(F83,15)&"0" -> 7943814314755140
A84: =ROUND(B84/(SUM(G:H)+SUM(J:J))*SUM(G:J),2) -> 4.64 | B84: =SUM(G84:J84) -> 4.15 | C84: 9294 | D84: =RIGHT(_xlfn.XLOOKUP(F84,'Recherche tracking'!A:A,'Recherche tracking'!B:B),16) -> #N/A | E84: =_xlfn.XLOOKUP(F84,'Nb colis et poids'!E:E,'Nb colis et poids'!F:F) -> 0.8 | F84: 7943814314754239 | H84: 4.15 | M84: 7.9438143e+15 | N84: =LEFT(F84,15)&"0" -> 7943814314754230
A85: =ROUND(B85/(SUM(G:H)+SUM(J:J))*SUM(G:J),2) -> 5.22 | B85: =SUM(G85:J85) -> 4.67 | C85: 8041 | D85: =RIGHT(_xlfn.XLOOKUP(F85,'Recherche tracking'!A:A,'Recherche tracking'!B:B),16) -> #N/A | E85: =_xlfn.XLOOKUP(F85,'Nb colis et poids'!E:E,'Nb colis et poids'!F:F) -> 3 | F85: 7843814314756657 | H85: 4.67 | M85: 7.8438143e+15 | N85: =LEFT(F85,15)&"0" -> 7843814314756650
A86: =ROUND(B86/(SUM(G:H)+SUM(J:J))*SUM(G:J),2) -> 4.64 | B86: =SUM(G86:J86) -> 4.15 | C86: 3752 | D86: =RIGHT(_xlfn.XLOOKUP(F86,'Recherche tracking'!A:A,'Recherche tracking'!B:B),16) -> #N/A | E86: =_xlfn.XLOOKUP(F86,'Nb colis et poids'!E:E,'Nb colis et poids'!F:F) -> 0.8 | F86: 7843814314756104 | H86: 4.15 | M86: 7.8438143e+15 | N86: =LEFT(F86,15)&"0" -> 7843814314756100
A87: =ROUND(B87/(SUM(G:H)+SUM(J:J))*SUM(G:J),2) -> 4.64 | B87: =SUM(G87:J87) -> 4.15 | C87: 3752 | D87: =RIGHT(_xlfn.XLOOKUP(F87,'Recherche tracking'!A:A,'Recherche tracking'!B:B),16) -> #N/A | E87: =_xlfn.XLOOKUP(F87,'Nb colis et poids'!E:E,'Nb colis et poids'!F:F) -> 0.8 | F87: 7843814314755922 | H87: 4.15 | M87: 7.8438143e+15 | N87: =LEFT(F87,15)&"0" -> 7843814314755920
... A191: =ROUND(B191/(SUM(G:H)+SUM(J:J))*SUM(G:J),2) -> 5.51 | B191: =SUM(G191:J191) -> 4.93 | C191: 9351 | D191: =RIGHT(_xlfn.XLOOKUP(F191,'Recherche tracking'!A:A,'Recherche tracking'!B:B),16) -> #N/A | E191: =_xlfn.XLOOKUP(F191,'Nb colis et poids'!E:E,'Nb colis et poids'!F:F) -> 3.8 | F191: 7443814314756848 | H191: 4.93 | M191: 7.4438143e+15 | N191: =LEFT(F191,15)&"0" -> 7443814314756840
A192: =ROUND(B192/(SUM(G:H)+SUM(J:J))*SUM(G:J),2) -> 26.5 | B192: =SUM(G192:J192) -> 23.73 | C192: 8041 | D192: =RIGHT(_xlfn.XLOOKUP(F192,'Recherche tracking'!A:A,'Recherche tracking'!B:B),16) -> #N/A | E192: =_xlfn.XLOOKUP(F192,'Nb colis et poids'!E:E,'Nb colis et poids'!F:F) -> 33.5 | F192: 7443814314756497 | H192: 13.73 | J192: 10 | M192: 7.4438143e+15 | N192: =LEFT(F192,15)&"0" -> 7443814314756490
A193: =ROUND(B193/(SUM(G:H)+SUM(J:J))*SUM(G:J),2) -> 4.64 | B193: =SUM(G193:J193) -> 4.15 | C193: 3752 | D193: =RIGHT(_xlfn.XLOOKUP(F193,'Recherche tracking'!A:A,'Recherche tracking'!B:B),16) -> #N/A | E193: =_xlfn.XLOOKUP(F193,'Nb colis et poids'!E:E,'Nb colis et poids'!F:F) -> 0.8 | F193: 7443814314756422 | H193: 4.15 | M193: 7.4438143e+15 | N193: =LEFT(F193,15)&"0" -> 7443814314756420
A194: =ROUND(B194/(SUM(G:H)+SUM(J:J))*SUM(G:J),2) -> 4.64 | B194: =SUM(G194:J194) -> 4.15 | C194: 3752 | D194: =RIGHT(_xlfn.XLOOKUP(F194,'Recherche tracking'!A:A,'Recherche tracking'!B:B),16) -> #N/A | E194: =_xlfn.XLOOKUP(F194,'Nb colis et poids'!E:E,'Nb colis et poids'!F:F) -> 0.8 | F194: 7443814314756284 | H194: 4.15 | M194: 7.4438143e+15 | N194: =LEFT(F194,15)&"0" -> 7443814314756280
A195: =ROUND(B195/(SUM(G:H)+SUM(J:J))*SUM(G:J),2) -> 4.64 | B195: =SUM(G195:J195) -> 4.15 | C195: 3752 | D195: =RIGHT(_xlfn.XLOOKUP(F195,'Recherche tracking'!A:A,'Recherche tracking'!B:B),16) -> #N/A | E195: =_xlfn.XLOOKUP(F195,'Nb colis et poids'!E:E,'Nb colis et poids'!F:F) -> 0.8 | F195: 7443814314755756 | H195: 4.15 | M195: 7.4438143e+15 | N195: =LEFT(F195,15)&"0" -> 7443814314755750
A196: =ROUND(B196/(SUM(G:H)+SUM(J:J))*SUM(G:J),2) -> 5.8 | B196: =SUM(G196:J196) -> 5.19 | C196: 9351 | D196: =RIGHT(_xlfn.XLOOKUP(F196,'Recherche tracking'!A:A,'Recherche tracking'!B:B),16) -> #N/A | E196: =_xlfn.XLOOKUP(F196,'Nb colis et poids'!E:E,'Nb colis et poids'!F:F) -> 4.1 | F196: 7443814314754693 | H196: 5.19 | M196: 7.4438143e+15 | N196: =LEFT(F196,15)&"0" -> 7443814314754690
A197: =ROUND(B197/(SUM(G:H)+SUM(J:J))*SUM(G:J),2) -> 17.32 | B197: =SUM(G197:J197) -> 15.51 | C197: 7254 | D197: =RIGHT(_xlfn.XLOOKUP(F197,'Recherche tracking'!A:A,'Recherche tracking'!B:B),16) -> #N/A | E197: =_xlfn.XLOOKUP(F197,'Nb colis et poids'!E:E,'Nb colis et poids'!F:F) -> 37 | F197: 7443814314754543 | H197: 15.51 | M197: 7.4438143e+15 | N197: =LEFT(F197,15)&"0" -> 7443814314754540
A198: =ROUND(B198/(SUM(G:H)+SUM(J:J))*SUM(G:J),2) -> 16.16 | B198: =SUM(G198:J198) -> 14.47 | C198: 7254 | D198: =RIGHT(_xlfn.XLOOKUP(F198,'Recherche tracking'!A:A,'Recherche tracking'!B:B),16) -> #N/A | E198: =_xlfn.XLOOKUP(F198,'Nb colis et poids'!E:E,'Nb colis et poids'!F:F) -> 32.2 | F198: 7443814314751525 | H198: 14.47 | M198: 7.4438143e+15 | N198: =LEFT(F198,15)&"0" -> 7443814314751520
A199: =ROUND(B199/(SUM(G:H)+SUM(J:J))*SUM(G:J),2) -> 16.61 | B199: =SUM(G199:J199) -> 14.87 | C199: 8041 | D199: =RIGHT(_xlfn.XLOOKUP(F199,'Recherche tracking'!A:A,'Recherche tracking'!B:B),16) -> #N/A | E199: =_xlfn.XLOOKUP(F199,'Nb colis et poids'!E:E,'Nb colis et poids'!F:F) -> 22.1 | F199: 7443814314751128 | H199: 9.87 | J199: 5 | M199: 7.4438143e+15 | N199: =LEFT(F199,15)&"0" -> 7443814314751120
A200: =ROUND(B200/(SUM(G:H)+SUM(J:J))*SUM(G:J),2) -> 5.51 | B200: =SUM(G200:J200) -> 4.93 | C200: 8041 | D200: =RIGHT(_xlfn.XLOOKUP(F200,'Recherche tracking'!A:A,'Recherche tracking'!B:B),16) -> #N/A | E200: =_xlfn.XLOOKUP(F200,'Nb colis et poids'!E:E,'Nb colis et poids'!F:F) -> 3.8 | F200: 7343814314756834 | H200: 4.93 | M200: 7.3438143e+15 | N200: =LEFT(F200,15)&"0" -> 7343814314756830
A201: =ROUND(B201/(SUM(G:H)+SUM(J:J))*SUM(G:J),2) -> 4.64 | B201: =SUM(G201:J201) -> 4.15 | C201: 3752 | D201: =RIGHT(_xlfn.XLOOKUP(F201,'Recherche tracking'!A:A,'Recherche tracking'!B:B),16) -> #N/A | E201: =_xlfn.XLOOKUP(F201,'Nb colis et poids'!E:E,'Nb colis et poids'!F:F) -> 0.8 | F201: 7343814314755771 | H201: 4.15 | M201: 7.3438143e+15 | N201: =LEFT(F201,15)&"0" -> 7343814314755770
A202: =ROUND(B202/(SUM(G:H)+SUM(J:J))*SUM(G:J),2) -> 9.86 | B202: =SUM(G202:J202) -> 8.83 | C202: 4565 | D202: =RIGHT(_xlfn.XLOOKUP(F202,'Recherche tracking'!A:A,'Recherche tracking'!B:B),16) -> #N/A | E202: =_xlfn.XLOOKUP(F202,'Nb colis et poids'!E:E,'Nb colis et poids'!F:F) -> 18.1 | F202: 7343814314753638 | H202: 8.83 | M202: 7.3438143e+15 | N202: =LEFT(F202,15)&"0" -> 7343814314753630
A203: =ROUND(B203/(SUM(G:H)+SUM(J:J))*SUM(G:J),2) -> 14.75 | B203: =SUM(G203:J203) -> 13.21 | C203: 7254 | D203: =RIGHT(_xlfn.XLOOKUP(F203,'Recherche tracking'!A:A,'Recherche tracking'!B:B),16) -> #N/A | E203: =_xlfn.XLOOKUP(F203,'Nb colis et poids'!E:E,'Nb colis et poids'!F:F) -> 31.1 | F203: 7343814314753137 | H203: 13.21 | M203: 7.3438143e+15 | N203: =LEFT(F203,15)&"0" -> 7343814314753130
A204: =ROUND(B204/(SUM(G:H)+SUM(J:J))*SUM(G:J),2) -> 5.51 | B204: =SUM(G204:J204) -> 4.93 | C204: 9351 | D204: =RIGHT(_xlfn.XLOOKUP(F204,'Recherche tracking'!A:A,'Recherche tracking'!B:B),16) -> #N/A | E204: =_xlfn.XLOOKUP(F204,'Nb colis et poids'!E:E,'Nb colis et poids'!F:F) -> 3.6 | F204: 7343814314752870 | H204: 4.93 | M204: 7.3438143e+15 | N204: =LEFT(F204,15)&"0" -> 7343814314752870
A205: =ROUND(B205/(SUM(G:H)+SUM(J:J))*SUM(G:J),2) -> 4.64 | B205: =SUM(G205:J205) -> 4.15 | C205: 9294 | D205: =RIGHT(_xlfn.XLOOKUP(F205,'Recherche tracking'!A:A,'Recherche tracking'!B:B),16) -> #N/A | E205: =_xlfn.XLOOKUP(F205,'Nb colis et poids'!E:E,'Nb colis et poids'!F:F) -> 0.5 | F205: 7243814314752958 | H205: 4.15 | M205: 7.2438143e+15 | N205: =LEFT(F205,15)&"0" -> 7243814314752950
A206: =ROUND(B206/(SUM(G:H)+SUM(J:J))*SUM(G:J),2) -> 11.85 | B206: =SUM(G206:J206) -> 10.61 | C206: 8656 | D206: =RIGHT(_xlfn.XLOOKUP(F206,'Recherche tracking'!A:A,'Recherche tracking'!B:B),16) -> #N/A | E206: =_xlfn.XLOOKUP(F206,'Nb colis et poids'!E:E,'Nb colis et poids'!F:F) -> 21.9 | F206: 7243814314752169 | H206: 10.61 | M206: 7.2438143e+15 | N206: =LEFT(F206,15)&"0" -> 7243814314752160
A207: =ROUND(B207/(SUM(G:H)+SUM(J:J))*SUM(G:J),2) -> 5.22 | B207: =SUM(G207:J207) -> 4.67 | C207: 9351 | D207: =RIGHT(_xlfn.XLOOKUP(F207,'Recherche tracking'!A:A,'Recherche tracking'!B:B),16) -> #N/A | E207: =_xlfn.XLOOKUP(F207,'Nb colis et poids'!E:E,'Nb colis et poids'!F:F) -> 2.9 | F207: 7143814314756564 | H207: 4.67 | M207: 7.1438143e+15 | N207: =LEFT(F207,15)&"0" -> 7143814314756560
A208: =ROUND(B208/(SUM(G:H)+SUM(J:J))*SUM(G:J),2) -> 4.64 | B208: =SUM(G208:J208) -> 4.15 | C208: 3752 | D208: =RIGHT(_xlfn.XLOOKUP(F208,'Recherche tracking'!A:A,'Recherche tracking'!B:B),16) -> #N/A | E208: =_xlfn.XLOOKUP(F208,'Nb colis et poids'!E:E,'Nb colis et poids'!F:F) -> 0.8 | F208: 7143814314755805 | H208: 4.15 | M208: 7.1438143e+15 | N208: =LEFT(F208,15)&"0" -> 7143814314755800
A209: =ROUND(B209/(SUM(G:H)+SUM(J:J))*SUM(G:J),2) -> 6.67 | B209: =SUM(G209:J209) -> 5.97 | C209: 7254 | D209: =RIGHT(_xlfn.XLOOKUP(F209,'Recherche tracking'!A:A,'Recherche tracking'!B:B),16) -> #N/A | E209: =_xlfn.XLOOKUP(F209,'Nb colis et poids'!E:E,'Nb colis et poids'!F:F) -> 7.4 | F209: 7143814314754777 | H209: 5.97 | M209: 7.1438143e+15 | N209: =LEFT(F209,15)&"0" -> 7143814314754770
A210: =ROUND(B210/(SUM(G:H)+SUM(J:J))*SUM(G:J),2) -> 5.51 | B210: =SUM(G210:J210) -> 4.93 | C210: 9351 | D210: =RIGHT(_xlfn.XLOOKUP(F210,'Recherche tracking'!A:A,'Recherche tracking'!B:B),16) -> #N/A | E210: =_xlfn.XLOOKUP(F210,'Nb colis et poids'!E:E,'Nb colis et poids'!F:F) -> 3.5 | F210: 7143814314754276 | H210: 4.93 | M210: 7.1438143e+15 | N210: =LEFT(F210,15)&"0" -> 7143814314754270
A211: =ROUND(B211/(SUM(G:H)+SUM(J:J))*SUM(G:J),2) -> 5.22 | B211: =SUM(G211:J211) -> 4.67 | C211: 9351 | D211: =RIGHT(_xlfn.XLOOKUP(F211,'Recherche tracking'!A:A,'Recherche tracking'!B:B),16) -> #N/A | E211: =_xlfn.XLOOKUP(F211,'Nb colis et poids'!E:E,'Nb colis et poids'!F:F) -> 2.9 | F211: 7143814314753691 | H211: 4.67 | M211: 7.1438143e+15 | N211: =LEFT(F211,15)&"0" -> 7143814314753690
... A424: =ROUND(B424/(SUM(G:H)+SUM(J:J))*SUM(G:J),2) -> 17.61 | B424: =SUM(G424:J424) -> 15.77 | C424: 8656 | D424: =RIGHT(_xlfn.XLOOKUP(F424,'Recherche tracking'!A:A,'Recherche tracking'!B:B),16) -> #N/A | E424: =_xlfn.XLOOKUP(F424,'Nb colis et poids'!E:E,'Nb colis et poids'!F:F) -> 37.5 | F424: 2243814314751731 | H424: 15.77 | M424: 2.2438143e+15 | N424: =LEFT(F424,15)&"0" -> 2243814314751730
A425: =ROUND(B425/(SUM(G:H)+SUM(J:J))*SUM(G:J),2) -> 15.78 | B425: =SUM(G425:J425) -> 14.13 | C425: Avoir | D425: =RIGHT(_xlfn.XLOOKUP(F425,'Recherche tracking'!A:A,'Recherche tracking'!B:B),16) -> #N/A | E425: =_xlfn.XLOOKUP(F425,'Nb colis et poids'!E:E,'Nb colis et poids'!F:F) -> 23.1 | F425: 2183814314003195 | H425: 14.13 | M425: 2.1838143e+15 | N425: =LEFT(F425,15)&"0" -> 2183814314003190
A426: =ROUND(B426/(SUM(G:H)+SUM(J:J))*SUM(G:J),2) -> 4.93 | B426: =SUM(G426:J426) -> 4.41 | C426: Avoir | D426: =RIGHT(_xlfn.XLOOKUP(F426,'Recherche tracking'!A:A,'Recherche tracking'!B:B),16) -> #N/A | E426: =_xlfn.XLOOKUP(F426,'Nb colis et poids'!E:E,'Nb colis et poids'!F:F) -> 1.6 | F426: 2183814314003143 | H426: 4.41 | M426: 2.1838143e+15 | N426: =LEFT(F426,15)&"0" -> 2183814314003140
A427: =ROUND(B427/(SUM(G:H)+SUM(J:J))*SUM(G:J),2) -> 4.64 | B427: =SUM(G427:J427) -> 4.15 | C427: Avoir | D427: =RIGHT(_xlfn.XLOOKUP(F427,'Recherche tracking'!A:A,'Recherche tracking'!B:B),16) -> #N/A | E427: =_xlfn.XLOOKUP(F427,'Nb colis et poids'!E:E,'Nb colis et poids'!F:F) -> 1 | F427: 2183814314003137 | H427: 4.15 | M427: 2.1838143e+15 | N427: =LEFT(F427,15)&"0" -> 2183814314003130
A428: =ROUND(B428/(SUM(G:H)+SUM(J:J))*SUM(G:J),2) -> 9.53 | B428: =SUM(G428:J428) -> 8.53 | C428: Avoir | D428: =RIGHT(_xlfn.XLOOKUP(F428,'Recherche tracking'!A:A,'Recherche tracking'!B:B),16) -> #N/A | E428: =_xlfn.XLOOKUP(F428,'Nb colis et poids'!E:E,'Nb colis et poids'!F:F) -> 13.5 | F428: 2183814314003125 | H428: 8.53 | M428: 2.1838143e+15 | N428: =LEFT(F428,15)&"0" -> 2183814314003120
A429: =ROUND(B429/(SUM(G:H)+SUM(J:J))*SUM(G:J),2) -> 4.64 | B429: =SUM(G429:J429) -> 4.15 | C429: Avoir | D429: =RIGHT(_xlfn.XLOOKUP(F429,'Recherche tracking'!A:A,'Recherche tracking'!B:B),16) -> #N/A | E429: =_xlfn.XLOOKUP(F429,'Nb colis et poids'!E:E,'Nb colis et poids'!F:F) -> 0.4 | F429: 2183814314003108 | H429: 4.15 | M429: 2.1838143e+15 | N429: =LEFT(F429,15)&"0" -> 2183814314003100
A430: =ROUND(B430/(SUM(G:H)+SUM(J:J))*SUM(G:J),2) -> 12.63 | B430: =SUM(G430:J430) -> 11.31 | C430: Avoir | D430: =RIGHT(_xlfn.XLOOKUP(F430,'Recherche tracking'!A:A,'Recherche tracking'!B:B),16) -> #N/A | E430: =_xlfn.XLOOKUP(F430,'Nb colis et poids'!E:E,'Nb colis et poids'!F:F) -> 16.4 | F430: 2183814314003097 | H430: 11.31 | M430: 2.1838143e+15 | N430: =LEFT(F430,15)&"0" -> 2183814314003090
A431: =ROUND(B431/(SUM(G:H)+SUM(J:J))*SUM(G:J),2) -> 6.87 | B431: =SUM(G431:J431) -> 6.15 | C431: Avoir | D431: =RIGHT(_xlfn.XLOOKUP(F431,'Recherche tracking'!A:A,'Recherche tracking'!B:B),16) -> #N/A | E431: =_xlfn.XLOOKUP(F431,'Nb colis et poids'!E:E,'Nb colis et poids'!F:F) -> 0.3 | F431: 2183814314003051 | H431: 6.15 | M431: 2.1838143e+15 | N431: =LEFT(F431,15)&"0" -> 2183814314003050
A432: =ROUND(B432/(SUM(G:H)+SUM(J:J))*SUM(G:J),2) -> 6.96 | B432: =SUM(G432:J432) -> 6.23 | C432: Avoir | D432: =RIGHT(_xlfn.XLOOKUP(F432,'Recherche tracking'!A:A,'Recherche tracking'!B:B),16) -> #N/A | E432: =_xlfn.XLOOKUP(F432,'Nb colis et poids'!E:E,'Nb colis et poids'!F:F) -> 8.8 | F432: 2183814314003022 | H432: 6.23 | M432: 2.1838143e+15 | N432: =LEFT(F432,15)&"0" -> 2183814314003020
A433: =ROUND(B433/(SUM(G:H)+SUM(J:J))*SUM(G:J),2) -> 5.51 | B433: =SUM(G433:J433) -> 4.93 | C433: 9351 | D433: =RIGHT(_xlfn.XLOOKUP(F433,'Recherche tracking'!A:A,'Recherche tracking'!B:B),16) -> #N/A | E433: =_xlfn.XLOOKUP(F433,'Nb colis et poids'!E:E,'Nb colis et poids'!F:F) -> 3.5 | F433: 2143814314757089 | H433: 4.93 | M433: 2.1438143e+15 | N433: =LEFT(F433,15)&"0" -> 2143814314757080
A434: =ROUND(B434/(SUM(G:H)+SUM(J:J))*SUM(G:J),2) -> 4.64 | B434: =SUM(G434:J434) -> 4.15 | C434: 3752 | D434: =RIGHT(_xlfn.XLOOKUP(F434,'Recherche tracking'!A:A,'Recherche tracking'!B:B),16) -> #N/A | E434: =_xlfn.XLOOKUP(F434,'Nb colis et poids'!E:E,'Nb colis et poids'!F:F) -> 0.8 | F434: 2143814314755734 | H434: 4.15 | M434: 2.1438143e+15 | N434: =LEFT(F434,15)&"0" -> 2143814314755730
A435: =ROUND(B435/(SUM(G:H)+SUM(J:J))*SUM(G:J),2) -> 12.14 | B435: =SUM(G435:J435) -> 10.87 | C435: 7254 | D435: =RIGHT(_xlfn.XLOOKUP(F435,'Recherche tracking'!A:A,'Recherche tracking'!B:B),16) -> #N/A | E435: =_xlfn.XLOOKUP(F435,'Nb colis et poids'!E:E,'Nb colis et poids'!F:F) -> 22.3 | F435: 2143814314755325 | H435: 10.87 | M435: 2.1438143e+15 | N435: =LEFT(F435,15)&"0" -> 2143814314755320
A436: =ROUND(B436/(SUM(G:H)+SUM(J:J))*SUM(G:J),2) -> 4.64 | B436: =SUM(G436:J436) -> 4.15 | C436: 9294 | D436: =RIGHT(_xlfn.XLOOKUP(F436,'Recherche tracking'!A:A,'Recherche tracking'!B:B),16) -> #N/A | E436: =_xlfn.XLOOKUP(F436,'Nb colis et poids'!E:E,'Nb colis et poids'!F:F) -> 0.5 | F436: 2143814314754895 | H436: 4.15 | M436: 2.1438143e+15 | N436: =LEFT(F436,15)&"0" -> 2143814314754890
A437: =ROUND(B437/(SUM(G:H)+SUM(J:J))*SUM(G:J),2) -> 5.51 | B437: =SUM(G437:J437) -> 4.93 | C437: 9351 | D437: =RIGHT(_xlfn.XLOOKUP(F437,'Recherche tracking'!A:A,'Recherche tracking'!B:B),16) -> #N/A | E437: =_xlfn.XLOOKUP(F437,'Nb colis et poids'!E:E,'Nb colis et poids'!F:F) -> 3.6 | F437: 2143814314754348 | H437: 4.93 | M437: 2.1438143e+15 | N437: =LEFT(F437,15)&"0" -> 2143814314754340
A438: =ROUND(B438/(SUM(G:H)+SUM(J:J))*SUM(G:J),2) -> 5.51 | B438: =SUM(G438:J438) -> 4.93 | C438: 9351 | D438: =RIGHT(_xlfn.XLOOKUP(F438,'Recherche tracking'!A:A,'Recherche tracking'!B:B),16) -> #N/A | E438: =_xlfn.XLOOKUP(F438,'Nb colis et poids'!E:E,'Nb colis et poids'!F:F) -> 3.2 | F438: 2143814314752262 | H438: 4.93 | M438: 2.1438143e+15 | N438: =LEFT(F438,15)&"0" -> 2143814314752260
A439: =ROUND(B439/(SUM(G:H)+SUM(J:J))*SUM(G:J),2) -> 4.64 | B439: =SUM(G439:J439) -> 4.15 | C439: 9294 | D439: =RIGHT(_xlfn.XLOOKUP(F439,'Recherche tracking'!A:A,'Recherche tracking'!B:B),16) -> #N/A | E439: =_xlfn.XLOOKUP(F439,'Nb colis et poids'!E:E,'Nb colis et poids'!F:F) -> 0.6 | F439: 2143814314751498 | H439: 4.15 | M439: 2.1438143e+15 | N439: =LEFT(F439,15)&"0" -> 2143814314751490
A440: =ROUND(B440/(SUM(G:H)+SUM(J:J))*SUM(G:J),2) -> 8.95 | B440: =SUM(G440:J440) -> 8.01 | C440: 3752 | D440: =RIGHT(_xlfn.XLOOKUP(F440,'Recherche tracking'!A:A,'Recherche tracking'!B:B),16) -> #N/A | E440: =_xlfn.XLOOKUP(F440,'Nb colis et poids'!E:E,'Nb colis et poids'!F:F) -> 11.71 | F440: 2124022012362077 | H440: 8.01 | M440: 2.124022e+15 | N440: =LEFT(F440,15)&"0" -> 2124022012362070
A441: =ROUND(B441/(SUM(G:H)+SUM(J:J))*SUM(G:J),2) -> 8.37 | B441: =SUM(G441:J441) -> 7.49 | C441: 3752 | D441: =RIGHT(_xlfn.XLOOKUP(F441,'Recherche tracking'!A:A,'Recherche tracking'!B:B),16) -> #N/A | E441: =_xlfn.XLOOKUP(F441,'Nb colis et poids'!E:E,'Nb colis et poids'!F:F) -> 10 | F441: 2124008001966725 | H441: 7.49 | M441: 2.124008e+15 | N441: =LEFT(F441,15)&"0" -> 2124008001966720
A442: =ROUND(B442/(SUM(G:H)+SUM(J:J))*SUM(G:J),2) -> 4.64 | B442: =SUM(G442:J442) -> 4.15 | C442: 3752 | D442: =RIGHT(_xlfn.XLOOKUP(F442,'Recherche tracking'!A:A,'Recherche tracking'!B:B),16) -> #N/A | E442: =_xlfn.XLOOKUP(F442,'Nb colis et poids'!E:E,'Nb colis et poids'!F:F) -> 0.8 | F442: 2120237069277562 | H442: 4.15 | M442: 2.1202371e+15 | N442: =LEFT(F442,15)&"0" -> 2120237069277560
A443: =ROUND(B443/(SUM(G:H)+SUM(J:J))*SUM(G:J),2) -> 14.46 | B443: =SUM(G443:J443) -> 12.95 | C443: 7254 | D443: =RIGHT(_xlfn.XLOOKUP(F443,'Recherche tracking'!A:A,'Recherche tracking'!B:B),16) -> #N/A | E443: =_xlfn.XLOOKUP(F443,'Nb colis et poids'!E:E,'Nb colis et poids'!F:F) -> 30.3 | F443: 2117777429708519 | H443: 12.95 | M443: 2.1177774e+15 | N443: =LEFT(F443,15)&"0" -> 2117777429708510
A444: =ROUND(B444/(SUM(G:H)+SUM(J:J))*SUM(G:J),2) -> 4.64 | B444: =SUM(G444:J444) -> 4.15 | C444: 3752 | D444: =RIGHT(_xlfn.XLOOKUP(F444,'Recherche tracking'!A:A,'Recherche tracking'!B:B),16) -> #N/A | E444: =_xlfn.XLOOKUP(F444,'Nb colis et poids'!E:E,'Nb colis et poids'!F:F) -> 0.8 | F444: 2043814314755599 | H444: 4.15 | M444: 2.0438143e+15 | N444: =LEFT(F444,15)&"0" -> 2043814314755590
... A516: =ROUND(B516/(SUM(G:H)+SUM(J:J))*SUM(G:J),2) -> 4.93 | B516: =SUM(G516:J516) -> 4.41 | C516: 9294 | D516: =RIGHT(_xlfn.XLOOKUP(F516,'Recherche tracking'!A:A,'Recherche tracking'!B:B),16) -> #N/A | E516: =_xlfn.XLOOKUP(F516,'Nb colis et poids'!E:E,'Nb colis et poids'!F:F) -> 1.34 | F516: 0143814314751704 | H516: 4.41 | M516: 143814314751704 | N516: =LEFT(F516,15)&"0" -> 0143814314751700
A517: =ROUND(B517/(SUM(G:H)+SUM(J:J))*SUM(G:J),2) -> 471.91 | B517: =SUM(G517:J517) -> 422.52 | D517: =RIGHT(_xlfn.XLOOKUP(F517,'Recherche tracking'!A:A,'Recherche tracking'!B:B),16) -> #N/A | E517: =_xlfn.XLOOKUP(F517,'Nb colis et poids'!E:E,'Nb colis et poids'!F:F) -> 0 | I517: 422.52

Sheet Bilan clients
A3: Étiquettes de lignes | B3: Somme de Total
A4: 3752 | B4: 768.62
A5: 4565 | B5: 243.27
A6: 6930 | B6: 28.09
A7: 7027 | B7: 18.27
A8: 7254 | B8: 926.09
A9: 8041 | B9: 347.3
A10: 8640 | B10: 204.83
A11: 8656 | B11: 131.75
A12: 9169 | B12: 6.96
A13: 9294 | B13: 141.81
A14: 9351 | B14: 1155.62
A15: Avoir | B15: 65.98
A16: client | B16: 0
A17: (vide) | B17: 471.91
A18: Total général | B18: 4510.5

Sheet Import csv
A1: Transporteur | B1: Date validité tarif | C1: Réf.1 | D1: Réf. 2 | E1: Id client | F1: N° Tracking | G1: Nom | H1: E / P | I1: Pays | J1: Zone | K1: Nbr Colis | L1: Poids | M1: mode envoi | N1: TVA | O1: Droits et taxes | P1: Assurance | Q1: Zones éloignées | R1: Colis volumineux | S1: Adresses | T1: Frêt | U1: plus-value BtoC | V1: Gazole | W1: Nb Colis | Y1: Attention aux poids sup > 15 kg avec nb colis = 1
A2: TNT | B2: 46174 | F2: =TCD!F3 -> (vide) | H2: E | I2: FR | J2: France | K2: {=IF(COUNTIF('Nb colis et poids'!A:A,F2)=0,1,LOOKUP(F2,'Nb colis et poids'!A:A,'Nb colis et poids'!B:B+1))} -> 1 | L2: =TCD!E3 -> 0 | M2: ST | N2: 0.2 | Q2: =IF(TCD!J3="","",TCD!J3) | R2: =IF(TCD!G3="","",TCD!G3) | T2: =TCD!H3 -> 0
A3: =A2 -> TNT | B3: =B2 -> 46174 | F3: =TCD!F4 -> 9543814314757247 | H3: =H2 -> E | I3: =I2 -> FR | J3: =J2 -> France | K3: {=IF(COUNTIF('Nb colis et poids'!A:A,F3)=0,1,LOOKUP(F3,'Nb colis et poids'!A:A,'Nb colis et poids'!B:B+1))} -> 5 | L3: =TCD!E4 -> 76.9 | M3: =M2 -> ST | N3: =N2 -> 0.2 | Q3: =IF(TCD!J4="","",TCD!J4) | R3: =IF(TCD!G4="","",TCD!G4) | T3: =TCD!H4 -> 27.91
A4: =A3 -> TNT | B4: =B3 -> 46174 | F4: =TCD!F5 -> 9543814314756996 | H4: =H3 -> E | I4: =I3 -> FR | J4: =J3 -> France | K4: {=IF(COUNTIF('Nb colis et poids'!A:A,F4)=0,1,LOOKUP(F4,'Nb colis et poids'!A:A,'Nb colis et poids'!B:B+1))} -> 1 | L4: =TCD!E5 -> 18 | M4: =M3 -> ST | N4: =N3 -> 0.2 | Q4: =IF(TCD!J5="","",TCD!J5) | R4: =IF(TCD!G5="","",TCD!G5) | T4: =TCD!H5 -> 8.57
A5: =A4 -> TNT | B5: =B4 -> 46174 | F5: =TCD!F6 -> 9543814314755656 | H5: =H4 -> E | I5: =I4 -> FR | J5: =J4 -> France | K5: {=IF(COUNTIF('Nb colis et poids'!A:A,F5)=0,1,LOOKUP(F5,'Nb colis et poids'!A:A,'Nb colis et poids'!B:B+1))} -> 1 | L5: =TCD!E6 -> 3.01 | M5: =M4 -> ST | N5: =N4 -> 0.2 | Q5: =IF(TCD!J6="","",TCD!J6) | R5: =IF(TCD!G6="","",TCD!G6) | T5: =TCD!H6 -> 4.93
A6: =A5 -> TNT | B6: =B5 -> 46174 | F6: =TCD!F7 -> 9543814314754754 | H6: =H5 -> E | I6: =I5 -> FR | J6: =J5 -> France | K6: {=IF(COUNTIF('Nb colis et poids'!A:A,F6)=0,1,LOOKUP(F6,'Nb colis et poids'!A:A,'Nb colis et poids'!B:B+1))} -> 1 | L6: =TCD!E7 -> 0.8 | M6: =M5 -> ST | N6: =N5 -> 0.2 | Q6: =IF(TCD!J7="","",TCD!J7) | R6: =IF(TCD!G7="","",TCD!G7) | T6: =TCD!H7 -> 4.15
A7: =A6 -> TNT | B7: =B6 -> 46174 | F7: =TCD!F8 -> 9524024014087290 | H7: =H6 -> E | I7: =I6 -> FR | J7: =J6 -> France | K7: {=IF(COUNTIF('Nb colis et poids'!A:A,F7)=0,1,LOOKUP(F7,'Nb colis et poids'!A:A,'Nb colis et poids'!B:B+1))} -> 1 | L7: =TCD!E8 -> 0.8 | M7: =M6 -> ST | N7: =N6 -> 0.2 | Q7: =IF(TCD!J8="","",TCD!J8) | R7: =IF(TCD!G8="","",TCD!G8) | T7: =TCD!H8 -> 4.15
A8: =A7 -> TNT | B8: =B7 -> 46174 | F8: =TCD!F9 -> 9443814314757475 | H8: =H7 -> E | I8: =I7 -> FR | J8: =J7 -> France | K8: {=IF(COUNTIF('Nb colis et poids'!A:A,F8)=0,1,LOOKUP(F8,'Nb colis et poids'!A:A,'Nb colis et poids'!B:B+1))} -> 2 | L8: =TCD!E9 -> 33.9 | M8: =M7 -> ST | N8: =N7 -> 0.2 | Q8: =IF(TCD!J9="","",TCD!J9) | R8: =IF(TCD!G9="","",TCD!G9) | T8: =TCD!H9 -> 13.73
A9: =A8 -> TNT | B9: =B8 -> 46174 | F9: =TCD!F10 -> 9443814314756452 | H9: =H8 -> E | I9: =I8 -> FR | J9: =J8 -> France | K9: {=IF(COUNTIF('Nb colis et poids'!A:A,F9)=0,1,LOOKUP(F9,'Nb colis et poids'!A:A,'Nb colis et poids'!B:B+1))} -> 1 | L9: =TCD!E10 -> 0.8 | M9: =M8 -> ST | N9: =N8 -> 0.2 | Q9: =IF(TCD!J10="","",TCD!J10) | R9: =IF(TCD!G10="","",TCD!G10) | T9: =TCD!H10 -> 4.15
A10: =A9 -> TNT | B10: =B9 -> 46174 | F10: =TCD!F11 -> 9443814314756240 | H10: =H9 -> E | I10: =I9 -> FR | J10: =J9 -> France | K10: {=IF(COUNTIF('Nb colis et poids'!A:A,F10)=0,1,LOOKUP(F10,'Nb colis et poids'!A:A,'Nb colis et poids'!B:B+1))} -> 1 | L10: =TCD!E11 -> 0.8 | M10: =M9 -> ST | N10: =N9 -> 0.2 | Q10: =IF(TCD!J11="","",TCD!J11) | R10: =IF(TCD!G11="","",TCD!G11) | T10: =TCD!H11 -> 4.15
A11: =A10 -> TNT | B11: =B10 -> 46174 | F11: =TCD!F12 -> 9443814314756072 | H11: =H10 -> E | I11: =I10 -> FR | J11: =J10 -> France | K11: {=IF(COUNTIF('Nb colis et poids'!A:A,F11)=0,1,LOOKUP(F11,'Nb colis et poids'!A:A,'Nb colis et poids'!B:B+1))} -> 1 | L11: =TCD!E12 -> 0.8 | M11: =M10 -> ST | N11: =N10 -> 0.2 | Q11: =IF(TCD!J12="","",TCD!J12) | R11: =IF(TCD!G12="","",TCD!G12) | T11: =TCD!H12 -> 4.15
A12: =A11 -> TNT | B12: =B11 -> 46174 | F12: =TCD!F13 -> 9443814314755728 | H12: =H11 -> E | I12: =I11 -> FR | J12: =J11 -> France | K12: {=IF(COUNTIF('Nb colis et poids'!A:A,F12)=0,1,LOOKUP(F12,'Nb colis et poids'!A:A,'Nb colis et poids'!B:B+1))} -> 1 | L12: =TCD!E13 -> 2.84 | M12: =M11 -> ST | N12: =N11 -> 0.2 | Q12: =IF(TCD!J13="","",TCD!J13) | R12: =IF(TCD!G13="","",TCD!G13) | T12: =TCD!H13 -> 4.67
A13: =A12 -> TNT | B13: =B12 -> 46174 | F13: =TCD!F14 -> 9443814314754803 | H13: =H12 -> E | I13: =I12 -> FR | J13: =J12 -> France | K13: {=IF(COUNTIF('Nb colis et poids'!A:A,F13)=0,1,LOOKUP(F13,'Nb colis et poids'!A:A,'Nb colis et poids'!B:B+1))} -> 1 | L13: =TCD!E14 -> 3.2 | M13: =M12 -> ST | N13: =N12 -> 0.2 | Q13: =IF(TCD!J14="","",TCD!J14) | R13: =IF(TCD!G14="","",TCD!G14) | T13: =TCD!H14 -> 4.93
A14: =A13 -> TNT | B14: =B13 -> 46174 | F14: =TCD!F15 -> 9443814314754050 | H14: =H13 -> E | I14: =I13 -> FR | J14: =J13 -> France | K14: {=IF(COUNTIF('Nb colis et poids'!A:A,F14)=0,1,LOOKUP(F14,'Nb colis et poids'!A:A,'Nb colis et poids'!B:B+1))} -> 1 | L14: =TCD!E15 -> 3.6 | M14: =M13 -> ST | N14: =N13 -> 0.2 | Q14: =IF(TCD!J15="","",TCD!J15) | R14: =IF(TCD!G15="","",TCD!G15) | T14: =TCD!H15 -> 4.93
... A515: =A514 -> TNT | B515: =B514 -> 46174 | F515: =TCD!F516 -> 0143814314751704 | H515: =H514 -> E | I515: =I514 -> FR | J515: =J514 -> France | K515: {=IF(COUNTIF('Nb colis et poids'!A:A,F515)=0,1,LOOKUP(F515,'Nb colis et poids'!A:A,'Nb colis et poids'!B:B+1))} -> 1 | L515: =TCD!E516 -> 1.34 | M515: =M514 -> ST | N515: =N514 -> 0.2 | Q515: =IF(TCD!J516="","",TCD!J516) | R515: =IF(TCD!G516="","",TCD!G516) | T515: =TCD!H516 -> 4.41

Sheet Demande d'avoir
A1: Trackings | B1: Raison | C1: Montant | D1: Suivi
A2: 2183814314002910 | B2: impossible d'identifier le client | C2: 4.15
A3: 2183814314003016 | B3: impossible d'identifier le client | C3: 4.15
A4: 2183814314003000 | B4: impossible d'identifier le client | C4: 4.15
A5: 2183814314002995 | B5: impossible d'identifier le client | C5: 4.15
A6: 1424014009525861. | B6: impossible d'identifier le client aucun suivis | C6: 14.25
A7: 2183814314003195 | B7: impossible d'identifier le client | C7: 14.13
A8: 2183814314003143. | B8: impossible d'identifier le client | C8: 4.41
A9: 2183814314003137. | B9: impossible d'identifier le client | C9: 4.15
A10: 2183814314003125. | B10: impossible d'identifier le client | C10: 8.53
A11: 2183814314003108. | B11: impossible d'identifier le client | C11: 4.15
A12: 2183814314003097 | B12: impossible d'identifier le client | C12: 11.31
A13: 2183814314003051. | B13: impossible d'identifier le client | C13: 6.15
A14: 2183814314003022 | B14: impossible d'identifier le client | C14: 6.23
