Workbook

Sheet PA GLS
A1: 0.5 | B1: 3.77
A2: 1 | B2: 4.1
A3: 2 | B3: 4.42
A4: 3 | B4: 4.74
A5: 4 | B5: 5.3
A6: 5 | B6: 5.86
A7: 6 | B7: 6.42
A8: 7 | B8: 6.98
A9: 8 | B9: 7.61
A10: 9 | B10: 8.26
A11: 10 | B11: 8.89
A12: 11 | B12: 9.53
... A31: 30 | B31: 28.59

Sheet Zoning
A1: Pays | B1: Zone | C1: TVA
A2: AD | B2: 2 | C2: 0.2
A3: AT | B3: 3 | C3: 0.2
A4: BE | B4: 1 | C4: 0.2
A5: BG | B5: 4 | C5: 0.2
A6: CH | B6: 3 | C6: 0
A7: CY | B7: 5 | C7: 0.2
A8: CZ | B8: 2 | C8: 0.2
A9: DE | B9: 1 | C9: 0.2
A10: DK | B10: 2 | C10: 0.2
A11: EE | B11: 4 | C11: 0.2
A12: ES | B12: 2 | C12: 0.2
A13: FI | B13: 4 | C13: 0.2
A14: FR | B14: France | C14: 0.2
A15: GB | B15: 3 | C15: 0.2
A16: GI | B16: 2 | C16: 0.2
A17: GR | B17: 5 | C17: 0.2
A18: HR | B18: 4 | C18: 0.2
A19: HU | B19: 2 | C19: 0.2
A20: IE | B20: 4 | C20: 0.2
A21: IT | B21: 2 | C21: 0.2
A22: LI | B22: 3 | C22: 0.2
A23: LU | B23: 1 | C23: 0.2
A24: LT | B24: 4 | C24: 0.2
A25: LV | B25: 4 | C25: 0.2
A26: MT | B26: 5 | C26: 0.2
... A38: VA | B38: 2 | C38: 0.2

Sheet Poids
A1: Étiquettes de lignes | B1: Max. de Poids pour le traitement commande vente | C1: poids | D1: poids < 500 g | E1: poids > 500 g | G1: poids < 500 g | H1: =SUM(D:D) -> 113 | I1: =H1/SUM(H1:H2) -> 0.26650943
A2: 00KUR5TU | B2: 0 | C2: =ROUNDUP(B2,1) -> 0 | D2: =IF(C2=0,0,IF(C2<=0.5,1,0)) -> 0 | E2: =IF(C2=0,0,1-D2) -> 0 | G2: poids > 500 g | H2: =SUM(E:E) -> 311
A3: 00KUR5TX | B3: 0.25 | C3: =ROUNDUP(B3,1) -> 0.3 | D3: =IF(C3=0,0,IF(C3<=0.5,1,0)) -> 1 | E3: =IF(C3=0,0,1-D3) -> 0
A4: 00KUR5TY | B4: 0.28 | C4: =ROUNDUP(B4,1) -> 0.3 | D4: =IF(C4=0,0,IF(C4<=0.5,1,0)) -> 1 | E4: =IF(C4=0,0,1-D4) -> 0
A5: 00KUR5TZ | B5: 0.26 | C5: =ROUNDUP(B5,1) -> 0.3 | D5: =IF(C5=0,0,IF(C5<=0.5,1,0)) -> 1 | E5: =IF(C5=0,0,1-D5) -> 0
A6: 00KUR5U0 | B6: 0.28 | C6: =ROUNDUP(B6,1) -> 0.3 | D6: =IF(C6=0,0,IF(C6<=0.5,1,0)) -> 1 | E6: =IF(C6=0,0,1-D6) -> 0
A7: 00KUR5U1 | B7: 0.54 | C7: =ROUNDUP(B7,1) -> 0.6 | D7: =IF(C7=0,0,IF(C7<=0.5,1,0)) -> 0 | E7: =IF(C7=0,0,1-D7) -> 1
A8: 00KUR5U2 | B8: 0.28 | C8: =ROUNDUP(B8,1) -> 0.3 | D8: =IF(C8=0,0,IF(C8<=0.5,1,0)) -> 1 | E8: =IF(C8=0,0,1-D8) -> 0
A9: 00KUR5U3 | B9: 0.3 | C9: =ROUNDUP(B9,1) -> 0.3 | D9: =IF(C9=0,0,IF(C9<=0.5,1,0)) -> 1 | E9: =IF(C9=0,0,1-D9) -> 0
A10: 00KUR5U4 | B10: 0.54 | C10: =ROUNDUP(B10,1) -> 0.6 | D10: =IF(C10=0,0,IF(C10<=0.5,1,0)) -> 0 | E10: =IF(C10=0,0,1-D10) -> 1
A11: 00KUR5U5 | B11: 0.56 | C11: =ROUNDUP(B11,1) -> 0.6 | D11: =IF(C11=0,0,IF(C11<=0.5,1,0)) -> 0 | E11: =IF(C11=0,0,1-D11) -> 1
A12: 00KUR5U6 | B12: 0.72 | C12: =ROUNDUP(B12,1) -> 0.8 | D12: =IF(C12=0,0,IF(C12<=0.5,1,0)) -> 0 | E12: =IF(C12=0,0,1-D12) -> 1
A13: 00KUR5U7 | B13: 0.48 | C13: =ROUNDUP(B13,1) -> 0.5 | D13: =IF(C13=0,0,IF(C13<=0.5,1,0)) -> 1 | E13: =IF(C13=0,0,1-D13) -> 0
A14: 00KUR5U8 | B14: 0.58 | C14: =ROUNDUP(B14,1) -> 0.6 | D14: =IF(C14=0,0,IF(C14<=0.5,1,0)) -> 0 | E14: =IF(C14=0,0,1-D14) -> 1
... A428: (vide) | B428: 0 | C428: =ROUNDUP(B428,1) -> 0 | D428: =IF(C428=0,0,IF(C428<=0.5,1,0)) -> 0 | E428: =IF(C428=0,0,1-D428) -> 0
A1348: zz

Sheet Comptes GLS
A1: Présence | B1: NÂ° compte exploit. | C1: Nom compte exploit. | E1: NÂ° compte exploit. | F1: Nom compte exploit. | G1: ID
A2: =COUNTIF(E:E,B2) -> 1 | B2: 9000037814 | C2: LA RUCHE | E2: 9000037814 | F2: LA RUCHE
A3: =COUNTIF(E:E,B3) -> 1 | B3: 9000079829 | C3: ANOTHER WAY | E3: 9000079828 | F3: ALL MY KETO | G3: 6259
A4: =COUNTIF(E:E,B4) -> 1 | B4: 9000079830 | C4: BY FOUTAS | E4: 9000079829 | F4: ANOTHER WAY | G4: 4565
A5: =COUNTIF(E:E,B5) -> 1 | B5: 9000082822 | C5: Laboratoires Christian Roche | E5: 9000079830 | F5: BY FOUTAS | G5: 3888
A6: =COUNTIF(E:E,B6) -> 1 | B6: 9000084612 | C6: EQUILIBRE CBD | E6: 9000079831 | F6: Prairymood | G6: 6210
A7: =COUNTIF(E:E,B7) -> 0 | B7: (vide) | C7: (vide) | E7: 9000079832 | F7: Le vapoteur tranquille | G7: 3997
E8: 9000079833 | F8: Atomic soda | G8: 6294
A9: 1 | E9: 9000081899 | F9: AÃ„SGARD | G9: 6262
E10: 9000082004 | F10: MOWLY | G10: 6516
E11: 9000082421 | F11: DRUYDES | G11: 6652
E12: 9000082422 | F12: HYDRATIS | G12: 3752
E13: 9000082423 | F13: NOSC | G13: 6665
E14: 9000082814 | F14: EDRA | G14: 6685
E15: 9000082815 | F15: DÃ©couvre Bitcoin | G15: 6705
E16: 9000082821 | F16: KERBI | G16: 6741
E17: 9000082822 | F17: Laboratoires Christian Roche | G17: 6739
E18: 9000083106 | F18: Par un Curieux Hasard | G18: 6814
E19: 9000083593 | F19: SpineFootwear | G19: 6639
E20: 9000083758 | F20: WISE | G20: 6851
E21: 9000083759 | F21: ADOPTE UN BRASSEUR | G21: 6910
... E25: 9000152816 | F25: ONEGUM | G25: 7494

Sheet Catégories
A1: Catégorie GLS | B1: Catégorie ERP | C1: Désignation article
A2: EXPREDOMESSTANDARD | B2: Frêt
A3: PARCEDOMESFDS | B3: Frêt | C3: BP FlexDelivery - Dis. 01 - Size 01
A4: PARCEDOMESPRTN | B4: Frêt - retour
A5: PARCEDOMESPSHP | B5: Frêt
A6: PARCEDOMESSHDS | B6: Frêt
A7: PARCEDOMESSTANDARD | B7: Frêt | C7: Business Parcel - Dis. 01 - Size 01
A8: PARCEEUROPFDS | B8: Frêt | C8: Euro FlexDelivery - Dis. 11 - Size 01
A9: PARCEEUROPSTANDARD | B9: Frêt | C9: EuroBusiness Parcel - Dis. 12 - S. 13
A10: PARCEGLOBASTANDARD | B10: Frêt
A11: SERVIALL FDS | B11: Frêt | C11: Service - FDS - Remise
A12: SURCHALL | B12: Frêt - avisé | C12: AvisÃ© FDS
A13: SURCHALL ADM | B13: Frais de gestion | C13: Frais de Gestion
A14: SURCHALL BPTOC | B14: Frêt
A15: SURCHALL GEO | B15: Zone éloignée
A16: SURCHALL NC | B16: Colis volumineux
A17: SURCHALL NTFCNCRD | B17: Adresse | C17: Majoration AvisÃ© sans TÃ©l ou mail
A18: SURCHALL PCKNOPAR | B18: Adresse
A19: SURCHALL RETURN | B19: Frêt - retour | C19: Retour Colis BUP - Classe 01
A20: SURCHALL SNGLPRCL | B20: ZZ_Ramasse unicolis | C20: Ramassage Uni - Colis - Type 01

Sheet Facture GLS
A1: Catégorie | B1: Total HT | C1: Gazole | D1: Total HT (hors gazole) | E1: Poids | F1: Facture | G1: Document de vente | H1: Date de la facture | I1: nÂ° client | J1: raison sociale | K1: nÂ° chargeur | L1: chargeur Alpha | M1: Nom chargeur | N1: NÂ° compte exploit. | O1: Nom compte exploit. | P1: Nom 2 | Q1: Nom 3 | R1: Nom 4 | S1: nÂ° payer | T1: Nom payer | U1: Groupe d'articles | V1: Article | W1: DÃ©signation article | X1: HiÃ©rarchie produits | Y1: PRICING_COND | Z1: Poste | AA1: Date jour | AB1: NumÃ©ro de colis | AC1: Numero Colis interne | AD1: Consignation ID | AE1: nombre de points | AF1: QuantitÃ© facturÃ©e | AG1: Nombre de colis | AH1: Poids pour le traitement commande vente | AI1: UnitÃ© de qtÃ© base | AJ1: Valeur de Base | AK1: CSR | AL1: PER | AM1: Taux SGO % | AN1: SGO | AO1: prix kilos additionnel | AP1: Saisie manuelle | AQ1: Monnaie ADV | AR1: Client RÃ©fÃ©rence | AS1: Client RÃ©fÃ©rence 1 | AT1: Client RÃ©fÃ©rence 2 | AU1: Client RÃ©fÃ©rence 3 | AV1: adresse de destination NOM | AW1: adresse de dest. ADR1 | AX1: adresse de destination ADR2 | AY1: adresse de destination ADR3 | AZ1: adresse de destination CP | BA1: adresse de destination VILLE | BB1: Code Pays | BC1: Pays | BD1: DSV_TRANSITNO
A2: =IF(COUNTIF(Catégories!A:A,X2)=0,"catégorie inconnue",_xlfn.XLOOKUP(X2,Catégories!A:A,Catégories!B:B)) -> Frêt | B2: =SUM(AJ2:AL2)+SUM(AN2:AP2) -> 7.43 | C2: =AN2 -> 1.64 | D2: =B2-C2 -> 5.79 | E2: =IF(AH2<>0,ROUNDUP(AH2,0),IF(BB2<>"FR","hors France",IF(AH2<>0,ROUNDUP(AH2,0),_xlfn.XLOOKUP(AJ2,'PA GLS'!B:B,'PA GLS'!A:A)))) -> 3 | F2: 2501382993 | G2: 1030231978 | H2: 30.06.2026 | I2: 2500034092 | J2: LA RUCHE LOGISTIQUE | K2: 9000009190 | L2: 46946 | M2: LA RUCHE | N2: 9000079830 | O2: BY FOUTAS | S2: 2507012387 | T2: LA RUCHE LOGISTIQUE | U2: FDS | V2: PARCEL_D01_S07 | W2: Business Parcel - Dis. 01 - Size 07 | X2: PARCEDOMESSTANDARD | Z2: 143 | AA2: 01.06.2026 | AB2: 00KZZJTF | AC2: 2604000030 | AE2: 0 | AF2: 0 | AG2: 0 | AH2: 0 | AI2: KG | AJ2: 4.74 | AK2: 0.9 | AL2: 0.15 | AM2: 29.1 | AN2: 1.64 | AO2: 0 | AP2: 0 | AQ2: EUR | AS2: EXP20260530-2770811- | AT2: EXP20260530-2770811- | AU2: 00KZZJTF | AV2: BERIOT LOUISE | AW2: 119 RUE DE LEGLISE | AZ2: 60140 | BA2: LABRUYERE | BB2: FR | BC2: France
A3: =IF(COUNTIF(Catégories!A:A,X3)=0,"catégorie inconnue",_xlfn.XLOOKUP(X3,Catégories!A:A,Catégories!B:B)) -> Frêt | B3: =SUM(AJ3:AL3)+SUM(AN3:AP3) -> 7.43 | C3: =AN3 -> 1.64 | D3: =B3-C3 -> 5.79 | E3: =IF(AH3<>0,ROUNDUP(AH3,0),IF(BB3<>"FR","hors France",IF(AH3<>0,ROUNDUP(AH3,0),_xlfn.XLOOKUP(AJ3,'PA GLS'!B:B,'PA GLS'!A:A)))) -> 3 | F3: 2501382993 | G3: 1030231978 | H3: 30.06.2026 | I3: 2500034092 | J3: LA RUCHE LOGISTIQUE | K3: 9000009190 | L3: 46946 | M3: LA RUCHE | N3: 9000079830 | O3: BY FOUTAS | S3: 2507012387 | T3: LA RUCHE LOGISTIQUE | U3: FDS | V3: PARCEL_D01_S07 | W3: Business Parcel - Dis. 01 - Size 07 | X3: PARCEDOMESSTANDARD | Z3: 143 | AA3: 01.06.2026 | AB3: 00KZZJTD | AC3: 2604000028 | AE3: 0 | AF3: 0 | AG3: 0 | AH3: 0 | AI3: KG | AJ3: 4.74 | AK3: 0.9 | AL3: 0.15 | AM3: 29.1 | AN3: 1.64 | AO3: 0 | AP3: 0 | AQ3: EUR | AS3: EXP20260529-2769727- | AT3: EXP20260529-2769727- | AU3: 00KZZJTD | AV3: GENDRON CARINE | AW3: 4 LOTISSEMENT PARK KOZH | AZ3: 29590 | BA3: SAINT-SEGAL | BB3: FR | BC3: France
A4: =IF(COUNTIF(Catégories!A:A,X4)=0,"catégorie inconnue",_xlfn.XLOOKUP(X4,Catégories!A:A,Catégories!B:B)) -> Frêt | B4: =SUM(AJ4:AL4)+SUM(AN4:AP4) -> 7.01 | C4: =AN4 -> 1.54 | D4: =B4-C4 -> 5.47 | E4: =IF(AH4<>0,ROUNDUP(AH4,0),IF(BB4<>"FR","hors France",IF(AH4<>0,ROUNDUP(AH4,0),_xlfn.XLOOKUP(AJ4,'PA GLS'!B:B,'PA GLS'!A:A)))) -> 2 | F4: 2501382993 | G4: 1030231978 | H4: 30.06.2026 | I4: 2500034092 | J4: LA RUCHE LOGISTIQUE | K4: 9000009190 | L4: 46946 | M4: LA RUCHE | N4: 9000079830 | O4: BY FOUTAS | S4: 2507012387 | T4: LA RUCHE LOGISTIQUE | U4: FDS | V4: PARCEL_D01_S06 | W4: Business Parcel - Dis. 01 - Size 06 | X4: PARCEDOMESSTANDARD | Z4: 142 | AA4: 01.06.2026 | AB4: 00KZZJTH | AC4: 2604000032 | AE4: 0 | AF4: 0 | AG4: 0 | AH4: 0 | AI4: KG | AJ4: 4.42 | AK4: 0.9 | AL4: 0.15 | AM4: 29.1 | AN4: 1.54 | AO4: 0 | AP4: 0 | AQ4: EUR | AS4: EXP20260529-2770182- | AT4: EXP20260529-2770182- | AU4: 00KZZJTH | AV4: KORMAS CELINE | AW4: 110 ROUTE DE THONES | AZ4: 74940 | BA4: ANNECY | BB4: FR | BC4: France
A5: =IF(COUNTIF(Catégories!A:A,X5)=0,"catégorie inconnue",_xlfn.XLOOKUP(X5,Catégories!A:A,Catégories!B:B)) -> Frêt | B5: =SUM(AJ5:AL5)+SUM(AN5:AP5) -> 7.01 | C5: =AN5 -> 1.54 | D5: =B5-C5 -> 5.47 | E5: =IF(AH5<>0,ROUNDUP(AH5,0),IF(BB5<>"FR","hors France",IF(AH5<>0,ROUNDUP(AH5,0),_xlfn.XLOOKUP(AJ5,'PA GLS'!B:B,'PA GLS'!A:A)))) -> 2 | F5: 2501382993 | G5: 1030231978 | H5: 30.06.2026 | I5: 2500034092 | J5: LA RUCHE LOGISTIQUE | K5: 9000009190 | L5: 46946 | M5: LA RUCHE | N5: 9000079830 | O5: BY FOUTAS | S5: 2507012387 | T5: LA RUCHE LOGISTIQUE | U5: FDS | V5: PARCEL_D01_S06 | W5: Business Parcel - Dis. 01 - Size 06 | X5: PARCEDOMESSTANDARD | Z5: 142 | AA5: 01.06.2026 | AB5: 00KZZJT9 | AC5: 2604000024 | AE5: 0 | AF5: 0 | AG5: 0 | AH5: 0 | AI5: KG | AJ5: 4.42 | AK5: 0.9 | AL5: 0.15 | AM5: 29.1 | AN5: 1.54 | AO5: 0 | AP5: 0 | AQ5: EUR | AS5: EXP20260529-2769320- | AT5: EXP20260529-2769320- | AU5: 00KZZJT9 | AV5: COSTE DE BAGNEAUX JUSTINE | AW5: 46 RUE LOUIS PETRI | AZ5: 35200 | BA5: RENNES | BB5: FR | BC5: France
A6: =IF(COUNTIF(Catégories!A:A,X6)=0,"catégorie inconnue",_xlfn.XLOOKUP(X6,Catégories!A:A,Catégories!B:B)) -> Frêt | B6: =SUM(AJ6:AL6)+SUM(AN6:AP6) -> 7.01 | C6: =AN6 -> 1.54 | D6: =B6-C6 -> 5.47 | E6: =IF(AH6<>0,ROUNDUP(AH6,0),IF(BB6<>"FR","hors France",IF(AH6<>0,ROUNDUP(AH6,0),_xlfn.XLOOKUP(AJ6,'PA GLS'!B:B,'PA GLS'!A:A)))) -> 2 | F6: 2501382993 | G6: 1030231978 | H6: 30.06.2026 | I6: 2500034092 | J6: LA RUCHE LOGISTIQUE | K6: 9000009190 | L6: 46946 | M6: LA RUCHE | N6: 9000079830 | O6: BY FOUTAS | S6: 2507012387 | T6: LA RUCHE LOGISTIQUE | U6: FDS | V6: PARCEL_D01_S05 | W6: Business Parcel - Dis. 01 - Size 05 | X6: PARCEDOMESSTANDARD | Z6: 141 | AA6: 01.06.2026 | AB6: 00KZZJTG | AC6: 2604000031 | AE6: 0 | AF6: 0 | AG6: 0 | AH6: 0 | AI6: KG | AJ6: 4.42 | AK6: 0.9 | AL6: 0.15 | AM6: 29.1 | AN6: 1.54 | AO6: 0 | AP6: 0 | AQ6: EUR | AS6: EXP20260530-2770970- | AT6: EXP20260530-2770970- | AU6: 00KZZJTG | AV6: REAL CHARLES | AW6: 8 RUE RUHMKORFF | AZ6: 75017 | BA6: PARIS | BB6: FR | BC6: France
A7: =IF(COUNTIF(Catégories!A:A,X7)=0,"catégorie inconnue",_xlfn.XLOOKUP(X7,Catégories!A:A,Catégories!B:B)) -> Frêt | B7: =SUM(AJ7:AL7)+SUM(AN7:AP7) -> 7.01 | C7: =AN7 -> 1.54 | D7: =B7-C7 -> 5.47 | E7: =IF(AH7<>0,ROUNDUP(AH7,0),IF(BB7<>"FR","hors France",IF(AH7<>0,ROUNDUP(AH7,0),_xlfn.XLOOKUP(AJ7,'PA GLS'!B:B,'PA GLS'!A:A)))) -> 2 | F7: 2501382993 | G7: 1030231978 | H7: 30.06.2026 | I7: 2500034092 | J7: LA RUCHE LOGISTIQUE | K7: 9000009190 | L7: 46946 | M7: LA RUCHE | N7: 9000079830 | O7: BY FOUTAS | S7: 2507012387 | T7: LA RUCHE LOGISTIQUE | U7: FDS | V7: PARCEL_D01_S05 | W7: Business Parcel - Dis. 01 - Size 05 | X7: PARCEDOMESSTANDARD | Z7: 141 | AA7: 01.06.2026 | AB7: 00KZZJTA | AC7: 2604000025 | AE7: 0 | AF7: 0 | AG7: 0 | AH7: 0 | AI7: KG | AJ7: 4.42 | AK7: 0.9 | AL7: 0.15 | AM7: 29.1 | AN7: 1.54 | AO7: 0 | AP7: 0 | AQ7: EUR | AS7: EXP20260529-2769726- | AT7: EXP20260529-2769726- | AU7: 00KZZJTA | AV7: GABORIT CLARISSE | AW7: 15 RUE DE LA LIBERTE | AZ7: 92150 | BA7: SURESNES | BB7: FR | BC7: France
A8: =IF(COUNTIF(Catégories!A:A,X8)=0,"catégorie inconnue",_xlfn.XLOOKUP(X8,Catégories!A:A,Catégories!B:B)) -> Frêt | B8: =SUM(AJ8:AL8)+SUM(AN8:AP8) -> 6.6 | C8: =AN8 -> 1.45 | D8: =B8-C8 -> 5.15 | E8: =IF(AH8<>0,ROUNDUP(AH8,0),IF(BB8<>"FR","hors France",IF(AH8<>0,ROUNDUP(AH8,0),_xlfn.XLOOKUP(AJ8,'PA GLS'!B:B,'PA GLS'!A:A)))) -> 1 | F8: 2501382993 | G8: 1030231978 | H8: 30.06.2026 | I8: 2500034092 | J8: LA RUCHE LOGISTIQUE | K8: 9000009190 | L8: 46946 | M8: LA RUCHE | N8: 9000079830 | O8: BY FOUTAS | S8: 2507012387 | T8: LA RUCHE LOGISTIQUE | U8: FDS | V8: PARCEL_D01_S04 | W8: Business Parcel - Dis. 01 - Size 04 | X8: PARCEDOMESSTANDARD | Z8: 140 | AA8: 01.06.2026 | AB8: 00KZZJTC | AC8: 2604000027 | AE8: 0 | AF8: 0 | AG8: 0 | AH8: 0 | AI8: KG | AJ8: 4.1 | AK8: 0.9 | AL8: 0.15 | AM8: 29.1 | AN8: 1.45 | AO8: 0 | AP8: 0 | AQ8: EUR | AS8: EXP20260529-2769287- | AT8: EXP20260529-2769287- | AU8: 00KZZJTC | AV8: HEUBES CAROLINE | AW8: 29 AVENUE FELIX FAURE | AZ8: 75015 | BA8: PARIS | BB8: FR | BC8: France
A9: =IF(COUNTIF(Catégories!A:A,X9)=0,"catégorie inconnue",_xlfn.XLOOKUP(X9,Catégories!A:A,Catégories!B:B)) -> Frêt | B9: =SUM(AJ9:AL9)+SUM(AN9:AP9) -> 6.6 | C9: =AN9 -> 1.45 | D9: =B9-C9 -> 5.15 | E9: =IF(AH9<>0,ROUNDUP(AH9,0),IF(BB9<>"FR","hors France",IF(AH9<>0,ROUNDUP(AH9,0),_xlfn.XLOOKUP(AJ9,'PA GLS'!B:B,'PA GLS'!A:A)))) -> 1 | F9: 2501382993 | G9: 1030231978 | H9: 30.06.2026 | I9: 2500034092 | J9: LA RUCHE LOGISTIQUE | K9: 9000009190 | L9: 46946 | M9: LA RUCHE | N9: 9000079830 | O9: BY FOUTAS | S9: 2507012387 | T9: LA RUCHE LOGISTIQUE | U9: FDS | V9: PARCEL_D01_S04 | W9: Business Parcel - Dis. 01 - Size 04 | X9: PARCEDOMESSTANDARD | Z9: 140 | AA9: 01.06.2026 | AB9: 00KZZJTB | AC9: 2604000026 | AE9: 0 | AF9: 0 | AG9: 0 | AH9: 0 | AI9: KG | AJ9: 4.1 | AK9: 0.9 | AL9: 0.15 | AM9: 29.1 | AN9: 1.45 | AO9: 0 | AP9: 0 | AQ9: EUR | AS9: EXP20260529-2769423- | AT9: EXP20260529-2769423- | AU9: 00KZZJTB | AV9: HERVOUET DOMINIQUE | AW9: 10 IMPASSE DE LA DOUETTEE | AZ9: 44120 | BA9: VERTOU | BB9: FR | BC9: France
A10: =IF(COUNTIF(Catégories!A:A,X10)=0,"catégorie inconnue",_xlfn.XLOOKUP(X10,Catégories!A:A,Catégories!B:B)) -> Frêt | B10: =SUM(AJ10:AL10)+SUM(AN10:AP10) -> 6.17 | C10: =AN10 -> 1.35 | D10: =B10-C10 -> 4.82 | E10: =IF(AH10<>0,ROUNDUP(AH10,0),IF(BB10<>"FR","hors France",IF(AH10<>0,ROUNDUP(AH10,0),_xlfn.XLOOKUP(AJ10,'PA GLS'!B:B,'PA GLS'!A:A)))) -> 0.5 | F10: 2501382993 | G10: 1030231978 | H10: 30.06.2026 | I10: 2500034092 | J10: LA RUCHE LOGISTIQUE | K10: 9000009190 | L10: 46946 | M10: LA RUCHE | N10: 9000079830 | O10: BY FOUTAS | S10: 2507012387 | T10: LA RUCHE LOGISTIQUE | U10: FDS | V10: PARCEL_D01_S02 | W10: Business Parcel - Dis. 01 - Size 02 | X10: PARCEDOMESSTANDARD | Z10: 139 | AA10: 01.06.2026 | AB10: 00KZZJTE | AC10: 2604000029 | AE10: 0 | AF10: 0 | AG10: 0 | AH10: 0 | AI10: KG | AJ10: 3.77 | AK10: 0.9 | AL10: 0.15 | AM10: 29.1 | AN10: 1.35 | AO10: 0 | AP10: 0 | AQ10: EUR | AS10: EXP20260529-2770183- | AT10: EXP20260529-2770183- | AU10: 00KZZJTE | AV10: CALLENDRET TIFFANY | AW10: 206 CHEMIN DE NARBAN | AZ10: 38510 | BA10: ST VICTOR DE MORESTEL | BB10: FR | BC10: France
A11: =IF(COUNTIF(Catégories!A:A,X11)=0,"catégorie inconnue",_xlfn.XLOOKUP(X11,Catégories!A:A,Catégories!B:B)) -> Frêt | B11: =SUM(AJ11:AL11)+SUM(AN11:AP11) -> 0 | C11: =AN11 -> 0 | D11: =B11-C11 -> 0 | E11: =IF(AH11<>0,ROUNDUP(AH11,0),IF(BB11<>"FR","hors France",IF(AH11<>0,ROUNDUP(AH11,0),_xlfn.XLOOKUP(AJ11,'PA GLS'!B:B,'PA GLS'!A:A)))) -> 2 | F11: 2501382993 | G11: 1030231978 | H11: 30.06.2026 | I11: 2500034092 | J11: LA RUCHE LOGISTIQUE | K11: 9000009190 | L11: 46946 | M11: LA RUCHE | N11: 9000079830 | O11: BY FOUTAS | S11: 2507012387 | T11: LA RUCHE LOGISTIQUE | U11: FDS | V11: FDS_D01_S01 | W11: BP FlexDelivery - Dis. 01 - Size 01 | X11: PARCEDOMESFDS | Z11: 138 | AA11: 01.06.2026 | AB11: 00KZZJTH | AC11: 2604000032 | AE11: 0 | AF11: 1 | AG11: 0 | AH11: 1.7 | AI11: KG | AJ11: 0 | AK11: 0 | AL11: 0 | AM11: 0 | AN11: 0 | AO11: 0 | AP11: 0 | AQ11: EUR | AS11: EXP20260529-2770182- | AT11: EXP20260529-2770182- | AU11: 00KZZJTH | AV11: KORMAS CELINE | AW11: 110 ROUTE DE THONES | AZ11: 74940 | BA11: ANNECY | BB11: FR | BC11: France
A12: =IF(COUNTIF(Catégories!A:A,X12)=0,"catégorie inconnue",_xlfn.XLOOKUP(X12,Catégories!A:A,Catégories!B:B)) -> Frêt | B12: =SUM(AJ12:AL12)+SUM(AN12:AP12) -> 0 | C12: =AN12 -> 0 | D12: =B12-C12 -> 0 | E12: =IF(AH12<>0,ROUNDUP(AH12,0),IF(BB12<>"FR","hors France",IF(AH12<>0,ROUNDUP(AH12,0),_xlfn.XLOOKUP(AJ12,'PA GLS'!B:B,'PA GLS'!A:A)))) -> 2 | F12: 2501382993 | G12: 1030231978 | H12: 30.06.2026 | I12: 2500034092 | J12: LA RUCHE LOGISTIQUE | K12: 9000009190 | L12: 46946 | M12: LA RUCHE | N12: 9000079830 | O12: BY FOUTAS | S12: 2507012387 | T12: LA RUCHE LOGISTIQUE | U12: FDS | V12: FDS_D01_S01 | W12: BP FlexDelivery - Dis. 01 - Size 01 | X12: PARCEDOMESFDS | Z12: 138 | AA12: 01.06.2026 | AB12: 00KZZJTG | AC12: 2604000031 | AE12: 0 | AF12: 1 | AG12: 0 | AH12: 1.15 | AI12: KG | AJ12: 0 | AK12: 0 | AL12: 0 | AM12: 0 | AN12: 0 | AO12: 0 | AP12: 0 | AQ12: EUR | AS12: EXP20260530-2770970- | AT12: EXP20260530-2770970- | AU12: 00KZZJTG | AV12: REAL CHARLES | AW12: 8 RUE RUHMKORFF | AZ12: 75017 | BA12: PARIS | BB12: FR | BC12: France
A13: =IF(COUNTIF(Catégories!A:A,X13)=0,"catégorie inconnue",_xlfn.XLOOKUP(X13,Catégories!A:A,Catégories!B:B)) -> Frêt | B13: =SUM(AJ13:AL13)+SUM(AN13:AP13) -> 0 | C13: =AN13 -> 0 | D13: =B13-C13 -> 0 | E13: =IF(AH13<>0,ROUNDUP(AH13,0),IF(BB13<>"FR","hors France",IF(AH13<>0,ROUNDUP(AH13,0),_xlfn.XLOOKUP(AJ13,'PA GLS'!B:B,'PA GLS'!A:A)))) -> 3 | F13: 2501382993 | G13: 1030231978 | H13: 30.06.2026 | I13: 2500034092 | J13: LA RUCHE LOGISTIQUE | K13: 9000009190 | L13: 46946 | M13: LA RUCHE | N13: 9000079830 | O13: BY FOUTAS | S13: 2507012387 | T13: LA RUCHE LOGISTIQUE | U13: FDS | V13: FDS_D01_S01 | W13: BP FlexDelivery - Dis. 01 - Size 01 | X13: PARCEDOMESFDS | Z13: 138 | AA13: 01.06.2026 | AB13: 00KZZJTF | AC13: 2604000030 | AE13: 0 | AF13: 1 | AG13: 0 | AH13: 2.42 | AI13: KG | AJ13: 0 | AK13: 0 | AL13: 0 | AM13: 0 | AN13: 0 | AO13: 0 | AP13: 0 | AQ13: EUR | AS13: EXP20260530-2770811- | AT13: EXP20260530-2770811- | AU13: 00KZZJTF | AV13: BERIOT LOUISE | AW13: 119 RUE DE LEGLISE | AZ13: 60140 | BA13: LABRUYERE | BB13: FR | BC13: France
... A26: =IF(COUNTIF(Catégories!A:A,X26)=0,"catégorie inconnue",_xlfn.XLOOKUP(X26,Catégories!A:A,Catégories!B:B)) -> Frêt - avisé | B26: =SUM(AJ26:AL26)+SUM(AN26:AP26) -> 0 | C26: =AN26 -> 0 | D26: =B26-C26 -> 0 | E26: =IF(AH26<>0,ROUNDUP(AH26,0),IF(BB26<>"FR","hors France",IF(AH26<>0,ROUNDUP(AH26,0),_xlfn.XLOOKUP(AJ26,'PA GLS'!B:B,'PA GLS'!A:A)))) -> #N/A | F26: 2501382993 | G26: 1030228091 | H26: 30.06.2026 | I26: 2500034092 | J26: LA RUCHE LOGISTIQUE | K26: 9000009190 | L26: 46946 | M26: LA RUCHE | N26: 9000037814 | O26: LA RUCHE | S26: 2507012387 | T26: LA RUCHE LOGISTIQUE | U26: FDS | V26: SUR_FS_AVIS_01 | W26: AvisÃ© FDS | X26: SURCHALL | Z26: 104 | AA26: 01.06.2026 | AB26: 00KUR5TU | AC26: 2604000012 | AE26: 0 | AF26: 0 | AG26: 0 | AH26: 0 | AI26: KG | AJ26: 0 | AK26: 0 | AL26: 0 | AM26: 0 | AN26: 0 | AO26: 0 | AP26: 0 | AQ26: EUR | AS26: EXP20260528-2768458- | AT26: EXP20260528-2768458- | AU26: 00KUR5TU | AV26: CARBALLEDA ELENA | AW26: 8 RUE ALFRED DE MUSSET | AZ26: 78330 | BA26: FONTENAY-LE-FLEURY | BB26: FR | BC26: France
A27: =IF(COUNTIF(Catégories!A:A,X27)=0,"catégorie inconnue",_xlfn.XLOOKUP(X27,Catégories!A:A,Catégories!B:B)) -> Frêt | B27: =SUM(AJ27:AL27)+SUM(AN27:AP27) -> 6.17 | C27: =AN27 -> 1.35 | D27: =B27-C27 -> 4.82 | E27: =IF(AH27<>0,ROUNDUP(AH27,0),IF(BB27<>"FR","hors France",IF(AH27<>0,ROUNDUP(AH27,0),_xlfn.XLOOKUP(AJ27,'PA GLS'!B:B,'PA GLS'!A:A)))) -> 0.5 | F27: 2501382993 | G27: 1030230689 | H27: 30.06.2026 | I27: 2500034092 | J27: LA RUCHE LOGISTIQUE | K27: 9000009190 | L27: 46946 | M27: LA RUCHE | N27: 9000079829 | O27: ANOTHER WAY | S27: 2507012387 | T27: LA RUCHE LOGISTIQUE | U27: FDS | V27: PARCEL_D01_S02 | W27: Business Parcel - Dis. 01 - Size 02 | X27: PARCEDOMESSTANDARD | Z27: 110 | AA27: 02.06.2026 | AB27: 00L0EX46 | AC27: 6699599 | AE27: 0 | AF27: 0 | AG27: 0 | AH27: 0 | AI27: KG | AJ27: 3.77 | AK27: 0.9 | AL27: 0.15 | AM27: 29.1 | AN27: 1.35 | AO27: 0 | AP27: 0 | AQ27: EUR | AS27: EXP20260601-2774736 | AU27: 00L0EX46 | AV27: LEROY FANNY | AW27: 9 RUE EMILE DUBOIS | AZ27: 75014 | BA27: PARIS | BB27: FR | BC27: France
A28: =IF(COUNTIF(Catégories!A:A,X28)=0,"catégorie inconnue",_xlfn.XLOOKUP(X28,Catégories!A:A,Catégories!B:B)) -> Frêt | B28: =SUM(AJ28:AL28)+SUM(AN28:AP28) -> 0 | C28: =AN28 -> 0 | D28: =B28-C28 -> 0 | E28: =IF(AH28<>0,ROUNDUP(AH28,0),IF(BB28<>"FR","hors France",IF(AH28<>0,ROUNDUP(AH28,0),_xlfn.XLOOKUP(AJ28,'PA GLS'!B:B,'PA GLS'!A:A)))) -> 1 | F28: 2501382993 | G28: 1030230689 | H28: 30.06.2026 | I28: 2500034092 | J28: LA RUCHE LOGISTIQUE | K28: 9000009190 | L28: 46946 | M28: LA RUCHE | N28: 9000079829 | O28: ANOTHER WAY | S28: 2507012387 | T28: LA RUCHE LOGISTIQUE | U28: FDS | V28: FDS_D01_S01 | W28: BP FlexDelivery - Dis. 01 - Size 01 | X28: PARCEDOMESFDS | Z28: 109 | AA28: 02.06.2026 | AB28: 00L0EXC0 | AC28: 6699902 | AE28: 0 | AF28: 1 | AG28: 0 | AH28: 0.4 | AI28: KG | AJ28: 0 | AK28: 0 | AL28: 0 | AM28: 0 | AN28: 0 | AO28: 0 | AP28: 0 | AQ28: EUR | AS28: EXP20260601-2772297 | AU28: 00L0EXC0 | AV28: GROSSEMY MARIE-LAURE | AW28: 24, RUE DES ERABLES | AZ28: 71640 | BA28: GIVRY | BB28: FR | BC28: France
A29: =IF(COUNTIF(Catégories!A:A,X29)=0,"catégorie inconnue",_xlfn.XLOOKUP(X29,Catégories!A:A,Catégories!B:B)) -> Frêt | B29: =SUM(AJ29:AL29)+SUM(AN29:AP29) -> 0 | C29: =AN29 -> 0 | D29: =B29-C29 -> 0 | E29: =IF(AH29<>0,ROUNDUP(AH29,0),IF(BB29<>"FR","hors France",IF(AH29<>0,ROUNDUP(AH29,0),_xlfn.XLOOKUP(AJ29,'PA GLS'!B:B,'PA GLS'!A:A)))) -> 1 | F29: 2501382993 | G29: 1030230689 | H29: 30.06.2026 | I29: 2500034092 | J29: LA RUCHE LOGISTIQUE | K29: 9000009190 | L29: 46946 | M29: LA RUCHE | N29: 9000079829 | O29: ANOTHER WAY | S29: 2507012387 | T29: LA RUCHE LOGISTIQUE | U29: FDS | V29: FDS_D01_S01 | W29: BP FlexDelivery - Dis. 01 - Size 01 | X29: PARCEDOMESFDS | Z29: 109 | AA29: 02.06.2026 | AB29: 00L0EX46 | AC29: 6699599 | AE29: 0 | AF29: 1 | AG29: 0 | AH29: 0.38 | AI29: KG | AJ29: 0 | AK29: 0 | AL29: 0 | AM29: 0 | AN29: 0 | AO29: 0 | AP29: 0 | AQ29: EUR | AS29: EXP20260601-2774736 | AU29: 00L0EX46 | AV29: LEROY FANNY | AW29: 9 RUE EMILE DUBOIS | AZ29: 75014 | BA29: PARIS | BB29: FR | BC29: France
A30: =IF(COUNTIF(Catégories!A:A,X30)=0,"catégorie inconnue",_xlfn.XLOOKUP(X30,Catégories!A:A,Catégories!B:B)) -> Frêt | B30: =SUM(AJ30:AL30)+SUM(AN30:AP30) -> 7.01 | C30: =AN30 -> 1.54 | D30: =B30-C30 -> 5.47 | E30: =IF(AH30<>0,ROUNDUP(AH30,0),IF(BB30<>"FR","hors France",IF(AH30<>0,ROUNDUP(AH30,0),_xlfn.XLOOKUP(AJ30,'PA GLS'!B:B,'PA GLS'!A:A)))) -> 2 | F30: 2501382993 | G30: 1030219781 | H30: 30.06.2026 | I30: 2500034092 | J30: LA RUCHE LOGISTIQUE | K30: 9000009190 | L30: 46946 | M30: LA RUCHE | N30: 9000079830 | O30: BY FOUTAS | S30: 2507012387 | T30: LA RUCHE LOGISTIQUE | U30: FDS | V30: PARCEL_D01_S05 | W30: Business Parcel - Dis. 01 - Size 05 | X30: PARCEDOMESSTANDARD | Z30: 44 | AA30: 02.06.2026 | AB30: 00KZZJTK | AC30: 2604000035 | AE30: 0 | AF30: 0 | AG30: 0 | AH30: 0 | AI30: KG | AJ30: 4.42 | AK30: 0.9 | AL30: 0.15 | AM30: 29.1 | AN30: 1.54 | AO30: 0 | AP30: 0 | AQ30: EUR | AS30: EXP20260530-2771113- | AT30: EXP20260530-2771113- | AU30: 00KZZJTK | AV30: BRAIZE FREDERIC | AW30: 420 AVENUE DE LA FRUITIERE | AZ30: 74140 | BA30: SCIEZ | BB30: FR | BC30: France
A31: =IF(COUNTIF(Catégories!A:A,X31)=0,"catégorie inconnue",_xlfn.XLOOKUP(X31,Catégories!A:A,Catégories!B:B)) -> Frêt | B31: =SUM(AJ31:AL31)+SUM(AN31:AP31) -> 7.01 | C31: =AN31 -> 1.54 | D31: =B31-C31 -> 5.47 | E31: =IF(AH31<>0,ROUNDUP(AH31,0),IF(BB31<>"FR","hors France",IF(AH31<>0,ROUNDUP(AH31,0),_xlfn.XLOOKUP(AJ31,'PA GLS'!B:B,'PA GLS'!A:A)))) -> 2 | F31: 2501382993 | G31: 1030219781 | H31: 30.06.2026 | I31: 2500034092 | J31: LA RUCHE LOGISTIQUE | K31: 9000009190 | L31: 46946 | M31: LA RUCHE | N31: 9000079830 | O31: BY FOUTAS | S31: 2507012387 | T31: LA RUCHE LOGISTIQUE | U31: FDS | V31: PARCEL_D01_S05 | W31: Business Parcel - Dis. 01 - Size 05 | X31: PARCEDOMESSTANDARD | Z31: 44 | AA31: 02.06.2026 | AB31: 00KZZJTI | AC31: 2604000033 | AE31: 0 | AF31: 0 | AG31: 0 | AH31: 0 | AI31: KG | AJ31: 4.42 | AK31: 0.9 | AL31: 0.15 | AM31: 29.1 | AN31: 1.54 | AO31: 0 | AP31: 0 | AQ31: EUR | AS31: EXP20260529-2769965- | AT31: EXP20260529-2769965- | AU31: 00KZZJTI | AV31: FICHET MORGAN | AW31: 9 RUE DU DOUET | AZ31: 35510 | BA31: CESSON-SEVIGNE | BB31: FR | BC31: France
A32: =IF(COUNTIF(Catégories!A:A,X32)=0,"catégorie inconnue",_xlfn.XLOOKUP(X32,Catégories!A:A,Catégories!B:B)) -> Frêt | B32: =SUM(AJ32:AL32)+SUM(AN32:AP32) -> 6.6 | C32: =AN32 -> 1.45 | D32: =B32-C32 -> 5.15 | E32: =IF(AH32<>0,ROUNDUP(AH32,0),IF(BB32<>"FR","hors France",IF(AH32<>0,ROUNDUP(AH32,0),_xlfn.XLOOKUP(AJ32,'PA GLS'!B:B,'PA GLS'!A:A)))) -> 1 | F32: 2501382993 | G32: 1030219781 | H32: 30.06.2026 | I32: 2500034092 | J32: LA RUCHE LOGISTIQUE | K32: 9000009190 | L32: 46946 | M32: LA RUCHE | N32: 9000079830 | O32: BY FOUTAS | S32: 2507012387 | T32: LA RUCHE LOGISTIQUE | U32: FDS | V32: PARCEL_D01_S04 | W32: Business Parcel - Dis. 01 - Size 04 | X32: PARCEDOMESSTANDARD | Z32: 43 | AA32: 02.06.2026 | AB32: 00KZZJU2 | AC32: 2604000053 | AE32: 0 | AF32: 0 | AG32: 0 | AH32: 0 | AI32: KG | AJ32: 4.1 | AK32: 0.9 | AL32: 0.15 | AM32: 29.1 | AN32: 1.45 | AO32: 0 | AP32: 0 | AQ32: EUR | AS32: EXP20260601-2774808- | AT32: EXP20260601-2774808- | AU32: 00KZZJU2 | AV32: AUDRAIN ESTELLE | AW32: 305 RUE JEAN DAUSSET | AZ32: 13090 | BA32: AIX-EN-PROVENCE | BB32: FR | BC32: France
A33: =IF(COUNTIF(Catégories!A:A,X33)=0,"catégorie inconnue",_xlfn.XLOOKUP(X33,Catégories!A:A,Catégories!B:B)) -> Frêt | B33: =SUM(AJ33:AL33)+SUM(AN33:AP33) -> 6.6 | C33: =AN33 -> 1.45 | D33: =B33-C33 -> 5.15 | E33: =IF(AH33<>0,ROUNDUP(AH33,0),IF(BB33<>"FR","hors France",IF(AH33<>0,ROUNDUP(AH33,0),_xlfn.XLOOKUP(AJ33,'PA GLS'!B:B,'PA GLS'!A:A)))) -> 1 | F33: 2501382993 | G33: 1030219781 | H33: 30.06.2026 | I33: 2500034092 | J33: LA RUCHE LOGISTIQUE | K33: 9000009190 | L33: 46946 | M33: LA RUCHE | N33: 9000079830 | O33: BY FOUTAS | S33: 2507012387 | T33: LA RUCHE LOGISTIQUE | U33: FDS | V33: PARCEL_D01_S04 | W33: Business Parcel - Dis. 01 - Size 04 | X33: PARCEDOMESSTANDARD | Z33: 43 | AA33: 02.06.2026 | AB33: 00KZZJTP | AC33: 2604000040 | AE33: 0 | AF33: 0 | AG33: 0 | AH33: 0 | AI33: KG | AJ33: 4.1 | AK33: 0.9 | AL33: 0.15 | AM33: 29.1 | AN33: 1.45 | AO33: 0 | AP33: 0 | AQ33: EUR | AS33: EXP20260530-2771224- | AT33: EXP20260530-2771224- | AU33: 00KZZJTP | AV33: LAMY MEGANE | AW33: 24 RUE DU CLOCHER | AZ33: 83990 | BA33: SAINT-TROPEZ | BB33: FR | BC33: France
A34: =IF(COUNTIF(Catégories!A:A,X34)=0,"catégorie inconnue",_xlfn.XLOOKUP(X34,Catégories!A:A,Catégories!B:B)) -> Frêt | B34: =SUM(AJ34:AL34)+SUM(AN34:AP34) -> 6.17 | C34: =AN34 -> 1.35 | D34: =B34-C34 -> 4.82 | E34: =IF(AH34<>0,ROUNDUP(AH34,0),IF(BB34<>"FR","hors France",IF(AH34<>0,ROUNDUP(AH34,0),_xlfn.XLOOKUP(AJ34,'PA GLS'!B:B,'PA GLS'!A:A)))) -> 0.5 | F34: 2501382993 | G34: 1030219781 | H34: 30.06.2026 | I34: 2500034092 | J34: LA RUCHE LOGISTIQUE | K34: 9000009190 | L34: 46946 | M34: LA RUCHE | N34: 9000079830 | O34: BY FOUTAS | S34: 2507012387 | T34: LA RUCHE LOGISTIQUE | U34: FDS | V34: PARCEL_D01_S02 | W34: Business Parcel - Dis. 01 - Size 02 | X34: PARCEDOMESSTANDARD | Z34: 42 | AA34: 02.06.2026 | AB34: 00KZZJTY | AC34: 2604000049 | AE34: 0 | AF34: 0 | AG34: 0 | AH34: 0 | AI34: KG | AJ34: 3.77 | AK34: 0.9 | AL34: 0.15 | AM34: 29.1 | AN34: 1.35 | AO34: 0 | AP34: 0 | AQ34: EUR | AS34: EXP20260601-2772286- | AT34: EXP20260601-2772286- | AU34: 00KZZJTY | AV34: ROBION MAEVA | AW34: 140 IMPASSE DES CHARMES | AZ34: 85220 | BA34: COMMEQUIERS | BB34: FR | BC34: France
A35: =IF(COUNTIF(Catégories!A:A,X35)=0,"catégorie inconnue",_xlfn.XLOOKUP(X35,Catégories!A:A,Catégories!B:B)) -> Frêt | B35: =SUM(AJ35:AL35)+SUM(AN35:AP35) -> 6.17 | C35: =AN35 -> 1.35 | D35: =B35-C35 -> 4.82 | E35: =IF(AH35<>0,ROUNDUP(AH35,0),IF(BB35<>"FR","hors France",IF(AH35<>0,ROUNDUP(AH35,0),_xlfn.XLOOKUP(AJ35,'PA GLS'!B:B,'PA GLS'!A:A)))) -> 0.5 | F35: 2501382993 | G35: 1030219781 | H35: 30.06.2026 | I35: 2500034092 | J35: LA RUCHE LOGISTIQUE | K35: 9000009190 | L35: 46946 | M35: LA RUCHE | N35: 9000079830 | O35: BY FOUTAS | S35: 2507012387 | T35: LA RUCHE LOGISTIQUE | U35: FDS | V35: PARCEL_D01_S02 | W35: Business Parcel - Dis. 01 - Size 02 | X35: PARCEDOMESSTANDARD | Z35: 42 | AA35: 02.06.2026 | AB35: 00KZZJTX | AC35: 2604000048 | AE35: 0 | AF35: 0 | AG35: 0 | AH35: 0 | AI35: KG | AJ35: 3.77 | AK35: 0.9 | AL35: 0.15 | AM35: 29.1 | AN35: 1.35 | AO35: 0 | AP35: 0 | AQ35: EUR | AS35: EXP20260601-2772275- | AT35: EXP20260601-2772275- | AU35: 00KZZJTX | AV35: PERSICO CELINE | AW35: 20 RUE DES MARES BATIMENT K AP | AZ35: 93230 | BA35: ROMAINVILLE | BB35: FR | BC35: France
A36: =IF(COUNTIF(Catégories!A:A,X36)=0,"catégorie inconnue",_xlfn.XLOOKUP(X36,Catégories!A:A,Catégories!B:B)) -> Frêt | B36: =SUM(AJ36:AL36)+SUM(AN36:AP36) -> 6.17 | C36: =AN36 -> 1.35 | D36: =B36-C36 -> 4.82 | E36: =IF(AH36<>0,ROUNDUP(AH36,0),IF(BB36<>"FR","hors France",IF(AH36<>0,ROUNDUP(AH36,0),_xlfn.XLOOKUP(AJ36,'PA GLS'!B:B,'PA GLS'!A:A)))) -> 0.5 | F36: 2501382993 | G36: 1030219781 | H36: 30.06.2026 | I36: 2500034092 | J36: LA RUCHE LOGISTIQUE | K36: 9000009190 | L36: 46946 | M36: LA RUCHE | N36: 9000079830 | O36: BY FOUTAS | S36: 2507012387 | T36: LA RUCHE LOGISTIQUE | U36: FDS | V36: PARCEL_D01_S02 | W36: Business Parcel - Dis. 01 - Size 02 | X36: PARCEDOMESSTANDARD | Z36: 42 | AA36: 02.06.2026 | AB36: 00KZZJTS | AC36: 2604000043 | AE36: 0 | AF36: 0 | AG36: 0 | AH36: 0 | AI36: KG | AJ36: 3.77 | AK36: 0.9 | AL36: 0.15 | AM36: 29.1 | AN36: 1.35 | AO36: 0 | AP36: 0 | AQ36: EUR | AS36: EXP20260601-2772276- | AT36: EXP20260601-2772276- | AU36: 00KZZJTS | AV36: PARIS VIRGINIE | AW36: 12 RUE DES CERISIERS | AZ36: 8090 | BA36: CLIRON | BB36: FR | BC36: France
A37: =IF(COUNTIF(Catégories!A:A,X37)=0,"catégorie inconnue",_xlfn.XLOOKUP(X37,Catégories!A:A,Catégories!B:B)) -> Frêt | B37: =SUM(AJ37:AL37)+SUM(AN37:AP37) -> 8.87 | C37: =AN37 -> 1.96 | D37: =B37-C37 -> 6.91 | E37: =IF(AH37<>0,ROUNDUP(AH37,0),IF(BB37<>"FR","hors France",IF(AH37<>0,ROUNDUP(AH37,0),_xlfn.XLOOKUP(AJ37,'PA GLS'!B:B,'PA GLS'!A:A)))) -> 5 | F37: 2501382993 | G37: 1030219781 | H37: 30.06.2026 | I37: 2500034092 | J37: LA RUCHE LOGISTIQUE | K37: 9000009190 | L37: 46946 | M37: LA RUCHE | N37: 9000079830 | O37: BY FOUTAS | S37: 2507012387 | T37: LA RUCHE LOGISTIQUE | U37: FDS | V37: PARCEL_D01_S09 | W37: Business Parcel - Dis. 01 - Size 09 | X37: PARCEDOMESSTANDARD | Z37: 47 | AA37: 02.06.2026 | AB37: 00KZZJU0 | AC37: 2604000051 | AE37: 0 | AF37: 0 | AG37: 0 | AH37: 0 | AI37: KG | AJ37: 5.86 | AK37: 0.9 | AL37: 0.15 | AM37: 29.1 | AN37: 1.96 | AO37: 0 | AP37: 0 | AQ37: EUR | AS37: EXP20260601-2772284- | AT37: EXP20260601-2772284- | AU37: 00KZZJU0 | AV37: MILVILLE JUSTINE | AW37: 7 TER IMPASSE DE LA PAIX | AZ37: 51370 | BA37: SAINT-BRICE-COURCELLES | BB37: FR | BC37: France
A38: =IF(COUNTIF(Catégories!A:A,X38)=0,"catégorie inconnue",_xlfn.XLOOKUP(X38,Catégories!A:A,Catégories!B:B)) -> Frêt | B38: =SUM(AJ38:AL38)+SUM(AN38:AP38) -> 7.43 | C38: =AN38 -> 1.64 | D38: =B38-C38 -> 5.79 | E38: =IF(AH38<>0,ROUNDUP(AH38,0),IF(BB38<>"FR","hors France",IF(AH38<>0,ROUNDUP(AH38,0),_xlfn.XLOOKUP(AJ38,'PA GLS'!B:B,'PA GLS'!A:A)))) -> 3 | F38: 2501382993 | G38: 1030219781 | H38: 30.06.2026 | I38: 2500034092 | J38: LA RUCHE LOGISTIQUE | K38: 9000009190 | L38: 46946 | M38: LA RUCHE | N38: 9000079830 | O38: BY FOUTAS | S38: 2507012387 | T38: LA RUCHE LOGISTIQUE | U38: FDS | V38: PARCEL_D01_S07 | W38: Business Parcel - Dis. 01 - Size 07 | X38: PARCEDOMESSTANDARD | Z38: 46 | AA38: 02.06.2026 | AB38: 00KZZJTV | AC38: 2604000046 | AE38: 0 | AF38: 0 | AG38: 0 | AH38: 0 | AI38: KG | AJ38: 4.74 | AK38: 0.9 | AL38: 0.15 | AM38: 29.1 | AN38: 1.64 | AO38: 0 | AP38: 0 | AQ38: EUR | AS38: EXP20260601-2772288- | AT38: EXP20260601-2772288- | AU38: 00KZZJTV | AV38: JURET NOLWEN | AW38: 19 PLACE DE L'HOTEL DE VILLE | AZ38: 49190 | BA38: ROCHEFORT-SUR-LOIRE | BB38: FR | BC38: France
A39: =IF(COUNTIF(Catégories!A:A,X39)=0,"catégorie inconnue",_xlfn.XLOOKUP(X39,Catégories!A:A,Catégories!B:B)) -> Frêt | B39: =SUM(AJ39:AL39)+SUM(AN39:AP39) -> 0 | C39: =AN39 -> 0 | D39: =B39-C39 -> 0 | E39: =IF(AH39<>0,ROUNDUP(AH39,0),IF(BB39<>"FR","hors France",IF(AH39<>0,ROUNDUP(AH39,0),_xlfn.XLOOKUP(AJ39,'PA GLS'!B:B,'PA GLS'!A:A)))) -> 2 | F39: 2501382993 | G39: 1030219781 | H39: 30.06.2026 | I39: 2500034092 | J39: LA RUCHE LOGISTIQUE | K39: 9000009190 | L39: 46946 | M39: LA RUCHE | N39: 9000079830 | O39: BY FOUTAS | S39: 2507012387 | T39: LA RUCHE LOGISTIQUE | U39: FDS | V39: FDS_D01_S01 | W39: BP FlexDelivery - Dis. 01 - Size 01 | X39: PARCEDOMESFDS | Z39: 41 | AA39: 02.06.2026 | AB39: 00KZZJTI | AC39: 2604000033 | AE39: 0 | AF39: 1 | AG39: 0 | AH39: 1.11 | AI39: KG | AJ39: 0 | AK39: 0 | AL39: 0 | AM39: 0 | AN39: 0 | AO39: 0 | AP39: 0 | AQ39: EUR | AS39: EXP20260529-2769965- | AT39: EXP20260529-2769965- | AU39: 00KZZJTI | AV39: FICHET MORGAN | AW39: 9 RUE DU DOUET | AZ39: 35510 | BA39: CESSON-SEVIGNE | BB39: FR | BC39: France
A40: =IF(COUNTIF(Catégories!A:A,X40)=0,"catégorie inconnue",_xlfn.XLOOKUP(X40,Catégories!A:A,Catégories!B:B)) -> Frêt | B40: =SUM(AJ40:AL40)+SUM(AN40:AP40) -> 0 | C40: =AN40 -> 0 | D40: =B40-C40 -> 0 | E40: =IF(AH40<>0,ROUNDUP(AH40,0),IF(BB40<>"FR","hors France",IF(AH40<>0,ROUNDUP(AH40,0),_xlfn.XLOOKUP(AJ40,'PA GLS'!B:B,'PA GLS'!A:A)))) -> 3 | F40: 2501382993 | G40: 1030219781 | H40: 30.06.2026 | I40: 2500034092 | J40: LA RUCHE LOGISTIQUE | K40: 9000009190 | L40: 46946 | M40: LA RUCHE | N40: 9000079830 | O40: BY FOUTAS | S40: 2507012387 | T40: LA RUCHE LOGISTIQUE | U40: FDS | V40: FDS_D01_S01 | W40: BP FlexDelivery - Dis. 01 - Size 01 | X40: PARCEDOMESFDS | Z40: 41 | AA40: 02.06.2026 | AB40: 00KZZJTJ | AC40: 2604000034 | AE40: 0 | AF40: 1 | AG40: 0 | AH40: 2.06 | AI40: KG | AJ40: 0 | AK40: 0 | AL40: 0 | AM40: 0 | AN40: 0 | AO40: 0 | AP40: 0 | AQ40: EUR | AS40: EXP20260529-2769861- | AT40: EXP20260529-2769861- | AU40: 00KZZJTJ | AV40: FLAMMEN AURELIE | AW40: LE GRAND BOISSIGNAN | AZ40: 56190 | BA40: NOYAL-MUZILLAC | BB40: FR | BC40: France
A41: =IF(COUNTIF(Catégories!A:A,X41)=0,"catégorie inconnue",_xlfn.XLOOKUP(X41,Catégories!A:A,Catégories!B:B)) -> Frêt | B41: =SUM(AJ41:AL41)+SUM(AN41:AP41) -> 0 | C41: =AN41 -> 0 | D41: =B41-C41 -> 0 | E41: =IF(AH41<>0,ROUNDUP(AH41,0),IF(BB41<>"FR","hors France",IF(AH41<>0,ROUNDUP(AH41,0),_xlfn.XLOOKUP(AJ41,'PA GLS'!B:B,'PA GLS'!A:A)))) -> 2 | F41: 2501382993 | G41: 1030219781 | H41: 30.06.2026 | I41: 2500034092 | J41: LA RUCHE LOGISTIQUE | K41: 9000009190 | L41: 46946 | M41: LA RUCHE | N41: 9000079830 | O41: BY FOUTAS | S41: 2507012387 | T41: LA RUCHE LOGISTIQUE | U41: FDS | V41: FDS_D01_S01 | W41: BP FlexDelivery - Dis. 01 - Size 01 | X41: PARCEDOMESFDS | Z41: 41 | AA41: 02.06.2026 | AB41: 00KZZJTK | AC41: 2604000035 | AE41: 0 | AF41: 1 | AG41: 0 | AH41: 1.18 | AI41: KG | AJ41: 0 | AK41: 0 | AL41: 0 | AM41: 0 | AN41: 0 | AO41: 0 | AP41: 0 | AQ41: EUR | AS41: EXP20260530-2771113- | AT41: EXP20260530-2771113- | AU41: 00KZZJTK | AV41: BRAIZE FREDERIC | AW41: 420 AVENUE DE LA FRUITIERE | AZ41: 74140 | BA41: SCIEZ | BB41: FR | BC41: France
... A80: =IF(COUNTIF(Catégories!A:A,X80)=0,"catégorie inconnue",_xlfn.XLOOKUP(X80,Catégories!A:A,Catégories!B:B)) -> Frêt | B80: =SUM(AJ80:AL80)+SUM(AN80:AP80) -> 6.6 | C80: =AN80 -> 1.45 | D80: =B80-C80 -> 5.15 | E80: =IF(AH80<>0,ROUNDUP(AH80,0),IF(BB80<>"FR","hors France",IF(AH80<>0,ROUNDUP(AH80,0),_xlfn.XLOOKUP(AJ80,'PA GLS'!B:B,'PA GLS'!A:A)))) -> 1 | F80: 2501382993 | G80: 1030212005 | H80: 30.06.2026 | I80: 2500034092 | J80: LA RUCHE LOGISTIQUE | K80: 9000009190 | L80: 46946 | M80: LA RUCHE | N80: 9000037814 | O80: LA RUCHE | S80: 2507012387 | T80: LA RUCHE LOGISTIQUE | U80: FDS | V80: PARCEL_D01_S03 | W80: Business Parcel - Dis. 01 - Size 03 | X80: PARCEDOMESSTANDARD | Z80: 30 | AA80: 02.06.2026 | AB80: 00KUR5U6 | AC80: 2604000024 | AE80: 0 | AF80: 0 | AG80: 0 | AH80: 0 | AI80: KG | AJ80: 4.1 | AK80: 0.9 | AL80: 0.15 | AM80: 29.1 | AN80: 1.45 | AO80: 0 | AP80: 0 | AQ80: EUR | AS80: EXP20260602-2775672- | AT80: EXP20260602-2775672- | AU80: 00KUR5U6 | AV80: LEVEQUE GUILLAUME | AW80: 1251 ROUTE DE LA TELECABINE | AZ80: 1170 | BA80: CROZET | BB80: FR | BC80: France
A81: =IF(COUNTIF(Catégories!A:A,X81)=0,"catégorie inconnue",_xlfn.XLOOKUP(X81,Catégories!A:A,Catégories!B:B)) -> Frêt | B81: =SUM(AJ81:AL81)+SUM(AN81:AP81) -> 0 | C81: =AN81 -> 0 | D81: =B81-C81 -> 0 | E81: =IF(AH81<>0,ROUNDUP(AH81,0),IF(BB81<>"FR","hors France",IF(AH81<>0,ROUNDUP(AH81,0),_xlfn.XLOOKUP(AJ81,'PA GLS'!B:B,'PA GLS'!A:A)))) -> 1 | F81: 2501382993 | G81: 1030216444 | H81: 30.06.2026 | I81: 2500034092 | J81: LA RUCHE LOGISTIQUE | K81: 9000009190 | L81: 46946 | M81: LA RUCHE | N81: 9000082822 | O81: Laboratoires Christian Roche | S81: 2507012387 | T81: LA RUCHE LOGISTIQUE | U81: FDS | V81: FDS_D01_S01 | W81: BP FlexDelivery - Dis. 01 - Size 01 | X81: PARCEDOMESFDS | Z81: 31 | AA81: 02.06.2026 | AB81: 00L0DR8P | AC81: 6694240 | AE81: 0 | AF81: 1 | AG81: 0 | AH81: 0.2 | AI81: KG | AJ81: 0 | AK81: 0 | AL81: 0 | AM81: 0 | AN81: 0 | AO81: 0 | AP81: 0 | AQ81: EUR | AS81: EXP20260601-2774231 | AU81: 00L0DR8P | AV81: AXEL TELECOM | AW81: 64 RUE DE LA REPUBLIQUE | AX81: KRIMOVICH FABIENNE | AZ81: 76000 | BA81: ROUEN | BB81: FR | BC81: France
A82: =IF(COUNTIF(Catégories!A:A,X82)=0,"catégorie inconnue",_xlfn.XLOOKUP(X82,Catégories!A:A,Catégories!B:B)) -> Frêt | B82: =SUM(AJ82:AL82)+SUM(AN82:AP82) -> 0 | C82: =AN82 -> 0 | D82: =B82-C82 -> 0 | E82: =IF(AH82<>0,ROUNDUP(AH82,0),IF(BB82<>"FR","hors France",IF(AH82<>0,ROUNDUP(AH82,0),_xlfn.XLOOKUP(AJ82,'PA GLS'!B:B,'PA GLS'!A:A)))) -> 3 | F82: 2501382993 | G82: 1030216444 | H82: 30.06.2026 | I82: 2500034092 | J82: LA RUCHE LOGISTIQUE | K82: 9000009190 | L82: 46946 | M82: LA RUCHE | N82: 9000082822 | O82: Laboratoires Christian Roche | S82: 2507012387 | T82: LA RUCHE LOGISTIQUE | U82: FDS | V82: FDS_D01_S01 | W82: BP FlexDelivery - Dis. 01 - Size 01 | X82: PARCEDOMESFDS | Z82: 31 | AA82: 02.06.2026 | AB82: 00L0DT0Y | AC82: 6694523 | AE82: 0 | AF82: 1 | AG82: 0 | AH82: 2.7 | AI82: KG | AJ82: 0 | AK82: 0 | AL82: 0 | AM82: 0 | AN82: 0 | AO82: 0 | AP82: 0 | AQ82: EUR | AS82: EXP20260601-2774558 | AU82: 00L0DT0Y | AV82: PHARMACIE TALENSAC | AW82: 19 RUE BEL AIR | AX82: DENYS HELENE | AZ82: 44000 | BA82: NANTES | BB82: FR | BC82: France
A83: =IF(COUNTIF(Catégories!A:A,X83)=0,"catégorie inconnue",_xlfn.XLOOKUP(X83,Catégories!A:A,Catégories!B:B)) -> Frêt | B83: =SUM(AJ83:AL83)+SUM(AN83:AP83) -> 0 | C83: =AN83 -> 0 | D83: =B83-C83 -> 0 | E83: =IF(AH83<>0,ROUNDUP(AH83,0),IF(BB83<>"FR","hors France",IF(AH83<>0,ROUNDUP(AH83,0),_xlfn.XLOOKUP(AJ83,'PA GLS'!B:B,'PA GLS'!A:A)))) -> 1 | F83: 2501382993 | G83: 1030216444 | H83: 30.06.2026 | I83: 2500034092 | J83: LA RUCHE LOGISTIQUE | K83: 9000009190 | L83: 46946 | M83: LA RUCHE | N83: 9000082822 | O83: Laboratoires Christian Roche | S83: 2507012387 | T83: LA RUCHE LOGISTIQUE | U83: FDS | V83: FDS_D01_S01 | W83: BP FlexDelivery - Dis. 01 - Size 01 | X83: PARCEDOMESFDS | Z83: 31 | AA83: 02.06.2026 | AB83: 00L0DT2S | AC83: 6694589 | AE83: 0 | AF83: 1 | AG83: 0 | AH83: 0.77 | AI83: KG | AJ83: 0 | AK83: 0 | AL83: 0 | AM83: 0 | AN83: 0 | AO83: 0 | AP83: 0 | AQ83: EUR | AS83: EXP20260601-2774236 | AU83: 00L0DT2S | AV83: LES PLOMBIERS DU VERCORS | AW83: 25 ALLEE DU LYONNAIS ZI NORD | AX83: RONDEL CATHERINE | AZ83: 26300 | BA83: BOURG DE PEAGE | BB83: FR | BC83: France
A84: =IF(COUNTIF(Catégories!A:A,X84)=0,"catégorie inconnue",_xlfn.XLOOKUP(X84,Catégories!A:A,Catégories!B:B)) -> Frêt | B84: =SUM(AJ84:AL84)+SUM(AN84:AP84) -> 6.17 | C84: =AN84 -> 1.35 | D84: =B84-C84 -> 4.82 | E84: =IF(AH84<>0,ROUNDUP(AH84,0),IF(BB84<>"FR","hors France",IF(AH84<>0,ROUNDUP(AH84,0),_xlfn.XLOOKUP(AJ84,'PA GLS'!B:B,'PA GLS'!A:A)))) -> 0.5 | F84: 2501382993 | G84: 1030216444 | H84: 30.06.2026 | I84: 2500034092 | J84: LA RUCHE LOGISTIQUE | K84: 9000009190 | L84: 46946 | M84: LA RUCHE | N84: 9000082822 | O84: Laboratoires Christian Roche | S84: 2507012387 | T84: LA RUCHE LOGISTIQUE | U84: FDS | V84: PARCEL_D01_S01 | W84: Business Parcel - Dis. 01 - Size 01 | X84: PARCEDOMESSTANDARD | Z84: 32 | AA84: 02.06.2026 | AB84: 00L0DR8P | AC84: 6694240 | AE84: 0 | AF84: 0 | AG84: 0 | AH84: 0 | AI84: KG | AJ84: 3.77 | AK84: 0.9 | AL84: 0.15 | AM84: 29.1 | AN84: 1.35 | AO84: 0 | AP84: 0 | AQ84: EUR | AS84: EXP20260601-2774231 | AU84: 00L0DR8P | AV84: AXEL TELECOM | AW84: 64 RUE DE LA REPUBLIQUE | AX84: KRIMOVICH FABIENNE | AZ84: 76000 | BA84: ROUEN | BB84: FR | BC84: France
A85: =IF(COUNTIF(Catégories!A:A,X85)=0,"catégorie inconnue",_xlfn.XLOOKUP(X85,Catégories!A:A,Catégories!B:B)) -> Frêt | B85: =SUM(AJ85:AL85)+SUM(AN85:AP85) -> 6.6 | C85: =AN85 -> 1.45 | D85: =B85-C85 -> 5.15 | E85: =IF(AH85<>0,ROUNDUP(AH85,0),IF(BB85<>"FR","hors France",IF(AH85<>0,ROUNDUP(AH85,0),_xlfn.XLOOKUP(AJ85,'PA GLS'!B:B,'PA GLS'!A:A)))) -> 1 | F85: 2501382993 | G85: 1030216444 | H85: 30.06.2026 | I85: 2500034092 | J85: LA RUCHE LOGISTIQUE | K85: 9000009190 | L85: 46946 | M85: LA RUCHE | N85: 9000082822 | O85: Laboratoires Christian Roche | S85: 2507012387 | T85: LA RUCHE LOGISTIQUE | U85: FDS | V85: PARCEL_D01_S04 | W85: Business Parcel - Dis. 01 - Size 04 | X85: PARCEDOMESSTANDARD | Z85: 33 | AA85: 02.06.2026 | AB85: 00L0DT2S | AC85: 6694589 | AE85: 0 | AF85: 0 | AG85: 0 | AH85: 0 | AI85: KG | AJ85: 4.1 | AK85: 0.9 | AL85: 0.15 | AM85: 29.1 | AN85: 1.45 | AO85: 0 | AP85: 0 | AQ85: EUR | AS85: EXP20260601-2774236 | AU85: 00L0DT2S | AV85: LES PLOMBIERS DU VERCORS | AW85: 25 ALLEE DU LYONNAIS ZI NORD | AX85: RONDEL CATHERINE | AZ85: 26300 | BA85: BOURG DE PEAGE | BB85: FR | BC85: France
A86: =IF(COUNTIF(Catégories!A:A,X86)=0,"catégorie inconnue",_xlfn.XLOOKUP(X86,Catégories!A:A,Catégories!B:B)) -> Frêt | B86: =SUM(AJ86:AL86)+SUM(AN86:AP86) -> 7.43 | C86: =AN86 -> 1.64 | D86: =B86-C86 -> 5.79 | E86: =IF(AH86<>0,ROUNDUP(AH86,0),IF(BB86<>"FR","hors France",IF(AH86<>0,ROUNDUP(AH86,0),_xlfn.XLOOKUP(AJ86,'PA GLS'!B:B,'PA GLS'!A:A)))) -> 3 | F86: 2501382993 | G86: 1030216444 | H86: 30.06.2026 | I86: 2500034092 | J86: LA RUCHE LOGISTIQUE | K86: 9000009190 | L86: 46946 | M86: LA RUCHE | N86: 9000082822 | O86: Laboratoires Christian Roche | S86: 2507012387 | T86: LA RUCHE LOGISTIQUE | U86: FDS | V86: PARCEL_D01_S07 | W86: Business Parcel - Dis. 01 - Size 07 | X86: PARCEDOMESSTANDARD | Z86: 34 | AA86: 02.06.2026 | AB86: 00L0DT0Y | AC86: 6694523 | AE86: 0 | AF86: 0 | AG86: 0 | AH86: 0 | AI86: KG | AJ86: 4.74 | AK86: 0.9 | AL86: 0.15 | AM86: 29.1 | AN86: 1.64 | AO86: 0 | AP86: 0 | AQ86: EUR | AS86: EXP20260601-2774558 | AU86: 00L0DT0Y | AV86: PHARMACIE TALENSAC | AW86: 19 RUE BEL AIR | AX86: DENYS HELENE | AZ86: 44000 | BA86: NANTES | BB86: FR | BC86: France
A87: =IF(COUNTIF(Catégories!A:A,X87)=0,"catégorie inconnue",_xlfn.XLOOKUP(X87,Catégories!A:A,Catégories!B:B)) -> Frêt | B87: =SUM(AJ87:AL87)+SUM(AN87:AP87) -> 7.01 | C87: =AN87 -> 1.54 | D87: =B87-C87 -> 5.47 | E87: =IF(AH87<>0,ROUNDUP(AH87,0),IF(BB87<>"FR","hors France",IF(AH87<>0,ROUNDUP(AH87,0),_xlfn.XLOOKUP(AJ87,'PA GLS'!B:B,'PA GLS'!A:A)))) -> 2 | F87: 2501382993 | G87: 1030219781 | H87: 30.06.2026 | I87: 2500034092 | J87: LA RUCHE LOGISTIQUE | K87: 9000009190 | L87: 46946 | M87: LA RUCHE | N87: 9000079830 | O87: BY FOUTAS | S87: 2507012387 | T87: LA RUCHE LOGISTIQUE | U87: FDS | V87: PARCEL_D01_S06 | W87: Business Parcel - Dis. 01 - Size 06 | X87: PARCEDOMESSTANDARD | Z87: 45 | AA87: 02.06.2026 | AB87: 00KZZJTM | AC87: 2604000037 | AE87: 0 | AF87: 0 | AG87: 0 | AH87: 0 | AI87: KG | AJ87: 4.42 | AK87: 0.9 | AL87: 0.15 | AM87: 29.1 | AN87: 1.54 | AO87: 0 | AP87: 0 | AQ87: EUR | AS87: EXP20260530-2771657- | AT87: EXP20260530-2771657- | AU87: 00KZZJTM | AV87: HARTMANN CHARLOTTE | AW87: 222 CHEMIN DENTABOR | AZ87: 31450 | BA87: BAZIEGE | BB87: FR | BC87: France
A88: =IF(COUNTIF(Catégories!A:A,X88)=0,"catégorie inconnue",_xlfn.XLOOKUP(X88,Catégories!A:A,Catégories!B:B)) -> Frêt | B88: =SUM(AJ88:AL88)+SUM(AN88:AP88) -> 7.01 | C88: =AN88 -> 1.54 | D88: =B88-C88 -> 5.47 | E88: =IF(AH88<>0,ROUNDUP(AH88,0),IF(BB88<>"FR","hors France",IF(AH88<>0,ROUNDUP(AH88,0),_xlfn.XLOOKUP(AJ88,'PA GLS'!B:B,'PA GLS'!A:A)))) -> 2 | F88: 2501382993 | G88: 1030219781 | H88: 30.06.2026 | I88: 2500034092 | J88: LA RUCHE LOGISTIQUE | K88: 9000009190 | L88: 46946 | M88: LA RUCHE | N88: 9000079830 | O88: BY FOUTAS | S88: 2507012387 | T88: LA RUCHE LOGISTIQUE | U88: FDS | V88: PARCEL_D01_S05 | W88: Business Parcel - Dis. 01 - Size 05 | X88: PARCEDOMESSTANDARD | Z88: 44 | AA88: 02.06.2026 | AB88: 00KZZJU1 | AC88: 2604000052 | AE88: 0 | AF88: 0 | AG88: 0 | AH88: 0 | AI88: KG | AJ88: 4.42 | AK88: 0.9 | AL88: 0.15 | AM88: 29.1 | AN88: 1.54 | AO88: 0 | AP88: 0 | AQ88: EUR | AS88: EXP20260601-2774809- | AT88: EXP20260601-2774809- | AU88: 00KZZJU1 | AV88: ROSET SOPHIE | AW88: 10 RUE DU MOULIN | AZ88: 92170 | BA88: VANVES | BB88: FR | BC88: France
A89: =IF(COUNTIF(Catégories!A:A,X89)=0,"catégorie inconnue",_xlfn.XLOOKUP(X89,Catégories!A:A,Catégories!B:B)) -> Frêt | B89: =SUM(AJ89:AL89)+SUM(AN89:AP89) -> 7.01 | C89: =AN89 -> 1.54 | D89: =B89-C89 -> 5.47 | E89: =IF(AH89<>0,ROUNDUP(AH89,0),IF(BB89<>"FR","hors France",IF(AH89<>0,ROUNDUP(AH89,0),_xlfn.XLOOKUP(AJ89,'PA GLS'!B:B,'PA GLS'!A:A)))) -> 2 | F89: 2501382993 | G89: 1030219781 | H89: 30.06.2026 | I89: 2500034092 | J89: LA RUCHE LOGISTIQUE | K89: 9000009190 | L89: 46946 | M89: LA RUCHE | N89: 9000079830 | O89: BY FOUTAS | S89: 2507012387 | T89: LA RUCHE LOGISTIQUE | U89: FDS | V89: PARCEL_D01_S05 | W89: Business Parcel - Dis. 01 - Size 05 | X89: PARCEDOMESSTANDARD | Z89: 44 | AA89: 02.06.2026 | AB89: 00KZZJTZ | AC89: 2604000050 | AE89: 0 | AF89: 0 | AG89: 0 | AH89: 0 | AI89: KG | AJ89: 4.42 | AK89: 0.9 | AL89: 0.15 | AM89: 29.1 | AN89: 1.54 | AO89: 0 | AP89: 0 | AQ89: EUR | AS89: EXP20260531-2771802- | AT89: EXP20260531-2771802- | AU89: 00KZZJTZ | AV89: ROBINSON THOMAS | AW89: 4 BOULEVARD GRIFFOUL DORVAL | AZ89: 31400 | BA89: TOULOUSE | BB89: FR | BC89: France
A90: =IF(COUNTIF(Catégories!A:A,X90)=0,"catégorie inconnue",_xlfn.XLOOKUP(X90,Catégories!A:A,Catégories!B:B)) -> Frêt | B90: =SUM(AJ90:AL90)+SUM(AN90:AP90) -> 7.01 | C90: =AN90 -> 1.54 | D90: =B90-C90 -> 5.47 | E90: =IF(AH90<>0,ROUNDUP(AH90,0),IF(BB90<>"FR","hors France",IF(AH90<>0,ROUNDUP(AH90,0),_xlfn.XLOOKUP(AJ90,'PA GLS'!B:B,'PA GLS'!A:A)))) -> 2 | F90: 2501382993 | G90: 1030219781 | H90: 30.06.2026 | I90: 2500034092 | J90: LA RUCHE LOGISTIQUE | K90: 9000009190 | L90: 46946 | M90: LA RUCHE | N90: 9000079830 | O90: BY FOUTAS | S90: 2507012387 | T90: LA RUCHE LOGISTIQUE | U90: FDS | V90: PARCEL_D01_S05 | W90: Business Parcel - Dis. 01 - Size 05 | X90: PARCEDOMESSTANDARD | Z90: 44 | AA90: 02.06.2026 | AB90: 00KZZJTW | AC90: 2604000047 | AE90: 0 | AF90: 0 | AG90: 0 | AH90: 0 | AI90: KG | AJ90: 4.42 | AK90: 0.9 | AL90: 0.15 | AM90: 29.1 | AN90: 1.54 | AO90: 0 | AP90: 0 | AQ90: EUR | AS90: EXP20260601-2772291- | AT90: EXP20260601-2772291- | AU90: 00KZZJTW | AV90: BUISSON JESSICA | AW90: 11 RUE DE L'ANCIEN LAVOIR | AZ90: 90110 | BA90: ROUGEMONT-LE-CHATEAU | BB90: FR | BC90: France
A91: =IF(COUNTIF(Catégories!A:A,X91)=0,"catégorie inconnue",_xlfn.XLOOKUP(X91,Catégories!A:A,Catégories!B:B)) -> Frêt | B91: =SUM(AJ91:AL91)+SUM(AN91:AP91) -> 7.01 | C91: =AN91 -> 1.54 | D91: =B91-C91 -> 5.47 | E91: =IF(AH91<>0,ROUNDUP(AH91,0),IF(BB91<>"FR","hors France",IF(AH91<>0,ROUNDUP(AH91,0),_xlfn.XLOOKUP(AJ91,'PA GLS'!B:B,'PA GLS'!A:A)))) -> 2 | F91: 2501382993 | G91: 1030219781 | H91: 30.06.2026 | I91: 2500034092 | J91: LA RUCHE LOGISTIQUE | K91: 9000009190 | L91: 46946 | M91: LA RUCHE | N91: 9000079830 | O91: BY FOUTAS | S91: 2507012387 | T91: LA RUCHE LOGISTIQUE | U91: FDS | V91: PARCEL_D01_S05 | W91: Business Parcel - Dis. 01 - Size 05 | X91: PARCEDOMESSTANDARD | Z91: 44 | AA91: 02.06.2026 | AB91: 00KZZJTQ | AC91: 2604000041 | AE91: 0 | AF91: 0 | AG91: 0 | AH91: 0 | AI91: KG | AJ91: 4.42 | AK91: 0.9 | AL91: 0.15 | AM91: 29.1 | AN91: 1.54 | AO91: 0 | AP91: 0 | AQ91: EUR | AS91: EXP20260601-2772278- | AT91: EXP20260601-2772278- | AU91: 00KZZJTQ | AV91: BOUZY CLAIRE | AW91: 11 RUE LOUIS GAIN | AZ91: 49100 | BA91: ANGERS | BB91: FR | BC91: France
A92: =IF(COUNTIF(Catégories!A:A,X92)=0,"catégorie inconnue",_xlfn.XLOOKUP(X92,Catégories!A:A,Catégories!B:B)) -> Frêt | B92: =SUM(AJ92:AL92)+SUM(AN92:AP92) -> 7.01 | C92: =AN92 -> 1.54 | D92: =B92-C92 -> 5.47 | E92: =IF(AH92<>0,ROUNDUP(AH92,0),IF(BB92<>"FR","hors France",IF(AH92<>0,ROUNDUP(AH92,0),_xlfn.XLOOKUP(AJ92,'PA GLS'!B:B,'PA GLS'!A:A)))) -> 2 | F92: 2501382993 | G92: 1030219781 | H92: 30.06.2026 | I92: 2500034092 | J92: LA RUCHE LOGISTIQUE | K92: 9000009190 | L92: 46946 | M92: LA RUCHE | N92: 9000079830 | O92: BY FOUTAS | S92: 2507012387 | T92: LA RUCHE LOGISTIQUE | U92: FDS | V92: PARCEL_D01_S05 | W92: Business Parcel - Dis. 01 - Size 05 | X92: PARCEDOMESSTANDARD | Z92: 44 | AA92: 02.06.2026 | AB92: 00KZZJTN | AC92: 2604000038 | AE92: 0 | AF92: 0 | AG92: 0 | AH92: 0 | AI92: KG | AJ92: 4.42 | AK92: 0.9 | AL92: 0.15 | AM92: 29.1 | AN92: 1.54 | AO92: 0 | AP92: 0 | AQ92: EUR | AS92: EXP20260530-2771449- | AT92: EXP20260530-2771449- | AU92: 00KZZJTN | AV92: LLOYD JULIETTE | AW92: 11 AVENUE DES CIGALES | AZ92: 91190 | BA92: GIF SUR YVETTE | BB92: FR | BC92: France
A93: =IF(COUNTIF(Catégories!A:A,X93)=0,"catégorie inconnue",_xlfn.XLOOKUP(X93,Catégories!A:A,Catégories!B:B)) -> Frêt | B93: =SUM(AJ93:AL93)+SUM(AN93:AP93) -> 7.01 | C93: =AN93 -> 1.54 | D93: =B93-C93 -> 5.47 | E93: =IF(AH93<>0,ROUNDUP(AH93,0),IF(BB93<>"FR","hors France",IF(AH93<>0,ROUNDUP(AH93,0),_xlfn.XLOOKUP(AJ93,'PA GLS'!B:B,'PA GLS'!A:A)))) -> 2 | F93: 2501382993 | G93: 1030219781 | H93: 30.06.2026 | I93: 2500034092 | J93: LA RUCHE LOGISTIQUE | K93: 9000009190 | L93: 46946 | M93: LA RUCHE | N93: 9000079830 | O93: BY FOUTAS | S93: 2507012387 | T93: LA RUCHE LOGISTIQUE | U93: FDS | V93: PARCEL_D01_S05 | W93: Business Parcel - Dis. 01 - Size 05 | X93: PARCEDOMESSTANDARD | Z93: 44 | AA93: 02.06.2026 | AB93: 00KZZJTL | AC93: 2604000036 | AE93: 0 | AF93: 0 | AG93: 0 | AH93: 0 | AI93: KG | AJ93: 4.42 | AK93: 0.9 | AL93: 0.15 | AM93: 29.1 | AN93: 1.54 | AO93: 0 | AP93: 0 | AQ93: EUR | AS93: EXP20260530-2771365- | AT93: EXP20260530-2771365- | AU93: 00KZZJTL | AV93: PERROT SIBYLLE | AW93: 18 RUE PAUL BLONDEAU | AZ93: 59700 | BA93: MARCQ-EN-BARUL | BB93: FR | BC93: France
A94: =IF(COUNTIF(Catégories!A:A,X94)=0,"catégorie inconnue",_xlfn.XLOOKUP(X94,Catégories!A:A,Catégories!B:B)) -> Frêt | B94: =SUM(AJ94:AL94)+SUM(AN94:AP94) -> 6.17 | C94: =AN94 -> 1.35 | D94: =B94-C94 -> 4.82 | E94: =IF(AH94<>0,ROUNDUP(AH94,0),IF(BB94<>"FR","hors France",IF(AH94<>0,ROUNDUP(AH94,0),_xlfn.XLOOKUP(AJ94,'PA GLS'!B:B,'PA GLS'!A:A)))) -> 0.5 | F94: 2501382993 | G94: 1030230689 | H94: 30.06.2026 | I94: 2500034092 | J94: LA RUCHE LOGISTIQUE | K94: 9000009190 | L94: 46946 | M94: LA RUCHE | N94: 9000079829 | O94: ANOTHER WAY | S94: 2507012387 | T94: LA RUCHE LOGISTIQUE | U94: FDS | V94: PARCEL_D01_S02 | W94: Business Parcel - Dis. 01 - Size 02 | X94: PARCEDOMESSTANDARD | Z94: 110 | AA94: 02.06.2026 | AB94: 00L0EXC0 | AC94: 6699902 | AE94: 0 | AF94: 0 | AG94: 0 | AH94: 0 | AI94: KG | AJ94: 3.77 | AK94: 0.9 | AL94: 0.15 | AM94: 29.1 | AN94: 1.35 | AO94: 0 | AP94: 0 | AQ94: EUR | AS94: EXP20260601-2772297 | AU94: 00L0EXC0 | AV94: GROSSEMY MARIE-LAURE | AW94: 24, RUE DES ERABLES | AZ94: 71640 | BA94: GIVRY | BB94: FR | BC94: France
A95: =IF(COUNTIF(Catégories!A:A,X95)=0,"catégorie inconnue",_xlfn.XLOOKUP(X95,Catégories!A:A,Catégories!B:B)) -> Frêt | B95: =SUM(AJ95:AL95)+SUM(AN95:AP95) -> 0 | C95: =AN95 -> 0 | D95: =B95-C95 -> 0 | E95: =IF(AH95<>0,ROUNDUP(AH95,0),IF(BB95<>"FR","hors France",IF(AH95<>0,ROUNDUP(AH95,0),_xlfn.XLOOKUP(AJ95,'PA GLS'!B:B,'PA GLS'!A:A)))) -> 3 | F95: 2501382993 | G95: 1030233879 | H95: 30.06.2026 | I95: 2500034092 | J95: LA RUCHE LOGISTIQUE | K95: 9000009190 | L95: 46946 | M95: LA RUCHE | N95: 9000037814 | O95: LA RUCHE | S95: 2507012387 | T95: LA RUCHE LOGISTIQUE | U95: FDS | V95: FDS_D01_S01 | W95: BP FlexDelivery - Dis. 01 - Size 01 | X95: PARCEDOMESFDS | Z95: 183 | AA95: 03.06.2026 | AB95: 00KUR5UE | AC95: 2604000032 | AE95: 0 | AF95: 1 | AG95: 0 | AH95: 2.88 | AI95: KG | AJ95: 0 | AK95: 0 | AL95: 0 | AM95: 0 | AN95: 0 | AO95: 0 | AP95: 0 | AQ95: EUR | AS95: EXP20260602-2776795- | AT95: EXP20260602-2776795- | AU95: 00KUR5UE | AV95: HAYER CECILIA | AW95: 11 RUE DE L'EGLISE | AZ95: 68250 | BA95: WESTHALTEN | BB95: FR | BC95: France
A96: =IF(COUNTIF(Catégories!A:A,X96)=0,"catégorie inconnue",_xlfn.XLOOKUP(X96,Catégories!A:A,Catégories!B:B)) -> Frêt | B96: =SUM(AJ96:AL96)+SUM(AN96:AP96) -> 0 | C96: =AN96 -> 0 | D96: =B96-C96 -> 0 | E96: =IF(AH96<>0,ROUNDUP(AH96,0),IF(BB96<>"FR","hors France",IF(AH96<>0,ROUNDUP(AH96,0),_xlfn.XLOOKUP(AJ96,'PA GLS'!B:B,'PA GLS'!A:A)))) -> 1 | F96: 2501382993 | G96: 1030233879 | H96: 30.06.2026 | I96: 2500034092 | J96: LA RUCHE LOGISTIQUE | K96: 9000009190 | L96: 46946 | M96: LA RUCHE | N96: 9000037814 | O96: LA RUCHE | S96: 2507012387 | T96: LA RUCHE LOGISTIQUE | U96: FDS | V96: FDS_D01_S01 | W96: BP FlexDelivery - Dis. 01 - Size 01 | X96: PARCEDOMESFDS | Z96: 183 | AA96: 03.06.2026 | AB96: 00KUR5UF | AC96: 2604000033 | AE96: 0 | AF96: 1 | AG96: 0 | AH96: 0.45 | AI96: KG | AJ96: 0 | AK96: 0 | AL96: 0 | AM96: 0 | AN96: 0 | AO96: 0 | AP96: 0 | AQ96: EUR | AS96: EXP20260603-2778695- | AT96: EXP20260603-2778695- | AU96: 00KUR5UF | AV96: UN LIVRE ANASTASIA | AW96: 6 AVENUE DE MESSINE | AZ96: 75008 | BA96: PARIS | BB96: FR | BC96: France
A97: =IF(COUNTIF(Catégories!A:A,X97)=0,"catégorie inconnue",_xlfn.XLOOKUP(X97,Catégories!A:A,Catégories!B:B)) -> Frêt | B97: =SUM(AJ97:AL97)+SUM(AN97:AP97) -> 6.17 | C97: =AN97 -> 1.35 | D97: =B97-C97 -> 4.82 | E97: =IF(AH97<>0,ROUNDUP(AH97,0),IF(BB97<>"FR","hors France",IF(AH97<>0,ROUNDUP(AH97,0),_xlfn.XLOOKUP(AJ97,'PA GLS'!B:B,'PA GLS'!A:A)))) -> 0.5 | F97: 2501382993 | G97: 1030233879 | H97: 30.06.2026 | I97: 2500034092 | J97: LA RUCHE LOGISTIQUE | K97: 9000009190 | L97: 46946 | M97: LA RUCHE | N97: 9000037814 | O97: LA RUCHE | S97: 2507012387 | T97: LA RUCHE LOGISTIQUE | U97: FDS | V97: PARCEL_D01_S01 | W97: Business Parcel - Dis. 01 - Size 01 | X97: PARCEDOMESSTANDARD | Z97: 184 | AA97: 03.06.2026 | AB97: 00KUR5UD | AC97: 2604000031 | AE97: 0 | AF97: 0 | AG97: 0 | AH97: 0 | AI97: KG | AJ97: 3.77 | AK97: 0.9 | AL97: 0.15 | AM97: 29.1 | AN97: 1.35 | AO97: 0 | AP97: 0 | AQ97: EUR | AS97: EXP20260602-2776136- | AT97: EXP20260602-2776136- | AU97: 00KUR5UD | AV97: LEBORGNE MAXIME | AW97: 77 QUATER ROUTE DE LA LOIRE | AZ97: 44450 | BA97: DIVATTE SUR LOIRE | BB97: FR | BC97: France
A98: =IF(COUNTIF(Catégories!A:A,X98)=0,"catégorie inconnue",_xlfn.XLOOKUP(X98,Catégories!A:A,Catégories!B:B)) -> Frêt | B98: =SUM(AJ98:AL98)+SUM(AN98:AP98) -> 6.17 | C98: =AN98 -> 1.35 | D98: =B98-C98 -> 4.82 | E98: =IF(AH98<>0,ROUNDUP(AH98,0),IF(BB98<>"FR","hors France",IF(AH98<>0,ROUNDUP(AH98,0),_xlfn.XLOOKUP(AJ98,'PA GLS'!B:B,'PA GLS'!A:A)))) -> 0.5 | F98: 2501382993 | G98: 1030233879 | H98: 30.06.2026 | I98: 2500034092 | J98: LA RUCHE LOGISTIQUE | K98: 9000009190 | L98: 46946 | M98: LA RUCHE | N98: 9000037814 | O98: LA RUCHE | S98: 2507012387 | T98: LA RUCHE LOGISTIQUE | U98: FDS | V98: PARCEL_D01_S02 | W98: Business Parcel - Dis. 01 - Size 02 | X98: PARCEDOMESSTANDARD | Z98: 185 | AA98: 03.06.2026 | AB98: 00KUR5U7 | AC98: 2604000025 | AE98: 0 | AF98: 0 | AG98: 0 | AH98: 0 | AI98: KG | AJ98: 3.77 | AK98: 0.9 | AL98: 0.15 | AM98: 29.1 | AN98: 1.35 | AO98: 0 | AP98: 0 | AQ98: EUR | AS98: EXP20260602-2776023- | AT98: EXP20260602-2776023- | AU98: 00KUR5U7 | AV98: CARBALLEDA ELENA | AW98: 8 RUE ALFRED DE MUSSET | AZ98: 78330 | BA98: FONTENAY-LE-FLEURY | BB98: FR | BC98: France
A99: =IF(COUNTIF(Catégories!A:A,X99)=0,"catégorie inconnue",_xlfn.XLOOKUP(X99,Catégories!A:A,Catégories!B:B)) -> Frêt | B99: =SUM(AJ99:AL99)+SUM(AN99:AP99) -> 6.17 | C99: =AN99 -> 1.35 | D99: =B99-C99 -> 4.82 | E99: =IF(AH99<>0,ROUNDUP(AH99,0),IF(BB99<>"FR","hors France",IF(AH99<>0,ROUNDUP(AH99,0),_xlfn.XLOOKUP(AJ99,'PA GLS'!B:B,'PA GLS'!A:A)))) -> 0.5 | F99: 2501382993 | G99: 1030233879 | H99: 30.06.2026 | I99: 2500034092 | J99: LA RUCHE LOGISTIQUE | K99: 9000009190 | L99: 46946 | M99: LA RUCHE | N99: 9000037814 | O99: LA RUCHE | S99: 2507012387 | T99: LA RUCHE LOGISTIQUE | U99: FDS | V99: PARCEL_D01_S02 | W99: Business Parcel - Dis. 01 - Size 02 | X99: PARCEDOMESSTANDARD | Z99: 185 | AA99: 03.06.2026 | AB99: 00KUR5U9 | AC99: 2604000027 | AE99: 0 | AF99: 0 | AG99: 0 | AH99: 0 | AI99: KG | AJ99: 3.77 | AK99: 0.9 | AL99: 0.15 | AM99: 29.1 | AN99: 1.35 | AO99: 0 | AP99: 0 | AQ99: EUR | AS99: EXP20260602-2776040- | AT99: EXP20260602-2776040- | AU99: 00KUR5U9 | AV99: RAIMBAUD MARINE | AW99: 6 RUE LOUIS CRISTAU | AZ99: 85800 | BA99: SAINT GILLES CROIX DE VIE | BB99: FR | BC99: France
A100: =IF(COUNTIF(Catégories!A:A,X100)=0,"catégorie inconnue",_xlfn.XLOOKUP(X100,Catégories!A:A,Catégories!B:B)) -> Frêt | B100: =SUM(AJ100:AL100)+SUM(AN100:AP100) -> 6.17 | C100: =AN100 -> 1.35 | D100: =B100-C100 -> 4.82 | E100: =IF(AH100<>0,ROUNDUP(AH100,0),IF(BB100<>"FR","hors France",IF(AH100<>0,ROUNDUP(AH100,0),_xlfn.XLOOKUP(AJ100,'PA GLS'!B:B,'PA GLS'!A:A)))) -> 0.5 | F100: 2501382993 | G100: 1030233879 | H100: 30.06.2026 | I100: 2500034092 | J100: LA RUCHE LOGISTIQUE | K100: 9000009190 | L100: 46946 | M100: LA RUCHE | N100: 9000037814 | O100: LA RUCHE | S100: 2507012387 | T100: LA RUCHE LOGISTIQUE | U100: FDS | V100: PARCEL_D01_S02 | W100: Business Parcel - Dis. 01 - Size 02 | X100: PARCEDOMESSTANDARD | Z100: 185 | AA100: 03.06.2026 | AB100: 00KUR5UC | AC100: 2604000030 | AE100: 0 | AF100: 0 | AG100: 0 | AH100: 0 | AI100: KG | AJ100: 3.77 | AK100: 0.9 | AL100: 0.15 | AM100: 29.1 | AN100: 1.35 | AO100: 0 | AP100: 0 | AQ100: EUR | AS100: EXP20260602-2776918- | AT100: EXP20260602-2776918- | AU100: 00KUR5UC | AV100: MANFREDI LUANA | AW100: 261 CHEMIN DE LA COSTIERE | AZ100: 6000 | BA100: NICE | BB100: FR | BC100: France
A101: =IF(COUNTIF(Catégories!A:A,X101)=0,"catégorie inconnue",_xlfn.XLOOKUP(X101,Catégories!A:A,Catégories!B:B)) -> Frêt | B101: =SUM(AJ101:AL101)+SUM(AN101:AP101) -> 6.17 | C101: =AN101 -> 1.35 | D101: =B101-C101 -> 4.82 | E101: =IF(AH101<>0,ROUNDUP(AH101,0),IF(BB101<>"FR","hors France",IF(AH101<>0,ROUNDUP(AH101,0),_xlfn.XLOOKUP(AJ101,'PA GLS'!B:B,'PA GLS'!A:A)))) -> 0.5 | F101: 2501382993 | G101: 1030233879 | H101: 30.06.2026 | I101: 2500034092 | J101: LA RUCHE LOGISTIQUE | K101: 9000009190 | L101: 46946 | M101: LA RUCHE | N101: 9000037814 | O101: LA RUCHE | S101: 2507012387 | T101: LA RUCHE LOGISTIQUE | U101: FDS | V101: PARCEL_D01_S02 | W101: Business Parcel - Dis. 01 - Size 02 | X101: PARCEDOMESSTANDARD | Z101: 185 | AA101: 03.06.2026 | AB101: 00KUR5UF | AC101: 2604000033 | AE101: 0 | AF101: 0 | AG101: 0 | AH101: 0 | AI101: KG | AJ101: 3.77 | AK101: 0.9 | AL101: 0.15 | AM101: 29.1 | AN101: 1.35 | AO101: 0 | AP101: 0 | AQ101: EUR | AS101: EXP20260603-2778695- | AT101: EXP20260603-2778695- | AU101: 00KUR5UF | AV101: UN LIVRE ANASTASIA | AW101: 6 AVENUE DE MESSINE | AZ101: 75008 | BA101: PARIS | BB101: FR | BC101: France
A102: =IF(COUNTIF(Catégories!A:A,X102)=0,"catégorie inconnue",_xlfn.XLOOKUP(X102,Catégories!A:A,Catégories!B:B)) -> Frêt | B102: =SUM(AJ102:AL102)+SUM(AN102:AP102) -> 0 | C102: =AN102 -> 0 | D102: =B102-C102 -> 0 | E102: =IF(AH102<>0,ROUNDUP(AH102,0),IF(BB102<>"FR","hors France",IF(AH102<>0,ROUNDUP(AH102,0),_xlfn.XLOOKUP(AJ102,'PA GLS'!B:B,'PA GLS'!A:A)))) -> 1 | F102: 2501382993 | G102: 1030233879 | H102: 30.06.2026 | I102: 2500034092 | J102: LA RUCHE LOGISTIQUE | K102: 9000009190 | L102: 46946 | M102: LA RUCHE | N102: 9000037814 | O102: LA RUCHE | S102: 2507012387 | T102: LA RUCHE LOGISTIQUE | U102: FDS | V102: FDS_D01_S01 | W102: BP FlexDelivery - Dis. 01 - Size 01 | X102: PARCEDOMESFDS | Z102: 183 | AA102: 03.06.2026 | AB102: 00KUR5U7 | AC102: 2604000025 | AE102: 0 | AF102: 1 | AG102: 0 | AH102: 0.48 | AI102: KG | AJ102: 0 | AK102: 0 | AL102: 0 | AM102: 0 | AN102: 0 | AO102: 0 | AP102: 0 | AQ102: EUR | AS102: EXP20260602-2776023- | AT102: EXP20260602-2776023- | AU102: 00KUR5U7 | AV102: CARBALLEDA ELENA | AW102: 8 RUE ALFRED DE MUSSET | AZ102: 78330 | BA102: FONTENAY-LE-FLEURY | BB102: FR | BC102: France
A103: =IF(COUNTIF(Catégories!A:A,X103)=0,"catégorie inconnue",_xlfn.XLOOKUP(X103,Catégories!A:A,Catégories!B:B)) -> Frêt | B103: =SUM(AJ103:AL103)+SUM(AN103:AP103) -> 0 | C103: =AN103 -> 0 | D103: =B103-C103 -> 0 | E103: =IF(AH103<>0,ROUNDUP(AH103,0),IF(BB103<>"FR","hors France",IF(AH103<>0,ROUNDUP(AH103,0),_xlfn.XLOOKUP(AJ103,'PA GLS'!B:B,'PA GLS'!A:A)))) -> 1 | F103: 2501382993 | G103: 1030233879 | H103: 30.06.2026 | I103: 2500034092 | J103: LA RUCHE LOGISTIQUE | K103: 9000009190 | L103: 46946 | M103: LA RUCHE | N103: 9000037814 | O103: LA RUCHE | S103: 2507012387 | T103: LA RUCHE LOGISTIQUE | U103: FDS | V103: FDS_D01_S01 | W103: BP FlexDelivery - Dis. 01 - Size 01 | X103: PARCEDOMESFDS | Z103: 183 | AA103: 03.06.2026 | AB103: 00KUR5U8 | AC103: 2604000026 | AE103: 0 | AF103: 1 | AG103: 0 | AH103: 0.58 | AI103: KG | AJ103: 0 | AK103: 0 | AL103: 0 | AM103: 0 | AN103: 0 | AO103: 0 | AP103: 0 | AQ103: EUR | AS103: EXP20260527-2766394- | AT103: EXP20260527-2766394- | AU103: 00KUR5U8 | AV103: DE COURCY CHRISTINE | AW103: 4, AVENUE DE LA GARE LES PRAI | AZ103: 33138 | BA103: LANTON | BB103: FR | BC103: France
A104: =IF(COUNTIF(Catégories!A:A,X104)=0,"catégorie inconnue",_xlfn.XLOOKUP(X104,Catégories!A:A,Catégories!B:B)) -> Frêt | B104: =SUM(AJ104:AL104)+SUM(AN104:AP104) -> 0 | C104: =AN104 -> 0 | D104: =B104-C104 -> 0 | E104: =IF(AH104<>0,ROUNDUP(AH104,0),IF(BB104<>"FR","hors France",IF(AH104<>0,ROUNDUP(AH104,0),_xlfn.XLOOKUP(AJ104,'PA GLS'!B:B,'PA GLS'!A:A)))) -> 1 | F104: 2501382993 | G104: 1030233879 | H104: 30.06.2026 | I104: 2500034092 | J104: LA RUCHE LOGISTIQUE | K104: 9000009190 | L104: 46946 | M104: LA RUCHE | N104: 9000037814 | O104: LA RUCHE | S104: 2507012387 | T104: LA RUCHE LOGISTIQUE | U104: FDS | V104: FDS_D01_S01 | W104: BP FlexDelivery - Dis. 01 - Size 01 | X104: PARCEDOMESFDS | Z104: 183 | AA104: 03.06.2026 | AB104: 00KUR5U9 | AC104: 2604000027 | AE104: 0 | AF104: 1 | AG104: 0 | AH104: 0.32 | AI104: KG | AJ104: 0 | AK104: 0 | AL104: 0 | AM104: 0 | AN104: 0 | AO104: 0 | AP104: 0 | AQ104: EUR | AS104: EXP20260602-2776040- | AT104: EXP20260602-2776040- | AU104: 00KUR5U9 | AV104: RAIMBAUD MARINE | AW104: 6 RUE LOUIS CRISTAU | AZ104: 85800 | BA104: SAINT GILLES CROIX DE VIE | BB104: FR | BC104: France
A105: =IF(COUNTIF(Catégories!A:A,X105)=0,"catégorie inconnue",_xlfn.XLOOKUP(X105,Catégories!A:A,Catégories!B:B)) -> Frêt | B105: =SUM(AJ105:AL105)+SUM(AN105:AP105) -> 0 | C105: =AN105 -> 0 | D105: =B105-C105 -> 0 | E105: =IF(AH105<>0,ROUNDUP(AH105,0),IF(BB105<>"FR","hors France",IF(AH105<>0,ROUNDUP(AH105,0),_xlfn.XLOOKUP(AJ105,'PA GLS'!B:B,'PA GLS'!A:A)))) -> 1 | F105: 2501382993 | G105: 1030233879 | H105: 30.06.2026 | I105: 2500034092 | J105: LA RUCHE LOGISTIQUE | K105: 9000009190 | L105: 46946 | M105: LA RUCHE | N105: 9000037814 | O105: LA RUCHE | S105: 2507012387 | T105: LA RUCHE LOGISTIQUE | U105: FDS | V105: FDS_D01_S01 | W105: BP FlexDelivery - Dis. 01 - Size 01 | X105: PARCEDOMESFDS | Z105: 183 | AA105: 03.06.2026 | AB105: 00KUR5UA | AC105: 2604000028 | AE105: 0 | AF105: 1 | AG105: 0 | AH105: 0.82 | AI105: KG | AJ105: 0 | AK105: 0 | AL105: 0 | AM105: 0 | AN105: 0 | AO105: 0 | AP105: 0 | AQ105: EUR | AS105: EXP20260602-2777009- | AT105: EXP20260602-2777009- | AU105: 00KUR5UA | AV105: DEVISME NOEMIE | AW105: 2 RUE DU POISSON BLEU | AZ105: 92290 | BA105: CHATENAY MALABRY | BB105: FR | BC105: France
A106: =IF(COUNTIF(Catégories!A:A,X106)=0,"catégorie inconnue",_xlfn.XLOOKUP(X106,Catégories!A:A,Catégories!B:B)) -> Frêt | B106: =SUM(AJ106:AL106)+SUM(AN106:AP106) -> 0 | C106: =AN106 -> 0 | D106: =B106-C106 -> 0 | E106: =IF(AH106<>0,ROUNDUP(AH106,0),IF(BB106<>"FR","hors France",IF(AH106<>0,ROUNDUP(AH106,0),_xlfn.XLOOKUP(AJ106,'PA GLS'!B:B,'PA GLS'!A:A)))) -> 1 | F106: 2501382993 | G106: 1030233879 | H106: 30.06.2026 | I106: 2500034092 | J106: LA RUCHE LOGISTIQUE | K106: 9000009190 | L106: 46946 | M106: LA RUCHE | N106: 9000037814 | O106: LA RUCHE | S106: 2507012387 | T106: LA RUCHE LOGISTIQUE | U106: FDS | V106: FDS_D01_S01 | W106: BP FlexDelivery - Dis. 01 - Size 01 | X106: PARCEDOMESFDS | Z106: 183 | AA106: 03.06.2026 | AB106: 00KUR5UB | AC106: 2604000029 | AE106: 0 | AF106: 1 | AG106: 0 | AH106: 0.8 | AI106: KG | AJ106: 0 | AK106: 0 | AL106: 0 | AM106: 0 | AN106: 0 | AO106: 0 | AP106: 0 | AQ106: EUR | AS106: EXP20260602-2776794- | AT106: EXP20260602-2776794- | AU106: 00KUR5UB | AV106: DEVISME NOEMIE | AW106: 2 RUE DU POISSON BLEU | AZ106: 92290 | BA106: CHATENAY MALABRY | BB106: FR | BC106: France
... A108: =IF(COUNTIF(Catégories!A:A,X108)=0,"catégorie inconnue",_xlfn.XLOOKUP(X108,Catégories!A:A,Catégories!B:B)) -> Frêt | B108: =SUM(AJ108:AL108)+SUM(AN108:AP108) -> 0 | C108: =AN108 -> 0 | D108: =B108-C108 -> 0 | E108: =IF(AH108<>0,ROUNDUP(AH108,0),IF(BB108<>"FR","hors France",IF(AH108<>0,ROUNDUP(AH108,0),_xlfn.XLOOKUP(AJ108,'PA GLS'!B:B,'PA GLS'!A:A)))) -> 1 | F108: 2501382993 | G108: 1030233879 | H108: 30.06.2026 | I108: 2500034092 | J108: LA RUCHE LOGISTIQUE | K108: 9000009190 | L108: 46946 | M108: LA RUCHE | N108: 9000037814 | O108: LA RUCHE | S108: 2507012387 | T108: LA RUCHE LOGISTIQUE | U108: FDS | V108: FDS_D01_S01 | W108: BP FlexDelivery - Dis. 01 - Size 01 | X108: PARCEDOMESFDS | Z108: 183 | AA108: 03.06.2026 | AB108: 00KUR5UD | AC108: 2604000031 | AE108: 0 | AF108: 1 | AG108: 0 | AH108: 0.16 | AI108: KG | AJ108: 0 | AK108: 0 | AL108: 0 | AM108: 0 | AN108: 0 | AO108: 0 | AP108: 0 | AQ108: EUR | AS108: EXP20260602-2776136- | AT108: EXP20260602-2776136- | AU108: 00KUR5UD | AV108: LEBORGNE MAXIME | AW108: 77 QUATER ROUTE DE LA LOIRE | AZ108: 44450 | BA108: DIVATTE SUR LOIRE | BB108: FR | BC108: France
A109: =IF(COUNTIF(Catégories!A:A,X109)=0,"catégorie inconnue",_xlfn.XLOOKUP(X109,Catégories!A:A,Catégories!B:B)) -> Frêt | B109: =SUM(AJ109:AL109)+SUM(AN109:AP109) -> 6.17 | C109: =AN109 -> 1.35 | D109: =B109-C109 -> 4.82 | E109: =IF(AH109<>0,ROUNDUP(AH109,0),IF(BB109<>"FR","hors France",IF(AH109<>0,ROUNDUP(AH109,0),_xlfn.XLOOKUP(AJ109,'PA GLS'!B:B,'PA GLS'!A:A)))) -> 0.5 | F109: 2501382993 | G109: 1030234750 | H109: 30.06.2026 | I109: 2500034092 | J109: LA RUCHE LOGISTIQUE | K109: 9000009190 | L109: 46946 | M109: LA RUCHE | N109: 9000082822 | O109: Laboratoires Christian Roche | S109: 2507012387 | T109: LA RUCHE LOGISTIQUE | U109: FDS | V109: PARCEL_D01_S02 | W109: Business Parcel - Dis. 01 - Size 02 | X109: PARCEDOMESSTANDARD | Z109: 210 | AA109: 03.06.2026 | AB109: 00L0GLJP | AC109: 6708090 | AE109: 0 | AF109: 0 | AG109: 0 | AH109: 0 | AI109: KG | AJ109: 3.77 | AK109: 0.9 | AL109: 0.15 | AM109: 29.1 | AN109: 1.35 | AO109: 0 | AP109: 0 | AQ109: EUR | AS109: EXP20260602-2777085 | AU109: 00L0GLJP | AV109: VEYSSADE SANDRA | AW109: 149 RUE DES ERABLES | AZ109: 13760 | BA109: SAINT CANNAT | BB109: FR | BC109: France
A110: =IF(COUNTIF(Catégories!A:A,X110)=0,"catégorie inconnue",_xlfn.XLOOKUP(X110,Catégories!A:A,Catégories!B:B)) -> Frêt | B110: =SUM(AJ110:AL110)+SUM(AN110:AP110) -> 0 | C110: =AN110 -> 0 | D110: =B110-C110 -> 0 | E110: =IF(AH110<>0,ROUNDUP(AH110,0),IF(BB110<>"FR","hors France",IF(AH110<>0,ROUNDUP(AH110,0),_xlfn.XLOOKUP(AJ110,'PA GLS'!B:B,'PA GLS'!A:A)))) -> 1 | F110: 2501382993 | G110: 1030234750 | H110: 30.06.2026 | I110: 2500034092 | J110: LA RUCHE LOGISTIQUE | K110: 9000009190 | L110: 46946 | M110: LA RUCHE | N110: 9000082822 | O110: Laboratoires Christian Roche | S110: 2507012387 | T110: LA RUCHE LOGISTIQUE | U110: FDS | V110: FDS_D01_S01 | W110: BP FlexDelivery - Dis. 01 - Size 01 | X110: PARCEDOMESFDS | Z110: 209 | AA110: 03.06.2026 | AB110: 00L0GLJP | AC110: 6708090 | AE110: 0 | AF110: 1 | AG110: 0 | AH110: 0.26 | AI110: KG | AJ110: 0 | AK110: 0 | AL110: 0 | AM110: 0 | AN110: 0 | AO110: 0 | AP110: 0 | AQ110: EUR | AS110: EXP20260602-2777085 | AU110: 00L0GLJP | AV110: VEYSSADE SANDRA | AW110: 149 RUE DES ERABLES | AZ110: 13760 | BA110: SAINT CANNAT | BB110: FR | BC110: France
A111: =IF(COUNTIF(Catégories!A:A,X111)=0,"catégorie inconnue",_xlfn.XLOOKUP(X111,Catégories!A:A,Catégories!B:B)) -> Frêt | B111: =SUM(AJ111:AL111)+SUM(AN111:AP111) -> 7.43 | C111: =AN111 -> 1.64 | D111: =B111-C111 -> 5.79 | E111: =IF(AH111<>0,ROUNDUP(AH111,0),IF(BB111<>"FR","hors France",IF(AH111<>0,ROUNDUP(AH111,0),_xlfn.XLOOKUP(AJ111,'PA GLS'!B:B,'PA GLS'!A:A)))) -> 3 | F111: 2501382993 | G111: 1030233879 | H111: 30.06.2026 | I111: 2500034092 | J111: LA RUCHE LOGISTIQUE | K111: 9000009190 | L111: 46946 | M111: LA RUCHE | N111: 9000037814 | O111: LA RUCHE | S111: 2507012387 | T111: LA RUCHE LOGISTIQUE | U111: FDS | V111: PARCEL_D01_S07 | W111: Business Parcel - Dis. 01 - Size 07 | X111: PARCEDOMESSTANDARD | Z111: 188 | AA111: 03.06.2026 | AB111: 00KUR5UE | AC111: 2604000032 | AE111: 0 | AF111: 0 | AG111: 0 | AH111: 0 | AI111: KG | AJ111: 4.74 | AK111: 0.9 | AL111: 0.15 | AM111: 29.1 | AN111: 1.64 | AO111: 0 | AP111: 0 | AQ111: EUR | AS111: EXP20260602-2776795- | AT111: EXP20260602-2776795- | AU111: 00KUR5UE | AV111: HAYER CECILIA | AW111: 11 RUE DE L'EGLISE | AZ111: 68250 | BA111: WESTHALTEN | BB111: FR | BC111: France
A112: =IF(COUNTIF(Catégories!A:A,X112)=0,"catégorie inconnue",_xlfn.XLOOKUP(X112,Catégories!A:A,Catégories!B:B)) -> Frêt | B112: =SUM(AJ112:AL112)+SUM(AN112:AP112) -> 6.6 | C112: =AN112 -> 1.45 | D112: =B112-C112 -> 5.15 | E112: =IF(AH112<>0,ROUNDUP(AH112,0),IF(BB112<>"FR","hors France",IF(AH112<>0,ROUNDUP(AH112,0),_xlfn.XLOOKUP(AJ112,'PA GLS'!B:B,'PA GLS'!A:A)))) -> 1 | F112: 2501382993 | G112: 1030233879 | H112: 30.06.2026 | I112: 2500034092 | J112: LA RUCHE LOGISTIQUE | K112: 9000009190 | L112: 46946 | M112: LA RUCHE | N112: 9000037814 | O112: LA RUCHE | S112: 2507012387 | T112: LA RUCHE LOGISTIQUE | U112: FDS | V112: PARCEL_D01_S04 | W112: Business Parcel - Dis. 01 - Size 04 | X112: PARCEDOMESSTANDARD | Z112: 187 | AA112: 03.06.2026 | AB112: 00KUR5UB | AC112: 2604000029 | AE112: 0 | AF112: 0 | AG112: 0 | AH112: 0 | AI112: KG | AJ112: 4.1 | AK112: 0.9 | AL112: 0.15 | AM112: 29.1 | AN112: 1.45 | AO112: 0 | AP112: 0 | AQ112: EUR | AS112: EXP20260602-2776794- | AT112: EXP20260602-2776794- | AU112: 00KUR5UB | AV112: DEVISME NOEMIE | AW112: 2 RUE DU POISSON BLEU | AZ112: 92290 | BA112: CHATENAY MALABRY | BB112: FR | BC112: France
A113: =IF(COUNTIF(Catégories!A:A,X113)=0,"catégorie inconnue",_xlfn.XLOOKUP(X113,Catégories!A:A,Catégories!B:B)) -> Frêt | B113: =SUM(AJ113:AL113)+SUM(AN113:AP113) -> 6.6 | C113: =AN113 -> 1.45 | D113: =B113-C113 -> 5.15 | E113: =IF(AH113<>0,ROUNDUP(AH113,0),IF(BB113<>"FR","hors France",IF(AH113<>0,ROUNDUP(AH113,0),_xlfn.XLOOKUP(AJ113,'PA GLS'!B:B,'PA GLS'!A:A)))) -> 1 | F113: 2501382993 | G113: 1030233879 | H113: 30.06.2026 | I113: 2500034092 | J113: LA RUCHE LOGISTIQUE | K113: 9000009190 | L113: 46946 | M113: LA RUCHE | N113: 9000037814 | O113: LA RUCHE | S113: 2507012387 | T113: LA RUCHE LOGISTIQUE | U113: FDS | V113: PARCEL_D01_S04 | W113: Business Parcel - Dis. 01 - Size 04 | X113: PARCEDOMESSTANDARD | Z113: 187 | AA113: 03.06.2026 | AB113: 00KUR5UA | AC113: 2604000028 | AE113: 0 | AF113: 0 | AG113: 0 | AH113: 0 | AI113: KG | AJ113: 4.1 | AK113: 0.9 | AL113: 0.15 | AM113: 29.1 | AN113: 1.45 | AO113: 0 | AP113: 0 | AQ113: EUR | AS113: EXP20260602-2777009- | AT113: EXP20260602-2777009- | AU113: 00KUR5UA | AV113: DEVISME NOEMIE | AW113: 2 RUE DU POISSON BLEU | AZ113: 92290 | BA113: CHATENAY MALABRY | BB113: FR | BC113: France
A114: =IF(COUNTIF(Catégories!A:A,X114)=0,"catégorie inconnue",_xlfn.XLOOKUP(X114,Catégories!A:A,Catégories!B:B)) -> Frêt | B114: =SUM(AJ114:AL114)+SUM(AN114:AP114) -> 6.6 | C114: =AN114 -> 1.45 | D114: =B114-C114 -> 5.15 | E114: =IF(AH114<>0,ROUNDUP(AH114,0),IF(BB114<>"FR","hors France",IF(AH114<>0,ROUNDUP(AH114,0),_xlfn.XLOOKUP(AJ114,'PA GLS'!B:B,'PA GLS'!A:A)))) -> 1 | F114: 2501382993 | G114: 1030233879 | H114: 30.06.2026 | I114: 2500034092 | J114: LA RUCHE LOGISTIQUE | K114: 9000009190 | L114: 46946 | M114: LA RUCHE | N114: 9000037814 | O114: LA RUCHE | S114: 2507012387 | T114: LA RUCHE LOGISTIQUE | U114: FDS | V114: PARCEL_D01_S03 | W114: Business Parcel - Dis. 01 - Size 03 | X114: PARCEDOMESSTANDARD | Z114: 186 | AA114: 03.06.2026 | AB114: 00KUR5U8 | AC114: 2604000026 | AE114: 0 | AF114: 0 | AG114: 0 | AH114: 0 | AI114: KG | AJ114: 4.1 | AK114: 0.9 | AL114: 0.15 | AM114: 29.1 | AN114: 1.45 | AO114: 0 | AP114: 0 | AQ114: EUR | AS114: EXP20260527-2766394- | AT114: EXP20260527-2766394- | AU114: 00KUR5U8 | AV114: DE COURCY CHRISTINE | AW114: 4, AVENUE DE LA GARE LES PRAI | AZ114: 33138 | BA114: LANTON | BB114: FR | BC114: France
A115: =IF(COUNTIF(Catégories!A:A,X115)=0,"catégorie inconnue",_xlfn.XLOOKUP(X115,Catégories!A:A,Catégories!B:B)) -> Frêt | B115: =SUM(AJ115:AL115)+SUM(AN115:AP115) -> 0 | C115: =AN115 -> 0 | D115: =B115-C115 -> 0 | E115: =IF(AH115<>0,ROUNDUP(AH115,0),IF(BB115<>"FR","hors France",IF(AH115<>0,ROUNDUP(AH115,0),_xlfn.XLOOKUP(AJ115,'PA GLS'!B:B,'PA GLS'!A:A)))) -> 2 | F115: 2501382993 | G115: 1030166881 | H115: 30.06.2026 | I115: 2500034092 | J115: LA RUCHE LOGISTIQUE | K115: 9000009190 | L115: 46946 | M115: LA RUCHE | N115: 9000079830 | O115: BY FOUTAS | S115: 2507012387 | T115: LA RUCHE LOGISTIQUE | U115: FDS | V115: FDS_D01_S01 | W115: BP FlexDelivery - Dis. 01 - Size 01 | X115: PARCEDOMESFDS | Z115: 17 | AA115: 03.06.2026 | AB115: 00KZZJU4 | AC115: 2604000055 | AE115: 0 | AF115: 1 | AG115: 0 | AH115: 1.18 | AI115: KG | AJ115: 0 | AK115: 0 | AL115: 0 | AM115: 0 | AN115: 0 | AO115: 0 | AP115: 0 | AQ115: EUR | AS115: EXP20260602-2776355- | AT115: EXP20260602-2776355- | AU115: 00KZZJU4 | AV115: DEWAELE HELENE | AW115: 287 AVENUE DE LA GARE | AZ115: 74130 | BA115: BONNEVILLE | BB115: FR | BC115: France
A116: =IF(COUNTIF(Catégories!A:A,X116)=0,"catégorie inconnue",_xlfn.XLOOKUP(X116,Catégories!A:A,Catégories!B:B)) -> Frêt | B116: =SUM(AJ116:AL116)+SUM(AN116:AP116) -> 0 | C116: =AN116 -> 0 | D116: =B116-C116 -> 0 | E116: =IF(AH116<>0,ROUNDUP(AH116,0),IF(BB116<>"FR","hors France",IF(AH116<>0,ROUNDUP(AH116,0),_xlfn.XLOOKUP(AJ116,'PA GLS'!B:B,'PA GLS'!A:A)))) -> 2 | F116: 2501382993 | G116: 1030166881 | H116: 30.06.2026 | I116: 2500034092 | J116: LA RUCHE LOGISTIQUE | K116: 9000009190 | L116: 46946 | M116: LA RUCHE | N116: 9000079830 | O116: BY FOUTAS | S116: 2507012387 | T116: LA RUCHE LOGISTIQUE | U116: FDS | V116: FDS_D01_S01 | W116: BP FlexDelivery - Dis. 01 - Size 01 | X116: PARCEDOMESFDS | Z116: 17 | AA116: 03.06.2026 | AB116: 00KZZJU5 | AC116: 2604000056 | AE116: 0 | AF116: 1 | AG116: 0 | AH116: 1.6 | AI116: KG | AJ116: 0 | AK116: 0 | AL116: 0 | AM116: 0 | AN116: 0 | AO116: 0 | AP116: 0 | AQ116: EUR | AS116: EXP20260601-2774807- | AT116: EXP20260601-2774807- | AU116: 00KZZJU5 | AV116: BROCHART NANS | AW116: 8 RUE CLEMENT VIENOT | AZ116: 94300 | BA116: VINCENNES | BB116: FR | BC116: France
A117: =IF(COUNTIF(Catégories!A:A,X117)=0,"catégorie inconnue",_xlfn.XLOOKUP(X117,Catégories!A:A,Catégories!B:B)) -> Frêt | B117: =SUM(AJ117:AL117)+SUM(AN117:AP117) -> 0 | C117: =AN117 -> 0 | D117: =B117-C117 -> 0 | E117: =IF(AH117<>0,ROUNDUP(AH117,0),IF(BB117<>"FR","hors France",IF(AH117<>0,ROUNDUP(AH117,0),_xlfn.XLOOKUP(AJ117,'PA GLS'!B:B,'PA GLS'!A:A)))) -> 2 | F117: 2501382993 | G117: 1030166881 | H117: 30.06.2026 | I117: 2500034092 | J117: LA RUCHE LOGISTIQUE | K117: 9000009190 | L117: 46946 | M117: LA RUCHE | N117: 9000079830 | O117: BY FOUTAS | S117: 2507012387 | T117: LA RUCHE LOGISTIQUE | U117: FDS | V117: FDS_D01_S01 | W117: BP FlexDelivery - Dis. 01 - Size 01 | X117: PARCEDOMESFDS | Z117: 17 | AA117: 03.06.2026 | AB117: 00KZZJU6 | AC117: 2604000057 | AE117: 0 | AF117: 1 | AG117: 0 | AH117: 1.11 | AI117: KG | AJ117: 0 | AK117: 0 | AL117: 0 | AM117: 0 | AN117: 0 | AO117: 0 | AP117: 0 | AQ117: EUR | AS117: EXP20260602-2777082- | AT117: EXP20260602-2777082- | AU117: 00KZZJU6 | AV117: LEA LABROUSSE | AW117: 86 AVENUE DE STALINGRAD | AZ117: 94120 | BA117: FONTENAY-SOUS-BOIS | BB117: FR | BC117: France
A118: =IF(COUNTIF(Catégories!A:A,X118)=0,"catégorie inconnue",_xlfn.XLOOKUP(X118,Catégories!A:A,Catégories!B:B)) -> Frêt | B118: =SUM(AJ118:AL118)+SUM(AN118:AP118) -> 0 | C118: =AN118 -> 0 | D118: =B118-C118 -> 0 | E118: =IF(AH118<>0,ROUNDUP(AH118,0),IF(BB118<>"FR","hors France",IF(AH118<>0,ROUNDUP(AH118,0),_xlfn.XLOOKUP(AJ118,'PA GLS'!B:B,'PA GLS'!A:A)))) -> 2 | F118: 2501382993 | G118: 1030166881 | H118: 30.06.2026 | I118: 2500034092 | J118: LA RUCHE LOGISTIQUE | K118: 9000009190 | L118: 46946 | M118: LA RUCHE | N118: 9000079830 | O118: BY FOUTAS | S118: 2507012387 | T118: LA RUCHE LOGISTIQUE | U118: FDS | V118: FDS_D01_S01 | W118: BP FlexDelivery - Dis. 01 - Size 01 | X118: PARCEDOMESFDS | Z118: 17 | AA118: 03.06.2026 | AB118: 00KZZJU7 | AC118: 2604000058 | AE118: 0 | AF118: 1 | AG118: 0 | AH118: 1.11 | AI118: KG | AJ118: 0 | AK118: 0 | AL118: 0 | AM118: 0 | AN118: 0 | AO118: 0 | AP118: 0 | AQ118: EUR | AS118: EXP20260603-2777637- | AT118: EXP20260603-2777637- | AU118: 00KZZJU7 | AV118: DROILLARD MAELIS | AW118: 4 RUE DU REDUIT | AZ118: 33520 | BA118: BRUGES | BB118: FR | BC118: France
A119: =IF(COUNTIF(Catégories!A:A,X119)=0,"catégorie inconnue",_xlfn.XLOOKUP(X119,Catégories!A:A,Catégories!B:B)) -> Frêt | B119: =SUM(AJ119:AL119)+SUM(AN119:AP119) -> 0 | C119: =AN119 -> 0 | D119: =B119-C119 -> 0 | E119: =IF(AH119<>0,ROUNDUP(AH119,0),IF(BB119<>"FR","hors France",IF(AH119<>0,ROUNDUP(AH119,0),_xlfn.XLOOKUP(AJ119,'PA GLS'!B:B,'PA GLS'!A:A)))) -> 2 | F119: 2501382993 | G119: 1030166881 | H119: 30.06.2026 | I119: 2500034092 | J119: LA RUCHE LOGISTIQUE | K119: 9000009190 | L119: 46946 | M119: LA RUCHE | N119: 9000079830 | O119: BY FOUTAS | S119: 2507012387 | T119: LA RUCHE LOGISTIQUE | U119: FDS | V119: FDS_D01_S01 | W119: BP FlexDelivery - Dis. 01 - Size 01 | X119: PARCEDOMESFDS | Z119: 17 | AA119: 03.06.2026 | AB119: 00KZZJU8 | AC119: 2604000059 | AE119: 0 | AF119: 1 | AG119: 0 | AH119: 1.56 | AI119: KG | AJ119: 0 | AK119: 0 | AL119: 0 | AM119: 0 | AN119: 0 | AO119: 0 | AP119: 0 | AQ119: EUR | AS119: EXP20260602-2777194- | AT119: EXP20260602-2777194- | AU119: 00KZZJU8 | AV119: SAINT BLANCAT MILENA | AW119: 29 IMPASSE CHIMENE | AZ119: 34070 | BA119: MONTPELLIER | BB119: FR | BC119: France
A120: =IF(COUNTIF(Catégories!A:A,X120)=0,"catégorie inconnue",_xlfn.XLOOKUP(X120,Catégories!A:A,Catégories!B:B)) -> Frêt | B120: =SUM(AJ120:AL120)+SUM(AN120:AP120) -> 0 | C120: =AN120 -> 0 | D120: =B120-C120 -> 0 | E120: =IF(AH120<>0,ROUNDUP(AH120,0),IF(BB120<>"FR","hors France",IF(AH120<>0,ROUNDUP(AH120,0),_xlfn.XLOOKUP(AJ120,'PA GLS'!B:B,'PA GLS'!A:A)))) -> 1 | F120: 2501382993 | G120: 1030166881 | H120: 30.06.2026 | I120: 2500034092 | J120: LA RUCHE LOGISTIQUE | K120: 9000009190 | L120: 46946 | M120: LA RUCHE | N120: 9000079830 | O120: BY FOUTAS | S120: 2507012387 | T120: LA RUCHE LOGISTIQUE | U120: FDS | V120: FDS_D01_S01 | W120: BP FlexDelivery - Dis. 01 - Size 01 | X120: PARCEDOMESFDS | Z120: 17 | AA120: 03.06.2026 | AB120: 00KZZJU9 | AC120: 2604000060 | AE120: 0 | AF120: 1 | AG120: 0 | AH120: 0.48 | AI120: KG | AJ120: 0 | AK120: 0 | AL120: 0 | AM120: 0 | AN120: 0 | AO120: 0 | AP120: 0 | AQ120: EUR | AS120: EXP20260602-2777192- | AT120: EXP20260602-2777192- | AU120: 00KZZJU9 | AV120: SERGENT AGATHE | AW120: 9 RUE DU LOCH | AZ120: 29780 | BA120: PLOUHINEC | BB120: FR | BC120: France
A121: =IF(COUNTIF(Catégories!A:A,X121)=0,"catégorie inconnue",_xlfn.XLOOKUP(X121,Catégories!A:A,Catégories!B:B)) -> Frêt | B121: =SUM(AJ121:AL121)+SUM(AN121:AP121) -> 0 | C121: =AN121 -> 0 | D121: =B121-C121 -> 0 | E121: =IF(AH121<>0,ROUNDUP(AH121,0),IF(BB121<>"FR","hors France",IF(AH121<>0,ROUNDUP(AH121,0),_xlfn.XLOOKUP(AJ121,'PA GLS'!B:B,'PA GLS'!A:A)))) -> 2 | F121: 2501382993 | G121: 1030166881 | H121: 30.06.2026 | I121: 2500034092 | J121: LA RUCHE LOGISTIQUE | K121: 9000009190 | L121: 46946 | M121: LA RUCHE | N121: 9000079830 | O121: BY FOUTAS | S121: 2507012387 | T121: LA RUCHE LOGISTIQUE | U121: FDS | V121: FDS_D01_S01 | W121: BP FlexDelivery - Dis. 01 - Size 01 | X121: PARCEDOMESFDS | Z121: 17 | AA121: 03.06.2026 | AB121: 00KZZJUA | AC121: 2604000061 | AE121: 0 | AF121: 1 | AG121: 0 | AH121: 1.56 | AI121: KG | AJ121: 0 | AK121: 0 | AL121: 0 | AM121: 0 | AN121: 0 | AO121: 0 | AP121: 0 | AQ121: EUR | AS121: EXP20260602-2777358- | AT121: EXP20260602-2777358- | AU121: 00KZZJUA | AV121: BAOUCHE FABIENNE | AW121: 2 RUE CHOPIN | AZ121: 62590 | BA121: OIGNIES | BB121: FR | BC121: France
A122: =IF(COUNTIF(Catégories!A:A,X122)=0,"catégorie inconnue",_xlfn.XLOOKUP(X122,Catégories!A:A,Catégories!B:B)) -> Frêt | B122: =SUM(AJ122:AL122)+SUM(AN122:AP122) -> 0 | C122: =AN122 -> 0 | D122: =B122-C122 -> 0 | E122: =IF(AH122<>0,ROUNDUP(AH122,0),IF(BB122<>"FR","hors France",IF(AH122<>0,ROUNDUP(AH122,0),_xlfn.XLOOKUP(AJ122,'PA GLS'!B:B,'PA GLS'!A:A)))) -> 3 | F122: 2501382993 | G122: 1030166881 | H122: 30.06.2026 | I122: 2500034092 | J122: LA RUCHE LOGISTIQUE | K122: 9000009190 | L122: 46946 | M122: LA RUCHE | N122: 9000079830 | O122: BY FOUTAS | S122: 2507012387 | T122: LA RUCHE LOGISTIQUE | U122: FDS | V122: FDS_D01_S01 | W122: BP FlexDelivery - Dis. 01 - Size 01 | X122: PARCEDOMESFDS | Z122: 17 | AA122: 03.06.2026 | AB122: 00KZZJUB | AC122: 2604000062 | AE122: 0 | AF122: 1 | AG122: 0 | AH122: 2.05 | AI122: KG | AJ122: 0 | AK122: 0 | AL122: 0 | AM122: 0 | AN122: 0 | AO122: 0 | AP122: 0 | AQ122: EUR | AS122: EXP20260602-2777018- | AT122: EXP20260602-2777018- | AU122: 00KZZJUB | AV122: TADRIST MAURANE | AW122: 5 RUE PASTEUR | AZ122: 91130 | BA122: RIS-ORANGIS | BB122: FR | BC122: France
... A134: =IF(COUNTIF(Catégories!A:A,X134)=0,"catégorie inconnue",_xlfn.XLOOKUP(X134,Catégories!A:A,Catégories!B:B)) -> Frêt - avisé | B134: =SUM(AJ134:AL134)+SUM(AN134:AP134) -> 0 | C134: =AN134 -> 0 | D134: =B134-C134 -> 0 | E134: =IF(AH134<>0,ROUNDUP(AH134,0),IF(BB134<>"FR","hors France",IF(AH134<>0,ROUNDUP(AH134,0),_xlfn.XLOOKUP(AJ134,'PA GLS'!B:B,'PA GLS'!A:A)))) -> #N/A | F134: 2501382993 | G134: 1030166881 | H134: 30.06.2026 | I134: 2500034092 | J134: LA RUCHE LOGISTIQUE | K134: 9000009190 | L134: 46946 | M134: LA RUCHE | N134: 9000079830 | O134: BY FOUTAS | S134: 2507012387 | T134: LA RUCHE LOGISTIQUE | U134: FDS | V134: SUR_FS_AVIS_01 | W134: AvisÃ© FDS | X134: SURCHALL | Z134: 24 | AA134: 03.06.2026 | AB134: 00KZZJTI | AC134: 2604000033 | AE134: 0 | AF134: 0 | AG134: 0 | AH134: 0 | AI134: KG | AJ134: 0 | AK134: 0 | AL134: 0 | AM134: 0 | AN134: 0 | AO134: 0 | AP134: 0 | AQ134: EUR | AS134: EXP20260529-2769965- | AT134: EXP20260529-2769965- | AU134: 00KZZJTI | AV134: FICHET MORGAN | AW134: 9 RUE DU DOUET | AZ134: 35510 | BA134: CESSON-SEVIGNE | BB134: FR | BC134: France
A135: =IF(COUNTIF(Catégories!A:A,X135)=0,"catégorie inconnue",_xlfn.XLOOKUP(X135,Catégories!A:A,Catégories!B:B)) -> Frêt | B135: =SUM(AJ135:AL135)+SUM(AN135:AP135) -> 0 | C135: =AN135 -> 0 | D135: =B135-C135 -> 0 | E135: =IF(AH135<>0,ROUNDUP(AH135,0),IF(BB135<>"FR","hors France",IF(AH135<>0,ROUNDUP(AH135,0),_xlfn.XLOOKUP(AJ135,'PA GLS'!B:B,'PA GLS'!A:A)))) -> 1 | F135: 2501382993 | G135: 1030206923 | H135: 30.06.2026 | I135: 2500034092 | J135: LA RUCHE LOGISTIQUE | K135: 9000009190 | L135: 46946 | M135: LA RUCHE | N135: 9000079829 | O135: ANOTHER WAY | S135: 2507012387 | T135: LA RUCHE LOGISTIQUE | U135: FDS | V135: FDS_D01_S01 | W135: BP FlexDelivery - Dis. 01 - Size 01 | X135: PARCEDOMESFDS | Z135: 25 | AA135: 03.06.2026 | AB135: 00L0EXFW | AC135: 6700045 | AE135: 0 | AF135: 1 | AG135: 0 | AH135: 0.22 | AI135: KG | AJ135: 0 | AK135: 0 | AL135: 0 | AM135: 0 | AN135: 0 | AO135: 0 | AP135: 0 | AQ135: EUR | AS135: EXP20260601-2772294 | AU135: 00L0EXFW | AV135: ROBERT MURIEL | AW135: 1 CHEMIN DU STADE | AZ135: 3210 | BA135: GIPCY | BB135: FR | BC135: France
A136: =IF(COUNTIF(Catégories!A:A,X136)=0,"catégorie inconnue",_xlfn.XLOOKUP(X136,Catégories!A:A,Catégories!B:B)) -> Frêt | B136: =SUM(AJ136:AL136)+SUM(AN136:AP136) -> 0 | C136: =AN136 -> 0 | D136: =B136-C136 -> 0 | E136: =IF(AH136<>0,ROUNDUP(AH136,0),IF(BB136<>"FR","hors France",IF(AH136<>0,ROUNDUP(AH136,0),_xlfn.XLOOKUP(AJ136,'PA GLS'!B:B,'PA GLS'!A:A)))) -> 1 | F136: 2501382993 | G136: 1030206923 | H136: 30.06.2026 | I136: 2500034092 | J136: LA RUCHE LOGISTIQUE | K136: 9000009190 | L136: 46946 | M136: LA RUCHE | N136: 9000079829 | O136: ANOTHER WAY | S136: 2507012387 | T136: LA RUCHE LOGISTIQUE | U136: FDS | V136: FDS_D01_S01 | W136: BP FlexDelivery - Dis. 01 - Size 01 | X136: PARCEDOMESFDS | Z136: 25 | AA136: 03.06.2026 | AB136: 00L0F7R5 | AC136: 6703047 | AE136: 0 | AF136: 1 | AG136: 0 | AH136: 0.28 | AI136: KG | AJ136: 0 | AK136: 0 | AL136: 0 | AM136: 0 | AN136: 0 | AO136: 0 | AP136: 0 | AQ136: EUR | AS136: EXP20260602-2775957 | AU136: 00L0F7R5 | AV136: BOISSIN CHANTAL | AW136: 11 LOTISSEMENT LA SONATINE 263 | AX136: INT MARCEL- LES-VALENCE | AY136: BOISSIN CHANTAL | AZ136: 26320 | BA136: SAINT MARCEL LES VALENCES | BB136: FR | BC136: France
A137: =IF(COUNTIF(Catégories!A:A,X137)=0,"catégorie inconnue",_xlfn.XLOOKUP(X137,Catégories!A:A,Catégories!B:B)) -> Frêt | B137: =SUM(AJ137:AL137)+SUM(AN137:AP137) -> 6.17 | C137: =AN137 -> 1.35 | D137: =B137-C137 -> 4.82 | E137: =IF(AH137<>0,ROUNDUP(AH137,0),IF(BB137<>"FR","hors France",IF(AH137<>0,ROUNDUP(AH137,0),_xlfn.XLOOKUP(AJ137,'PA GLS'!B:B,'PA GLS'!A:A)))) -> 0.5 | F137: 2501382993 | G137: 1030206923 | H137: 30.06.2026 | I137: 2500034092 | J137: LA RUCHE LOGISTIQUE | K137: 9000009190 | L137: 46946 | M137: LA RUCHE | N137: 9000079829 | O137: ANOTHER WAY | S137: 2507012387 | T137: LA RUCHE LOGISTIQUE | U137: FDS | V137: PARCEL_D01_S02 | W137: Business Parcel - Dis. 01 - Size 02 | X137: PARCEDOMESSTANDARD | Z137: 27 | AA137: 03.06.2026 | AB137: 00L0F7R5 | AC137: 6703047 | AE137: 0 | AF137: 0 | AG137: 0 | AH137: 0 | AI137: KG | AJ137: 3.77 | AK137: 0.9 | AL137: 0.15 | AM137: 29.1 | AN137: 1.35 | AO137: 0 | AP137: 0 | AQ137: EUR | AS137: EXP20260602-2775957 | AU137: 00L0F7R5 | AV137: BOISSIN CHANTAL | AW137: 11 LOTISSEMENT LA SONATINE 263 | AX137: INT MARCEL- LES-VALENCE | AY137: BOISSIN CHANTAL | AZ137: 26320 | BA137: SAINT MARCEL LES VALENCES | BB137: FR | BC137: France
A138: =IF(COUNTIF(Catégories!A:A,X138)=0,"catégorie inconnue",_xlfn.XLOOKUP(X138,Catégories!A:A,Catégories!B:B)) -> Frêt | B138: =SUM(AJ138:AL138)+SUM(AN138:AP138) -> 6.17 | C138: =AN138 -> 1.35 | D138: =B138-C138 -> 4.82 | E138: =IF(AH138<>0,ROUNDUP(AH138,0),IF(BB138<>"FR","hors France",IF(AH138<>0,ROUNDUP(AH138,0),_xlfn.XLOOKUP(AJ138,'PA GLS'!B:B,'PA GLS'!A:A)))) -> 0.5 | F138: 2501382993 | G138: 1030206923 | H138: 30.06.2026 | I138: 2500034092 | J138: LA RUCHE LOGISTIQUE | K138: 9000009190 | L138: 46946 | M138: LA RUCHE | N138: 9000079829 | O138: ANOTHER WAY | S138: 2507012387 | T138: LA RUCHE LOGISTIQUE | U138: FDS | V138: PARCEL_D01_S01 | W138: Business Parcel - Dis. 01 - Size 01 | X138: PARCEDOMESSTANDARD | Z138: 26 | AA138: 03.06.2026 | AB138: 00L0EXFW | AC138: 6700045 | AE138: 0 | AF138: 0 | AG138: 0 | AH138: 0 | AI138: KG | AJ138: 3.77 | AK138: 0.9 | AL138: 0.15 | AM138: 29.1 | AN138: 1.35 | AO138: 0 | AP138: 0 | AQ138: EUR | AS138: EXP20260601-2772294 | AU138: 00L0EXFW | AV138: ROBERT MURIEL | AW138: 1 CHEMIN DU STADE | AZ138: 3210 | BA138: GIPCY | BB138: FR | BC138: France
A139: =IF(COUNTIF(Catégories!A:A,X139)=0,"catégorie inconnue",_xlfn.XLOOKUP(X139,Catégories!A:A,Catégories!B:B)) -> Frêt | B139: =SUM(AJ139:AL139)+SUM(AN139:AP139) -> 0 | C139: =AN139 -> 0 | D139: =B139-C139 -> 0 | E139: =IF(AH139<>0,ROUNDUP(AH139,0),IF(BB139<>"FR","hors France",IF(AH139<>0,ROUNDUP(AH139,0),_xlfn.XLOOKUP(AJ139,'PA GLS'!B:B,'PA GLS'!A:A)))) -> 1 | F139: 2501382993 | G139: 1030230693 | H139: 30.06.2026 | I139: 2500034092 | J139: LA RUCHE LOGISTIQUE | K139: 9000009190 | L139: 46946 | M139: LA RUCHE | N139: 9000079830 | O139: BY FOUTAS | S139: 2507012387 | T139: LA RUCHE LOGISTIQUE | U139: FDS | V139: FDS_D01_S01 | W139: BP FlexDelivery - Dis. 01 - Size 01 | X139: PARCEDOMESFDS | Z139: 111 | AA139: 04.06.2026 | AB139: 00KZZJUE | AC139: 2604000065 | AE139: 0 | AF139: 1 | AG139: 0 | AH139: 0.81 | AI139: KG | AJ139: 0 | AK139: 0 | AL139: 0 | AM139: 0 | AN139: 0 | AO139: 0 | AP139: 0 | AQ139: EUR | AS139: EXP20260603-2779671- | AT139: EXP20260603-2779671- | AU139: 00KZZJUE | AV139: THOULOUZE ELODIE | AW139: RUE DES FARAYETTES | AZ139: 83136 | BA139: GAREOULT | BB139: FR | BC139: France
A140: =IF(COUNTIF(Catégories!A:A,X140)=0,"catégorie inconnue",_xlfn.XLOOKUP(X140,Catégories!A:A,Catégories!B:B)) -> Frêt | B140: =SUM(AJ140:AL140)+SUM(AN140:AP140) -> 0 | C140: =AN140 -> 0 | D140: =B140-C140 -> 0 | E140: =IF(AH140<>0,ROUNDUP(AH140,0),IF(BB140<>"FR","hors France",IF(AH140<>0,ROUNDUP(AH140,0),_xlfn.XLOOKUP(AJ140,'PA GLS'!B:B,'PA GLS'!A:A)))) -> 4 | F140: 2501382993 | G140: 1030230693 | H140: 30.06.2026 | I140: 2500034092 | J140: LA RUCHE LOGISTIQUE | K140: 9000009190 | L140: 46946 | M140: LA RUCHE | N140: 9000079830 | O140: BY FOUTAS | S140: 2507012387 | T140: LA RUCHE LOGISTIQUE | U140: FDS | V140: FDS_D01_S01 | W140: BP FlexDelivery - Dis. 01 - Size 01 | X140: PARCEDOMESFDS | Z140: 111 | AA140: 04.06.2026 | AB140: 00KZZJUD | AC140: 2604000064 | AE140: 0 | AF140: 1 | AG140: 0 | AH140: 3.12 | AI140: KG | AJ140: 0 | AK140: 0 | AL140: 0 | AM140: 0 | AN140: 0 | AO140: 0 | AP140: 0 | AQ140: EUR | AS140: EXP20260604-2779972- | AT140: EXP20260604-2779972- | AU140: 00KZZJUD | AV140: DEVEVEY JULIA | AW140: 42 ROUTE DE LAIVES | AZ140: 71240 | BA140: LALHEUE | BB140: FR | BC140: France
A141: =IF(COUNTIF(Catégories!A:A,X141)=0,"catégorie inconnue",_xlfn.XLOOKUP(X141,Catégories!A:A,Catégories!B:B)) -> Frêt - retour | B141: =SUM(AJ141:AL141)+SUM(AN141:AP141) -> 5.29 | C141: =AN141 -> 1.19 | D141: =B141-C141 -> 4.1 | E141: =IF(AH141<>0,ROUNDUP(AH141,0),IF(BB141<>"FR","hors France",IF(AH141<>0,ROUNDUP(AH141,0),_xlfn.XLOOKUP(AJ141,'PA GLS'!B:B,'PA GLS'!A:A)))) -> 1 | F141: 2501382993 | G141: 1030230693 | H141: 30.06.2026 | I141: 2500034092 | J141: LA RUCHE LOGISTIQUE | K141: 9000009190 | L141: 46946 | M141: LA RUCHE | N141: 9000079830 | O141: BY FOUTAS | S141: 2507012387 | T141: LA RUCHE LOGISTIQUE | U141: FDS | V141: SUR_RET_BUP_D01 | W141: Retour Colis BUP - Classe 01 | X141: SURCHALL RETURN | Z141: 119 | AA141: 04.06.2026 | AB141: 00KZ5BVG | AC141: 6579152 | AE141: 0 | AF141: 0 | AG141: 0 | AH141: 0 | AI141: KG | AJ141: 4.1 | AK141: 0 | AL141: 0 | AM141: 29.1 | AN141: 1.19 | AO141: 0 | AP141: 0 | AQ141: EUR | AS141: EXP20260522-2756836 | AU141: 00KZ5BVG | AV141: RINCK MARIE | AW141: 191 RUE DE LA PRADELLE | AZ141: 63000 | BA141: CLERMONT-FERRAND | BB141: FR | BC141: France
A142: =IF(COUNTIF(Catégories!A:A,X142)=0,"catégorie inconnue",_xlfn.XLOOKUP(X142,Catégories!A:A,Catégories!B:B)) -> Frêt - avisé | B142: =SUM(AJ142:AL142)+SUM(AN142:AP142) -> 0 | C142: =AN142 -> 0 | D142: =B142-C142 -> 0 | E142: =IF(AH142<>0,ROUNDUP(AH142,0),IF(BB142<>"FR","hors France",IF(AH142<>0,ROUNDUP(AH142,0),_xlfn.XLOOKUP(AJ142,'PA GLS'!B:B,'PA GLS'!A:A)))) -> #N/A | F142: 2501382993 | G142: 1030230693 | H142: 30.06.2026 | I142: 2500034092 | J142: LA RUCHE LOGISTIQUE | K142: 9000009190 | L142: 46946 | M142: LA RUCHE | N142: 9000079830 | O142: BY FOUTAS | S142: 2507012387 | T142: LA RUCHE LOGISTIQUE | U142: FDS | V142: SUR_FS_AVIS_01 | W142: AvisÃ© FDS | X142: SURCHALL | Z142: 118 | AA142: 04.06.2026 | AB142: 00KZZJUC | AC142: 2604000063 | AE142: 0 | AF142: 0 | AG142: 0 | AH142: 0 | AI142: KG | AJ142: 0 | AK142: 0 | AL142: 0 | AM142: 0 | AN142: 0 | AO142: 0 | AP142: 0 | AQ142: EUR | AS142: EXP20260603-2777940- | AT142: EXP20260603-2777940- | AU142: 00KZZJUC | AV142: TOUTENU CAMILLE | AW142: CHEMIN DU PRE POULET | AZ142: 69700 | BA142: MONTAGNY | BB142: FR | BC142: France
A143: =IF(COUNTIF(Catégories!A:A,X143)=0,"catégorie inconnue",_xlfn.XLOOKUP(X143,Catégories!A:A,Catégories!B:B)) -> Adresse | B143: =SUM(AJ143:AL143)+SUM(AN143:AP143) -> 3.04 | C143: =AN143 -> 0.68 | D143: =B143-C143 -> 2.36 | E143: =IF(AH143<>0,ROUNDUP(AH143,0),IF(BB143<>"FR","hors France",IF(AH143<>0,ROUNDUP(AH143,0),_xlfn.XLOOKUP(AJ143,'PA GLS'!B:B,'PA GLS'!A:A)))) -> #N/A | F143: 2501382993 | G143: 1030230693 | H143: 30.06.2026 | I143: 2500034092 | J143: LA RUCHE LOGISTIQUE | K143: 9000009190 | L143: 46946 | M143: LA RUCHE | N143: 9000079830 | O143: BY FOUTAS | S143: 2507012387 | T143: LA RUCHE LOGISTIQUE | U143: FDS | V143: SUR_CARD_01 | W143: Majoration AvisÃ© sans TÃ©l ou mail | X143: SURCHALL NTFCNCRD | Z143: 117 | AA143: 04.06.2026 | AB143: 00KZZJUC | AC143: 2604000063 | AE143: 0 | AF143: 0 | AG143: 0 | AH143: 0 | AI143: KG | AJ143: 2.36 | AK143: 0 | AL143: 0 | AM143: 29.1 | AN143: 0.68 | AO143: 0 | AP143: 0 | AQ143: EUR | AS143: EXP20260603-2777940- | AT143: EXP20260603-2777940- | AU143: 00KZZJUC | AV143: TOUTENU CAMILLE | AW143: CHEMIN DU PRE POULET | AZ143: 69700 | BA143: MONTAGNY | BB143: FR | BC143: France
A144: =IF(COUNTIF(Catégories!A:A,X144)=0,"catégorie inconnue",_xlfn.XLOOKUP(X144,Catégories!A:A,Catégories!B:B)) -> Frêt | B144: =SUM(AJ144:AL144)+SUM(AN144:AP144) -> 8.15 | C144: =AN144 -> 1.8 | D144: =B144-C144 -> 6.35 | E144: =IF(AH144<>0,ROUNDUP(AH144,0),IF(BB144<>"FR","hors France",IF(AH144<>0,ROUNDUP(AH144,0),_xlfn.XLOOKUP(AJ144,'PA GLS'!B:B,'PA GLS'!A:A)))) -> 4 | F144: 2501382993 | G144: 1030230693 | H144: 30.06.2026 | I144: 2500034092 | J144: LA RUCHE LOGISTIQUE | K144: 9000009190 | L144: 46946 | M144: LA RUCHE | N144: 9000079830 | O144: BY FOUTAS | S144: 2507012387 | T144: LA RUCHE LOGISTIQUE | U144: FDS | V144: PARCEL_D01_S08 | W144: Business Parcel - Dis. 01 - Size 08 | X144: PARCEDOMESSTANDARD | Z144: 116 | AA144: 04.06.2026 | AB144: 00KZZJUD | AC144: 2604000064 | AE144: 0 | AF144: 0 | AG144: 0 | AH144: 0 | AI144: KG | AJ144: 5.3 | AK144: 0.9 | AL144: 0.15 | AM144: 29.1 | AN144: 1.8 | AO144: 0 | AP144: 0 | AQ144: EUR | AS144: EXP20260604-2779972- | AT144: EXP20260604-2779972- | AU144: 00KZZJUD | AV144: DEVEVEY JULIA | AW144: 42 ROUTE DE LAIVES | AZ144: 71240 | BA144: LALHEUE | BB144: FR | BC144: France
A145: =IF(COUNTIF(Catégories!A:A,X145)=0,"catégorie inconnue",_xlfn.XLOOKUP(X145,Catégories!A:A,Catégories!B:B)) -> Frêt | B145: =SUM(AJ145:AL145)+SUM(AN145:AP145) -> 7.01 | C145: =AN145 -> 1.54 | D145: =B145-C145 -> 5.47 | E145: =IF(AH145<>0,ROUNDUP(AH145,0),IF(BB145<>"FR","hors France",IF(AH145<>0,ROUNDUP(AH145,0),_xlfn.XLOOKUP(AJ145,'PA GLS'!B:B,'PA GLS'!A:A)))) -> 2 | F145: 2501382993 | G145: 1030230693 | H145: 30.06.2026 | I145: 2500034092 | J145: LA RUCHE LOGISTIQUE | K145: 9000009190 | L145: 46946 | M145: LA RUCHE | N145: 9000079830 | O145: BY FOUTAS | S145: 2507012387 | T145: LA RUCHE LOGISTIQUE | U145: FDS | V145: PARCEL_D01_S06 | W145: Business Parcel - Dis. 01 - Size 06 | X145: PARCEDOMESSTANDARD | Z145: 115 | AA145: 04.06.2026 | AB145: 00KZZJUH | AC145: 2604000068 | AE145: 0 | AF145: 0 | AG145: 0 | AH145: 0 | AI145: KG | AJ145: 4.42 | AK145: 0.9 | AL145: 0.15 | AM145: 29.1 | AN145: 1.54 | AO145: 0 | AP145: 0 | AQ145: EUR | AS145: EXP20260603-2779673- | AT145: EXP20260603-2779673- | AU145: 00KZZJUH | AV145: TERNISIEN HELENE | AW145: 13 RUE EMILE BATAILLE | AZ145: 93100 | BA145: MONTREUIL | BB145: FR | BC145: France
A146: =IF(COUNTIF(Catégories!A:A,X146)=0,"catégorie inconnue",_xlfn.XLOOKUP(X146,Catégories!A:A,Catégories!B:B)) -> Frêt | B146: =SUM(AJ146:AL146)+SUM(AN146:AP146) -> 0 | C146: =AN146 -> 0 | D146: =B146-C146 -> 0 | E146: =IF(AH146<>0,ROUNDUP(AH146,0),IF(BB146<>"FR","hors France",IF(AH146<>0,ROUNDUP(AH146,0),_xlfn.XLOOKUP(AJ146,'PA GLS'!B:B,'PA GLS'!A:A)))) -> 1 | F146: 2501382993 | G146: 1030232655 | H146: 30.06.2026 | I146: 2500034092 | J146: LA RUCHE LOGISTIQUE | K146: 9000009190 | L146: 46946 | M146: LA RUCHE | N146: 9000037814 | O146: LA RUCHE | S146: 2507012387 | T146: LA RUCHE LOGISTIQUE | U146: FDS | V146: FDS_D01_S01 | W146: BP FlexDelivery - Dis. 01 - Size 01 | X146: PARCEDOMESFDS | Z146: 144 | AA146: 04.06.2026 | AB146: 00KUR5UG | AC146: 2604000034 | AE146: 0 | AF146: 1 | AG146: 0 | AH146: 0.38 | AI146: KG | AJ146: 0 | AK146: 0 | AL146: 0 | AM146: 0 | AN146: 0 | AO146: 0 | AP146: 0 | AQ146: EUR | AS146: EXP20260603-2778120- | AT146: EXP20260603-2778120- | AU146: 00KUR5UG | AV146: MARTINE ABITBOL | AW146: 4 RUE SAINT GILLES 75003 PARIS | AZ146: 75003 | BA146: PARIS | BB146: FR | BC146: France
A147: =IF(COUNTIF(Catégories!A:A,X147)=0,"catégorie inconnue",_xlfn.XLOOKUP(X147,Catégories!A:A,Catégories!B:B)) -> Frêt | B147: =SUM(AJ147:AL147)+SUM(AN147:AP147) -> 0 | C147: =AN147 -> 0 | D147: =B147-C147 -> 0 | E147: =IF(AH147<>0,ROUNDUP(AH147,0),IF(BB147<>"FR","hors France",IF(AH147<>0,ROUNDUP(AH147,0),_xlfn.XLOOKUP(AJ147,'PA GLS'!B:B,'PA GLS'!A:A)))) -> 1 | F147: 2501382993 | G147: 1030232655 | H147: 30.06.2026 | I147: 2500034092 | J147: LA RUCHE LOGISTIQUE | K147: 9000009190 | L147: 46946 | M147: LA RUCHE | N147: 9000037814 | O147: LA RUCHE | S147: 2507012387 | T147: LA RUCHE LOGISTIQUE | U147: FDS | V147: FDS_D01_S01 | W147: BP FlexDelivery - Dis. 01 - Size 01 | X147: PARCEDOMESFDS | Z147: 144 | AA147: 04.06.2026 | AB147: 00KUR5UH | AC147: 2604000035 | AE147: 0 | AF147: 1 | AG147: 0 | AH147: 0.64 | AI147: KG | AJ147: 0 | AK147: 0 | AL147: 0 | AM147: 0 | AN147: 0 | AO147: 0 | AP147: 0 | AQ147: EUR | AS147: EXP20260603-2779498- | AT147: EXP20260603-2779498- | AU147: 00KUR5UH | AV147: MESNARD RAYAN | AW147: 6 RUE DE LA HOLLANDE | AZ147: 49300 | BA147: CHOLET | BB147: FR | BC147: France
A148: =IF(COUNTIF(Catégories!A:A,X148)=0,"catégorie inconnue",_xlfn.XLOOKUP(X148,Catégories!A:A,Catégories!B:B)) -> Frêt | B148: =SUM(AJ148:AL148)+SUM(AN148:AP148) -> 0 | C148: =AN148 -> 0 | D148: =B148-C148 -> 0 | E148: =IF(AH148<>0,ROUNDUP(AH148,0),IF(BB148<>"FR","hors France",IF(AH148<>0,ROUNDUP(AH148,0),_xlfn.XLOOKUP(AJ148,'PA GLS'!B:B,'PA GLS'!A:A)))) -> 1 | F148: 2501382993 | G148: 1030232655 | H148: 30.06.2026 | I148: 2500034092 | J148: LA RUCHE LOGISTIQUE | K148: 9000009190 | L148: 46946 | M148: LA RUCHE | N148: 9000037814 | O148: LA RUCHE | S148: 2507012387 | T148: LA RUCHE LOGISTIQUE | U148: FDS | V148: FDS_D01_S01 | W148: BP FlexDelivery - Dis. 01 - Size 01 | X148: PARCEDOMESFDS | Z148: 144 | AA148: 04.06.2026 | AB148: 00KUR5UI | AC148: 2604000036 | AE148: 0 | AF148: 1 | AG148: 0 | AH148: 0.28 | AI148: KG | AJ148: 0 | AK148: 0 | AL148: 0 | AM148: 0 | AN148: 0 | AO148: 0 | AP148: 0 | AQ148: EUR | AS148: EXP20260603-2779680- | AT148: EXP20260603-2779680- | AU148: 00KUR5UI | AV148: OGEZ MAXIME | AW148: 39, RUE DU LEVANT | AZ148: 34830 | BA148: JACOU | BB148: FR | BC148: France
A149: =IF(COUNTIF(Catégories!A:A,X149)=0,"catégorie inconnue",_xlfn.XLOOKUP(X149,Catégories!A:A,Catégories!B:B)) -> Frêt | B149: =SUM(AJ149:AL149)+SUM(AN149:AP149) -> 6.17 | C149: =AN149 -> 1.35 | D149: =B149-C149 -> 4.82 | E149: =IF(AH149<>0,ROUNDUP(AH149,0),IF(BB149<>"FR","hors France",IF(AH149<>0,ROUNDUP(AH149,0),_xlfn.XLOOKUP(AJ149,'PA GLS'!B:B,'PA GLS'!A:A)))) -> 0.5 | F149: 2501382993 | G149: 1030232655 | H149: 30.06.2026 | I149: 2500034092 | J149: LA RUCHE LOGISTIQUE | K149: 9000009190 | L149: 46946 | M149: LA RUCHE | N149: 9000037814 | O149: LA RUCHE | S149: 2507012387 | T149: LA RUCHE LOGISTIQUE | U149: FDS | V149: PARCEL_D01_S02 | W149: Business Parcel - Dis. 01 - Size 02 | X149: PARCEDOMESSTANDARD | Z149: 145 | AA149: 04.06.2026 | AB149: 00KUR5UG | AC149: 2604000034 | AE149: 0 | AF149: 0 | AG149: 0 | AH149: 0 | AI149: KG | AJ149: 3.77 | AK149: 0.9 | AL149: 0.15 | AM149: 29.1 | AN149: 1.35 | AO149: 0 | AP149: 0 | AQ149: EUR | AS149: EXP20260603-2778120- | AT149: EXP20260603-2778120- | AU149: 00KUR5UG | AV149: MARTINE ABITBOL | AW149: 4 RUE SAINT GILLES 75003 PARIS | AZ149: 75003 | BA149: PARIS | BB149: FR | BC149: France
A150: =IF(COUNTIF(Catégories!A:A,X150)=0,"catégorie inconnue",_xlfn.XLOOKUP(X150,Catégories!A:A,Catégories!B:B)) -> Frêt | B150: =SUM(AJ150:AL150)+SUM(AN150:AP150) -> 6.17 | C150: =AN150 -> 1.35 | D150: =B150-C150 -> 4.82 | E150: =IF(AH150<>0,ROUNDUP(AH150,0),IF(BB150<>"FR","hors France",IF(AH150<>0,ROUNDUP(AH150,0),_xlfn.XLOOKUP(AJ150,'PA GLS'!B:B,'PA GLS'!A:A)))) -> 0.5 | F150: 2501382993 | G150: 1030232655 | H150: 30.06.2026 | I150: 2500034092 | J150: LA RUCHE LOGISTIQUE | K150: 9000009190 | L150: 46946 | M150: LA RUCHE | N150: 9000037814 | O150: LA RUCHE | S150: 2507012387 | T150: LA RUCHE LOGISTIQUE | U150: FDS | V150: PARCEL_D01_S02 | W150: Business Parcel - Dis. 01 - Size 02 | X150: PARCEDOMESSTANDARD | Z150: 145 | AA150: 04.06.2026 | AB150: 00KUR5UI | AC150: 2604000036 | AE150: 0 | AF150: 0 | AG150: 0 | AH150: 0 | AI150: KG | AJ150: 3.77 | AK150: 0.9 | AL150: 0.15 | AM150: 29.1 | AN150: 1.35 | AO150: 0 | AP150: 0 | AQ150: EUR | AS150: EXP20260603-2779680- | AT150: EXP20260603-2779680- | AU150: 00KUR5UI | AV150: OGEZ MAXIME | AW150: 39, RUE DU LEVANT | AZ150: 34830 | BA150: JACOU | BB150: FR | BC150: France
A151: =IF(COUNTIF(Catégories!A:A,X151)=0,"catégorie inconnue",_xlfn.XLOOKUP(X151,Catégories!A:A,Catégories!B:B)) -> Frêt | B151: =SUM(AJ151:AL151)+SUM(AN151:AP151) -> 6.6 | C151: =AN151 -> 1.45 | D151: =B151-C151 -> 5.15 | E151: =IF(AH151<>0,ROUNDUP(AH151,0),IF(BB151<>"FR","hors France",IF(AH151<>0,ROUNDUP(AH151,0),_xlfn.XLOOKUP(AJ151,'PA GLS'!B:B,'PA GLS'!A:A)))) -> 1 | F151: 2501382993 | G151: 1030232655 | H151: 30.06.2026 | I151: 2500034092 | J151: LA RUCHE LOGISTIQUE | K151: 9000009190 | L151: 46946 | M151: LA RUCHE | N151: 9000037814 | O151: LA RUCHE | S151: 2507012387 | T151: LA RUCHE LOGISTIQUE | U151: FDS | V151: PARCEL_D01_S03 | W151: Business Parcel - Dis. 01 - Size 03 | X151: PARCEDOMESSTANDARD | Z151: 146 | AA151: 04.06.2026 | AB151: 00KUR5UH | AC151: 2604000035 | AE151: 0 | AF151: 0 | AG151: 0 | AH151: 0 | AI151: KG | AJ151: 4.1 | AK151: 0.9 | AL151: 0.15 | AM151: 29.1 | AN151: 1.45 | AO151: 0 | AP151: 0 | AQ151: EUR | AS151: EXP20260603-2779498- | AT151: EXP20260603-2779498- | AU151: 00KUR5UH | AV151: MESNARD RAYAN | AW151: 6 RUE DE LA HOLLANDE | AZ151: 49300 | BA151: CHOLET | BB151: FR | BC151: France
A152: =IF(COUNTIF(Catégories!A:A,X152)=0,"catégorie inconnue",_xlfn.XLOOKUP(X152,Catégories!A:A,Catégories!B:B)) -> Frêt - avisé | B152: =SUM(AJ152:AL152)+SUM(AN152:AP152) -> 0 | C152: =AN152 -> 0 | D152: =B152-C152 -> 0 | E152: =IF(AH152<>0,ROUNDUP(AH152,0),IF(BB152<>"FR","hors France",IF(AH152<>0,ROUNDUP(AH152,0),_xlfn.XLOOKUP(AJ152,'PA GLS'!B:B,'PA GLS'!A:A)))) -> #N/A | F152: 2501382993 | G152: 1030232655 | H152: 30.06.2026 | I152: 2500034092 | J152: LA RUCHE LOGISTIQUE | K152: 9000009190 | L152: 46946 | M152: LA RUCHE | N152: 9000037814 | O152: LA RUCHE | S152: 2507012387 | T152: LA RUCHE LOGISTIQUE | U152: FDS | V152: SUR_FS_AVIS_01 | W152: AvisÃ© FDS | X152: SURCHALL | Z152: 147 | AA152: 04.06.2026 | AB152: 00KUR5U2 | AC152: 2604000020 | AE152: 0 | AF152: 0 | AG152: 0 | AH152: 0 | AI152: KG | AJ152: 0 | AK152: 0 | AL152: 0 | AM152: 0 | AN152: 0 | AO152: 0 | AP152: 0 | AQ152: EUR | AS152: EXP20260529-2770258- | AT152: EXP20260529-2770258- | AU152: 00KUR5U2 | AV152: DOUCE CANDICE | AW152: 475 RUE PARADIS | AZ152: 13008 | BA152: MARSEILLE | BB152: FR | BC152: France
A153: =IF(COUNTIF(Catégories!A:A,X153)=0,"catégorie inconnue",_xlfn.XLOOKUP(X153,Catégories!A:A,Catégories!B:B)) -> Frêt | B153: =SUM(AJ153:AL153)+SUM(AN153:AP153) -> 7.01 | C153: =AN153 -> 1.54 | D153: =B153-C153 -> 5.47 | E153: =IF(AH153<>0,ROUNDUP(AH153,0),IF(BB153<>"FR","hors France",IF(AH153<>0,ROUNDUP(AH153,0),_xlfn.XLOOKUP(AJ153,'PA GLS'!B:B,'PA GLS'!A:A)))) -> 2 | F153: 2501382993 | G153: 1030230693 | H153: 30.06.2026 | I153: 2500034092 | J153: LA RUCHE LOGISTIQUE | K153: 9000009190 | L153: 46946 | M153: LA RUCHE | N153: 9000079830 | O153: BY FOUTAS | S153: 2507012387 | T153: LA RUCHE LOGISTIQUE | U153: FDS | V153: PARCEL_D01_S06 | W153: Business Parcel - Dis. 01 - Size 06 | X153: PARCEDOMESSTANDARD | Z153: 115 | AA153: 04.06.2026 | AB153: 00KZZJUF | AC153: 2604000066 | AE153: 0 | AF153: 0 | AG153: 0 | AH153: 0 | AI153: KG | AJ153: 4.42 | AK153: 0.9 | AL153: 0.15 | AM153: 29.1 | AN153: 1.54 | AO153: 0 | AP153: 0 | AQ153: EUR | AS153: EXP20260604-2779957- | AT153: EXP20260604-2779957- | AU153: 00KZZJUF | AV153: BENCHEIKH NAJAT | AW153: 33 RUE DES BERGERES | AZ153: 91940 | BA153: LES ULIS | BB153: FR | BC153: France
... A193: =IF(COUNTIF(Catégories!A:A,X193)=0,"catégorie inconnue",_xlfn.XLOOKUP(X193,Catégories!A:A,Catégories!B:B)) -> Frêt - avisé | B193: =SUM(AJ193:AL193)+SUM(AN193:AP193) -> 0 | C193: =AN193 -> 0 | D193: =B193-C193 -> 0 | E193: =IF(AH193<>0,ROUNDUP(AH193,0),IF(BB193<>"FR","hors France",IF(AH193<>0,ROUNDUP(AH193,0),_xlfn.XLOOKUP(AJ193,'PA GLS'!B:B,'PA GLS'!A:A)))) -> #N/A | F193: 2501382993 | G193: 1030234353 | H193: 30.06.2026 | I193: 2500034092 | J193: LA RUCHE LOGISTIQUE | K193: 9000009190 | L193: 46946 | M193: LA RUCHE | N193: 9000079830 | O193: BY FOUTAS | S193: 2507012387 | T193: LA RUCHE LOGISTIQUE | U193: FDS | V193: SUR_FS_AVIS_02 | W193: AvisÃ© FDS 2eme passage | X193: SURCHALL | Z193: 197 | AA193: 08.06.2026 | AB193: 00KZZJTM | AC193: 2604000037 | AE193: 0 | AF193: 0 | AG193: 0 | AH193: 0 | AI193: KG | AJ193: 0 | AK193: 0 | AL193: 0 | AM193: 0 | AN193: 0 | AO193: 0 | AP193: 0 | AQ193: EUR | AS193: EXP20260530-2771657- | AT193: EXP20260530-2771657- | AU193: 00KZZJTM | AV193: HARTMANN CHARLOTTE | AW193: 222 CHEMIN DENTABOR | AZ193: 31450 | BA193: BAZIEGE | BB193: FR | BC193: France
A194: =IF(COUNTIF(Catégories!A:A,X194)=0,"catégorie inconnue",_xlfn.XLOOKUP(X194,Catégories!A:A,Catégories!B:B)) -> Frêt | B194: =SUM(AJ194:AL194)+SUM(AN194:AP194) -> 0 | C194: =AN194 -> 0 | D194: =B194-C194 -> 0 | E194: =IF(AH194<>0,ROUNDUP(AH194,0),IF(BB194<>"FR","hors France",IF(AH194<>0,ROUNDUP(AH194,0),_xlfn.XLOOKUP(AJ194,'PA GLS'!B:B,'PA GLS'!A:A)))) -> 2 | F194: 2501382993 | G194: 1030234552 | H194: 30.06.2026 | I194: 2500034092 | J194: LA RUCHE LOGISTIQUE | K194: 9000009190 | L194: 46946 | M194: LA RUCHE | N194: 9000084611 | O194: HARMANDI | S194: 2507012387 | T194: LA RUCHE LOGISTIQUE | U194: FDS | V194: FDS_D01_S01 | W194: BP FlexDelivery - Dis. 01 - Size 01 | X194: PARCEDOMESFDS | Z194: 198 | AA194: 08.06.2026 | AB194: 00L0SRL4 | AC194: 6761431 | AE194: 0 | AF194: 1 | AG194: 0 | AH194: 1.02 | AI194: KG | AJ194: 0 | AK194: 0 | AL194: 0 | AM194: 0 | AN194: 0 | AO194: 0 | AP194: 0 | AQ194: EUR | AS194: EXP20260607-2784982 | AU194: 00L0SRL4 | AV194: MAZZOLENI SANDRA | AW194: 354 ROUTE DES PRES COMMUNAUX | AZ194: 73110 | BA194: ROTHERENS | BB194: FR | BC194: France
A195: =IF(COUNTIF(Catégories!A:A,X195)=0,"catégorie inconnue",_xlfn.XLOOKUP(X195,Catégories!A:A,Catégories!B:B)) -> Frêt | B195: =SUM(AJ195:AL195)+SUM(AN195:AP195) -> 7.01 | C195: =AN195 -> 1.54 | D195: =B195-C195 -> 5.47 | E195: =IF(AH195<>0,ROUNDUP(AH195,0),IF(BB195<>"FR","hors France",IF(AH195<>0,ROUNDUP(AH195,0),_xlfn.XLOOKUP(AJ195,'PA GLS'!B:B,'PA GLS'!A:A)))) -> 2 | F195: 2501382993 | G195: 1030234552 | H195: 30.06.2026 | I195: 2500034092 | J195: LA RUCHE LOGISTIQUE | K195: 9000009190 | L195: 46946 | M195: LA RUCHE | N195: 9000084611 | O195: HARMANDI | S195: 2507012387 | T195: LA RUCHE LOGISTIQUE | U195: FDS | V195: PARCEL_D01_S05 | W195: Business Parcel - Dis. 01 - Size 05 | X195: PARCEDOMESSTANDARD | Z195: 199 | AA195: 08.06.2026 | AB195: 00L0SRL4 | AC195: 6761431 | AE195: 0 | AF195: 0 | AG195: 0 | AH195: 0 | AI195: KG | AJ195: 4.42 | AK195: 0.9 | AL195: 0.15 | AM195: 29.1 | AN195: 1.54 | AO195: 0 | AP195: 0 | AQ195: EUR | AS195: EXP20260607-2784982 | AU195: 00L0SRL4 | AV195: MAZZOLENI SANDRA | AW195: 354 ROUTE DES PRES COMMUNAUX | AZ195: 73110 | BA195: ROTHERENS | BB195: FR | BC195: France
A196: =IF(COUNTIF(Catégories!A:A,X196)=0,"catégorie inconnue",_xlfn.XLOOKUP(X196,Catégories!A:A,Catégories!B:B)) -> Frêt | B196: =SUM(AJ196:AL196)+SUM(AN196:AP196) -> 9.6 | C196: =AN196 -> 2.13 | D196: =B196-C196 -> 7.47 | E196: =IF(AH196<>0,ROUNDUP(AH196,0),IF(BB196<>"FR","hors France",IF(AH196<>0,ROUNDUP(AH196,0),_xlfn.XLOOKUP(AJ196,'PA GLS'!B:B,'PA GLS'!A:A)))) -> 6 | F196: 2501382993 | G196: 1030234353 | H196: 30.06.2026 | I196: 2500034092 | J196: LA RUCHE LOGISTIQUE | K196: 9000009190 | L196: 46946 | M196: LA RUCHE | N196: 9000079830 | O196: BY FOUTAS | S196: 2507012387 | T196: LA RUCHE LOGISTIQUE | U196: FDS | V196: PARCEL_D01_S10 | W196: Business Parcel - Dis. 01 - Size 10 | X196: PARCEDOMESSTANDARD | Z196: 196 | AA196: 08.06.2026 | AB196: 00KZZJUQ | AC196: 2604000077 | AE196: 0 | AF196: 0 | AG196: 0 | AH196: 0 | AI196: KG | AJ196: 6.42 | AK196: 0.9 | AL196: 0.15 | AM196: 29.1 | AN196: 2.13 | AO196: 0 | AP196: 0 | AQ196: EUR | AS196: EXP20260606-2783929- | AT196: EXP20260606-2783929- | AU196: 00KZZJUQ | AV196: DRAY CANDICE | AW196: 4 RUE DE LA COURONNE | AZ196: 30000 | BA196: NIMES | BB196: FR | BC196: France
A197: =IF(COUNTIF(Catégories!A:A,X197)=0,"catégorie inconnue",_xlfn.XLOOKUP(X197,Catégories!A:A,Catégories!B:B)) -> Frêt | B197: =SUM(AJ197:AL197)+SUM(AN197:AP197) -> 0 | C197: =AN197 -> 0 | D197: =B197-C197 -> 0 | E197: =IF(AH197<>0,ROUNDUP(AH197,0),IF(BB197<>"FR","hors France",IF(AH197<>0,ROUNDUP(AH197,0),_xlfn.XLOOKUP(AJ197,'PA GLS'!B:B,'PA GLS'!A:A)))) -> 6 | F197: 2501382993 | G197: 1030234353 | H197: 30.06.2026 | I197: 2500034092 | J197: LA RUCHE LOGISTIQUE | K197: 9000009190 | L197: 46946 | M197: LA RUCHE | N197: 9000079830 | O197: BY FOUTAS | S197: 2507012387 | T197: LA RUCHE LOGISTIQUE | U197: FDS | V197: FDS_D01_S01 | W197: BP FlexDelivery - Dis. 01 - Size 01 | X197: PARCEDOMESFDS | Z197: 195 | AA197: 08.06.2026 | AB197: 00KZZJUQ | AC197: 2604000077 | AE197: 0 | AF197: 1 | AG197: 0 | AH197: 5.44 | AI197: KG | AJ197: 0 | AK197: 0 | AL197: 0 | AM197: 0 | AN197: 0 | AO197: 0 | AP197: 0 | AQ197: EUR | AS197: EXP20260606-2783929- | AT197: EXP20260606-2783929- | AU197: 00KZZJUQ | AV197: DRAY CANDICE | AW197: 4 RUE DE LA COURONNE | AZ197: 30000 | BA197: NIMES | BB197: FR | BC197: France
A198: =IF(COUNTIF(Catégories!A:A,X198)=0,"catégorie inconnue",_xlfn.XLOOKUP(X198,Catégories!A:A,Catégories!B:B)) -> Frêt | B198: =SUM(AJ198:AL198)+SUM(AN198:AP198) -> 6.6 | C198: =AN198 -> 1.45 | D198: =B198-C198 -> 5.15 | E198: =IF(AH198<>0,ROUNDUP(AH198,0),IF(BB198<>"FR","hors France",IF(AH198<>0,ROUNDUP(AH198,0),_xlfn.XLOOKUP(AJ198,'PA GLS'!B:B,'PA GLS'!A:A)))) -> 1 | F198: 2501382993 | G198: 1030233969 | H198: 30.06.2026 | I198: 2500034092 | J198: LA RUCHE LOGISTIQUE | K198: 9000009190 | L198: 46946 | M198: LA RUCHE | N198: 9000037814 | O198: LA RUCHE | S198: 2507012387 | T198: LA RUCHE LOGISTIQUE | U198: FDS | V198: PARCEL_D01_S03 | W198: Business Parcel - Dis. 01 - Size 03 | X198: PARCEDOMESSTANDARD | Z198: 191 | AA198: 08.06.2026 | AB198: 00KUR5UQ | AC198: 2604000044 | AE198: 0 | AF198: 0 | AG198: 0 | AH198: 0 | AI198: KG | AJ198: 4.1 | AK198: 0.9 | AL198: 0.15 | AM198: 29.1 | AN198: 1.45 | AO198: 0 | AP198: 0 | AQ198: EUR | AS198: EXP20260605-2783071- | AT198: EXP20260605-2783071- | AU198: 00KUR5UQ | AV198: CONGI MELISSA | AW198: 12 RUE TRUFFAUT | AZ198: 75017 | BA198: PARIS | BB198: FR | BC198: France
A199: =IF(COUNTIF(Catégories!A:A,X199)=0,"catégorie inconnue",_xlfn.XLOOKUP(X199,Catégories!A:A,Catégories!B:B)) -> Frêt | B199: =SUM(AJ199:AL199)+SUM(AN199:AP199) -> 6.17 | C199: =AN199 -> 1.35 | D199: =B199-C199 -> 4.82 | E199: =IF(AH199<>0,ROUNDUP(AH199,0),IF(BB199<>"FR","hors France",IF(AH199<>0,ROUNDUP(AH199,0),_xlfn.XLOOKUP(AJ199,'PA GLS'!B:B,'PA GLS'!A:A)))) -> 0.5 | F199: 2501382993 | G199: 1030233969 | H199: 30.06.2026 | I199: 2500034092 | J199: LA RUCHE LOGISTIQUE | K199: 9000009190 | L199: 46946 | M199: LA RUCHE | N199: 9000037814 | O199: LA RUCHE | S199: 2507012387 | T199: LA RUCHE LOGISTIQUE | U199: FDS | V199: PARCEL_D01_S02 | W199: Business Parcel - Dis. 01 - Size 02 | X199: PARCEDOMESSTANDARD | Z199: 190 | AA199: 08.06.2026 | AB199: 00KUR5UR | AC199: 2604000045 | AE199: 0 | AF199: 0 | AG199: 0 | AH199: 0 | AI199: KG | AJ199: 3.77 | AK199: 0.9 | AL199: 0.15 | AM199: 29.1 | AN199: 1.35 | AO199: 0 | AP199: 0 | AQ199: EUR | AS199: EXP20260605-2783070- | AT199: EXP20260605-2783070- | AU199: 00KUR5UR | AV199: COIGNARD JADE | AW199: 21 RUE REAUMUR | AZ199: 75003 | BA199: PARIS | BB199: FR | BC199: France
A200: =IF(COUNTIF(Catégories!A:A,X200)=0,"catégorie inconnue",_xlfn.XLOOKUP(X200,Catégories!A:A,Catégories!B:B)) -> Frêt | B200: =SUM(AJ200:AL200)+SUM(AN200:AP200) -> 0 | C200: =AN200 -> 0 | D200: =B200-C200 -> 0 | E200: =IF(AH200<>0,ROUNDUP(AH200,0),IF(BB200<>"FR","hors France",IF(AH200<>0,ROUNDUP(AH200,0),_xlfn.XLOOKUP(AJ200,'PA GLS'!B:B,'PA GLS'!A:A)))) -> 1 | F200: 2501382993 | G200: 1030233969 | H200: 30.06.2026 | I200: 2500034092 | J200: LA RUCHE LOGISTIQUE | K200: 9000009190 | L200: 46946 | M200: LA RUCHE | N200: 9000037814 | O200: LA RUCHE | S200: 2507012387 | T200: LA RUCHE LOGISTIQUE | U200: FDS | V200: FDS_D01_S01 | W200: BP FlexDelivery - Dis. 01 - Size 01 | X200: PARCEDOMESFDS | Z200: 189 | AA200: 08.06.2026 | AB200: 00KUR5UR | AC200: 2604000045 | AE200: 0 | AF200: 1 | AG200: 0 | AH200: 0.3 | AI200: KG | AJ200: 0 | AK200: 0 | AL200: 0 | AM200: 0 | AN200: 0 | AO200: 0 | AP200: 0 | AQ200: EUR | AS200: EXP20260605-2783070- | AT200: EXP20260605-2783070- | AU200: 00KUR5UR | AV200: COIGNARD JADE | AW200: 21 RUE REAUMUR | AZ200: 75003 | BA200: PARIS | BB200: FR | BC200: France
A201: =IF(COUNTIF(Catégories!A:A,X201)=0,"catégorie inconnue",_xlfn.XLOOKUP(X201,Catégories!A:A,Catégories!B:B)) -> Frêt | B201: =SUM(AJ201:AL201)+SUM(AN201:AP201) -> 0 | C201: =AN201 -> 0 | D201: =B201-C201 -> 0 | E201: =IF(AH201<>0,ROUNDUP(AH201,0),IF(BB201<>"FR","hors France",IF(AH201<>0,ROUNDUP(AH201,0),_xlfn.XLOOKUP(AJ201,'PA GLS'!B:B,'PA GLS'!A:A)))) -> 1 | F201: 2501382993 | G201: 1030233969 | H201: 30.06.2026 | I201: 2500034092 | J201: LA RUCHE LOGISTIQUE | K201: 9000009190 | L201: 46946 | M201: LA RUCHE | N201: 9000037814 | O201: LA RUCHE | S201: 2507012387 | T201: LA RUCHE LOGISTIQUE | U201: FDS | V201: FDS_D01_S01 | W201: BP FlexDelivery - Dis. 01 - Size 01 | X201: PARCEDOMESFDS | Z201: 189 | AA201: 08.06.2026 | AB201: 00KUR5UQ | AC201: 2604000044 | AE201: 0 | AF201: 1 | AG201: 0 | AH201: 0.52 | AI201: KG | AJ201: 0 | AK201: 0 | AL201: 0 | AM201: 0 | AN201: 0 | AO201: 0 | AP201: 0 | AQ201: EUR | AS201: EXP20260605-2783071- | AT201: EXP20260605-2783071- | AU201: 00KUR5UQ | AV201: CONGI MELISSA | AW201: 12 RUE TRUFFAUT | AZ201: 75017 | BA201: PARIS | BB201: FR | BC201: France
...

Sheet TCD
D1: Nom compte exploit. | E1: (Tous) | P1: Total | Q1: =SUM('Facture GLS'!B:B) -> 3069.2 | R1: HT | S1: =Q1*1.2 -> 3683.04 | T1: TTC
A2: Total GO | B2: Total | C2: ID clients | O2: tracking | P2: Gazole | Q2: =SUM('Facture GLS'!AN:AN) -> 669.88 | R2: =Q2/Q3 -> 0.27919577
A3: =B3*(1+$R$2) -> 0 | B3: =SUM(E3:L3) -> 0 | D3: Somme de Total HT (hors gazole) | E3: Catégorie | P3: Hors gazole | Q3: =Q1-Q2 -> 2399.32
A4: =B4*(1+$R$2) -> 0 | B4: =SUM(E4:L4) -> 0 | D4: NumÃ©ro de colis | E4: Adresse | F4: Colis volumineux | G4: Frais de gestion | H4: Frêt | I4: Frêt - avisé | J4: Frêt - retour | K4: Zone éloignée | L4: ZZ_Ramasse unicolis | M4: (vide)
A5: =B5*(1+$R$2) -> 0 | B5: =SUM(E5:L5) -> 0 | D5: 00KUR5TU | I5: 0 | N5: =D5&"R" -> 00KUR5TUR | P5: Taux gazole | Q5: 45689 | R5: 0.309
A6: =B6*(1+$R$2) -> 6.1657236 | B6: =SUM(E6:L6) -> 4.82 | D6: 00KUR5TX | H6: 4.82 | N6: =D6&"R" -> 00KUR5TXR
A7: =B7*(1+$R$2) -> 6.1657236 | B7: =SUM(E7:L7) -> 4.82 | D7: 00KUR5TY | H7: 4.82 | N7: =D7&"R" -> 00KUR5TYR | P7: Fichier import | Q7: =SUM('Import csv'!P:V) -> 2365.61
A8: =B8*(1+$R$2) -> 6.1657236 | B8: =SUM(E8:L8) -> 4.82 | D8: 00KUR5TZ | H8: 4.82 | N8: =D8&"R" -> 00KUR5TZR | P8: Ecart | Q8: =Q3-Q7 -> 33.71 | R8: Frais de gestion ok | T8: 45992
A9: =B9*(1+$R$2) -> 6.1657236 | B9: =SUM(E9:L9) -> 4.82 | D9: 00KUR5U0 | H9: 4.82 | N9: =D9&"R" -> 00KUR5U0R
A10: =B10*(1+$R$2) -> 11.832561 | B10: =SUM(E10:L10) -> 9.25 | D10: 00KUR5U1 | H10: 5.15 | J10: 4.1 | N10: =D10&"R" -> 00KUR5U1R
A11: =B11*(1+$R$2) -> 10.988292 | B11: =SUM(E11:L11) -> 8.59 | D11: 00KUR5U2 | H11: 4.82 | I11: 0 | J11: 3.77 | N11: =D11&"R" -> 00KUR5U2R
A12: =B12*(1+$R$2) -> 6.1657236 | B12: =SUM(E12:L12) -> 4.82 | D12: 00KUR5U3 | H12: 4.82 | N12: =D12&"R" -> 00KUR5U3R
A13: =B13*(1+$R$2) -> 6.5878582 | B13: =SUM(E13:L13) -> 5.15 | D13: 00KUR5U4 | H13: 5.15 | N13: =D13&"R" -> 00KUR5U4R
A14: =B14*(1+$R$2) -> 6.5878582 | B14: =SUM(E14:L14) -> 5.15 | D14: 00KUR5U5 | H14: 5.15 | N14: =D14&"R" -> 00KUR5U5R
A15: =B15*(1+$R$2) -> 6.5878582 | B15: =SUM(E15:L15) -> 5.15 | D15: 00KUR5U6 | H15: 5.15 | N15: =D15&"R" -> 00KUR5U6R
A16: =B16*(1+$R$2) -> 6.1657236 | B16: =SUM(E16:L16) -> 4.82 | D16: 00KUR5U7 | H16: 4.82 | N16: =D16&"R" -> 00KUR5U7R
A17: =B17*(1+$R$2) -> 6.5878582 | B17: =SUM(E17:L17) -> 5.15 | D17: 00KUR5U8 | H17: 5.15 | N17: =D17&"R" -> 00KUR5U8R
A18: =B18*(1+$R$2) -> 6.1657236 | B18: =SUM(E18:L18) -> 4.82 | D18: 00KUR5U9 | H18: 4.82 | N18: =D18&"R" -> 00KUR5U9R
A19: =B19*(1+$R$2) -> 6.5878582 | B19: =SUM(E19:L19) -> 5.15 | D19: 00KUR5UA | H19: 5.15 | N19: =D19&"R" -> 00KUR5UAR
A20: =B20*(1+$R$2) -> 6.5878582 | B20: =SUM(E20:L20) -> 5.15 | D20: 00KUR5UB | H20: 5.15 | N20: =D20&"R" -> 00KUR5UBR
A21: =B21*(1+$R$2) -> 6.1657236 | B21: =SUM(E21:L21) -> 4.82 | D21: 00KUR5UC | H21: 4.82 | N21: =D21&"R" -> 00KUR5UCR
A22: =B22*(1+$R$2) -> 6.1657236 | B22: =SUM(E22:L22) -> 4.82 | D22: 00KUR5UD | H22: 4.82 | N22: =D22&"R" -> 00KUR5UDR
A23: =B23*(1+$R$2) -> 7.4065435 | B23: =SUM(E23:L23) -> 5.79 | D23: 00KUR5UE | H23: 5.79 | N23: =D23&"R" -> 00KUR5UER
... A37: =B37*(1+$R$2) -> 6.1657236 | B37: =SUM(E37:L37) -> 4.82 | D37: 00KUR5US | H37: 4.82 | N37: =D37&"R" -> 00KUR5USR
A38: =B38*(1+$R$2) -> 12.651246 | B38: =SUM(E38:L38) -> 9.89 | D38: 00KUR5UT | H38: 5.47 | J38: 4.42 | N38: =D38&"R" -> 00KUR5UTR
A39: =B39*(1+$R$2) -> 6.5878582 | B39: =SUM(E39:L39) -> 5.15 | D39: 00KUR5UU | H39: 5.15 | N39: =D39&"R" -> 00KUR5UUR
A40: =B40*(1+$R$2) -> 8.8392428 | B40: =SUM(E40:L40) -> 6.91 | D40: 00KUR5UV | H40: 6.91 | N40: =D40&"R" -> 00KUR5UVR
A41: =B41*(1+$R$2) -> 6.1657236 | B41: =SUM(E41:L41) -> 4.82 | D41: 00KUR5UW | H41: 4.82 | N41: =D41&"R" -> 00KUR5UWR
A42: =B42*(1+$R$2) -> 6.9972009 | B42: =SUM(E42:L42) -> 5.47 | D42: 00KUR5UX | H42: 5.47 | N42: =D42&"R" -> 00KUR5UXR
A43: =B43*(1+$R$2) -> 6.5878582 | B43: =SUM(E43:L43) -> 5.15 | D43: 00KUR5UY | H43: 5.15 | N43: =D43&"R" -> 00KUR5UYR
A44: =B44*(1+$R$2) -> 6.1657236 | B44: =SUM(E44:L44) -> 4.82 | D44: 00KUR5UZ | H44: 4.82 | N44: =D44&"R" -> 00KUR5UZR
A45: =B45*(1+$R$2) -> 6.5878582 | B45: =SUM(E45:L45) -> 5.15 | D45: 00KUR5V0 | H45: 5.15 | N45: =D45&"R" -> 00KUR5V0R
A46: =B46*(1+$R$2) -> 6.1657236 | B46: =SUM(E46:L46) -> 4.82 | D46: 00KUR5V1 | H46: 4.82 | N46: =D46&"R" -> 00KUR5V1R
A47: =B47*(1+$R$2) -> 6.1657236 | B47: =SUM(E47:L47) -> 4.82 | D47: 00KUR5V2 | H47: 4.82 | N47: =D47&"R" -> 00KUR5V2R
A48: =B48*(1+$R$2) -> 8.1228932 | B48: =SUM(E48:L48) -> 6.35 | D48: 00KUR5V3 | H48: 6.35 | N48: =D48&"R" -> 00KUR5V3R
A49: =B49*(1+$R$2) -> 6.5878582 | B49: =SUM(E49:L49) -> 5.15 | D49: 00KUR5V4 | H49: 5.15 | N49: =D49&"R" -> 00KUR5V4R
A50: =B50*(1+$R$2) -> 6.5878582 | B50: =SUM(E50:L50) -> 5.15 | D50: 00KUR5V5 | H50: 5.15 | N50: =D50&"R" -> 00KUR5V5R
A51: =B51*(1+$R$2) -> 6.1657236 | B51: =SUM(E51:L51) -> 4.82 | D51: 00KUR5V6 | H51: 4.82 | N51: =D51&"R" -> 00KUR5V6R
A52: =B52*(1+$R$2) -> 10.016103 | B52: =SUM(E52:L52) -> 7.83 | D52: 00KUR5V7 | E52: 2.36 | H52: 5.47 | I52: 0 | N52: =D52&"R" -> 00KUR5V7R
A53: =B53*(1+$R$2) -> 6.5878582 | B53: =SUM(E53:L53) -> 5.15 | D53: 00KUR5V8 | H53: 5.15 | N53: =D53&"R" -> 00KUR5V8R
A54: =B54*(1+$R$2) -> 6.5878582 | B54: =SUM(E54:L54) -> 5.15 | D54: 00KUR5V9 | H54: 5.15 | N54: =D54&"R" -> 00KUR5V9R
A55: =B55*(1+$R$2) -> 6.5878582 | B55: =SUM(E55:L55) -> 5.15 | D55: 00KUR5VA | H55: 5.15 | N55: =D55&"R" -> 00KUR5VAR
A56: =B56*(1+$R$2) -> 6.9972009 | B56: =SUM(E56:L56) -> 5.47 | D56: 00KUR5VB | H56: 5.47 | N56: =D56&"R" -> 00KUR5VBR
A57: =B57*(1+$R$2) -> 6.5878582 | B57: =SUM(E57:L57) -> 5.15 | D57: 00KUR5VC | H57: 5.15 | N57: =D57&"R" -> 00KUR5VCR
A58: =B58*(1+$R$2) -> 6.1657236 | B58: =SUM(E58:L58) -> 4.82 | D58: 00KUR5VD | H58: 4.82 | N58: =D58&"R" -> 00KUR5VDR
A59: =B59*(1+$R$2) -> 6.1657236 | B59: =SUM(E59:L59) -> 4.82 | D59: 00KUR5VE | H59: 4.82 | N59: =D59&"R" -> 00KUR5VER
A60: =B60*(1+$R$2) -> 6.5878582 | B60: =SUM(E60:L60) -> 5.15 | D60: 00KUR5VF | H60: 5.15 | N60: =D60&"R" -> 00KUR5VFR
A61: =B61*(1+$R$2) -> 6.1657236 | B61: =SUM(E61:L61) -> 4.82 | D61: 00KUR5VG | H61: 4.82 | N61: =D61&"R" -> 00KUR5VGR
A62: =B62*(1+$R$2) -> 6.9972009 | B62: =SUM(E62:L62) -> 5.47 | D62: 00KUR5VH | H62: 5.47 | N62: =D62&"R" -> 00KUR5VHR
A63: =B63*(1+$R$2) -> 6.1657236 | B63: =SUM(E63:L63) -> 4.82 | D63: 00KUR5VI | H63: 4.82 | N63: =D63&"R" -> 00KUR5VIR
A64: =B64*(1+$R$2) -> 6.1657236 | B64: =SUM(E64:L64) -> 4.82 | D64: 00KUR5VJ | H64: 4.82 | N64: =D64&"R" -> 00KUR5VJR
... A76: =B76*(1+$R$2) -> 6.1657236 | B76: =SUM(E76:L76) -> 4.82 | D76: 00KUR5VV | H76: 4.82 | N76: =D76&"R" -> 00KUR5VVR
A77: =B77*(1+$R$2) -> 10.425446 | B77: =SUM(E77:L77) -> 8.15 | D77: 00KUR5VW | E77: 2.36 | H77: 5.79 | I77: 0 | N77: =D77&"R" -> 00KUR5VWR
A78: =B78*(1+$R$2) -> 6.5878582 | B78: =SUM(E78:L78) -> 5.15 | D78: 00KUR5VX | H78: 5.15 | N78: =D78&"R" -> 00KUR5VXR
A79: =B79*(1+$R$2) -> 6.9972009 | B79: =SUM(E79:L79) -> 5.47 | D79: 00KUR5VY | H79: 5.47 | N79: =D79&"R" -> 00KUR5VYR
A80: =B80*(1+$R$2) -> 6.5878582 | B80: =SUM(E80:L80) -> 5.15 | D80: 00KUR5VZ | H80: 5.15 | N80: =D80&"R" -> 00KUR5VZR
A81: =B81*(1+$R$2) -> 6.5878582 | B81: =SUM(E81:L81) -> 5.15 | D81: 00KUR5W0 | H81: 5.15 | N81: =D81&"R" -> 00KUR5W0R
A82: =B82*(1+$R$2) -> 6.1657236 | B82: =SUM(E82:L82) -> 4.82 | D82: 00KUR5W1 | H82: 4.82 | N82: =D82&"R" -> 00KUR5W1R
A83: =B83*(1+$R$2) -> 6.1657236 | B83: =SUM(E83:L83) -> 4.82 | D83: 00KUR5W2 | H83: 4.82 | N83: =D83&"R" -> 00KUR5W2R
A84: =B84*(1+$R$2) -> 6.1657236 | B84: =SUM(E84:L84) -> 4.82 | D84: 00KUR5W3 | H84: 4.82 | N84: =D84&"R" -> 00KUR5W3R
A85: =B85*(1+$R$2) -> 6.1657236 | B85: =SUM(E85:L85) -> 4.82 | D85: 00KUR5W4 | H85: 4.82 | N85: =D85&"R" -> 00KUR5W4R
A86: =B86*(1+$R$2) -> 8.1228932 | B86: =SUM(E86:L86) -> 6.35 | D86: 00KUR5W5 | H86: 6.35 | N86: =D86&"R" -> 00KUR5W5R
A87: =B87*(1+$R$2) -> 6.1657236 | B87: =SUM(E87:L87) -> 4.82 | D87: 00KUR5W6 | H87: 4.82 | N87: =D87&"R" -> 00KUR5W6R
A88: =B88*(1+$R$2) -> 6.5878582 | B88: =SUM(E88:L88) -> 5.15 | D88: 00KUR5W7 | H88: 5.15 | N88: =D88&"R" -> 00KUR5W7R
A89: =B89*(1+$R$2) -> 6.1657236 | B89: =SUM(E89:L89) -> 4.82 | D89: 00KUR5W8 | H89: 4.82 | N89: =D89&"R" -> 00KUR5W8R
... A122: =B122*(1+$R$2) -> 6.1657236 | B122: =SUM(E122:L122) -> 4.82 | D122: 00KUR5X5 | H122: 4.82 | N122: =D122&"R" -> 00KUR5X5R
A123: =B123*(1+$R$2) -> 10.016103 | B123: =SUM(E123:L123) -> 7.83 | D123: 00KUR5X6 | E123: 2.36 | H123: 5.47 | I123: 0 | N123: =D123&"R" -> 00KUR5X6R
A124: =B124*(1+$R$2) -> 6.5878582 | B124: =SUM(E124:L124) -> 5.15 | D124: 00KUR5X7 | H124: 5.15 | N124: =D124&"R" -> 00KUR5X7R
A125: =B125*(1+$R$2) -> 6.1657236 | B125: =SUM(E125:L125) -> 4.82 | D125: 00KUR5X8 | H125: 4.82 | N125: =D125&"R" -> 00KUR5X8R
A126: =B126*(1+$R$2) -> 6.1657236 | B126: =SUM(E126:L126) -> 4.82 | D126: 00KUR5X9 | H126: 4.82 | N126: =D126&"R" -> 00KUR5X9R
A127: =B127*(1+$R$2) -> 6.1657236 | B127: =SUM(E127:L127) -> 4.82 | D127: 00KUR5XA | H127: 4.82 | N127: =D127&"R" -> 00KUR5XAR
A128: =B128*(1+$R$2) -> 6.1657236 | B128: =SUM(E128:L128) -> 4.82 | D128: 00KUR5XB | H128: 4.82 | N128: =D128&"R" -> 00KUR5XBR
A129: =B129*(1+$R$2) -> 5.2447027 | B129: =SUM(E129:L129) -> 4.1 | D129: 00KZ5BVG | J129: 4.1 | N129: =D129&"R" -> 00KZ5BVGR
A130: =B130*(1+$R$2) -> 6.9972009 | B130: =SUM(E130:L130) -> 5.47 | D130: 00KZZJT9 | H130: 5.47 | N130: =D130&"R" -> 00KZZJT9R
A131: =B131*(1+$R$2) -> 6.9972009 | B131: =SUM(E131:L131) -> 5.47 | D131: 00KZZJTA | H131: 5.47 | N131: =D131&"R" -> 00KZZJTAR
A132: =B132*(1+$R$2) -> 6.5878582 | B132: =SUM(E132:L132) -> 5.15 | D132: 00KZZJTB | H132: 5.15 | N132: =D132&"R" -> 00KZZJTBR
A133: =B133*(1+$R$2) -> 6.5878582 | B133: =SUM(E133:L133) -> 5.15 | D133: 00KZZJTC | H133: 5.15 | N133: =D133&"R" -> 00KZZJTCR
A134: =B134*(1+$R$2) -> 7.4065435 | B134: =SUM(E134:L134) -> 5.79 | D134: 00KZZJTD | H134: 5.79 | N134: =D134&"R" -> 00KZZJTDR
A135: =B135*(1+$R$2) -> 6.1657236 | B135: =SUM(E135:L135) -> 4.82 | D135: 00KZZJTE | H135: 4.82 | N135: =D135&"R" -> 00KZZJTER
A136: =B136*(1+$R$2) -> 7.4065435 | B136: =SUM(E136:L136) -> 5.79 | D136: 00KZZJTF | H136: 5.79 | N136: =D136&"R" -> 00KZZJTFR
A137: =B137*(1+$R$2) -> 12.651246 | B137: =SUM(E137:L137) -> 9.89 | D137: 00KZZJTG | H137: 5.47 | J137: 4.42 | N137: =D137&"R" -> 00KZZJTGR
A138: =B138*(1+$R$2) -> 6.9972009 | B138: =SUM(E138:L138) -> 5.47 | D138: 00KZZJTH | H138: 5.47 | N138: =D138&"R" -> 00KZZJTHR
A139: =B139*(1+$R$2) -> 10.016103 | B139: =SUM(E139:L139) -> 7.83 | D139: 00KZZJTI | E139: 2.36 | H139: 5.47 | I139: 0 | N139: =D139&"R" -> 00KZZJTIR
A140: =B140*(1+$R$2) -> 7.4065435 | B140: =SUM(E140:L140) -> 5.79 | D140: 00KZZJTJ | H140: 5.79 | N140: =D140&"R" -> 00KZZJTJR
A141: =B141*(1+$R$2) -> 6.9972009 | B141: =SUM(E141:L141) -> 5.47 | D141: 00KZZJTK | H141: 5.47 | N141: =D141&"R" -> 00KZZJTKR
A142: =B142*(1+$R$2) -> 6.9972009 | B142: =SUM(E142:L142) -> 5.47 | D142: 00KZZJTL | H142: 5.47 | N142: =D142&"R" -> 00KZZJTLR
A143: =B143*(1+$R$2) -> 6.9972009 | B143: =SUM(E143:L143) -> 5.47 | D143: 00KZZJTM | H143: 5.47 | I143: 0 | N143: =D143&"R" -> 00KZZJTMR
A144: =B144*(1+$R$2) -> 6.9972009 | B144: =SUM(E144:L144) -> 5.47 | D144: 00KZZJTN | H144: 5.47 | N144: =D144&"R" -> 00KZZJTNR
A145: =B145*(1+$R$2) -> 6.9972009 | B145: =SUM(E145:L145) -> 5.47 | D145: 00KZZJTO | H145: 5.47 | N145: =D145&"R" -> 00KZZJTOR
A146: =B146*(1+$R$2) -> 6.5878582 | B146: =SUM(E146:L146) -> 5.15 | D146: 00KZZJTP | H146: 5.15 | N146: =D146&"R" -> 00KZZJTPR
A147: =B147*(1+$R$2) -> 6.9972009 | B147: =SUM(E147:L147) -> 5.47 | D147: 00KZZJTQ | H147: 5.47 | N147: =D147&"R" -> 00KZZJTQR
A148: =B148*(1+$R$2) -> 6.9972009 | B148: =SUM(E148:L148) -> 5.47 | D148: 00KZZJTR | H148: 5.47 | N148: =D148&"R" -> 00KZZJTRR
A149: =B149*(1+$R$2) -> 6.1657236 | B149: =SUM(E149:L149) -> 4.82 | D149: 00KZZJTS | H149: 4.82 | N149: =D149&"R" -> 00KZZJTSR
A150: =B150*(1+$R$2) -> 6.9972009 | B150: =SUM(E150:L150) -> 5.47 | D150: 00KZZJTT | H150: 5.47 | N150: =D150&"R" -> 00KZZJTTR
A151: =B151*(1+$R$2) -> 7.4065435 | B151: =SUM(E151:L151) -> 5.79 | D151: 00KZZJTU | H151: 5.79 | N151: =D151&"R" -> 00KZZJTUR
A152: =B152*(1+$R$2) -> 7.4065435 | B152: =SUM(E152:L152) -> 5.79 | D152: 00KZZJTV | H152: 5.79 | N152: =D152&"R" -> 00KZZJTVR
A153: =B153*(1+$R$2) -> 6.9972009 | B153: =SUM(E153:L153) -> 5.47 | D153: 00KZZJTW | H153: 5.47 | N153: =D153&"R" -> 00KZZJTWR
A154: =B154*(1+$R$2) -> 6.1657236 | B154: =SUM(E154:L154) -> 4.82 | D154: 00KZZJTX | H154: 4.82 | N154: =D154&"R" -> 00KZZJTXR
A155: =B155*(1+$R$2) -> 6.1657236 | B155: =SUM(E155:L155) -> 4.82 | D155: 00KZZJTY | H155: 4.82 | N155: =D155&"R" -> 00KZZJTYR
... A168: =B168*(1+$R$2) -> 7.4065435 | B168: =SUM(E168:L168) -> 5.79 | D168: 00KZZJUB | H168: 5.79 | N168: =D168&"R" -> 00KZZJUBR
...

Sheet Import csv
A1: SENEA | B1: Transporteur | C1: Date validité tarif | D1: Réf.1 | E1: Réf. 2 | F1: Id client | G1: N° Tracking | H1: Nom | I1: E / P | J1: Pays | K1: Zone | L1: Nbr Colis | M1: Poids | N1: mode envoi | O1: TVA | P1: Droits et taxes | Q1: Assurance | R1: Zones éloignées | S1: Colis volumineux | T1: Adresses | U1: Frêt | V1: plus-value BtoC | W1: Gazole
A2: =_xlfn.XLOOKUP(G2,'Facture GLS'!AB:AB,'Facture GLS'!O:O) -> #N/A | B2: GLS | C2: 46174 | G2: =TCD!D3 -> Somme de Total HT (hors gazole) | I2: P | J2: =_xlfn.XLOOKUP(G2,'Facture GLS'!AB:AB,'Facture GLS'!BB:BB) -> #N/A | K2: =IF(COUNTIF(Zoning!A:A,J2)=0,"pays inconnu",LOOKUP(J2,Zoning!A:A,Zoning!B:B)) -> pays inconnu | L2: 1 | M2: =_xlfn.XLOOKUP(G2,Poids!A:A,Poids!C:C) -> #N/A | N2: =IF(COUNTIF(Zoning!A:A,J2)=0,"zone inconnue","France") -> zone inconnue | O2: =IF(COUNTIF(Zoning!A:A,J2)=0,"taux inconnu",_xlfn.XLOOKUP(J2,Zoning!A:A,Zoning!C:C)) -> taux inconnu | R2: =IF(TCD!K3="","",TCD!K3) | S2: =IF(TCD!F3="","",TCD!F3) | T2: =IF(TCD!E3="","",TCD!E3) -> Catégorie | U2: =SUM(TCD!H3:J3) -> 0
A3: =_xlfn.XLOOKUP(G3,'Facture GLS'!AB:AB,'Facture GLS'!O:O) -> Nom compte exploit. | B3: =B2 -> GLS | C3: =C2 -> 46174 | G3: =TCD!D4 -> NumÃ©ro de colis | I3: P | J3: =_xlfn.XLOOKUP(G3,'Facture GLS'!AB:AB,'Facture GLS'!BB:BB) -> Code Pays | K3: =IF(COUNTIF(Zoning!A:A,J3)=0,"pays inconnu",LOOKUP(J3,Zoning!A:A,Zoning!B:B)) -> pays inconnu | L3: =L2 -> 1 | M3: =_xlfn.XLOOKUP(G3,Poids!A:A,Poids!C:C) -> #N/A | N3: =IF(COUNTIF(Zoning!A:A,J3)=0,"zone inconnue","France") -> zone inconnue | O3: =IF(COUNTIF(Zoning!A:A,J3)=0,"taux inconnu",_xlfn.XLOOKUP(J3,Zoning!A:A,Zoning!C:C)) -> taux inconnu | R3: =IF(TCD!K4="","",TCD!K4) -> Zone éloignée | S3: =IF(TCD!F4="","",TCD!F4) -> Colis volumineux | T3: =IF(TCD!E4="","",TCD!E4) -> Adresse | U3: =SUM(TCD!H4:J4) -> 0 | W3: RENSEIGNER LES POIDS
A4: =_xlfn.XLOOKUP(G4,'Facture GLS'!AB:AB,'Facture GLS'!O:O) -> LA RUCHE | B4: =B3 -> GLS | C4: =C3 -> 46174 | G4: =TCD!D5 -> 00KUR5TU | I4: P | J4: =_xlfn.XLOOKUP(G4,'Facture GLS'!AB:AB,'Facture GLS'!BB:BB) -> FR | K4: =IF(COUNTIF(Zoning!A:A,J4)=0,"pays inconnu",LOOKUP(J4,Zoning!A:A,Zoning!B:B)) -> France | L4: =L3 -> 1 | M4: =_xlfn.XLOOKUP(G4,Poids!A:A,Poids!C:C) -> 0 | N4: =IF(COUNTIF(Zoning!A:A,J4)=0,"zone inconnue","France") -> France | O4: =IF(COUNTIF(Zoning!A:A,J4)=0,"taux inconnu",_xlfn.XLOOKUP(J4,Zoning!A:A,Zoning!C:C)) -> 0.2 | R4: =IF(TCD!K5="","",TCD!K5) | S4: =IF(TCD!F5="","",TCD!F5) | T4: =IF(TCD!E5="","",TCD!E5) | U4: =SUM(TCD!H5:J5) -> 0
A5: =_xlfn.XLOOKUP(G5,'Facture GLS'!AB:AB,'Facture GLS'!O:O) -> LA RUCHE | B5: =B4 -> GLS | C5: =C4 -> 46174 | G5: =TCD!D6 -> 00KUR5TX | I5: P | J5: =_xlfn.XLOOKUP(G5,'Facture GLS'!AB:AB,'Facture GLS'!BB:BB) -> FR | K5: =IF(COUNTIF(Zoning!A:A,J5)=0,"pays inconnu",LOOKUP(J5,Zoning!A:A,Zoning!B:B)) -> France | L5: =L4 -> 1 | M5: =_xlfn.XLOOKUP(G5,Poids!A:A,Poids!C:C) -> 0.3 | N5: =IF(COUNTIF(Zoning!A:A,J5)=0,"zone inconnue","France") -> France | O5: =IF(COUNTIF(Zoning!A:A,J5)=0,"taux inconnu",_xlfn.XLOOKUP(J5,Zoning!A:A,Zoning!C:C)) -> 0.2 | R5: =IF(TCD!K6="","",TCD!K6) | S5: =IF(TCD!F6="","",TCD!F6) | T5: =IF(TCD!E6="","",TCD!E6) | U5: =SUM(TCD!H6:J6) -> 4.82
A6: =_xlfn.XLOOKUP(G6,'Facture GLS'!AB:AB,'Facture GLS'!O:O) -> LA RUCHE | B6: =B5 -> GLS | C6: =C5 -> 46174 | G6: =TCD!D7 -> 00KUR5TY | I6: P | J6: =_xlfn.XLOOKUP(G6,'Facture GLS'!AB:AB,'Facture GLS'!BB:BB) -> FR | K6: =IF(COUNTIF(Zoning!A:A,J6)=0,"pays inconnu",LOOKUP(J6,Zoning!A:A,Zoning!B:B)) -> France | L6: =L5 -> 1 | M6: =_xlfn.XLOOKUP(G6,Poids!A:A,Poids!C:C) -> 0.3 | N6: =IF(COUNTIF(Zoning!A:A,J6)=0,"zone inconnue","France") -> France | O6: =IF(COUNTIF(Zoning!A:A,J6)=0,"taux inconnu",_xlfn.XLOOKUP(J6,Zoning!A:A,Zoning!C:C)) -> 0.2 | R6: =IF(TCD!K7="","",TCD!K7) | S6: =IF(TCD!F7="","",TCD!F7) | T6: =IF(TCD!E7="","",TCD!E7) | U6: =SUM(TCD!H7:J7) -> 4.82
A7: =_xlfn.XLOOKUP(G7,'Facture GLS'!AB:AB,'Facture GLS'!O:O) -> LA RUCHE | B7: =B6 -> GLS | C7: =C6 -> 46174 | G7: =TCD!D8 -> 00KUR5TZ | I7: P | J7: =_xlfn.XLOOKUP(G7,'Facture GLS'!AB:AB,'Facture GLS'!BB:BB) -> FR | K7: =IF(COUNTIF(Zoning!A:A,J7)=0,"pays inconnu",LOOKUP(J7,Zoning!A:A,Zoning!B:B)) -> France | L7: =L6 -> 1 | M7: =_xlfn.XLOOKUP(G7,Poids!A:A,Poids!C:C) -> 0.3 | N7: =IF(COUNTIF(Zoning!A:A,J7)=0,"zone inconnue","France") -> France | O7: =IF(COUNTIF(Zoning!A:A,J7)=0,"taux inconnu",_xlfn.XLOOKUP(J7,Zoning!A:A,Zoning!C:C)) -> 0.2 | R7: =IF(TCD!K8="","",TCD!K8) | S7: =IF(TCD!F8="","",TCD!F8) | T7: =IF(TCD!E8="","",TCD!E8) | U7: =SUM(TCD!H8:J8) -> 4.82
A8: =_xlfn.XLOOKUP(G8,'Facture GLS'!AB:AB,'Facture GLS'!O:O) -> LA RUCHE | B8: =B7 -> GLS | C8: =C7 -> 46174 | G8: =TCD!D9 -> 00KUR5U0 | I8: P | J8: =_xlfn.XLOOKUP(G8,'Facture GLS'!AB:AB,'Facture GLS'!BB:BB) -> FR | K8: =IF(COUNTIF(Zoning!A:A,J8)=0,"pays inconnu",LOOKUP(J8,Zoning!A:A,Zoning!B:B)) -> France | L8: =L7 -> 1 | M8: =_xlfn.XLOOKUP(G8,Poids!A:A,Poids!C:C) -> 0.3 | N8: =IF(COUNTIF(Zoning!A:A,J8)=0,"zone inconnue","France") -> France | O8: =IF(COUNTIF(Zoning!A:A,J8)=0,"taux inconnu",_xlfn.XLOOKUP(J8,Zoning!A:A,Zoning!C:C)) -> 0.2 | R8: =IF(TCD!K9="","",TCD!K9) | S8: =IF(TCD!F9="","",TCD!F9) | T8: =IF(TCD!E9="","",TCD!E9) | U8: =SUM(TCD!H9:J9) -> 4.82
A9: =_xlfn.XLOOKUP(G9,'Facture GLS'!AB:AB,'Facture GLS'!O:O) -> LA RUCHE | B9: =B8 -> GLS | C9: =C8 -> 46174 | G9: =TCD!D10 -> 00KUR5U1 | I9: P | J9: =_xlfn.XLOOKUP(G9,'Facture GLS'!AB:AB,'Facture GLS'!BB:BB) -> FR | K9: =IF(COUNTIF(Zoning!A:A,J9)=0,"pays inconnu",LOOKUP(J9,Zoning!A:A,Zoning!B:B)) -> France | L9: =L8 -> 1 | M9: =_xlfn.XLOOKUP(G9,Poids!A:A,Poids!C:C) -> 0.6 | N9: =IF(COUNTIF(Zoning!A:A,J9)=0,"zone inconnue","France") -> France | O9: =IF(COUNTIF(Zoning!A:A,J9)=0,"taux inconnu",_xlfn.XLOOKUP(J9,Zoning!A:A,Zoning!C:C)) -> 0.2 | R9: =IF(TCD!K10="","",TCD!K10) | S9: =IF(TCD!F10="","",TCD!F10) | T9: =IF(TCD!E10="","",TCD!E10) | U9: =SUM(TCD!H10:J10) -> 9.25
A10: =_xlfn.XLOOKUP(G10,'Facture GLS'!AB:AB,'Facture GLS'!O:O) -> LA RUCHE | B10: =B9 -> GLS | C10: =C9 -> 46174 | G10: =TCD!D11 -> 00KUR5U2 | I10: P | J10: =_xlfn.XLOOKUP(G10,'Facture GLS'!AB:AB,'Facture GLS'!BB:BB) -> FR | K10: =IF(COUNTIF(Zoning!A:A,J10)=0,"pays inconnu",LOOKUP(J10,Zoning!A:A,Zoning!B:B)) -> France | L10: =L9 -> 1 | M10: =_xlfn.XLOOKUP(G10,Poids!A:A,Poids!C:C) -> 0.3 | N10: =IF(COUNTIF(Zoning!A:A,J10)=0,"zone inconnue","France") -> France | O10: =IF(COUNTIF(Zoning!A:A,J10)=0,"taux inconnu",_xlfn.XLOOKUP(J10,Zoning!A:A,Zoning!C:C)) -> 0.2 | R10: =IF(TCD!K11="","",TCD!K11) | S10: =IF(TCD!F11="","",TCD!F11) | T10: =IF(TCD!E11="","",TCD!E11) | U10: =SUM(TCD!H11:J11) -> 8.59
A11: =_xlfn.XLOOKUP(G11,'Facture GLS'!AB:AB,'Facture GLS'!O:O) -> LA RUCHE | B11: =B10 -> GLS | C11: =C10 -> 46174 | G11: =TCD!D12 -> 00KUR5U3 | I11: P | J11: =_xlfn.XLOOKUP(G11,'Facture GLS'!AB:AB,'Facture GLS'!BB:BB) -> FR | K11: =IF(COUNTIF(Zoning!A:A,J11)=0,"pays inconnu",LOOKUP(J11,Zoning!A:A,Zoning!B:B)) -> France | L11: =L10 -> 1 | M11: =_xlfn.XLOOKUP(G11,Poids!A:A,Poids!C:C) -> 0.3 | N11: =IF(COUNTIF(Zoning!A:A,J11)=0,"zone inconnue","France") -> France | O11: =IF(COUNTIF(Zoning!A:A,J11)=0,"taux inconnu",_xlfn.XLOOKUP(J11,Zoning!A:A,Zoning!C:C)) -> 0.2 | R11: =IF(TCD!K12="","",TCD!K12) | S11: =IF(TCD!F12="","",TCD!F12) | T11: =IF(TCD!E12="","",TCD!E12) | U11: =SUM(TCD!H12:J12) -> 4.82
A12: =_xlfn.XLOOKUP(G12,'Facture GLS'!AB:AB,'Facture GLS'!O:O) -> LA RUCHE | B12: =B11 -> GLS | C12: =C11 -> 46174 | G12: =TCD!D13 -> 00KUR5U4 | I12: P | J12: =_xlfn.XLOOKUP(G12,'Facture GLS'!AB:AB,'Facture GLS'!BB:BB) -> FR | K12: =IF(COUNTIF(Zoning!A:A,J12)=0,"pays inconnu",LOOKUP(J12,Zoning!A:A,Zoning!B:B)) -> France | L12: =L11 -> 1 | M12: =_xlfn.XLOOKUP(G12,Poids!A:A,Poids!C:C) -> 0.6 | N12: =IF(COUNTIF(Zoning!A:A,J12)=0,"zone inconnue","France") -> France | O12: =IF(COUNTIF(Zoning!A:A,J12)=0,"taux inconnu",_xlfn.XLOOKUP(J12,Zoning!A:A,Zoning!C:C)) -> 0.2 | R12: =IF(TCD!K13="","",TCD!K13) | S12: =IF(TCD!F13="","",TCD!F13) | T12: =IF(TCD!E13="","",TCD!E13) | U12: =SUM(TCD!H13:J13) -> 5.15
A13: =_xlfn.XLOOKUP(G13,'Facture GLS'!AB:AB,'Facture GLS'!O:O) -> LA RUCHE | B13: =B12 -> GLS | C13: =C12 -> 46174 | G13: =TCD!D14 -> 00KUR5U5 | I13: P | J13: =_xlfn.XLOOKUP(G13,'Facture GLS'!AB:AB,'Facture GLS'!BB:BB) -> FR | K13: =IF(COUNTIF(Zoning!A:A,J13)=0,"pays inconnu",LOOKUP(J13,Zoning!A:A,Zoning!B:B)) -> France | L13: =L12 -> 1 | M13: =_xlfn.XLOOKUP(G13,Poids!A:A,Poids!C:C) -> 0.6 | N13: =IF(COUNTIF(Zoning!A:A,J13)=0,"zone inconnue","France") -> France | O13: =IF(COUNTIF(Zoning!A:A,J13)=0,"taux inconnu",_xlfn.XLOOKUP(J13,Zoning!A:A,Zoning!C:C)) -> 0.2 | R13: =IF(TCD!K14="","",TCD!K14) | S13: =IF(TCD!F14="","",TCD!F14) | T13: =IF(TCD!E14="","",TCD!E14) | U13: =SUM(TCD!H14:J14) -> 5.15
A14: =_xlfn.XLOOKUP(G14,'Facture GLS'!AB:AB,'Facture GLS'!O:O) -> LA RUCHE | B14: =B13 -> GLS | C14: =C13 -> 46174 | G14: =TCD!D15 -> 00KUR5U6 | I14: P | J14: =_xlfn.XLOOKUP(G14,'Facture GLS'!AB:AB,'Facture GLS'!BB:BB) -> FR | K14: =IF(COUNTIF(Zoning!A:A,J14)=0,"pays inconnu",LOOKUP(J14,Zoning!A:A,Zoning!B:B)) -> France | L14: =L13 -> 1 | M14: =_xlfn.XLOOKUP(G14,Poids!A:A,Poids!C:C) -> 0.8 | N14: =IF(COUNTIF(Zoning!A:A,J14)=0,"zone inconnue","France") -> France | O14: =IF(COUNTIF(Zoning!A:A,J14)=0,"taux inconnu",_xlfn.XLOOKUP(J14,Zoning!A:A,Zoning!C:C)) -> 0.2 | R14: =IF(TCD!K15="","",TCD!K15) | S14: =IF(TCD!F15="","",TCD!F15) | T14: =IF(TCD!E15="","",TCD!E15) | U14: =SUM(TCD!H15:J15) -> 5.15
A15: =_xlfn.XLOOKUP(G15,'Facture GLS'!AB:AB,'Facture GLS'!O:O) -> LA RUCHE | B15: =B14 -> GLS | C15: =C14 -> 46174 | G15: =TCD!D16 -> 00KUR5U7 | I15: P | J15: =_xlfn.XLOOKUP(G15,'Facture GLS'!AB:AB,'Facture GLS'!BB:BB) -> FR | K15: =IF(COUNTIF(Zoning!A:A,J15)=0,"pays inconnu",LOOKUP(J15,Zoning!A:A,Zoning!B:B)) -> France | L15: =L14 -> 1 | M15: =_xlfn.XLOOKUP(G15,Poids!A:A,Poids!C:C) -> 0.5 | N15: =IF(COUNTIF(Zoning!A:A,J15)=0,"zone inconnue","France") -> France | O15: =IF(COUNTIF(Zoning!A:A,J15)=0,"taux inconnu",_xlfn.XLOOKUP(J15,Zoning!A:A,Zoning!C:C)) -> 0.2 | R15: =IF(TCD!K16="","",TCD!K16) | S15: =IF(TCD!F16="","",TCD!F16) | T15: =IF(TCD!E16="","",TCD!E16) | U15: =SUM(TCD!H16:J16) -> 4.82
... A429: =_xlfn.XLOOKUP(G429,'Facture GLS'!AB:AB,'Facture GLS'!O:O) -> LA RUCHE | B429: =B428 -> GLS | C429: =C428 -> 46174 | G429: =TCD!D430 -> ZWLMMM8W | I429: P | J429: =_xlfn.XLOOKUP(G429,'Facture GLS'!AB:AB,'Facture GLS'!BB:BB) -> DE | K429: =IF(COUNTIF(Zoning!A:A,J429)=0,"pays inconnu",LOOKUP(J429,Zoning!A:A,Zoning!B:B)) -> 1 | L429: =L428 -> 1 | M429: =_xlfn.XLOOKUP(G429,Poids!A:A,Poids!C:C) -> 19.6 | N429: =IF(COUNTIF(Zoning!A:A,J429)=0,"zone inconnue","France") -> France | O429: =IF(COUNTIF(Zoning!A:A,J429)=0,"taux inconnu",_xlfn.XLOOKUP(J429,Zoning!A:A,Zoning!C:C)) -> 0.2 | R429: =IF(TCD!K430="","",TCD!K430) | S429: =IF(TCD!F430="","",TCD!F430) | T429: =IF(TCD!E430="","",TCD!E430) | U429: =SUM(TCD!H430:J430) -> 18.33

Sheet Bilan factures
A3: Étiquettes de lignes | B3: Somme de Total HT | C3: TTC
A4: 2501382993 | B4: 3069.2 | C4: 3069.2 | D4: ok
A5: (vide)
A6: Total général | B6: 3069.2

Sheet Bilan clients
A1: Étiquettes de lignes | B1: Somme de Total GO | C1: Logistique | E1: Facture pdf | F1: Montant
A2: 361 | B2: 498.23313 | E2: 2500931230 | F2: 4443.8
A3: 3888 | B3: 1069.2257 | E3: 2500931231 | F3: 17.73
A4: 4565 | B4: 49.037775
A5: 4813 | B5: 651.17965
A6: 6199 | B6: 184.08286
A7: 6685 | B7: 23.138363
A8: 6739 | B8: 91.51644
A9: 6813 | B9: 6.2480062
A10: 6930 | B10: 20.01436
A11: 7254 | B11: 51.669197
A12: 7413 | B12: 24.992025
A13: 7515 | B13: 6.6757743
A14: 8041 | B14: 172.64978
A15: 8568 | B15: 82.079617 | F15: =SUM(F2:F14) -> 4461.53 | G15: novembre 2022 -> ok
A16: 8656 | B16: 62.531913
A17: 9351 | B17: 48.882223
A18: 9512 | B18: 12.496012
A19: (vide) | B19: 43.697156

Sheet Avoir
A1: Tracking | B1: Raison | C1: Tarif
